Workbook

Sheet Transaction Summary
A1: American Express - The Plum Card
A2: The Plum Card® | Statement Summary
A4: Account Holder | B4: John B Dunning
A5: Account | B5: XXXX-XXXXXX-27008
A6: Statement Period (Full Year) | B6: Jan 2025 - Dec 2025
A8: TOTALS
A9: Charges | B9: ='Transaction Details'!D427 -> 218574.69
A10: Credits & Payments | B10: ='Transaction Details'!D428 -> -182795.92
A11: Net Balance | B11: =B9+B10 -> 35778.77
A13: SPEND BY CATEGORY
A14: Category | B14: Amount | C14: % of Charges
A15: DWGCP / DWG Operating
A16: DWG-RE Listing Platform (Redirected) | B16: =SUMIFS('Transaction Details'!D:D,'Transaction Details'!C:C,A16) -> 4000 | C16: =IFERROR(B16/$B$9,0) -> 0.018300381
A17: DWG Investor Meeting (San Francisco) | B17: =SUMIFS('Transaction Details'!D:D,'Transaction Details'!C:C,A17) -> 3235.05 | C17: =IFERROR(B17/$B$9,0) -> 0.014800662
A18: DWG Marketing | B18: =SUMIFS('Transaction Details'!D:D,'Transaction Details'!C:C,A18) -> 2133.93 | C18: =IFERROR(B18/$B$9,0) -> 0.0097629328
A19: DWG Canceled Software | B19: =SUMIFS('Transaction Details'!D:D,'Transaction Details'!C:C,A19) -> 1358 | C19: =IFERROR(B19/$B$9,0) -> 0.0062129792
A20: Software & Subscriptions | B20: =SUMIFS('Transaction Details'!D:D,'Transaction Details'!C:C,A20) -> 471.89 | C20: =IFERROR(B20/$B$9,0) -> 0.0021589416
A21: Go Daddy | B21: =SUMIFS('Transaction Details'!D:D,'Transaction Details'!C:C,A21) -> 778.98 | C21: =IFERROR(B21/$B$9,0) -> 0.0035639076
A22: Wordpress | B22: =SUMIFS('Transaction Details'!D:D,'Transaction Details'!C:C,A22) -> 621 | C22: =IFERROR(B22/$B$9,0) -> 0.0028411341
A23: Costar Billing | B23: =SUMIFS('Transaction Details'!D:D,'Transaction Details'!C:C,A23) -> 9247.18 | C23: =IFERROR(B23/$B$9,0) -> 0.042306728
A24: Fund Launch | B24: =SUMIFS('Transaction Details'!D:D,'Transaction Details'!C:C,A24) -> 883 | C24: =IFERROR(B24/$B$9,0) -> 0.004039809
A25: Team Travel (Judd) | B25: =SUMIFS('Transaction Details'!D:D,'Transaction Details'!C:C,A25) -> 1813.46 | C25: =IFERROR(B25/$B$9,0) -> 0.008296752
A26: Team Lunch | B26: =SUMIFS('Transaction Details'!D:D,'Transaction Details'!C:C,A26) -> 184.45 | C26: =IFERROR(B26/$B$9,0) -> 0.0008438763
A27: Employee Bonus | B27: =SUMIFS('Transaction Details'!D:D,'Transaction Details'!C:C,A27) -> 6657.5 | C27: =IFERROR(B27/$B$9,0) -> 0.030458696
... A29: Renewal Membership Fee | B29: =SUMIFS('Transaction Details'!D:D,'Transaction Details'!C:C,A29) -> 250 | C29: =IFERROR(B29/$B$9,0) -> 0.0011437738
A30: Subtotal — Operating | B30: =SUM(B16:B29) -> 34030.46
A32: Deal-Specific
A33: Deal Specific: 260 S Hibbert - Taxes | B33: =SUMIFS('Transaction Details'!D:D,'Transaction Details'!C:C,A33) -> 23243.89 | C33: =IFERROR(B33/$B$9,0) -> 0.10634301
A34: Deal Specific: 260 S Hibbert - Insurance | B34: =SUMIFS('Transaction Details'!D:D,'Transaction Details'!C:C,A34) -> 8287.62 | C34: =IFERROR(B34/$B$9,0) -> 0.03791665
A35: Deal Specific: 260 S Hibbert - Utilities | B35: =SUMIFS('Transaction Details'!D:D,'Transaction Details'!C:C,A35) -> 67.5 | C35: =IFERROR(B35/$B$9,0) -> 0.00030881892
A36: Deal Specific - 260 S Hibbert - Marketing | B36: =SUMIFS('Transaction Details'!D:D,'Transaction Details'!C:C,A36) -> 1055.92 | C36: =IFERROR(B36/$B$9,0) -> 0.0048309345
A37: Deal Specific: Stryten Energy | B37: =SUMIFS('Transaction Details'!D:D,'Transaction Details'!C:C,A37) -> 399.67 | C37: =IFERROR(B37/$B$9,0) -> 0.0018285283
A38: Deal Specific - Bankhead Marketing | B38: =SUMIFS('Transaction Details'!D:D,'Transaction Details'!C:C,A38) -> 1323.03 | C38: =IFERROR(B38/$B$9,0) -> 0.0060529881
A39: Moab Appraisal | B39: =SUMIFS('Transaction Details'!D:D,'Transaction Details'!C:C,A39) -> 2175 | C39: =IFERROR(B39/$B$9,0) -> 0.0099508319
A40: Subtotal — Deal-Specific | B40: =SUM(B33:B39) -> 36552.63
A42: Legal / Professional / Other
A43: Jeff Farjado - Unconfirmed | B43: =SUMIFS('Transaction Details'!D:D,'Transaction Details'!C:C,A43) -> 17778.8 | C43: =IFERROR(B43/$B$9,0) -> 0.081339701
A44: The Brandon Law Firm | B44: =SUMIFS('Transaction Details'!D:D,'Transaction Details'!C:C,A44) -> 507.35 | C44: =IFERROR(B44/$B$9,0) -> 0.0023211745
A45: Adameer | B45: =SUMIFS('Transaction Details'!D:D,'Transaction Details'!C:C,A45) -> 4116.3 | C45: =IFERROR(B45/$B$9,0) -> 0.018832464
A46: Bridge Loan (Cash Reimbursement) - $11,300 total loss | B46: =SUMIFS('Transaction Details'!D:D,'Transaction Details'!C:C,A46) -> 11300 | C46: =IFERROR(B46/$B$9,0) -> 0.051698575
A47: Donation | B47: =SUMIFS('Transaction Details'!D:D,'Transaction Details'!C:C,A47) -> 818 | C47: =IFERROR(B47/$B$9,0) -> 0.0037424278
A48: Venmo | B48: =SUMIFS('Transaction Details'!D:D,'Transaction Details'!C:C,A48) -> 144.2 | C48: =IFERROR(B48/$B$9,0) -> 0.00065972872
A49: Utilities | B49: =SUMIFS('Transaction Details'!D:D,'Transaction Details'!C:C,A49) -> 455.49 | C49: =IFERROR(B49/$B$9,0) -> 0.0020839101
A50: Travel - Lodging | B50: =SUMIFS('Transaction Details'!D:D,'Transaction Details'!C:C,A50) -> 46.07 | C50: =IFERROR(B50/$B$9,0) -> 0.00021077463
A51: Restaurant | B51: =SUMIFS('Transaction Details'!D:D,'Transaction Details'!C:C,A51) -> 27.68 | C51: =IFERROR(B51/$B$9,0) -> 0.00012663863
A52: Miscellaneous | B52: =SUMIFS('Transaction Details'!D:D,'Transaction Details'!C:C,A52) -> 26.98 | C52: =IFERROR(B52/$B$9,0) -> 0.00012343607
A53: Subtotal — Other | B53: =SUM(B43:B52) -> 35220.87
A55: Personal — Reimburse to Company
A56: Judd/Angela Italy Trip | B56: =SUMIFS('Transaction Details'!D:D,'Transaction Details'!C:C,A56) -> 46924.98 | C56: =IFERROR(B56/$B$9,0) -> 0.21468625
A57: Family Trip | B57: =SUMIFS('Transaction Details'!D:D,'Transaction Details'!C:C,A57) -> 22193.31 | C57: =IFERROR(B57/$B$9,0) -> 0.1015365
A58: Personal - Car | B58: =SUMIFS('Transaction Details'!D:D,'Transaction Details'!C:C,A58) -> 6299.35 | C58: =IFERROR(B58/$B$9,0) -> 0.028820126
A59: Personal - House | B59: =SUMIFS('Transaction Details'!D:D,'Transaction Details'!C:C,A59) -> 3824.54 | C59: =IFERROR(B59/$B$9,0) -> 0.017497634
A60: Personal - Food | B60: =SUMIFS('Transaction Details'!D:D,'Transaction Details'!C:C,A60) -> 3592.71 | C60: =IFERROR(B60/$B$9,0) -> 0.01643699
A61: Colorado Trip | B61: =SUMIFS('Transaction Details'!D:D,'Transaction Details'!C:C,A61) -> 2661.33 | C61: =IFERROR(B61/$B$9,0) -> 0.012175838
A62: Personal - Entertainment | B62: =SUMIFS('Transaction Details'!D:D,'Transaction Details'!C:C,A62) -> 717.17 | C62: =IFERROR(B62/$B$9,0) -> 0.003281121
A63: Personal - Clothing | B63: =SUMIFS('Transaction Details'!D:D,'Transaction Details'!C:C,A63) -> 711.69 | C63: =IFERROR(B63/$B$9,0) -> 0.0032560495
A64: Personal - Eureka, NV Property | B64: =SUMIFS('Transaction Details'!D:D,'Transaction Details'!C:C,A64) -> 595 | C64: =IFERROR(B64/$B$9,0) -> 0.0027221816
A65: Personal - Health | B65: =SUMIFS('Transaction Details'!D:D,'Transaction Details'!C:C,A65) -> 507.16 | C65: =IFERROR(B65/$B$9,0) -> 0.0023203052
A66: Personal - Family | B66: =SUMIFS('Transaction Details'!D:D,'Transaction Details'!C:C,A66) -> 249.9 | C66: =IFERROR(B66/$B$9,0) -> 0.0011433163
A67: Subtotal — Personal | B67: =SUM(B56:B66) -> 88277.14
A69: Credits, Refunds & Payments
A70: Online AMEX Payment | B70: =SUMIFS('Transaction Details'!D:D,'Transaction Details'!C:C,A70) -> -157731.26 | C70: =IFERROR(B70/$B$9,0) -> -0.72163552
A71: Early Pay Discount | B71: =SUMIFS('Transaction Details'!D:D,'Transaction Details'!C:C,A71) -> -571.07 | C71: =IFERROR(B71/$B$9,0) -> -0.0026126996
A72: Subtotal — Credits/Payments | B72: =SUM(B70:B71) -> -158302.33
A74: GRAND TOTAL | B74: =B30+B40+B53+B67+B72 -> 35778.77 | C74: =IFERROR(B74/$B$9,0) -> 0.16369128
A76: SPEND BY MONTH
A77: Month | B77: Charges | C77: Credits | D77: Net
A78: =DATE(2025,1,1) -> 45658 | B78: =SUMIFS('Transaction Details'!D:D,'Transaction Details'!A:A,">="&DATE(2025,1,1),'Transaction Details'!A:A,"<"&DATE(2025,2,1),'Transaction Details'!D:D,">0") -> 3295.93 | C78: =SUMIFS('Transaction Details'!D:D,'Transaction Details'!A:A,">="&DATE(2025,1,1),'Transaction Details'!A:A,"<"&DATE(2025,2,1),'Transaction Details'!D:D,"<0") -> -3951.39 | D78: =B78+C78 -> -655.46
A79: =DATE(2025,2,1) -> 45689 | B79: =SUMIFS('Transaction Details'!D:D,'Transaction Details'!A:A,">="&DATE(2025,2,1),'Transaction Details'!A:A,"<"&DATE(2025,3,1),'Transaction Details'!D:D,">0") -> 10924.32 | C79: =SUMIFS('Transaction Details'!D:D,'Transaction Details'!A:A,">="&DATE(2025,2,1),'Transaction Details'!A:A,"<"&DATE(2025,3,1),'Transaction Details'!D:D,"<0") -> -14054.21 | D79: =B79+C79 -> -3129.89
A80: =DATE(2025,3,1) -> 45717 | B80: =SUMIFS('Transaction Details'!D:D,'Transaction Details'!A:A,">="&DATE(2025,3,1),'Transaction Details'!A:A,"<"&DATE(2025,4,1),'Transaction Details'!D:D,">0") -> 28470.11 | C80: =SUMIFS('Transaction Details'!D:D,'Transaction Details'!A:A,">="&DATE(2025,3,1),'Transaction Details'!A:A,"<"&DATE(2025,4,1),'Transaction Details'!D:D,"<0") -> -28325.73 | D80: =B80+C80 -> 144.38
A81: =DATE(2025,4,1) -> 45748 | B81: =SUMIFS('Transaction Details'!D:D,'Transaction Details'!A:A,">="&DATE(2025,4,1),'Transaction Details'!A:A,"<"&DATE(2025,5,1),'Transaction Details'!D:D,">0") -> 33631.94 | C81: =SUMIFS('Transaction Details'!D:D,'Transaction Details'!A:A,">="&DATE(2025,4,1),'Transaction Details'!A:A,"<"&DATE(2025,5,1),'Transaction Details'!D:D,"<0") -> -2258.41 | D81: =B81+C81 -> 31373.53
A82: =DATE(2025,5,1) -> 45778 | B82: =SUMIFS('Transaction Details'!D:D,'Transaction Details'!A:A,">="&DATE(2025,5,1),'Transaction Details'!A:A,"<"&DATE(2025,6,1),'Transaction Details'!D:D,">0") -> 24171.19 | C82: =SUMIFS('Transaction Details'!D:D,'Transaction Details'!A:A,">="&DATE(2025,5,1),'Transaction Details'!A:A,"<"&DATE(2025,6,1),'Transaction Details'!D:D,"<0") -> -20785.03 | D82: =B82+C82 -> 3386.16
A83: =DATE(2025,6,1) -> 45809 | B83: =SUMIFS('Transaction Details'!D:D,'Transaction Details'!A:A,">="&DATE(2025,6,1),'Transaction Details'!A:A,"<"&DATE(2025,7,1),'Transaction Details'!D:D,">0") -> 8810.71 | C83: =SUMIFS('Transaction Details'!D:D,'Transaction Details'!A:A,">="&DATE(2025,6,1),'Transaction Details'!A:A,"<"&DATE(2025,7,1),'Transaction Details'!D:D,"<0") -> -13301.49 | D83: =B83+C83 -> -4490.78
A84: =DATE(2025,7,1) -> 45839 | B84: =SUMIFS('Transaction Details'!D:D,'Transaction Details'!A:A,">="&DATE(2025,7,1),'Transaction Details'!A:A,"<"&DATE(2025,8,1),'Transaction Details'!D:D,">0") -> 13281.82 | C84: =SUMIFS('Transaction Details'!D:D,'Transaction Details'!A:A,">="&DATE(2025,7,1),'Transaction Details'!A:A,"<"&DATE(2025,8,1),'Transaction Details'!D:D,"<0") -> -23574.61 | D84: =B84+C84 -> -10292.79
A85: =DATE(2025,8,1) -> 45870 | B85: =SUMIFS('Transaction Details'!D:D,'Transaction Details'!A:A,">="&DATE(2025,8,1),'Transaction Details'!A:A,"<"&DATE(2025,9,1),'Transaction Details'!D:D,">0") -> 11799.44 | C85: =SUMIFS('Transaction Details'!D:D,'Transaction Details'!A:A,">="&DATE(2025,8,1),'Transaction Details'!A:A,"<"&DATE(2025,9,1),'Transaction Details'!D:D,"<0") -> -17183.32 | D85: =B85+C85 -> -5383.88
A86: =DATE(2025,9,1) -> 45901 | B86: =SUMIFS('Transaction Details'!D:D,'Transaction Details'!A:A,">="&DATE(2025,9,1),'Transaction Details'!A:A,"<"&DATE(2025,10,1),'Transaction Details'!D:D,">0") -> 3516.28 | C86: =SUMIFS('Transaction Details'!D:D,'Transaction Details'!A:A,">="&DATE(2025,9,1),'Transaction Details'!A:A,"<"&DATE(2025,10,1),'Transaction Details'!D:D,"<0") -> -14871.34 | D86: =B86+C86 -> -11355.06
A87: =DATE(2025,10,1) -> 45931 | B87: =SUMIFS('Transaction Details'!D:D,'Transaction Details'!A:A,">="&DATE(2025,10,1),'Transaction Details'!A:A,"<"&DATE(2025,11,1),'Transaction Details'!D:D,">0") -> 29177.1 | C87: =SUMIFS('Transaction Details'!D:D,'Transaction Details'!A:A,">="&DATE(2025,10,1),'Transaction Details'!A:A,"<"&DATE(2025,11,1),'Transaction Details'!D:D,"<0") -> -11350 | D87: =B87+C87 -> 17827.1
A88: =DATE(2025,11,1) -> 45962 | B88: =SUMIFS('Transaction Details'!D:D,'Transaction Details'!A:A,">="&DATE(2025,11,1),'Transaction Details'!A:A,"<"&DATE(2025,12,1),'Transaction Details'!D:D,">0") -> 7515.29 | C88: =SUMIFS('Transaction Details'!D:D,'Transaction Details'!A:A,">="&DATE(2025,11,1),'Transaction Details'!A:A,"<"&DATE(2025,12,1),'Transaction Details'!D:D,"<0") -> -2134.33 | D88: =B88+C88 -> 5380.96
A89: =DATE(2025,12,1) -> 45992 | B89: =SUMIFS('Transaction Details'!D:D,'Transaction Details'!A:A,">="&DATE(2025,12,1),'Transaction Details'!A:A,"<"&DATE(2026,1,1),'Transaction Details'!D:D,">0") -> 43980.56 | C89: =SUMIFS('Transaction Details'!D:D,'Transaction Details'!A:A,">="&DATE(2025,12,1),'Transaction Details'!A:A,"<"&DATE(2026,1,1),'Transaction Details'!D:D,"<0") -> -31006.06 | D89: =B89+C89 -> 12974.5
A90: Total | B90: =SUM(B78:B89) -> 218574.69 | C90: =SUM(C78:C89) -> -182795.92 | D90: =B90+C90 -> 35778.77
A92: PAYMENTS, CREDITS & REFUNDS DETAIL
A93: Date | B93: Description | C93: Type | D93: Amount
A94: 45996 | B94: CUSTOMER SERVICE PAYMENT - THANK YOU | C94: Payment | D94: -4281.72
A95: 45995 | B95: ONLINE PAYMENT - THANK YOU | C95: Payment | D95: -16724.33
A96: 45994 | B96: MOBILE PAYMENT - THANK YOU | C96: Payment | D96: -10000
A97: 45992 | B97: PAYPAL *WALMART COM 8009256278 | C97: Refund/Credit | D97: -0.01
A98: 45987 | B98: CUSTOMER SERVICE PAYMENT - THANK YOU | C98: Payment | D98: -2134.33
A99: 45947 | B99: COMMON LOTS | C99: Refund/Credit | D99: -11300
A100: 45947 | B100: COMMON LOTS | C100: Refund/Credit | D100: -50
A101: 45928 | B101: ONLINE PAYMENT - THANK YOU | C101: Payment | D101: -14871.34
A102: 45897 | B102: ONLINE PAYMENT - THANK YOU | C102: Payment | D102: -17183.32
A103: 45862 | B103: ONLINE PAYMENT - THANK YOU | C103: Payment | D103: -23574.61
A104: 45835 | B104: CUSTOMER SERVICE PAYMENT - THANK YOU | C104: Payment | D104: -11337.06
A105: 45821 | B105: AIRBNB * HMAQP82TKX SAN FRANCISCO | C105: Refund/Credit | D105: -1841.03
... A124: 45685 | B124: ONLINE PAYMENT - THANK YOU | C124: Payment | D124: -1000
A125: Total Credits & Payments | D125: =SUM(D94:D124) -> -182795.92

Sheet Monthly Breakdown
A1: DWG CAPITAL PARTNERS
A2: The Plum Card® | Monthly Breakdown
A4: Period | B4: Jan 2025 - Dec 2025
A6: =DATE(2025,1,1) -> 45658
A7: Category | B7: Amount | C7: % of Month Charges
A8: Online AMEX Payment | B8: =SUMIFS('Transaction Details'!D:D,'Transaction Details'!C:C,A8,'Transaction Details'!A:A,">="&DATE(2025,1,1),'Transaction Details'!A:A,"<"&DATE(2025,2,1)) -> -3951.39 | C8: =IFERROR(B8/$B$18,0) -> -1.1988695
A9: Deal Specific - Bankhead Marketing | B9: =SUMIFS('Transaction Details'!D:D,'Transaction Details'!C:C,A9,'Transaction Details'!A:A,">="&DATE(2025,1,1),'Transaction Details'!A:A,"<"&DATE(2025,2,1)) -> 1323.03 | C9: =IFERROR(B9/$B$18,0) -> 0.40141326
A10: Donation | B10: =SUMIFS('Transaction Details'!D:D,'Transaction Details'!C:C,A10,'Transaction Details'!A:A,">="&DATE(2025,1,1),'Transaction Details'!A:A,"<"&DATE(2025,2,1)) -> 818 | C10: =IFERROR(B10/$B$18,0) -> 0.24818488
A11: Personal - Food | B11: =SUMIFS('Transaction Details'!D:D,'Transaction Details'!C:C,A11,'Transaction Details'!A:A,">="&DATE(2025,1,1),'Transaction Details'!A:A,"<"&DATE(2025,2,1)) -> 582 | C11: =IFERROR(B11/$B$18,0) -> 0.17658142
A12: DWG Canceled Software | B12: =SUMIFS('Transaction Details'!D:D,'Transaction Details'!C:C,A12,'Transaction Details'!A:A,">="&DATE(2025,1,1),'Transaction Details'!A:A,"<"&DATE(2025,2,1)) -> 219 | C12: =IFERROR(B12/$B$18,0) -> 0.066445586
A13: Team Travel (Judd) | B13: =SUMIFS('Transaction Details'!D:D,'Transaction Details'!C:C,A13,'Transaction Details'!A:A,">="&DATE(2025,1,1),'Transaction Details'!A:A,"<"&DATE(2025,2,1)) -> 152.54 | C13: =IFERROR(B13/$B$18,0) -> 0.046281323
A14: Go Daddy | B14: =SUMIFS('Transaction Details'!D:D,'Transaction Details'!C:C,A14,'Transaction Details'!A:A,">="&DATE(2025,1,1),'Transaction Details'!A:A,"<"&DATE(2025,2,1)) -> 104.7 | C14: =IFERROR(B14/$B$18,0) -> 0.031766451
A15: Software & Subscriptions | B15: =SUMIFS('Transaction Details'!D:D,'Transaction Details'!C:C,A15,'Transaction Details'!A:A,">="&DATE(2025,1,1),'Transaction Details'!A:A,"<"&DATE(2025,2,1)) -> 37.6 | C15: =IFERROR(B15/$B$18,0) -> 0.011408009
A16: Personal - Car | B16: =SUMIFS('Transaction Details'!D:D,'Transaction Details'!C:C,A16,'Transaction Details'!A:A,">="&DATE(2025,1,1),'Transaction Details'!A:A,"<"&DATE(2025,2,1)) -> 34.07 | C16: =IFERROR(B16/$B$18,0) -> 0.010336991
A17: Personal - Family | B17: =SUMIFS('Transaction Details'!D:D,'Transaction Details'!C:C,A17,'Transaction Details'!A:A,">="&DATE(2025,1,1),'Transaction Details'!A:A,"<"&DATE(2025,2,1)) -> 24.99 | C17: =IFERROR(B17/$B$18,0) -> 0.0075820785
A18: Total Charges | B18: =SUMIFS('Transaction Details'!D:D,'Transaction Details'!A:A,">="&DATE(2025,1,1),'Transaction Details'!A:A,"<"&DATE(2025,2,1),'Transaction Details'!D:D,">0") -> 3295.93
A19: Credits & Payments | B19: =SUMIFS('Transaction Details'!D:D,'Transaction Details'!A:A,">="&DATE(2025,1,1),'Transaction Details'!A:A,"<"&DATE(2025,2,1),'Transaction Details'!D:D,"<0") -> -3951.39
A20: Net | B20: =B18+B19 -> -655.46
A22: =DATE(2025,2,1) -> 45689
A23: Category | B23: Amount | C23: % of Month Charges
A24: Online AMEX Payment | B24: =SUMIFS('Transaction Details'!D:D,'Transaction Details'!C:C,A24,'Transaction Details'!A:A,">="&DATE(2025,2,1),'Transaction Details'!A:A,"<"&DATE(2025,3,1)) -> -14054.21 | C24: =IFERROR(B24/$B$35,0) -> -1.2865066
A25: Costar Billing | B25: =SUMIFS('Transaction Details'!D:D,'Transaction Details'!C:C,A25,'Transaction Details'!A:A,">="&DATE(2025,2,1),'Transaction Details'!A:A,"<"&DATE(2025,3,1)) -> 9247.18 | C25: =IFERROR(B25/$B$35,0) -> 0.84647649
A26: The Brandon Law Firm | B26: =SUMIFS('Transaction Details'!D:D,'Transaction Details'!C:C,A26,'Transaction Details'!A:A,">="&DATE(2025,2,1),'Transaction Details'!A:A,"<"&DATE(2025,3,1)) -> 507.35 | C26: =IFERROR(B26/$B$35,0) -> 0.04644225
A27: Personal - Food | B27: =SUMIFS('Transaction Details'!D:D,'Transaction Details'!C:C,A27,'Transaction Details'!A:A,">="&DATE(2025,2,1),'Transaction Details'!A:A,"<"&DATE(2025,3,1)) -> 486.73 | C27: =IFERROR(B27/$B$35,0) -> 0.044554718
A28: DWG Canceled Software | B28: =SUMIFS('Transaction Details'!D:D,'Transaction Details'!C:C,A28,'Transaction Details'!A:A,">="&DATE(2025,2,1),'Transaction Details'!A:A,"<"&DATE(2025,3,1)) -> 219 | C28: =IFERROR(B28/$B$35,0) -> 0.020047014
A29: Go Daddy | B29: =SUMIFS('Transaction Details'!D:D,'Transaction Details'!C:C,A29,'Transaction Details'!A:A,">="&DATE(2025,2,1),'Transaction Details'!A:A,"<"&DATE(2025,3,1)) -> 132.86 | C29: =IFERROR(B29/$B$35,0) -> 0.012161855
A30: Personal - Health | B30: =SUMIFS('Transaction Details'!D:D,'Transaction Details'!C:C,A30,'Transaction Details'!A:A,">="&DATE(2025,2,1),'Transaction Details'!A:A,"<"&DATE(2025,3,1)) -> 114.91 | C30: =IFERROR(B30/$B$35,0) -> 0.010518733
A31: Personal - Entertainment | B31: =SUMIFS('Transaction Details'!D:D,'Transaction Details'!C:C,A31,'Transaction Details'!A:A,">="&DATE(2025,2,1),'Transaction Details'!A:A,"<"&DATE(2025,3,1)) -> 109.71 | C31: =IFERROR(B31/$B$35,0) -> 0.01004273
A32: Software & Subscriptions | B32: =SUMIFS('Transaction Details'!D:D,'Transaction Details'!C:C,A32,'Transaction Details'!A:A,">="&DATE(2025,2,1),'Transaction Details'!A:A,"<"&DATE(2025,3,1)) -> 42.59 | C32: =IFERROR(B32/$B$35,0) -> 0.0038986408
A33: Team Travel (Judd) | B33: =SUMIFS('Transaction Details'!D:D,'Transaction Details'!C:C,A33,'Transaction Details'!A:A,">="&DATE(2025,2,1),'Transaction Details'!A:A,"<"&DATE(2025,3,1)) -> 39 | C33: =IFERROR(B33/$B$35,0) -> 0.0035700163
A34: Personal - Family | B34: =SUMIFS('Transaction Details'!D:D,'Transaction Details'!C:C,A34,'Transaction Details'!A:A,">="&DATE(2025,2,1),'Transaction Details'!A:A,"<"&DATE(2025,3,1)) -> 24.99 | C34: =IFERROR(B34/$B$35,0) -> 0.0022875566
A35: Total Charges | B35: =SUMIFS('Transaction Details'!D:D,'Transaction Details'!A:A,">="&DATE(2025,2,1),'Transaction Details'!A:A,"<"&DATE(2025,3,1),'Transaction Details'!D:D,">0") -> 10924.32
A36: Credits & Payments | B36: =SUMIFS('Transaction Details'!D:D,'Transaction Details'!A:A,">="&DATE(2025,2,1),'Transaction Details'!A:A,"<"&DATE(2025,3,1),'Transaction Details'!D:D,"<0") -> -14054.21
A37: Net | B37: =B35+B36 -> -3129.89
A39: =DATE(2025,3,1) -> 45717
A40: Category | B40: Amount | C40: % of Month Charges
A41: Online AMEX Payment | B41: =SUMIFS('Transaction Details'!D:D,'Transaction Details'!C:C,A41,'Transaction Details'!A:A,">="&DATE(2025,3,1),'Transaction Details'!A:A,"<"&DATE(2025,4,1)) -> -18892.34 | C41: =IFERROR(B41/$B$50,0) -> -0.66358507
A42: Judd/Angela Italy Trip | B42: =SUMIFS('Transaction Details'!D:D,'Transaction Details'!C:C,A42,'Transaction Details'!A:A,">="&DATE(2025,3,1),'Transaction Details'!A:A,"<"&DATE(2025,4,1)) -> 18579.8 | C42: =IFERROR(B42/$B$50,0) -> 0.65260724
A43: DWG Canceled Software | B43: =SUMIFS('Transaction Details'!D:D,'Transaction Details'!C:C,A43,'Transaction Details'!A:A,">="&DATE(2025,3,1),'Transaction Details'!A:A,"<"&DATE(2025,4,1)) -> 219 | C43: =IFERROR(B43/$B$50,0) -> 0.007692278
A44: Personal - Food | B44: =SUMIFS('Transaction Details'!D:D,'Transaction Details'!C:C,A44,'Transaction Details'!A:A,">="&DATE(2025,3,1),'Transaction Details'!A:A,"<"&DATE(2025,4,1)) -> 177.71 | C44: =IFERROR(B44/$B$50,0) -> 0.006241985
A45: Early Pay Discount | B45: =SUMIFS('Transaction Details'!D:D,'Transaction Details'!C:C,A45,'Transaction Details'!A:A,">="&DATE(2025,3,1),'Transaction Details'!A:A,"<"&DATE(2025,4,1)) -> -158.42 | C45: =IFERROR(B45/$B$50,0) -> -0.0055644323
A46: Go Daddy | B46: =SUMIFS('Transaction Details'!D:D,'Transaction Details'!C:C,A46,'Transaction Details'!A:A,">="&DATE(2025,3,1),'Transaction Details'!A:A,"<"&DATE(2025,4,1)) -> 118.67 | C46: =IFERROR(B46/$B$50,0) -> 0.0041682312
A47: Software & Subscriptions | B47: =SUMIFS('Transaction Details'!D:D,'Transaction Details'!C:C,A47,'Transaction Details'!A:A,">="&DATE(2025,3,1),'Transaction Details'!A:A,"<"&DATE(2025,4,1)) -> 37.6 | C47: =IFERROR(B47/$B$50,0) -> 0.0013206833
A48: Personal - Car | B48: =SUMIFS('Transaction Details'!D:D,'Transaction Details'!C:C,A48,'Transaction Details'!A:A,">="&DATE(2025,3,1),'Transaction Details'!A:A,"<"&DATE(2025,4,1)) -> 37.37 | C48: =IFERROR(B48/$B$50,0) -> 0.0013126047
A49: Personal - Family | B49: =SUMIFS('Transaction Details'!D:D,'Transaction Details'!C:C,A49,'Transaction Details'!A:A,">="&DATE(2025,3,1),'Transaction Details'!A:A,"<"&DATE(2025,4,1)) -> 24.99 | C49: =IFERROR(B49/$B$50,0) -> 0.00087776268
A50: Total Charges | B50: =SUMIFS('Transaction Details'!D:D,'Transaction Details'!A:A,">="&DATE(2025,3,1),'Transaction Details'!A:A,"<"&DATE(2025,4,1),'Transaction Details'!D:D,">0") -> 28470.11
A51: Credits & Payments | B51: =SUMIFS('Transaction Details'!D:D,'Transaction Details'!A:A,">="&DATE(2025,3,1),'Transaction Details'!A:A,"<"&DATE(2025,4,1),'Transaction Details'!D:D,"<0") -> -28325.73
A52: Net | B52: =B50+B51 -> 144.38
A54: =DATE(2025,4,1) -> 45748
A55: Category | B55: Amount | C55: % of Month Charges
A56: Judd/Angela Italy Trip | B56: =SUMIFS('Transaction Details'!D:D,'Transaction Details'!C:C,A56,'Transaction Details'!A:A,">="&DATE(2025,4,1),'Transaction Details'!A:A,"<"&DATE(2025,5,1)) -> 26603.77 | C56: =IFERROR(B56/$B$67,0) -> 0.79102692
A57: Personal - House | B57: =SUMIFS('Transaction Details'!D:D,'Transaction Details'!C:C,A57,'Transaction Details'!A:A,">="&DATE(2025,4,1),'Transaction Details'!A:A,"<"&DATE(2025,5,1)) -> 3316.02 | C57: =IFERROR(B57/$B$67,0) -> 0.098597345
A58: Personal - Food | B58: =SUMIFS('Transaction Details'!D:D,'Transaction Details'!C:C,A58,'Transaction Details'!A:A,">="&DATE(2025,4,1),'Transaction Details'!A:A,"<"&DATE(2025,5,1)) -> 786.46 | C58: =IFERROR(B58/$B$67,0) -> 0.023384319
A59: Early Pay Discount | B59: =SUMIFS('Transaction Details'!D:D,'Transaction Details'!C:C,A59,'Transaction Details'!A:A,">="&DATE(2025,4,1),'Transaction Details'!A:A,"<"&DATE(2025,5,1)) -> -284.98 | C59: =IFERROR(B59/$B$67,0) -> -0.0084734928
A60: Renewal Membership Fee | B60: =SUMIFS('Transaction Details'!D:D,'Transaction Details'!C:C,A60,'Transaction Details'!A:A,">="&DATE(2025,4,1),'Transaction Details'!A:A,"<"&DATE(2025,5,1)) -> 250 | C60: =IFERROR(B60/$B$67,0) -> 0.00743341
A61: DWG Canceled Software | B61: =SUMIFS('Transaction Details'!D:D,'Transaction Details'!C:C,A61,'Transaction Details'!A:A,">="&DATE(2025,4,1),'Transaction Details'!A:A,"<"&DATE(2025,5,1)) -> 219 | C61: =IFERROR(B61/$B$67,0) -> 0.0065116672
A62: Team Travel (Judd) | B62: =SUMIFS('Transaction Details'!D:D,'Transaction Details'!C:C,A62,'Transaction Details'!A:A,">="&DATE(2025,4,1),'Transaction Details'!A:A,"<"&DATE(2025,5,1)) -> 150 | C62: =IFERROR(B62/$B$67,0) -> 0.004460046
A63: Personal - Health | B63: =SUMIFS('Transaction Details'!D:D,'Transaction Details'!C:C,A63,'Transaction Details'!A:A,">="&DATE(2025,4,1),'Transaction Details'!A:A,"<"&DATE(2025,5,1)) -> 150 | C63: =IFERROR(B63/$B$67,0) -> 0.004460046
A64: Go Daddy | B64: =SUMIFS('Transaction Details'!D:D,'Transaction Details'!C:C,A64,'Transaction Details'!A:A,">="&DATE(2025,4,1),'Transaction Details'!A:A,"<"&DATE(2025,5,1)) -> 120.67 | C64: =IFERROR(B64/$B$67,0) -> 0.0035879584
A65: Software & Subscriptions | B65: =SUMIFS('Transaction Details'!D:D,'Transaction Details'!C:C,A65,'Transaction Details'!A:A,">="&DATE(2025,4,1),'Transaction Details'!A:A,"<"&DATE(2025,5,1)) -> 37.6 | C65: =IFERROR(B65/$B$67,0) -> 0.0011179849
A66: Personal - Family | B66: =SUMIFS('Transaction Details'!D:D,'Transaction Details'!C:C,A66,'Transaction Details'!A:A,">="&DATE(2025,4,1),'Transaction Details'!A:A,"<"&DATE(2025,5,1)) -> 24.99 | C66: =IFERROR(B66/$B$67,0) -> 0.00074304367
A67: Total Charges | B67: =SUMIFS('Transaction Details'!D:D,'Transaction Details'!A:A,">="&DATE(2025,4,1),'Transaction Details'!A:A,"<"&DATE(2025,5,1),'Transaction Details'!D:D,">0") -> 33631.94
A68: Credits & Payments | B68: =SUMIFS('Transaction Details'!D:D,'Transaction Details'!A:A,">="&DATE(2025,4,1),'Transaction Details'!A:A,"<"&DATE(2025,5,1),'Transaction Details'!D:D,"<0") -> -2258.41
A69: Net | B69: =B67+B68 -> 31373.53
A71: =DATE(2025,5,1) -> 45778
A72: Category | B72: Amount | C72: % of Month Charges
A73: Online AMEX Payment | B73: =SUMIFS('Transaction Details'!D:D,'Transaction Details'!C:C,A73,'Transaction Details'!A:A,">="&DATE(2025,5,1),'Transaction Details'!A:A,"<"&DATE(2025,6,1)) -> -20726.61 | C73: =IFERROR(B73/$B$88,0) -> -0.85749233
A74: Jeff Farjado - Unconfirmed | B74: =SUMIFS('Transaction Details'!D:D,'Transaction Details'!C:C,A74,'Transaction Details'!A:A,">="&DATE(2025,5,1),'Transaction Details'!A:A,"<"&DATE(2025,6,1)) -> 17778.8 | C74: =IFERROR(B74/$B$88,0) -> 0.73553681
A75: DWG Marketing | B75: =SUMIFS('Transaction Details'!D:D,'Transaction Details'!C:C,A75,'Transaction Details'!A:A,">="&DATE(2025,5,1),'Transaction Details'!A:A,"<"&DATE(2025,6,1)) -> 1855.93 | C75: =IFERROR(B75/$B$88,0) -> 0.076782732
A76: Judd/Angela Italy Trip | B76: =SUMIFS('Transaction Details'!D:D,'Transaction Details'!C:C,A76,'Transaction Details'!A:A,">="&DATE(2025,5,1),'Transaction Details'!A:A,"<"&DATE(2025,6,1)) -> 1741.41 | C76: =IFERROR(B76/$B$88,0) -> 0.07204486
A77: Deal Specific - 260 S Hibbert - Marketing | B77: =SUMIFS('Transaction Details'!D:D,'Transaction Details'!C:C,A77,'Transaction Details'!A:A,">="&DATE(2025,5,1),'Transaction Details'!A:A,"<"&DATE(2025,6,1)) -> 1055.92 | C77: =IFERROR(B77/$B$88,0) -> 0.043685065
A78: Personal - Entertainment | B78: =SUMIFS('Transaction Details'!D:D,'Transaction Details'!C:C,A78,'Transaction Details'!A:A,">="&DATE(2025,5,1),'Transaction Details'!A:A,"<"&DATE(2025,6,1)) -> 394.23 | C78: =IFERROR(B78/$B$88,0) -> 0.016309913
A79: Personal - Food | B79: =SUMIFS('Transaction Details'!D:D,'Transaction Details'!C:C,A79,'Transaction Details'!A:A,">="&DATE(2025,5,1),'Transaction Details'!A:A,"<"&DATE(2025,6,1)) -> 305.05 | C79: =IFERROR(B79/$B$88,0) -> 0.012620396
A80: Team Travel (Judd) | B80: =SUMIFS('Transaction Details'!D:D,'Transaction Details'!C:C,A80,'Transaction Details'!A:A,">="&DATE(2025,5,1),'Transaction Details'!A:A,"<"&DATE(2025,6,1)) -> 283.27 | C80: =IFERROR(B80/$B$88,0) -> 0.011719324
A81: DWG Canceled Software | B81: =SUMIFS('Transaction Details'!D:D,'Transaction Details'!C:C,A81,'Transaction Details'!A:A,">="&DATE(2025,5,1),'Transaction Details'!A:A,"<"&DATE(2025,6,1)) -> 263 | C81: =IFERROR(B81/$B$88,0) -> 0.010880722
A82: Personal - House | B82: =SUMIFS('Transaction Details'!D:D,'Transaction Details'!C:C,A82,'Transaction Details'!A:A,">="&DATE(2025,5,1),'Transaction Details'!A:A,"<"&DATE(2025,6,1)) -> 205.17 | C82: =IFERROR(B82/$B$88,0) -> 0.0084882043
A83: Go Daddy | B83: =SUMIFS('Transaction Details'!D:D,'Transaction Details'!C:C,A83,'Transaction Details'!A:A,">="&DATE(2025,5,1),'Transaction Details'!A:A,"<"&DATE(2025,6,1)) -> 121.67 | C83: =IFERROR(B83/$B$88,0) -> 0.0050336785
A84: Software & Subscriptions | B84: =SUMIFS('Transaction Details'!D:D,'Transaction Details'!C:C,A84,'Transaction Details'!A:A,">="&DATE(2025,5,1),'Transaction Details'!A:A,"<"&DATE(2025,6,1)) -> 51.61 | C84: =IFERROR(B84/$B$88,0) -> 0.0021351866
... A87: Early Pay Discount | B87: =SUMIFS('Transaction Details'!D:D,'Transaction Details'!C:C,A87,'Transaction Details'!A:A,">="&DATE(2025,5,1),'Transaction Details'!A:A,"<"&DATE(2025,6,1)) -> -4.27 | C87: =IFERROR(B87/$B$88,0) -> -0.00017665659
A88: Total Charges | B88: =SUMIFS('Transaction Details'!D:D,'Transaction Details'!A:A,">="&DATE(2025,5,1),'Transaction Details'!A:A,"<"&DATE(2025,6,1),'Transaction Details'!D:D,">0") -> 24171.19
A89: Credits & Payments | B89: =SUMIFS('Transaction Details'!D:D,'Transaction Details'!A:A,">="&DATE(2025,5,1),'Transaction Details'!A:A,"<"&DATE(2025,6,1),'Transaction Details'!D:D,"<0") -> -20785.03
A90: Net | B90: =B88+B89 -> 3386.16
A92: =DATE(2025,6,1) -> 45809
A93: Category | B93: Amount | C93: % of Month Charges
A94: Online AMEX Payment | B94: =SUMIFS('Transaction Details'!D:D,'Transaction Details'!C:C,A94,'Transaction Details'!A:A,">="&DATE(2025,6,1),'Transaction Details'!A:A,"<"&DATE(2025,7,1)) -> -11337.06 | C94: =IFERROR(B94/$B$112,0) -> -1.2867363
A95: Deal Specific: 260 S Hibbert - Taxes | B95: =SUMIFS('Transaction Details'!D:D,'Transaction Details'!C:C,A95,'Transaction Details'!A:A,">="&DATE(2025,6,1),'Transaction Details'!A:A,"<"&DATE(2025,7,1)) -> 3000 | C95: =IFERROR(B95/$B$112,0) -> 0.34049469
A96: Mike Paytonjian (Salary/Stay) | B96: =SUMIFS('Transaction Details'!D:D,'Transaction Details'!C:C,A96,'Transaction Details'!A:A,">="&DATE(2025,6,1),'Transaction Details'!A:A,"<"&DATE(2025,7,1)) -> 2396.02 | C96: =IFERROR(B96/$B$112,0) -> 0.27194403
A97: Personal - Clothing | B97: =SUMIFS('Transaction Details'!D:D,'Transaction Details'!C:C,A97,'Transaction Details'!A:A,">="&DATE(2025,6,1),'Transaction Details'!A:A,"<"&DATE(2025,7,1)) -> 283.16 | C97: =IFERROR(B97/$B$112,0) -> 0.032138159
A98: DWG Marketing | B98: =SUMIFS('Transaction Details'!D:D,'Transaction Details'!C:C,A98,'Transaction Details'!A:A,">="&DATE(2025,6,1),'Transaction Details'!A:A,"<"&DATE(2025,7,1)) -> 278 | C98: =IFERROR(B98/$B$112,0) -> 0.031552508
A99: Personal - Food | B99: =SUMIFS('Transaction Details'!D:D,'Transaction Details'!C:C,A99,'Transaction Details'!A:A,">="&DATE(2025,6,1),'Transaction Details'!A:A,"<"&DATE(2025,7,1)) -> 250.39 | C99: =IFERROR(B99/$B$112,0) -> 0.028418822
A100: DWG Canceled Software | B100: =SUMIFS('Transaction Details'!D:D,'Transaction Details'!C:C,A100,'Transaction Details'!A:A,">="&DATE(2025,6,1),'Transaction Details'!A:A,"<"&DATE(2025,7,1)) -> 219 | C100: =IFERROR(B100/$B$112,0) -> 0.024856113
A101: Early Pay Discount | B101: =SUMIFS('Transaction Details'!D:D,'Transaction Details'!C:C,A101,'Transaction Details'!A:A,">="&DATE(2025,6,1),'Transaction Details'!A:A,"<"&DATE(2025,7,1)) -> -123.4 | C101: =IFERROR(B101/$B$112,0) -> -0.014005682
A102: Personal - Health | B102: =SUMIFS('Transaction Details'!D:D,'Transaction Details'!C:C,A102,'Transaction Details'!A:A,">="&DATE(2025,6,1),'Transaction Details'!A:A,"<"&DATE(2025,7,1)) -> 103.2 | C102: =IFERROR(B102/$B$112,0) -> 0.011713017
A103: Go Daddy | B103: =SUMIFS('Transaction Details'!D:D,'Transaction Details'!C:C,A103,'Transaction Details'!A:A,">="&DATE(2025,6,1),'Transaction Details'!A:A,"<"&DATE(2025,7,1)) -> 94.69 | C103: =IFERROR(B103/$B$112,0) -> 0.010747148
A104: Personal - Entertainment | B104: =SUMIFS('Transaction Details'!D:D,'Transaction Details'!C:C,A104,'Transaction Details'!A:A,">="&DATE(2025,6,1),'Transaction Details'!A:A,"<"&DATE(2025,7,1)) -> 81.31 | C104: =IFERROR(B104/$B$112,0) -> 0.0092285412
A105: Deal Specific: 260 S Hibbert - Utilities | B105: =SUMIFS('Transaction Details'!D:D,'Transaction Details'!C:C,A105,'Transaction Details'!A:A,">="&DATE(2025,6,1),'Transaction Details'!A:A,"<"&DATE(2025,7,1)) -> 67.5 | C105: =IFERROR(B105/$B$112,0) -> 0.0076611306
... A111: Personal - Family | B111: =SUMIFS('Transaction Details'!D:D,'Transaction Details'!C:C,A111,'Transaction Details'!A:A,">="&DATE(2025,6,1),'Transaction Details'!A:A,"<"&DATE(2025,7,1)) -> 24.99 | C111: =IFERROR(B111/$B$112,0) -> 0.0028363208
A112: Total Charges | B112: =SUMIFS('Transaction Details'!D:D,'Transaction Details'!A:A,">="&DATE(2025,6,1),'Transaction Details'!A:A,"<"&DATE(2025,7,1),'Transaction Details'!D:D,">0") -> 8810.71
A113: Credits & Payments | B113: =SUMIFS('Transaction Details'!D:D,'Transaction Details'!A:A,">="&DATE(2025,6,1),'Transaction Details'!A:A,"<"&DATE(2025,7,1),'Transaction Details'!D:D,"<0") -> -13301.49
A114: Net | B114: =B112+B113 -> -4490.78
...

Sheet Transaction Details
A1: DWG CAPITAL PARTNERS
A2: The Plum Card® | Transaction Detail
A4: Account Holder | B4: John B Dunning
A5: Account | B5: XXXX-XXXXXX-27008
A6: Statement Period | B6: Jan 1, 2025 – Dec 31, 2025
A7: Entity | B7: DWG Capital Partners
A9: Date | B9: Merchant | C9: Category | D9: Amount | E9: B/P | F9: Reimb. | G9: Notes
A10: 46022 | B10: ETERNAL ABUNDANCE | C10: Family Trip | D10: 53.09 | E10: P | F10: Yes
A11: 46022 | B11: ICONS SPORTS BAR & GRICHMOND | C11: Family Trip | D11: 91.62 | E11: P | F11: Yes
A12: 46022 | B12: STARBUCKS US | C12: Family Trip | D12: 3.84 | E12: P | F12: Yes
A13: 46022 | B13: STARBUCKS US | C13: Family Trip | D13: 33.6 | E13: P | F13: Yes
A14: 46022 | B14: UNITED AIRLINES | C14: Family Trip | D14: 38.36 | E14: P | F14: Yes
A15: 46021 | B15: BANANA REPUBLIC 6734VANCOUVER | C15: Family Trip | D15: 128.98 | E15: P | F15: Yes
A16: 46021 | B16: MOLTAQA MOROCCAN RESVANCOUVER | C16: Family Trip | D16: 219.81 | E16: P | F16: Yes
A17: 46021 | B17: MUJI ROBSON STREET 4VANCOUVER | C17: Family Trip | D17: 97.45 | E17: P | F17: Yes
A18: 46021 | B18: PUERTO MEXICO | C18: Family Trip | D18: 12.06 | E18: P | F18: Yes
A19: 46021 | B19: SAVE ON FOODS #999 | C19: Family Trip | D19: 3.17 | E19: P | F19: Yes
A20: 46021 | B20: STEVE MADDEN (SM16 VVANCOUVER | C20: Family Trip | D20: 202.67 | E20: P | F20: Yes
A21: 46021 | B21: THE NAAM RESTAURANT VANCOUVER | C21: Family Trip | D21: 208.09 | E21: P | F21: Yes
... A56: 46009 | B56: WOK N ROLL RESTAURANDELTA | C56: Family Trip | D56: 4.74 | E56: P | F56: Yes
A57: 46007 | B57: LEV INC | C57: DWG-RE Listing Platform (Redirected) | D57: 2000 | E57: B
A58: 46005 | B58: SETHAN HILL | C58: Employee Bonus | D58: 1657.5 | E58: B
A59: 45999 | B59: PUBLICGOODS.COM | C59: Personal - House | D59: 79 | E59: P | F59: Yes
A60: 45996 | B60: AMERICAN AIRLINES | C60: Team Travel (Judd) | D60: 36.14 | E60: B
A61: 45996 | B61: AMERICAN AIRLINES | C61: Team Travel (Judd) | D61: 418.18 | E61: B
A62: 45996 | B62: CUSTOMER SERVICE PAYMENT - THANK YOU | C62: Online AMEX Payment | D62: -4281.72
A63: 45996 | B63: EXPEDIA 733192261296EXPEDIA.COM | C63: Team Travel (Judd) | D63: 125.59 | E63: B
A64: 45996 | B64: MCTO TAX PAYMENT | C64: Deal Specific: 260 S Hibbert - Taxes | D64: 20243.89 | E64: B
A65: 45996 | B65: PAYMENTUS CORPORATIO800-420-1663 | C65: Utilities | D65: 455.49 | E65: B
A66: 45995 | B66: GOOGLE *HURDLR MILEA G.CO/HELPPAY# | C66: Software & Subscriptions | D66: 10.81 | E66: B
A67: 45995 | B67: ONLINE PAYMENT - THANK YOU | C67: Online AMEX Payment | D67: -16724.33
A68: 45995 | B68: UNITED AIRLINES | C68: Team Travel (Judd) | D68: 49.44 | E68: B
A69: 45995 | B69: UNITED AIRLINES | C69: Team Travel (Judd) | D69: 468.49 | E69: B
A70: 45994 | B70: FS *WICKANINNISH INNTOFINO | C70: Family Trip | D70: 4281.72 | E70: P | F70: Yes
A71: 45994 | B71: MOBILE PAYMENT - THANK YOU | C71: Online AMEX Payment | D71: -10000
A72: 45994 | B72: PROPERTYRATE APPRAISORANGE | C72: Moab Appraisal | D72: 250 | E72: B
A73: 45994 | B73: PROPERTYRATE APPRAISORANGE | C73: Moab Appraisal | D73: 250 | E73: B
A74: 45992 | B74: PAYPAL *WALMART COM 8009256278 | C74: Personal - House | D74: -0.01 | E74: P | F74: Yes
A75: 45991 | B75: PAYPAL *APPLE.COM/BI8002752273 | C75: Software & Subscriptions | D75: 8.99 | E75: B
A76: 45990 | B76: PAYPAL *APPLE.COM/BI8002752273 | C76: Software & Subscriptions | D76: 18.99 | E76: B
A77: 45990 | B77: PAYPAL *WALMART COM 8009256278 | C77: Personal - House | D77: 82.18 | E77: P | F77: Yes
A78: 45990 | B78: VENMO *JAMES BRANAMA8558124430 | C78: Venmo | D78: 5.15 | E78: B
A79: 45989 | B79: WORDPRESS BLAZE | C79: Wordpress | D79: 99 | E79: B
A80: 45987 | B80: CUSTOMER SERVICE PAYMENT - THANK YOU | C80: Online AMEX Payment | D80: -2134.33
A81: 45987 | B81: LEV INC | C81: DWG-RE Listing Platform (Redirected) | D81: 2000 | E81: B
A82: 45987 | B82: VENMO *JAMES PHILLIP8558124430 | C82: Venmo | D82: 139.05 | E82: B
A83: 45985 | B83: DD *DOORDASHDASHPASSSAN FRANCISCO | C83: Software & Subscriptions | D83: 9.99 | E83: B
A84: 45985 | B84: PAYPAL *TICKETMASTER8006538000 | C84: Personal - Entertainment | D84: 97.2 | E84: P | F84: Yes
A85: 45979 | B85: FLOHEALTH.COM | C85: Personal - Family | D85: 24.99 | E85: P | F85: Yes
A86: 45975 | B86: WORDPRESS BLAZE | C86: Wordpress | D86: 77 | E86: B
A87: 45971 | B87: PREMIER PHOTOGRAPHY,FORT SMITH | C87: Deal Specific: Stryten Energy | D87: 399.67 | E87: B
A88: 45968 | B88: WORDPRESS BLAZE | C88: Wordpress | D88: 275 | E88: B
A89: 45966 | B89: DD *DOORDASHDASHPASSSAN FRANCISCO | C89: Software & Subscriptions | D89: 9.99 | E89: B
A90: 45965 | B90: GOOGLE *HURDLR MILEA G.CO/HELPPAY# | C90: Software & Subscriptions | D90: 10.81 | E90: B
A91: 45964 | B91: FS *WICKANINNISH INNTOFINO | C91: Family Trip | D91: 4257.28 | E91: P | F91: Yes
A92: 45959 | B92: CORPORATE FILINGS LLSHERIDAN | C92: Software & Subscriptions | D92: 35 | E92: B
A93: 45956 | B93: WORDPRESS BLAZE | C93: Wordpress | D93: 70 | E93: B
A94: 45951 | B94: COMMONLOTS LLC 65000CAMARILLO | C94: Bridge Loan (Cash Reimbursement) - $11,300 total loss | D94: 11300 | E94: B
A95: 45949 | B95: PAYPAL *SARAHDETCHMA4029357733 | C95: Adameer | D95: 4116.3 | E95: B
A96: 45948 | B96: FLOHEALTH.COM | C96: Personal - Family | D96: 24.99 | E96: P | F96: Yes
A97: 45947 | B97: COMMON LOTS | C97: Bridge Loan (Cash Reimbursement) - $11,300 total loss | D97: -11300 | E97: B
A98: 45947 | B98: COMMON LOTS | C98: Bridge Loan (Cash Reimbursement) - $11,300 total loss | D98: -50 | E98: B
A99: 45939 | B99: COMMON LOTS 0000 | C99: Bridge Loan (Cash Reimbursement) - $11,300 total loss | D99: 11350 | E99: B
A100: 45937 | B100: COMMON LOTS 0000 | C100: Personal - Eureka, NV Property | D100: 595 | E100: P | F100: Yes
A101: 45934 | B101: GOOGLE *HURDLR MILEA G.CO/HELPPAY# | C101: Software & Subscriptions | D101: 10.81 | E101: B
A102: 45931 | B102: PROPERTYRATE APPRAISORANGE | C102: Moab Appraisal | D102: 750 | E102: B
A103: 45931 | B103: PROPERTYRATE APPRAISORANGE | C103: Moab Appraisal | D103: 925 | E103: B
A104: 45928 | B104: ONLINE PAYMENT - THANK YOU | C104: Online AMEX Payment | D104: -14871.34
A105: 45924 | B105: DD *DOORDASHDASHPASSSAN FRANCISCO | C105: Software & Subscriptions | D105: 9.99 | E105: B
A106: 45921 | B106: LA EATS AT SOFI STADInglewood | C106: Personal - Entertainment | D106: 24.72 | E106: P | F106: Yes
A107: 45921 | B107: WORDPRESS BLAZE | C107: Wordpress | D107: 72.97 | E107: B
A108: 45918 | B108: EXPEDIA 732463466178EXPEDIA.COM | C108: Colorado Trip | D108: 2661.33 | E108: P | F108: Yes
A109: 45918 | B109: FLOHEALTH.COM | C109: Personal - Family | D109: 24.99 | E109: P | F109: Yes
A110: 45915 | B110: TST* BLUEYS KITCHEN LOS ANGELES | C110: Team Lunch | D110: 140.15 | E110: B
A111: 45914 | B111: WORDPRESS BLAZE | C111: Wordpress | D111: 27.03 | E111: B
A112: 45913 | B112: LA CABANA - VENICE 5877-8144102 | C112: Personal - Food | D112: 115.13 | E112: P | F112: Yes
A113: 45913 | B113: PAYA THAI LA LLC. BLLOS ANGELES | C113: Personal - Food | D113: 161 | E113: P | F113: Yes
A114: 45913 | B114: TST* VESPAIO 0008079LOS ANGELES | C114: Personal - Food | D114: 66.03 | E114: P | F114: Yes
A115: 45912 | B115: RIDER SHACK | C115: Personal - Clothing | D115: 192.14 | E115: P | F115: Yes
A116: 45905 | B116: DD *DOORDASHDASHPASSSAN FRANCISCO | C116: Software & Subscriptions | D116: 9.99 | E116: B
A117: 45904 | B117: GOOGLE *HURDLR MILEA G.CO/HELPPAY# | C117: Software & Subscriptions | D117: 10.81 | E117: B
A118: 45897 | B118: ONLINE PAYMENT - THANK YOU | C118: Online AMEX Payment | D118: -17183.32
A119: 45889 | B119: LOVE'S #0273 INSIDE/WEATHERFORD | C119: Personal - Car | D119: 6.72 | E119: P | F119: Yes
A120: 45888 | B120: BLVD | C120: Personal - Health | D120: 139.05 | E120: P | F120: Yes
A121: 45888 | B121: SHEP'S 5455000014071702-5672666 | C121: Team Lunch | D121: 44.3 | E121: B
A122: 45887 | B122: FIVE STAR FORD LEWISLEWISVILLE | C122: Employee Bonus | D122: 5000 | E122: B
A123: 45887 | B123: FLOHEALTH.COM | C123: Software & Subscriptions | D123: 24.99 | E123: B
A124: 45879 | B124: PAYA THAI LA LLC. BLLOS ANGELES | C124: Personal - Food | D124: 155 | E124: P | F124: Yes
A125: 45878 | B125: ROSS DRESS FOR LESS VENICE | C125: Personal - House | D125: 142.18 | E125: P | F125: Yes
A126: 45873 | B126: GOOGLE *REA APP | C126: Software & Subscriptions | D126: 10.81 | E126: B
A127: 45873 | B127: HYATT REGENCY NEWPORNEWPORT BEACH | C127: Team Travel (Judd) | D127: 46 | E127: B
A128: 45872 | B128: MERCEDES BENZ OF LAGLAGUNA NIGUEL | C128: Personal - Car | D128: 6156.05 | E128: P | F128: Yes
A129: 45871 | B129: ABM PARKING CARDIFF CULVER CITY | C129: Personal - Car | D129: 2 | E129: P | F129: Yes
A130: 45871 | B130: PHOVORITE VIETNAMESECULVER CITY | C130: Personal - Food | D130: 72.34 | E130: P | F130: Yes
A131: 45862 | B131: ONLINE PAYMENT - THANK YOU | C131: Online AMEX Payment | D131: -23574.61
A132: 45856 | B132: FLOHEALTH.COM | C132: Personal - Family | D132: 24.99 | E132: P | F132: Yes
A133: 45851 | B133: TST* WILDSEED - UNIOSAN FRANCISCO | C133: Personal - Food | D133: 193.19 | E133: P | F133: Yes
A134: 45851 | B134: UBER EATS | C134: Personal - Food | D134: 58.08 | E134: P | F134: Yes
A135: 45850 | B135: GOOGLE *INAPP PURCHA G.CO/HELPPAY# | C135: Software & Subscriptions | D135: 17.31 | E135: B
A136: 45850 | B136: SP TAYLOR STITCH | C136: Personal - Clothing | D136: 236.39 | E136: P | F136: Yes
...

Sheet Raw Data
A1: Transaction Details | B1: The Plum Card® / Jan 01, 2025 to Dec 31, 2025
A2: Prepared for
A3: JOHN B DUNNING
A4: Account Number
A5: XXXX-XXXXXX-27008
A7: Date | B7: Description | C7: Card Member | D7: Account # | E7: Amount | F7: Extended Details | G7: Appears On Your Statement As | H7: Category
A8: 12/31/2025 | B8: ETERNAL ABUNDANCE VANCOUVER CA | C8: JOHN B DUNNING | D8: -27008 | E8: 53.09 | F8: OXOYI5 squareup.com/receipts ETERNAL ABUNDANCE VANCOUVER CA squareup.com/receiptsForeign Spend Amount: 72.60 CANADIAN DOLLAR Commission Amount: Currency Exchange Rate: null | G8: ETERNAL ABUNDANCE VANCOUVER CA | H8: Family Trip
A9: 12/31/2025 | B9: ICONS SPORTS BAR & GRICHMOND CA | C9: JOHN B DUNNING | D9: -27008 | E9: 91.62 | F9: 4379 RESTAURANT ICONS SPORTS BAR & G RICHMOND CA RESTAURANTForeign Spend Amount: 125.38 CANADIAN DOLLAR Commission Amount: Currency Exchange Rate: null | G9: ICONS SPORTS BAR & GRICHMOND CA | H9: Family Trip
A10: 12/31/2025 | B10: STARBUCKS US RICHMOND CA | C10: JOHN B DUNNING | D10: -27008 | E10: 3.84 | F10: 481210 FAST FOOD RESTAURANT STARBUCKS US RICHMOND CA FAST FOOD RESTAURANTForeign Spend Amount: 5.25 CANADIAN DOLLAR Commission Amount: Currency Exchange Rate: null | G10: STARBUCKS US RICHMOND CA | H10: Family Trip
A11: 12/31/2025 | B11: STARBUCKS US RICHMOND CA | C11: JOHN B DUNNING | D11: -27008 | E11: 33.6 | F11: 481204 FAST FOOD RESTAURANT STARBUCKS US RICHMOND CA FAST FOOD RESTAURANTForeign Spend Amount: 45.98 CANADIAN DOLLAR Commission Amount: Currency Exchange Rate: null | G11: STARBUCKS US RICHMOND CA | H11: Family Trip
A12: 12/31/2025 | B12: UNITED AIRLINES VANCOUVER CA | C12: JOHN B DUNNING | D12: -27008 | E12: 38.36 | F12: 00183460 WWW.UNITED.COM EXCESS BAGGAGE UNITED AIRLINES VANCOUVER CA Carrier : UNITED AIRLINES Passenger Name : DUNNING /SPORTING EQUIP Ticket Number : 01643581108562 Departure Day : 12/31 Additional Info : EXCESS BAGGAGE From : VANCOUVER INTERNAT To : LOS ANGELES INTERNForeign Spend Amount: 52.50 CANADIAN DOLLAR Commission Amount: Currency Exchange Rate: null | G12: UNITED AIRLINES VANCOUVER CA | H12: Family Trip
A13: 12/30/2025 | B13: BANANA REPUBLIC 6734VANCOUVER CA | C13: JOHN B DUNNING | D13: -27008 | E13: 128.98 | F13: 06734659044 FAMILY CLOTHING BANANA REPUBLIC 6734 VANCOUVER CA FAMILY CLOTHINGForeign Spend Amount: 176.39 CANADIAN DOLLAR Commission Amount: Currency Exchange Rate: null | G13: BANANA REPUBLIC 6734VANCOUVER CA | H13: Family Trip
A14: 12/30/2025 | B14: MOLTAQA MOROCCAN RESVANCOUVER CA | C14: JOHN B DUNNING | D14: -27008 | E14: 219.81 | F14: 01858251 604-696-4055 MOLTAQA MOROCCAN RESTAUR 001 VANCOUVER CA 604-696-4055Foreign Spend Amount: 300.61 CANADIAN DOLLAR Commission Amount: Currency Exchange Rate: null | G14: MOLTAQA MOROCCAN RESVANCOUVER CA | H14: Family Trip
A15: 12/30/2025 | B15: MUJI ROBSON STREET 4VANCOUVER CA | C15: JOHN B DUNNING | D15: -27008 | E15: 97.45 | F15: 11106582536 DEPARTMENT STORE MUJI ROBSON STREET 409756081 VANCOUVER CA DEPARTMENT STOREForeign Spend Amount: 133.27 CANADIAN DOLLAR Commission Amount: Currency Exchange Rate: null | G15: MUJI ROBSON STREET 4VANCOUVER CA | H15: Family Trip
A16: 12/30/2025 | B16: PUERTO MEXICO VANCOUVER CA | C16: JOHN B DUNNING | D16: -27008 | E16: 12.06 | F16: OXHHYK squareup.com/receipts PUERTO MEXICO VANCOUVER CA squareup.com/receiptsForeign Spend Amount: 16.47 CANADIAN DOLLAR Commission Amount: Currency Exchange Rate: null | G16: PUERTO MEXICO VANCOUVER CA | H16: Family Trip
A17: 12/30/2025 | B17: SAVE ON FOODS #999 NORTH VANCOUVER CA | C17: JOHN B DUNNING | D17: -27008 | E17: 3.17 | F17: 18002429229 SAVE ON FOODS #999 NORTH VANCOUVER CA 18002429229Foreign Spend Amount: 4.34 CANADIAN DOLLAR Commission Amount: Currency Exchange Rate: null | G17: SAVE ON FOODS #999 NORTH VANCOUVER CA | H17: Family Trip
A18: 12/30/2025 | B18: STEVE MADDEN (SM16 VVANCOUVER CA | C18: JOHN B DUNNING | D18: -27008 | E18: 202.67 | F18: 8 SHOE STORE STEVE MADDEN (SM16 VANCOUVER VANCOUVER CA Description : 12303598 Price : 0.00 SHOE STOREForeign Spend Amount: 277.17 CANADIAN DOLLAR Commission Amount: Currency Exchange Rate: null | G18: STEVE MADDEN (SM16 VVANCOUVER CA | H18: Family Trip
A19: 12/30/2025 | B19: THE NAAM RESTAURANT VANCOUVER CA | C19: JOHN B DUNNING | D19: -27008 | E19: 208.09 | F19: 21105185365 RESTAURANT THE NAAM RESTAURANT VANCOUVER CA RESTAURANTForeign Spend Amount: 284.59 CANADIAN DOLLAR Commission Amount: Currency Exchange Rate: null | G19: THE NAAM RESTAURANT VANCOUVER CA | H19: Family Trip
... A423: 01/01/2025 | B423: AplPay WIFIONBOARD AVANCOUVER CA | C423: JOHN B DUNNING | D423: -27008 | E423: 11.34 | F423: 409214217SS INFLIGHTWIFI AplPay WIFIONBOARD AIR CANA VANCOUVER CA INFLIGHTWIFIForeign Spend Amount: 16.28 CANADIAN DOLLAR Commission Amount: Currency Exchange Rate: null | G423: AplPay WIFIONBOARD AVANCOUVER CA | H423: Team Travel (Judd)
