Workbook

Sheet Transaction Summary
A1: American Express — Business Platinum Card
A2: Statement Summary | Jan 1, 2025 – Dec 31, 2025
A4: Prepared For | B4: John Dunning
A5: Account | B5: XXXX-XXXXXX-02000
A6: Statement Period | B6: Jan 2025 – Dec 2025
A8: TOTALS
A9: Charges | B9: =SUMIFS('Raw Data'!$F$8:$F$2052,'Raw Data'!$F$8:$F$2052,">0") -> 347202.33
A10: Credits & Payments | B10: =SUMIFS('Raw Data'!$F$8:$F$2052,'Raw Data'!$F$8:$F$2052,"<0") -> -354496.62
A11: Net Balance | B11: =B9+B10 -> -7294.29
A13: ACTIVITY BY CARD
A14: Card Member | B14: Payments & Credits | C14: Charges | D14: Total
A15: JOHN DUNNING | B15: =SUMIFS('Raw Data'!$F$8:$F$2052,'Raw Data'!$D$8:$D$2052,$A15,'Raw Data'!$F$8:$F$2052,"<0") -> -351061.92 | C15: =SUMIFS('Raw Data'!$F$8:$F$2052,'Raw Data'!$D$8:$D$2052,$A15,'Raw Data'!$F$8:$F$2052,">0") -> 308718.72 | D15: =B15+C15 -> -42343.2
A16: ANGELA LISA DUNNING | B16: =SUMIFS('Raw Data'!$F$8:$F$2052,'Raw Data'!$D$8:$D$2052,$A16,'Raw Data'!$F$8:$F$2052,"<0") -> -3434.7 | C16: =SUMIFS('Raw Data'!$F$8:$F$2052,'Raw Data'!$D$8:$D$2052,$A16,'Raw Data'!$F$8:$F$2052,">0") -> 38483.61 | D16: =B16+C16 -> 35048.91
A17: AVA YEMNA PEREZ | B17: =SUMIFS('Raw Data'!$F$8:$F$2052,'Raw Data'!$D$8:$D$2052,$A17,'Raw Data'!$F$8:$F$2052,"<0") -> 0 | C17: =SUMIFS('Raw Data'!$F$8:$F$2052,'Raw Data'!$D$8:$D$2052,$A17,'Raw Data'!$F$8:$F$2052,">0") -> 0 | D17: =B17+C17 -> 0
A18: Total | B18: =SUMIFS('Raw Data'!$F$8:$F$2052,'Raw Data'!$F$8:$F$2052,"<0") -> -354496.62 | C18: =SUMIFS('Raw Data'!$F$8:$F$2052,'Raw Data'!$F$8:$F$2052,">0") -> 347202.33 | D18: =B18+C18 -> -7294.29
A20: SPEND BY CATEGORY
A21: Category | B21: Amount | C21: % of Charges
A22: DWG / Operating
A23: DWG Listing Platform | B23: =SUMIF('Raw Data'!$I$8:$I$2052,$A23,'Raw Data'!$F$8:$F$2052) -> 21635 | C23: =B23/$B$9 -> 0.06231237
A24: Sponsor Cloud | B24: =SUMIF('Raw Data'!$I$8:$I$2052,$A24,'Raw Data'!$F$8:$F$2052) -> 8690.84 | C24: =B24/$B$9 -> 0.025031053
A25: Software & Subscriptions | B25: =SUMIF('Raw Data'!$I$8:$I$2052,$A25,'Raw Data'!$F$8:$F$2052) -> 9932.65 | C25: =B25/$B$9 -> 0.028607671
A26: AI Subscriptions | B26: =SUMIF('Raw Data'!$I$8:$I$2052,$A26,'Raw Data'!$F$8:$F$2052) -> 790.29 | C26: =B26/$B$9 -> 0.0022761656
A27: Go Daddy | B27: =SUMIF('Raw Data'!$I$8:$I$2052,$A27,'Raw Data'!$F$8:$F$2052) -> 8972.87 | C27: =B27/$B$9 -> 0.025843346
A28: DWG Operations | B28: =SUMIF('Raw Data'!$I$8:$I$2052,$A28,'Raw Data'!$F$8:$F$2052) -> 7689.66 | C28: =B28/$B$9 -> 0.02214749
A29: DWG Conference | B29: =SUMIF('Raw Data'!$I$8:$I$2052,$A29,'Raw Data'!$F$8:$F$2052) -> 6935 | C29: =B29/$B$9 -> 0.019973944
A30: DWG Marketing | B30: =SUMIF('Raw Data'!$I$8:$I$2052,$A30,'Raw Data'!$F$8:$F$2052) -> 3107 | C30: =B30/$B$9 -> 0.0089486727
A31: DWG Electronics | B31: =SUMIF('Raw Data'!$I$8:$I$2052,$A31,'Raw Data'!$F$8:$F$2052) -> 2691.84 | C31: =B31/$B$9 -> 0.0077529434
A32: DWG Development | B32: =SUMIF('Raw Data'!$I$8:$I$2052,$A32,'Raw Data'!$F$8:$F$2052) -> 194.85 | C32: =B32/$B$9 -> 0.00056120015
A33: DWG Swag | B33: =SUMIF('Raw Data'!$I$8:$I$2052,$A33,'Raw Data'!$F$8:$F$2052) -> 183.18 | C33: =B33/$B$9 -> 0.00052758863
A34: DWG-RE Platform (Redirected) | B34: =SUMIF('Raw Data'!$I$8:$I$2052,$A34,'Raw Data'!$F$8:$F$2052) -> 584 | C34: =B34/$B$9 -> 0.0016820164
... A36: RENEWAL MEMBERSHIP FEE | B36: =SUMIF('Raw Data'!$I$8:$I$2052,$A36,'Raw Data'!$F$8:$F$2052) -> 695 | C36: =B36/$B$9 -> 0.0020017147
A37: Subtotal — Operating | B37: =SUM(B23:B36) -> 74751.18 | C37: =B37/$B$9 -> 0.21529573
A39: Deal-Specific
A40: Deal Specific: Moab | B40: =SUMIF('Raw Data'!$I$8:$I$2052,$A40,'Raw Data'!$F$8:$F$2052) -> 72 | C40: =B40/$B$9 -> 0.00020737188
A41: Deal Specific - 260 S Hibbert | B41: =SUMIF('Raw Data'!$I$8:$I$2052,$A41,'Raw Data'!$F$8:$F$2052) -> 32 | C41: =B41/$B$9 -> 9.216528e-05
A42: Subtotal — Deal-Specific | B42: =SUM(B40:B41) -> 104 | C42: =B42/$B$9 -> 0.00029953716
A44: Legal / Professional / Other
A45: The Brandon Law Firm | B45: =SUMIF('Raw Data'!$I$8:$I$2052,$A45,'Raw Data'!$F$8:$F$2052) -> 4377.5 | C45: =B45/$B$9 -> 0.012607922
A46: Donation | B46: =SUMIF('Raw Data'!$I$8:$I$2052,$A46,'Raw Data'!$F$8:$F$2052) -> 330 | C46: =B46/$B$9 -> 0.00095045445
A47: Interest Charge on Pay Over Time Purchases | B47: =SUMIF('Raw Data'!$I$8:$I$2052,$A47,'Raw Data'!$F$8:$F$2052) -> 694.13 | C47: =B47/$B$9 -> 0.0019992089
A48: Late Fee | B48: =SUMIF('Raw Data'!$I$8:$I$2052,$A48,'Raw Data'!$F$8:$F$2052) -> 39 | C48: =B48/$B$9 -> 0.00011232644
A49: Amazon | B49: =SUMIF('Raw Data'!$I$8:$I$2052,$A49,'Raw Data'!$F$8:$F$2052) -> 4442.82 | C49: =B49/$B$9 -> 0.012796055
A50: AMEX Travel (PwP) | B50: =SUMIF('Raw Data'!$I$8:$I$2052,"*AMEXTRAVEL*",'Raw Data'!$F$8:$F$2052) -> 349.18 | C50: =B50/$B$9 -> 0.001005696
A51: Subtotal — Other | B51: =SUM(B45:B50) -> 10232.63 | C51: =B51/$B$9 -> 0.029471663
A53: Business Travel
A54: Miami Investor Trip | B54: =SUMIF('Raw Data'!$I$8:$I$2052,$A54,'Raw Data'!$F$8:$F$2052) -> 9209.38 | C54: =B54/$B$9 -> 0.026524534
A55: Team Travel (Angela) | B55: =SUMIF('Raw Data'!$I$8:$I$2052,$A55,'Raw Data'!$F$8:$F$2052) -> 13483.71 | C55: =B55/$B$9 -> 0.03883531
A56: Team Travel (Judd) | B56: =SUMIF('Raw Data'!$I$8:$I$2052,$A56,'Raw Data'!$F$8:$F$2052) -> 5816.57 | C56: =B56/$B$9 -> 0.016752681
A57: Ohio Site Visit | B57: =SUMIF('Raw Data'!$I$8:$I$2052,$A57,'Raw Data'!$F$8:$F$2052) -> 3281.97 | C57: =B57/$B$9 -> 0.0094526151
A58: San Francisco Investor Meeting | B58: =SUMIF('Raw Data'!$I$8:$I$2052,$A58,'Raw Data'!$F$8:$F$2052) -> 2113.34 | C58: =B58/$B$9 -> 0.0060867679
A59: Fort Worth Investor Dinner | B59: =SUMIF('Raw Data'!$I$8:$I$2052,$A59,'Raw Data'!$F$8:$F$2052) -> 2000.81 | C59: =B59/$B$9 -> 0.0057626629
A60: Arizona Site Visit | B60: =SUMIF('Raw Data'!$I$8:$I$2052,$A60,'Raw Data'!$F$8:$F$2052) -> 601.15 | C60: =B60/$B$9 -> 0.0017314112
A61: Denver Trip | B61: =SUMIF('Raw Data'!$I$8:$I$2052,$A61,'Raw Data'!$F$8:$F$2052) -> 587.17 | C61: =B61/$B$9 -> 0.0016911465
A62: Subtotal — Business Travel | B62: =SUM(B54:B61) -> 37094.1 | C62: =B62/$B$9 -> 0.10683713
A64: Personal — Reimburse to Company
A65: Personal - Food | B65: =SUMIF('Raw Data'!$I$8:$I$2052,$A65,'Raw Data'!$F$8:$F$2052) -> 22725.9 | C65: =B65/$B$9 -> 0.065454342
A66: Personal - House | B66: =SUMIF('Raw Data'!$I$8:$I$2052,$A66,'Raw Data'!$F$8:$F$2052) -> 21765.14 | C66: =B66/$B$9 -> 0.062687195
A67: Personal - Clothing | B67: =SUMIF('Raw Data'!$I$8:$I$2052,$A67,'Raw Data'!$F$8:$F$2052) -> 16428.78 | C67: =B67/$B$9 -> 0.047317597
A68: Personal - Health | B68: =SUMIF('Raw Data'!$I$8:$I$2052,$A68,'Raw Data'!$F$8:$F$2052) -> 15264 | C68: =B68/$B$9 -> 0.043962839
A69: Personal - Car | B69: =SUMIF('Raw Data'!$I$8:$I$2052,$A69,'Raw Data'!$F$8:$F$2052) -> 7821.83 | C69: =B69/$B$9 -> 0.022528161
A70: Personal - Entertainment | B70: =SUMIF('Raw Data'!$I$8:$I$2052,$A70,'Raw Data'!$F$8:$F$2052) -> 5783.8 | C70: =B70/$B$9 -> 0.016658298
A71: Personal - Family | B71: =SUMIF('Raw Data'!$I$8:$I$2052,$A71,'Raw Data'!$F$8:$F$2052) -> 255.71 | C71: =B71/$B$9 -> 0.00073648699
A72: New Orleans Family Trip | B72: =SUMIF('Raw Data'!$I$8:$I$2052,$A72,'Raw Data'!$F$8:$F$2052) -> 6941.32 | C72: =B72/$B$9 -> 0.019992147
A73: Costa Rica Trip | B73: =SUMIF('Raw Data'!$I$8:$I$2052,$A73,'Raw Data'!$F$8:$F$2052) -> 6166.99 | C73: =B73/$B$9 -> 0.017761949
A74: Family Trip | B74: =SUMIF('Raw Data'!$I$8:$I$2052,$A74,'Raw Data'!$F$8:$F$2052) -> 2538.64 | C74: =B74/$B$9 -> 0.0073117021
A75: Italy Trip (Judd/Angela) | B75: =SUMIF('Raw Data'!$I$8:$I$2052,$A75,'Raw Data'!$F$8:$F$2052) -> 3141.17 | C75: =B75/$B$9 -> 0.0090470879
A76: 2024/2025 Canada Family Trip | B76: =SUMIF('Raw Data'!$I$8:$I$2052,$A76,'Raw Data'!$F$8:$F$2052) -> 2139.02 | C76: =B76/$B$9 -> 0.0061607305
... A80: Family Travel MISC | B80: =SUMIF('Raw Data'!$I$8:$I$2052,$A80,'Raw Data'!$F$8:$F$2052) -> 4056.1 | C80: =B80/$B$9 -> 0.011682237
A81: Subtotal — Personal | B81: =SUM(B65:B80) -> 118086.84 | C81: =B81/$B$9 -> 0.34010958
A83: Unclassified
A84: TBD | B84: =SUMIF('Raw Data'!$I$8:$I$2052,$A84,'Raw Data'!$F$8:$F$2052) -> 6326.72 | C84: =B84/$B$9 -> 0.018221998
A85: Subtotal — Unclassified | B85: =B84 -> 6326.72 | C85: =B85/$B$9 -> 0.018221998
A87: Adjustments & Distributions (net ≈ $0)
A88: DEBIT - DISTRIBUTION OF PAYMENT | B88: =SUMIF('Raw Data'!$I$8:$I$2052,$A88,'Raw Data'!$F$8:$F$2052) -> 26819.93 | C88: =B88/$B$9 -> 0.077245824
A89: CREDIT - DISTRIBUTION OF PAYMENT | B89: =SUMIF('Raw Data'!$I$8:$I$2052,$A89,'Raw Data'!$F$8:$F$2052) -> -26819.93 | C89: =B89/$B$9 -> -0.077245824
A90: DR ADJ REDIST CADV PRIN | B90: =SUMIF('Raw Data'!$I$8:$I$2052,$A90,'Raw Data'!$F$8:$F$2052) -> 9765.86 | C90: =B90/$B$9 -> 0.028127288
A91: ADJ REDIST PURCHASE BAL | B91: =SUMIF('Raw Data'!$I$8:$I$2052,$A91,'Raw Data'!$F$8:$F$2052) -> -9765.86 | C91: =B91/$B$9 -> -0.028127288
A92: Subtotal — Adjustments | B92: =SUM(B88:B91) -> 0 | C92: =B92/$B$9 -> 0
A94: Credits, Refunds & Payments
A95: Online AMEX Payment | B95: =SUMIF('Raw Data'!$I$8:$I$2052,$A95,'Raw Data'!$F$8:$F$2052) -> -237662.31 | C95: =B95/$B$9 -> -0.68450667
A96: FRAUD CREDIT | B96: =SUMIF('Raw Data'!$I$8:$I$2052,$A96,'Raw Data'!$F$8:$F$2052) -> -14045.91 | C96: =B96/$B$9 -> -0.040454538 | D96: Incorrect
A97: Points for Amex Trvl | B97: =SUMIF('Raw Data'!$I$8:$I$2052,$A97,'Raw Data'!$F$8:$F$2052) -> -2181.54 | C97: =B97/$B$9 -> -0.0062831952
A98: Subtotal — Credits/Payments | B98: =SUM(B95:B97) -> -253889.76 | C98: =B98/$B$9 -> -0.7312444
A100: GRAND TOTAL | B100: =B37+B42+B51+B62+B81+B85+B92+B98 -> -7294.29 | C100: =B100/$B$9 -> -0.021008759
A102: SPEND BY MONTH
A103: Month | B103: Charges | C103: Credits | D103: Net
A104: =DATE(2025,1,1) -> 45658 | B104: =SUMIFS('Raw Data'!$F$8:$F$2052,'Raw Data'!$K$8:$K$2052,MONTH($A104),'Raw Data'!$F$8:$F$2052,">0") -> 24571.86 | C104: =SUMIFS('Raw Data'!$F$8:$F$2052,'Raw Data'!$K$8:$K$2052,MONTH($A104),'Raw Data'!$F$8:$F$2052,"<0") -> -39722.02 | D104: =B104+C104 -> -15150.16
A105: =DATE(2025,2,1) -> 45689 | B105: =SUMIFS('Raw Data'!$F$8:$F$2052,'Raw Data'!$K$8:$K$2052,MONTH($A105),'Raw Data'!$F$8:$F$2052,">0") -> 37245.2 | C105: =SUMIFS('Raw Data'!$F$8:$F$2052,'Raw Data'!$K$8:$K$2052,MONTH($A105),'Raw Data'!$F$8:$F$2052,"<0") -> -58256.28 | D105: =B105+C105 -> -21011.08
A106: =DATE(2025,3,1) -> 45717 | B106: =SUMIFS('Raw Data'!$F$8:$F$2052,'Raw Data'!$K$8:$K$2052,MONTH($A106),'Raw Data'!$F$8:$F$2052,">0") -> 41402.51 | C106: =SUMIFS('Raw Data'!$F$8:$F$2052,'Raw Data'!$K$8:$K$2052,MONTH($A106),'Raw Data'!$F$8:$F$2052,"<0") -> -18566.78 | D106: =B106+C106 -> 22835.73
A107: =DATE(2025,4,1) -> 45748 | B107: =SUMIFS('Raw Data'!$F$8:$F$2052,'Raw Data'!$K$8:$K$2052,MONTH($A107),'Raw Data'!$F$8:$F$2052,">0") -> 17276.73 | C107: =SUMIFS('Raw Data'!$F$8:$F$2052,'Raw Data'!$K$8:$K$2052,MONTH($A107),'Raw Data'!$F$8:$F$2052,"<0") -> -47599.85 | D107: =B107+C107 -> -30323.12
A108: =DATE(2025,5,1) -> 45778 | B108: =SUMIFS('Raw Data'!$F$8:$F$2052,'Raw Data'!$K$8:$K$2052,MONTH($A108),'Raw Data'!$F$8:$F$2052,">0") -> 41536.56 | C108: =SUMIFS('Raw Data'!$F$8:$F$2052,'Raw Data'!$K$8:$K$2052,MONTH($A108),'Raw Data'!$F$8:$F$2052,"<0") -> -33104.63 | D108: =B108+C108 -> 8431.93
A109: =DATE(2025,6,1) -> 45809 | B109: =SUMIFS('Raw Data'!$F$8:$F$2052,'Raw Data'!$K$8:$K$2052,MONTH($A109),'Raw Data'!$F$8:$F$2052,">0") -> 31391.19 | C109: =SUMIFS('Raw Data'!$F$8:$F$2052,'Raw Data'!$K$8:$K$2052,MONTH($A109),'Raw Data'!$F$8:$F$2052,"<0") -> -48224.69 | D109: =B109+C109 -> -16833.5
A110: =DATE(2025,7,1) -> 45839 | B110: =SUMIFS('Raw Data'!$F$8:$F$2052,'Raw Data'!$K$8:$K$2052,MONTH($A110),'Raw Data'!$F$8:$F$2052,">0") -> 16773.37 | C110: =SUMIFS('Raw Data'!$F$8:$F$2052,'Raw Data'!$K$8:$K$2052,MONTH($A110),'Raw Data'!$F$8:$F$2052,"<0") -> -4909.08 | D110: =B110+C110 -> 11864.29
A111: =DATE(2025,8,1) -> 45870 | B111: =SUMIFS('Raw Data'!$F$8:$F$2052,'Raw Data'!$K$8:$K$2052,MONTH($A111),'Raw Data'!$F$8:$F$2052,">0") -> 72007.43 | C111: =SUMIFS('Raw Data'!$F$8:$F$2052,'Raw Data'!$K$8:$K$2052,MONTH($A111),'Raw Data'!$F$8:$F$2052,"<0") -> -37254.02 | D111: =B111+C111 -> 34753.41
A112: =DATE(2025,9,1) -> 45901 | B112: =SUMIFS('Raw Data'!$F$8:$F$2052,'Raw Data'!$K$8:$K$2052,MONTH($A112),'Raw Data'!$F$8:$F$2052,">0") -> 21910.07 | C112: =SUMIFS('Raw Data'!$F$8:$F$2052,'Raw Data'!$K$8:$K$2052,MONTH($A112),'Raw Data'!$F$8:$F$2052,"<0") -> -14268.42 | D112: =B112+C112 -> 7641.65
A113: =DATE(2025,10,1) -> 45931 | B113: =SUMIFS('Raw Data'!$F$8:$F$2052,'Raw Data'!$K$8:$K$2052,MONTH($A113),'Raw Data'!$F$8:$F$2052,">0") -> 19777.62 | C113: =SUMIFS('Raw Data'!$F$8:$F$2052,'Raw Data'!$K$8:$K$2052,MONTH($A113),'Raw Data'!$F$8:$F$2052,"<0") -> -822.32 | D113: =B113+C113 -> 18955.3
A114: =DATE(2025,11,1) -> 45962 | B114: =SUMIFS('Raw Data'!$F$8:$F$2052,'Raw Data'!$K$8:$K$2052,MONTH($A114),'Raw Data'!$F$8:$F$2052,">0") -> 8688.68 | C114: =SUMIFS('Raw Data'!$F$8:$F$2052,'Raw Data'!$K$8:$K$2052,MONTH($A114),'Raw Data'!$F$8:$F$2052,"<0") -> -1484 | D114: =B114+C114 -> 7204.68
A115: =DATE(2025,12,1) -> 45992 | B115: =SUMIFS('Raw Data'!$F$8:$F$2052,'Raw Data'!$K$8:$K$2052,MONTH($A115),'Raw Data'!$F$8:$F$2052,">0") -> 14621.11 | C115: =SUMIFS('Raw Data'!$F$8:$F$2052,'Raw Data'!$K$8:$K$2052,MONTH($A115),'Raw Data'!$F$8:$F$2052,"<0") -> -50284.53 | D115: =B115+C115 -> -35663.42
A116: Total | B116: =SUM(B104:B115) -> 347202.33 | C116: =SUM(C104:C115) -> -354496.62 | D116: =SUM(D104:D115) -> -7294.29
A118: PAYMENTS & CREDITS SUMMARY
...

Sheet Monthly Breakdown
A1: American Express — Business Platinum Card
A2: Monthly Breakdown | Jan 1, 2025 – Dec 31, 2025
A4: Period | B4: Jan 2025 – Dec 2025
A6: =DATE(2025,1,1) -> 45658
A7: Category | B7: Amount | C7: % of Month Charges
A8: DWG Listing Platform | B8: =SUMIFS('Raw Data'!$F$8:$F$2052,'Raw Data'!$I$8:$I$2052,$A8,'Raw Data'!$K$8:$K$2052,MONTH($A$6)) -> 2260 | C8: =IFERROR(B8/$B$25,0) -> 0.091975129
A9: Team Travel (Angela) | B9: =SUMIFS('Raw Data'!$F$8:$F$2052,'Raw Data'!$I$8:$I$2052,$A9,'Raw Data'!$K$8:$K$2052,MONTH($A$6)) -> 2226.75 | C9: =IFERROR(B9/$B$25,0) -> 0.090621955
A10: 2024/2025 Canada Family Trip | B10: =SUMIFS('Raw Data'!$F$8:$F$2052,'Raw Data'!$I$8:$I$2052,$A10,'Raw Data'!$K$8:$K$2052,MONTH($A$6)) -> 2139.02 | C10: =IFERROR(B10/$B$25,0) -> 0.087051611
A11: Personal - Food | B11: =SUMIFS('Raw Data'!$F$8:$F$2052,'Raw Data'!$I$8:$I$2052,$A11,'Raw Data'!$K$8:$K$2052,MONTH($A$6)) -> 977.84 | C11: =IFERROR(B11/$B$25,0) -> 0.039795115
A12: Software & Subscriptions | B12: =SUMIFS('Raw Data'!$F$8:$F$2052,'Raw Data'!$I$8:$I$2052,$A12,'Raw Data'!$K$8:$K$2052,MONTH($A$6)) -> 969.1 | C12: =IFERROR(B12/$B$25,0) -> 0.039439424
A13: Personal - Health | B13: =SUMIFS('Raw Data'!$F$8:$F$2052,'Raw Data'!$I$8:$I$2052,$A13,'Raw Data'!$K$8:$K$2052,MONTH($A$6)) -> 868.51 | C13: =IFERROR(B13/$B$25,0) -> 0.035345717
A14: Amazon | B14: =SUMIFS('Raw Data'!$F$8:$F$2052,'Raw Data'!$I$8:$I$2052,$A14,'Raw Data'!$K$8:$K$2052,MONTH($A$6)) -> 617.5 | C14: =IFERROR(B14/$B$25,0) -> 0.025130373
A15: Palm Springs Renewal | B15: =SUMIFS('Raw Data'!$F$8:$F$2052,'Raw Data'!$I$8:$I$2052,$A15,'Raw Data'!$K$8:$K$2052,MONTH($A$6)) -> 599 | C15: =IFERROR(B15/$B$25,0) -> 0.024377479
A16: Personal - Entertainment | B16: =SUMIFS('Raw Data'!$F$8:$F$2052,'Raw Data'!$I$8:$I$2052,$A16,'Raw Data'!$K$8:$K$2052,MONTH($A$6)) -> 474.85 | C16: =IFERROR(B16/$B$25,0) -> 0.019324951
A17: Go Daddy | B17: =SUMIFS('Raw Data'!$F$8:$F$2052,'Raw Data'!$I$8:$I$2052,$A17,'Raw Data'!$K$8:$K$2052,MONTH($A$6)) -> 412.37 | C17: =IFERROR(B17/$B$25,0) -> 0.016782205
A18: Donation | B18: =SUMIFS('Raw Data'!$F$8:$F$2052,'Raw Data'!$I$8:$I$2052,$A18,'Raw Data'!$K$8:$K$2052,MONTH($A$6)) -> 330 | C18: =IFERROR(B18/$B$25,0) -> 0.013429997
A19: Personal - House | B19: =SUMIFS('Raw Data'!$F$8:$F$2052,'Raw Data'!$I$8:$I$2052,$A19,'Raw Data'!$K$8:$K$2052,MONTH($A$6)) -> 269.84 | C19: =IFERROR(B19/$B$25,0) -> 0.010981668
... A24: Online AMEX Payment | B24: =SUMIFS('Raw Data'!$F$8:$F$2052,'Raw Data'!$I$8:$I$2052,$A24,'Raw Data'!$K$8:$K$2052,MONTH($A$6)) -> -27459.41 | C24: =IFERROR(B24/$B$25,0) -> -1.1175145
A25: Total Charges | B25: =SUMIFS('Raw Data'!$F$8:$F$2052,'Raw Data'!$K$8:$K$2052,MONTH($A$6),'Raw Data'!$F$8:$F$2052,">0") -> 24571.86
A26: Credits & Payments | B26: =SUMIFS('Raw Data'!$F$8:$F$2052,'Raw Data'!$K$8:$K$2052,MONTH($A$6),'Raw Data'!$F$8:$F$2052,"<0") -> -39722.02
A27: Net | B27: =B25+B26 -> -15150.16
A29: =DATE(2025,2,1) -> 45689
A30: Category | B30: Amount | C30: % of Month Charges
A31: Sponsor Cloud | B31: =SUMIFS('Raw Data'!$F$8:$F$2052,'Raw Data'!$I$8:$I$2052,$A31,'Raw Data'!$K$8:$K$2052,MONTH($A$29)) -> 7200 | C31: =IFERROR(B31/$B$49,0) -> 0.1933135
A32: Personal - Car | B32: =SUMIFS('Raw Data'!$F$8:$F$2052,'Raw Data'!$I$8:$I$2052,$A32,'Raw Data'!$K$8:$K$2052,MONTH($A$29)) -> 5057.91 | C32: =IFERROR(B32/$B$49,0) -> 0.13580032
A33: Personal - Food | B33: =SUMIFS('Raw Data'!$F$8:$F$2052,'Raw Data'!$I$8:$I$2052,$A33,'Raw Data'!$K$8:$K$2052,MONTH($A$29)) -> 3560.74 | C33: =IFERROR(B33/$B$49,0) -> 0.095602655
A34: Team Travel (Angela) | B34: =SUMIFS('Raw Data'!$F$8:$F$2052,'Raw Data'!$I$8:$I$2052,$A34,'Raw Data'!$K$8:$K$2052,MONTH($A$29)) -> 2386.31 | C34: =IFERROR(B34/$B$49,0) -> 0.064070269
A35: DWG Listing Platform | B35: =SUMIFS('Raw Data'!$F$8:$F$2052,'Raw Data'!$I$8:$I$2052,$A35,'Raw Data'!$K$8:$K$2052,MONTH($A$29)) -> 2260 | C35: =IFERROR(B35/$B$49,0) -> 0.06067896
A36: Personal - Health | B36: =SUMIFS('Raw Data'!$F$8:$F$2052,'Raw Data'!$I$8:$I$2052,$A36,'Raw Data'!$K$8:$K$2052,MONTH($A$29)) -> 1405.22 | C36: =IFERROR(B36/$B$49,0) -> 0.037728889
A37: DWG Operations | B37: =SUMIFS('Raw Data'!$F$8:$F$2052,'Raw Data'!$I$8:$I$2052,$A37,'Raw Data'!$K$8:$K$2052,MONTH($A$29)) -> 1251.43 | C37: =IFERROR(B37/$B$49,0) -> 0.033599766
A38: DWG Marketing | B38: =SUMIFS('Raw Data'!$F$8:$F$2052,'Raw Data'!$I$8:$I$2052,$A38,'Raw Data'!$K$8:$K$2052,MONTH($A$29)) -> 1172 | C38: =IFERROR(B38/$B$49,0) -> 0.031467142
A39: The Brandon Law Firm | B39: =SUMIFS('Raw Data'!$F$8:$F$2052,'Raw Data'!$I$8:$I$2052,$A39,'Raw Data'!$K$8:$K$2052,MONTH($A$29)) -> 1030 | C39: =IFERROR(B39/$B$49,0) -> 0.02765457
A40: Software & Subscriptions | B40: =SUMIFS('Raw Data'!$F$8:$F$2052,'Raw Data'!$I$8:$I$2052,$A40,'Raw Data'!$K$8:$K$2052,MONTH($A$29)) -> 793.1 | C40: =IFERROR(B40/$B$49,0) -> 0.021294019
A41: Go Daddy | B41: =SUMIFS('Raw Data'!$F$8:$F$2052,'Raw Data'!$I$8:$I$2052,$A41,'Raw Data'!$K$8:$K$2052,MONTH($A$29)) -> 435.74 | C41: =IFERROR(B41/$B$49,0) -> 0.011699226
A42: Personal - House | B42: =SUMIFS('Raw Data'!$F$8:$F$2052,'Raw Data'!$I$8:$I$2052,$A42,'Raw Data'!$K$8:$K$2052,MONTH($A$29)) -> 343.96 | C42: =IFERROR(B42/$B$49,0) -> 0.0092350155
... A48: Online AMEX Payment | B48: =SUMIFS('Raw Data'!$F$8:$F$2052,'Raw Data'!$I$8:$I$2052,$A48,'Raw Data'!$K$8:$K$2052,MONTH($A$29)) -> -48648.58 | C48: =IFERROR(B48/$B$49,0) -> -1.3061705
A49: Total Charges | B49: =SUMIFS('Raw Data'!$F$8:$F$2052,'Raw Data'!$K$8:$K$2052,MONTH($A$29),'Raw Data'!$F$8:$F$2052,">0") -> 37245.2
A50: Credits & Payments | B50: =SUMIFS('Raw Data'!$F$8:$F$2052,'Raw Data'!$K$8:$K$2052,MONTH($A$29),'Raw Data'!$F$8:$F$2052,"<0") -> -58256.28
A51: Net | B51: =B49+B50 -> -21011.08
A53: =DATE(2025,3,1) -> 45717
A54: Category | B54: Amount | C54: % of Month Charges
A55: Team Travel (Angela) | B55: =SUMIFS('Raw Data'!$F$8:$F$2052,'Raw Data'!$I$8:$I$2052,$A55,'Raw Data'!$K$8:$K$2052,MONTH($A$53)) -> 8870.65 | C55: =IFERROR(B55/$B$74,0) -> 0.21425392
A56: Personal - Health | B56: =SUMIFS('Raw Data'!$F$8:$F$2052,'Raw Data'!$I$8:$I$2052,$A56,'Raw Data'!$K$8:$K$2052,MONTH($A$53)) -> 3405.71 | C56: =IFERROR(B56/$B$74,0) -> 0.082258539
A57: Costa Rica Trip | B57: =SUMIFS('Raw Data'!$F$8:$F$2052,'Raw Data'!$I$8:$I$2052,$A57,'Raw Data'!$K$8:$K$2052,MONTH($A$53)) -> 3330.28 | C57: =IFERROR(B57/$B$74,0) -> 0.080436669
A58: Personal - Food | B58: =SUMIFS('Raw Data'!$F$8:$F$2052,'Raw Data'!$I$8:$I$2052,$A58,'Raw Data'!$K$8:$K$2052,MONTH($A$53)) -> 3066.17 | C58: =IFERROR(B58/$B$74,0) -> 0.074057587
A59: Personal - House | B59: =SUMIFS('Raw Data'!$F$8:$F$2052,'Raw Data'!$I$8:$I$2052,$A59,'Raw Data'!$K$8:$K$2052,MONTH($A$53)) -> 2628.67 | C59: =IFERROR(B59/$B$74,0) -> 0.063490595
A60: Italy Trip (Judd/Angela) | B60: =SUMIFS('Raw Data'!$F$8:$F$2052,'Raw Data'!$I$8:$I$2052,$A60,'Raw Data'!$K$8:$K$2052,MONTH($A$53)) -> 2461.49 | C60: =IFERROR(B60/$B$74,0) -> 0.059452676
A61: DWG Listing Platform | B61: =SUMIFS('Raw Data'!$F$8:$F$2052,'Raw Data'!$I$8:$I$2052,$A61,'Raw Data'!$K$8:$K$2052,MONTH($A$53)) -> 2260 | C61: =IFERROR(B61/$B$74,0) -> 0.054586063
A62: DWG Electronics | B62: =SUMIFS('Raw Data'!$F$8:$F$2052,'Raw Data'!$I$8:$I$2052,$A62,'Raw Data'!$K$8:$K$2052,MONTH($A$53)) -> 1898.17 | C62: =IFERROR(B62/$B$74,0) -> 0.045846737
A63: The Brandon Law Firm | B63: =SUMIFS('Raw Data'!$F$8:$F$2052,'Raw Data'!$I$8:$I$2052,$A63,'Raw Data'!$K$8:$K$2052,MONTH($A$53)) -> 1545 | C63: =IFERROR(B63/$B$74,0) -> 0.037316578
A64: Personal - Entertainment | B64: =SUMIFS('Raw Data'!$F$8:$F$2052,'Raw Data'!$I$8:$I$2052,$A64,'Raw Data'!$K$8:$K$2052,MONTH($A$53)) -> 1330.31 | C64: =IFERROR(B64/$B$74,0) -> 0.032131144
A65: Go Daddy | B65: =SUMIFS('Raw Data'!$F$8:$F$2052,'Raw Data'!$I$8:$I$2052,$A65,'Raw Data'!$K$8:$K$2052,MONTH($A$53)) -> 1004.8 | C65: =IFERROR(B65/$B$74,0) -> 0.02426906
A66: Team Travel (Judd) | B66: =SUMIFS('Raw Data'!$F$8:$F$2052,'Raw Data'!$I$8:$I$2052,$A66,'Raw Data'!$K$8:$K$2052,MONTH($A$53)) -> 917.82 | C66: =IFERROR(B66/$B$74,0) -> 0.022168221
... A73: Online AMEX Payment | B73: =SUMIFS('Raw Data'!$F$8:$F$2052,'Raw Data'!$I$8:$I$2052,$A73,'Raw Data'!$K$8:$K$2052,MONTH($A$53)) -> -12000 | C73: =IFERROR(B73/$B$74,0) -> -0.2898375
A74: Total Charges | B74: =SUMIFS('Raw Data'!$F$8:$F$2052,'Raw Data'!$K$8:$K$2052,MONTH($A$53),'Raw Data'!$F$8:$F$2052,">0") -> 41402.51
A75: Credits & Payments | B75: =SUMIFS('Raw Data'!$F$8:$F$2052,'Raw Data'!$K$8:$K$2052,MONTH($A$53),'Raw Data'!$F$8:$F$2052,"<0") -> -18566.78
A76: Net | B76: =B74+B75 -> 22835.73
A78: =DATE(2025,4,1) -> 45748
A79: Category | B79: Amount | C79: % of Month Charges
A80: Go Daddy | B80: =SUMIFS('Raw Data'!$F$8:$F$2052,'Raw Data'!$I$8:$I$2052,$A80,'Raw Data'!$K$8:$K$2052,MONTH($A$78)) -> 2574.58 | C80: =IFERROR(B80/$B$92,0) -> 0.1490201
A81: DWG Listing Platform | B81: =SUMIFS('Raw Data'!$F$8:$F$2052,'Raw Data'!$I$8:$I$2052,$A81,'Raw Data'!$K$8:$K$2052,MONTH($A$78)) -> 2260 | C81: =IFERROR(B81/$B$92,0) -> 0.13081179
A82: Personal - Car | B82: =SUMIFS('Raw Data'!$F$8:$F$2052,'Raw Data'!$I$8:$I$2052,$A82,'Raw Data'!$K$8:$K$2052,MONTH($A$78)) -> 1520.22 | C82: =IFERROR(B82/$B$92,0) -> 0.087992346
A83: Software & Subscriptions | B83: =SUMIFS('Raw Data'!$F$8:$F$2052,'Raw Data'!$I$8:$I$2052,$A83,'Raw Data'!$K$8:$K$2052,MONTH($A$78)) -> 793.1 | C83: =IFERROR(B83/$B$92,0) -> 0.045905678
A84: Personal - Entertainment | B84: =SUMIFS('Raw Data'!$F$8:$F$2052,'Raw Data'!$I$8:$I$2052,$A84,'Raw Data'!$K$8:$K$2052,MONTH($A$78)) -> 737.7 | C84: =IFERROR(B84/$B$92,0) -> 0.042699052
A85: Italy Trip (Judd/Angela) | B85: =SUMIFS('Raw Data'!$F$8:$F$2052,'Raw Data'!$I$8:$I$2052,$A85,'Raw Data'!$K$8:$K$2052,MONTH($A$78)) -> 679.68 | C85: =IFERROR(B85/$B$92,0) -> 0.039340778
A86: Personal - Health | B86: =SUMIFS('Raw Data'!$F$8:$F$2052,'Raw Data'!$I$8:$I$2052,$A86,'Raw Data'!$K$8:$K$2052,MONTH($A$78)) -> 436.51 | C86: =IFERROR(B86/$B$92,0) -> 0.025265777
A87: DWG Marketing | B87: =SUMIFS('Raw Data'!$F$8:$F$2052,'Raw Data'!$I$8:$I$2052,$A87,'Raw Data'!$K$8:$K$2052,MONTH($A$78)) -> 298 | C87: =IFERROR(B87/$B$92,0) -> 0.017248634
A88: Amazon | B88: =SUMIFS('Raw Data'!$F$8:$F$2052,'Raw Data'!$I$8:$I$2052,$A88,'Raw Data'!$K$8:$K$2052,MONTH($A$78)) -> 257.59 | C88: =IFERROR(B88/$B$92,0) -> 0.01490965
A89: AI Subscriptions | B89: =SUMIFS('Raw Data'!$F$8:$F$2052,'Raw Data'!$I$8:$I$2052,$A89,'Raw Data'!$K$8:$K$2052,MONTH($A$78)) -> 60 | C89: =IFERROR(B89/$B$92,0) -> 0.0034728794
A90: TBD | B90: =SUMIFS('Raw Data'!$F$8:$F$2052,'Raw Data'!$I$8:$I$2052,$A90,'Raw Data'!$K$8:$K$2052,MONTH($A$78)) -> 59.5 | C90: =IFERROR(B90/$B$92,0) -> 0.0034439388
A91: Online AMEX Payment | B91: =SUMIFS('Raw Data'!$F$8:$F$2052,'Raw Data'!$I$8:$I$2052,$A91,'Raw Data'!$K$8:$K$2052,MONTH($A$78)) -> -40000 | C91: =IFERROR(B91/$B$92,0) -> -2.3152529
A92: Total Charges | B92: =SUMIFS('Raw Data'!$F$8:$F$2052,'Raw Data'!$K$8:$K$2052,MONTH($A$78),'Raw Data'!$F$8:$F$2052,">0") -> 17276.73
A93: Credits & Payments | B93: =SUMIFS('Raw Data'!$F$8:$F$2052,'Raw Data'!$K$8:$K$2052,MONTH($A$78),'Raw Data'!$F$8:$F$2052,"<0") -> -47599.85
A94: Net | B94: =B92+B93 -> -30323.12
A96: =DATE(2025,5,1) -> 45778
A97: Category | B97: Amount | C97: % of Month Charges
A98: New Orleans Family Trip | B98: =SUMIFS('Raw Data'!$F$8:$F$2052,'Raw Data'!$I$8:$I$2052,$A98,'Raw Data'!$K$8:$K$2052,MONTH($A$96)) -> 6941.32 | C98: =IFERROR(B98/$B$118,0) -> 0.1671135
A99: Family Travel MISC | B99: =SUMIFS('Raw Data'!$F$8:$F$2052,'Raw Data'!$I$8:$I$2052,$A99,'Raw Data'!$K$8:$K$2052,MONTH($A$96)) -> 4056.1 | C99: =IFERROR(B99/$B$118,0) -> 0.097651322
A100: Personal - House | B100: =SUMIFS('Raw Data'!$F$8:$F$2052,'Raw Data'!$I$8:$I$2052,$A100,'Raw Data'!$K$8:$K$2052,MONTH($A$96)) -> 3633.06 | C100: =IFERROR(B100/$B$118,0) -> 0.08746656
A101: Personal - Food | B101: =SUMIFS('Raw Data'!$F$8:$F$2052,'Raw Data'!$I$8:$I$2052,$A101,'Raw Data'!$K$8:$K$2052,MONTH($A$96)) -> 3382.84 | C101: =IFERROR(B101/$B$118,0) -> 0.081442469
A102: DWG Listing Platform | B102: =SUMIFS('Raw Data'!$F$8:$F$2052,'Raw Data'!$I$8:$I$2052,$A102,'Raw Data'!$K$8:$K$2052,MONTH($A$96)) -> 2260 | C102: =IFERROR(B102/$B$118,0) -> 0.054409898
A103: The Brandon Law Firm | B103: =SUMIFS('Raw Data'!$F$8:$F$2052,'Raw Data'!$I$8:$I$2052,$A103,'Raw Data'!$K$8:$K$2052,MONTH($A$96)) -> 1802.5 | C103: =IFERROR(B103/$B$118,0) -> 0.043395505
A104: Amazon | B104: =SUMIFS('Raw Data'!$F$8:$F$2052,'Raw Data'!$I$8:$I$2052,$A104,'Raw Data'!$K$8:$K$2052,MONTH($A$96)) -> 1085.91 | C104: =IFERROR(B104/$B$118,0) -> 0.026143475
A105: DWG Operations | B105: =SUMIFS('Raw Data'!$F$8:$F$2052,'Raw Data'!$I$8:$I$2052,$A105,'Raw Data'!$K$8:$K$2052,MONTH($A$96)) -> 1049.34 | C105: =IFERROR(B105/$B$118,0) -> 0.025263045
A106: DWG Electronics | B106: =SUMIFS('Raw Data'!$F$8:$F$2052,'Raw Data'!$I$8:$I$2052,$A106,'Raw Data'!$K$8:$K$2052,MONTH($A$96)) -> 793.67 | C106: =IFERROR(B106/$B$118,0) -> 0.019107745
A107: Software & Subscriptions | B107: =SUMIFS('Raw Data'!$F$8:$F$2052,'Raw Data'!$I$8:$I$2052,$A107,'Raw Data'!$K$8:$K$2052,MONTH($A$96)) -> 793.1 | C107: =IFERROR(B107/$B$118,0) -> 0.019094022
A108: Go Daddy | B108: =SUMIFS('Raw Data'!$F$8:$F$2052,'Raw Data'!$I$8:$I$2052,$A108,'Raw Data'!$K$8:$K$2052,MONTH($A$96)) -> 688.2 | C108: =IFERROR(B108/$B$118,0) -> 0.016568536
A109: Personal - Health | B109: =SUMIFS('Raw Data'!$F$8:$F$2052,'Raw Data'!$I$8:$I$2052,$A109,'Raw Data'!$K$8:$K$2052,MONTH($A$96)) -> 623.26 | C109: =IFERROR(B109/$B$118,0) -> 0.015005094
... A117: Online AMEX Payment | B117: =SUMIFS('Raw Data'!$F$8:$F$2052,'Raw Data'!$I$8:$I$2052,$A117,'Raw Data'!$K$8:$K$2052,MONTH($A$96)) -> -21109.5 | C117: =IFERROR(B117/$B$118,0) -> -0.50821493
A118: Total Charges | B118: =SUMIFS('Raw Data'!$F$8:$F$2052,'Raw Data'!$K$8:$K$2052,MONTH($A$96),'Raw Data'!$F$8:$F$2052,">0") -> 41536.56
A119: Credits & Payments | B119: =SUMIFS('Raw Data'!$F$8:$F$2052,'Raw Data'!$K$8:$K$2052,MONTH($A$96),'Raw Data'!$F$8:$F$2052,"<0") -> -33104.63
A120: Net | B120: =B118+B119 -> 8431.93
A122: =DATE(2025,6,1) -> 45809
A123: Category | B123: Amount | C123: % of Month Charges
A124: TBD | B124: =SUMIFS('Raw Data'!$F$8:$F$2052,'Raw Data'!$I$8:$I$2052,$A124,'Raw Data'!$K$8:$K$2052,MONTH($A$122)) -> 3513.41 | C124: =IFERROR(B124/$B$146,0) -> 0.11192344
A125: Ohio Site Visit | B125: =SUMIFS('Raw Data'!$F$8:$F$2052,'Raw Data'!$I$8:$I$2052,$A125,'Raw Data'!$K$8:$K$2052,MONTH($A$122)) -> 3281.97 | C125: =IFERROR(B125/$B$146,0) -> 0.10455067
A126: San Diego - Judd/Angela Trip | B126: =SUMIFS('Raw Data'!$F$8:$F$2052,'Raw Data'!$I$8:$I$2052,$A126,'Raw Data'!$K$8:$K$2052,MONTH($A$122)) -> 1910.44 | C126: =IFERROR(B126/$B$146,0) -> 0.060859114
A127: DWG Operations | B127: =SUMIFS('Raw Data'!$F$8:$F$2052,'Raw Data'!$I$8:$I$2052,$A127,'Raw Data'!$K$8:$K$2052,MONTH($A$122)) -> 1883.18 | C127: =IFERROR(B127/$B$146,0) -> 0.059990717
A128: DWG Conference | B128: =SUMIFS('Raw Data'!$F$8:$F$2052,'Raw Data'!$I$8:$I$2052,$A128,'Raw Data'!$K$8:$K$2052,MONTH($A$122)) -> 1700 | C128: =IFERROR(B128/$B$146,0) -> 0.054155322
A129: Amazon | B129: =SUMIFS('Raw Data'!$F$8:$F$2052,'Raw Data'!$I$8:$I$2052,$A129,'Raw Data'!$K$8:$K$2052,MONTH($A$122)) -> 1342.89 | C129: =IFERROR(B129/$B$146,0) -> 0.0427792
...

Sheet Transaction Details
A1: American Express — Business Platinum Card
A2: Transaction Detail | Jan 1, 2025 – Dec 31, 2025
A4: Date | B4: Merchant | C4: Category | D4: Amount
A5: ='Raw Data'!A8 -> 12/31/2025 | B5: ='Raw Data'!C8 -> A&R NOTARY PLUS Los Angeles CA | C5: ='Raw Data'!I8 -> Deal Specific: Moab | D5: ='Raw Data'!F8 -> 72
A6: ='Raw Data'!A9 -> 12/31/2025 | B6: ='Raw Data'!C9 -> BUDGET RENT A CAR RICHMOND CA | C6: ='Raw Data'!I9 -> Family Trip | D6: ='Raw Data'!F9 -> 2160.6
A7: ='Raw Data'!A10 -> 12/31/2025 | B7: ='Raw Data'!C10 -> SPONSORCLOUD (SYNPROSALT LAKE CITY UT | C7: ='Raw Data'!I10 -> Sponsor Cloud | D7: ='Raw Data'!F10 -> 180.14
A8: ='Raw Data'!A11 -> 12/29/2025 | B8: ='Raw Data'!C11 -> DNH*GODADDY#39806828Tempe AZ | C8: ='Raw Data'!I11 -> Go Daddy | D8: ='Raw Data'!F11 -> 22.98
A9: ='Raw Data'!A12 -> 12/29/2025 | B9: ='Raw Data'!C12 -> OPENAI *CHATGPT SUBSSAN FRANCISCO CA | C9: ='Raw Data'!I12 -> AI Subscriptions | D9: ='Raw Data'!F12 -> 20
A10: ='Raw Data'!A13 -> 12/28/2025 | B10: ='Raw Data'!C13 -> ONLINE PAYMENT - THANK YOU | C10: ='Raw Data'!I13 -> Online AMEX Payment | D10: ='Raw Data'!F13 -> -29571.15
A11: ='Raw Data'!A14 -> 12/27/2025 | B11: ='Raw Data'!C14 -> DNH*GODADDY#39792539Tempe AZ | C11: ='Raw Data'!I14 -> Go Daddy | D11: ='Raw Data'!F14 -> 11.99
A12: ='Raw Data'!A15 -> 12/27/2025 | B12: ='Raw Data'!C15 -> SPLICE.COM NEW YORK NY | C12: ='Raw Data'!I15 -> Software & Subscriptions | D12: ='Raw Data'!F15 -> 39.99
A13: ='Raw Data'!A16 -> 12/25/2025 | B13: ='Raw Data'!C16 -> DNH*GODADDY#39778629Tempe AZ | C13: ='Raw Data'!I16 -> Go Daddy | D13: ='Raw Data'!F16 -> 15.98
A14: ='Raw Data'!A17 -> 12/23/2025 | B14: ='Raw Data'!C17 -> DNH*GODADDY#39769602Tempe AZ | C14: ='Raw Data'!I17 -> Go Daddy | D14: ='Raw Data'!F17 -> 40.97
A15: ='Raw Data'!A18 -> 12/20/2025 | B15: ='Raw Data'!C18 -> CAMPAIGNER SVC 888-845-4544 CA | C15: ='Raw Data'!I18 -> DWG-RE Platform (Redirected) | D15: ='Raw Data'!F18 -> 584
A16: ='Raw Data'!A19 -> 12/20/2025 | B16: ='Raw Data'!C19 -> DNH*GODADDY#39749794Tempe AZ | C16: ='Raw Data'!I19 -> Go Daddy | D16: ='Raw Data'!F19 -> 17.97
... A2049: ='Raw Data'!A2052 -> 01/01/2025 | B2049: ='Raw Data'!C2052 -> WICKANINNISH INN LTDTOFINO CA | C2049: ='Raw Data'!I2052 -> 2024/2025 Canada Family Trip | D2049: ='Raw Data'!F2052 -> 951.4

Sheet Raw Data
A1: Transaction Details | B1: Business Platinum Card® / Jan 01, 2025 to Dec 31, 2025
A2: Prepared for
A3: JOHN DUNNING
A4: Account Number
A5: XXXX-XXXXXX-02000
A7: Date | B7: Receipt | C7: Description | D7: Card Member | E7: Account # | F7: Amount | G7: Extended Details | H7: Appears On Your Statement As | I7: Category | K7: Month #
A8: 12/31/2025 | C8: A&R NOTARY PLUS Los Angeles CA | D8: JOHN DUNNING | E8: -02000 | F8: 72 | G8: NoLBczBdb3W squareup.com/receipts A&R NOTARY PLUS Los Angeles CA squareup.com/receipts | H8: A&R NOTARY PLUS Los Angeles CA | I8: Deal Specific: Moab | K8: =IF($A8="","",IF(ISNUMBER($A8),MONTH($A8),MONTH(DATEVALUE($A8)))) -> 12
A9: 12/31/2025 | C9: BUDGET RENT A CAR RICHMOND CA | D9: JOHN DUNNING | E9: -02000 | F9: 2160.6 | G9: R/A# 964532601 1-800-621-2844 BUDGET RENT A CAR RICHMOND CA Foreign Spend Amount: 2956.78 CANADIAN DOLLAR Commission Amount: Currency Exchange Rate: null | H9: BUDGET RENT A CAR RICHMOND CA | I9: Family Trip | K9: =IF($A9="","",IF(ISNUMBER($A9),MONTH($A9),MONTH(DATEVALUE($A9)))) -> 12
A10: 12/31/2025 | C10: SPONSORCLOUD (SYNPROSALT LAKE CITY UT | D10: JOHN DUNNING | E10: -02000 | F10: 180.14 | G10: CH_3SKZJQB7 +13854834872 SPONSORCLOUD (SYNPRO) SALT LAKE CITY UT +13854834872 | H10: SPONSORCLOUD (SYNPROSALT LAKE CITY UT | I10: Sponsor Cloud | K10: =IF($A10="","",IF(ISNUMBER($A10),MONTH($A10),MONTH(DATEVALUE($A10)))) -> 12
A11: 12/29/2025 | C11: DNH*GODADDY#39806828Tempe AZ | D11: JOHN DUNNING | E11: -02000 | F11: 22.98 | G11: 3980682814 4805058855 Microsoft 365 Online Business Essentials Email - Archiving - Renewal DNH*GODADDY#3980682814 Tempe AZ Microsoft 365 Online Business Essentials Email - Archiving - Renewal 4805058855 | H11: DNH*GODADDY#39806828Tempe AZ | I11: Go Daddy | K11: =IF($A11="","",IF(ISNUMBER($A11),MONTH($A11),MONTH(DATEVALUE($A11)))) -> 12
A12: 12/29/2025 | C12: OPENAI *CHATGPT SUBSSAN FRANCISCO CA | D12: JOHN DUNNING | E12: -02000 | F12: 20 | G12: CH_3SJMPNC6 +14158799686 OPENAI *CHATGPT SUBSCR SAN FRANCISCO CA +14158799686 | H12: OPENAI *CHATGPT SUBSSAN FRANCISCO CA | I12: AI Subscriptions | K12: =IF($A12="","",IF(ISNUMBER($A12),MONTH($A12),MONTH(DATEVALUE($A12)))) -> 12
A13: 12/28/2025 | C13: ONLINE PAYMENT - THANK YOU | D13: JOHN DUNNING | E13: -02000 | F13: -29571.15 | G13: ONLINE PAYMENT - THANK YOU | H13: ONLINE PAYMENT - THANK YOU | I13: Online AMEX Payment | K13: =IF($A13="","",IF(ISNUMBER($A13),MONTH($A13),MONTH(DATEVALUE($A13)))) -> 12
A14: 12/27/2025 | C14: DNH*GODADDY#39792539Tempe AZ | D14: JOHN DUNNING | E14: -02000 | F14: 11.99 | G14: 3979253910 4805058855 Hosting - Web - Economy - Linux cPanel - DNH*GODADDY#3979253910 Tempe AZ Hosting - Web - Economy - Linux cPanel - 4805058855 | H14: DNH*GODADDY#39792539Tempe AZ | I14: Go Daddy | K14: =IF($A14="","",IF(ISNUMBER($A14),MONTH($A14),MONTH(DATEVALUE($A14)))) -> 12
A15: 12/27/2025 | C15: SPLICE.COM NEW YORK NY | D15: JOHN DUNNING | E15: -02000 | F15: 39.99 | G15: CH_3SIYBXCF 3235775423 SPLICE.COM NEW YORK NY 3235775423 | H15: SPLICE.COM NEW YORK NY | I15: Software & Subscriptions | K15: =IF($A15="","",IF(ISNUMBER($A15),MONTH($A15),MONTH(DATEVALUE($A15)))) -> 12
A16: 12/25/2025 | C16: DNH*GODADDY#39778629Tempe AZ | D16: JOHN DUNNING | E16: -02000 | F16: 15.98 | G16: 3977862936 4805058855 Email Plus - Renewal - monthly Email - Archiving - Renewal DNH*GODADDY#3977862936 Tempe AZ Email Plus - Renewal - monthly Email - Archiving - Renewal 4805058855 | H16: DNH*GODADDY#39778629Tempe AZ | I16: Go Daddy | K16: =IF($A16="","",IF(ISNUMBER($A16),MONTH($A16),MONTH(DATEVALUE($A16)))) -> 12
A17: 12/23/2025 | C17: DNH*GODADDY#39769602Tempe AZ | D17: JOHN DUNNING | E17: -02000 | F17: 40.97 | G17: 3976960263 4805058855 Business Enterprise - Renewal - 1 month Email - Archiving - Renewal Microsoft 365 Email Backup - Renewal DNH*GODADDY#3976960263 Tempe AZ Business Enterprise - Renewal - 1 month Email - Archiving - Renewal Microsoft 365 Email Backup - Renewal 4805058855 | H17: DNH*GODADDY#39769602Tempe AZ | I17: Go Daddy | K17: =IF($A17="","",IF(ISNUMBER($A17),MONTH($A17),MONTH(DATEVALUE($A17)))) -> 12
A18: 12/20/2025 | C18: CAMPAIGNER SVC 888-845-4544 CA | D18: JOHN DUNNING | E18: -02000 | F18: 584 | G18: 34200007 EMAIL MARKET CAMPAIGNER SVC 888-845-4544 CA EMAIL MARKET | H18: CAMPAIGNER SVC 888-845-4544 CA | I18: DWG-RE Platform (Redirected) | K18: =IF($A18="","",IF(ISNUMBER($A18),MONTH($A18),MONTH(DATEVALUE($A18)))) -> 12
A19: 12/20/2025 | C19: DNH*GODADDY#39749794Tempe AZ | D19: JOHN DUNNING | E19: -02000 | F19: 17.97 | G19: 3974979472 4805058855 Microsoft 365 Email Essentials - Renewal Email - Archiving - Renewal Microsoft 365 Email Backup - Renewal DNH*GODADDY#3974979472 Tempe AZ Microsoft 365 Email Essentials - Renewal Email - Archiving - Renewal Microsoft 365 Email Backup - Renewal 4805058855 | H19: DNH*GODADDY#39749794Tempe AZ | I19: Go Daddy | K19: =IF($A19="","",IF(ISNUMBER($A19),MONTH($A19),MONTH(DATEVALUE($A19)))) -> 12
... A108: 11/30/2025 | C108: LA FIESTA FOODS INC.Los Angeles CA | D108: JOHN DUNNING | E108: -02000 | F108: 74.35 | G108: 5GDNzGPjewG squareup.com/receipts LA FIESTA FOODS INC. DBA THE TAMALE FI Los Angeles CA squareup.com/receipts | H108: LA FIESTA FOODS INC.Los Angeles CA | I108: Personal - Food | K108: =IF($A108="","",IF(ISNUMBER($A108),MONTH($A108),MONTH(DATEVALUE($A108)))) -> 11
A109: 11/30/2025 | B109: * | C109: PICKLED BY SHRED LLCLos Angeles CA | D109: JOHN DUNNING | E109: -02000 | F109: 58 | G109: LtAkhbwJuJj squareup.com/receipts PICKLED BY SHRED LLC Los Angeles CA squareup.com/receipts | H109: PICKLED BY SHRED LLCLos Angeles CA | I109: Personal - Food | K109: =IF($A109="","",IF(ISNUMBER($A109),MONTH($A109),MONTH(DATEVALUE($A109)))) -> 11
A110: 11/30/2025 | C110: PY *FATBURGER 65 000MARINA DEL RE CA | D110: JOHN DUNNING | E110: -02000 | F110: 54.37 | G110: 99999995334 3107490925 PY *FATBURGER 65 000007086 MARINA DEL RE CA 3107490925 | H110: PY *FATBURGER 65 000MARINA DEL RE CA | I110: Personal - Food | K110: =IF($A110="","",IF(ISNUMBER($A110),MONTH($A110),MONTH(DATEVALUE($A110)))) -> 11
A111: 11/30/2025 | C111: SPONSORCLOUD (SYNPROSALT LAKE CITY UT | D111: JOHN DUNNING | E111: -02000 | F111: 180.14 | G111: CH_3SZKXLB7 +13854834872 SPONSORCLOUD (SYNPRO) SALT LAKE CITY UT +13854834872 | H111: SPONSORCLOUD (SYNPROSALT LAKE CITY UT | I111: Sponsor Cloud | K111: =IF($A111="","",IF(ISNUMBER($A111),MONTH($A111),MONTH(DATEVALUE($A111)))) -> 11
A112: 11/30/2025 | C112: TST* BEETHOVEN 00200LOS ANGELES CA | D112: JOHN DUNNING | E112: -02000 | F112: 283.23 | G112: 00200094029 RESTAURANT TST* BEETHOVEN 00200094 LOS ANGELES CA RESTAURANT | H112: TST* BEETHOVEN 00200LOS ANGELES CA | I112: Personal - Food | K112: =IF($A112="","",IF(ISNUMBER($A112),MONTH($A112),MONTH(DATEVALUE($A112)))) -> 11
A113: 11/30/2025 | C113: UNION 76 10194728 LOS ANGELES CA | D113: JOHN DUNNING | E113: -02000 | F113: 6.69 | G113: 11813046054 UNION 76 UNION 76 10194728 LOS ANGELES CA UNION 76 | H113: UNION 76 10194728 LOS ANGELES CA | I113: Personal - Car | K113: =IF($A113="","",IF(ISNUMBER($A113),MONTH($A113),MONTH(DATEVALUE($A113)))) -> 11
A114: 11/29/2025 | C114: CASABLANCA RESTAURANVENICE CA | D114: JOHN DUNNING | E114: -02000 | F114: 147.86 | G114: 31099535334 RESTAURANT CASABLANCA RESTAURANT 00-08045339838 VENICE CA RESTAURANT | H114: CASABLANCA RESTAURANVENICE CA | I114: Personal - Food | K114: =IF($A114="","",IF(ISNUMBER($A114),MONTH($A114),MONTH(DATEVALUE($A114)))) -> 11
A115: 11/29/2025 | C115: DNH*GODADDY#39582504Tempe AZ | D115: JOHN DUNNING | E115: -02000 | F115: 22.98 | G115: 3958250499 4805058855 Microsoft 365 Online Business Essentials Email - Archiving - Renewal DNH*GODADDY#3958250499 Tempe AZ Microsoft 365 Online Business Essentials Email - Archiving - Renewal 4805058855 | H115: DNH*GODADDY#39582504Tempe AZ | I115: Go Daddy | K115: =IF($A115="","",IF(ISNUMBER($A115),MONTH($A115),MONTH(DATEVALUE($A115)))) -> 11
A116: 11/29/2025 | C116: JACKS SURF BOARDS SANTA MONICA CA | D116: JOHN DUNNING | E116: -02000 | F116: 614.29 | G116: 3104506569 JACKS SURF BOARDS SANTA MONICA CA 3104506569 | H116: JACKS SURF BOARDS SANTA MONICA CA | I116: Personal - Entertainment | K116: =IF($A116="","",IF(ISNUMBER($A116),MONTH($A116),MONTH(DATEVALUE($A116)))) -> 11
A117: 11/29/2025 | C117: LARRYS SHAVER SHOPPESANTA MONICA CA | D117: JOHN DUNNING | E117: -02000 | F117: 99.62 | G117: 73011395334 RNAWPAR@GMAIL.COM LARRYS SHAVER SHOPPE 965797900664226 SANTA MONICA CA RNAWPAR@GMAIL.COM | H117: LARRYS SHAVER SHOPPESANTA MONICA CA | I117: Personal - Entertainment | K117: =IF($A117="","",IF(ISNUMBER($A117),MONTH($A117),MONTH(DATEVALUE($A117)))) -> 11
A118: 11/29/2025 | C118: OPENAI *CHATGPT SUBSSAN FRANCISCO CA | D118: JOHN DUNNING | E118: -02000 | F118: 20 | G118: CH_3SYUZBC6 +14158799686 OPENAI *CHATGPT SUBSCR SAN FRANCISCO CA +14158799686 | H118: OPENAI *CHATGPT SUBSSAN FRANCISCO CA | I118: AI Subscriptions | K118: =IF($A118="","",IF(ISNUMBER($A118),MONTH($A118),MONTH(DATEVALUE($A118)))) -> 11
A119: 11/29/2025 | C119: STARBUCKS STORE 0566SANTA MONICA CA | D119: JOHN DUNNING | E119: -02000 | F119: 8.3 | G119: 11D0075BB69 FAST FOOD RESTAURANT STARBUCKS STORE 0566 SANTA MONICA CA FAST FOOD RESTAURANT | H119: STARBUCKS STORE 0566SANTA MONICA CA | I119: Personal - Food | K119: =IF($A119="","",IF(ISNUMBER($A119),MONTH($A119),MONTH(DATEVALUE($A119)))) -> 11
A120: 11/28/2025 | C120: ANACAPA SURF N SPORTOXNARD CA | D120: JOHN DUNNING | E120: -02000 | F120: 87.4 | G120: 44900014 805-382-1602 ANACAPA SURF N SPORT OXNARD CA Description : SPORTING GOODS/APPA Price : 0.00 805-382-1602 | H120: ANACAPA SURF N SPORTOXNARD CA | I120: Personal - Entertainment | K120: =IF($A120="","",IF(ISNUMBER($A120),MONTH($A120),MONTH(DATEVALUE($A120)))) -> 11
A121: 11/28/2025 | C121: ANACAPA SURF N SPORTOXNARD CA | D121: JOHN DUNNING | E121: -02000 | F121: 318.96 | G121: 44900013 805-382-1602 ANACAPA SURF N SPORT OXNARD CA Description : SPORTING GOODS/APPA Price : 0.00 805-382-1602 | H121: ANACAPA SURF N SPORTOXNARD CA | I121: Personal - Entertainment | K121: =IF($A121="","",IF(ISNUMBER($A121),MONTH($A121),MONTH(DATEVALUE($A121)))) -> 11
... A148: 11/16/2025 | C148: SOCIALPILOT LEWES DE | D148: JOHN DUNNING | E148: -02000 | F148: 50 | G148: CH_2SUATN04 +14154506060 SOCIALPILOT LEWES DE +14154506060 | H148: SOCIALPILOT LEWES DE | I148: Software & Subscriptions | K148: =IF($A148="","",IF(ISNUMBER($A148),MONTH($A148),MONTH(DATEVALUE($A148)))) -> 11
A149: 11/16/2025 | B149: * | C149: THE ODYSSEY THEATRE Los Angeles CA | D149: JOHN DUNNING | E149: -02000 | F149: 7 | G149: ZcMQjWOp7Un squareup.com/receipts THE ODYSSEY THEATRE ENSEMBLE Los Angeles CA squareup.com/receipts | H149: THE ODYSSEY THEATRE Los Angeles CA | I149: Personal - Entertainment | K149: =IF($A149="","",IF(ISNUMBER($A149),MONTH($A149),MONTH(DATEVALUE($A149)))) -> 11
A150: 11/15/2025 | C150: 800.COM, LLC 800-800-4321 FL | D150: JOHN DUNNING | E150: -02000 | F150: 69.62 | G150: 21105175320 ESTABLISHES 800.COM, LLC 800-800-4321 FL ESTABLISHES | H150: 800.COM, LLC 800-800-4321 FL | I150: Software & Subscriptions | K150: =IF($A150="","",IF(ISNUMBER($A150),MONTH($A150),MONTH(DATEVALUE($A150)))) -> 11
A151: 11/15/2025 | C151: CVS PHARMACY LOS ANGELES CA | D151: JOHN DUNNING | E151: -02000 | F151: 31.26 | G151: 10052191 8007467287 PHARMACIES CVS PHARMACY LOS ANGELES CA PHARMACIES 8007467287 | H151: CVS PHARMACY LOS ANGELES CA | I151: Personal - Health | K151: =IF($A151="","",IF(ISNUMBER($A151),MONTH($A151),MONTH(DATEVALUE($A151)))) -> 11
A152: 11/15/2025 | C152: RESTORE.COM AUSTIN TX | D152: JOHN DUNNING | E152: -02000 | F152: 199 | G152: CH_3STFJAA8 +15125374087 RESTORE.COM AUSTIN TX +15125374087 | H152: RESTORE.COM AUSTIN TX | I152: Personal - Health | K152: =IF($A152="","",IF(ISNUMBER($A152),MONTH($A152),MONTH(DATEVALUE($A152)))) -> 11
A153: 11/15/2025 | C153: TST* TAVERNA AT THE LOS ANGELES CA | D153: JOHN DUNNING | E153: -02000 | F153: 88.94 | G153: 21105175320 RESTAURANT TST* TAVERNA AT THE MAR V 00207350 LOS ANGELES CA RESTAURANT | H153: TST* TAVERNA AT THE LOS ANGELES CA | I153: Personal - Food | K153: =IF($A153="","",IF(ISNUMBER($A153),MONTH($A153),MONTH(DATEVALUE($A153)))) -> 11
A154: 11/14/2025 | C154: RESTORE.COM AUSTIN TX | D154: JOHN DUNNING | E154: -02000 | F154: 206 | G154: CH_3STYNYA8 +15125374087 RESTORE.COM AUSTIN TX +15125374087 | H154: RESTORE.COM AUSTIN TX | I154: Personal - Health | K154: =IF($A154="","",IF(ISNUMBER($A154),MONTH($A154),MONTH(DATEVALUE($A154)))) -> 11
A155: 11/14/2025 | C155: TST* BLUEYS KITCHEN LOS ANGELES CA | D155: JOHN DUNNING | E155: -02000 | F155: 96.64 | G155: 21105175319 RESTAURANT TST* BLUEYS KITCHEN MAR V 00098618 LOS ANGELES CA RESTAURANT | H155: TST* BLUEYS KITCHEN LOS ANGELES CA | I155: Personal - Food | K155: =IF($A155="","",IF(ISNUMBER($A155),MONTH($A155),MONTH(DATEVALUE($A155)))) -> 11
A156: 11/13/2025 | C156: DNH*GODADDY#39459571Tempe AZ | D156: JOHN DUNNING | E156: -02000 | F156: 43.96 | G156: 3945957161 4805058855 Microsoft 365 Online Business Essentials Email - Archiving - Renewal DNH*GODADDY#3945957161 Tempe AZ Microsoft 365 Online Business Essentials Email - Archiving - Renewal 4805058855 | H156: DNH*GODADDY#39459571Tempe AZ | I156: Go Daddy | K156: =IF($A156="","",IF(ISNUMBER($A156),MONTH($A156),MONTH(DATEVALUE($A156)))) -> 11
A157: 11/13/2025 | C157: PACOS TACOS LOS ANGELES CA | D157: JOHN DUNNING | E157: -02000 | F157: 91.61 | G157: 84600051 310-850-1336 PACOS TACOS LOS ANGELES CA Description : FOOD/BEVERAGE Price : 0.00 310-850-1336 | H157: PACOS TACOS LOS ANGELES CA | I157: Personal - Food | K157: =IF($A157="","",IF(ISNUMBER($A157),MONTH($A157),MONTH(DATEVALUE($A157)))) -> 11
A158: 11/13/2025 | C158: RENOUVEAUM* RENOUVEALOS ANGELES CA | D158: JOHN DUNNING | E158: -02000 | F158: 845.2 | G158: CH_3ST9Z2HU +14697464855 RENOUVEAUM* RENOUVEAUM LOS ANGELES CA +14697464855 | H158: RENOUVEAUM* RENOUVEALOS ANGELES CA | I158: Personal - Health | K158: =IF($A158="","",IF(ISNUMBER($A158),MONTH($A158),MONTH(DATEVALUE($A158)))) -> 11
A159: 11/12/2025 | C159: CITY OF SANTA MONICASANTA MONICA CA | D159: JOHN DUNNING | E159: -02000 | F159: 1.25 | G159: 509377 100003841692546 90401 CITY OF SANTA MONICA SANTA MONICA CA 100003841692546 90401 | H159: CITY OF SANTA MONICASANTA MONICA CA | I159: Personal - Car | K159: =IF($A159="","",IF(ISNUMBER($A159),MONTH($A159),MONTH(DATEVALUE($A159)))) -> 11
A160: 11/12/2025 | C160: SPOTIFY USA NEW YORK NY | D160: JOHN DUNNING | E160: -02000 | F160: 12.98 | G160: P3C5AB5F35 CABLE & PAY TV SPOTIFY USA NEW YORK NY CABLE & PAY TV | H160: SPOTIFY USA NEW YORK NY | I160: Software & Subscriptions | K160: =IF($A160="","",IF(ISNUMBER($A160),MONTH($A160),MONTH(DATEVALUE($A160)))) -> 11
A161: 11/11/2025 | C161: DNH*GODADDY#39446192Tempe AZ | D161: JOHN DUNNING | E161: -02000 | F161: 57.73 | G161: 3944619259 4805058855 Email Essentials - Renewal - monthly Email - Archiving - Renewal DNH*GODADDY#3944619259 Tempe AZ Email Essentials - Renewal - monthly Email - Archiving - Renewal 4805058855 | H161: DNH*GODADDY#39446192Tempe AZ | I161: Go Daddy | K161: =IF($A161="","",IF(ISNUMBER($A161),MONTH($A161),MONTH(DATEVALUE($A161)))) -> 11
... A187: 11/03/2025 | C187: WEATHERFORD MASSAGE WEATHERFORD TX | D187: JOHN DUNNING | E187: -02000 | F187: 90 | G187: 61200001 817-550-6688 WEATHERFORD MASSAGE WEATHERFORD TX Description : MASSAGE PARLOR Price : 0.00 817-550-6688 | H187: WEATHERFORD MASSAGE WEATHERFORD TX | I187: Personal - Health | K187: =IF($A187="","",IF(ISNUMBER($A187),MONTH($A187),MONTH(DATEVALUE($A187)))) -> 11
A188: 11/02/2025 | B188: * | C188: CASA MANANA Fort Worth TX | D188: JOHN DUNNING | E188: -02000 | F188: 7.8 | G188: DH3Wcf10c5Z squareup.com/receipts CASA MANANA Fort Worth TX squareup.com/receipts | H188: CASA MANANA Fort Worth TX | I188: Personal - Entertainment | K188: =IF($A188="","",IF(ISNUMBER($A188),MONTH($A188),MONTH(DATEVALUE($A188)))) -> 11
A189: 11/02/2025 | B189: * | C189: CASA MANANA Fort Worth TX | D189: JOHN DUNNING | E189: -02000 | F189: 16.8 | G189: pWXJP424JBx squareup.com/receipts CASA MANANA Fort Worth TX | H189: CASA MANANA Fort Worth TX | I189: Personal - Entertainment | K189: =IF($A189="","",IF(ISNUMBER($A189),MONTH($A189),MONTH(DATEVALUE($A189)))) -> 11
A190: 11/02/2025 | C190: DNH*GODADDY#39371537Tempe AZ | D190: JOHN DUNNING | E190: -02000 | F190: 19.97 | G190: 3937153772 4805058855 Microsoft 365 Email Essentials - Renewal Email - Archiving - Renewal Professional Email - Individual - Renewa DNH*GODADDY#3937153772 Tempe AZ Microsoft 365 Email Essentials - Renewal Email - Archiving - Renewal Professional Email - Individual - Renewa 4805058855 | H190: DNH*GODADDY#39371537Tempe AZ | I190: Go Daddy | K190: =IF($A190="","",IF(ISNUMBER($A190),MONTH($A190),MONTH(DATEVALUE($A190)))) -> 11
A191: 11/02/2025 | C191: SP FW LOCALS - FWTX FORT WORTH TX | D191: JOHN DUNNING | E191: -02000 | F191: 30.31 | G191: CH_3SPA1DJ8 +18177044258 SP FW LOCALS - FWTX FORT WORTH TX +18177044258 | H191: SP FW LOCALS - FWTX FORT WORTH TX | I191: Personal - Clothing | K191: =IF($A191="","",IF(ISNUMBER($A191),MONTH($A191),MONTH(DATEVALUE($A191)))) -> 11
A192: 11/02/2025 | C192: SP FW LOCALS - FWTX FORT WORTH TX | D192: JOHN DUNNING | E192: -02000 | F192: 30.31 | G192: CH_3SPA6TJ8 +18177044258 SP FW LOCALS - FWTX FORT WORTH TX +18177044258 | H192: SP FW LOCALS - FWTX FORT WORTH TX | I192: Personal - Clothing | K192: =IF($A192="","",IF(ISNUMBER($A192),MONTH($A192),MONTH(DATEVALUE($A192)))) -> 11
A193: 11/01/2025 | C193: ABC*ICONFIT LOS ANGELES CA | D193: JOHN DUNNING | E193: -02000 | F193: 119.52 | G193: 71094475305 310-836-8000 ABC*ICONFIT LOS ANGELES CA 310-836-8000 | H193: ABC*ICONFIT LOS ANGELES CA | I193: Personal - Health | K193: =IF($A193="","",IF(ISNUMBER($A193),MONTH($A193),MONTH(DATEVALUE($A193)))) -> 11
A194: 11/01/2025 | B194: * | C194: BOULEVARD OF GREENS Fort Worth TX | D194: JOHN DUNNING | E194: -02000 | F194: 51.64 | G194: TVEj8jYFy56 squareup.com/receipts BOULEVARD OF GREENS Fort Worth TX squareup.com/receipts | H194: BOULEVARD OF GREENS Fort Worth TX | I194: Personal - Food | K194: =IF($A194="","",IF(ISNUMBER($A194),MONTH($A194),MONTH(DATEVALUE($A194)))) -> 11
A195: 11/01/2025 | C195: DNH*GODADDY#39368645Tempe AZ | D195: JOHN DUNNING | E195: -02000 | F195: 30.97 | G195: 3936864575 4805058855 Business Professional - Renewal - month Email - Archiving - Renewal Microsoft 365 Email Backup - Renewal DNH*GODADDY#3936864575 Tempe AZ Business Professional - Renewal - month Email - Archiving - Renewal Microsoft 365 Email Backup - Renewal 4805058855 | H195: DNH*GODADDY#39368645Tempe AZ | I195: Go Daddy | K195: =IF($A195="","",IF(ISNUMBER($A195),MONTH($A195),MONTH(DATEVALUE($A195)))) -> 11
A196: 11/01/2025 | C196: LOOM SUBSCRIPTION AUSTIN TX | D196: JOHN DUNNING | E196: -02000 | F196: 20 | G196: CH_3SOFCXD0 +16780000000 LOOM SUBSCRIPTION AUSTIN TX +16780000000 | H196: LOOM SUBSCRIPTION AUSTIN TX | I196: Software & Subscriptions | K196: =IF($A196="","",IF(ISNUMBER($A196),MONTH($A196),MONTH(DATEVALUE($A196)))) -> 11
A197: 10/31/2025 | C197: PAYPAL *CREPUSHCOM 4029357733 FL | D197: JOHN DUNNING | E197: -02000 | F197: 139 | G197: 10194218800 4029357733 PAYPAL *CREPUSHCOM 4029357733 FL "Description : MANAGEMENT, CONSULT Price : 0.00" 4029357733 | H197: PAYPAL *CREPUSHCOM 4029357733 FL | I197: DWG Marketing | K197: =IF($A197="","",IF(ISNUMBER($A197),MONTH($A197),MONTH(DATEVALUE($A197)))) -> 10
A198: 10/31/2025 | C198: PROPERTYBLAST.COM 800-418-4452 FL | D198: JOHN DUNNING | E198: -02000 | F198: 159 | G198: 85189935304800-418-4452 PROPERTYBLAST.COM 800-418-4452 FL 800-418-4452 | H198: PROPERTYBLAST.COM 800-418-4452 FL | I198: DWG Marketing | K198: =IF($A198="","",IF(ISNUMBER($A198),MONTH($A198),MONTH(DATEVALUE($A198)))) -> 10
A199: 10/31/2025 | C199: SPONSORCLOUD (SYNPROSALT LAKE CITY UT | D199: JOHN DUNNING | E199: -02000 | F199: 179.16 | G199: CH_3SOSEVB7 +13854834872 SPONSORCLOUD (SYNPRO) SALT LAKE CITY UT +13854834872 | H199: SPONSORCLOUD (SYNPROSALT LAKE CITY UT | I199: Sponsor Cloud | K199: =IF($A199="","",IF(ISNUMBER($A199),MONTH($A199),MONTH(DATEVALUE($A199)))) -> 10
A200: 10/31/2025 | C200: ZENO'S ON THE SQUAREWEATHERFORD TX | D200: JOHN DUNNING | E200: -02000 | F200: 154.49 | G200: 21105175305 RESTAURANT ZENO'S ON THE SQUARE WEATHERFORD TX RESTAURANT | H200: ZENO'S ON THE SQUAREWEATHERFORD TX | I200: Personal - Food | K200: =IF($A200="","",IF(ISNUMBER($A200),MONTH($A200),MONTH(DATEVALUE($A200)))) -> 10
A201: 10/30/2025 | C201: MINTY BOI INC Dallas TX | D201: JOHN DUNNING | E201: -02000 | F201: 108.25 | G201: frCG2iYRfNz squareup.com/receipts MINTY BOI INC Dallas TX | H201: MINTY BOI INC Dallas TX | I201: Personal - Food | K201: =IF($A201="","",IF(ISNUMBER($A201),MONTH($A201),MONTH(DATEVALUE($A201)))) -> 10
A202: 10/30/2025 | C202: TST* GRANADA THEATERDALLAS TX | D202: JOHN DUNNING | E202: -02000 | F202: 7.39 | G202: 99999995303 2148249933 TST* GRANADA THEATER 300569169 DALLAS TX Description : BARS Price : 0.0739 2148249933 | H202: TST* GRANADA THEATERDALLAS TX | I202: Personal - Food | K202: =IF($A202="","",IF(ISNUMBER($A202),MONTH($A202),MONTH(DATEVALUE($A202)))) -> 10
A203: 10/29/2025 | C203: DNH*GODADDY#39344090Tempe AZ | D203: JOHN DUNNING | E203: -02000 | F203: 22.98 | G203: 3934409076 4805058855 Microsoft 365 Online Business Essentials Email - Archiving - Renewal DNH*GODADDY#3934409076 Tempe AZ Microsoft 365 Online Business Essentials Email - Archiving - Renewal 4805058855 | H203: DNH*GODADDY#39344090Tempe AZ | I203: Go Daddy | K203: =IF($A203="","",IF(ISNUMBER($A203),MONTH($A203),MONTH(DATEVALUE($A203)))) -> 10
A204: 10/29/2025 | C204: EXXONMOBIL WEATHERFORD TX | D204: JOHN DUNNING | E204: -02000 | F204: 57.62 | G204: 00013767 817-613-9437 EXXONMOBIL WEATHERFORD TX Description : 001 Price : 0.00 817-613-9437 | H204: EXXONMOBIL WEATHERFORD TX | I204: Personal - Car | K204: =IF($A204="","",IF(ISNUMBER($A204),MONTH($A204),MONTH(DATEVALUE($A204)))) -> 10
A205: 10/29/2025 | C205: GAMMA.APP SAN FRANCISCO CA | D205: JOHN DUNNING | E205: -02000 | F205: 180 | G205: CH_3SNCRHAC +14152371288 GAMMA.APP SAN FRANCISCO CA +14152371288 | H205: GAMMA.APP SAN FRANCISCO CA | I205: DWG Marketing | K205: =IF($A205="","",IF(ISNUMBER($A205),MONTH($A205),MONTH(DATEVALUE($A205)))) -> 10
A206: 10/29/2025 | C206: ONLINE PAYMENT - THANK YOU | D206: JOHN DUNNING | E206: -02000 | F206: -380.97 | G206: ONLINE PAYMENT - THANK YOU | H206: ONLINE PAYMENT - THANK YOU | I206: Online AMEX Payment | K206: =IF($A206="","",IF(ISNUMBER($A206),MONTH($A206),MONTH(DATEVALUE($A206)))) -> 10
... A259: 10/12/2025 | C259: SPOTIFY USA NEW YORK NY | D259: JOHN DUNNING | E259: -02000 | F259: 12.98 | G259: P3B6DE9252 CABLE & PAY TV SPOTIFY USA NEW YORK NY CABLE & PAY TV | H259: SPOTIFY USA NEW YORK NY | I259: Software & Subscriptions | K259: =IF($A259="","",IF(ISNUMBER($A259),MONTH($A259),MONTH(DATEVALUE($A259)))) -> 10
A260: 10/12/2025 | B260: * | C260: THE CORNER BEET Denver CO | D260: JOHN DUNNING | E260: -02000 | F260: 144.54 | G260: 7z97BY5krK6 squareup.com/receipts THE CORNER BEET Denver CO squareup.com/receipts | H260: THE CORNER BEET Denver CO | I260: Personal - Food | K260: =IF($A260="","",IF(ISNUMBER($A260),MONTH($A260),MONTH(DATEVALUE($A260)))) -> 10
A261: 10/11/2025 | C261: DNH*GODADDY#39202417Tempe AZ | D261: JOHN DUNNING | E261: -02000 | F261: 81.91 | G261: 3920241732 4805058855 COM Domain Name Renewal - 1 Year recur Full Domain Protection - Renewal Email Essentials - Renewal - monthly Email - Archiving - Renewal DNH*GODADDY#3920241732 Tempe AZ COM Domain Name Renewal - 1 Year recur Full Domain Protection - Renewal Email Essentials - Renewal - monthly Email - Archiving - Renewal 4805058855 | H261: DNH*GODADDY#39202417Tempe AZ | I261: Go Daddy | K261: =IF($A261="","",IF(ISNUMBER($A261),MONTH($A261),MONTH(DATEVALUE($A261)))) -> 10
A262: 10/11/2025 | C262: TST* LAS MONTANAS 00ASPEN CO | D262: JOHN DUNNING | E262: -02000 | F262: 300 | G262: 21105175285 RESTAURANT TST* LAS MONTANAS 00085873 ASPEN CO RESTAURANT | H262: TST* LAS MONTANAS 00ASPEN CO | I262: Personal - Food | K262: =IF($A262="","",IF(ISNUMBER($A262),MONTH($A262),MONTH(DATEVALUE($A262)))) -> 10
A263: 10/10/2025 | C263: AMAZON.COM AMZN.COM/BILL WA | D263: JOHN DUNNING | E263: -02000 | F263: 205.66 | G263: 2I1O5Z4OTMP MERCHANDISE AMAZON.COM AMZN.COM/BILL WA MERCHANDISE | H263: AMAZON.COM AMZN.COM/BILL WA | I263: Amazon | K263: =IF($A263="","",IF(ISNUMBER($A263),MONTH($A263),MONTH(DATEVALUE($A263)))) -> 10
A264: 10/10/2025 | C264: DNH*GODADDY#39192267Tempe AZ | D264: JOHN DUNNING | E264: -02000 | F264: 174.76 | G264: 3919226711 4805058855 Websites Marketing with Email Renewal Business Professional - Renewal - month Email - Archiving - Renewal Email Essentials - Renewal - 1 Year DNH*GODADDY#3919226711 Tempe AZ Websites Marketing with Email Renewal Business Professional - Renewal - month Email - Archiving - Renewal Email Essentials - Renewal - 1 Year 4805058855 | H264: DNH*GODADDY#39192267Tempe AZ | I264: Go Daddy | K264: =IF($A264="","",IF(ISNUMBER($A264),MONTH($A264),MONTH(DATEVALUE($A264)))) -> 10
A265: 10/10/2025 | C265: TST* POPULUS HOTEL- DENVER CO | D265: JOHN DUNNING | E265: -02000 | F265: 101.78 | G265: YqTcSmdTI00 3038004240 TST* POPULUS HOTEL- STELL 300569983 DENVER CO Description : RESTAURANTS Price : 1.0178 3038004240 | H265: TST* POPULUS HOTEL- DENVER CO | I265: Denver Trip | K265: =IF($A265="","",IF(ISNUMBER($A265),MONTH($A265),MONTH(DATEVALUE($A265)))) -> 10
A266: 10/10/2025 | C266: VIMEO PRO 212-625-0668 NY | D266: JOHN DUNNING | E266: -02000 | F266: 24 | G266: P-05695735 MEMBERSHIP VIMEO PRO 212-625-0668 NY MEMBERSHIP | H266: VIMEO PRO 212-625-0668 NY | I266: Software & Subscriptions | K266: =IF($A266="","",IF(ISNUMBER($A266),MONTH($A266),MONTH(DATEVALUE($A266)))) -> 10
A267: 10/09/2025 | C267: BALANCED ROOT APOTHEDenver CO | D267: JOHN DUNNING | E267: -02000 | F267: 26.2 | G267: HZXcfG5gULg squareup.com/receipts BALANCED ROOT APOTHECARY Denver CO squareup.com/receipts | H267: BALANCED ROOT APOTHEDenver CO | I267: Denver Trip | K267: =IF($A267="","",IF(ISNUMBER($A267),MONTH($A267),MONTH(DATEVALUE($A267)))) -> 10
A268: 10/09/2025 | C268: COLORADO CC DPAC CONDENVER CO | D268: JOHN DUNNING | E268: -02000 | F268: 14.75 | G268: 00000010806 7303001762 COLORADO CC DPAC CONC DENVER CO Description : NO DATA SUBMITTED Price : 0.00 7303001762 | H268: COLORADO CC DPAC CONDENVER CO | I268: Denver Trip | K268: =IF($A268="","",IF(ISNUMBER($A268),MONTH($A268),MONTH(DATEVALUE($A268)))) -> 10
A269: 10/09/2025 | C269: DNH*GODADDY#39184358Tempe AZ | D269: JOHN DUNNING | E269: -02000 | F269: 13.79 | G269: 3918435839 4805058855 Conversations Deluxe - 1 Month - Renewal DNH*GODADDY#3918435839 Tempe AZ Conversations Deluxe - 1 Month - Renewal 4805058855 | H269: DNH*GODADDY#39184358Tempe AZ | I269: Go Daddy | K269: =IF($A269="","",IF(ISNUMBER($A269),MONTH($A269),MONTH(DATEVALUE($A269)))) -> 10
A270: 10/09/2025 | C270: HYDRATEIVBAR.COM DENVER CO | D270: JOHN DUNNING | E270: -02000 | F270: 180 | G270: CH_3SGQCFBB +13852336964 HYDRATEIVBAR.COM DENVER CO +13852336964 | H270: HYDRATEIVBAR.COM DENVER CO | I270: Denver Trip | K270: =IF($A270="","",IF(ISNUMBER($A270),MONTH($A270),MONTH(DATEVALUE($A270)))) -> 10
A271: 10/09/2025 | B271: * | C271: THE CORNER BEET Denver CO | D271: JOHN DUNNING | E271: -02000 | F271: 133.89 | G271: 3JXi7rK13Bo squareup.com/receipts THE CORNER BEET Denver CO squareup.com/receipts | H271: THE CORNER BEET Denver CO | I271: Denver Trip | K271: =IF($A271="","",IF(ISNUMBER($A271),MONTH($A271),MONTH(DATEVALUE($A271)))) -> 10
A272: 10/08/2025 | C272: DNH*GODADDY#39175484Tempe AZ | D272: JOHN DUNNING | E272: -02000 | F272: 30.97 | G272: 3917548488 4805058855 Microsoft 365 Business Professional- Ren Email - Archiving - Renewal Microsoft 365 Email Backup - Renewal DNH*GODADDY#3917548488 Tempe AZ Microsoft 365 Business Professional- Ren Email - Archiving - Renewal Microsoft 365 Email Backup - Renewal 4805058855 | H272: DNH*GODADDY#39175484Tempe AZ | I272: Go Daddy | K272: =IF($A272="","",IF(ISNUMBER($A272),MONTH($A272),MONTH(DATEVALUE($A272)))) -> 10
A273: 10/08/2025 | C273: LAX AIRP BGRILL BY BLOS ANGELES CA | D273: JOHN DUNNING | E273: -02000 | F273: 130.55 | G273: 004328083 866-820-1178 LAX AIRP BGRILL BY BOA LAX AIRP BGRILL LOS ANGELES CA 866-820-1178 | H273: LAX AIRP BGRILL BY BLOS ANGELES CA | I273: Denver Trip | K273: =IF($A273="","",IF(ISNUMBER($A273),MONTH($A273),MONTH(DATEVALUE($A273)))) -> 10
A274: 10/08/2025 | C274: OPENAI *CHATGPT SUBSSAN FRANCISCO CA | D274: JOHN DUNNING | E274: -02000 | F274: 20 | G274: CH_3SG7ABC6 +14158799686 OPENAI *CHATGPT SUBSCR SAN FRANCISCO CA +14158799686 | H274: OPENAI *CHATGPT SUBSSAN FRANCISCO CA | I274: AI Subscriptions | K274: =IF($A274="","",IF(ISNUMBER($A274),MONTH($A274),MONTH(DATEVALUE($A274)))) -> 10
A275: 10/08/2025 | C275: PACIFIC SPAS & SAUNALOS ANGELES CA | D275: JOHN DUNNING | E275: -02000 | F275: 410.2 | G275: 50300006 310-445-7727 PACIFIC SPAS & SAUNA 0000 LOS ANGELES CA Description : POOL/PATIO/SPA/SPLY Price : 0.00 310-445-7727 | H275: PACIFIC SPAS & SAUNALOS ANGELES CA | I275: Personal - House | K275: =IF($A275="","",IF(ISNUMBER($A275),MONTH($A275),MONTH(DATEVALUE($A275)))) -> 10
A276: 10/07/2025 | C276: CITY OF SANTA MONICASANTA MONICA CA | D276: JOHN DUNNING | E276: -02000 | F276: 1.25 | G276: 547243 100003822024681 90401 CITY OF SANTA MONICA SANTA MONICA CA 100003822024681 90401 | H276: CITY OF SANTA MONICASANTA MONICA CA | I276: Personal - Car | K276: =IF($A276="","",IF(ISNUMBER($A276),MONTH($A276),MONTH(DATEVALUE($A276)))) -> 10
A277: 10/07/2025 | C277: DNH*GODADDY#39169529Tempe AZ | D277: JOHN DUNNING | E277: -02000 | F277: 10.99 | G277: 3916952965 4805058855 Microsoft 365 Email Plus- Renewal - mont DNH*GODADDY#3916952965 Tempe AZ Microsoft 365 Email Plus- Renewal - mont 4805058855 | H277: DNH*GODADDY#39169529Tempe AZ | I277: Go Daddy | K277: =IF($A277="","",IF(ISNUMBER($A277),MONTH($A277),MONTH(DATEVALUE($A277)))) -> 10
A278: 10/07/2025 | C278: Points for Amex Trvl | D278: JOHN DUNNING | E278: -02000 | F278: -290 | G278: Points for Amex Trvl | H278: Points for Amex Trvl | I278: Points for Amex Trvl | K278: =IF($A278="","",IF(ISNUMBER($A278),MONTH($A278),MONTH(DATEVALUE($A278)))) -> 10
A279: 10/07/2025 | C279: PwP AMERICAN EXPRSEATTLE WA | D279: JOHN DUNNING | E279: -02000 | F279: 312.48 | G279: 100809 AIRLINE/AIR CARRIER PASSENGER TICKET PwP AMERICAN EXPRESS TRAVEL SEATTLE WA Carrier : UNITED AIRLINES Passenger Name : HARTMAYER/SAGIV Ticket Number : 01673389276145 Departure Day : 10/09 Additional Info : PASSENGER TICKET From : PHOENIX SKY HARBOR To : LOS ANGELES INTERN Class : U | H279: PwP AMERICAN EXPRSEATTLE WA | I279: Team Travel (Judd) | K279: =IF($A279="","",IF(ISNUMBER($A279),MONTH($A279),MONTH(DATEVALUE($A279)))) -> 10
A280: 10/07/2025 | C280: REI#274 MARINA D RAYMARINA DEL REY CA | D280: JOHN DUNNING | E280: -02000 | F280: 82.26 | G280: 822848 0000000000000000090292 REI#274 MARINA D RAY MARINA DEL REY CA 0000000000000000090292 | H280: REI#274 MARINA D RAYMARINA DEL REY CA | I280: Personal - Clothing | K280: =IF($A280="","",IF(ISNUMBER($A280),MONTH($A280),MONTH(DATEVALUE($A280)))) -> 10
A281: 10/07/2025 | C281: RENTV.COM, INC. 310-242-8613 CA | D281: JOHN DUNNING | E281: -02000 | F281: 1350 | G281: 21105175281 ADVERTISING RENTV.COM, INC. 310-242-8613 CA ADVERTISING | H281: RENTV.COM, INC. 310-242-8613 CA | I281: DWG Conference | K281: =IF($A281="","",IF(ISNUMBER($A281),MONTH($A281),MONTH(DATEVALUE($A281)))) -> 10
A282: 10/07/2025 | C282: RESTORE.COM AUSTIN TX | D282: JOHN DUNNING | E282: -02000 | F282: 120 | G282: CH_3SFLJRA8 +15125374087 RESTORE.COM AUSTIN TX +15125374087 | H282: RESTORE.COM AUSTIN TX | I282: Personal - Health | K282: =IF($A282="","",IF(ISNUMBER($A282),MONTH($A282),MONTH(DATEVALUE($A282)))) -> 10
A283: 10/07/2025 | C283: Southwest Airlines DALLAS TX | D283: JOHN DUNNING | E283: -02000 | F283: 244.48 | G283: 7900405470 (214) 792 - 4223 PASSENGER TICKET Southwest Airlines DALLAS TX Carrier : SOUTHWEST AIRLINES (MASTE Passenger Name : HARTMAYER/SAGIV Ticket Number : 5262393917509 Departure Day : 10/09 Additional Info : PASSENGER TICKET From : LOS ANGELES INTERN To : PHOENIX SKY HARBOR Class : N | H283: Southwest Airlines DALLAS TX | I283: Team Travel (Judd) | K283: =IF($A283="","",IF(ISNUMBER($A283),MONTH($A283),MONTH(DATEVALUE($A283)))) -> 10
... A302: 10/03/2025 | C302: SALESMESSAGE.COM DELRAY BEACH FL | D302: JOHN DUNNING | E302: -02000 | F302: 52.14 | G302: CH_3SEN5DCY +18884092298 SALESMESSAGE.COM DELRAY BEACH FL +18884092298 | H302: SALESMESSAGE.COM DELRAY BEACH FL | I302: Software & Subscriptions | K302: =IF($A302="","",IF(ISNUMBER($A302),MONTH($A302),MONTH(DATEVALUE($A302)))) -> 10
A303: 10/03/2025 | B303: * | C303: THE HANGAR Santa Monica CA | D303: JOHN DUNNING | E303: -02000 | F303: 1529.73 | G303: j9aiOBcO9Gs squareup.com/receipts THE HANGAR Santa Monica CA squareup.com/receipts | H303: THE HANGAR Santa Monica CA | I303: Personal - House | K303: =IF($A303="","",IF(ISNUMBER($A303),MONTH($A303),MONTH(DATEVALUE($A303)))) -> 10
A304: 10/03/2025 | C304: TST* BLUEYS KITCHEN LOS ANGELES CA | D304: JOHN DUNNING | E304: -02000 | F304: 121.01 | G304: 21105175277 RESTAURANT TST* BLUEYS KITCHEN MAR V 00098618 LOS ANGELES CA RESTAURANT | H304: TST* BLUEYS KITCHEN LOS ANGELES CA | I304: Personal - Food | K304: =IF($A304="","",IF(ISNUMBER($A304),MONTH($A304),MONTH(DATEVALUE($A304)))) -> 10
A305: 10/02/2025 | C305: CASABLANCA 00-080164VENICE CA | D305: JOHN DUNNING | E305: -02000 | F305: 80.1 | G305: 31099535276 RESTAURANT CASABLANCA 00-08016445473 VENICE CA RESTAURANT | H305: CASABLANCA 00-080164VENICE CA | I305: Personal - Food | K305: =IF($A305="","",IF(ISNUMBER($A305),MONTH($A305),MONTH(DATEVALUE($A305)))) -> 10
A306: 10/02/2025 | C306: DNH*GODADDY#39125988Tempe AZ | D306: JOHN DUNNING | E306: -02000 | F306: 19.97 | G306: 3912598837 4805058855 Microsoft 365 Email Essentials - Renewal Email - Archiving - Renewal Professional Email - Individual - Renewa DNH*GODADDY#3912598837 Tempe AZ Microsoft 365 Email Essentials - Renewal Email - Archiving - Renewal Professional Email - Individual - Renewa 4805058855 | H306: DNH*GODADDY#39125988Tempe AZ | I306: Go Daddy | K306: =IF($A306="","",IF(ISNUMBER($A306),MONTH($A306),MONTH(DATEVALUE($A306)))) -> 10
A307: 10/01/2025 | C307: ABC*ICONFIT LOS ANGELES CA | D307: JOHN DUNNING | E307: -02000 | F307: 119.52 | G307: 71094475274 310-836-8000 ABC*ICONFIT LOS ANGELES CA 310-836-8000 | H307: ABC*ICONFIT LOS ANGELES CA | I307: Personal - Health | K307: =IF($A307="","",IF(ISNUMBER($A307),MONTH($A307),MONTH(DATEVALUE($A307)))) -> 10
A308: 10/01/2025 | C308: DNH*GODADDY#39115285Tempe AZ | D308: JOHN DUNNING | E308: -02000 | F308: 30.97 | G308: 3911528509 4805058855 Business Professional - Renewal - month Email - Archiving - Renewal Microsoft 365 Email Backup - Renewal DNH*GODADDY#3911528509 Tempe AZ Business Professional - Renewal - month Email - Archiving - Renewal Microsoft 365 Email Backup - Renewal 4805058855 | H308: DNH*GODADDY#39115285Tempe AZ | I308: Go Daddy | K308: =IF($A308="","",IF(ISNUMBER($A308),MONTH($A308),MONTH(DATEVALUE($A308)))) -> 10
A309: 10/01/2025 | C309: EGNYTE INC 000000001MOUNTAIN VIEW CA | D309: JOHN DUNNING | E309: -02000 | F309: 2484 | G309: 13358061 6509684018 EGNYTE INC 000000001 MOUNTAIN VIEW CA Description : REFER TO RECEIPT Price : 0.00 6509684018 | H309: EGNYTE INC 000000001MOUNTAIN VIEW CA | I309: DWG Operations | K309: =IF($A309="","",IF(ISNUMBER($A309),MONTH($A309),MONTH(DATEVALUE($A309)))) -> 10
A310: 10/01/2025 | C310: LOOM SUBSCRIPTION AUSTIN TX | D310: JOHN DUNNING | E310: -02000 | F310: 20 | G310: CH_3SDQRQD0 +16780000000 LOOM SUBSCRIPTION AUSTIN TX +16780000000 | H310: LOOM SUBSCRIPTION AUSTIN TX | I310: Software & Subscriptions | K310: =IF($A310="","",IF(ISNUMBER($A310),MONTH($A310),MONTH(DATEVALUE($A310)))) -> 10
...
