Workbook

Sheet Category Summary
A1: Chase 9335 — 2025 Activity
A2: Category Summary | Jan 2025 – Dec 2025
A4: Entity | B4: Poseidon Asset Group
A5: Account | B5: Personal Checking — Chase 9335
A6: Period | B6: Jan 2025 – Dec 2025
A8: TOTALS
A9: Total Inflows | B9: =SUMIFS('Transaction Overview'!$D$2:$D$790,'Transaction Overview'!$D$2:$D$790,">0") -> 2665832.7
A10: Total Outflows | B10: =SUMIFS('Transaction Overview'!$D$2:$D$790,'Transaction Overview'!$D$2:$D$790,"<0") -> -2704637.9
A11: Net Change | B11: =B9+B10 -> -38805.16
A14: Category | B14: Inflows | C14: Outflows | D14: Net
A15: Deal-Specific
A16: Deal Specific: Austin Iron | B16: =SUMIFS('Transaction Overview'!$D$2:$D$790,'Transaction Overview'!$G$2:$G$790,$A16,'Transaction Overview'!$D$2:$D$790,">0") -> 4200 | C16: =SUMIFS('Transaction Overview'!$D$2:$D$790,'Transaction Overview'!$G$2:$G$790,$A16,'Transaction Overview'!$D$2:$D$790,"<0") -> 0 | D16: =B16+C16 -> 4200
A17: Deal Specific: Cloverdale | B17: =SUMIFS('Transaction Overview'!$D$2:$D$790,'Transaction Overview'!$G$2:$G$790,$A17,'Transaction Overview'!$D$2:$D$790,">0") -> 0 | C17: =SUMIFS('Transaction Overview'!$D$2:$D$790,'Transaction Overview'!$G$2:$G$790,$A17,'Transaction Overview'!$D$2:$D$790,"<0") -> -155000 | D17: =B17+C17 -> -155000
A18: Deal Specific: Hibbert | B18: =SUMIFS('Transaction Overview'!$D$2:$D$790,'Transaction Overview'!$G$2:$G$790,$A18,'Transaction Overview'!$D$2:$D$790,">0") -> 0 | C18: =SUMIFS('Transaction Overview'!$D$2:$D$790,'Transaction Overview'!$G$2:$G$790,$A18,'Transaction Overview'!$D$2:$D$790,"<0") -> -46528.05 | D18: =B18+C18 -> -46528.05
A19: Deal Specific: JAL Breese | B19: =SUMIFS('Transaction Overview'!$D$2:$D$790,'Transaction Overview'!$G$2:$G$790,$A19,'Transaction Overview'!$D$2:$D$790,">0") -> 0 | C19: =SUMIFS('Transaction Overview'!$D$2:$D$790,'Transaction Overview'!$G$2:$G$790,$A19,'Transaction Overview'!$D$2:$D$790,"<0") -> -50000 | D19: =B19+C19 -> -50000
A20: Deal Specific: Merit-Lancaster | B20: =SUMIFS('Transaction Overview'!$D$2:$D$790,'Transaction Overview'!$G$2:$G$790,$A20,'Transaction Overview'!$D$2:$D$790,">0") -> 5687.14 | C20: =SUMIFS('Transaction Overview'!$D$2:$D$790,'Transaction Overview'!$G$2:$G$790,$A20,'Transaction Overview'!$D$2:$D$790,"<0") -> 0 | D20: =B20+C20 -> 5687.14
A21: Deal Specific: Moab | B21: =SUMIFS('Transaction Overview'!$D$2:$D$790,'Transaction Overview'!$G$2:$G$790,$A21,'Transaction Overview'!$D$2:$D$790,">0") -> 626675 | C21: =SUMIFS('Transaction Overview'!$D$2:$D$790,'Transaction Overview'!$G$2:$G$790,$A21,'Transaction Overview'!$D$2:$D$790,"<0") -> -620000 | D21: =B21+C21 -> 6675
A22: Deal Specific: MRM | B22: =SUMIFS('Transaction Overview'!$D$2:$D$790,'Transaction Overview'!$G$2:$G$790,$A22,'Transaction Overview'!$D$2:$D$790,">0") -> 2847.44 | C22: =SUMIFS('Transaction Overview'!$D$2:$D$790,'Transaction Overview'!$G$2:$G$790,$A22,'Transaction Overview'!$D$2:$D$790,"<0") -> 0 | D22: =B22+C22 -> 2847.44
A23: Deal Specific: Rabourn Road | B23: =SUMIFS('Transaction Overview'!$D$2:$D$790,'Transaction Overview'!$G$2:$G$790,$A23,'Transaction Overview'!$D$2:$D$790,">0") -> 1166.65 | C23: =SUMIFS('Transaction Overview'!$D$2:$D$790,'Transaction Overview'!$G$2:$G$790,$A23,'Transaction Overview'!$D$2:$D$790,"<0") -> 0 | D23: =B23+C23 -> 1166.65
A24: Deal Specific: T&T Machine | B24: =SUMIFS('Transaction Overview'!$D$2:$D$790,'Transaction Overview'!$G$2:$G$790,$A24,'Transaction Overview'!$D$2:$D$790,">0") -> 4315.42 | C24: =SUMIFS('Transaction Overview'!$D$2:$D$790,'Transaction Overview'!$G$2:$G$790,$A24,'Transaction Overview'!$D$2:$D$790,"<0") -> 0 | D24: =B24+C24 -> 4315.42
A25: Subtotal — Deal-Specific | B25: =SUMIFS('Transaction Overview'!$D$2:$D$790,'Transaction Overview'!$J$2:$J$790,"Deal-Specific",'Transaction Overview'!$D$2:$D$790,">0") -> 644891.65 | C25: =SUMIFS('Transaction Overview'!$D$2:$D$790,'Transaction Overview'!$J$2:$J$790,"Deal-Specific",'Transaction Overview'!$D$2:$D$790,"<0") -> -871528.05 | D25: =B25+C25 -> -226636.4
A27: Commissions — Incoming
A28: Incoming Commission: Breese | B28: =SUMIFS('Transaction Overview'!$D$2:$D$790,'Transaction Overview'!$G$2:$G$790,$A28,'Transaction Overview'!$D$2:$D$790,">0") -> 269473.73 | C28: =SUMIFS('Transaction Overview'!$D$2:$D$790,'Transaction Overview'!$G$2:$G$790,$A28,'Transaction Overview'!$D$2:$D$790,"<0") -> 0 | D28: =B28+C28 -> 269473.73
A29: Incoming Commission: Butler Weldments | B29: =SUMIFS('Transaction Overview'!$D$2:$D$790,'Transaction Overview'!$G$2:$G$790,$A29,'Transaction Overview'!$D$2:$D$790,">0") -> 164150.5 | C29: =SUMIFS('Transaction Overview'!$D$2:$D$790,'Transaction Overview'!$G$2:$G$790,$A29,'Transaction Overview'!$D$2:$D$790,"<0") -> 0 | D29: =B29+C29 -> 164150.5
A30: Incoming Commission: Edge Builder | B30: =SUMIFS('Transaction Overview'!$D$2:$D$790,'Transaction Overview'!$G$2:$G$790,$A30,'Transaction Overview'!$D$2:$D$790,">0") -> 148250 | C30: =SUMIFS('Transaction Overview'!$D$2:$D$790,'Transaction Overview'!$G$2:$G$790,$A30,'Transaction Overview'!$D$2:$D$790,"<0") -> 0 | D30: =B30+C30 -> 148250
A31: Incoming Commission: Kalkaska Screw | B31: =SUMIFS('Transaction Overview'!$D$2:$D$790,'Transaction Overview'!$G$2:$G$790,$A31,'Transaction Overview'!$D$2:$D$790,">0") -> 133875 | C31: =SUMIFS('Transaction Overview'!$D$2:$D$790,'Transaction Overview'!$G$2:$G$790,$A31,'Transaction Overview'!$D$2:$D$790,"<0") -> 0 | D31: =B31+C31 -> 133875
A32: Incoming Commission: Stryten Energy | B32: =SUMIFS('Transaction Overview'!$D$2:$D$790,'Transaction Overview'!$G$2:$G$790,$A32,'Transaction Overview'!$D$2:$D$790,">0") -> 318189.39 | C32: =SUMIFS('Transaction Overview'!$D$2:$D$790,'Transaction Overview'!$G$2:$G$790,$A32,'Transaction Overview'!$D$2:$D$790,"<0") -> 0 | D32: =B32+C32 -> 318189.39
A33: Subtotal — Commissions — Incoming | B33: =SUMIFS('Transaction Overview'!$D$2:$D$790,'Transaction Overview'!$J$2:$J$790,"Commissions — Incoming",'Transaction Overview'!$D$2:$D$790,">0") -> 1033938.6 | C33: =SUMIFS('Transaction Overview'!$D$2:$D$790,'Transaction Overview'!$J$2:$J$790,"Commissions — Incoming",'Transaction Overview'!$D$2:$D$790,"<0") -> 0 | D33: =B33+C33 -> 1033938.6
A35: Commissions — Outgoing
A36: Wire Out — Edge Builder Commission Payments | B36: =SUMIFS('Transaction Overview'!$D$2:$D$790,'Transaction Overview'!$G$2:$G$790,$A36,'Transaction Overview'!$D$2:$D$790,">0") -> 0 | C36: =SUMIFS('Transaction Overview'!$D$2:$D$790,'Transaction Overview'!$G$2:$G$790,$A36,'Transaction Overview'!$D$2:$D$790,"<0") -> -23830 | D36: =B36+C36 -> -23830
A37: Wire Out — Stryten Commission Payments | B37: =SUMIFS('Transaction Overview'!$D$2:$D$790,'Transaction Overview'!$G$2:$G$790,$A37,'Transaction Overview'!$D$2:$D$790,">0") -> 0 | C37: =SUMIFS('Transaction Overview'!$D$2:$D$790,'Transaction Overview'!$G$2:$G$790,$A37,'Transaction Overview'!$D$2:$D$790,"<0") -> -47820 | D37: =B37+C37 -> -47820
A38: Subtotal — Commissions — Outgoing | B38: =SUMIFS('Transaction Overview'!$D$2:$D$790,'Transaction Overview'!$J$2:$J$790,"Commissions — Outgoing",'Transaction Overview'!$D$2:$D$790,">0") -> 0 | C38: =SUMIFS('Transaction Overview'!$D$2:$D$790,'Transaction Overview'!$J$2:$J$790,"Commissions — Outgoing",'Transaction Overview'!$D$2:$D$790,"<0") -> -71650 | D38: =B38+C38 -> -71650
A40: MAG Pass-Through
A41: Due to Andrew – MAG Pass-Through 30% | B41: =SUMIFS('Transaction Overview'!$D$2:$D$790,'Transaction Overview'!$G$2:$G$790,$A41,'Transaction Overview'!$D$2:$D$790,">0") -> 0 | C41: =SUMIFS('Transaction Overview'!$D$2:$D$790,'Transaction Overview'!$G$2:$G$790,$A41,'Transaction Overview'!$D$2:$D$790,"<0") -> -21000 | D41: =B41+C41 -> -21000
A42: Due to Dax – MAG Pass-Through 70% | B42: =SUMIFS('Transaction Overview'!$D$2:$D$790,'Transaction Overview'!$G$2:$G$790,$A42,'Transaction Overview'!$D$2:$D$790,">0") -> 0 | C42: =SUMIFS('Transaction Overview'!$D$2:$D$790,'Transaction Overview'!$G$2:$G$790,$A42,'Transaction Overview'!$D$2:$D$790,"<0") -> -39000 | D42: =B42+C42 -> -39000
A43: MAG - Admeer Advisory Reimbursement | B43: =SUMIFS('Transaction Overview'!$D$2:$D$790,'Transaction Overview'!$G$2:$G$790,$A43,'Transaction Overview'!$D$2:$D$790,">0") -> 35000 | C43: =SUMIFS('Transaction Overview'!$D$2:$D$790,'Transaction Overview'!$G$2:$G$790,$A43,'Transaction Overview'!$D$2:$D$790,"<0") -> 0 | D43: =B43+C43 -> 35000
A44: MAG - Admeer Advisory Transfer | B44: =SUMIFS('Transaction Overview'!$D$2:$D$790,'Transaction Overview'!$G$2:$G$790,$A44,'Transaction Overview'!$D$2:$D$790,">0") -> 0 | C44: =SUMIFS('Transaction Overview'!$D$2:$D$790,'Transaction Overview'!$G$2:$G$790,$A44,'Transaction Overview'!$D$2:$D$790,"<0") -> -42450 | D44: =B44+C44 -> -42450
A45: MAG Capital Partners Pass-Through Wire – 70/30 Split | B45: =SUMIFS('Transaction Overview'!$D$2:$D$790,'Transaction Overview'!$G$2:$G$790,$A45,'Transaction Overview'!$D$2:$D$790,">0") -> 75000 | C45: =SUMIFS('Transaction Overview'!$D$2:$D$790,'Transaction Overview'!$G$2:$G$790,$A45,'Transaction Overview'!$D$2:$D$790,"<0") -> 0 | D45: =B45+C45 -> 75000
A46: MAG Marketing Reimbursement | B46: =SUMIFS('Transaction Overview'!$D$2:$D$790,'Transaction Overview'!$G$2:$G$790,$A46,'Transaction Overview'!$D$2:$D$790,">0") -> 15000 | C46: =SUMIFS('Transaction Overview'!$D$2:$D$790,'Transaction Overview'!$G$2:$G$790,$A46,'Transaction Overview'!$D$2:$D$790,"<0") -> 0 | D46: =B46+C46 -> 15000
A47: Subtotal — MAG Pass-Through | B47: =SUMIFS('Transaction Overview'!$D$2:$D$790,'Transaction Overview'!$J$2:$J$790,"MAG Pass-Through",'Transaction Overview'!$D$2:$D$790,">0") -> 125000 | C47: =SUMIFS('Transaction Overview'!$D$2:$D$790,'Transaction Overview'!$J$2:$J$790,"MAG Pass-Through",'Transaction Overview'!$D$2:$D$790,"<0") -> -102450 | D47: =B47+C47 -> 22550
A49: Wire Transfers — Incoming
A50: Incoming Crystal Asset Management Wire | B50: =SUMIFS('Transaction Overview'!$D$2:$D$790,'Transaction Overview'!$G$2:$G$790,$A50,'Transaction Overview'!$D$2:$D$790,">0") -> 100000 | C50: =SUMIFS('Transaction Overview'!$D$2:$D$790,'Transaction Overview'!$G$2:$G$790,$A50,'Transaction Overview'!$D$2:$D$790,"<0") -> 0 | D50: =B50+C50 -> 100000
A51: Incoming wire from JC Whitner | B51: =SUMIFS('Transaction Overview'!$D$2:$D$790,'Transaction Overview'!$G$2:$G$790,$A51,'Transaction Overview'!$D$2:$D$790,">0") -> 20000 | C51: =SUMIFS('Transaction Overview'!$D$2:$D$790,'Transaction Overview'!$G$2:$G$790,$A51,'Transaction Overview'!$D$2:$D$790,"<0") -> 0 | D51: =B51+C51 -> 20000
A52: Subtotal — Wire Transfers — Incoming | B52: =SUMIFS('Transaction Overview'!$D$2:$D$790,'Transaction Overview'!$J$2:$J$790,"Wire Transfers — Incoming",'Transaction Overview'!$D$2:$D$790,">0") -> 120000 | C52: =SUMIFS('Transaction Overview'!$D$2:$D$790,'Transaction Overview'!$J$2:$J$790,"Wire Transfers — Incoming",'Transaction Overview'!$D$2:$D$790,"<0") -> 0 | D52: =B52+C52 -> 120000
A54: Wire Transfers — Outgoing
A55: Outgoing Crystal Asset Management Wire | B55: =SUMIFS('Transaction Overview'!$D$2:$D$790,'Transaction Overview'!$G$2:$G$790,$A55,'Transaction Overview'!$D$2:$D$790,">0") -> 0 | C55: =SUMIFS('Transaction Overview'!$D$2:$D$790,'Transaction Overview'!$G$2:$G$790,$A55,'Transaction Overview'!$D$2:$D$790,"<0") -> -100000 | D55: =B55+C55 -> -100000
A56: Outgoing wire to JC Whitner | B56: =SUMIFS('Transaction Overview'!$D$2:$D$790,'Transaction Overview'!$G$2:$G$790,$A56,'Transaction Overview'!$D$2:$D$790,">0") -> 0 | C56: =SUMIFS('Transaction Overview'!$D$2:$D$790,'Transaction Overview'!$G$2:$G$790,$A56,'Transaction Overview'!$D$2:$D$790,"<0") -> -35000 | D56: =B56+C56 -> -35000
A57: Wire to Binder Family Trust - TBD | B57: =SUMIFS('Transaction Overview'!$D$2:$D$790,'Transaction Overview'!$G$2:$G$790,$A57,'Transaction Overview'!$D$2:$D$790,">0") -> 0 | C57: =SUMIFS('Transaction Overview'!$D$2:$D$790,'Transaction Overview'!$G$2:$G$790,$A57,'Transaction Overview'!$D$2:$D$790,"<0") -> -6000 | D57: =B57+C57 -> -6000
A58: Wire to Top Shield Roofing CO | B58: =SUMIFS('Transaction Overview'!$D$2:$D$790,'Transaction Overview'!$G$2:$G$790,$A58,'Transaction Overview'!$D$2:$D$790,">0") -> 0 | C58: =SUMIFS('Transaction Overview'!$D$2:$D$790,'Transaction Overview'!$G$2:$G$790,$A58,'Transaction Overview'!$D$2:$D$790,"<0") -> -15500 | D58: =B58+C58 -> -15500
A59: Subtotal — Wire Transfers — Outgoing | B59: =SUMIFS('Transaction Overview'!$D$2:$D$790,'Transaction Overview'!$J$2:$J$790,"Wire Transfers — Outgoing",'Transaction Overview'!$D$2:$D$790,">0") -> 0 | C59: =SUMIFS('Transaction Overview'!$D$2:$D$790,'Transaction Overview'!$J$2:$J$790,"Wire Transfers — Outgoing",'Transaction Overview'!$D$2:$D$790,"<0") -> -156500 | D59: =B59+C59 -> -156500
A61: Intercompany & Savings Transfers
A62: Transfer from Breese | B62: =SUMIFS('Transaction Overview'!$D$2:$D$790,'Transaction Overview'!$G$2:$G$790,$A62,'Transaction Overview'!$D$2:$D$790,">0") -> 150000 | C62: =SUMIFS('Transaction Overview'!$D$2:$D$790,'Transaction Overview'!$G$2:$G$790,$A62,'Transaction Overview'!$D$2:$D$790,"<0") -> 0 | D62: =B62+C62 -> 150000
A63: Transfer from DWG Capital Partners | B63: =SUMIFS('Transaction Overview'!$D$2:$D$790,'Transaction Overview'!$G$2:$G$790,$A63,'Transaction Overview'!$D$2:$D$790,">0") -> 383350 | C63: =SUMIFS('Transaction Overview'!$D$2:$D$790,'Transaction Overview'!$G$2:$G$790,$A63,'Transaction Overview'!$D$2:$D$790,"<0") -> 0 | D63: =B63+C63 -> 383350
A64: Transfer from Hibbert | B64: =SUMIFS('Transaction Overview'!$D$2:$D$790,'Transaction Overview'!$G$2:$G$790,$A64,'Transaction Overview'!$D$2:$D$790,">0") -> 117500 | C64: =SUMIFS('Transaction Overview'!$D$2:$D$790,'Transaction Overview'!$G$2:$G$790,$A64,'Transaction Overview'!$D$2:$D$790,"<0") -> 0 | D64: =B64+C64 -> 117500
A65: Transfer from Kalkaska Screw | B65: =SUMIFS('Transaction Overview'!$D$2:$D$790,'Transaction Overview'!$G$2:$G$790,$A65,'Transaction Overview'!$D$2:$D$790,">0") -> 62800 | C65: =SUMIFS('Transaction Overview'!$D$2:$D$790,'Transaction Overview'!$G$2:$G$790,$A65,'Transaction Overview'!$D$2:$D$790,"<0") -> 0 | D65: =B65+C65 -> 62800
A66: Transfer to DWG Capital Group | B66: =SUMIFS('Transaction Overview'!$D$2:$D$790,'Transaction Overview'!$G$2:$G$790,$A66,'Transaction Overview'!$D$2:$D$790,">0") -> 0 | C66: =SUMIFS('Transaction Overview'!$D$2:$D$790,'Transaction Overview'!$G$2:$G$790,$A66,'Transaction Overview'!$D$2:$D$790,"<0") -> -678000 | D66: =B66+C66 -> -678000
A67: Transfer to DWG Capital Group_Costar | B67: =SUMIFS('Transaction Overview'!$D$2:$D$790,'Transaction Overview'!$G$2:$G$790,$A67,'Transaction Overview'!$D$2:$D$790,">0") -> 0 | C67: =SUMIFS('Transaction Overview'!$D$2:$D$790,'Transaction Overview'!$G$2:$G$790,$A67,'Transaction Overview'!$D$2:$D$790,"<0") -> -6450 | D67: =B67+C67 -> -6450
A68: Transfer to DWG Capital Partners | B68: =SUMIFS('Transaction Overview'!$D$2:$D$790,'Transaction Overview'!$G$2:$G$790,$A68,'Transaction Overview'!$D$2:$D$790,">0") -> 0 | C68: =SUMIFS('Transaction Overview'!$D$2:$D$790,'Transaction Overview'!$G$2:$G$790,$A68,'Transaction Overview'!$D$2:$D$790,"<0") -> -271500 | D68: =B68+C68 -> -271500
A69: Transfer to Edgebuilders | B69: =SUMIFS('Transaction Overview'!$D$2:$D$790,'Transaction Overview'!$G$2:$G$790,$A69,'Transaction Overview'!$D$2:$D$790,">0") -> 0 | C69: =SUMIFS('Transaction Overview'!$D$2:$D$790,'Transaction Overview'!$G$2:$G$790,$A69,'Transaction Overview'!$D$2:$D$790,"<0") -> -50000 | D69: =B69+C69 -> -50000
A70: Transfer to Hibbert | B70: =SUMIFS('Transaction Overview'!$D$2:$D$790,'Transaction Overview'!$G$2:$G$790,$A70,'Transaction Overview'!$D$2:$D$790,">0") -> 0 | C70: =SUMIFS('Transaction Overview'!$D$2:$D$790,'Transaction Overview'!$G$2:$G$790,$A70,'Transaction Overview'!$D$2:$D$790,"<0") -> -50918.73 | D70: =B70+C70 -> -50918.73
A71: Transfer to JAL Southbend | B71: =SUMIFS('Transaction Overview'!$D$2:$D$790,'Transaction Overview'!$G$2:$G$790,$A71,'Transaction Overview'!$D$2:$D$790,">0") -> 0 | C71: =SUMIFS('Transaction Overview'!$D$2:$D$790,'Transaction Overview'!$G$2:$G$790,$A71,'Transaction Overview'!$D$2:$D$790,"<0") -> -57349 | D71: =B71+C71 -> -57349
A72: Transfer to Kalkaska Screw | B72: =SUMIFS('Transaction Overview'!$D$2:$D$790,'Transaction Overview'!$G$2:$G$790,$A72,'Transaction Overview'!$D$2:$D$790,">0") -> 0 | C72: =SUMIFS('Transaction Overview'!$D$2:$D$790,'Transaction Overview'!$G$2:$G$790,$A72,'Transaction Overview'!$D$2:$D$790,"<0") -> -12800 | D72: =B72+C72 -> -12800
A73: Transfer to Kecy Metals | B73: =SUMIFS('Transaction Overview'!$D$2:$D$790,'Transaction Overview'!$G$2:$G$790,$A73,'Transaction Overview'!$D$2:$D$790,">0") -> 0 | C73: =SUMIFS('Transaction Overview'!$D$2:$D$790,'Transaction Overview'!$G$2:$G$790,$A73,'Transaction Overview'!$D$2:$D$790,"<0") -> -17000 | D73: =B73+C73 -> -17000
... A75: Transfer to T&T Machine | B75: =SUMIFS('Transaction Overview'!$D$2:$D$790,'Transaction Overview'!$G$2:$G$790,$A75,'Transaction Overview'!$D$2:$D$790,">0") -> 0 | C75: =SUMIFS('Transaction Overview'!$D$2:$D$790,'Transaction Overview'!$G$2:$G$790,$A75,'Transaction Overview'!$D$2:$D$790,"<0") -> -20000 | D75: =B75+C75 -> -20000
A76: Subtotal — Intercompany & Savings Transfers | B76: =SUMIFS('Transaction Overview'!$D$2:$D$790,'Transaction Overview'!$J$2:$J$790,"Intercompany & Savings Transfers",'Transaction Overview'!$D$2:$D$790,">0") -> 738650 | C76: =SUMIFS('Transaction Overview'!$D$2:$D$790,'Transaction Overview'!$J$2:$J$790,"Intercompany & Savings Transfers",'Transaction Overview'!$D$2:$D$790,"<0") -> -1164017.7 | D76: =B76+C76 -> -425367.73
A78: Owner / Family Distributions
A79: Transfer to Angela Dunning | B79: =SUMIFS('Transaction Overview'!$D$2:$D$790,'Transaction Overview'!$G$2:$G$790,$A79,'Transaction Overview'!$D$2:$D$790,">0") -> 0 | C79: =SUMIFS('Transaction Overview'!$D$2:$D$790,'Transaction Overview'!$G$2:$G$790,$A79,'Transaction Overview'!$D$2:$D$790,"<0") -> -1000 | D79: =B79+C79 -> -1000
A80: Transfer to Ava | B80: =SUMIFS('Transaction Overview'!$D$2:$D$790,'Transaction Overview'!$G$2:$G$790,$A80,'Transaction Overview'!$D$2:$D$790,">0") -> 0 | C80: =SUMIFS('Transaction Overview'!$D$2:$D$790,'Transaction Overview'!$G$2:$G$790,$A80,'Transaction Overview'!$D$2:$D$790,"<0") -> -500 | D80: =B80+C80 -> -500
A81: Subtotal — Owner / Family Distributions | B81: =SUMIFS('Transaction Overview'!$D$2:$D$790,'Transaction Overview'!$J$2:$J$790,"Owner / Family Distributions",'Transaction Overview'!$D$2:$D$790,">0") -> 0 | C81: =SUMIFS('Transaction Overview'!$D$2:$D$790,'Transaction Overview'!$J$2:$J$790,"Owner / Family Distributions",'Transaction Overview'!$D$2:$D$790,"<0") -> -1500 | D81: =B81+C81 -> -1500
A83: P2P Payments (Zelle/Venmo/PayPal)
A84: Apple Payment | B84: =SUMIFS('Transaction Overview'!$D$2:$D$790,'Transaction Overview'!$G$2:$G$790,$A84,'Transaction Overview'!$D$2:$D$790,">0") -> 0 | C84: =SUMIFS('Transaction Overview'!$D$2:$D$790,'Transaction Overview'!$G$2:$G$790,$A84,'Transaction Overview'!$D$2:$D$790,"<0") -> -331 | D84: =B84+C84 -> -331
A85: Zelle to Ashley Sarshar | B85: =SUMIFS('Transaction Overview'!$D$2:$D$790,'Transaction Overview'!$G$2:$G$790,$A85,'Transaction Overview'!$D$2:$D$790,">0") -> 0 | C85: =SUMIFS('Transaction Overview'!$D$2:$D$790,'Transaction Overview'!$G$2:$G$790,$A85,'Transaction Overview'!$D$2:$D$790,"<0") -> -247 | D85: =B85+C85 -> -247
A86: Zelle to David Goldsmith | B86: =SUMIFS('Transaction Overview'!$D$2:$D$790,'Transaction Overview'!$G$2:$G$790,$A86,'Transaction Overview'!$D$2:$D$790,">0") -> 0 | C86: =SUMIFS('Transaction Overview'!$D$2:$D$790,'Transaction Overview'!$G$2:$G$790,$A86,'Transaction Overview'!$D$2:$D$790,"<0") -> -500 | D86: =B86+C86 -> -500
A87: Zelle to Mark Atkins | B87: =SUMIFS('Transaction Overview'!$D$2:$D$790,'Transaction Overview'!$G$2:$G$790,$A87,'Transaction Overview'!$D$2:$D$790,">0") -> 0 | C87: =SUMIFS('Transaction Overview'!$D$2:$D$790,'Transaction Overview'!$G$2:$G$790,$A87,'Transaction Overview'!$D$2:$D$790,"<0") -> -500 | D87: =B87+C87 -> -500
A88: Zelle to Menashe | B88: =SUMIFS('Transaction Overview'!$D$2:$D$790,'Transaction Overview'!$G$2:$G$790,$A88,'Transaction Overview'!$D$2:$D$790,">0") -> 0 | C88: =SUMIFS('Transaction Overview'!$D$2:$D$790,'Transaction Overview'!$G$2:$G$790,$A88,'Transaction Overview'!$D$2:$D$790,"<0") -> -750 | D88: =B88+C88 -> -750
A89: Zelle to Rami Frankl | B89: =SUMIFS('Transaction Overview'!$D$2:$D$790,'Transaction Overview'!$G$2:$G$790,$A89,'Transaction Overview'!$D$2:$D$790,">0") -> 0 | C89: =SUMIFS('Transaction Overview'!$D$2:$D$790,'Transaction Overview'!$G$2:$G$790,$A89,'Transaction Overview'!$D$2:$D$790,"<0") -> -500 | D89: =B89+C89 -> -500
A90: Zelle to Sentha | B90: =SUMIFS('Transaction Overview'!$D$2:$D$790,'Transaction Overview'!$G$2:$G$790,$A90,'Transaction Overview'!$D$2:$D$790,">0") -> 0 | C90: =SUMIFS('Transaction Overview'!$D$2:$D$790,'Transaction Overview'!$G$2:$G$790,$A90,'Transaction Overview'!$D$2:$D$790,"<0") -> -350 | D90: =B90+C90 -> -350
A91: Subtotal — P2P Payments (Zelle/Venmo/PayPal) | B91: =SUMIFS('Transaction Overview'!$D$2:$D$790,'Transaction Overview'!$J$2:$J$790,"P2P Payments (Zelle/Venmo/PayPal)",'Transaction Overview'!$D$2:$D$790,">0") -> 0 | C91: =SUMIFS('Transaction Overview'!$D$2:$D$790,'Transaction Overview'!$J$2:$J$790,"P2P Payments (Zelle/Venmo/PayPal)",'Transaction Overview'!$D$2:$D$790,"<0") -> -3178 | D91: =B91+C91 -> -3178
A93: Payroll & Contractors
A94: Ben Mandel - Payroll | B94: =SUMIFS('Transaction Overview'!$D$2:$D$790,'Transaction Overview'!$G$2:$G$790,$A94,'Transaction Overview'!$D$2:$D$790,">0") -> 0 | C94: =SUMIFS('Transaction Overview'!$D$2:$D$790,'Transaction Overview'!$G$2:$G$790,$A94,'Transaction Overview'!$D$2:$D$790,"<0") -> -10000 | D94: =B94+C94 -> -10000
A95: Employee Bonus | B95: =SUMIFS('Transaction Overview'!$D$2:$D$790,'Transaction Overview'!$G$2:$G$790,$A95,'Transaction Overview'!$D$2:$D$790,">0") -> 0 | C95: =SUMIFS('Transaction Overview'!$D$2:$D$790,'Transaction Overview'!$G$2:$G$790,$A95,'Transaction Overview'!$D$2:$D$790,"<0") -> -28000 | D95: =B95+C95 -> -28000
A96: Office/Miscellaneous Reimbursement - Mike P. | B96: =SUMIFS('Transaction Overview'!$D$2:$D$790,'Transaction Overview'!$G$2:$G$790,$A96,'Transaction Overview'!$D$2:$D$790,">0") -> 0 | C96: =SUMIFS('Transaction Overview'!$D$2:$D$790,'Transaction Overview'!$G$2:$G$790,$A96,'Transaction Overview'!$D$2:$D$790,"<0") -> -872 | D96: =B96+C96 -> -872
A97: Subtotal — Payroll & Contractors | B97: =SUMIFS('Transaction Overview'!$D$2:$D$790,'Transaction Overview'!$J$2:$J$790,"Payroll & Contractors",'Transaction Overview'!$D$2:$D$790,">0") -> 0 | C97: =SUMIFS('Transaction Overview'!$D$2:$D$790,'Transaction Overview'!$J$2:$J$790,"Payroll & Contractors",'Transaction Overview'!$D$2:$D$790,"<0") -> -38872 | D97: =B97+C97 -> -38872
A99: Credit Card & Loan Payments
A100: American Express Credit Card PMT | B100: =SUMIFS('Transaction Overview'!$D$2:$D$790,'Transaction Overview'!$G$2:$G$790,$A100,'Transaction Overview'!$D$2:$D$790,">0") -> 0 | C100: =SUMIFS('Transaction Overview'!$D$2:$D$790,'Transaction Overview'!$G$2:$G$790,$A100,'Transaction Overview'!$D$2:$D$790,"<0") -> -231476.49 | D100: =B100+C100 -> -231476.49
A101: Subtotal — Credit Card & Loan Payments | B101: =SUMIFS('Transaction Overview'!$D$2:$D$790,'Transaction Overview'!$J$2:$J$790,"Credit Card & Loan Payments",'Transaction Overview'!$D$2:$D$790,">0") -> 0 | C101: =SUMIFS('Transaction Overview'!$D$2:$D$790,'Transaction Overview'!$J$2:$J$790,"Credit Card & Loan Payments",'Transaction Overview'!$D$2:$D$790,"<0") -> -231476.49 | D101: =B101+C101 -> -231476.49
A103: Personal — Owner
A104: AI Subscriptions | B104: =SUMIFS('Transaction Overview'!$D$2:$D$790,'Transaction Overview'!$G$2:$G$790,$A104,'Transaction Overview'!$D$2:$D$790,">0") -> 0 | C104: =SUMIFS('Transaction Overview'!$D$2:$D$790,'Transaction Overview'!$G$2:$G$790,$A104,'Transaction Overview'!$D$2:$D$790,"<0") -> -216 | D104: =B104+C104 -> -216
A105: Amazon | B105: =SUMIFS('Transaction Overview'!$D$2:$D$790,'Transaction Overview'!$G$2:$G$790,$A105,'Transaction Overview'!$D$2:$D$790,">0") -> 352.47 | C105: =SUMIFS('Transaction Overview'!$D$2:$D$790,'Transaction Overview'!$G$2:$G$790,$A105,'Transaction Overview'!$D$2:$D$790,"<0") -> -8378.59 | D105: =B105+C105 -> -8026.12
A106: Amazon Prime Video | B106: =SUMIFS('Transaction Overview'!$D$2:$D$790,'Transaction Overview'!$G$2:$G$790,$A106,'Transaction Overview'!$D$2:$D$790,">0") -> 0 | C106: =SUMIFS('Transaction Overview'!$D$2:$D$790,'Transaction Overview'!$G$2:$G$790,$A106,'Transaction Overview'!$D$2:$D$790,"<0") -> -642.16 | D106: =B106+C106 -> -642.16
A107: Personal - Car | B107: =SUMIFS('Transaction Overview'!$D$2:$D$790,'Transaction Overview'!$G$2:$G$790,$A107,'Transaction Overview'!$D$2:$D$790,">0") -> 0 | C107: =SUMIFS('Transaction Overview'!$D$2:$D$790,'Transaction Overview'!$G$2:$G$790,$A107,'Transaction Overview'!$D$2:$D$790,"<0") -> -114.12 | D107: =B107+C107 -> -114.12
A108: Personal - Clothing | B108: =SUMIFS('Transaction Overview'!$D$2:$D$790,'Transaction Overview'!$G$2:$G$790,$A108,'Transaction Overview'!$D$2:$D$790,">0") -> 0 | C108: =SUMIFS('Transaction Overview'!$D$2:$D$790,'Transaction Overview'!$G$2:$G$790,$A108,'Transaction Overview'!$D$2:$D$790,"<0") -> -328.19 | D108: =B108+C108 -> -328.19
A109: Personal - Donation | B109: =SUMIFS('Transaction Overview'!$D$2:$D$790,'Transaction Overview'!$G$2:$G$790,$A109,'Transaction Overview'!$D$2:$D$790,">0") -> 0 | C109: =SUMIFS('Transaction Overview'!$D$2:$D$790,'Transaction Overview'!$G$2:$G$790,$A109,'Transaction Overview'!$D$2:$D$790,"<0") -> -28 | D109: =B109+C109 -> -28
A110: Personal - Entertainment | B110: =SUMIFS('Transaction Overview'!$D$2:$D$790,'Transaction Overview'!$G$2:$G$790,$A110,'Transaction Overview'!$D$2:$D$790,">0") -> 0 | C110: =SUMIFS('Transaction Overview'!$D$2:$D$790,'Transaction Overview'!$G$2:$G$790,$A110,'Transaction Overview'!$D$2:$D$790,"<0") -> -187.64 | D110: =B110+C110 -> -187.64
A111: Personal - Food & Dining | B111: =SUMIFS('Transaction Overview'!$D$2:$D$790,'Transaction Overview'!$G$2:$G$790,$A111,'Transaction Overview'!$D$2:$D$790,">0") -> 0 | C111: =SUMIFS('Transaction Overview'!$D$2:$D$790,'Transaction Overview'!$G$2:$G$790,$A111,'Transaction Overview'!$D$2:$D$790,"<0") -> -645.37 | D111: =B111+C111 -> -645.37
A112: Personal - Gift (Dax Mitchell) | B112: =SUMIFS('Transaction Overview'!$D$2:$D$790,'Transaction Overview'!$G$2:$G$790,$A112,'Transaction Overview'!$D$2:$D$790,">0") -> 0 | C112: =SUMIFS('Transaction Overview'!$D$2:$D$790,'Transaction Overview'!$G$2:$G$790,$A112,'Transaction Overview'!$D$2:$D$790,"<0") -> -1035.46 | D112: =B112+C112 -> -1035.46
A113: Personal - Health (incl. Ins.) | B113: =SUMIFS('Transaction Overview'!$D$2:$D$790,'Transaction Overview'!$G$2:$G$790,$A113,'Transaction Overview'!$D$2:$D$790,">0") -> 0 | C113: =SUMIFS('Transaction Overview'!$D$2:$D$790,'Transaction Overview'!$G$2:$G$790,$A113,'Transaction Overview'!$D$2:$D$790,"<0") -> -391.54 | D113: =B113+C113 -> -391.54
A114: Personal - Shopping | B114: =SUMIFS('Transaction Overview'!$D$2:$D$790,'Transaction Overview'!$G$2:$G$790,$A114,'Transaction Overview'!$D$2:$D$790,">0") -> 0 | C114: =SUMIFS('Transaction Overview'!$D$2:$D$790,'Transaction Overview'!$G$2:$G$790,$A114,'Transaction Overview'!$D$2:$D$790,"<0") -> -705.44 | D114: =B114+C114 -> -705.44
A115: Personal - Subscriptions | B115: =SUMIFS('Transaction Overview'!$D$2:$D$790,'Transaction Overview'!$G$2:$G$790,$A115,'Transaction Overview'!$D$2:$D$790,">0") -> 0 | C115: =SUMIFS('Transaction Overview'!$D$2:$D$790,'Transaction Overview'!$G$2:$G$790,$A115,'Transaction Overview'!$D$2:$D$790,"<0") -> -3178.75 | D115: =B115+C115 -> -3178.75
... A120: Personal - Travel (Italy) | B120: =SUMIFS('Transaction Overview'!$D$2:$D$790,'Transaction Overview'!$G$2:$G$790,$A120,'Transaction Overview'!$D$2:$D$790,">0") -> 0 | C120: =SUMIFS('Transaction Overview'!$D$2:$D$790,'Transaction Overview'!$G$2:$G$790,$A120,'Transaction Overview'!$D$2:$D$790,"<0") -> -767.08 | D120: =B120+C120 -> -767.08
...

Sheet Commission
A1: Chase 9335 — 2025 Activity
A2: Commissions Statement | Jan 2025 – Dec 2025
A4: SUMMARY
A5: Commissions Earned (net) | C5: =SUMIFS('Transaction Overview'!$D$2:$D$790,'Transaction Overview'!$J$2:$J$790,"Commissions — Incoming") -> 1033938.6
A6: Commissions Paid Out | C6: =SUMIFS('Transaction Overview'!$D$2:$D$790,'Transaction Overview'!$J$2:$J$790,"Commissions — Outgoing") -> -71650
A7: Net Commission Kept | C7: =C5+C6 -> 962288.62

Sheet Monthly Breakdown
A1: Chase 9335 — 2025 Activity
A2: Monthly Breakdown | Net by Category | Jan 2025 – Dec 2025
A4: Category | B4: =DATE(2025,1,1) -> 45658 | C4: =DATE(2025,2,1) -> 45689 | D4: =DATE(2025,3,1) -> 45717 | E4: =DATE(2025,4,1) -> 45748 | F4: =DATE(2025,5,1) -> 45778 | G4: =DATE(2025,6,1) -> 45809 | H4: =DATE(2025,7,1) -> 45839 | I4: =DATE(2025,8,1) -> 45870 | J4: =DATE(2025,9,1) -> 45901 | K4: =DATE(2025,10,1) -> 45931 | L4: =DATE(2025,11,1) -> 45962 | M4: =DATE(2025,12,1) -> 45992 | N4: Total
A5: Deal-Specific
A6: Deal Specific: Austin Iron | B6: =SUMIFS('Transaction Overview'!$D$2:$D$790,'Transaction Overview'!$I$2:$I$790,$A6,'Transaction Overview'!$H$2:$H$790,B$4) -> 350 | C6: =SUMIFS('Transaction Overview'!$D$2:$D$790,'Transaction Overview'!$I$2:$I$790,$A6,'Transaction Overview'!$H$2:$H$790,C$4) -> 350 | D6: =SUMIFS('Transaction Overview'!$D$2:$D$790,'Transaction Overview'!$I$2:$I$790,$A6,'Transaction Overview'!$H$2:$H$790,D$4) -> 350 | E6: =SUMIFS('Transaction Overview'!$D$2:$D$790,'Transaction Overview'!$I$2:$I$790,$A6,'Transaction Overview'!$H$2:$H$790,E$4) -> 350 | F6: =SUMIFS('Transaction Overview'!$D$2:$D$790,'Transaction Overview'!$I$2:$I$790,$A6,'Transaction Overview'!$H$2:$H$790,F$4) -> 350 | G6: =SUMIFS('Transaction Overview'!$D$2:$D$790,'Transaction Overview'!$I$2:$I$790,$A6,'Transaction Overview'!$H$2:$H$790,G$4) -> 350 | H6: =SUMIFS('Transaction Overview'!$D$2:$D$790,'Transaction Overview'!$I$2:$I$790,$A6,'Transaction Overview'!$H$2:$H$790,H$4) -> 350 | I6: =SUMIFS('Transaction Overview'!$D$2:$D$790,'Transaction Overview'!$I$2:$I$790,$A6,'Transaction Overview'!$H$2:$H$790,I$4) -> 350 | ... M6: =SUMIFS('Transaction Overview'!$D$2:$D$790,'Transaction Overview'!$I$2:$I$790,$A6,'Transaction Overview'!$H$2:$H$790,M$4) -> 350 | N6: =SUM(B6:M6) -> 4200
A7: Deal Specific: Cloverdale | B7: =SUMIFS('Transaction Overview'!$D$2:$D$790,'Transaction Overview'!$I$2:$I$790,$A7,'Transaction Overview'!$H$2:$H$790,B$4) -> 0 | C7: =SUMIFS('Transaction Overview'!$D$2:$D$790,'Transaction Overview'!$I$2:$I$790,$A7,'Transaction Overview'!$H$2:$H$790,C$4) -> 0 | D7: =SUMIFS('Transaction Overview'!$D$2:$D$790,'Transaction Overview'!$I$2:$I$790,$A7,'Transaction Overview'!$H$2:$H$790,D$4) -> 0 | E7: =SUMIFS('Transaction Overview'!$D$2:$D$790,'Transaction Overview'!$I$2:$I$790,$A7,'Transaction Overview'!$H$2:$H$790,E$4) -> 0 | F7: =SUMIFS('Transaction Overview'!$D$2:$D$790,'Transaction Overview'!$I$2:$I$790,$A7,'Transaction Overview'!$H$2:$H$790,F$4) -> 0 | G7: =SUMIFS('Transaction Overview'!$D$2:$D$790,'Transaction Overview'!$I$2:$I$790,$A7,'Transaction Overview'!$H$2:$H$790,G$4) -> 0 | H7: =SUMIFS('Transaction Overview'!$D$2:$D$790,'Transaction Overview'!$I$2:$I$790,$A7,'Transaction Overview'!$H$2:$H$790,H$4) -> 0 | I7: =SUMIFS('Transaction Overview'!$D$2:$D$790,'Transaction Overview'!$I$2:$I$790,$A7,'Transaction Overview'!$H$2:$H$790,I$4) -> 0 | ... M7: =SUMIFS('Transaction Overview'!$D$2:$D$790,'Transaction Overview'!$I$2:$I$790,$A7,'Transaction Overview'!$H$2:$H$790,M$4) -> -155000 | N7: =SUM(B7:M7) -> -155000
A8: Deal Specific: Hibbert | B8: =SUMIFS('Transaction Overview'!$D$2:$D$790,'Transaction Overview'!$I$2:$I$790,$A8,'Transaction Overview'!$H$2:$H$790,B$4) -> 0 | C8: =SUMIFS('Transaction Overview'!$D$2:$D$790,'Transaction Overview'!$I$2:$I$790,$A8,'Transaction Overview'!$H$2:$H$790,C$4) -> 0 | D8: =SUMIFS('Transaction Overview'!$D$2:$D$790,'Transaction Overview'!$I$2:$I$790,$A8,'Transaction Overview'!$H$2:$H$790,D$4) -> 0 | E8: =SUMIFS('Transaction Overview'!$D$2:$D$790,'Transaction Overview'!$I$2:$I$790,$A8,'Transaction Overview'!$H$2:$H$790,E$4) -> 0 | F8: =SUMIFS('Transaction Overview'!$D$2:$D$790,'Transaction Overview'!$I$2:$I$790,$A8,'Transaction Overview'!$H$2:$H$790,F$4) -> 0 | G8: =SUMIFS('Transaction Overview'!$D$2:$D$790,'Transaction Overview'!$I$2:$I$790,$A8,'Transaction Overview'!$H$2:$H$790,G$4) -> 0 | H8: =SUMIFS('Transaction Overview'!$D$2:$D$790,'Transaction Overview'!$I$2:$I$790,$A8,'Transaction Overview'!$H$2:$H$790,H$4) -> 0 | I8: =SUMIFS('Transaction Overview'!$D$2:$D$790,'Transaction Overview'!$I$2:$I$790,$A8,'Transaction Overview'!$H$2:$H$790,I$4) -> 0 | ... M8: =SUMIFS('Transaction Overview'!$D$2:$D$790,'Transaction Overview'!$I$2:$I$790,$A8,'Transaction Overview'!$H$2:$H$790,M$4) -> 0 | N8: =SUM(B8:M8) -> -46528.05
A9: Deal Specific: JAL Breese | B9: =SUMIFS('Transaction Overview'!$D$2:$D$790,'Transaction Overview'!$I$2:$I$790,$A9,'Transaction Overview'!$H$2:$H$790,B$4) -> 0 | C9: =SUMIFS('Transaction Overview'!$D$2:$D$790,'Transaction Overview'!$I$2:$I$790,$A9,'Transaction Overview'!$H$2:$H$790,C$4) -> 0 | D9: =SUMIFS('Transaction Overview'!$D$2:$D$790,'Transaction Overview'!$I$2:$I$790,$A9,'Transaction Overview'!$H$2:$H$790,D$4) -> 0 | E9: =SUMIFS('Transaction Overview'!$D$2:$D$790,'Transaction Overview'!$I$2:$I$790,$A9,'Transaction Overview'!$H$2:$H$790,E$4) -> -50000 | F9: =SUMIFS('Transaction Overview'!$D$2:$D$790,'Transaction Overview'!$I$2:$I$790,$A9,'Transaction Overview'!$H$2:$H$790,F$4) -> 0 | G9: =SUMIFS('Transaction Overview'!$D$2:$D$790,'Transaction Overview'!$I$2:$I$790,$A9,'Transaction Overview'!$H$2:$H$790,G$4) -> 0 | H9: =SUMIFS('Transaction Overview'!$D$2:$D$790,'Transaction Overview'!$I$2:$I$790,$A9,'Transaction Overview'!$H$2:$H$790,H$4) -> 0 | I9: =SUMIFS('Transaction Overview'!$D$2:$D$790,'Transaction Overview'!$I$2:$I$790,$A9,'Transaction Overview'!$H$2:$H$790,I$4) -> 0 | ... M9: =SUMIFS('Transaction Overview'!$D$2:$D$790,'Transaction Overview'!$I$2:$I$790,$A9,'Transaction Overview'!$H$2:$H$790,M$4) -> 0 | N9: =SUM(B9:M9) -> -50000
A10: Deal Specific: Merit-Lancaster | B10: =SUMIFS('Transaction Overview'!$D$2:$D$790,'Transaction Overview'!$I$2:$I$790,$A10,'Transaction Overview'!$H$2:$H$790,B$4) -> 461.52 | C10: =SUMIFS('Transaction Overview'!$D$2:$D$790,'Transaction Overview'!$I$2:$I$790,$A10,'Transaction Overview'!$H$2:$H$790,C$4) -> 461.52 | D10: =SUMIFS('Transaction Overview'!$D$2:$D$790,'Transaction Overview'!$I$2:$I$790,$A10,'Transaction Overview'!$H$2:$H$790,D$4) -> 476.41 | E10: =SUMIFS('Transaction Overview'!$D$2:$D$790,'Transaction Overview'!$I$2:$I$790,$A10,'Transaction Overview'!$H$2:$H$790,E$4) -> 476.41 | F10: =SUMIFS('Transaction Overview'!$D$2:$D$790,'Transaction Overview'!$I$2:$I$790,$A10,'Transaction Overview'!$H$2:$H$790,F$4) -> 476.41 | G10: =SUMIFS('Transaction Overview'!$D$2:$D$790,'Transaction Overview'!$I$2:$I$790,$A10,'Transaction Overview'!$H$2:$H$790,G$4) -> 476.41 | H10: =SUMIFS('Transaction Overview'!$D$2:$D$790,'Transaction Overview'!$I$2:$I$790,$A10,'Transaction Overview'!$H$2:$H$790,H$4) -> 476.41 | I10: =SUMIFS('Transaction Overview'!$D$2:$D$790,'Transaction Overview'!$I$2:$I$790,$A10,'Transaction Overview'!$H$2:$H$790,I$4) -> 476.41 | ... M10: =SUMIFS('Transaction Overview'!$D$2:$D$790,'Transaction Overview'!$I$2:$I$790,$A10,'Transaction Overview'!$H$2:$H$790,M$4) -> 476.41 | N10: =SUM(B10:M10) -> 5687.14
A11: Deal Specific: Moab | B11: =SUMIFS('Transaction Overview'!$D$2:$D$790,'Transaction Overview'!$I$2:$I$790,$A11,'Transaction Overview'!$H$2:$H$790,B$4) -> 0 | C11: =SUMIFS('Transaction Overview'!$D$2:$D$790,'Transaction Overview'!$I$2:$I$790,$A11,'Transaction Overview'!$H$2:$H$790,C$4) -> 0 | D11: =SUMIFS('Transaction Overview'!$D$2:$D$790,'Transaction Overview'!$I$2:$I$790,$A11,'Transaction Overview'!$H$2:$H$790,D$4) -> 0 | E11: =SUMIFS('Transaction Overview'!$D$2:$D$790,'Transaction Overview'!$I$2:$I$790,$A11,'Transaction Overview'!$H$2:$H$790,E$4) -> 0 | F11: =SUMIFS('Transaction Overview'!$D$2:$D$790,'Transaction Overview'!$I$2:$I$790,$A11,'Transaction Overview'!$H$2:$H$790,F$4) -> 0 | G11: =SUMIFS('Transaction Overview'!$D$2:$D$790,'Transaction Overview'!$I$2:$I$790,$A11,'Transaction Overview'!$H$2:$H$790,G$4) -> 0 | H11: =SUMIFS('Transaction Overview'!$D$2:$D$790,'Transaction Overview'!$I$2:$I$790,$A11,'Transaction Overview'!$H$2:$H$790,H$4) -> 0 | I11: =SUMIFS('Transaction Overview'!$D$2:$D$790,'Transaction Overview'!$I$2:$I$790,$A11,'Transaction Overview'!$H$2:$H$790,I$4) -> 0 | ... M11: =SUMIFS('Transaction Overview'!$D$2:$D$790,'Transaction Overview'!$I$2:$I$790,$A11,'Transaction Overview'!$H$2:$H$790,M$4) -> 5000 | N11: =SUM(B11:M11) -> 6675
A12: Deal Specific: MRM | B12: =SUMIFS('Transaction Overview'!$D$2:$D$790,'Transaction Overview'!$I$2:$I$790,$A12,'Transaction Overview'!$H$2:$H$790,B$4) -> 236.37 | C12: =SUMIFS('Transaction Overview'!$D$2:$D$790,'Transaction Overview'!$I$2:$I$790,$A12,'Transaction Overview'!$H$2:$H$790,C$4) -> 236.37 | D12: =SUMIFS('Transaction Overview'!$D$2:$D$790,'Transaction Overview'!$I$2:$I$790,$A12,'Transaction Overview'!$H$2:$H$790,D$4) -> 236.37 | E12: =SUMIFS('Transaction Overview'!$D$2:$D$790,'Transaction Overview'!$I$2:$I$790,$A12,'Transaction Overview'!$H$2:$H$790,E$4) -> 236.37 | F12: =SUMIFS('Transaction Overview'!$D$2:$D$790,'Transaction Overview'!$I$2:$I$790,$A12,'Transaction Overview'!$H$2:$H$790,F$4) -> 236.37 | G12: =SUMIFS('Transaction Overview'!$D$2:$D$790,'Transaction Overview'!$I$2:$I$790,$A12,'Transaction Overview'!$H$2:$H$790,G$4) -> 236.37 | H12: =SUMIFS('Transaction Overview'!$D$2:$D$790,'Transaction Overview'!$I$2:$I$790,$A12,'Transaction Overview'!$H$2:$H$790,H$4) -> 236.37 | I12: =SUMIFS('Transaction Overview'!$D$2:$D$790,'Transaction Overview'!$I$2:$I$790,$A12,'Transaction Overview'!$H$2:$H$790,I$4) -> 236.37 | ... M12: =SUMIFS('Transaction Overview'!$D$2:$D$790,'Transaction Overview'!$I$2:$I$790,$A12,'Transaction Overview'!$H$2:$H$790,M$4) -> 241.87 | N12: =SUM(B12:M12) -> 2847.44
A13: Deal Specific: Rabourn Road | B13: =SUMIFS('Transaction Overview'!$D$2:$D$790,'Transaction Overview'!$I$2:$I$790,$A13,'Transaction Overview'!$H$2:$H$790,B$4) -> 0 | C13: =SUMIFS('Transaction Overview'!$D$2:$D$790,'Transaction Overview'!$I$2:$I$790,$A13,'Transaction Overview'!$H$2:$H$790,C$4) -> 0 | D13: =SUMIFS('Transaction Overview'!$D$2:$D$790,'Transaction Overview'!$I$2:$I$790,$A13,'Transaction Overview'!$H$2:$H$790,D$4) -> 0 | E13: =SUMIFS('Transaction Overview'!$D$2:$D$790,'Transaction Overview'!$I$2:$I$790,$A13,'Transaction Overview'!$H$2:$H$790,E$4) -> 0 | F13: =SUMIFS('Transaction Overview'!$D$2:$D$790,'Transaction Overview'!$I$2:$I$790,$A13,'Transaction Overview'!$H$2:$H$790,F$4) -> 0 | G13: =SUMIFS('Transaction Overview'!$D$2:$D$790,'Transaction Overview'!$I$2:$I$790,$A13,'Transaction Overview'!$H$2:$H$790,G$4) -> 0 | H13: =SUMIFS('Transaction Overview'!$D$2:$D$790,'Transaction Overview'!$I$2:$I$790,$A13,'Transaction Overview'!$H$2:$H$790,H$4) -> 0 | I13: =SUMIFS('Transaction Overview'!$D$2:$D$790,'Transaction Overview'!$I$2:$I$790,$A13,'Transaction Overview'!$H$2:$H$790,I$4) -> 233.33 | ... M13: =SUMIFS('Transaction Overview'!$D$2:$D$790,'Transaction Overview'!$I$2:$I$790,$A13,'Transaction Overview'!$H$2:$H$790,M$4) -> 233.33 | N13: =SUM(B13:M13) -> 1166.65
A14: Deal Specific: T&T Machine | B14: =SUMIFS('Transaction Overview'!$D$2:$D$790,'Transaction Overview'!$I$2:$I$790,$A14,'Transaction Overview'!$H$2:$H$790,B$4) -> 345.24 | C14: =SUMIFS('Transaction Overview'!$D$2:$D$790,'Transaction Overview'!$I$2:$I$790,$A14,'Transaction Overview'!$H$2:$H$790,C$4) -> 356.38 | D14: =SUMIFS('Transaction Overview'!$D$2:$D$790,'Transaction Overview'!$I$2:$I$790,$A14,'Transaction Overview'!$H$2:$H$790,D$4) -> 356.38 | E14: =SUMIFS('Transaction Overview'!$D$2:$D$790,'Transaction Overview'!$I$2:$I$790,$A14,'Transaction Overview'!$H$2:$H$790,E$4) -> 356.38 | F14: =SUMIFS('Transaction Overview'!$D$2:$D$790,'Transaction Overview'!$I$2:$I$790,$A14,'Transaction Overview'!$H$2:$H$790,F$4) -> 356.38 | G14: =SUMIFS('Transaction Overview'!$D$2:$D$790,'Transaction Overview'!$I$2:$I$790,$A14,'Transaction Overview'!$H$2:$H$790,G$4) -> 356.38 | H14: =SUMIFS('Transaction Overview'!$D$2:$D$790,'Transaction Overview'!$I$2:$I$790,$A14,'Transaction Overview'!$H$2:$H$790,H$4) -> 356.38 | I14: =SUMIFS('Transaction Overview'!$D$2:$D$790,'Transaction Overview'!$I$2:$I$790,$A14,'Transaction Overview'!$H$2:$H$790,I$4) -> 356.38 | ... M14: =SUMIFS('Transaction Overview'!$D$2:$D$790,'Transaction Overview'!$I$2:$I$790,$A14,'Transaction Overview'!$H$2:$H$790,M$4) -> 356.38 | N14: =SUM(B14:M14) -> 4315.42
A15: Subtotal — Deal-Specific | B15: =SUMIFS('Transaction Overview'!$D$2:$D$790,'Transaction Overview'!$J$2:$J$790,"Deal-Specific",'Transaction Overview'!$H$2:$H$790,B$4) -> 1393.13 | C15: =SUMIFS('Transaction Overview'!$D$2:$D$790,'Transaction Overview'!$J$2:$J$790,"Deal-Specific",'Transaction Overview'!$H$2:$H$790,C$4) -> 1404.27 | D15: =SUMIFS('Transaction Overview'!$D$2:$D$790,'Transaction Overview'!$J$2:$J$790,"Deal-Specific",'Transaction Overview'!$H$2:$H$790,D$4) -> 1419.16 | E15: =SUMIFS('Transaction Overview'!$D$2:$D$790,'Transaction Overview'!$J$2:$J$790,"Deal-Specific",'Transaction Overview'!$H$2:$H$790,E$4) -> -48580.84 | F15: =SUMIFS('Transaction Overview'!$D$2:$D$790,'Transaction Overview'!$J$2:$J$790,"Deal-Specific",'Transaction Overview'!$H$2:$H$790,F$4) -> 1419.16 | G15: =SUMIFS('Transaction Overview'!$D$2:$D$790,'Transaction Overview'!$J$2:$J$790,"Deal-Specific",'Transaction Overview'!$H$2:$H$790,G$4) -> 1419.16 | H15: =SUMIFS('Transaction Overview'!$D$2:$D$790,'Transaction Overview'!$J$2:$J$790,"Deal-Specific",'Transaction Overview'!$H$2:$H$790,H$4) -> 1419.16 | I15: =SUMIFS('Transaction Overview'!$D$2:$D$790,'Transaction Overview'!$J$2:$J$790,"Deal-Specific",'Transaction Overview'!$H$2:$H$790,I$4) -> 1652.49 | ... M15: =SUMIFS('Transaction Overview'!$D$2:$D$790,'Transaction Overview'!$J$2:$J$790,"Deal-Specific",'Transaction Overview'!$H$2:$H$790,M$4) -> -148342.01 | N15: =SUM(B15:M15) -> -226636.4
A17: Commissions — Incoming
A18: Incoming Commission: Breese | B18: =SUMIFS('Transaction Overview'!$D$2:$D$790,'Transaction Overview'!$I$2:$I$790,$A18,'Transaction Overview'!$H$2:$H$790,B$4) -> 0 | C18: =SUMIFS('Transaction Overview'!$D$2:$D$790,'Transaction Overview'!$I$2:$I$790,$A18,'Transaction Overview'!$H$2:$H$790,C$4) -> 0 | D18: =SUMIFS('Transaction Overview'!$D$2:$D$790,'Transaction Overview'!$I$2:$I$790,$A18,'Transaction Overview'!$H$2:$H$790,D$4) -> 0 | E18: =SUMIFS('Transaction Overview'!$D$2:$D$790,'Transaction Overview'!$I$2:$I$790,$A18,'Transaction Overview'!$H$2:$H$790,E$4) -> 0 | F18: =SUMIFS('Transaction Overview'!$D$2:$D$790,'Transaction Overview'!$I$2:$I$790,$A18,'Transaction Overview'!$H$2:$H$790,F$4) -> 0 | G18: =SUMIFS('Transaction Overview'!$D$2:$D$790,'Transaction Overview'!$I$2:$I$790,$A18,'Transaction Overview'!$H$2:$H$790,G$4) -> 0 | H18: =SUMIFS('Transaction Overview'!$D$2:$D$790,'Transaction Overview'!$I$2:$I$790,$A18,'Transaction Overview'!$H$2:$H$790,H$4) -> 269473.73 | I18: =SUMIFS('Transaction Overview'!$D$2:$D$790,'Transaction Overview'!$I$2:$I$790,$A18,'Transaction Overview'!$H$2:$H$790,I$4) -> 0 | ... M18: =SUMIFS('Transaction Overview'!$D$2:$D$790,'Transaction Overview'!$I$2:$I$790,$A18,'Transaction Overview'!$H$2:$H$790,M$4) -> 0 | N18: =SUM(B18:M18) -> 269473.73
A19: Incoming Commission: Butler Weldments | B19: =SUMIFS('Transaction Overview'!$D$2:$D$790,'Transaction Overview'!$I$2:$I$790,$A19,'Transaction Overview'!$H$2:$H$790,B$4) -> 0 | C19: =SUMIFS('Transaction Overview'!$D$2:$D$790,'Transaction Overview'!$I$2:$I$790,$A19,'Transaction Overview'!$H$2:$H$790,C$4) -> 0 | D19: =SUMIFS('Transaction Overview'!$D$2:$D$790,'Transaction Overview'!$I$2:$I$790,$A19,'Transaction Overview'!$H$2:$H$790,D$4) -> 164150.5 | E19: =SUMIFS('Transaction Overview'!$D$2:$D$790,'Transaction Overview'!$I$2:$I$790,$A19,'Transaction Overview'!$H$2:$H$790,E$4) -> 0 | F19: =SUMIFS('Transaction Overview'!$D$2:$D$790,'Transaction Overview'!$I$2:$I$790,$A19,'Transaction Overview'!$H$2:$H$790,F$4) -> 0 | G19: =SUMIFS('Transaction Overview'!$D$2:$D$790,'Transaction Overview'!$I$2:$I$790,$A19,'Transaction Overview'!$H$2:$H$790,G$4) -> 0 | H19: =SUMIFS('Transaction Overview'!$D$2:$D$790,'Transaction Overview'!$I$2:$I$790,$A19,'Transaction Overview'!$H$2:$H$790,H$4) -> 0 | I19: =SUMIFS('Transaction Overview'!$D$2:$D$790,'Transaction Overview'!$I$2:$I$790,$A19,'Transaction Overview'!$H$2:$H$790,I$4) -> 0 | ... M19: =SUMIFS('Transaction Overview'!$D$2:$D$790,'Transaction Overview'!$I$2:$I$790,$A19,'Transaction Overview'!$H$2:$H$790,M$4) -> 0 | N19: =SUM(B19:M19) -> 164150.5
A20: Incoming Commission: Edge Builder | B20: =SUMIFS('Transaction Overview'!$D$2:$D$790,'Transaction Overview'!$I$2:$I$790,$A20,'Transaction Overview'!$H$2:$H$790,B$4) -> 148250 | C20: =SUMIFS('Transaction Overview'!$D$2:$D$790,'Transaction Overview'!$I$2:$I$790,$A20,'Transaction Overview'!$H$2:$H$790,C$4) -> 0 | D20: =SUMIFS('Transaction Overview'!$D$2:$D$790,'Transaction Overview'!$I$2:$I$790,$A20,'Transaction Overview'!$H$2:$H$790,D$4) -> 0 | E20: =SUMIFS('Transaction Overview'!$D$2:$D$790,'Transaction Overview'!$I$2:$I$790,$A20,'Transaction Overview'!$H$2:$H$790,E$4) -> 0 | F20: =SUMIFS('Transaction Overview'!$D$2:$D$790,'Transaction Overview'!$I$2:$I$790,$A20,'Transaction Overview'!$H$2:$H$790,F$4) -> 0 | G20: =SUMIFS('Transaction Overview'!$D$2:$D$790,'Transaction Overview'!$I$2:$I$790,$A20,'Transaction Overview'!$H$2:$H$790,G$4) -> 0 | H20: =SUMIFS('Transaction Overview'!$D$2:$D$790,'Transaction Overview'!$I$2:$I$790,$A20,'Transaction Overview'!$H$2:$H$790,H$4) -> 0 | I20: =SUMIFS('Transaction Overview'!$D$2:$D$790,'Transaction Overview'!$I$2:$I$790,$A20,'Transaction Overview'!$H$2:$H$790,I$4) -> 0 | ... M20: =SUMIFS('Transaction Overview'!$D$2:$D$790,'Transaction Overview'!$I$2:$I$790,$A20,'Transaction Overview'!$H$2:$H$790,M$4) -> 0 | N20: =SUM(B20:M20) -> 148250
A21: Incoming Commission: Kalkaska Screw | B21: =SUMIFS('Transaction Overview'!$D$2:$D$790,'Transaction Overview'!$I$2:$I$790,$A21,'Transaction Overview'!$H$2:$H$790,B$4) -> 0 | C21: =SUMIFS('Transaction Overview'!$D$2:$D$790,'Transaction Overview'!$I$2:$I$790,$A21,'Transaction Overview'!$H$2:$H$790,C$4) -> 0 | D21: =SUMIFS('Transaction Overview'!$D$2:$D$790,'Transaction Overview'!$I$2:$I$790,$A21,'Transaction Overview'!$H$2:$H$790,D$4) -> 0 | E21: =SUMIFS('Transaction Overview'!$D$2:$D$790,'Transaction Overview'!$I$2:$I$790,$A21,'Transaction Overview'!$H$2:$H$790,E$4) -> 133875 | F21: =SUMIFS('Transaction Overview'!$D$2:$D$790,'Transaction Overview'!$I$2:$I$790,$A21,'Transaction Overview'!$H$2:$H$790,F$4) -> 0 | G21: =SUMIFS('Transaction Overview'!$D$2:$D$790,'Transaction Overview'!$I$2:$I$790,$A21,'Transaction Overview'!$H$2:$H$790,G$4) -> 0 | H21: =SUMIFS('Transaction Overview'!$D$2:$D$790,'Transaction Overview'!$I$2:$I$790,$A21,'Transaction Overview'!$H$2:$H$790,H$4) -> 0 | I21: =SUMIFS('Transaction Overview'!$D$2:$D$790,'Transaction Overview'!$I$2:$I$790,$A21,'Transaction Overview'!$H$2:$H$790,I$4) -> 0 | ... M21: =SUMIFS('Transaction Overview'!$D$2:$D$790,'Transaction Overview'!$I$2:$I$790,$A21,'Transaction Overview'!$H$2:$H$790,M$4) -> 0 | N21: =SUM(B21:M21) -> 133875
A22: Incoming Commission: Stryten Energy | B22: =SUMIFS('Transaction Overview'!$D$2:$D$790,'Transaction Overview'!$I$2:$I$790,$A22,'Transaction Overview'!$H$2:$H$790,B$4) -> 0 | C22: =SUMIFS('Transaction Overview'!$D$2:$D$790,'Transaction Overview'!$I$2:$I$790,$A22,'Transaction Overview'!$H$2:$H$790,C$4) -> 0 | D22: =SUMIFS('Transaction Overview'!$D$2:$D$790,'Transaction Overview'!$I$2:$I$790,$A22,'Transaction Overview'!$H$2:$H$790,D$4) -> 0 | E22: =SUMIFS('Transaction Overview'!$D$2:$D$790,'Transaction Overview'!$I$2:$I$790,$A22,'Transaction Overview'!$H$2:$H$790,E$4) -> 0 | F22: =SUMIFS('Transaction Overview'!$D$2:$D$790,'Transaction Overview'!$I$2:$I$790,$A22,'Transaction Overview'!$H$2:$H$790,F$4) -> 0 | G22: =SUMIFS('Transaction Overview'!$D$2:$D$790,'Transaction Overview'!$I$2:$I$790,$A22,'Transaction Overview'!$H$2:$H$790,G$4) -> 0 | H22: =SUMIFS('Transaction Overview'!$D$2:$D$790,'Transaction Overview'!$I$2:$I$790,$A22,'Transaction Overview'!$H$2:$H$790,H$4) -> 0 | I22: =SUMIFS('Transaction Overview'!$D$2:$D$790,'Transaction Overview'!$I$2:$I$790,$A22,'Transaction Overview'!$H$2:$H$790,I$4) -> 0 | ... M22: =SUMIFS('Transaction Overview'!$D$2:$D$790,'Transaction Overview'!$I$2:$I$790,$A22,'Transaction Overview'!$H$2:$H$790,M$4) -> 318189.39 | N22: =SUM(B22:M22) -> 318189.39
A23: Subtotal — Commissions — Incoming | B23: =SUMIFS('Transaction Overview'!$D$2:$D$790,'Transaction Overview'!$J$2:$J$790,"Commissions — Incoming",'Transaction Overview'!$H$2:$H$790,B$4) -> 148250 | C23: =SUMIFS('Transaction Overview'!$D$2:$D$790,'Transaction Overview'!$J$2:$J$790,"Commissions — Incoming",'Transaction Overview'!$H$2:$H$790,C$4) -> 0 | D23: =SUMIFS('Transaction Overview'!$D$2:$D$790,'Transaction Overview'!$J$2:$J$790,"Commissions — Incoming",'Transaction Overview'!$H$2:$H$790,D$4) -> 164150.5 | E23: =SUMIFS('Transaction Overview'!$D$2:$D$790,'Transaction Overview'!$J$2:$J$790,"Commissions — Incoming",'Transaction Overview'!$H$2:$H$790,E$4) -> 133875 | F23: =SUMIFS('Transaction Overview'!$D$2:$D$790,'Transaction Overview'!$J$2:$J$790,"Commissions — Incoming",'Transaction Overview'!$H$2:$H$790,F$4) -> 0 | G23: =SUMIFS('Transaction Overview'!$D$2:$D$790,'Transaction Overview'!$J$2:$J$790,"Commissions — Incoming",'Transaction Overview'!$H$2:$H$790,G$4) -> 0 | H23: =SUMIFS('Transaction Overview'!$D$2:$D$790,'Transaction Overview'!$J$2:$J$790,"Commissions — Incoming",'Transaction Overview'!$H$2:$H$790,H$4) -> 269473.73 | I23: =SUMIFS('Transaction Overview'!$D$2:$D$790,'Transaction Overview'!$J$2:$J$790,"Commissions — Incoming",'Transaction Overview'!$H$2:$H$790,I$4) -> 0 | ... M23: =SUMIFS('Transaction Overview'!$D$2:$D$790,'Transaction Overview'!$J$2:$J$790,"Commissions — Incoming",'Transaction Overview'!$H$2:$H$790,M$4) -> 318189.39 | N23: =SUM(B23:M23) -> 1033938.6
A25: Commissions — Outgoing
A26: Wire Out — Edge Builder Commission Payments | B26: =SUMIFS('Transaction Overview'!$D$2:$D$790,'Transaction Overview'!$I$2:$I$790,$A26,'Transaction Overview'!$H$2:$H$790,B$4) -> -23830 | C26: =SUMIFS('Transaction Overview'!$D$2:$D$790,'Transaction Overview'!$I$2:$I$790,$A26,'Transaction Overview'!$H$2:$H$790,C$4) -> 0 | D26: =SUMIFS('Transaction Overview'!$D$2:$D$790,'Transaction Overview'!$I$2:$I$790,$A26,'Transaction Overview'!$H$2:$H$790,D$4) -> 0 | E26: =SUMIFS('Transaction Overview'!$D$2:$D$790,'Transaction Overview'!$I$2:$I$790,$A26,'Transaction Overview'!$H$2:$H$790,E$4) -> 0 | F26: =SUMIFS('Transaction Overview'!$D$2:$D$790,'Transaction Overview'!$I$2:$I$790,$A26,'Transaction Overview'!$H$2:$H$790,F$4) -> 0 | G26: =SUMIFS('Transaction Overview'!$D$2:$D$790,'Transaction Overview'!$I$2:$I$790,$A26,'Transaction Overview'!$H$2:$H$790,G$4) -> 0 | H26: =SUMIFS('Transaction Overview'!$D$2:$D$790,'Transaction Overview'!$I$2:$I$790,$A26,'Transaction Overview'!$H$2:$H$790,H$4) -> 0 | I26: =SUMIFS('Transaction Overview'!$D$2:$D$790,'Transaction Overview'!$I$2:$I$790,$A26,'Transaction Overview'!$H$2:$H$790,I$4) -> 0 | ... M26: =SUMIFS('Transaction Overview'!$D$2:$D$790,'Transaction Overview'!$I$2:$I$790,$A26,'Transaction Overview'!$H$2:$H$790,M$4) -> 0 | N26: =SUM(B26:M26) -> -23830
A27: Wire Out — Stryten Commission Payments | B27: =SUMIFS('Transaction Overview'!$D$2:$D$790,'Transaction Overview'!$I$2:$I$790,$A27,'Transaction Overview'!$H$2:$H$790,B$4) -> 0 | C27: =SUMIFS('Transaction Overview'!$D$2:$D$790,'Transaction Overview'!$I$2:$I$790,$A27,'Transaction Overview'!$H$2:$H$790,C$4) -> 0 | D27: =SUMIFS('Transaction Overview'!$D$2:$D$790,'Transaction Overview'!$I$2:$I$790,$A27,'Transaction Overview'!$H$2:$H$790,D$4) -> 0 | E27: =SUMIFS('Transaction Overview'!$D$2:$D$790,'Transaction Overview'!$I$2:$I$790,$A27,'Transaction Overview'!$H$2:$H$790,E$4) -> 0 | F27: =SUMIFS('Transaction Overview'!$D$2:$D$790,'Transaction Overview'!$I$2:$I$790,$A27,'Transaction Overview'!$H$2:$H$790,F$4) -> 0 | G27: =SUMIFS('Transaction Overview'!$D$2:$D$790,'Transaction Overview'!$I$2:$I$790,$A27,'Transaction Overview'!$H$2:$H$790,G$4) -> 0 | H27: =SUMIFS('Transaction Overview'!$D$2:$D$790,'Transaction Overview'!$I$2:$I$790,$A27,'Transaction Overview'!$H$2:$H$790,H$4) -> 0 | I27: =SUMIFS('Transaction Overview'!$D$2:$D$790,'Transaction Overview'!$I$2:$I$790,$A27,'Transaction Overview'!$H$2:$H$790,I$4) -> 0 | ... M27: =SUMIFS('Transaction Overview'!$D$2:$D$790,'Transaction Overview'!$I$2:$I$790,$A27,'Transaction Overview'!$H$2:$H$790,M$4) -> -47820 | N27: =SUM(B27:M27) -> -47820
A28: Subtotal — Commissions — Outgoing | B28: =SUMIFS('Transaction Overview'!$D$2:$D$790,'Transaction Overview'!$J$2:$J$790,"Commissions — Outgoing",'Transaction Overview'!$H$2:$H$790,B$4) -> -23830 | C28: =SUMIFS('Transaction Overview'!$D$2:$D$790,'Transaction Overview'!$J$2:$J$790,"Commissions — Outgoing",'Transaction Overview'!$H$2:$H$790,C$4) -> 0 | D28: =SUMIFS('Transaction Overview'!$D$2:$D$790,'Transaction Overview'!$J$2:$J$790,"Commissions — Outgoing",'Transaction Overview'!$H$2:$H$790,D$4) -> 0 | E28: =SUMIFS('Transaction Overview'!$D$2:$D$790,'Transaction Overview'!$J$2:$J$790,"Commissions — Outgoing",'Transaction Overview'!$H$2:$H$790,E$4) -> 0 | F28: =SUMIFS('Transaction Overview'!$D$2:$D$790,'Transaction Overview'!$J$2:$J$790,"Commissions — Outgoing",'Transaction Overview'!$H$2:$H$790,F$4) -> 0 | G28: =SUMIFS('Transaction Overview'!$D$2:$D$790,'Transaction Overview'!$J$2:$J$790,"Commissions — Outgoing",'Transaction Overview'!$H$2:$H$790,G$4) -> 0 | H28: =SUMIFS('Transaction Overview'!$D$2:$D$790,'Transaction Overview'!$J$2:$J$790,"Commissions — Outgoing",'Transaction Overview'!$H$2:$H$790,H$4) -> 0 | I28: =SUMIFS('Transaction Overview'!$D$2:$D$790,'Transaction Overview'!$J$2:$J$790,"Commissions — Outgoing",'Transaction Overview'!$H$2:$H$790,I$4) -> 0 | ... M28: =SUMIFS('Transaction Overview'!$D$2:$D$790,'Transaction Overview'!$J$2:$J$790,"Commissions — Outgoing",'Transaction Overview'!$H$2:$H$790,M$4) -> -47820 | N28: =SUM(B28:M28) -> -71650
A30: MAG Pass-Through
A31: Due to Andrew – MAG Pass-Through 30% | B31: =SUMIFS('Transaction Overview'!$D$2:$D$790,'Transaction Overview'!$I$2:$I$790,$A31,'Transaction Overview'!$H$2:$H$790,B$4) -> 0 | C31: =SUMIFS('Transaction Overview'!$D$2:$D$790,'Transaction Overview'!$I$2:$I$790,$A31,'Transaction Overview'!$H$2:$H$790,C$4) -> 0 | D31: =SUMIFS('Transaction Overview'!$D$2:$D$790,'Transaction Overview'!$I$2:$I$790,$A31,'Transaction Overview'!$H$2:$H$790,D$4) -> 0 | E31: =SUMIFS('Transaction Overview'!$D$2:$D$790,'Transaction Overview'!$I$2:$I$790,$A31,'Transaction Overview'!$H$2:$H$790,E$4) -> 0 | F31: =SUMIFS('Transaction Overview'!$D$2:$D$790,'Transaction Overview'!$I$2:$I$790,$A31,'Transaction Overview'!$H$2:$H$790,F$4) -> 0 | G31: =SUMIFS('Transaction Overview'!$D$2:$D$790,'Transaction Overview'!$I$2:$I$790,$A31,'Transaction Overview'!$H$2:$H$790,G$4) -> 0 | H31: =SUMIFS('Transaction Overview'!$D$2:$D$790,'Transaction Overview'!$I$2:$I$790,$A31,'Transaction Overview'!$H$2:$H$790,H$4) -> 0 | I31: =SUMIFS('Transaction Overview'!$D$2:$D$790,'Transaction Overview'!$I$2:$I$790,$A31,'Transaction Overview'!$H$2:$H$790,I$4) -> 0 | ... M31: =SUMIFS('Transaction Overview'!$D$2:$D$790,'Transaction Overview'!$I$2:$I$790,$A31,'Transaction Overview'!$H$2:$H$790,M$4) -> -21000 | N31: =SUM(B31:M31) -> -21000
A32: Due to Dax – MAG Pass-Through 70% | B32: =SUMIFS('Transaction Overview'!$D$2:$D$790,'Transaction Overview'!$I$2:$I$790,$A32,'Transaction Overview'!$H$2:$H$790,B$4) -> 0 | C32: =SUMIFS('Transaction Overview'!$D$2:$D$790,'Transaction Overview'!$I$2:$I$790,$A32,'Transaction Overview'!$H$2:$H$790,C$4) -> 0 | D32: =SUMIFS('Transaction Overview'!$D$2:$D$790,'Transaction Overview'!$I$2:$I$790,$A32,'Transaction Overview'!$H$2:$H$790,D$4) -> 0 | E32: =SUMIFS('Transaction Overview'!$D$2:$D$790,'Transaction Overview'!$I$2:$I$790,$A32,'Transaction Overview'!$H$2:$H$790,E$4) -> 0 | F32: =SUMIFS('Transaction Overview'!$D$2:$D$790,'Transaction Overview'!$I$2:$I$790,$A32,'Transaction Overview'!$H$2:$H$790,F$4) -> 0 | G32: =SUMIFS('Transaction Overview'!$D$2:$D$790,'Transaction Overview'!$I$2:$I$790,$A32,'Transaction Overview'!$H$2:$H$790,G$4) -> 0 | H32: =SUMIFS('Transaction Overview'!$D$2:$D$790,'Transaction Overview'!$I$2:$I$790,$A32,'Transaction Overview'!$H$2:$H$790,H$4) -> 0 | I32: =SUMIFS('Transaction Overview'!$D$2:$D$790,'Transaction Overview'!$I$2:$I$790,$A32,'Transaction Overview'!$H$2:$H$790,I$4) -> 0 | ... M32: =SUMIFS('Transaction Overview'!$D$2:$D$790,'Transaction Overview'!$I$2:$I$790,$A32,'Transaction Overview'!$H$2:$H$790,M$4) -> -39000 | N32: =SUM(B32:M32) -> -39000
A33: MAG - Admeer Advisory Reimbursement | B33: =SUMIFS('Transaction Overview'!$D$2:$D$790,'Transaction Overview'!$I$2:$I$790,$A33,'Transaction Overview'!$H$2:$H$790,B$4) -> 15000 | C33: =SUMIFS('Transaction Overview'!$D$2:$D$790,'Transaction Overview'!$I$2:$I$790,$A33,'Transaction Overview'!$H$2:$H$790,C$4) -> 20000 | D33: =SUMIFS('Transaction Overview'!$D$2:$D$790,'Transaction Overview'!$I$2:$I$790,$A33,'Transaction Overview'!$H$2:$H$790,D$4) -> 0 | E33: =SUMIFS('Transaction Overview'!$D$2:$D$790,'Transaction Overview'!$I$2:$I$790,$A33,'Transaction Overview'!$H$2:$H$790,E$4) -> 0 | F33: =SUMIFS('Transaction Overview'!$D$2:$D$790,'Transaction Overview'!$I$2:$I$790,$A33,'Transaction Overview'!$H$2:$H$790,F$4) -> 0 | G33: =SUMIFS('Transaction Overview'!$D$2:$D$790,'Transaction Overview'!$I$2:$I$790,$A33,'Transaction Overview'!$H$2:$H$790,G$4) -> 0 | H33: =SUMIFS('Transaction Overview'!$D$2:$D$790,'Transaction Overview'!$I$2:$I$790,$A33,'Transaction Overview'!$H$2:$H$790,H$4) -> 0 | I33: =SUMIFS('Transaction Overview'!$D$2:$D$790,'Transaction Overview'!$I$2:$I$790,$A33,'Transaction Overview'!$H$2:$H$790,I$4) -> 0 | ... M33: =SUMIFS('Transaction Overview'!$D$2:$D$790,'Transaction Overview'!$I$2:$I$790,$A33,'Transaction Overview'!$H$2:$H$790,M$4) -> 0 | N33: =SUM(B33:M33) -> 35000
A34: MAG - Admeer Advisory Transfer | B34: =SUMIFS('Transaction Overview'!$D$2:$D$790,'Transaction Overview'!$I$2:$I$790,$A34,'Transaction Overview'!$H$2:$H$790,B$4) -> -9950 | C34: =SUMIFS('Transaction Overview'!$D$2:$D$790,'Transaction Overview'!$I$2:$I$790,$A34,'Transaction Overview'!$H$2:$H$790,C$4) -> -15000 | D34: =SUMIFS('Transaction Overview'!$D$2:$D$790,'Transaction Overview'!$I$2:$I$790,$A34,'Transaction Overview'!$H$2:$H$790,D$4) -> 0 | E34: =SUMIFS('Transaction Overview'!$D$2:$D$790,'Transaction Overview'!$I$2:$I$790,$A34,'Transaction Overview'!$H$2:$H$790,E$4) -> 0 | F34: =SUMIFS('Transaction Overview'!$D$2:$D$790,'Transaction Overview'!$I$2:$I$790,$A34,'Transaction Overview'!$H$2:$H$790,F$4) -> -2500 | G34: =SUMIFS('Transaction Overview'!$D$2:$D$790,'Transaction Overview'!$I$2:$I$790,$A34,'Transaction Overview'!$H$2:$H$790,G$4) -> -5000 | H34: =SUMIFS('Transaction Overview'!$D$2:$D$790,'Transaction Overview'!$I$2:$I$790,$A34,'Transaction Overview'!$H$2:$H$790,H$4) -> 0 | I34: =SUMIFS('Transaction Overview'!$D$2:$D$790,'Transaction Overview'!$I$2:$I$790,$A34,'Transaction Overview'!$H$2:$H$790,I$4) -> 0 | ... M34: =SUMIFS('Transaction Overview'!$D$2:$D$790,'Transaction Overview'!$I$2:$I$790,$A34,'Transaction Overview'!$H$2:$H$790,M$4) -> 0 | N34: =SUM(B34:M34) -> -42450
A35: MAG Capital Partners Pass-Through Wire – 70/30 Split | B35: =SUMIFS('Transaction Overview'!$D$2:$D$790,'Transaction Overview'!$I$2:$I$790,$A35,'Transaction Overview'!$H$2:$H$790,B$4) -> 0 | C35: =SUMIFS('Transaction Overview'!$D$2:$D$790,'Transaction Overview'!$I$2:$I$790,$A35,'Transaction Overview'!$H$2:$H$790,C$4) -> 0 | D35: =SUMIFS('Transaction Overview'!$D$2:$D$790,'Transaction Overview'!$I$2:$I$790,$A35,'Transaction Overview'!$H$2:$H$790,D$4) -> 0 | E35: =SUMIFS('Transaction Overview'!$D$2:$D$790,'Transaction Overview'!$I$2:$I$790,$A35,'Transaction Overview'!$H$2:$H$790,E$4) -> 0 | F35: =SUMIFS('Transaction Overview'!$D$2:$D$790,'Transaction Overview'!$I$2:$I$790,$A35,'Transaction Overview'!$H$2:$H$790,F$4) -> 0 | G35: =SUMIFS('Transaction Overview'!$D$2:$D$790,'Transaction Overview'!$I$2:$I$790,$A35,'Transaction Overview'!$H$2:$H$790,G$4) -> 0 | H35: =SUMIFS('Transaction Overview'!$D$2:$D$790,'Transaction Overview'!$I$2:$I$790,$A35,'Transaction Overview'!$H$2:$H$790,H$4) -> 0 | I35: =SUMIFS('Transaction Overview'!$D$2:$D$790,'Transaction Overview'!$I$2:$I$790,$A35,'Transaction Overview'!$H$2:$H$790,I$4) -> 0 | ... M35: =SUMIFS('Transaction Overview'!$D$2:$D$790,'Transaction Overview'!$I$2:$I$790,$A35,'Transaction Overview'!$H$2:$H$790,M$4) -> 75000 | N35: =SUM(B35:M35) -> 75000
A36: MAG Marketing Reimbursement | B36: =SUMIFS('Transaction Overview'!$D$2:$D$790,'Transaction Overview'!$I$2:$I$790,$A36,'Transaction Overview'!$H$2:$H$790,B$4) -> 0 | C36: =SUMIFS('Transaction Overview'!$D$2:$D$790,'Transaction Overview'!$I$2:$I$790,$A36,'Transaction Overview'!$H$2:$H$790,C$4) -> 0 | D36: =SUMIFS('Transaction Overview'!$D$2:$D$790,'Transaction Overview'!$I$2:$I$790,$A36,'Transaction Overview'!$H$2:$H$790,D$4) -> 0 | E36: =SUMIFS('Transaction Overview'!$D$2:$D$790,'Transaction Overview'!$I$2:$I$790,$A36,'Transaction Overview'!$H$2:$H$790,E$4) -> 0 | F36: =SUMIFS('Transaction Overview'!$D$2:$D$790,'Transaction Overview'!$I$2:$I$790,$A36,'Transaction Overview'!$H$2:$H$790,F$4) -> 0 | G36: =SUMIFS('Transaction Overview'!$D$2:$D$790,'Transaction Overview'!$I$2:$I$790,$A36,'Transaction Overview'!$H$2:$H$790,G$4) -> 0 | H36: =SUMIFS('Transaction Overview'!$D$2:$D$790,'Transaction Overview'!$I$2:$I$790,$A36,'Transaction Overview'!$H$2:$H$790,H$4) -> 0 | I36: =SUMIFS('Transaction Overview'!$D$2:$D$790,'Transaction Overview'!$I$2:$I$790,$A36,'Transaction Overview'!$H$2:$H$790,I$4) -> 0 | ... M36: =SUMIFS('Transaction Overview'!$D$2:$D$790,'Transaction Overview'!$I$2:$I$790,$A36,'Transaction Overview'!$H$2:$H$790,M$4) -> 0 | N36: =SUM(B36:M36) -> 15000
A37: Subtotal — MAG Pass-Through | B37: =SUMIFS('Transaction Overview'!$D$2:$D$790,'Transaction Overview'!$J$2:$J$790,"MAG Pass-Through",'Transaction Overview'!$H$2:$H$790,B$4) -> 5050 | C37: =SUMIFS('Transaction Overview'!$D$2:$D$790,'Transaction Overview'!$J$2:$J$790,"MAG Pass-Through",'Transaction Overview'!$H$2:$H$790,C$4) -> 5000 | D37: =SUMIFS('Transaction Overview'!$D$2:$D$790,'Transaction Overview'!$J$2:$J$790,"MAG Pass-Through",'Transaction Overview'!$H$2:$H$790,D$4) -> 0 | E37: =SUMIFS('Transaction Overview'!$D$2:$D$790,'Transaction Overview'!$J$2:$J$790,"MAG Pass-Through",'Transaction Overview'!$H$2:$H$790,E$4) -> 0 | F37: =SUMIFS('Transaction Overview'!$D$2:$D$790,'Transaction Overview'!$J$2:$J$790,"MAG Pass-Through",'Transaction Overview'!$H$2:$H$790,F$4) -> -2500 | G37: =SUMIFS('Transaction Overview'!$D$2:$D$790,'Transaction Overview'!$J$2:$J$790,"MAG Pass-Through",'Transaction Overview'!$H$2:$H$790,G$4) -> -5000 | H37: =SUMIFS('Transaction Overview'!$D$2:$D$790,'Transaction Overview'!$J$2:$J$790,"MAG Pass-Through",'Transaction Overview'!$H$2:$H$790,H$4) -> 0 | I37: =SUMIFS('Transaction Overview'!$D$2:$D$790,'Transaction Overview'!$J$2:$J$790,"MAG Pass-Through",'Transaction Overview'!$H$2:$H$790,I$4) -> 0 | ... M37: =SUMIFS('Transaction Overview'!$D$2:$D$790,'Transaction Overview'!$J$2:$J$790,"MAG Pass-Through",'Transaction Overview'!$H$2:$H$790,M$4) -> 15000 | N37: =SUM(B37:M37) -> 22550
A39: Wire Transfers — Incoming
A40: Incoming Crystal Asset Management Wire | B40: =SUMIFS('Transaction Overview'!$D$2:$D$790,'Transaction Overview'!$I$2:$I$790,$A40,'Transaction Overview'!$H$2:$H$790,B$4) -> 0 | C40: =SUMIFS('Transaction Overview'!$D$2:$D$790,'Transaction Overview'!$I$2:$I$790,$A40,'Transaction Overview'!$H$2:$H$790,C$4) -> 0 | D40: =SUMIFS('Transaction Overview'!$D$2:$D$790,'Transaction Overview'!$I$2:$I$790,$A40,'Transaction Overview'!$H$2:$H$790,D$4) -> 0 | E40: =SUMIFS('Transaction Overview'!$D$2:$D$790,'Transaction Overview'!$I$2:$I$790,$A40,'Transaction Overview'!$H$2:$H$790,E$4) -> 0 | F40: =SUMIFS('Transaction Overview'!$D$2:$D$790,'Transaction Overview'!$I$2:$I$790,$A40,'Transaction Overview'!$H$2:$H$790,F$4) -> 0 | G40: =SUMIFS('Transaction Overview'!$D$2:$D$790,'Transaction Overview'!$I$2:$I$790,$A40,'Transaction Overview'!$H$2:$H$790,G$4) -> 100000 | H40: =SUMIFS('Transaction Overview'!$D$2:$D$790,'Transaction Overview'!$I$2:$I$790,$A40,'Transaction Overview'!$H$2:$H$790,H$4) -> 0 | I40: =SUMIFS('Transaction Overview'!$D$2:$D$790,'Transaction Overview'!$I$2:$I$790,$A40,'Transaction Overview'!$H$2:$H$790,I$4) -> 0 | ... M40: =SUMIFS('Transaction Overview'!$D$2:$D$790,'Transaction Overview'!$I$2:$I$790,$A40,'Transaction Overview'!$H$2:$H$790,M$4) -> 0 | N40: =SUM(B40:M40) -> 100000
A41: Incoming wire from JC Whitner | B41: =SUMIFS('Transaction Overview'!$D$2:$D$790,'Transaction Overview'!$I$2:$I$790,$A41,'Transaction Overview'!$H$2:$H$790,B$4) -> 0 | C41: =SUMIFS('Transaction Overview'!$D$2:$D$790,'Transaction Overview'!$I$2:$I$790,$A41,'Transaction Overview'!$H$2:$H$790,C$4) -> 0 | D41: =SUMIFS('Transaction Overview'!$D$2:$D$790,'Transaction Overview'!$I$2:$I$790,$A41,'Transaction Overview'!$H$2:$H$790,D$4) -> 0 | E41: =SUMIFS('Transaction Overview'!$D$2:$D$790,'Transaction Overview'!$I$2:$I$790,$A41,'Transaction Overview'!$H$2:$H$790,E$4) -> 0 | F41: =SUMIFS('Transaction Overview'!$D$2:$D$790,'Transaction Overview'!$I$2:$I$790,$A41,'Transaction Overview'!$H$2:$H$790,F$4) -> 0 | G41: =SUMIFS('Transaction Overview'!$D$2:$D$790,'Transaction Overview'!$I$2:$I$790,$A41,'Transaction Overview'!$H$2:$H$790,G$4) -> 0 | H41: =SUMIFS('Transaction Overview'!$D$2:$D$790,'Transaction Overview'!$I$2:$I$790,$A41,'Transaction Overview'!$H$2:$H$790,H$4) -> 0 | I41: =SUMIFS('Transaction Overview'!$D$2:$D$790,'Transaction Overview'!$I$2:$I$790,$A41,'Transaction Overview'!$H$2:$H$790,I$4) -> 20000 | ... M41: =SUMIFS('Transaction Overview'!$D$2:$D$790,'Transaction Overview'!$I$2:$I$790,$A41,'Transaction Overview'!$H$2:$H$790,M$4) -> 0 | N41: =SUM(B41:M41) -> 20000
A42: Subtotal — Wire Transfers — Incoming | B42: =SUMIFS('Transaction Overview'!$D$2:$D$790,'Transaction Overview'!$J$2:$J$790,"Wire Transfers — Incoming",'Transaction Overview'!$H$2:$H$790,B$4) -> 0 | C42: =SUMIFS('Transaction Overview'!$D$2:$D$790,'Transaction Overview'!$J$2:$J$790,"Wire Transfers — Incoming",'Transaction Overview'!$H$2:$H$790,C$4) -> 0 | D42: =SUMIFS('Transaction Overview'!$D$2:$D$790,'Transaction Overview'!$J$2:$J$790,"Wire Transfers — Incoming",'Transaction Overview'!$H$2:$H$790,D$4) -> 0 | E42: =SUMIFS('Transaction Overview'!$D$2:$D$790,'Transaction Overview'!$J$2:$J$790,"Wire Transfers — Incoming",'Transaction Overview'!$H$2:$H$790,E$4) -> 0 | F42: =SUMIFS('Transaction Overview'!$D$2:$D$790,'Transaction Overview'!$J$2:$J$790,"Wire Transfers — Incoming",'Transaction Overview'!$H$2:$H$790,F$4) -> 0 | G42: =SUMIFS('Transaction Overview'!$D$2:$D$790,'Transaction Overview'!$J$2:$J$790,"Wire Transfers — Incoming",'Transaction Overview'!$H$2:$H$790,G$4) -> 100000 | H42: =SUMIFS('Transaction Overview'!$D$2:$D$790,'Transaction Overview'!$J$2:$J$790,"Wire Transfers — Incoming",'Transaction Overview'!$H$2:$H$790,H$4) -> 0 | I42: =SUMIFS('Transaction Overview'!$D$2:$D$790,'Transaction Overview'!$J$2:$J$790,"Wire Transfers — Incoming",'Transaction Overview'!$H$2:$H$790,I$4) -> 20000 | ... M42: =SUMIFS('Transaction Overview'!$D$2:$D$790,'Transaction Overview'!$J$2:$J$790,"Wire Transfers — Incoming",'Transaction Overview'!$H$2:$H$790,M$4) -> 0 | N42: =SUM(B42:M42) -> 120000
A44: Wire Transfers — Outgoing
A45: Outgoing Crystal Asset Management Wire | B45: =SUMIFS('Transaction Overview'!$D$2:$D$790,'Transaction Overview'!$I$2:$I$790,$A45,'Transaction Overview'!$H$2:$H$790,B$4) -> 0 | C45: =SUMIFS('Transaction Overview'!$D$2:$D$790,'Transaction Overview'!$I$2:$I$790,$A45,'Transaction Overview'!$H$2:$H$790,C$4) -> 0 | D45: =SUMIFS('Transaction Overview'!$D$2:$D$790,'Transaction Overview'!$I$2:$I$790,$A45,'Transaction Overview'!$H$2:$H$790,D$4) -> 0 | E45: =SUMIFS('Transaction Overview'!$D$2:$D$790,'Transaction Overview'!$I$2:$I$790,$A45,'Transaction Overview'!$H$2:$H$790,E$4) -> 0 | F45: =SUMIFS('Transaction Overview'!$D$2:$D$790,'Transaction Overview'!$I$2:$I$790,$A45,'Transaction Overview'!$H$2:$H$790,F$4) -> 0 | G45: =SUMIFS('Transaction Overview'!$D$2:$D$790,'Transaction Overview'!$I$2:$I$790,$A45,'Transaction Overview'!$H$2:$H$790,G$4) -> -100000 | H45: =SUMIFS('Transaction Overview'!$D$2:$D$790,'Transaction Overview'!$I$2:$I$790,$A45,'Transaction Overview'!$H$2:$H$790,H$4) -> 0 | I45: =SUMIFS('Transaction Overview'!$D$2:$D$790,'Transaction Overview'!$I$2:$I$790,$A45,'Transaction Overview'!$H$2:$H$790,I$4) -> 0 | ... M45: =SUMIFS('Transaction Overview'!$D$2:$D$790,'Transaction Overview'!$I$2:$I$790,$A45,'Transaction Overview'!$H$2:$H$790,M$4) -> 0 | N45: =SUM(B45:M45) -> -100000
A46: Outgoing wire to JC Whitner | B46: =SUMIFS('Transaction Overview'!$D$2:$D$790,'Transaction Overview'!$I$2:$I$790,$A46,'Transaction Overview'!$H$2:$H$790,B$4) -> 0 | C46: =SUMIFS('Transaction Overview'!$D$2:$D$790,'Transaction Overview'!$I$2:$I$790,$A46,'Transaction Overview'!$H$2:$H$790,C$4) -> 0 | D46: =SUMIFS('Transaction Overview'!$D$2:$D$790,'Transaction Overview'!$I$2:$I$790,$A46,'Transaction Overview'!$H$2:$H$790,D$4) -> 0 | E46: =SUMIFS('Transaction Overview'!$D$2:$D$790,'Transaction Overview'!$I$2:$I$790,$A46,'Transaction Overview'!$H$2:$H$790,E$4) -> 0 | F46: =SUMIFS('Transaction Overview'!$D$2:$D$790,'Transaction Overview'!$I$2:$I$790,$A46,'Transaction Overview'!$H$2:$H$790,F$4) -> 0 | G46: =SUMIFS('Transaction Overview'!$D$2:$D$790,'Transaction Overview'!$I$2:$I$790,$A46,'Transaction Overview'!$H$2:$H$790,G$4) -> 0 | H46: =SUMIFS('Transaction Overview'!$D$2:$D$790,'Transaction Overview'!$I$2:$I$790,$A46,'Transaction Overview'!$H$2:$H$790,H$4) -> 0 | I46: =SUMIFS('Transaction Overview'!$D$2:$D$790,'Transaction Overview'!$I$2:$I$790,$A46,'Transaction Overview'!$H$2:$H$790,I$4) -> -25000 | ... M46: =SUMIFS('Transaction Overview'!$D$2:$D$790,'Transaction Overview'!$I$2:$I$790,$A46,'Transaction Overview'!$H$2:$H$790,M$4) -> -10000 | N46: =SUM(B46:M46) -> -35000
A47: Wire to Binder Family Trust - TBD | B47: =SUMIFS('Transaction Overview'!$D$2:$D$790,'Transaction Overview'!$I$2:$I$790,$A47,'Transaction Overview'!$H$2:$H$790,B$4) -> 0 | C47: =SUMIFS('Transaction Overview'!$D$2:$D$790,'Transaction Overview'!$I$2:$I$790,$A47,'Transaction Overview'!$H$2:$H$790,C$4) -> 0 | D47: =SUMIFS('Transaction Overview'!$D$2:$D$790,'Transaction Overview'!$I$2:$I$790,$A47,'Transaction Overview'!$H$2:$H$790,D$4) -> -6000 | E47: =SUMIFS('Transaction Overview'!$D$2:$D$790,'Transaction Overview'!$I$2:$I$790,$A47,'Transaction Overview'!$H$2:$H$790,E$4) -> 0 | F47: =SUMIFS('Transaction Overview'!$D$2:$D$790,'Transaction Overview'!$I$2:$I$790,$A47,'Transaction Overview'!$H$2:$H$790,F$4) -> 0 | G47: =SUMIFS('Transaction Overview'!$D$2:$D$790,'Transaction Overview'!$I$2:$I$790,$A47,'Transaction Overview'!$H$2:$H$790,G$4) -> 0 | H47: =SUMIFS('Transaction Overview'!$D$2:$D$790,'Transaction Overview'!$I$2:$I$790,$A47,'Transaction Overview'!$H$2:$H$790,H$4) -> 0 | I47: =SUMIFS('Transaction Overview'!$D$2:$D$790,'Transaction Overview'!$I$2:$I$790,$A47,'Transaction Overview'!$H$2:$H$790,I$4) -> 0 | ... M47: =SUMIFS('Transaction Overview'!$D$2:$D$790,'Transaction Overview'!$I$2:$I$790,$A47,'Transaction Overview'!$H$2:$H$790,M$4) -> 0 | N47: =SUM(B47:M47) -> -6000
A48: Wire to Top Shield Roofing CO | B48: =SUMIFS('Transaction Overview'!$D$2:$D$790,'Transaction Overview'!$I$2:$I$790,$A48,'Transaction Overview'!$H$2:$H$790,B$4) -> 0 | C48: =SUMIFS('Transaction Overview'!$D$2:$D$790,'Transaction Overview'!$I$2:$I$790,$A48,'Transaction Overview'!$H$2:$H$790,C$4) -> 0 | D48: =SUMIFS('Transaction Overview'!$D$2:$D$790,'Transaction Overview'!$I$2:$I$790,$A48,'Transaction Overview'!$H$2:$H$790,D$4) -> 0 | E48: =SUMIFS('Transaction Overview'!$D$2:$D$790,'Transaction Overview'!$I$2:$I$790,$A48,'Transaction Overview'!$H$2:$H$790,E$4) -> 0 | F48: =SUMIFS('Transaction Overview'!$D$2:$D$790,'Transaction Overview'!$I$2:$I$790,$A48,'Transaction Overview'!$H$2:$H$790,F$4) -> 0 | G48: =SUMIFS('Transaction Overview'!$D$2:$D$790,'Transaction Overview'!$I$2:$I$790,$A48,'Transaction Overview'!$H$2:$H$790,G$4) -> 0 | H48: =SUMIFS('Transaction Overview'!$D$2:$D$790,'Transaction Overview'!$I$2:$I$790,$A48,'Transaction Overview'!$H$2:$H$790,H$4) -> 0 | I48: =SUMIFS('Transaction Overview'!$D$2:$D$790,'Transaction Overview'!$I$2:$I$790,$A48,'Transaction Overview'!$H$2:$H$790,I$4) -> 0 | ... M48: =SUMIFS('Transaction Overview'!$D$2:$D$790,'Transaction Overview'!$I$2:$I$790,$A48,'Transaction Overview'!$H$2:$H$790,M$4) -> -15500 | N48: =SUM(B48:M48) -> -15500
A49: Subtotal — Wire Transfers — Outgoing | B49: =SUMIFS('Transaction Overview'!$D$2:$D$790,'Transaction Overview'!$J$2:$J$790,"Wire Transfers — Outgoing",'Transaction Overview'!$H$2:$H$790,B$4) -> 0 | C49: =SUMIFS('Transaction Overview'!$D$2:$D$790,'Transaction Overview'!$J$2:$J$790,"Wire Transfers — Outgoing",'Transaction Overview'!$H$2:$H$790,C$4) -> 0 | D49: =SUMIFS('Transaction Overview'!$D$2:$D$790,'Transaction Overview'!$J$2:$J$790,"Wire Transfers — Outgoing",'Transaction Overview'!$H$2:$H$790,D$4) -> -6000 | E49: =SUMIFS('Transaction Overview'!$D$2:$D$790,'Transaction Overview'!$J$2:$J$790,"Wire Transfers — Outgoing",'Transaction Overview'!$H$2:$H$790,E$4) -> 0 | F49: =SUMIFS('Transaction Overview'!$D$2:$D$790,'Transaction Overview'!$J$2:$J$790,"Wire Transfers — Outgoing",'Transaction Overview'!$H$2:$H$790,F$4) -> 0 | G49: =SUMIFS('Transaction Overview'!$D$2:$D$790,'Transaction Overview'!$J$2:$J$790,"Wire Transfers — Outgoing",'Transaction Overview'!$H$2:$H$790,G$4) -> -100000 | H49: =SUMIFS('Transaction Overview'!$D$2:$D$790,'Transaction Overview'!$J$2:$J$790,"Wire Transfers — Outgoing",'Transaction Overview'!$H$2:$H$790,H$4) -> 0 | I49: =SUMIFS('Transaction Overview'!$D$2:$D$790,'Transaction Overview'!$J$2:$J$790,"Wire Transfers — Outgoing",'Transaction Overview'!$H$2:$H$790,I$4) -> -25000 | ... M49: =SUMIFS('Transaction Overview'!$D$2:$D$790,'Transaction Overview'!$J$2:$J$790,"Wire Transfers — Outgoing",'Transaction Overview'!$H$2:$H$790,M$4) -> -25500 | N49: =SUM(B49:M49) -> -156500
A51: Intercompany & Savings Transfers
A52: Transfer from Breese | B52: =SUMIFS('Transaction Overview'!$D$2:$D$790,'Transaction Overview'!$I$2:$I$790,$A52,'Transaction Overview'!$H$2:$H$790,B$4) -> 0 | C52: =SUMIFS('Transaction Overview'!$D$2:$D$790,'Transaction Overview'!$I$2:$I$790,$A52,'Transaction Overview'!$H$2:$H$790,C$4) -> 0 | D52: =SUMIFS('Transaction Overview'!$D$2:$D$790,'Transaction Overview'!$I$2:$I$790,$A52,'Transaction Overview'!$H$2:$H$790,D$4) -> 0 | E52: =SUMIFS('Transaction Overview'!$D$2:$D$790,'Transaction Overview'!$I$2:$I$790,$A52,'Transaction Overview'!$H$2:$H$790,E$4) -> 0 | F52: =SUMIFS('Transaction Overview'!$D$2:$D$790,'Transaction Overview'!$I$2:$I$790,$A52,'Transaction Overview'!$H$2:$H$790,F$4) -> 0 | G52: =SUMIFS('Transaction Overview'!$D$2:$D$790,'Transaction Overview'!$I$2:$I$790,$A52,'Transaction Overview'!$H$2:$H$790,G$4) -> 0 | H52: =SUMIFS('Transaction Overview'!$D$2:$D$790,'Transaction Overview'!$I$2:$I$790,$A52,'Transaction Overview'!$H$2:$H$790,H$4) -> 100000 | I52: =SUMIFS('Transaction Overview'!$D$2:$D$790,'Transaction Overview'!$I$2:$I$790,$A52,'Transaction Overview'!$H$2:$H$790,I$4) -> 0 | ... M52: =SUMIFS('Transaction Overview'!$D$2:$D$790,'Transaction Overview'!$I$2:$I$790,$A52,'Transaction Overview'!$H$2:$H$790,M$4) -> 0 | N52: =SUM(B52:M52) -> 150000
A53: Transfer from DWG Capital Partners | B53: =SUMIFS('Transaction Overview'!$D$2:$D$790,'Transaction Overview'!$I$2:$I$790,$A53,'Transaction Overview'!$H$2:$H$790,B$4) -> 0 | C53: =SUMIFS('Transaction Overview'!$D$2:$D$790,'Transaction Overview'!$I$2:$I$790,$A53,'Transaction Overview'!$H$2:$H$790,C$4) -> 0 | D53: =SUMIFS('Transaction Overview'!$D$2:$D$790,'Transaction Overview'!$I$2:$I$790,$A53,'Transaction Overview'!$H$2:$H$790,D$4) -> 0 | E53: =SUMIFS('Transaction Overview'!$D$2:$D$790,'Transaction Overview'!$I$2:$I$790,$A53,'Transaction Overview'!$H$2:$H$790,E$4) -> 0 | F53: =SUMIFS('Transaction Overview'!$D$2:$D$790,'Transaction Overview'!$I$2:$I$790,$A53,'Transaction Overview'!$H$2:$H$790,F$4) -> 0 | G53: =SUMIFS('Transaction Overview'!$D$2:$D$790,'Transaction Overview'!$I$2:$I$790,$A53,'Transaction Overview'!$H$2:$H$790,G$4) -> 0 | H53: =SUMIFS('Transaction Overview'!$D$2:$D$790,'Transaction Overview'!$I$2:$I$790,$A53,'Transaction Overview'!$H$2:$H$790,H$4) -> 0 | I53: =SUMIFS('Transaction Overview'!$D$2:$D$790,'Transaction Overview'!$I$2:$I$790,$A53,'Transaction Overview'!$H$2:$H$790,I$4) -> 0 | ... M53: =SUMIFS('Transaction Overview'!$D$2:$D$790,'Transaction Overview'!$I$2:$I$790,$A53,'Transaction Overview'!$H$2:$H$790,M$4) -> 113350 | N53: =SUM(B53:M53) -> 383350
A54: Transfer from Hibbert | B54: =SUMIFS('Transaction Overview'!$D$2:$D$790,'Transaction Overview'!$I$2:$I$790,$A54,'Transaction Overview'!$H$2:$H$790,B$4) -> 0 | C54: =SUMIFS('Transaction Overview'!$D$2:$D$790,'Transaction Overview'!$I$2:$I$790,$A54,'Transaction Overview'!$H$2:$H$790,C$4) -> 0 | D54: =SUMIFS('Transaction Overview'!$D$2:$D$790,'Transaction Overview'!$I$2:$I$790,$A54,'Transaction Overview'!$H$2:$H$790,D$4) -> 0 | E54: =SUMIFS('Transaction Overview'!$D$2:$D$790,'Transaction Overview'!$I$2:$I$790,$A54,'Transaction Overview'!$H$2:$H$790,E$4) -> 0 | F54: =SUMIFS('Transaction Overview'!$D$2:$D$790,'Transaction Overview'!$I$2:$I$790,$A54,'Transaction Overview'!$H$2:$H$790,F$4) -> 17500 | G54: =SUMIFS('Transaction Overview'!$D$2:$D$790,'Transaction Overview'!$I$2:$I$790,$A54,'Transaction Overview'!$H$2:$H$790,G$4) -> 0 | H54: =SUMIFS('Transaction Overview'!$D$2:$D$790,'Transaction Overview'!$I$2:$I$790,$A54,'Transaction Overview'!$H$2:$H$790,H$4) -> 0 | I54: =SUMIFS('Transaction Overview'!$D$2:$D$790,'Transaction Overview'!$I$2:$I$790,$A54,'Transaction Overview'!$H$2:$H$790,I$4) -> 0 | ... M54: =SUMIFS('Transaction Overview'!$D$2:$D$790,'Transaction Overview'!$I$2:$I$790,$A54,'Transaction Overview'!$H$2:$H$790,M$4) -> 100000 | N54: =SUM(B54:M54) -> 117500
A55: Transfer from Kalkaska Screw | B55: =SUMIFS('Transaction Overview'!$D$2:$D$790,'Transaction Overview'!$I$2:$I$790,$A55,'Transaction Overview'!$H$2:$H$790,B$4) -> 0 | C55: =SUMIFS('Transaction Overview'!$D$2:$D$790,'Transaction Overview'!$I$2:$I$790,$A55,'Transaction Overview'!$H$2:$H$790,C$4) -> 0 | D55: =SUMIFS('Transaction Overview'!$D$2:$D$790,'Transaction Overview'!$I$2:$I$790,$A55,'Transaction Overview'!$H$2:$H$790,D$4) -> 0 | E55: =SUMIFS('Transaction Overview'!$D$2:$D$790,'Transaction Overview'!$I$2:$I$790,$A55,'Transaction Overview'!$H$2:$H$790,E$4) -> 50000 | F55: =SUMIFS('Transaction Overview'!$D$2:$D$790,'Transaction Overview'!$I$2:$I$790,$A55,'Transaction Overview'!$H$2:$H$790,F$4) -> 0 | G55: =SUMIFS('Transaction Overview'!$D$2:$D$790,'Transaction Overview'!$I$2:$I$790,$A55,'Transaction Overview'!$H$2:$H$790,G$4) -> 0 | H55: =SUMIFS('Transaction Overview'!$D$2:$D$790,'Transaction Overview'!$I$2:$I$790,$A55,'Transaction Overview'!$H$2:$H$790,H$4) -> 0 | I55: =SUMIFS('Transaction Overview'!$D$2:$D$790,'Transaction Overview'!$I$2:$I$790,$A55,'Transaction Overview'!$H$2:$H$790,I$4) -> 0 | ... M55: =SUMIFS('Transaction Overview'!$D$2:$D$790,'Transaction Overview'!$I$2:$I$790,$A55,'Transaction Overview'!$H$2:$H$790,M$4) -> 0 | N55: =SUM(B55:M55) -> 62800
A56: Transfer to DWG Capital Group | B56: =SUMIFS('Transaction Overview'!$D$2:$D$790,'Transaction Overview'!$I$2:$I$790,$A56,'Transaction Overview'!$H$2:$H$790,B$4) -> -30000 | C56: =SUMIFS('Transaction Overview'!$D$2:$D$790,'Transaction Overview'!$I$2:$I$790,$A56,'Transaction Overview'!$H$2:$H$790,C$4) -> -50000 | D56: =SUMIFS('Transaction Overview'!$D$2:$D$790,'Transaction Overview'!$I$2:$I$790,$A56,'Transaction Overview'!$H$2:$H$790,D$4) -> -105000 | E56: =SUMIFS('Transaction Overview'!$D$2:$D$790,'Transaction Overview'!$I$2:$I$790,$A56,'Transaction Overview'!$H$2:$H$790,E$4) -> -30000 | F56: =SUMIFS('Transaction Overview'!$D$2:$D$790,'Transaction Overview'!$I$2:$I$790,$A56,'Transaction Overview'!$H$2:$H$790,F$4) -> -40000 | G56: =SUMIFS('Transaction Overview'!$D$2:$D$790,'Transaction Overview'!$I$2:$I$790,$A56,'Transaction Overview'!$H$2:$H$790,G$4) -> -63000 | H56: =SUMIFS('Transaction Overview'!$D$2:$D$790,'Transaction Overview'!$I$2:$I$790,$A56,'Transaction Overview'!$H$2:$H$790,H$4) -> -80000 | I56: =SUMIFS('Transaction Overview'!$D$2:$D$790,'Transaction Overview'!$I$2:$I$790,$A56,'Transaction Overview'!$H$2:$H$790,I$4) -> -30000 | ... M56: =SUMIFS('Transaction Overview'!$D$2:$D$790,'Transaction Overview'!$I$2:$I$790,$A56,'Transaction Overview'!$H$2:$H$790,M$4) -> -50000 | N56: =SUM(B56:M56) -> -678000
A57: Transfer to DWG Capital Group_Costar | B57: =SUMIFS('Transaction Overview'!$D$2:$D$790,'Transaction Overview'!$I$2:$I$790,$A57,'Transaction Overview'!$H$2:$H$790,B$4) -> 0 | C57: =SUMIFS('Transaction Overview'!$D$2:$D$790,'Transaction Overview'!$I$2:$I$790,$A57,'Transaction Overview'!$H$2:$H$790,C$4) -> 0 | D57: =SUMIFS('Transaction Overview'!$D$2:$D$790,'Transaction Overview'!$I$2:$I$790,$A57,'Transaction Overview'!$H$2:$H$790,D$4) -> 0 | E57: =SUMIFS('Transaction Overview'!$D$2:$D$790,'Transaction Overview'!$I$2:$I$790,$A57,'Transaction Overview'!$H$2:$H$790,E$4) -> 0 | F57: =SUMIFS('Transaction Overview'!$D$2:$D$790,'Transaction Overview'!$I$2:$I$790,$A57,'Transaction Overview'!$H$2:$H$790,F$4) -> 0 | G57: =SUMIFS('Transaction Overview'!$D$2:$D$790,'Transaction Overview'!$I$2:$I$790,$A57,'Transaction Overview'!$H$2:$H$790,G$4) -> 0 | H57: =SUMIFS('Transaction Overview'!$D$2:$D$790,'Transaction Overview'!$I$2:$I$790,$A57,'Transaction Overview'!$H$2:$H$790,H$4) -> 0 | I57: =SUMIFS('Transaction Overview'!$D$2:$D$790,'Transaction Overview'!$I$2:$I$790,$A57,'Transaction Overview'!$H$2:$H$790,I$4) -> 0 | ... M57: =SUMIFS('Transaction Overview'!$D$2:$D$790,'Transaction Overview'!$I$2:$I$790,$A57,'Transaction Overview'!$H$2:$H$790,M$4) -> -1300 | N57: =SUM(B57:M57) -> -6450
A58: Transfer to DWG Capital Partners | B58: =SUMIFS('Transaction Overview'!$D$2:$D$790,'Transaction Overview'!$I$2:$I$790,$A58,'Transaction Overview'!$H$2:$H$790,B$4) -> 0 | C58: =SUMIFS('Transaction Overview'!$D$2:$D$790,'Transaction Overview'!$I$2:$I$790,$A58,'Transaction Overview'!$H$2:$H$790,C$4) -> 0 | D58: =SUMIFS('Transaction Overview'!$D$2:$D$790,'Transaction Overview'!$I$2:$I$790,$A58,'Transaction Overview'!$H$2:$H$790,D$4) -> -40000 | E58: =SUMIFS('Transaction Overview'!$D$2:$D$790,'Transaction Overview'!$I$2:$I$790,$A58,'Transaction Overview'!$H$2:$H$790,E$4) -> -30000 | F58: =SUMIFS('Transaction Overview'!$D$2:$D$790,'Transaction Overview'!$I$2:$I$790,$A58,'Transaction Overview'!$H$2:$H$790,F$4) -> 0 | G58: =SUMIFS('Transaction Overview'!$D$2:$D$790,'Transaction Overview'!$I$2:$I$790,$A58,'Transaction Overview'!$H$2:$H$790,G$4) -> -20000 | H58: =SUMIFS('Transaction Overview'!$D$2:$D$790,'Transaction Overview'!$I$2:$I$790,$A58,'Transaction Overview'!$H$2:$H$790,H$4) -> -65000 | I58: =SUMIFS('Transaction Overview'!$D$2:$D$790,'Transaction Overview'!$I$2:$I$790,$A58,'Transaction Overview'!$H$2:$H$790,I$4) -> -20000 | ... M58: =SUMIFS('Transaction Overview'!$D$2:$D$790,'Transaction Overview'!$I$2:$I$790,$A58,'Transaction Overview'!$H$2:$H$790,M$4) -> -26500 | N58: =SUM(B58:M58) -> -271500
A59: Transfer to Edgebuilders | B59: =SUMIFS('Transaction Overview'!$D$2:$D$790,'Transaction Overview'!$I$2:$I$790,$A59,'Transaction Overview'!$H$2:$H$790,B$4) -> -50000 | C59: =SUMIFS('Transaction Overview'!$D$2:$D$790,'Transaction Overview'!$I$2:$I$790,$A59,'Transaction Overview'!$H$2:$H$790,C$4) -> 0 | D59: =SUMIFS('Transaction Overview'!$D$2:$D$790,'Transaction Overview'!$I$2:$I$790,$A59,'Transaction Overview'!$H$2:$H$790,D$4) -> 0 | E59: =SUMIFS('Transaction Overview'!$D$2:$D$790,'Transaction Overview'!$I$2:$I$790,$A59,'Transaction Overview'!$H$2:$H$790,E$4) -> 0 | F59: =SUMIFS('Transaction Overview'!$D$2:$D$790,'Transaction Overview'!$I$2:$I$790,$A59,'Transaction Overview'!$H$2:$H$790,F$4) -> 0 | G59: =SUMIFS('Transaction Overview'!$D$2:$D$790,'Transaction Overview'!$I$2:$I$790,$A59,'Transaction Overview'!$H$2:$H$790,G$4) -> 0 | H59: =SUMIFS('Transaction Overview'!$D$2:$D$790,'Transaction Overview'!$I$2:$I$790,$A59,'Transaction Overview'!$H$2:$H$790,H$4) -> 0 | I59: =SUMIFS('Transaction Overview'!$D$2:$D$790,'Transaction Overview'!$I$2:$I$790,$A59,'Transaction Overview'!$H$2:$H$790,I$4) -> 0 | ... M59: =SUMIFS('Transaction Overview'!$D$2:$D$790,'Transaction Overview'!$I$2:$I$790,$A59,'Transaction Overview'!$H$2:$H$790,M$4) -> 0 | N59: =SUM(B59:M59) -> -50000
A60: Transfer to Hibbert | B60: =SUMIFS('Transaction Overview'!$D$2:$D$790,'Transaction Overview'!$I$2:$I$790,$A60,'Transaction Overview'!$H$2:$H$790,B$4) -> 0 | C60: =SUMIFS('Transaction Overview'!$D$2:$D$790,'Transaction Overview'!$I$2:$I$790,$A60,'Transaction Overview'!$H$2:$H$790,C$4) -> 0 | D60: =SUMIFS('Transaction Overview'!$D$2:$D$790,'Transaction Overview'!$I$2:$I$790,$A60,'Transaction Overview'!$H$2:$H$790,D$4) -> 0 | E60: =SUMIFS('Transaction Overview'!$D$2:$D$790,'Transaction Overview'!$I$2:$I$790,$A60,'Transaction Overview'!$H$2:$H$790,E$4) -> 0 | F60: =SUMIFS('Transaction Overview'!$D$2:$D$790,'Transaction Overview'!$I$2:$I$790,$A60,'Transaction Overview'!$H$2:$H$790,F$4) -> -17500 | G60: =SUMIFS('Transaction Overview'!$D$2:$D$790,'Transaction Overview'!$I$2:$I$790,$A60,'Transaction Overview'!$H$2:$H$790,G$4) -> 0 | H60: =SUMIFS('Transaction Overview'!$D$2:$D$790,'Transaction Overview'!$I$2:$I$790,$A60,'Transaction Overview'!$H$2:$H$790,H$4) -> 0 | I60: =SUMIFS('Transaction Overview'!$D$2:$D$790,'Transaction Overview'!$I$2:$I$790,$A60,'Transaction Overview'!$H$2:$H$790,I$4) -> 0 | ... M60: =SUMIFS('Transaction Overview'!$D$2:$D$790,'Transaction Overview'!$I$2:$I$790,$A60,'Transaction Overview'!$H$2:$H$790,M$4) -> -28000 | N60: =SUM(B60:M60) -> -50918.73
A61: Transfer to JAL Southbend | B61: =SUMIFS('Transaction Overview'!$D$2:$D$790,'Transaction Overview'!$I$2:$I$790,$A61,'Transaction Overview'!$H$2:$H$790,B$4) -> 0 | C61: =SUMIFS('Transaction Overview'!$D$2:$D$790,'Transaction Overview'!$I$2:$I$790,$A61,'Transaction Overview'!$H$2:$H$790,C$4) -> 0 | D61: =SUMIFS('Transaction Overview'!$D$2:$D$790,'Transaction Overview'!$I$2:$I$790,$A61,'Transaction Overview'!$H$2:$H$790,D$4) -> 0 | E61: =SUMIFS('Transaction Overview'!$D$2:$D$790,'Transaction Overview'!$I$2:$I$790,$A61,'Transaction Overview'!$H$2:$H$790,E$4) -> 0 | F61: =SUMIFS('Transaction Overview'!$D$2:$D$790,'Transaction Overview'!$I$2:$I$790,$A61,'Transaction Overview'!$H$2:$H$790,F$4) -> 0 | G61: =SUMIFS('Transaction Overview'!$D$2:$D$790,'Transaction Overview'!$I$2:$I$790,$A61,'Transaction Overview'!$H$2:$H$790,G$4) -> 0 | H61: =SUMIFS('Transaction Overview'!$D$2:$D$790,'Transaction Overview'!$I$2:$I$790,$A61,'Transaction Overview'!$H$2:$H$790,H$4) -> -10000 | I61: =SUMIFS('Transaction Overview'!$D$2:$D$790,'Transaction Overview'!$I$2:$I$790,$A61,'Transaction Overview'!$H$2:$H$790,I$4) -> 0 | ... M61: =SUMIFS('Transaction Overview'!$D$2:$D$790,'Transaction Overview'!$I$2:$I$790,$A61,'Transaction Overview'!$H$2:$H$790,M$4) -> -47349 | N61: =SUM(B61:M61) -> -57349
A62: Transfer to Kalkaska Screw | B62: =SUMIFS('Transaction Overview'!$D$2:$D$790,'Transaction Overview'!$I$2:$I$790,$A62,'Transaction Overview'!$H$2:$H$790,B$4) -> 0 | C62: =SUMIFS('Transaction Overview'!$D$2:$D$790,'Transaction Overview'!$I$2:$I$790,$A62,'Transaction Overview'!$H$2:$H$790,C$4) -> 0 | D62: =SUMIFS('Transaction Overview'!$D$2:$D$790,'Transaction Overview'!$I$2:$I$790,$A62,'Transaction Overview'!$H$2:$H$790,D$4) -> 0 | E62: =SUMIFS('Transaction Overview'!$D$2:$D$790,'Transaction Overview'!$I$2:$I$790,$A62,'Transaction Overview'!$H$2:$H$790,E$4) -> 0 | F62: =SUMIFS('Transaction Overview'!$D$2:$D$790,'Transaction Overview'!$I$2:$I$790,$A62,'Transaction Overview'!$H$2:$H$790,F$4) -> 0 | G62: =SUMIFS('Transaction Overview'!$D$2:$D$790,'Transaction Overview'!$I$2:$I$790,$A62,'Transaction Overview'!$H$2:$H$790,G$4) -> 0 | H62: =SUMIFS('Transaction Overview'!$D$2:$D$790,'Transaction Overview'!$I$2:$I$790,$A62,'Transaction Overview'!$H$2:$H$790,H$4) -> 0 | I62: =SUMIFS('Transaction Overview'!$D$2:$D$790,'Transaction Overview'!$I$2:$I$790,$A62,'Transaction Overview'!$H$2:$H$790,I$4) -> 0 | ... M62: =SUMIFS('Transaction Overview'!$D$2:$D$790,'Transaction Overview'!$I$2:$I$790,$A62,'Transaction Overview'!$H$2:$H$790,M$4) -> 0 | N62: =SUM(B62:M62) -> -12800
A63: Transfer to Kecy Metals | B63: =SUMIFS('Transaction Overview'!$D$2:$D$790,'Transaction Overview'!$I$2:$I$790,$A63,'Transaction Overview'!$H$2:$H$790,B$4) -> 0 | C63: =SUMIFS('Transaction Overview'!$D$2:$D$790,'Transaction Overview'!$I$2:$I$790,$A63,'Transaction Overview'!$H$2:$H$790,C$4) -> 0 | D63: =SUMIFS('Transaction Overview'!$D$2:$D$790,'Transaction Overview'!$I$2:$I$790,$A63,'Transaction Overview'!$H$2:$H$790,D$4) -> 0 | E63: =SUMIFS('Transaction Overview'!$D$2:$D$790,'Transaction Overview'!$I$2:$I$790,$A63,'Transaction Overview'!$H$2:$H$790,E$4) -> 0 | F63: =SUMIFS('Transaction Overview'!$D$2:$D$790,'Transaction Overview'!$I$2:$I$790,$A63,'Transaction Overview'!$H$2:$H$790,F$4) -> 0 | G63: =SUMIFS('Transaction Overview'!$D$2:$D$790,'Transaction Overview'!$I$2:$I$790,$A63,'Transaction Overview'!$H$2:$H$790,G$4) -> 0 | H63: =SUMIFS('Transaction Overview'!$D$2:$D$790,'Transaction Overview'!$I$2:$I$790,$A63,'Transaction Overview'!$H$2:$H$790,H$4) -> 0 | I63: =SUMIFS('Transaction Overview'!$D$2:$D$790,'Transaction Overview'!$I$2:$I$790,$A63,'Transaction Overview'!$H$2:$H$790,I$4) -> 0 | ... M63: =SUMIFS('Transaction Overview'!$D$2:$D$790,'Transaction Overview'!$I$2:$I$790,$A63,'Transaction Overview'!$H$2:$H$790,M$4) -> -17000 | N63: =SUM(B63:M63) -> -17000
... A65: Transfer to T&T Machine | B65: =SUMIFS('Transaction Overview'!$D$2:$D$790,'Transaction Overview'!$I$2:$I$790,$A65,'Transaction Overview'!$H$2:$H$790,B$4) -> 0 | C65: =SUMIFS('Transaction Overview'!$D$2:$D$790,'Transaction Overview'!$I$2:$I$790,$A65,'Transaction Overview'!$H$2:$H$790,C$4) -> 0 | D65: =SUMIFS('Transaction Overview'!$D$2:$D$790,'Transaction Overview'!$I$2:$I$790,$A65,'Transaction Overview'!$H$2:$H$790,D$4) -> 0 | E65: =SUMIFS('Transaction Overview'!$D$2:$D$790,'Transaction Overview'!$I$2:$I$790,$A65,'Transaction Overview'!$H$2:$H$790,E$4) -> 0 | F65: =SUMIFS('Transaction Overview'!$D$2:$D$790,'Transaction Overview'!$I$2:$I$790,$A65,'Transaction Overview'!$H$2:$H$790,F$4) -> 0 | G65: =SUMIFS('Transaction Overview'!$D$2:$D$790,'Transaction Overview'!$I$2:$I$790,$A65,'Transaction Overview'!$H$2:$H$790,G$4) -> -20000 | H65: =SUMIFS('Transaction Overview'!$D$2:$D$790,'Transaction Overview'!$I$2:$I$790,$A65,'Transaction Overview'!$H$2:$H$790,H$4) -> 0 | I65: =SUMIFS('Transaction Overview'!$D$2:$D$790,'Transaction Overview'!$I$2:$I$790,$A65,'Transaction Overview'!$H$2:$H$790,I$4) -> 0 | ... M65: =SUMIFS('Transaction Overview'!$D$2:$D$790,'Transaction Overview'!$I$2:$I$790,$A65,'Transaction Overview'!$H$2:$H$790,M$4) -> 0 | N65: =SUM(B65:M65) -> -20000
A66: Subtotal — Intercompany & Savings Transfers | B66: =SUMIFS('Transaction Overview'!$D$2:$D$790,'Transaction Overview'!$J$2:$J$790,"Intercompany & Savings Transfers",'Transaction Overview'!$H$2:$H$790,B$4) -> -80000 | C66: =SUMIFS('Transaction Overview'!$D$2:$D$790,'Transaction Overview'!$J$2:$J$790,"Intercompany & Savings Transfers",'Transaction Overview'!$H$2:$H$790,C$4) -> -50000 | D66: =SUMIFS('Transaction Overview'!$D$2:$D$790,'Transaction Overview'!$J$2:$J$790,"Intercompany & Savings Transfers",'Transaction Overview'!$H$2:$H$790,D$4) -> -145000 | E66: =SUMIFS('Transaction Overview'!$D$2:$D$790,'Transaction Overview'!$J$2:$J$790,"Intercompany & Savings Transfers",'Transaction Overview'!$H$2:$H$790,E$4) -> -10000 | F66: =SUMIFS('Transaction Overview'!$D$2:$D$790,'Transaction Overview'!$J$2:$J$790,"Intercompany & Savings Transfers",'Transaction Overview'!$H$2:$H$790,F$4) -> -40000 | G66: =SUMIFS('Transaction Overview'!$D$2:$D$790,'Transaction Overview'!$J$2:$J$790,"Intercompany & Savings Transfers",'Transaction Overview'!$H$2:$H$790,G$4) -> -103000 | H66: =SUMIFS('Transaction Overview'!$D$2:$D$790,'Transaction Overview'!$J$2:$J$790,"Intercompany & Savings Transfers",'Transaction Overview'!$H$2:$H$790,H$4) -> -55000 | I66: =SUMIFS('Transaction Overview'!$D$2:$D$790,'Transaction Overview'!$J$2:$J$790,"Intercompany & Savings Transfers",'Transaction Overview'!$H$2:$H$790,I$4) -> -50000 | ... M66: =SUMIFS('Transaction Overview'!$D$2:$D$790,'Transaction Overview'!$J$2:$J$790,"Intercompany & Savings Transfers",'Transaction Overview'!$H$2:$H$790,M$4) -> 43201 | N66: =SUM(B66:M66) -> -425367.73
A68: Owner / Family Distributions
A69: Transfer to Angela Dunning | B69: =SUMIFS('Transaction Overview'!$D$2:$D$790,'Transaction Overview'!$I$2:$I$790,$A69,'Transaction Overview'!$H$2:$H$790,B$4) -> 0 | C69: =SUMIFS('Transaction Overview'!$D$2:$D$790,'Transaction Overview'!$I$2:$I$790,$A69,'Transaction Overview'!$H$2:$H$790,C$4) -> 0 | D69: =SUMIFS('Transaction Overview'!$D$2:$D$790,'Transaction Overview'!$I$2:$I$790,$A69,'Transaction Overview'!$H$2:$H$790,D$4) -> 0 | E69: =SUMIFS('Transaction Overview'!$D$2:$D$790,'Transaction Overview'!$I$2:$I$790,$A69,'Transaction Overview'!$H$2:$H$790,E$4) -> 0 | F69: =SUMIFS('Transaction Overview'!$D$2:$D$790,'Transaction Overview'!$I$2:$I$790,$A69,'Transaction Overview'!$H$2:$H$790,F$4) -> -1000 | G69: =SUMIFS('Transaction Overview'!$D$2:$D$790,'Transaction Overview'!$I$2:$I$790,$A69,'Transaction Overview'!$H$2:$H$790,G$4) -> 0 | H69: =SUMIFS('Transaction Overview'!$D$2:$D$790,'Transaction Overview'!$I$2:$I$790,$A69,'Transaction Overview'!$H$2:$H$790,H$4) -> 0 | I69: =SUMIFS('Transaction Overview'!$D$2:$D$790,'Transaction Overview'!$I$2:$I$790,$A69,'Transaction Overview'!$H$2:$H$790,I$4) -> 0 | ... M69: =SUMIFS('Transaction Overview'!$D$2:$D$790,'Transaction Overview'!$I$2:$I$790,$A69,'Transaction Overview'!$H$2:$H$790,M$4) -> 0 | N69: =SUM(B69:M69) -> -1000
A70: Transfer to Ava | B70: =SUMIFS('Transaction Overview'!$D$2:$D$790,'Transaction Overview'!$I$2:$I$790,$A70,'Transaction Overview'!$H$2:$H$790,B$4) -> 0 | C70: =SUMIFS('Transaction Overview'!$D$2:$D$790,'Transaction Overview'!$I$2:$I$790,$A70,'Transaction Overview'!$H$2:$H$790,C$4) -> 0 | D70: =SUMIFS('Transaction Overview'!$D$2:$D$790,'Transaction Overview'!$I$2:$I$790,$A70,'Transaction Overview'!$H$2:$H$790,D$4) -> 0 | E70: =SUMIFS('Transaction Overview'!$D$2:$D$790,'Transaction Overview'!$I$2:$I$790,$A70,'Transaction Overview'!$H$2:$H$790,E$4) -> 0 | F70: =SUMIFS('Transaction Overview'!$D$2:$D$790,'Transaction Overview'!$I$2:$I$790,$A70,'Transaction Overview'!$H$2:$H$790,F$4) -> 0 | G70: =SUMIFS('Transaction Overview'!$D$2:$D$790,'Transaction Overview'!$I$2:$I$790,$A70,'Transaction Overview'!$H$2:$H$790,G$4) -> 0 | H70: =SUMIFS('Transaction Overview'!$D$2:$D$790,'Transaction Overview'!$I$2:$I$790,$A70,'Transaction Overview'!$H$2:$H$790,H$4) -> 0 | I70: =SUMIFS('Transaction Overview'!$D$2:$D$790,'Transaction Overview'!$I$2:$I$790,$A70,'Transaction Overview'!$H$2:$H$790,I$4) -> 0 | ... M70: =SUMIFS('Transaction Overview'!$D$2:$D$790,'Transaction Overview'!$I$2:$I$790,$A70,'Transaction Overview'!$H$2:$H$790,M$4) -> 0 | N70: =SUM(B70:M70) -> -500
A71: Subtotal — Owner / Family Distributions | B71: =SUMIFS('Transaction Overview'!$D$2:$D$790,'Transaction Overview'!$J$2:$J$790,"Owner / Family Distributions",'Transaction Overview'!$H$2:$H$790,B$4) -> 0 | C71: =SUMIFS('Transaction Overview'!$D$2:$D$790,'Transaction Overview'!$J$2:$J$790,"Owner / Family Distributions",'Transaction Overview'!$H$2:$H$790,C$4) -> 0 | D71: =SUMIFS('Transaction Overview'!$D$2:$D$790,'Transaction Overview'!$J$2:$J$790,"Owner / Family Distributions",'Transaction Overview'!$H$2:$H$790,D$4) -> 0 | E71: =SUMIFS('Transaction Overview'!$D$2:$D$790,'Transaction Overview'!$J$2:$J$790,"Owner / Family Distributions",'Transaction Overview'!$H$2:$H$790,E$4) -> 0 | F71: =SUMIFS('Transaction Overview'!$D$2:$D$790,'Transaction Overview'!$J$2:$J$790,"Owner / Family Distributions",'Transaction Overview'!$H$2:$H$790,F$4) -> -1000 | G71: =SUMIFS('Transaction Overview'!$D$2:$D$790,'Transaction Overview'!$J$2:$J$790,"Owner / Family Distributions",'Transaction Overview'!$H$2:$H$790,G$4) -> 0 | H71: =SUMIFS('Transaction Overview'!$D$2:$D$790,'Transaction Overview'!$J$2:$J$790,"Owner / Family Distributions",'Transaction Overview'!$H$2:$H$790,H$4) -> 0 | I71: =SUMIFS('Transaction Overview'!$D$2:$D$790,'Transaction Overview'!$J$2:$J$790,"Owner / Family Distributions",'Transaction Overview'!$H$2:$H$790,I$4) -> 0 | ... M71: =SUMIFS('Transaction Overview'!$D$2:$D$790,'Transaction Overview'!$J$2:$J$790,"Owner / Family Distributions",'Transaction Overview'!$H$2:$H$790,M$4) -> 0 | N71: =SUM(B71:M71) -> -1500
A73: P2P Payments (Zelle/Venmo/PayPal)
A74: Apple Payment | B74: =SUMIFS('Transaction Overview'!$D$2:$D$790,'Transaction Overview'!$I$2:$I$790,$A74,'Transaction Overview'!$H$2:$H$790,B$4) -> 0 | C74: =SUMIFS('Transaction Overview'!$D$2:$D$790,'Transaction Overview'!$I$2:$I$790,$A74,'Transaction Overview'!$H$2:$H$790,C$4) -> 0 | D74: =SUMIFS('Transaction Overview'!$D$2:$D$790,'Transaction Overview'!$I$2:$I$790,$A74,'Transaction Overview'!$H$2:$H$790,D$4) -> -100 | E74: =SUMIFS('Transaction Overview'!$D$2:$D$790,'Transaction Overview'!$I$2:$I$790,$A74,'Transaction Overview'!$H$2:$H$790,E$4) -> 0 | F74: =SUMIFS('Transaction Overview'!$D$2:$D$790,'Transaction Overview'!$I$2:$I$790,$A74,'Transaction Overview'!$H$2:$H$790,F$4) -> 0 | G74: =SUMIFS('Transaction Overview'!$D$2:$D$790,'Transaction Overview'!$I$2:$I$790,$A74,'Transaction Overview'!$H$2:$H$790,G$4) -> 0 | H74: =SUMIFS('Transaction Overview'!$D$2:$D$790,'Transaction Overview'!$I$2:$I$790,$A74,'Transaction Overview'!$H$2:$H$790,H$4) -> 0 | I74: =SUMIFS('Transaction Overview'!$D$2:$D$790,'Transaction Overview'!$I$2:$I$790,$A74,'Transaction Overview'!$H$2:$H$790,I$4) -> 0 | ... M74: =SUMIFS('Transaction Overview'!$D$2:$D$790,'Transaction Overview'!$I$2:$I$790,$A74,'Transaction Overview'!$H$2:$H$790,M$4) -> -31 | N74: =SUM(B74:M74) -> -331
A75: Zelle to Ashley Sarshar | B75: =SUMIFS('Transaction Overview'!$D$2:$D$790,'Transaction Overview'!$I$2:$I$790,$A75,'Transaction Overview'!$H$2:$H$790,B$4) -> 0 | C75: =SUMIFS('Transaction Overview'!$D$2:$D$790,'Transaction Overview'!$I$2:$I$790,$A75,'Transaction Overview'!$H$2:$H$790,C$4) -> 0 | D75: =SUMIFS('Transaction Overview'!$D$2:$D$790,'Transaction Overview'!$I$2:$I$790,$A75,'Transaction Overview'!$H$2:$H$790,D$4) -> 0 | E75: =SUMIFS('Transaction Overview'!$D$2:$D$790,'Transaction Overview'!$I$2:$I$790,$A75,'Transaction Overview'!$H$2:$H$790,E$4) -> 0 | F75: =SUMIFS('Transaction Overview'!$D$2:$D$790,'Transaction Overview'!$I$2:$I$790,$A75,'Transaction Overview'!$H$2:$H$790,F$4) -> 0 | G75: =SUMIFS('Transaction Overview'!$D$2:$D$790,'Transaction Overview'!$I$2:$I$790,$A75,'Transaction Overview'!$H$2:$H$790,G$4) -> 0 | H75: =SUMIFS('Transaction Overview'!$D$2:$D$790,'Transaction Overview'!$I$2:$I$790,$A75,'Transaction Overview'!$H$2:$H$790,H$4) -> 0 | I75: =SUMIFS('Transaction Overview'!$D$2:$D$790,'Transaction Overview'!$I$2:$I$790,$A75,'Transaction Overview'!$H$2:$H$790,I$4) -> 0 | ... M75: =SUMIFS('Transaction Overview'!$D$2:$D$790,'Transaction Overview'!$I$2:$I$790,$A75,'Transaction Overview'!$H$2:$H$790,M$4) -> 0 | N75: =SUM(B75:M75) -> -247
A76: Zelle to David Goldsmith | B76: =SUMIFS('Transaction Overview'!$D$2:$D$790,'Transaction Overview'!$I$2:$I$790,$A76,'Transaction Overview'!$H$2:$H$790,B$4) -> 0 | C76: =SUMIFS('Transaction Overview'!$D$2:$D$790,'Transaction Overview'!$I$2:$I$790,$A76,'Transaction Overview'!$H$2:$H$790,C$4) -> 0 | D76: =SUMIFS('Transaction Overview'!$D$2:$D$790,'Transaction Overview'!$I$2:$I$790,$A76,'Transaction Overview'!$H$2:$H$790,D$4) -> 0 | E76: =SUMIFS('Transaction Overview'!$D$2:$D$790,'Transaction Overview'!$I$2:$I$790,$A76,'Transaction Overview'!$H$2:$H$790,E$4) -> 0 | F76: =SUMIFS('Transaction Overview'!$D$2:$D$790,'Transaction Overview'!$I$2:$I$790,$A76,'Transaction Overview'!$H$2:$H$790,F$4) -> 0 | G76: =SUMIFS('Transaction Overview'!$D$2:$D$790,'Transaction Overview'!$I$2:$I$790,$A76,'Transaction Overview'!$H$2:$H$790,G$4) -> 0 | H76: =SUMIFS('Transaction Overview'!$D$2:$D$790,'Transaction Overview'!$I$2:$I$790,$A76,'Transaction Overview'!$H$2:$H$790,H$4) -> 0 | I76: =SUMIFS('Transaction Overview'!$D$2:$D$790,'Transaction Overview'!$I$2:$I$790,$A76,'Transaction Overview'!$H$2:$H$790,I$4) -> 0 | ... M76: =SUMIFS('Transaction Overview'!$D$2:$D$790,'Transaction Overview'!$I$2:$I$790,$A76,'Transaction Overview'!$H$2:$H$790,M$4) -> 0 | N76: =SUM(B76:M76) -> -500
A77: Zelle to Mark Atkins | B77: =SUMIFS('Transaction Overview'!$D$2:$D$790,'Transaction Overview'!$I$2:$I$790,$A77,'Transaction Overview'!$H$2:$H$790,B$4) -> 0 | C77: =SUMIFS('Transaction Overview'!$D$2:$D$790,'Transaction Overview'!$I$2:$I$790,$A77,'Transaction Overview'!$H$2:$H$790,C$4) -> 0 | D77: =SUMIFS('Transaction Overview'!$D$2:$D$790,'Transaction Overview'!$I$2:$I$790,$A77,'Transaction Overview'!$H$2:$H$790,D$4) -> 0 | E77: =SUMIFS('Transaction Overview'!$D$2:$D$790,'Transaction Overview'!$I$2:$I$790,$A77,'Transaction Overview'!$H$2:$H$790,E$4) -> 0 | F77: =SUMIFS('Transaction Overview'!$D$2:$D$790,'Transaction Overview'!$I$2:$I$790,$A77,'Transaction Overview'!$H$2:$H$790,F$4) -> 0 | G77: =SUMIFS('Transaction Overview'!$D$2:$D$790,'Transaction Overview'!$I$2:$I$790,$A77,'Transaction Overview'!$H$2:$H$790,G$4) -> 0 | H77: =SUMIFS('Transaction Overview'!$D$2:$D$790,'Transaction Overview'!$I$2:$I$790,$A77,'Transaction Overview'!$H$2:$H$790,H$4) -> 0 | I77: =SUMIFS('Transaction Overview'!$D$2:$D$790,'Transaction Overview'!$I$2:$I$790,$A77,'Transaction Overview'!$H$2:$H$790,I$4) -> -500 | ... M77: =SUMIFS('Transaction Overview'!$D$2:$D$790,'Transaction Overview'!$I$2:$I$790,$A77,'Transaction Overview'!$H$2:$H$790,M$4) -> 0 | N77: =SUM(B77:M77) -> -500
A78: Zelle to Menashe | B78: =SUMIFS('Transaction Overview'!$D$2:$D$790,'Transaction Overview'!$I$2:$I$790,$A78,'Transaction Overview'!$H$2:$H$790,B$4) -> 0 | C78: =SUMIFS('Transaction Overview'!$D$2:$D$790,'Transaction Overview'!$I$2:$I$790,$A78,'Transaction Overview'!$H$2:$H$790,C$4) -> 0 | D78: =SUMIFS('Transaction Overview'!$D$2:$D$790,'Transaction Overview'!$I$2:$I$790,$A78,'Transaction Overview'!$H$2:$H$790,D$4) -> 0 | E78: =SUMIFS('Transaction Overview'!$D$2:$D$790,'Transaction Overview'!$I$2:$I$790,$A78,'Transaction Overview'!$H$2:$H$790,E$4) -> 0 | F78: =SUMIFS('Transaction Overview'!$D$2:$D$790,'Transaction Overview'!$I$2:$I$790,$A78,'Transaction Overview'!$H$2:$H$790,F$4) -> 0 | G78: =SUMIFS('Transaction Overview'!$D$2:$D$790,'Transaction Overview'!$I$2:$I$790,$A78,'Transaction Overview'!$H$2:$H$790,G$4) -> 0 | H78: =SUMIFS('Transaction Overview'!$D$2:$D$790,'Transaction Overview'!$I$2:$I$790,$A78,'Transaction Overview'!$H$2:$H$790,H$4) -> 0 | I78: =SUMIFS('Transaction Overview'!$D$2:$D$790,'Transaction Overview'!$I$2:$I$790,$A78,'Transaction Overview'!$H$2:$H$790,I$4) -> 0 | ... M78: =SUMIFS('Transaction Overview'!$D$2:$D$790,'Transaction Overview'!$I$2:$I$790,$A78,'Transaction Overview'!$H$2:$H$790,M$4) -> 0 | N78: =SUM(B78:M78) -> -750
A79: Zelle to Rami Frankl | B79: =SUMIFS('Transaction Overview'!$D$2:$D$790,'Transaction Overview'!$I$2:$I$790,$A79,'Transaction Overview'!$H$2:$H$790,B$4) -> 0 | C79: =SUMIFS('Transaction Overview'!$D$2:$D$790,'Transaction Overview'!$I$2:$I$790,$A79,'Transaction Overview'!$H$2:$H$790,C$4) -> 0 | D79: =SUMIFS('Transaction Overview'!$D$2:$D$790,'Transaction Overview'!$I$2:$I$790,$A79,'Transaction Overview'!$H$2:$H$790,D$4) -> 0 | E79: =SUMIFS('Transaction Overview'!$D$2:$D$790,'Transaction Overview'!$I$2:$I$790,$A79,'Transaction Overview'!$H$2:$H$790,E$4) -> 0 | F79: =SUMIFS('Transaction Overview'!$D$2:$D$790,'Transaction Overview'!$I$2:$I$790,$A79,'Transaction Overview'!$H$2:$H$790,F$4) -> 0 | G79: =SUMIFS('Transaction Overview'!$D$2:$D$790,'Transaction Overview'!$I$2:$I$790,$A79,'Transaction Overview'!$H$2:$H$790,G$4) -> 0 | H79: =SUMIFS('Transaction Overview'!$D$2:$D$790,'Transaction Overview'!$I$2:$I$790,$A79,'Transaction Overview'!$H$2:$H$790,H$4) -> 0 | I79: =SUMIFS('Transaction Overview'!$D$2:$D$790,'Transaction Overview'!$I$2:$I$790,$A79,'Transaction Overview'!$H$2:$H$790,I$4) -> 0 | ... M79: =SUMIFS('Transaction Overview'!$D$2:$D$790,'Transaction Overview'!$I$2:$I$790,$A79,'Transaction Overview'!$H$2:$H$790,M$4) -> 0 | N79: =SUM(B79:M79) -> -500
A80: Zelle to Sentha | B80: =SUMIFS('Transaction Overview'!$D$2:$D$790,'Transaction Overview'!$I$2:$I$790,$A80,'Transaction Overview'!$H$2:$H$790,B$4) -> 0 | C80: =SUMIFS('Transaction Overview'!$D$2:$D$790,'Transaction Overview'!$I$2:$I$790,$A80,'Transaction Overview'!$H$2:$H$790,C$4) -> 0 | D80: =SUMIFS('Transaction Overview'!$D$2:$D$790,'Transaction Overview'!$I$2:$I$790,$A80,'Transaction Overview'!$H$2:$H$790,D$4) -> 0 | E80: =SUMIFS('Transaction Overview'!$D$2:$D$790,'Transaction Overview'!$I$2:$I$790,$A80,'Transaction Overview'!$H$2:$H$790,E$4) -> 0 | F80: =SUMIFS('Transaction Overview'!$D$2:$D$790,'Transaction Overview'!$I$2:$I$790,$A80,'Transaction Overview'!$H$2:$H$790,F$4) -> 0 | G80: =SUMIFS('Transaction Overview'!$D$2:$D$790,'Transaction Overview'!$I$2:$I$790,$A80,'Transaction Overview'!$H$2:$H$790,G$4) -> 0 | H80: =SUMIFS('Transaction Overview'!$D$2:$D$790,'Transaction Overview'!$I$2:$I$790,$A80,'Transaction Overview'!$H$2:$H$790,H$4) -> -350 | I80: =SUMIFS('Transaction Overview'!$D$2:$D$790,'Transaction Overview'!$I$2:$I$790,$A80,'Transaction Overview'!$H$2:$H$790,I$4) -> 0 | ... M80: =SUMIFS('Transaction Overview'!$D$2:$D$790,'Transaction Overview'!$I$2:$I$790,$A80,'Transaction Overview'!$H$2:$H$790,M$4) -> 0 | N80: =SUM(B80:M80) -> -350
A81: Subtotal — P2P Payments (Zelle/Venmo/PayPal) | B81: =SUMIFS('Transaction Overview'!$D$2:$D$790,'Transaction Overview'!$J$2:$J$790,"P2P Payments (Zelle/Venmo/PayPal)",'Transaction Overview'!$H$2:$H$790,B$4) -> 0 | C81: =SUMIFS('Transaction Overview'!$D$2:$D$790,'Transaction Overview'!$J$2:$J$790,"P2P Payments (Zelle/Venmo/PayPal)",'Transaction Overview'!$H$2:$H$790,C$4) -> 0 | D81: =SUMIFS('Transaction Overview'!$D$2:$D$790,'Transaction Overview'!$J$2:$J$790,"P2P Payments (Zelle/Venmo/PayPal)",'Transaction Overview'!$H$2:$H$790,D$4) -> -100 | E81: =SUMIFS('Transaction Overview'!$D$2:$D$790,'Transaction Overview'!$J$2:$J$790,"P2P Payments (Zelle/Venmo/PayPal)",'Transaction Overview'!$H$2:$H$790,E$4) -> 0 | F81: =SUMIFS('Transaction Overview'!$D$2:$D$790,'Transaction Overview'!$J$2:$J$790,"P2P Payments (Zelle/Venmo/PayPal)",'Transaction Overview'!$H$2:$H$790,F$4) -> 0 | G81: =SUMIFS('Transaction Overview'!$D$2:$D$790,'Transaction Overview'!$J$2:$J$790,"P2P Payments (Zelle/Venmo/PayPal)",'Transaction Overview'!$H$2:$H$790,G$4) -> 0 | H81: =SUMIFS('Transaction Overview'!$D$2:$D$790,'Transaction Overview'!$J$2:$J$790,"P2P Payments (Zelle/Venmo/PayPal)",'Transaction Overview'!$H$2:$H$790,H$4) -> -350 | I81: =SUMIFS('Transaction Overview'!$D$2:$D$790,'Transaction Overview'!$J$2:$J$790,"P2P Payments (Zelle/Venmo/PayPal)",'Transaction Overview'!$H$2:$H$790,I$4) -> -500 | ... M81: =SUMIFS('Transaction Overview'!$D$2:$D$790,'Transaction Overview'!$J$2:$J$790,"P2P Payments (Zelle/Venmo/PayPal)",'Transaction Overview'!$H$2:$H$790,M$4) -> -31 | N81: =SUM(B81:M81) -> -3178
A83: Payroll & Contractors
A84: Ben Mandel - Payroll | B84: =SUMIFS('Transaction Overview'!$D$2:$D$790,'Transaction Overview'!$I$2:$I$790,$A84,'Transaction Overview'!$H$2:$H$790,B$4) -> 0 | C84: =SUMIFS('Transaction Overview'!$D$2:$D$790,'Transaction Overview'!$I$2:$I$790,$A84,'Transaction Overview'!$H$2:$H$790,C$4) -> 0 | D84: =SUMIFS('Transaction Overview'!$D$2:$D$790,'Transaction Overview'!$I$2:$I$790,$A84,'Transaction Overview'!$H$2:$H$790,D$4) -> 0 | E84: =SUMIFS('Transaction Overview'!$D$2:$D$790,'Transaction Overview'!$I$2:$I$790,$A84,'Transaction Overview'!$H$2:$H$790,E$4) -> 0 | F84: =SUMIFS('Transaction Overview'!$D$2:$D$790,'Transaction Overview'!$I$2:$I$790,$A84,'Transaction Overview'!$H$2:$H$790,F$4) -> 0 | G84: =SUMIFS('Transaction Overview'!$D$2:$D$790,'Transaction Overview'!$I$2:$I$790,$A84,'Transaction Overview'!$H$2:$H$790,G$4) -> 0 | H84: =SUMIFS('Transaction Overview'!$D$2:$D$790,'Transaction Overview'!$I$2:$I$790,$A84,'Transaction Overview'!$H$2:$H$790,H$4) -> 0 | I84: =SUMIFS('Transaction Overview'!$D$2:$D$790,'Transaction Overview'!$I$2:$I$790,$A84,'Transaction Overview'!$H$2:$H$790,I$4) -> 0 | ... M84: =SUMIFS('Transaction Overview'!$D$2:$D$790,'Transaction Overview'!$I$2:$I$790,$A84,'Transaction Overview'!$H$2:$H$790,M$4) -> -10000 | N84: =SUM(B84:M84) -> -10000
A85: Employee Bonus | B85: =SUMIFS('Transaction Overview'!$D$2:$D$790,'Transaction Overview'!$I$2:$I$790,$A85,'Transaction Overview'!$H$2:$H$790,B$4) -> 0 | C85: =SUMIFS('Transaction Overview'!$D$2:$D$790,'Transaction Overview'!$I$2:$I$790,$A85,'Transaction Overview'!$H$2:$H$790,C$4) -> 0 | D85: =SUMIFS('Transaction Overview'!$D$2:$D$790,'Transaction Overview'!$I$2:$I$790,$A85,'Transaction Overview'!$H$2:$H$790,D$4) -> 0 | E85: =SUMIFS('Transaction Overview'!$D$2:$D$790,'Transaction Overview'!$I$2:$I$790,$A85,'Transaction Overview'!$H$2:$H$790,E$4) -> 0 | F85: =SUMIFS('Transaction Overview'!$D$2:$D$790,'Transaction Overview'!$I$2:$I$790,$A85,'Transaction Overview'!$H$2:$H$790,F$4) -> 0 | G85: =SUMIFS('Transaction Overview'!$D$2:$D$790,'Transaction Overview'!$I$2:$I$790,$A85,'Transaction Overview'!$H$2:$H$790,G$4) -> 0 | H85: =SUMIFS('Transaction Overview'!$D$2:$D$790,'Transaction Overview'!$I$2:$I$790,$A85,'Transaction Overview'!$H$2:$H$790,H$4) -> 0 | I85: =SUMIFS('Transaction Overview'!$D$2:$D$790,'Transaction Overview'!$I$2:$I$790,$A85,'Transaction Overview'!$H$2:$H$790,I$4) -> 0 | ... M85: =SUMIFS('Transaction Overview'!$D$2:$D$790,'Transaction Overview'!$I$2:$I$790,$A85,'Transaction Overview'!$H$2:$H$790,M$4) -> -28000 | N85: =SUM(B85:M85) -> -28000
A86: Office/Miscellaneous Reimbursement - Mike P. | B86: =SUMIFS('Transaction Overview'!$D$2:$D$790,'Transaction Overview'!$I$2:$I$790,$A86,'Transaction Overview'!$H$2:$H$790,B$4) -> 0 | C86: =SUMIFS('Transaction Overview'!$D$2:$D$790,'Transaction Overview'!$I$2:$I$790,$A86,'Transaction Overview'!$H$2:$H$790,C$4) -> 0 | D86: =SUMIFS('Transaction Overview'!$D$2:$D$790,'Transaction Overview'!$I$2:$I$790,$A86,'Transaction Overview'!$H$2:$H$790,D$4) -> 0 | E86: =SUMIFS('Transaction Overview'!$D$2:$D$790,'Transaction Overview'!$I$2:$I$790,$A86,'Transaction Overview'!$H$2:$H$790,E$4) -> 0 | F86: =SUMIFS('Transaction Overview'!$D$2:$D$790,'Transaction Overview'!$I$2:$I$790,$A86,'Transaction Overview'!$H$2:$H$790,F$4) -> 0 | G86: =SUMIFS('Transaction Overview'!$D$2:$D$790,'Transaction Overview'!$I$2:$I$790,$A86,'Transaction Overview'!$H$2:$H$790,G$4) -> 0 | H86: =SUMIFS('Transaction Overview'!$D$2:$D$790,'Transaction Overview'!$I$2:$I$790,$A86,'Transaction Overview'!$H$2:$H$790,H$4) -> 0 | I86: =SUMIFS('Transaction Overview'!$D$2:$D$790,'Transaction Overview'!$I$2:$I$790,$A86,'Transaction Overview'!$H$2:$H$790,I$4) -> 0 | ... M86: =SUMIFS('Transaction Overview'!$D$2:$D$790,'Transaction Overview'!$I$2:$I$790,$A86,'Transaction Overview'!$H$2:$H$790,M$4) -> -200 | N86: =SUM(B86:M86) -> -872
A87: Subtotal — Payroll & Contractors | B87: =SUMIFS('Transaction Overview'!$D$2:$D$790,'Transaction Overview'!$J$2:$J$790,"Payroll & Contractors",'Transaction Overview'!$H$2:$H$790,B$4) -> 0 | C87: =SUMIFS('Transaction Overview'!$D$2:$D$790,'Transaction Overview'!$J$2:$J$790,"Payroll & Contractors",'Transaction Overview'!$H$2:$H$790,C$4) -> 0 | D87: =SUMIFS('Transaction Overview'!$D$2:$D$790,'Transaction Overview'!$J$2:$J$790,"Payroll & Contractors",'Transaction Overview'!$H$2:$H$790,D$4) -> 0 | E87: =SUMIFS('Transaction Overview'!$D$2:$D$790,'Transaction Overview'!$J$2:$J$790,"Payroll & Contractors",'Transaction Overview'!$H$2:$H$790,E$4) -> 0 | F87: =SUMIFS('Transaction Overview'!$D$2:$D$790,'Transaction Overview'!$J$2:$J$790,"Payroll & Contractors",'Transaction Overview'!$H$2:$H$790,F$4) -> 0 | G87: =SUMIFS('Transaction Overview'!$D$2:$D$790,'Transaction Overview'!$J$2:$J$790,"Payroll & Contractors",'Transaction Overview'!$H$2:$H$790,G$4) -> 0 | H87: =SUMIFS('Transaction Overview'!$D$2:$D$790,'Transaction Overview'!$J$2:$J$790,"Payroll & Contractors",'Transaction Overview'!$H$2:$H$790,H$4) -> 0 | I87: =SUMIFS('Transaction Overview'!$D$2:$D$790,'Transaction Overview'!$J$2:$J$790,"Payroll & Contractors",'Transaction Overview'!$H$2:$H$790,I$4) -> 0 | ... M87: =SUMIFS('Transaction Overview'!$D$2:$D$790,'Transaction Overview'!$J$2:$J$790,"Payroll & Contractors",'Transaction Overview'!$H$2:$H$790,M$4) -> -38200 | N87: =SUM(B87:M87) -> -38872
A89: Credit Card & Loan Payments
A90: American Express Credit Card PMT | B90: =SUMIFS('Transaction Overview'!$D$2:$D$790,'Transaction Overview'!$I$2:$I$790,$A90,'Transaction Overview'!$H$2:$H$790,B$4) -> -27459.41 | C90: =SUMIFS('Transaction Overview'!$D$2:$D$790,'Transaction Overview'!$I$2:$I$790,$A90,'Transaction Overview'!$H$2:$H$790,C$4) -> 0 | D90: =SUMIFS('Transaction Overview'!$D$2:$D$790,'Transaction Overview'!$I$2:$I$790,$A90,'Transaction Overview'!$H$2:$H$790,D$4) -> -32874.62 | E90: =SUMIFS('Transaction Overview'!$D$2:$D$790,'Transaction Overview'!$I$2:$I$790,$A90,'Transaction Overview'!$H$2:$H$790,E$4) -> -42222.92 | F90: =SUMIFS('Transaction Overview'!$D$2:$D$790,'Transaction Overview'!$I$2:$I$790,$A90,'Transaction Overview'!$H$2:$H$790,F$4) -> -8226.61 | G90: =SUMIFS('Transaction Overview'!$D$2:$D$790,'Transaction Overview'!$I$2:$I$790,$A90,'Transaction Overview'!$H$2:$H$790,G$4) -> 0 | H90: =SUMIFS('Transaction Overview'!$D$2:$D$790,'Transaction Overview'!$I$2:$I$790,$A90,'Transaction Overview'!$H$2:$H$790,H$4) -> -23574.61 | I90: =SUMIFS('Transaction Overview'!$D$2:$D$790,'Transaction Overview'!$I$2:$I$790,$A90,'Transaction Overview'!$H$2:$H$790,I$4) -> -19118.35 | ... M90: =SUMIFS('Transaction Overview'!$D$2:$D$790,'Transaction Overview'!$I$2:$I$790,$A90,'Transaction Overview'!$H$2:$H$790,M$4) -> -52631.91 | N90: =SUM(B90:M90) -> -231476.49
A91: Subtotal — Credit Card & Loan Payments | B91: =SUMIFS('Transaction Overview'!$D$2:$D$790,'Transaction Overview'!$J$2:$J$790,"Credit Card & Loan Payments",'Transaction Overview'!$H$2:$H$790,B$4) -> -27459.41 | C91: =SUMIFS('Transaction Overview'!$D$2:$D$790,'Transaction Overview'!$J$2:$J$790,"Credit Card & Loan Payments",'Transaction Overview'!$H$2:$H$790,C$4) -> 0 | D91: =SUMIFS('Transaction Overview'!$D$2:$D$790,'Transaction Overview'!$J$2:$J$790,"Credit Card & Loan Payments",'Transaction Overview'!$H$2:$H$790,D$4) -> -32874.62 | E91: =SUMIFS('Transaction Overview'!$D$2:$D$790,'Transaction Overview'!$J$2:$J$790,"Credit Card & Loan Payments",'Transaction Overview'!$H$2:$H$790,E$4) -> -42222.92 | F91: =SUMIFS('Transaction Overview'!$D$2:$D$790,'Transaction Overview'!$J$2:$J$790,"Credit Card & Loan Payments",'Transaction Overview'!$H$2:$H$790,F$4) -> -8226.61 | G91: =SUMIFS('Transaction Overview'!$D$2:$D$790,'Transaction Overview'!$J$2:$J$790,"Credit Card & Loan Payments",'Transaction Overview'!$H$2:$H$790,G$4) -> 0 | H91: =SUMIFS('Transaction Overview'!$D$2:$D$790,'Transaction Overview'!$J$2:$J$790,"Credit Card & Loan Payments",'Transaction Overview'!$H$2:$H$790,H$4) -> -23574.61 | I91: =SUMIFS('Transaction Overview'!$D$2:$D$790,'Transaction Overview'!$J$2:$J$790,"Credit Card & Loan Payments",'Transaction Overview'!$H$2:$H$790,I$4) -> -19118.35 | ... M91: =SUMIFS('Transaction Overview'!$D$2:$D$790,'Transaction Overview'!$J$2:$J$790,"Credit Card & Loan Payments",'Transaction Overview'!$H$2:$H$790,M$4) -> -52631.91 | N91: =SUM(B91:M91) -> -231476.49
A93: Personal — Owner
A94: AI Subscriptions | B94: =SUMIFS('Transaction Overview'!$D$2:$D$790,'Transaction Overview'!$I$2:$I$790,$A94,'Transaction Overview'!$H$2:$H$790,B$4) -> 0 | C94: =SUMIFS('Transaction Overview'!$D$2:$D$790,'Transaction Overview'!$I$2:$I$790,$A94,'Transaction Overview'!$H$2:$H$790,C$4) -> 0 | D94: =SUMIFS('Transaction Overview'!$D$2:$D$790,'Transaction Overview'!$I$2:$I$790,$A94,'Transaction Overview'!$H$2:$H$790,D$4) -> 0 | E94: =SUMIFS('Transaction Overview'!$D$2:$D$790,'Transaction Overview'!$I$2:$I$790,$A94,'Transaction Overview'!$H$2:$H$790,E$4) -> 0 | F94: =SUMIFS('Transaction Overview'!$D$2:$D$790,'Transaction Overview'!$I$2:$I$790,$A94,'Transaction Overview'!$H$2:$H$790,F$4) -> 0 | G94: =SUMIFS('Transaction Overview'!$D$2:$D$790,'Transaction Overview'!$I$2:$I$790,$A94,'Transaction Overview'!$H$2:$H$790,G$4) -> 0 | H94: =SUMIFS('Transaction Overview'!$D$2:$D$790,'Transaction Overview'!$I$2:$I$790,$A94,'Transaction Overview'!$H$2:$H$790,H$4) -> 0 | I94: =SUMIFS('Transaction Overview'!$D$2:$D$790,'Transaction Overview'!$I$2:$I$790,$A94,'Transaction Overview'!$H$2:$H$790,I$4) -> 0 | ... M94: =SUMIFS('Transaction Overview'!$D$2:$D$790,'Transaction Overview'!$I$2:$I$790,$A94,'Transaction Overview'!$H$2:$H$790,M$4) -> 0 | N94: =SUM(B94:M94) -> -216
A95: Amazon | B95: =SUMIFS('Transaction Overview'!$D$2:$D$790,'Transaction Overview'!$I$2:$I$790,$A95,'Transaction Overview'!$H$2:$H$790,B$4) -> -67.24 | C95: =SUMIFS('Transaction Overview'!$D$2:$D$790,'Transaction Overview'!$I$2:$I$790,$A95,'Transaction Overview'!$H$2:$H$790,C$4) -> -116.29 | D95: =SUMIFS('Transaction Overview'!$D$2:$D$790,'Transaction Overview'!$I$2:$I$790,$A95,'Transaction Overview'!$H$2:$H$790,D$4) -> -62.94 | E95: =SUMIFS('Transaction Overview'!$D$2:$D$790,'Transaction Overview'!$I$2:$I$790,$A95,'Transaction Overview'!$H$2:$H$790,E$4) -> -196.91 | F95: =SUMIFS('Transaction Overview'!$D$2:$D$790,'Transaction Overview'!$I$2:$I$790,$A95,'Transaction Overview'!$H$2:$H$790,F$4) -> -226.7 | G95: =SUMIFS('Transaction Overview'!$D$2:$D$790,'Transaction Overview'!$I$2:$I$790,$A95,'Transaction Overview'!$H$2:$H$790,G$4) -> -257.89 | H95: =SUMIFS('Transaction Overview'!$D$2:$D$790,'Transaction Overview'!$I$2:$I$790,$A95,'Transaction Overview'!$H$2:$H$790,H$4) -> -543.28 | I95: =SUMIFS('Transaction Overview'!$D$2:$D$790,'Transaction Overview'!$I$2:$I$790,$A95,'Transaction Overview'!$H$2:$H$790,I$4) -> -1763.91 | ... M95: =SUMIFS('Transaction Overview'!$D$2:$D$790,'Transaction Overview'!$I$2:$I$790,$A95,'Transaction Overview'!$H$2:$H$790,M$4) -> -814.3 | N95: =SUM(B95:M95) -> -8026.12
A96: Amazon Prime Video | B96: =SUMIFS('Transaction Overview'!$D$2:$D$790,'Transaction Overview'!$I$2:$I$790,$A96,'Transaction Overview'!$H$2:$H$790,B$4) -> -43.65 | C96: =SUMIFS('Transaction Overview'!$D$2:$D$790,'Transaction Overview'!$I$2:$I$790,$A96,'Transaction Overview'!$H$2:$H$790,C$4) -> -56.45 | D96: =SUMIFS('Transaction Overview'!$D$2:$D$790,'Transaction Overview'!$I$2:$I$790,$A96,'Transaction Overview'!$H$2:$H$790,D$4) -> -14.92 | E96: =SUMIFS('Transaction Overview'!$D$2:$D$790,'Transaction Overview'!$I$2:$I$790,$A96,'Transaction Overview'!$H$2:$H$790,E$4) -> -19.19 | F96: =SUMIFS('Transaction Overview'!$D$2:$D$790,'Transaction Overview'!$I$2:$I$790,$A96,'Transaction Overview'!$H$2:$H$790,F$4) -> -129.69 | G96: =SUMIFS('Transaction Overview'!$D$2:$D$790,'Transaction Overview'!$I$2:$I$790,$A96,'Transaction Overview'!$H$2:$H$790,G$4) -> -61.18 | H96: =SUMIFS('Transaction Overview'!$D$2:$D$790,'Transaction Overview'!$I$2:$I$790,$A96,'Transaction Overview'!$H$2:$H$790,H$4) -> -20.67 | I96: =SUMIFS('Transaction Overview'!$D$2:$D$790,'Transaction Overview'!$I$2:$I$790,$A96,'Transaction Overview'!$H$2:$H$790,I$4) -> -31.29 | ... M96: =SUMIFS('Transaction Overview'!$D$2:$D$790,'Transaction Overview'!$I$2:$I$790,$A96,'Transaction Overview'!$H$2:$H$790,M$4) -> -99.47 | N96: =SUM(B96:M96) -> -642.16
A97: Personal - Car & Auto | B97: =SUMIFS('Transaction Overview'!$D$2:$D$790,'Transaction Overview'!$I$2:$I$790,$A97,'Transaction Overview'!$H$2:$H$790,B$4) -> 0 | C97: =SUMIFS('Transaction Overview'!$D$2:$D$790,'Transaction Overview'!$I$2:$I$790,$A97,'Transaction Overview'!$H$2:$H$790,C$4) -> 0 | D97: =SUMIFS('Transaction Overview'!$D$2:$D$790,'Transaction Overview'!$I$2:$I$790,$A97,'Transaction Overview'!$H$2:$H$790,D$4) -> 0 | E97: =SUMIFS('Transaction Overview'!$D$2:$D$790,'Transaction Overview'!$I$2:$I$790,$A97,'Transaction Overview'!$H$2:$H$790,E$4) -> 0 | F97: =SUMIFS('Transaction Overview'!$D$2:$D$790,'Transaction Overview'!$I$2:$I$790,$A97,'Transaction Overview'!$H$2:$H$790,F$4) -> -3.25 | G97: =SUMIFS('Transaction Overview'!$D$2:$D$790,'Transaction Overview'!$I$2:$I$790,$A97,'Transaction Overview'!$H$2:$H$790,G$4) -> -4.75 | H97: =SUMIFS('Transaction Overview'!$D$2:$D$790,'Transaction Overview'!$I$2:$I$790,$A97,'Transaction Overview'!$H$2:$H$790,H$4) -> -12 | I97: =SUMIFS('Transaction Overview'!$D$2:$D$790,'Transaction Overview'!$I$2:$I$790,$A97,'Transaction Overview'!$H$2:$H$790,I$4) -> -17.12 | ... M97: =SUMIFS('Transaction Overview'!$D$2:$D$790,'Transaction Overview'!$I$2:$I$790,$A97,'Transaction Overview'!$H$2:$H$790,M$4) -> -7 | N97: =SUM(B97:M97) -> -114.12
A98: Personal - Clothing | B98: =SUMIFS('Transaction Overview'!$D$2:$D$790,'Transaction Overview'!$I$2:$I$790,$A98,'Transaction Overview'!$H$2:$H$790,B$4) -> 0 | C98: =SUMIFS('Transaction Overview'!$D$2:$D$790,'Transaction Overview'!$I$2:$I$790,$A98,'Transaction Overview'!$H$2:$H$790,C$4) -> 0 | D98: =SUMIFS('Transaction Overview'!$D$2:$D$790,'Transaction Overview'!$I$2:$I$790,$A98,'Transaction Overview'!$H$2:$H$790,D$4) -> 0 | E98: =SUMIFS('Transaction Overview'!$D$2:$D$790,'Transaction Overview'!$I$2:$I$790,$A98,'Transaction Overview'!$H$2:$H$790,E$4) -> 0 | F98: =SUMIFS('Transaction Overview'!$D$2:$D$790,'Transaction Overview'!$I$2:$I$790,$A98,'Transaction Overview'!$H$2:$H$790,F$4) -> 0 | G98: =SUMIFS('Transaction Overview'!$D$2:$D$790,'Transaction Overview'!$I$2:$I$790,$A98,'Transaction Overview'!$H$2:$H$790,G$4) -> 0 | H98: =SUMIFS('Transaction Overview'!$D$2:$D$790,'Transaction Overview'!$I$2:$I$790,$A98,'Transaction Overview'!$H$2:$H$790,H$4) -> 0 | I98: =SUMIFS('Transaction Overview'!$D$2:$D$790,'Transaction Overview'!$I$2:$I$790,$A98,'Transaction Overview'!$H$2:$H$790,I$4) -> 0 | ... M98: =SUMIFS('Transaction Overview'!$D$2:$D$790,'Transaction Overview'!$I$2:$I$790,$A98,'Transaction Overview'!$H$2:$H$790,M$4) -> -328.19 | N98: =SUM(B98:M98) -> -328.19
A99: Personal - Donation | B99: =SUMIFS('Transaction Overview'!$D$2:$D$790,'Transaction Overview'!$I$2:$I$790,$A99,'Transaction Overview'!$H$2:$H$790,B$4) -> 0 | C99: =SUMIFS('Transaction Overview'!$D$2:$D$790,'Transaction Overview'!$I$2:$I$790,$A99,'Transaction Overview'!$H$2:$H$790,C$4) -> 0 | D99: =SUMIFS('Transaction Overview'!$D$2:$D$790,'Transaction Overview'!$I$2:$I$790,$A99,'Transaction Overview'!$H$2:$H$790,D$4) -> 0 | E99: =SUMIFS('Transaction Overview'!$D$2:$D$790,'Transaction Overview'!$I$2:$I$790,$A99,'Transaction Overview'!$H$2:$H$790,E$4) -> 0 | F99: =SUMIFS('Transaction Overview'!$D$2:$D$790,'Transaction Overview'!$I$2:$I$790,$A99,'Transaction Overview'!$H$2:$H$790,F$4) -> 0 | G99: =SUMIFS('Transaction Overview'!$D$2:$D$790,'Transaction Overview'!$I$2:$I$790,$A99,'Transaction Overview'!$H$2:$H$790,G$4) -> 0 | H99: =SUMIFS('Transaction Overview'!$D$2:$D$790,'Transaction Overview'!$I$2:$I$790,$A99,'Transaction Overview'!$H$2:$H$790,H$4) -> 0 | I99: =SUMIFS('Transaction Overview'!$D$2:$D$790,'Transaction Overview'!$I$2:$I$790,$A99,'Transaction Overview'!$H$2:$H$790,I$4) -> 0 | ... M99: =SUMIFS('Transaction Overview'!$D$2:$D$790,'Transaction Overview'!$I$2:$I$790,$A99,'Transaction Overview'!$H$2:$H$790,M$4) -> -5 | N99: =SUM(B99:M99) -> -28
A100: Personal - Entertainment | B100: =SUMIFS('Transaction Overview'!$D$2:$D$790,'Transaction Overview'!$I$2:$I$790,$A100,'Transaction Overview'!$H$2:$H$790,B$4) -> 0 | C100: =SUMIFS('Transaction Overview'!$D$2:$D$790,'Transaction Overview'!$I$2:$I$790,$A100,'Transaction Overview'!$H$2:$H$790,C$4) -> 0 | D100: =SUMIFS('Transaction Overview'!$D$2:$D$790,'Transaction Overview'!$I$2:$I$790,$A100,'Transaction Overview'!$H$2:$H$790,D$4) -> 0 | E100: =SUMIFS('Transaction Overview'!$D$2:$D$790,'Transaction Overview'!$I$2:$I$790,$A100,'Transaction Overview'!$H$2:$H$790,E$4) -> 0 | F100: =SUMIFS('Transaction Overview'!$D$2:$D$790,'Transaction Overview'!$I$2:$I$790,$A100,'Transaction Overview'!$H$2:$H$790,F$4) -> 0 | G100: =SUMIFS('Transaction Overview'!$D$2:$D$790,'Transaction Overview'!$I$2:$I$790,$A100,'Transaction Overview'!$H$2:$H$790,G$4) -> -33.17 | H100: =SUMIFS('Transaction Overview'!$D$2:$D$790,'Transaction Overview'!$I$2:$I$790,$A100,'Transaction Overview'!$H$2:$H$790,H$4) -> 0 | I100: =SUMIFS('Transaction Overview'!$D$2:$D$790,'Transaction Overview'!$I$2:$I$790,$A100,'Transaction Overview'!$H$2:$H$790,I$4) -> -10.77 | ... M100: =SUMIFS('Transaction Overview'!$D$2:$D$790,'Transaction Overview'!$I$2:$I$790,$A100,'Transaction Overview'!$H$2:$H$790,M$4) -> -70.72 | N100: =SUM(B100:M100) -> -187.64
A101: Personal - Food & Dining | B101: =SUMIFS('Transaction Overview'!$D$2:$D$790,'Transaction Overview'!$I$2:$I$790,$A101,'Transaction Overview'!$H$2:$H$790,B$4) -> 0 | C101: =SUMIFS('Transaction Overview'!$D$2:$D$790,'Transaction Overview'!$I$2:$I$790,$A101,'Transaction Overview'!$H$2:$H$790,C$4) -> 0 | D101: =SUMIFS('Transaction Overview'!$D$2:$D$790,'Transaction Overview'!$I$2:$I$790,$A101,'Transaction Overview'!$H$2:$H$790,D$4) -> -13.2 | E101: =SUMIFS('Transaction Overview'!$D$2:$D$790,'Transaction Overview'!$I$2:$I$790,$A101,'Transaction Overview'!$H$2:$H$790,E$4) -> 0 | F101: =SUMIFS('Transaction Overview'!$D$2:$D$790,'Transaction Overview'!$I$2:$I$790,$A101,'Transaction Overview'!$H$2:$H$790,F$4) -> 0 | G101: =SUMIFS('Transaction Overview'!$D$2:$D$790,'Transaction Overview'!$I$2:$I$790,$A101,'Transaction Overview'!$H$2:$H$790,G$4) -> 0 | H101: =SUMIFS('Transaction Overview'!$D$2:$D$790,'Transaction Overview'!$I$2:$I$790,$A101,'Transaction Overview'!$H$2:$H$790,H$4) -> -13.72 | I101: =SUMIFS('Transaction Overview'!$D$2:$D$790,'Transaction Overview'!$I$2:$I$790,$A101,'Transaction Overview'!$H$2:$H$790,I$4) -> -97.12 | ... M101: =SUMIFS('Transaction Overview'!$D$2:$D$790,'Transaction Overview'!$I$2:$I$790,$A101,'Transaction Overview'!$H$2:$H$790,M$4) -> 0 | N101: =SUM(B101:M101) -> -645.37
A102: Personal - Gift (Dax Mitchell) | B102: =SUMIFS('Transaction Overview'!$D$2:$D$790,'Transaction Overview'!$I$2:$I$790,$A102,'Transaction Overview'!$H$2:$H$790,B$4) -> 0 | C102: =SUMIFS('Transaction Overview'!$D$2:$D$790,'Transaction Overview'!$I$2:$I$790,$A102,'Transaction Overview'!$H$2:$H$790,C$4) -> 0 | D102: =SUMIFS('Transaction Overview'!$D$2:$D$790,'Transaction Overview'!$I$2:$I$790,$A102,'Transaction Overview'!$H$2:$H$790,D$4) -> 0 | E102: =SUMIFS('Transaction Overview'!$D$2:$D$790,'Transaction Overview'!$I$2:$I$790,$A102,'Transaction Overview'!$H$2:$H$790,E$4) -> 0 | F102: =SUMIFS('Transaction Overview'!$D$2:$D$790,'Transaction Overview'!$I$2:$I$790,$A102,'Transaction Overview'!$H$2:$H$790,F$4) -> 0 | G102: =SUMIFS('Transaction Overview'!$D$2:$D$790,'Transaction Overview'!$I$2:$I$790,$A102,'Transaction Overview'!$H$2:$H$790,G$4) -> 0 | H102: =SUMIFS('Transaction Overview'!$D$2:$D$790,'Transaction Overview'!$I$2:$I$790,$A102,'Transaction Overview'!$H$2:$H$790,H$4) -> 0 | I102: =SUMIFS('Transaction Overview'!$D$2:$D$790,'Transaction Overview'!$I$2:$I$790,$A102,'Transaction Overview'!$H$2:$H$790,I$4) -> 0 | ... M102: =SUMIFS('Transaction Overview'!$D$2:$D$790,'Transaction Overview'!$I$2:$I$790,$A102,'Transaction Overview'!$H$2:$H$790,M$4) -> 0 | N102: =SUM(B102:M102) -> -1035.46
A103: Personal - Health (incl. Ins.) | B103: =SUMIFS('Transaction Overview'!$D$2:$D$790,'Transaction Overview'!$I$2:$I$790,$A103,'Transaction Overview'!$H$2:$H$790,B$4) -> 0 | C103: =SUMIFS('Transaction Overview'!$D$2:$D$790,'Transaction Overview'!$I$2:$I$790,$A103,'Transaction Overview'!$H$2:$H$790,C$4) -> 0 | D103: =SUMIFS('Transaction Overview'!$D$2:$D$790,'Transaction Overview'!$I$2:$I$790,$A103,'Transaction Overview'!$H$2:$H$790,D$4) -> 0 | E103: =SUMIFS('Transaction Overview'!$D$2:$D$790,'Transaction Overview'!$I$2:$I$790,$A103,'Transaction Overview'!$H$2:$H$790,E$4) -> 0 | F103: =SUMIFS('Transaction Overview'!$D$2:$D$790,'Transaction Overview'!$I$2:$I$790,$A103,'Transaction Overview'!$H$2:$H$790,F$4) -> 0 | G103: =SUMIFS('Transaction Overview'!$D$2:$D$790,'Transaction Overview'!$I$2:$I$790,$A103,'Transaction Overview'!$H$2:$H$790,G$4) -> 0 | H103: =SUMIFS('Transaction Overview'!$D$2:$D$790,'Transaction Overview'!$I$2:$I$790,$A103,'Transaction Overview'!$H$2:$H$790,H$4) -> 0 | I103: =SUMIFS('Transaction Overview'!$D$2:$D$790,'Transaction Overview'!$I$2:$I$790,$A103,'Transaction Overview'!$H$2:$H$790,I$4) -> -171.54 | ... M103: =SUMIFS('Transaction Overview'!$D$2:$D$790,'Transaction Overview'!$I$2:$I$790,$A103,'Transaction Overview'!$H$2:$H$790,M$4) -> -220 | N103: =SUM(B103:M103) -> -391.54
A104: Personal - Shopping | B104: =SUMIFS('Transaction Overview'!$D$2:$D$790,'Transaction Overview'!$I$2:$I$790,$A104,'Transaction Overview'!$H$2:$H$790,B$4) -> 0 | C104: =SUMIFS('Transaction Overview'!$D$2:$D$790,'Transaction Overview'!$I$2:$I$790,$A104,'Transaction Overview'!$H$2:$H$790,C$4) -> 0 | D104: =SUMIFS('Transaction Overview'!$D$2:$D$790,'Transaction Overview'!$I$2:$I$790,$A104,'Transaction Overview'!$H$2:$H$790,D$4) -> 0 | E104: =SUMIFS('Transaction Overview'!$D$2:$D$790,'Transaction Overview'!$I$2:$I$790,$A104,'Transaction Overview'!$H$2:$H$790,E$4) -> 0 | F104: =SUMIFS('Transaction Overview'!$D$2:$D$790,'Transaction Overview'!$I$2:$I$790,$A104,'Transaction Overview'!$H$2:$H$790,F$4) -> 0 | G104: =SUMIFS('Transaction Overview'!$D$2:$D$790,'Transaction Overview'!$I$2:$I$790,$A104,'Transaction Overview'!$H$2:$H$790,G$4) -> 0 | H104: =SUMIFS('Transaction Overview'!$D$2:$D$790,'Transaction Overview'!$I$2:$I$790,$A104,'Transaction Overview'!$H$2:$H$790,H$4) -> 0 | I104: =SUMIFS('Transaction Overview'!$D$2:$D$790,'Transaction Overview'!$I$2:$I$790,$A104,'Transaction Overview'!$H$2:$H$790,I$4) -> 0 | ... M104: =SUMIFS('Transaction Overview'!$D$2:$D$790,'Transaction Overview'!$I$2:$I$790,$A104,'Transaction Overview'!$H$2:$H$790,M$4) -> -676.9 | N104: =SUM(B104:M104) -> -705.44
A105: Personal - Subscriptions | B105: =SUMIFS('Transaction Overview'!$D$2:$D$790,'Transaction Overview'!$I$2:$I$790,$A105,'Transaction Overview'!$H$2:$H$790,B$4) -> -218.41 | C105: =SUMIFS('Transaction Overview'!$D$2:$D$790,'Transaction Overview'!$I$2:$I$790,$A105,'Transaction Overview'!$H$2:$H$790,C$4) -> -166.91 | D105: =SUMIFS('Transaction Overview'!$D$2:$D$790,'Transaction Overview'!$I$2:$I$790,$A105,'Transaction Overview'!$H$2:$H$790,D$4) -> -277.59 | E105: =SUMIFS('Transaction Overview'!$D$2:$D$790,'Transaction Overview'!$I$2:$I$790,$A105,'Transaction Overview'!$H$2:$H$790,E$4) -> -257.03 | F105: =SUMIFS('Transaction Overview'!$D$2:$D$790,'Transaction Overview'!$I$2:$I$790,$A105,'Transaction Overview'!$H$2:$H$790,F$4) -> -226.14 | G105: =SUMIFS('Transaction Overview'!$D$2:$D$790,'Transaction Overview'!$I$2:$I$790,$A105,'Transaction Overview'!$H$2:$H$790,G$4) -> -205.58 | H105: =SUMIFS('Transaction Overview'!$D$2:$D$790,'Transaction Overview'!$I$2:$I$790,$A105,'Transaction Overview'!$H$2:$H$790,H$4) -> -292.59 | I105: =SUMIFS('Transaction Overview'!$D$2:$D$790,'Transaction Overview'!$I$2:$I$790,$A105,'Transaction Overview'!$H$2:$H$790,I$4) -> -241.14 | ... M105: =SUMIFS('Transaction Overview'!$D$2:$D$790,'Transaction Overview'!$I$2:$I$790,$A105,'Transaction Overview'!$H$2:$H$790,M$4) -> -409.64 | N105: =SUM(B105:M105) -> -3178.75
... A110: Personal - Travel (Italy) | B110: =SUMIFS('Transaction Overview'!$D$2:$D$790,'Transaction Overview'!$I$2:$I$790,$A110,'Transaction Overview'!$H$2:$H$790,B$4) -> 0 | C110: =SUMIFS('Transaction Overview'!$D$2:$D$790,'Transaction Overview'!$I$2:$I$790,$A110,'Transaction Overview'!$H$2:$H$790,C$4) -> 0 | D110: =SUMIFS('Transaction Overview'!$D$2:$D$790,'Transaction Overview'!$I$2:$I$790,$A110,'Transaction Overview'!$H$2:$H$790,D$4) -> 0 | E110: =SUMIFS('Transaction Overview'!$D$2:$D$790,'Transaction Overview'!$I$2:$I$790,$A110,'Transaction Overview'!$H$2:$H$790,E$4) -> -767.08 | F110: =SUMIFS('Transaction Overview'!$D$2:$D$790,'Transaction Overview'!$I$2:$I$790,$A110,'Transaction Overview'!$H$2:$H$790,F$4) -> 0 | G110: =SUMIFS('Transaction Overview'!$D$2:$D$790,'Transaction Overview'!$I$2:$I$790,$A110,'Transaction Overview'!$H$2:$H$790,G$4) -> 0 | H110: =SUMIFS('Transaction Overview'!$D$2:$D$790,'Transaction Overview'!$I$2:$I$790,$A110,'Transaction Overview'!$H$2:$H$790,H$4) -> 0 | I110: =SUMIFS('Transaction Overview'!$D$2:$D$790,'Transaction Overview'!$I$2:$I$790,$A110,'Transaction Overview'!$H$2:$H$790,I$4) -> 0 | ... M110: =SUMIFS('Transaction Overview'!$D$2:$D$790,'Transaction Overview'!$I$2:$I$790,$A110,'Transaction Overview'!$H$2:$H$790,M$4) -> 0 | N110: =SUM(B110:M110) -> -767.08
A111: Subtotal — Personal — Owner | B111: =SUMIFS('Transaction Overview'!$D$2:$D$790,'Transaction Overview'!$J$2:$J$790,"Personal — Owner",'Transaction Overview'!$H$2:$H$790,B$4) -> -329.3 | C111: =SUMIFS('Transaction Overview'!$D$2:$D$790,'Transaction Overview'!$J$2:$J$790,"Personal — Owner",'Transaction Overview'!$H$2:$H$790,C$4) -> -339.65 | D111: =SUMIFS('Transaction Overview'!$D$2:$D$790,'Transaction Overview'!$J$2:$J$790,"Personal — Owner",'Transaction Overview'!$H$2:$H$790,D$4) -> -1924.57 | E111: =SUMIFS('Transaction Overview'!$D$2:$D$790,'Transaction Overview'!$J$2:$J$790,"Personal — Owner",'Transaction Overview'!$H$2:$H$790,E$4) -> -1240.21 | F111: =SUMIFS('Transaction Overview'!$D$2:$D$790,'Transaction Overview'!$J$2:$J$790,"Personal — Owner",'Transaction Overview'!$H$2:$H$790,F$4) -> -585.78 | G111: =SUMIFS('Transaction Overview'!$D$2:$D$790,'Transaction Overview'!$J$2:$J$790,"Personal — Owner",'Transaction Overview'!$H$2:$H$790,G$4) -> -562.57 | H111: =SUMIFS('Transaction Overview'!$D$2:$D$790,'Transaction Overview'!$J$2:$J$790,"Personal — Owner",'Transaction Overview'!$H$2:$H$790,H$4) -> -882.26 | I111: =SUMIFS('Transaction Overview'!$D$2:$D$790,'Transaction Overview'!$J$2:$J$790,"Personal — Owner",'Transaction Overview'!$H$2:$H$790,I$4) -> -2376.89 | ... M111: =SUMIFS('Transaction Overview'!$D$2:$D$790,'Transaction Overview'!$J$2:$J$790,"Personal — Owner",'Transaction Overview'!$H$2:$H$790,M$4) -> -3382.21 | N111: =SUM(B111:M111) -> -18981.77
A113: DWG Operating
A114: ACH Payment - Astronomics | B114: =SUMIFS('Transaction Overview'!$D$2:$D$790,'Transaction Overview'!$I$2:$I$790,$A114,'Transaction Overview'!$H$2:$H$790,B$4) -> 0 | C114: =SUMIFS('Transaction Overview'!$D$2:$D$790,'Transaction Overview'!$I$2:$I$790,$A114,'Transaction Overview'!$H$2:$H$790,C$4) -> 0 | D114: =SUMIFS('Transaction Overview'!$D$2:$D$790,'Transaction Overview'!$I$2:$I$790,$A114,'Transaction Overview'!$H$2:$H$790,D$4) -> 0 | E114: =SUMIFS('Transaction Overview'!$D$2:$D$790,'Transaction Overview'!$I$2:$I$790,$A114,'Transaction Overview'!$H$2:$H$790,E$4) -> 0 | F114: =SUMIFS('Transaction Overview'!$D$2:$D$790,'Transaction Overview'!$I$2:$I$790,$A114,'Transaction Overview'!$H$2:$H$790,F$4) -> 0 | G114: =SUMIFS('Transaction Overview'!$D$2:$D$790,'Transaction Overview'!$I$2:$I$790,$A114,'Transaction Overview'!$H$2:$H$790,G$4) -> 0 | H114: =SUMIFS('Transaction Overview'!$D$2:$D$790,'Transaction Overview'!$I$2:$I$790,$A114,'Transaction Overview'!$H$2:$H$790,H$4) -> -5000 | I114: =SUMIFS('Transaction Overview'!$D$2:$D$790,'Transaction Overview'!$I$2:$I$790,$A114,'Transaction Overview'!$H$2:$H$790,I$4) -> 0 | ... M114: =SUMIFS('Transaction Overview'!$D$2:$D$790,'Transaction Overview'!$I$2:$I$790,$A114,'Transaction Overview'!$H$2:$H$790,M$4) -> 0 | N114: =SUM(B114:M114) -> -5000
A115: ACH payment to CALCPA group | B115: =SUMIFS('Transaction Overview'!$D$2:$D$790,'Transaction Overview'!$I$2:$I$790,$A115,'Transaction Overview'!$H$2:$H$790,B$4) -> 0 | C115: =SUMIFS('Transaction Overview'!$D$2:$D$790,'Transaction Overview'!$I$2:$I$790,$A115,'Transaction Overview'!$H$2:$H$790,C$4) -> 0 | D115: =SUMIFS('Transaction Overview'!$D$2:$D$790,'Transaction Overview'!$I$2:$I$790,$A115,'Transaction Overview'!$H$2:$H$790,D$4) -> 0 | E115: =SUMIFS('Transaction Overview'!$D$2:$D$790,'Transaction Overview'!$I$2:$I$790,$A115,'Transaction Overview'!$H$2:$H$790,E$4) -> 0 | F115: =SUMIFS('Transaction Overview'!$D$2:$D$790,'Transaction Overview'!$I$2:$I$790,$A115,'Transaction Overview'!$H$2:$H$790,F$4) -> 0 | G115: =SUMIFS('Transaction Overview'!$D$2:$D$790,'Transaction Overview'!$I$2:$I$790,$A115,'Transaction Overview'!$H$2:$H$790,G$4) -> 0 | H115: =SUMIFS('Transaction Overview'!$D$2:$D$790,'Transaction Overview'!$I$2:$I$790,$A115,'Transaction Overview'!$H$2:$H$790,H$4) -> 0 | I115: =SUMIFS('Transaction Overview'!$D$2:$D$790,'Transaction Overview'!$I$2:$I$790,$A115,'Transaction Overview'!$H$2:$H$790,I$4) -> 0 | ... M115: =SUMIFS('Transaction Overview'!$D$2:$D$790,'Transaction Overview'!$I$2:$I$790,$A115,'Transaction Overview'!$H$2:$H$790,M$4) -> 0 | N115: =SUM(B115:M115) -> -10000
A116: Bank Fees | B116: =SUMIFS('Transaction Overview'!$D$2:$D$790,'Transaction Overview'!$I$2:$I$790,$A116,'Transaction Overview'!$H$2:$H$790,B$4) -> -80 | C116: =SUMIFS('Transaction Overview'!$D$2:$D$790,'Transaction Overview'!$I$2:$I$790,$A116,'Transaction Overview'!$H$2:$H$790,C$4) -> -50 | D116: =SUMIFS('Transaction Overview'!$D$2:$D$790,'Transaction Overview'!$I$2:$I$790,$A116,'Transaction Overview'!$H$2:$H$790,D$4) -> -65 | E116: =SUMIFS('Transaction Overview'!$D$2:$D$790,'Transaction Overview'!$I$2:$I$790,$A116,'Transaction Overview'!$H$2:$H$790,E$4) -> -25 | F116: =SUMIFS('Transaction Overview'!$D$2:$D$790,'Transaction Overview'!$I$2:$I$790,$A116,'Transaction Overview'!$H$2:$H$790,F$4) -> -25 | G116: =SUMIFS('Transaction Overview'!$D$2:$D$790,'Transaction Overview'!$I$2:$I$790,$A116,'Transaction Overview'!$H$2:$H$790,G$4) -> -75 | H116: =SUMIFS('Transaction Overview'!$D$2:$D$790,'Transaction Overview'!$I$2:$I$790,$A116,'Transaction Overview'!$H$2:$H$790,H$4) -> -45 | I116: =SUMIFS('Transaction Overview'!$D$2:$D$790,'Transaction Overview'!$I$2:$I$790,$A116,'Transaction Overview'!$H$2:$H$790,I$4) -> -40 | ... M116: =SUMIFS('Transaction Overview'!$D$2:$D$790,'Transaction Overview'!$I$2:$I$790,$A116,'Transaction Overview'!$H$2:$H$790,M$4) -> -370 | N116: =SUM(B116:M116) -> -830
A117: DWG Operations | B117: =SUMIFS('Transaction Overview'!$D$2:$D$790,'Transaction Overview'!$I$2:$I$790,$A117,'Transaction Overview'!$H$2:$H$790,B$4) -> 0 | C117: =SUMIFS('Transaction Overview'!$D$2:$D$790,'Transaction Overview'!$I$2:$I$790,$A117,'Transaction Overview'!$H$2:$H$790,C$4) -> 0 | D117: =SUMIFS('Transaction Overview'!$D$2:$D$790,'Transaction Overview'!$I$2:$I$790,$A117,'Transaction Overview'!$H$2:$H$790,D$4) -> 0 | E117: =SUMIFS('Transaction Overview'!$D$2:$D$790,'Transaction Overview'!$I$2:$I$790,$A117,'Transaction Overview'!$H$2:$H$790,E$4) -> 0 | F117: =SUMIFS('Transaction Overview'!$D$2:$D$790,'Transaction Overview'!$I$2:$I$790,$A117,'Transaction Overview'!$H$2:$H$790,F$4) -> 0 | G117: =SUMIFS('Transaction Overview'!$D$2:$D$790,'Transaction Overview'!$I$2:$I$790,$A117,'Transaction Overview'!$H$2:$H$790,G$4) -> 0 | H117: =SUMIFS('Transaction Overview'!$D$2:$D$790,'Transaction Overview'!$I$2:$I$790,$A117,'Transaction Overview'!$H$2:$H$790,H$4) -> 0 | I117: =SUMIFS('Transaction Overview'!$D$2:$D$790,'Transaction Overview'!$I$2:$I$790,$A117,'Transaction Overview'!$H$2:$H$790,I$4) -> 0 | ... M117: =SUMIFS('Transaction Overview'!$D$2:$D$790,'Transaction Overview'!$I$2:$I$790,$A117,'Transaction Overview'!$H$2:$H$790,M$4) -> -4605.49 | N117: =SUM(B117:M117) -> -4605.49
A118: IRS Tax Payment | B118: =SUMIFS('Transaction Overview'!$D$2:$D$790,'Transaction Overview'!$I$2:$I$790,$A118,'Transaction Overview'!$H$2:$H$790,B$4) -> 0 | C118: =SUMIFS('Transaction Overview'!$D$2:$D$790,'Transaction Overview'!$I$2:$I$790,$A118,'Transaction Overview'!$H$2:$H$790,C$4) -> 0 | D118: =SUMIFS('Transaction Overview'!$D$2:$D$790,'Transaction Overview'!$I$2:$I$790,$A118,'Transaction Overview'!$H$2:$H$790,D$4) -> 0 | E118: =SUMIFS('Transaction Overview'!$D$2:$D$790,'Transaction Overview'!$I$2:$I$790,$A118,'Transaction Overview'!$H$2:$H$790,E$4) -> 0 | F118: =SUMIFS('Transaction Overview'!$D$2:$D$790,'Transaction Overview'!$I$2:$I$790,$A118,'Transaction Overview'!$H$2:$H$790,F$4) -> 0 | G118: =SUMIFS('Transaction Overview'!$D$2:$D$790,'Transaction Overview'!$I$2:$I$790,$A118,'Transaction Overview'!$H$2:$H$790,G$4) -> 0 | H118: =SUMIFS('Transaction Overview'!$D$2:$D$790,'Transaction Overview'!$I$2:$I$790,$A118,'Transaction Overview'!$H$2:$H$790,H$4) -> 0 | I118: =SUMIFS('Transaction Overview'!$D$2:$D$790,'Transaction Overview'!$I$2:$I$790,$A118,'Transaction Overview'!$H$2:$H$790,I$4) -> 0 | ... M118: =SUMIFS('Transaction Overview'!$D$2:$D$790,'Transaction Overview'!$I$2:$I$790,$A118,'Transaction Overview'!$H$2:$H$790,M$4) -> 0 | N118: =SUM(B118:M118) -> -23695.9
...

Sheet Monthly Detail
A1: Chase 9335 — 2025 Activity
A2: Monthly Detail — Spend by Individual Category | Jan 2025 – Dec 2025
A4: Category | B4: Group | C4: =DATE(2025,1,1) -> 45658 | D4: =DATE(2025,2,1) -> 45689 | E4: =DATE(2025,3,1) -> 45717 | F4: =DATE(2025,4,1) -> 45748 | G4: =DATE(2025,5,1) -> 45778 | H4: =DATE(2025,6,1) -> 45809 | I4: =DATE(2025,7,1) -> 45839 | J4: =DATE(2025,8,1) -> 45870 | K4: =DATE(2025,9,1) -> 45901 | L4: =DATE(2025,10,1) -> 45931 | M4: =DATE(2025,11,1) -> 45962 | N4: =DATE(2025,12,1) -> 45992 | O4: Total
A5: Deal Specific: Austin Iron | B5: Deal-Specific | C5: =SUMIFS('Transaction Overview'!$D$2:$D$790,'Transaction Overview'!$G$2:$G$790,$A5,'Transaction Overview'!$H$2:$H$790,C$4) -> 350 | D5: =SUMIFS('Transaction Overview'!$D$2:$D$790,'Transaction Overview'!$G$2:$G$790,$A5,'Transaction Overview'!$H$2:$H$790,D$4) -> 350 | E5: =SUMIFS('Transaction Overview'!$D$2:$D$790,'Transaction Overview'!$G$2:$G$790,$A5,'Transaction Overview'!$H$2:$H$790,E$4) -> 350 | F5: =SUMIFS('Transaction Overview'!$D$2:$D$790,'Transaction Overview'!$G$2:$G$790,$A5,'Transaction Overview'!$H$2:$H$790,F$4) -> 350 | G5: =SUMIFS('Transaction Overview'!$D$2:$D$790,'Transaction Overview'!$G$2:$G$790,$A5,'Transaction Overview'!$H$2:$H$790,G$4) -> 350 | H5: =SUMIFS('Transaction Overview'!$D$2:$D$790,'Transaction Overview'!$G$2:$G$790,$A5,'Transaction Overview'!$H$2:$H$790,H$4) -> 350 | I5: =SUMIFS('Transaction Overview'!$D$2:$D$790,'Transaction Overview'!$G$2:$G$790,$A5,'Transaction Overview'!$H$2:$H$790,I$4) -> 350 | J5: =SUMIFS('Transaction Overview'!$D$2:$D$790,'Transaction Overview'!$G$2:$G$790,$A5,'Transaction Overview'!$H$2:$H$790,J$4) -> 350 | ... N5: =SUMIFS('Transaction Overview'!$D$2:$D$790,'Transaction Overview'!$G$2:$G$790,$A5,'Transaction Overview'!$H$2:$H$790,N$4) -> 350 | O5: =SUM(C5:N5) -> 4200
A6: Deal Specific: Cloverdale | B6: Deal-Specific | C6: =SUMIFS('Transaction Overview'!$D$2:$D$790,'Transaction Overview'!$G$2:$G$790,$A6,'Transaction Overview'!$H$2:$H$790,C$4) -> 0 | D6: =SUMIFS('Transaction Overview'!$D$2:$D$790,'Transaction Overview'!$G$2:$G$790,$A6,'Transaction Overview'!$H$2:$H$790,D$4) -> 0 | E6: =SUMIFS('Transaction Overview'!$D$2:$D$790,'Transaction Overview'!$G$2:$G$790,$A6,'Transaction Overview'!$H$2:$H$790,E$4) -> 0 | F6: =SUMIFS('Transaction Overview'!$D$2:$D$790,'Transaction Overview'!$G$2:$G$790,$A6,'Transaction Overview'!$H$2:$H$790,F$4) -> 0 | G6: =SUMIFS('Transaction Overview'!$D$2:$D$790,'Transaction Overview'!$G$2:$G$790,$A6,'Transaction Overview'!$H$2:$H$790,G$4) -> 0 | H6: =SUMIFS('Transaction Overview'!$D$2:$D$790,'Transaction Overview'!$G$2:$G$790,$A6,'Transaction Overview'!$H$2:$H$790,H$4) -> 0 | I6: =SUMIFS('Transaction Overview'!$D$2:$D$790,'Transaction Overview'!$G$2:$G$790,$A6,'Transaction Overview'!$H$2:$H$790,I$4) -> 0 | J6: =SUMIFS('Transaction Overview'!$D$2:$D$790,'Transaction Overview'!$G$2:$G$790,$A6,'Transaction Overview'!$H$2:$H$790,J$4) -> 0 | ... N6: =SUMIFS('Transaction Overview'!$D$2:$D$790,'Transaction Overview'!$G$2:$G$790,$A6,'Transaction Overview'!$H$2:$H$790,N$4) -> -155000 | O6: =SUM(C6:N6) -> -155000
A7: Deal Specific: Hibbert | B7: Deal-Specific | C7: =SUMIFS('Transaction Overview'!$D$2:$D$790,'Transaction Overview'!$G$2:$G$790,$A7,'Transaction Overview'!$H$2:$H$790,C$4) -> 0 | D7: =SUMIFS('Transaction Overview'!$D$2:$D$790,'Transaction Overview'!$G$2:$G$790,$A7,'Transaction Overview'!$H$2:$H$790,D$4) -> 0 | E7: =SUMIFS('Transaction Overview'!$D$2:$D$790,'Transaction Overview'!$G$2:$G$790,$A7,'Transaction Overview'!$H$2:$H$790,E$4) -> 0 | F7: =SUMIFS('Transaction Overview'!$D$2:$D$790,'Transaction Overview'!$G$2:$G$790,$A7,'Transaction Overview'!$H$2:$H$790,F$4) -> 0 | G7: =SUMIFS('Transaction Overview'!$D$2:$D$790,'Transaction Overview'!$G$2:$G$790,$A7,'Transaction Overview'!$H$2:$H$790,G$4) -> 0 | H7: =SUMIFS('Transaction Overview'!$D$2:$D$790,'Transaction Overview'!$G$2:$G$790,$A7,'Transaction Overview'!$H$2:$H$790,H$4) -> 0 | I7: =SUMIFS('Transaction Overview'!$D$2:$D$790,'Transaction Overview'!$G$2:$G$790,$A7,'Transaction Overview'!$H$2:$H$790,I$4) -> 0 | J7: =SUMIFS('Transaction Overview'!$D$2:$D$790,'Transaction Overview'!$G$2:$G$790,$A7,'Transaction Overview'!$H$2:$H$790,J$4) -> 0 | ... N7: =SUMIFS('Transaction Overview'!$D$2:$D$790,'Transaction Overview'!$G$2:$G$790,$A7,'Transaction Overview'!$H$2:$H$790,N$4) -> 0 | O7: =SUM(C7:N7) -> -46528.05
A8: Deal Specific: JAL Breese | B8: Deal-Specific | C8: =SUMIFS('Transaction Overview'!$D$2:$D$790,'Transaction Overview'!$G$2:$G$790,$A8,'Transaction Overview'!$H$2:$H$790,C$4) -> 0 | D8: =SUMIFS('Transaction Overview'!$D$2:$D$790,'Transaction Overview'!$G$2:$G$790,$A8,'Transaction Overview'!$H$2:$H$790,D$4) -> 0 | E8: =SUMIFS('Transaction Overview'!$D$2:$D$790,'Transaction Overview'!$G$2:$G$790,$A8,'Transaction Overview'!$H$2:$H$790,E$4) -> 0 | F8: =SUMIFS('Transaction Overview'!$D$2:$D$790,'Transaction Overview'!$G$2:$G$790,$A8,'Transaction Overview'!$H$2:$H$790,F$4) -> -50000 | G8: =SUMIFS('Transaction Overview'!$D$2:$D$790,'Transaction Overview'!$G$2:$G$790,$A8,'Transaction Overview'!$H$2:$H$790,G$4) -> 0 | H8: =SUMIFS('Transaction Overview'!$D$2:$D$790,'Transaction Overview'!$G$2:$G$790,$A8,'Transaction Overview'!$H$2:$H$790,H$4) -> 0 | I8: =SUMIFS('Transaction Overview'!$D$2:$D$790,'Transaction Overview'!$G$2:$G$790,$A8,'Transaction Overview'!$H$2:$H$790,I$4) -> 0 | J8: =SUMIFS('Transaction Overview'!$D$2:$D$790,'Transaction Overview'!$G$2:$G$790,$A8,'Transaction Overview'!$H$2:$H$790,J$4) -> 0 | ... N8: =SUMIFS('Transaction Overview'!$D$2:$D$790,'Transaction Overview'!$G$2:$G$790,$A8,'Transaction Overview'!$H$2:$H$790,N$4) -> 0 | O8: =SUM(C8:N8) -> -50000
A9: Deal Specific: Merit-Lancaster | B9: Deal-Specific | C9: =SUMIFS('Transaction Overview'!$D$2:$D$790,'Transaction Overview'!$G$2:$G$790,$A9,'Transaction Overview'!$H$2:$H$790,C$4) -> 461.52 | D9: =SUMIFS('Transaction Overview'!$D$2:$D$790,'Transaction Overview'!$G$2:$G$790,$A9,'Transaction Overview'!$H$2:$H$790,D$4) -> 461.52 | E9: =SUMIFS('Transaction Overview'!$D$2:$D$790,'Transaction Overview'!$G$2:$G$790,$A9,'Transaction Overview'!$H$2:$H$790,E$4) -> 476.41 | F9: =SUMIFS('Transaction Overview'!$D$2:$D$790,'Transaction Overview'!$G$2:$G$790,$A9,'Transaction Overview'!$H$2:$H$790,F$4) -> 476.41 | G9: =SUMIFS('Transaction Overview'!$D$2:$D$790,'Transaction Overview'!$G$2:$G$790,$A9,'Transaction Overview'!$H$2:$H$790,G$4) -> 476.41 | H9: =SUMIFS('Transaction Overview'!$D$2:$D$790,'Transaction Overview'!$G$2:$G$790,$A9,'Transaction Overview'!$H$2:$H$790,H$4) -> 476.41 | I9: =SUMIFS('Transaction Overview'!$D$2:$D$790,'Transaction Overview'!$G$2:$G$790,$A9,'Transaction Overview'!$H$2:$H$790,I$4) -> 476.41 | J9: =SUMIFS('Transaction Overview'!$D$2:$D$790,'Transaction Overview'!$G$2:$G$790,$A9,'Transaction Overview'!$H$2:$H$790,J$4) -> 476.41 | ... N9: =SUMIFS('Transaction Overview'!$D$2:$D$790,'Transaction Overview'!$G$2:$G$790,$A9,'Transaction Overview'!$H$2:$H$790,N$4) -> 476.41 | O9: =SUM(C9:N9) -> 5687.14
A10: Deal Specific: Moab | B10: Deal-Specific | C10: =SUMIFS('Transaction Overview'!$D$2:$D$790,'Transaction Overview'!$G$2:$G$790,$A10,'Transaction Overview'!$H$2:$H$790,C$4) -> 0 | D10: =SUMIFS('Transaction Overview'!$D$2:$D$790,'Transaction Overview'!$G$2:$G$790,$A10,'Transaction Overview'!$H$2:$H$790,D$4) -> 0 | E10: =SUMIFS('Transaction Overview'!$D$2:$D$790,'Transaction Overview'!$G$2:$G$790,$A10,'Transaction Overview'!$H$2:$H$790,E$4) -> 0 | F10: =SUMIFS('Transaction Overview'!$D$2:$D$790,'Transaction Overview'!$G$2:$G$790,$A10,'Transaction Overview'!$H$2:$H$790,F$4) -> 0 | G10: =SUMIFS('Transaction Overview'!$D$2:$D$790,'Transaction Overview'!$G$2:$G$790,$A10,'Transaction Overview'!$H$2:$H$790,G$4) -> 0 | H10: =SUMIFS('Transaction Overview'!$D$2:$D$790,'Transaction Overview'!$G$2:$G$790,$A10,'Transaction Overview'!$H$2:$H$790,H$4) -> 0 | I10: =SUMIFS('Transaction Overview'!$D$2:$D$790,'Transaction Overview'!$G$2:$G$790,$A10,'Transaction Overview'!$H$2:$H$790,I$4) -> 0 | J10: =SUMIFS('Transaction Overview'!$D$2:$D$790,'Transaction Overview'!$G$2:$G$790,$A10,'Transaction Overview'!$H$2:$H$790,J$4) -> 0 | ... N10: =SUMIFS('Transaction Overview'!$D$2:$D$790,'Transaction Overview'!$G$2:$G$790,$A10,'Transaction Overview'!$H$2:$H$790,N$4) -> 5000 | O10: =SUM(C10:N10) -> 6675
A11: Deal Specific: MRM | B11: Deal-Specific | C11: =SUMIFS('Transaction Overview'!$D$2:$D$790,'Transaction Overview'!$G$2:$G$790,$A11,'Transaction Overview'!$H$2:$H$790,C$4) -> 236.37 | D11: =SUMIFS('Transaction Overview'!$D$2:$D$790,'Transaction Overview'!$G$2:$G$790,$A11,'Transaction Overview'!$H$2:$H$790,D$4) -> 236.37 | E11: =SUMIFS('Transaction Overview'!$D$2:$D$790,'Transaction Overview'!$G$2:$G$790,$A11,'Transaction Overview'!$H$2:$H$790,E$4) -> 236.37 | F11: =SUMIFS('Transaction Overview'!$D$2:$D$790,'Transaction Overview'!$G$2:$G$790,$A11,'Transaction Overview'!$H$2:$H$790,F$4) -> 236.37 | G11: =SUMIFS('Transaction Overview'!$D$2:$D$790,'Transaction Overview'!$G$2:$G$790,$A11,'Transaction Overview'!$H$2:$H$790,G$4) -> 236.37 | H11: =SUMIFS('Transaction Overview'!$D$2:$D$790,'Transaction Overview'!$G$2:$G$790,$A11,'Transaction Overview'!$H$2:$H$790,H$4) -> 236.37 | I11: =SUMIFS('Transaction Overview'!$D$2:$D$790,'Transaction Overview'!$G$2:$G$790,$A11,'Transaction Overview'!$H$2:$H$790,I$4) -> 236.37 | J11: =SUMIFS('Transaction Overview'!$D$2:$D$790,'Transaction Overview'!$G$2:$G$790,$A11,'Transaction Overview'!$H$2:$H$790,J$4) -> 236.37 | ... N11: =SUMIFS('Transaction Overview'!$D$2:$D$790,'Transaction Overview'!$G$2:$G$790,$A11,'Transaction Overview'!$H$2:$H$790,N$4) -> 241.87 | O11: =SUM(C11:N11) -> 2847.44
A12: Deal Specific: Rabourn Road | B12: Deal-Specific | C12: =SUMIFS('Transaction Overview'!$D$2:$D$790,'Transaction Overview'!$G$2:$G$790,$A12,'Transaction Overview'!$H$2:$H$790,C$4) -> 0 | D12: =SUMIFS('Transaction Overview'!$D$2:$D$790,'Transaction Overview'!$G$2:$G$790,$A12,'Transaction Overview'!$H$2:$H$790,D$4) -> 0 | E12: =SUMIFS('Transaction Overview'!$D$2:$D$790,'Transaction Overview'!$G$2:$G$790,$A12,'Transaction Overview'!$H$2:$H$790,E$4) -> 0 | F12: =SUMIFS('Transaction Overview'!$D$2:$D$790,'Transaction Overview'!$G$2:$G$790,$A12,'Transaction Overview'!$H$2:$H$790,F$4) -> 0 | G12: =SUMIFS('Transaction Overview'!$D$2:$D$790,'Transaction Overview'!$G$2:$G$790,$A12,'Transaction Overview'!$H$2:$H$790,G$4) -> 0 | H12: =SUMIFS('Transaction Overview'!$D$2:$D$790,'Transaction Overview'!$G$2:$G$790,$A12,'Transaction Overview'!$H$2:$H$790,H$4) -> 0 | I12: =SUMIFS('Transaction Overview'!$D$2:$D$790,'Transaction Overview'!$G$2:$G$790,$A12,'Transaction Overview'!$H$2:$H$790,I$4) -> 0 | J12: =SUMIFS('Transaction Overview'!$D$2:$D$790,'Transaction Overview'!$G$2:$G$790,$A12,'Transaction Overview'!$H$2:$H$790,J$4) -> 233.33 | ... N12: =SUMIFS('Transaction Overview'!$D$2:$D$790,'Transaction Overview'!$G$2:$G$790,$A12,'Transaction Overview'!$H$2:$H$790,N$4) -> 233.33 | O12: =SUM(C12:N12) -> 1166.65
A13: Deal Specific: T&T Machine | B13: Deal-Specific | C13: =SUMIFS('Transaction Overview'!$D$2:$D$790,'Transaction Overview'!$G$2:$G$790,$A13,'Transaction Overview'!$H$2:$H$790,C$4) -> 345.24 | D13: =SUMIFS('Transaction Overview'!$D$2:$D$790,'Transaction Overview'!$G$2:$G$790,$A13,'Transaction Overview'!$H$2:$H$790,D$4) -> 356.38 | E13: =SUMIFS('Transaction Overview'!$D$2:$D$790,'Transaction Overview'!$G$2:$G$790,$A13,'Transaction Overview'!$H$2:$H$790,E$4) -> 356.38 | F13: =SUMIFS('Transaction Overview'!$D$2:$D$790,'Transaction Overview'!$G$2:$G$790,$A13,'Transaction Overview'!$H$2:$H$790,F$4) -> 356.38 | G13: =SUMIFS('Transaction Overview'!$D$2:$D$790,'Transaction Overview'!$G$2:$G$790,$A13,'Transaction Overview'!$H$2:$H$790,G$4) -> 356.38 | H13: =SUMIFS('Transaction Overview'!$D$2:$D$790,'Transaction Overview'!$G$2:$G$790,$A13,'Transaction Overview'!$H$2:$H$790,H$4) -> 356.38 | I13: =SUMIFS('Transaction Overview'!$D$2:$D$790,'Transaction Overview'!$G$2:$G$790,$A13,'Transaction Overview'!$H$2:$H$790,I$4) -> 356.38 | J13: =SUMIFS('Transaction Overview'!$D$2:$D$790,'Transaction Overview'!$G$2:$G$790,$A13,'Transaction Overview'!$H$2:$H$790,J$4) -> 356.38 | ... N13: =SUMIFS('Transaction Overview'!$D$2:$D$790,'Transaction Overview'!$G$2:$G$790,$A13,'Transaction Overview'!$H$2:$H$790,N$4) -> 356.38 | O13: =SUM(C13:N13) -> 4315.42
A14: Incoming Commission: Breese | B14: Commissions — Incoming | C14: =SUMIFS('Transaction Overview'!$D$2:$D$790,'Transaction Overview'!$G$2:$G$790,$A14,'Transaction Overview'!$H$2:$H$790,C$4) -> 0 | D14: =SUMIFS('Transaction Overview'!$D$2:$D$790,'Transaction Overview'!$G$2:$G$790,$A14,'Transaction Overview'!$H$2:$H$790,D$4) -> 0 | E14: =SUMIFS('Transaction Overview'!$D$2:$D$790,'Transaction Overview'!$G$2:$G$790,$A14,'Transaction Overview'!$H$2:$H$790,E$4) -> 0 | F14: =SUMIFS('Transaction Overview'!$D$2:$D$790,'Transaction Overview'!$G$2:$G$790,$A14,'Transaction Overview'!$H$2:$H$790,F$4) -> 0 | G14: =SUMIFS('Transaction Overview'!$D$2:$D$790,'Transaction Overview'!$G$2:$G$790,$A14,'Transaction Overview'!$H$2:$H$790,G$4) -> 0 | H14: =SUMIFS('Transaction Overview'!$D$2:$D$790,'Transaction Overview'!$G$2:$G$790,$A14,'Transaction Overview'!$H$2:$H$790,H$4) -> 0 | I14: =SUMIFS('Transaction Overview'!$D$2:$D$790,'Transaction Overview'!$G$2:$G$790,$A14,'Transaction Overview'!$H$2:$H$790,I$4) -> 269473.73 | J14: =SUMIFS('Transaction Overview'!$D$2:$D$790,'Transaction Overview'!$G$2:$G$790,$A14,'Transaction Overview'!$H$2:$H$790,J$4) -> 0 | ... N14: =SUMIFS('Transaction Overview'!$D$2:$D$790,'Transaction Overview'!$G$2:$G$790,$A14,'Transaction Overview'!$H$2:$H$790,N$4) -> 0 | O14: =SUM(C14:N14) -> 269473.73
A15: Incoming Commission: Butler Weldments | B15: Commissions — Incoming | C15: =SUMIFS('Transaction Overview'!$D$2:$D$790,'Transaction Overview'!$G$2:$G$790,$A15,'Transaction Overview'!$H$2:$H$790,C$4) -> 0 | D15: =SUMIFS('Transaction Overview'!$D$2:$D$790,'Transaction Overview'!$G$2:$G$790,$A15,'Transaction Overview'!$H$2:$H$790,D$4) -> 0 | E15: =SUMIFS('Transaction Overview'!$D$2:$D$790,'Transaction Overview'!$G$2:$G$790,$A15,'Transaction Overview'!$H$2:$H$790,E$4) -> 164150.5 | F15: =SUMIFS('Transaction Overview'!$D$2:$D$790,'Transaction Overview'!$G$2:$G$790,$A15,'Transaction Overview'!$H$2:$H$790,F$4) -> 0 | G15: =SUMIFS('Transaction Overview'!$D$2:$D$790,'Transaction Overview'!$G$2:$G$790,$A15,'Transaction Overview'!$H$2:$H$790,G$4) -> 0 | H15: =SUMIFS('Transaction Overview'!$D$2:$D$790,'Transaction Overview'!$G$2:$G$790,$A15,'Transaction Overview'!$H$2:$H$790,H$4) -> 0 | I15: =SUMIFS('Transaction Overview'!$D$2:$D$790,'Transaction Overview'!$G$2:$G$790,$A15,'Transaction Overview'!$H$2:$H$790,I$4) -> 0 | J15: =SUMIFS('Transaction Overview'!$D$2:$D$790,'Transaction Overview'!$G$2:$G$790,$A15,'Transaction Overview'!$H$2:$H$790,J$4) -> 0 | ... N15: =SUMIFS('Transaction Overview'!$D$2:$D$790,'Transaction Overview'!$G$2:$G$790,$A15,'Transaction Overview'!$H$2:$H$790,N$4) -> 0 | O15: =SUM(C15:N15) -> 164150.5
A16: Incoming Commission: Edge Builder | B16: Commissions — Incoming | C16: =SUMIFS('Transaction Overview'!$D$2:$D$790,'Transaction Overview'!$G$2:$G$790,$A16,'Transaction Overview'!$H$2:$H$790,C$4) -> 148250 | D16: =SUMIFS('Transaction Overview'!$D$2:$D$790,'Transaction Overview'!$G$2:$G$790,$A16,'Transaction Overview'!$H$2:$H$790,D$4) -> 0 | E16: =SUMIFS('Transaction Overview'!$D$2:$D$790,'Transaction Overview'!$G$2:$G$790,$A16,'Transaction Overview'!$H$2:$H$790,E$4) -> 0 | F16: =SUMIFS('Transaction Overview'!$D$2:$D$790,'Transaction Overview'!$G$2:$G$790,$A16,'Transaction Overview'!$H$2:$H$790,F$4) -> 0 | G16: =SUMIFS('Transaction Overview'!$D$2:$D$790,'Transaction Overview'!$G$2:$G$790,$A16,'Transaction Overview'!$H$2:$H$790,G$4) -> 0 | H16: =SUMIFS('Transaction Overview'!$D$2:$D$790,'Transaction Overview'!$G$2:$G$790,$A16,'Transaction Overview'!$H$2:$H$790,H$4) -> 0 | I16: =SUMIFS('Transaction Overview'!$D$2:$D$790,'Transaction Overview'!$G$2:$G$790,$A16,'Transaction Overview'!$H$2:$H$790,I$4) -> 0 | J16: =SUMIFS('Transaction Overview'!$D$2:$D$790,'Transaction Overview'!$G$2:$G$790,$A16,'Transaction Overview'!$H$2:$H$790,J$4) -> 0 | ... N16: =SUMIFS('Transaction Overview'!$D$2:$D$790,'Transaction Overview'!$G$2:$G$790,$A16,'Transaction Overview'!$H$2:$H$790,N$4) -> 0 | O16: =SUM(C16:N16) -> 148250
... A82: Deposit | B82: Uncategorized — Review | C82: =SUMIFS('Transaction Overview'!$D$2:$D$790,'Transaction Overview'!$G$2:$G$790,$A82,'Transaction Overview'!$H$2:$H$790,C$4) -> 0 | D82: =SUMIFS('Transaction Overview'!$D$2:$D$790,'Transaction Overview'!$G$2:$G$790,$A82,'Transaction Overview'!$H$2:$H$790,D$4) -> 0 | E82: =SUMIFS('Transaction Overview'!$D$2:$D$790,'Transaction Overview'!$G$2:$G$790,$A82,'Transaction Overview'!$H$2:$H$790,E$4) -> 0 | F82: =SUMIFS('Transaction Overview'!$D$2:$D$790,'Transaction Overview'!$G$2:$G$790,$A82,'Transaction Overview'!$H$2:$H$790,F$4) -> 0 | G82: =SUMIFS('Transaction Overview'!$D$2:$D$790,'Transaction Overview'!$G$2:$G$790,$A82,'Transaction Overview'!$H$2:$H$790,G$4) -> 0 | H82: =SUMIFS('Transaction Overview'!$D$2:$D$790,'Transaction Overview'!$G$2:$G$790,$A82,'Transaction Overview'!$H$2:$H$790,H$4) -> 0 | I82: =SUMIFS('Transaction Overview'!$D$2:$D$790,'Transaction Overview'!$G$2:$G$790,$A82,'Transaction Overview'!$H$2:$H$790,I$4) -> 0 | J82: =SUMIFS('Transaction Overview'!$D$2:$D$790,'Transaction Overview'!$G$2:$G$790,$A82,'Transaction Overview'!$H$2:$H$790,J$4) -> 3000 | ... N82: =SUMIFS('Transaction Overview'!$D$2:$D$790,'Transaction Overview'!$G$2:$G$790,$A82,'Transaction Overview'!$H$2:$H$790,N$4) -> 0 | O82: =SUM(C82:N82) -> 3000

Sheet Transfer In
A1: Chase 9335 — 2025 Activity — Transfer In
A2: Statement | Jan 2025 – Dec 2025
A4: SUMMARY
A5: Total | C5: =SUMIFS('Transaction Overview'!$D$2:$D$790,'Transaction Overview'!$E$2:$E$790,"ACCT_XFER",'Transaction Overview'!$D$2:$D$790,">0")+SUMIFS('Transaction Overview'!$D$2:$D$790,'Transaction Overview'!$E$2:$E$790,"CHASE_TO_PARTNERFI",'Transaction Overview'!$D$2:$D$790,">0")+SUMIFS('Transaction Overview'!$D$2:$D$790,'Transaction Overview'!$E$2:$E$790,"QUICKPAY_DEBIT",'Transaction Overview'!$D$2:$D$790,">0") -> 738650
A6: # Transactions | C6: =COUNTIFS('Transaction Overview'!$E$2:$E$790,"ACCT_XFER",'Transaction Overview'!$D$2:$D$790,">0")+COUNTIFS('Transaction Overview'!$E$2:$E$790,"CHASE_TO_PARTNERFI",'Transaction Overview'!$D$2:$D$790,">0")+COUNTIFS('Transaction Overview'!$E$2:$E$790,"QUICKPAY_DEBIT",'Transaction Overview'!$D$2:$D$790,">0") -> 10
A8: BY COUNTERPARTY
A9: Counterparty | B9: # Txns | C9: Amount
A10: Transfer from Breese | B10: =COUNTIFS('Transaction Overview'!$G$2:$G$790,$A10,'Transaction Overview'!$D$2:$D$790,">0") -> 2 | C10: =SUMIFS('Transaction Overview'!$D$2:$D$790,'Transaction Overview'!$G$2:$G$790,$A10,'Transaction Overview'!$D$2:$D$790,">0") -> 150000
A11: Transfer from DWG Capital Partners | B11: =COUNTIFS('Transaction Overview'!$G$2:$G$790,$A11,'Transaction Overview'!$D$2:$D$790,">0") -> 3 | C11: =SUMIFS('Transaction Overview'!$D$2:$D$790,'Transaction Overview'!$G$2:$G$790,$A11,'Transaction Overview'!$D$2:$D$790,">0") -> 383350
A12: Transfer from Hibbert | B12: =COUNTIFS('Transaction Overview'!$G$2:$G$790,$A12,'Transaction Overview'!$D$2:$D$790,">0") -> 2 | C12: =SUMIFS('Transaction Overview'!$D$2:$D$790,'Transaction Overview'!$G$2:$G$790,$A12,'Transaction Overview'!$D$2:$D$790,">0") -> 117500
A13: Transfer from Kalkaska Screw | B13: =COUNTIFS('Transaction Overview'!$G$2:$G$790,$A13,'Transaction Overview'!$D$2:$D$790,">0") -> 2 | C13: =SUMIFS('Transaction Overview'!$D$2:$D$790,'Transaction Overview'!$G$2:$G$790,$A13,'Transaction Overview'!$D$2:$D$790,">0") -> 62800
A14: Transfer to MRM | B14: =COUNTIFS('Transaction Overview'!$G$2:$G$790,$A14,'Transaction Overview'!$D$2:$D$790,">0") -> 1 | C14: =SUMIFS('Transaction Overview'!$D$2:$D$790,'Transaction Overview'!$G$2:$G$790,$A14,'Transaction Overview'!$D$2:$D$790,">0") -> 25000
A15: Subtotal | B15: =SUM(B10:B14) -> 10 | C15: =SUM(C10:C14) -> 738650
A16: DETAIL
A17: Date | B17: Counterparty | C17: Amount
A18: {=_xlfn._xlws.FILTER('Transaction Overview'!$B$2:$B$790,(('Transaction Overview'!$E$2:$E$790="ACCT_XFER")+('Transaction Overview'!$E$2:$E$790="CHASE_TO_PARTNERFI")+('Transaction Overview'!$E$2:$E$790="QUICKPAY_DEBIT"))*('Transaction Overview'!$D$2:$D$790>0))} -> 46022 | B18: {=_xlfn._xlws.FILTER('Transaction Overview'!$G$2:$G$790,(('Transaction Overview'!$E$2:$E$790="ACCT_XFER")+('Transaction Overview'!$E$2:$E$790="CHASE_TO_PARTNERFI")+('Transaction Overview'!$E$2:$E$790="QUICKPAY_DEBIT"))*('Transaction Overview'!$D$2:$D$790>0))} -> Transfer from DWG Capital Partners | C18: {=_xlfn._xlws.FILTER('Transaction Overview'!$D$2:$D$790,(('Transaction Overview'!$E$2:$E$790="ACCT_XFER")+('Transaction Overview'!$E$2:$E$790="CHASE_TO_PARTNERFI")+('Transaction Overview'!$E$2:$E$790="QUICKPAY_DEBIT"))*('Transaction Overview'!$D$2:$D$790>0))} -> 23350
A19: 46013 | B19: Transfer from DWG Capital Partners | C19: 90000
A20: 46006 | B20: Transfer from Hibbert | C20: 100000
A21: 45987 | B21: Transfer from DWG Capital Partners | C21: 270000
A22: 45936 | B22: Transfer from Kalkaska Screw | C22: 12800
A23: 45931 | B23: Transfer to MRM | C23: 25000
A24: 45910 | B24: Transfer from Breese | C24: 50000
A25: 45852 | B25: Transfer from Breese | C25: 100000
A26: 45793 | B26: Transfer from Hibbert | C26: 17500
A27: 45756 | B27: Transfer from Kalkaska Screw | C27: 50000

Sheet Transfer Out
A1: Chase 9335 — 2025 Activity — Transfer Out
A2: Statement | Jan 2025 – Dec 2025
A4: SUMMARY
A5: Total | C5: =SUMIFS('Transaction Overview'!$D$2:$D$790,'Transaction Overview'!$E$2:$E$790,"ACCT_XFER",'Transaction Overview'!$D$2:$D$790,"<0")+SUMIFS('Transaction Overview'!$D$2:$D$790,'Transaction Overview'!$E$2:$E$790,"CHASE_TO_PARTNERFI",'Transaction Overview'!$D$2:$D$790,"<0")+SUMIFS('Transaction Overview'!$D$2:$D$790,'Transaction Overview'!$E$2:$E$790,"QUICKPAY_DEBIT",'Transaction Overview'!$D$2:$D$790,"<0") -> -1175986.7
A6: # Transactions | C6: =COUNTIFS('Transaction Overview'!$E$2:$E$790,"ACCT_XFER",'Transaction Overview'!$D$2:$D$790,"<0")+COUNTIFS('Transaction Overview'!$E$2:$E$790,"CHASE_TO_PARTNERFI",'Transaction Overview'!$D$2:$D$790,"<0")+COUNTIFS('Transaction Overview'!$E$2:$E$790,"QUICKPAY_DEBIT",'Transaction Overview'!$D$2:$D$790,"<0") -> 83
A8: BY COUNTERPARTY
A9: Counterparty | B9: # Txns | C9: Amount
A10: Office/Miscellaneous Reimbursement - Mike P. | B10: =COUNTIFS('Transaction Overview'!$G$2:$G$790,$A10,'Transaction Overview'!$D$2:$D$790,"<0") -> 9 | C10: =SUMIFS('Transaction Overview'!$D$2:$D$790,'Transaction Overview'!$G$2:$G$790,$A10,'Transaction Overview'!$D$2:$D$790,"<0") -> -872
A11: Outgoing wire to JC Whitner | B11: =COUNTIFS('Transaction Overview'!$G$2:$G$790,$A11,'Transaction Overview'!$D$2:$D$790,"<0") -> 3 | C11: =SUMIFS('Transaction Overview'!$D$2:$D$790,'Transaction Overview'!$G$2:$G$790,$A11,'Transaction Overview'!$D$2:$D$790,"<0") -> -35000
A12: Transfer to Angela Dunning | B12: =COUNTIFS('Transaction Overview'!$G$2:$G$790,$A12,'Transaction Overview'!$D$2:$D$790,"<0") -> 1 | C12: =SUMIFS('Transaction Overview'!$D$2:$D$790,'Transaction Overview'!$G$2:$G$790,$A12,'Transaction Overview'!$D$2:$D$790,"<0") -> -1000
A13: Transfer to Ava | B13: =COUNTIFS('Transaction Overview'!$G$2:$G$790,$A13,'Transaction Overview'!$D$2:$D$790,"<0") -> 1 | C13: =SUMIFS('Transaction Overview'!$D$2:$D$790,'Transaction Overview'!$G$2:$G$790,$A13,'Transaction Overview'!$D$2:$D$790,"<0") -> -500
A14: Transfer to DWG Capital Group | B14: =COUNTIFS('Transaction Overview'!$G$2:$G$790,$A14,'Transaction Overview'!$D$2:$D$790,"<0") -> 34 | C14: =SUMIFS('Transaction Overview'!$D$2:$D$790,'Transaction Overview'!$G$2:$G$790,$A14,'Transaction Overview'!$D$2:$D$790,"<0") -> -678000
A15: Transfer to DWG Capital Group_Costar | B15: =COUNTIFS('Transaction Overview'!$G$2:$G$790,$A15,'Transaction Overview'!$D$2:$D$790,"<0") -> 2 | C15: =SUMIFS('Transaction Overview'!$D$2:$D$790,'Transaction Overview'!$G$2:$G$790,$A15,'Transaction Overview'!$D$2:$D$790,"<0") -> -6450
A16: Transfer to DWG Capital Partners | B16: =COUNTIFS('Transaction Overview'!$G$2:$G$790,$A16,'Transaction Overview'!$D$2:$D$790,"<0") -> 17 | C16: =SUMIFS('Transaction Overview'!$D$2:$D$790,'Transaction Overview'!$G$2:$G$790,$A16,'Transaction Overview'!$D$2:$D$790,"<0") -> -271500
A17: Transfer to Edgebuilders | B17: =COUNTIFS('Transaction Overview'!$G$2:$G$790,$A17,'Transaction Overview'!$D$2:$D$790,"<0") -> 1 | C17: =SUMIFS('Transaction Overview'!$D$2:$D$790,'Transaction Overview'!$G$2:$G$790,$A17,'Transaction Overview'!$D$2:$D$790,"<0") -> -50000
A18: Transfer to Hibbert | B18: =COUNTIFS('Transaction Overview'!$G$2:$G$790,$A18,'Transaction Overview'!$D$2:$D$790,"<0") -> 5 | C18: =SUMIFS('Transaction Overview'!$D$2:$D$790,'Transaction Overview'!$G$2:$G$790,$A18,'Transaction Overview'!$D$2:$D$790,"<0") -> -50918.73
A19: Transfer to JAL Southbend | B19: =COUNTIFS('Transaction Overview'!$G$2:$G$790,$A19,'Transaction Overview'!$D$2:$D$790,"<0") -> 3 | C19: =SUMIFS('Transaction Overview'!$D$2:$D$790,'Transaction Overview'!$G$2:$G$790,$A19,'Transaction Overview'!$D$2:$D$790,"<0") -> -57349
A20: Transfer to Kalkaska Screw | B20: =COUNTIFS('Transaction Overview'!$G$2:$G$790,$A20,'Transaction Overview'!$D$2:$D$790,"<0") -> 1 | C20: =SUMIFS('Transaction Overview'!$D$2:$D$790,'Transaction Overview'!$G$2:$G$790,$A20,'Transaction Overview'!$D$2:$D$790,"<0") -> -12800
A21: Transfer to Kecy Metals | B21: =COUNTIFS('Transaction Overview'!$G$2:$G$790,$A21,'Transaction Overview'!$D$2:$D$790,"<0") -> 1 | C21: =SUMIFS('Transaction Overview'!$D$2:$D$790,'Transaction Overview'!$G$2:$G$790,$A21,'Transaction Overview'!$D$2:$D$790,"<0") -> -17000
... A27: Zelle to Sentha | B27: =COUNTIFS('Transaction Overview'!$G$2:$G$790,$A27,'Transaction Overview'!$D$2:$D$790,"<0") -> 1 | C27: =SUMIFS('Transaction Overview'!$D$2:$D$790,'Transaction Overview'!$G$2:$G$790,$A27,'Transaction Overview'!$D$2:$D$790,"<0") -> -350
A28: Subtotal | B28: =SUM(B10:B27) -> 85 | C28: =SUM(C10:C27) -> -1203486.7
A29: DETAIL
A30: Date | B30: Counterparty | C30: Amount
A31: {=_xlfn._xlws.FILTER('Transaction Overview'!$B$2:$B$790,(('Transaction Overview'!$E$2:$E$790="ACCT_XFER")+('Transaction Overview'!$E$2:$E$790="CHASE_TO_PARTNERFI")+('Transaction Overview'!$E$2:$E$790="QUICKPAY_DEBIT"))*('Transaction Overview'!$D$2:$D$790<0))} -> 46022 | B31: {=_xlfn._xlws.FILTER('Transaction Overview'!$G$2:$G$790,(('Transaction Overview'!$E$2:$E$790="ACCT_XFER")+('Transaction Overview'!$E$2:$E$790="CHASE_TO_PARTNERFI")+('Transaction Overview'!$E$2:$E$790="QUICKPAY_DEBIT"))*('Transaction Overview'!$D$2:$D$790<0))} -> Transfer to JAL Southbend | C31: {=_xlfn._xlws.FILTER('Transaction Overview'!$D$2:$D$790,(('Transaction Overview'!$E$2:$E$790="ACCT_XFER")+('Transaction Overview'!$E$2:$E$790="CHASE_TO_PARTNERFI")+('Transaction Overview'!$E$2:$E$790="QUICKPAY_DEBIT"))*('Transaction Overview'!$D$2:$D$790<0))} -> -33349
A32: 46008 | B32: Transfer to DWG Capital Partners | C32: -20000
A33: 46007 | B33: Transfer to Hibbert | C33: -8000
A34: 46007 | B34: Office/Miscellaneous Reimbursement - Mike P. | C34: -65
A35: 46003 | B35: Transfer to DWG Capital Partners | C35: -5000
A36: 46002 | B36: Transfer to Hibbert | C36: -20000
A37: 46002 | B37: Transfer to Kecy Metals | C37: -17000
A38: 46002 | B38: Transfer to JAL Southbend | C38: -14000
A39: 45995 | B39: Office/Miscellaneous Reimbursement - Mike P. | C39: -110
A40: 45995 | B40: Transfer to DWG Capital Group | C40: -20000
A41: 45995 | B41: Transfer to DWG Capital Group_Costar | C41: -1300
A42: 45994 | B42: Transfer to DWG Capital Partners | C42: -500
A43: 45993 | B43: Transfer to DWG Capital Partners | C43: -500
... A113: 45671 | B113: Transfer to Edgebuilders | C113: -50000

Sheet Wire In
A1: Chase 9335 — 2025 Activity — Wire In
A2: Statement | Jan 2025 – Dec 2025
A4: SUMMARY
A5: Total | C5: =SUMIFS('Transaction Overview'!$D$2:$D$790,'Transaction Overview'!$E$2:$E$790,"WIRE_INCOMING") -> 1888938.6
A6: # Transactions | C6: =COUNTIFS('Transaction Overview'!$E$2:$E$790,"WIRE_INCOMING") -> 21
A8: BY COUNTERPARTY
A9: Counterparty | B9: # Txns | C9: Amount
A10: Deal Specific: Moab | B10: =COUNTIFS('Transaction Overview'!$G$2:$G$790,$A10,'Transaction Overview'!$E$2:$E$790,"WIRE_INCOMING") -> 1 | C10: =SUMIFS('Transaction Overview'!$D$2:$D$790,'Transaction Overview'!$G$2:$G$790,$A10,'Transaction Overview'!$E$2:$E$790,"WIRE_INCOMING") -> 625000
A11: Incoming Commission: Breese | B11: =COUNTIFS('Transaction Overview'!$G$2:$G$790,$A11,'Transaction Overview'!$E$2:$E$790,"WIRE_INCOMING") -> 3 | C11: =SUMIFS('Transaction Overview'!$D$2:$D$790,'Transaction Overview'!$G$2:$G$790,$A11,'Transaction Overview'!$E$2:$E$790,"WIRE_INCOMING") -> 269473.73
A12: Incoming Commission: Butler Weldments | B12: =COUNTIFS('Transaction Overview'!$G$2:$G$790,$A12,'Transaction Overview'!$E$2:$E$790,"WIRE_INCOMING") -> 2 | C12: =SUMIFS('Transaction Overview'!$D$2:$D$790,'Transaction Overview'!$G$2:$G$790,$A12,'Transaction Overview'!$E$2:$E$790,"WIRE_INCOMING") -> 164150.5
A13: Incoming Commission: Edge Builder | B13: =COUNTIFS('Transaction Overview'!$G$2:$G$790,$A13,'Transaction Overview'!$E$2:$E$790,"WIRE_INCOMING") -> 2 | C13: =SUMIFS('Transaction Overview'!$D$2:$D$790,'Transaction Overview'!$G$2:$G$790,$A13,'Transaction Overview'!$E$2:$E$790,"WIRE_INCOMING") -> 148250
A14: Incoming Commission: Kalkaska Screw | B14: =COUNTIFS('Transaction Overview'!$G$2:$G$790,$A14,'Transaction Overview'!$E$2:$E$790,"WIRE_INCOMING") -> 2 | C14: =SUMIFS('Transaction Overview'!$D$2:$D$790,'Transaction Overview'!$G$2:$G$790,$A14,'Transaction Overview'!$E$2:$E$790,"WIRE_INCOMING") -> 133875
A15: Incoming Commission: Stryten Energy | B15: =COUNTIFS('Transaction Overview'!$G$2:$G$790,$A15,'Transaction Overview'!$E$2:$E$790,"WIRE_INCOMING") -> 4 | C15: =SUMIFS('Transaction Overview'!$D$2:$D$790,'Transaction Overview'!$G$2:$G$790,$A15,'Transaction Overview'!$E$2:$E$790,"WIRE_INCOMING") -> 318189.39
A16: Incoming Crystal Asset Management Wire | B16: =COUNTIFS('Transaction Overview'!$G$2:$G$790,$A16,'Transaction Overview'!$E$2:$E$790,"WIRE_INCOMING") -> 1 | C16: =SUMIFS('Transaction Overview'!$D$2:$D$790,'Transaction Overview'!$G$2:$G$790,$A16,'Transaction Overview'!$E$2:$E$790,"WIRE_INCOMING") -> 100000
A17: Incoming wire from JC Whitner | B17: =COUNTIFS('Transaction Overview'!$G$2:$G$790,$A17,'Transaction Overview'!$E$2:$E$790,"WIRE_INCOMING") -> 1 | C17: =SUMIFS('Transaction Overview'!$D$2:$D$790,'Transaction Overview'!$G$2:$G$790,$A17,'Transaction Overview'!$E$2:$E$790,"WIRE_INCOMING") -> 20000
A18: MAG - Admeer Advisory Reimbursement | B18: =COUNTIFS('Transaction Overview'!$G$2:$G$790,$A18,'Transaction Overview'!$E$2:$E$790,"WIRE_INCOMING") -> 4 | C18: =SUMIFS('Transaction Overview'!$D$2:$D$790,'Transaction Overview'!$G$2:$G$790,$A18,'Transaction Overview'!$E$2:$E$790,"WIRE_INCOMING") -> 35000
A19: MAG Capital Partners Pass-Through Wire – 70/30 Split | B19: =COUNTIFS('Transaction Overview'!$G$2:$G$790,$A19,'Transaction Overview'!$E$2:$E$790,"WIRE_INCOMING") -> 1 | C19: =SUMIFS('Transaction Overview'!$D$2:$D$790,'Transaction Overview'!$G$2:$G$790,$A19,'Transaction Overview'!$E$2:$E$790,"WIRE_INCOMING") -> 75000
A20: Subtotal | B20: =SUM(B10:B19) -> 21 | C20: =SUM(C10:C19) -> 1888938.6
A21: DETAIL
A22: Date | B22: Counterparty | C22: Amount
A23: {=_xlfn._xlws.FILTER('Transaction Overview'!$B$2:$B$790,('Transaction Overview'!$E$2:$E$790="WIRE_INCOMING"))} -> 46008 | B23: {=_xlfn._xlws.FILTER('Transaction Overview'!$G$2:$G$790,('Transaction Overview'!$E$2:$E$790="WIRE_INCOMING"))} -> Deal Specific: Moab | C23: {=_xlfn._xlws.FILTER('Transaction Overview'!$D$2:$D$790,('Transaction Overview'!$E$2:$E$790="WIRE_INCOMING"))} -> 625000
A24: 46003 | B24: MAG Capital Partners Pass-Through Wire – 70/30 Split | C24: 75000
A25: 45993 | B25: Incoming Commission: Stryten Energy | C25: 50000
A26: 45993 | B26: Incoming Commission: Stryten Energy | C26: 75750
A27: 45992 | B27: Incoming Commission: Stryten Energy | C27: 75750
A28: 45992 | B28: Incoming Commission: Stryten Energy | C28: 116689.39
A29: 45884 | B29: Incoming wire from JC Whitner | C29: 20000
A30: 45853 | B30: Incoming Commission: Breese | C30: 6973.73
A31: 45848 | B31: Incoming Commission: Breese | C31: 52500
A32: 45848 | B32: Incoming Commission: Breese | C32: 210000
A33: 45821 | B33: Incoming Crystal Asset Management Wire | C33: 100000
A34: 45775 | B34: Incoming Commission: Kalkaska Screw | C34: 26775
A35: 45775 | B35: Incoming Commission: Kalkaska Screw | C35: 107100
... A43: 45659 | B43: Incoming Commission: Edge Builder | C43: 78600

Sheet Wire Out
A1: Chase 9335 — 2025 Activity — Wire Out
A2: Statement | Jan 2025 – Dec 2025
A4: SUMMARY
A5: Total | C5: =SUMIFS('Transaction Overview'!$D$2:$D$790,'Transaction Overview'!$E$2:$E$790,"WIRE_OUTGOING") -> -1109100
A6: # Transactions | C6: =COUNTIFS('Transaction Overview'!$E$2:$E$790,"WIRE_OUTGOING") -> 23
A8: BY COUNTERPARTY
A9: Counterparty | B9: # Txns | C9: Amount
A10: Deal Specific: Cloverdale | B10: =COUNTIFS('Transaction Overview'!$G$2:$G$790,$A10,'Transaction Overview'!$E$2:$E$790,"WIRE_OUTGOING") -> 1 | C10: =SUMIFS('Transaction Overview'!$D$2:$D$790,'Transaction Overview'!$G$2:$G$790,$A10,'Transaction Overview'!$E$2:$E$790,"WIRE_OUTGOING") -> -100000
A11: Deal Specific: JAL Breese | B11: =COUNTIFS('Transaction Overview'!$G$2:$G$790,$A11,'Transaction Overview'!$E$2:$E$790,"WIRE_OUTGOING") -> 1 | C11: =SUMIFS('Transaction Overview'!$D$2:$D$790,'Transaction Overview'!$G$2:$G$790,$A11,'Transaction Overview'!$E$2:$E$790,"WIRE_OUTGOING") -> -50000
A12: Deal Specific: Moab | B12: =COUNTIFS('Transaction Overview'!$G$2:$G$790,$A12,'Transaction Overview'!$E$2:$E$790,"WIRE_OUTGOING") -> 1 | C12: =SUMIFS('Transaction Overview'!$D$2:$D$790,'Transaction Overview'!$G$2:$G$790,$A12,'Transaction Overview'!$E$2:$E$790,"WIRE_OUTGOING") -> -620000
A13: Due to Andrew – MAG Pass-Through 30% | B13: =COUNTIFS('Transaction Overview'!$G$2:$G$790,$A13,'Transaction Overview'!$E$2:$E$790,"WIRE_OUTGOING") -> 1 | C13: =SUMIFS('Transaction Overview'!$D$2:$D$790,'Transaction Overview'!$G$2:$G$790,$A13,'Transaction Overview'!$E$2:$E$790,"WIRE_OUTGOING") -> -21000
A14: Due to Dax – MAG Pass-Through 70% | B14: =COUNTIFS('Transaction Overview'!$G$2:$G$790,$A14,'Transaction Overview'!$E$2:$E$790,"WIRE_OUTGOING") -> 1 | C14: =SUMIFS('Transaction Overview'!$D$2:$D$790,'Transaction Overview'!$G$2:$G$790,$A14,'Transaction Overview'!$E$2:$E$790,"WIRE_OUTGOING") -> -39000
A15: Employee Bonus | B15: =COUNTIFS('Transaction Overview'!$G$2:$G$790,$A15,'Transaction Overview'!$E$2:$E$790,"WIRE_OUTGOING") -> 2 | C15: =SUMIFS('Transaction Overview'!$D$2:$D$790,'Transaction Overview'!$G$2:$G$790,$A15,'Transaction Overview'!$E$2:$E$790,"WIRE_OUTGOING") -> -16000
A16: MAG - Admeer Advisory Transfer | B16: =COUNTIFS('Transaction Overview'!$G$2:$G$790,$A16,'Transaction Overview'!$E$2:$E$790,"WIRE_OUTGOING") -> 7 | C16: =SUMIFS('Transaction Overview'!$D$2:$D$790,'Transaction Overview'!$G$2:$G$790,$A16,'Transaction Overview'!$E$2:$E$790,"WIRE_OUTGOING") -> -42450
A17: Outgoing Crystal Asset Management Wire | B17: =COUNTIFS('Transaction Overview'!$G$2:$G$790,$A17,'Transaction Overview'!$E$2:$E$790,"WIRE_OUTGOING") -> 1 | C17: =SUMIFS('Transaction Overview'!$D$2:$D$790,'Transaction Overview'!$G$2:$G$790,$A17,'Transaction Overview'!$E$2:$E$790,"WIRE_OUTGOING") -> -100000
A18: Outgoing wire to JC Whitner | B18: =COUNTIFS('Transaction Overview'!$G$2:$G$790,$A18,'Transaction Overview'!$E$2:$E$790,"WIRE_OUTGOING") -> 2 | C18: =SUMIFS('Transaction Overview'!$D$2:$D$790,'Transaction Overview'!$G$2:$G$790,$A18,'Transaction Overview'!$E$2:$E$790,"WIRE_OUTGOING") -> -27500
A19: Wire Out — Edge Builder Commission Payments | B19: =COUNTIFS('Transaction Overview'!$G$2:$G$790,$A19,'Transaction Overview'!$E$2:$E$790,"WIRE_OUTGOING") -> 1 | C19: =SUMIFS('Transaction Overview'!$D$2:$D$790,'Transaction Overview'!$G$2:$G$790,$A19,'Transaction Overview'!$E$2:$E$790,"WIRE_OUTGOING") -> -23830
A20: Wire Out — Stryten Commission Payments | B20: =COUNTIFS('Transaction Overview'!$G$2:$G$790,$A20,'Transaction Overview'!$E$2:$E$790,"WIRE_OUTGOING") -> 3 | C20: =SUMIFS('Transaction Overview'!$D$2:$D$790,'Transaction Overview'!$G$2:$G$790,$A20,'Transaction Overview'!$E$2:$E$790,"WIRE_OUTGOING") -> -47820
A21: Wire to Binder Family Trust - TBD | B21: =COUNTIFS('Transaction Overview'!$G$2:$G$790,$A21,'Transaction Overview'!$E$2:$E$790,"WIRE_OUTGOING") -> 1 | C21: =SUMIFS('Transaction Overview'!$D$2:$D$790,'Transaction Overview'!$G$2:$G$790,$A21,'Transaction Overview'!$E$2:$E$790,"WIRE_OUTGOING") -> -6000
A22: Wire to Top Shield Roofing CO | B22: =COUNTIFS('Transaction Overview'!$G$2:$G$790,$A22,'Transaction Overview'!$E$2:$E$790,"WIRE_OUTGOING") -> 1 | C22: =SUMIFS('Transaction Overview'!$D$2:$D$790,'Transaction Overview'!$G$2:$G$790,$A22,'Transaction Overview'!$E$2:$E$790,"WIRE_OUTGOING") -> -15500
A23: Subtotal | B23: =SUM(B10:B22) -> 23 | C23: =SUM(C10:C22) -> -1109100
A24: DETAIL
A25: Date | B25: Counterparty | C25: Amount
A26: {=_xlfn._xlws.FILTER('Transaction Overview'!$B$2:$B$790,('Transaction Overview'!$E$2:$E$790="WIRE_OUTGOING"))} -> 46009 | B26: {=_xlfn._xlws.FILTER('Transaction Overview'!$G$2:$G$790,('Transaction Overview'!$E$2:$E$790="WIRE_OUTGOING"))} -> Deal Specific: Moab | C26: {=_xlfn._xlws.FILTER('Transaction Overview'!$D$2:$D$790,('Transaction Overview'!$E$2:$E$790="WIRE_OUTGOING"))} -> -620000
A27: 46007 | B27: Due to Dax – MAG Pass-Through 70% | C27: -39000
A28: 46007 | B28: Due to Andrew – MAG Pass-Through 30% | C28: -21000
A29: 46006 | B29: Deal Specific: Cloverdale | C29: -100000
A30: 45996 | B30: Wire to Top Shield Roofing CO | C30: -15500
A31: 45995 | B31: Wire Out — Stryten Commission Payments | C31: -25000
A32: 45995 | B32: Wire Out — Stryten Commission Payments | C32: -17820
A33: 45994 | B33: Wire Out — Stryten Commission Payments | C33: -5000
A34: 45994 | B34: Outgoing wire to JC Whitner | C34: -10000
A35: 45993 | B35: Employee Bonus | C35: -10000
A36: 45993 | B36: Employee Bonus | C36: -6000
A37: 45950 | B37: MAG - Admeer Advisory Transfer | C37: -5000
A38: 45933 | B38: MAG - Admeer Advisory Transfer | C38: -5000
... A48: 45660 | B48: Wire Out — Edge Builder Commission Payments | C48: -23830

Sheet Transaction Overview
A1: Details | B1: Posting Date | C1: Description | D1: Amount | E1: Type | F1: Balance | G1: Category | H1: Month | I1: Combined Category | J1: Group
A2: ='2025_Chase9335_Activity_2026062'!A2 -> DEBIT | B2: ='2025_Chase9335_Activity_2026062'!B2 -> 46022 | C2: ='2025_Chase9335_Activity_2026062'!C2 -> Online Transfer to CHK ...9769 transaction#: 27532473331 12/31 | D2: ='2025_Chase9335_Activity_2026062'!D2 -> -33349 | E2: ='2025_Chase9335_Activity_2026062'!E2 -> ACCT_XFER | F2: ='2025_Chase9335_Activity_2026062'!F2 -> 263614.45 | G2: ='2025_Chase9335_Activity_2026062'!G2 -> Transfer to JAL Southbend | H2: =IF($B2="","",DATE(YEAR($B2),MONTH($B2),1)) -> 45992 | I2: =IF($G2="","Uncategorized — Review",IFERROR(_xlfn.XLOOKUP($G2,Mapping!$A:$A,Mapping!$B:$B),"Uncategorized — Review")) -> Transfer to JAL Southbend | J2: =IF($G2="","Uncategorized — Review",IFERROR(_xlfn.XLOOKUP($G2,Mapping!$A:$A,Mapping!$C:$C),"Uncategorized — Review")) -> Intercompany & Savings Transfers
A3: ='2025_Chase9335_Activity_2026062'!A3 -> DEBIT | B3: ='2025_Chase9335_Activity_2026062'!B3 -> 46022 | C3: ='2025_Chase9335_Activity_2026062'!C3 -> APPLE.COM/BILL 866-712-7753 CA 12/31 | D3: ='2025_Chase9335_Activity_2026062'!D3 -> -51.45 | E3: ='2025_Chase9335_Activity_2026062'!E3 -> DEBIT_CARD | F3: ='2025_Chase9335_Activity_2026062'!F3 -> 296963.45 | G3: ='2025_Chase9335_Activity_2026062'!G3 -> Personal - Subscriptions | H3: =IF($B3="","",DATE(YEAR($B3),MONTH($B3),1)) -> 45992 | I3: =IF($G3="","Uncategorized — Review",IFERROR(_xlfn.XLOOKUP($G3,Mapping!$A:$A,Mapping!$B:$B),"Uncategorized — Review")) -> Personal - Subscriptions | J3: =IF($G3="","Uncategorized — Review",IFERROR(_xlfn.XLOOKUP($G3,Mapping!$A:$A,Mapping!$C:$C),"Uncategorized — Review")) -> Personal — Owner
A4: ='2025_Chase9335_Activity_2026062'!A4 -> CREDIT | B4: ='2025_Chase9335_Activity_2026062'!B4 -> 46022 | C4: ='2025_Chase9335_Activity_2026062'!C4 -> Online Transfer from CHK ...3922 transaction#: 27532478452 | D4: ='2025_Chase9335_Activity_2026062'!D4 -> 23350 | E4: ='2025_Chase9335_Activity_2026062'!E4 -> ACCT_XFER | F4: ='2025_Chase9335_Activity_2026062'!F4 -> 297014.9 | G4: ='2025_Chase9335_Activity_2026062'!G4 -> Transfer from DWG Capital Partners | H4: =IF($B4="","",DATE(YEAR($B4),MONTH($B4),1)) -> 45992 | I4: =IF($G4="","Uncategorized — Review",IFERROR(_xlfn.XLOOKUP($G4,Mapping!$A:$A,Mapping!$B:$B),"Uncategorized — Review")) -> Transfer from DWG Capital Partners | J4: =IF($G4="","Uncategorized — Review",IFERROR(_xlfn.XLOOKUP($G4,Mapping!$A:$A,Mapping!$C:$C),"Uncategorized — Review")) -> Intercompany & Savings Transfers
A5: ='2025_Chase9335_Activity_2026062'!A5 -> DEBIT | B5: ='2025_Chase9335_Activity_2026062'!B5 -> 46021 | C5: ='2025_Chase9335_Activity_2026062'!C5 -> FOREIGN EXCHANGE RATE ADJUSTMENT FEE 12/30R PARKING | D5: ='2025_Chase9335_Activity_2026062'!D5 -> -0.17 | E5: ='2025_Chase9335_Activity_2026062'!E5 -> FEE_TRANSACTION | F5: ='2025_Chase9335_Activity_2026062'!F5 -> 273664.9 | G5: ='2025_Chase9335_Activity_2026062'!G5 -> Personal - Travel (Canada) | H5: =IF($B5="","",DATE(YEAR($B5),MONTH($B5),1)) -> 45992 | I5: =IF($G5="","Uncategorized — Review",IFERROR(_xlfn.XLOOKUP($G5,Mapping!$A:$A,Mapping!$B:$B),"Uncategorized — Review")) -> Personal - Travel (Canada) | J5: =IF($G5="","Uncategorized — Review",IFERROR(_xlfn.XLOOKUP($G5,Mapping!$A:$A,Mapping!$C:$C),"Uncategorized — Review")) -> Personal — Owner
A6: ='2025_Chase9335_Activity_2026062'!A6 -> DEBIT | B6: ='2025_Chase9335_Activity_2026062'!B6 -> 46021 | C6: ='2025_Chase9335_Activity_2026062'!C6 -> R PARKING VIC VICTORIA BC 12/30 CA DOLLAR 8.00 X 0.7325000 (EXCHG RTE) | D6: ='2025_Chase9335_Activity_2026062'!D6 -> -5.86 | E6: ='2025_Chase9335_Activity_2026062'!E6 -> DEBIT_CARD | F6: ='2025_Chase9335_Activity_2026062'!F6 -> 273665.07 | G6: ='2025_Chase9335_Activity_2026062'!G6 -> Personal - Travel (Canada) | H6: =IF($B6="","",DATE(YEAR($B6),MONTH($B6),1)) -> 45992 | I6: =IF($G6="","Uncategorized — Review",IFERROR(_xlfn.XLOOKUP($G6,Mapping!$A:$A,Mapping!$B:$B),"Uncategorized — Review")) -> Personal - Travel (Canada) | J6: =IF($G6="","Uncategorized — Review",IFERROR(_xlfn.XLOOKUP($G6,Mapping!$A:$A,Mapping!$C:$C),"Uncategorized — Review")) -> Personal — Owner
A7: ='2025_Chase9335_Activity_2026062'!A7 -> DEBIT | B7: ='2025_Chase9335_Activity_2026062'!B7 -> 46020 | C7: ='2025_Chase9335_Activity_2026062'!C7 -> FOREIGN EXCHANGE RATE ADJUSTMENT FEE 12/26HARBOURVI | D7: ='2025_Chase9335_Activity_2026062'!D7 -> -3.96 | E7: ='2025_Chase9335_Activity_2026062'!E7 -> FEE_TRANSACTION | F7: ='2025_Chase9335_Activity_2026062'!F7 -> 273670.93 | G7: ='2025_Chase9335_Activity_2026062'!G7 -> Personal - Travel (Canada) | H7: =IF($B7="","",DATE(YEAR($B7),MONTH($B7),1)) -> 45992 | I7: =IF($G7="","Uncategorized — Review",IFERROR(_xlfn.XLOOKUP($G7,Mapping!$A:$A,Mapping!$B:$B),"Uncategorized — Review")) -> Personal - Travel (Canada) | J7: =IF($G7="","Uncategorized — Review",IFERROR(_xlfn.XLOOKUP($G7,Mapping!$A:$A,Mapping!$C:$C),"Uncategorized — Review")) -> Personal — Owner
A8: ='2025_Chase9335_Activity_2026062'!A8 -> DEBIT | B8: ='2025_Chase9335_Activity_2026062'!B8 -> 46020 | C8: ='2025_Chase9335_Activity_2026062'!C8 -> FOREIGN EXCHANGE RATE ADJUSTMENT FEE 12/26SHED TOFI | D8: ='2025_Chase9335_Activity_2026062'!D8 -> -4.21 | E8: ='2025_Chase9335_Activity_2026062'!E8 -> FEE_TRANSACTION | F8: ='2025_Chase9335_Activity_2026062'!F8 -> 273674.89 | G8: ='2025_Chase9335_Activity_2026062'!G8 -> Personal - Travel (Canada) | H8: =IF($B8="","",DATE(YEAR($B8),MONTH($B8),1)) -> 45992 | I8: =IF($G8="","Uncategorized — Review",IFERROR(_xlfn.XLOOKUP($G8,Mapping!$A:$A,Mapping!$B:$B),"Uncategorized — Review")) -> Personal - Travel (Canada) | J8: =IF($G8="","Uncategorized — Review",IFERROR(_xlfn.XLOOKUP($G8,Mapping!$A:$A,Mapping!$C:$C),"Uncategorized — Review")) -> Personal — Owner
A9: ='2025_Chase9335_Activity_2026062'!A9 -> DEBIT | B9: ='2025_Chase9335_Activity_2026062'!B9 -> 46020 | C9: ='2025_Chase9335_Activity_2026062'!C9 -> Prime Video *NV19F8ZS 888-802-3080 WA 12/29 | D9: ='2025_Chase9335_Activity_2026062'!D9 -> -16 | E9: ='2025_Chase9335_Activity_2026062'!E9 -> DEBIT_CARD | F9: ='2025_Chase9335_Activity_2026062'!F9 -> 273679.1 | G9: ='2025_Chase9335_Activity_2026062'!G9 -> Amazon Prime Video | H9: =IF($B9="","",DATE(YEAR($B9),MONTH($B9),1)) -> 45992 | I9: =IF($G9="","Uncategorized — Review",IFERROR(_xlfn.XLOOKUP($G9,Mapping!$A:$A,Mapping!$B:$B),"Uncategorized — Review")) -> Amazon Prime Video | J9: =IF($G9="","Uncategorized — Review",IFERROR(_xlfn.XLOOKUP($G9,Mapping!$A:$A,Mapping!$C:$C),"Uncategorized — Review")) -> Personal — Owner
A10: ='2025_Chase9335_Activity_2026062'!A10 -> DEBIT | B10: ='2025_Chase9335_Activity_2026062'!B10 -> 46020 | C10: ='2025_Chase9335_Activity_2026062'!C10 -> APPLE COM BILL CUPERTINO CA 115913 12/27 | D10: ='2025_Chase9335_Activity_2026062'!D10 -> -30.89 | E10: ='2025_Chase9335_Activity_2026062'!E10 -> DEBIT_CARD | F10: ='2025_Chase9335_Activity_2026062'!F10 -> 273695.1 | G10: ='2025_Chase9335_Activity_2026062'!G10 -> Personal - Subscriptions | H10: =IF($B10="","",DATE(YEAR($B10),MONTH($B10),1)) -> 45992 | I10: =IF($G10="","Uncategorized — Review",IFERROR(_xlfn.XLOOKUP($G10,Mapping!$A:$A,Mapping!$B:$B),"Uncategorized — Review")) -> Personal - Subscriptions | J10: =IF($G10="","Uncategorized — Review",IFERROR(_xlfn.XLOOKUP($G10,Mapping!$A:$A,Mapping!$C:$C),"Uncategorized — Review")) -> Personal — Owner
A11: ='2025_Chase9335_Activity_2026062'!A11 -> DEBIT | B11: ='2025_Chase9335_Activity_2026062'!B11 -> 46020 | C11: ='2025_Chase9335_Activity_2026062'!C11 -> Amazon.com*9E8JZ24W3 Amzn.com/bill WA 12/27 | D11: ='2025_Chase9335_Activity_2026062'!D11 -> -22.87 | E11: ='2025_Chase9335_Activity_2026062'!E11 -> DEBIT_CARD | F11: ='2025_Chase9335_Activity_2026062'!F11 -> 273725.99 | G11: ='2025_Chase9335_Activity_2026062'!G11 -> Amazon | H11: =IF($B11="","",DATE(YEAR($B11),MONTH($B11),1)) -> 45992 | I11: =IF($G11="","Uncategorized — Review",IFERROR(_xlfn.XLOOKUP($G11,Mapping!$A:$A,Mapping!$B:$B),"Uncategorized — Review")) -> Amazon | J11: =IF($G11="","Uncategorized — Review",IFERROR(_xlfn.XLOOKUP($G11,Mapping!$A:$A,Mapping!$C:$C),"Uncategorized — Review")) -> Personal — Owner
A12: ='2025_Chase9335_Activity_2026062'!A12 -> DEBIT | B12: ='2025_Chase9335_Activity_2026062'!B12 -> 46020 | C12: ='2025_Chase9335_Activity_2026062'!C12 -> SHED TOFINO BC 12/26 CA DOLLAR 191.46 X 0.7331558 (EXCHG RTE) | D12: ='2025_Chase9335_Activity_2026062'!D12 -> -140.37 | E12: ='2025_Chase9335_Activity_2026062'!E12 -> DEBIT_CARD | F12: ='2025_Chase9335_Activity_2026062'!F12 -> 273748.86 | G12: ='2025_Chase9335_Activity_2026062'!G12 -> Personal - Travel (Canada) | H12: =IF($B12="","",DATE(YEAR($B12),MONTH($B12),1)) -> 45992 | I12: =IF($G12="","Uncategorized — Review",IFERROR(_xlfn.XLOOKUP($G12,Mapping!$A:$A,Mapping!$B:$B),"Uncategorized — Review")) -> Personal - Travel (Canada) | J12: =IF($G12="","Uncategorized — Review",IFERROR(_xlfn.XLOOKUP($G12,Mapping!$A:$A,Mapping!$C:$C),"Uncategorized — Review")) -> Personal — Owner
A13: ='2025_Chase9335_Activity_2026062'!A13 -> DEBIT | B13: ='2025_Chase9335_Activity_2026062'!B13 -> 46020 | C13: ='2025_Chase9335_Activity_2026062'!C13 -> HARBOURVIEW DRUGSTORE UCLUELET BC 12/26 CA DOLLAR 180.35 X 0.7319656 (EXCHG RTE) | D13: ='2025_Chase9335_Activity_2026062'!D13 -> -132.01 | E13: ='2025_Chase9335_Activity_2026062'!E13 -> DEBIT_CARD | F13: ='2025_Chase9335_Activity_2026062'!F13 -> 273889.23 | G13: ='2025_Chase9335_Activity_2026062'!G13 -> Personal - Travel (Canada) | H13: =IF($B13="","",DATE(YEAR($B13),MONTH($B13),1)) -> 45992 | I13: =IF($G13="","Uncategorized — Review",IFERROR(_xlfn.XLOOKUP($G13,Mapping!$A:$A,Mapping!$B:$B),"Uncategorized — Review")) -> Personal - Travel (Canada) | J13: =IF($G13="","Uncategorized — Review",IFERROR(_xlfn.XLOOKUP($G13,Mapping!$A:$A,Mapping!$C:$C),"Uncategorized — Review")) -> Personal — Owner
... A790: ='2025_Chase9335_Activity_2026062'!A790 -> CREDIT | B790: ='2025_Chase9335_Activity_2026062'!B790 -> 45659 | C790: ='2025_Chase9335_Activity_2026062'!C790 -> FEDWIRE CREDIT VIA: BANK OF AMERICA, N.A./026009593 B/O: CT SOCAL COMM FBSC/CT BS FXBC RIVERSIDE CA 92505 US REF: CHASE NYC/CTR/BNF=POSEIDON ASSET GROUP, LLC LOS ANGELES CA 90066-3638 US/AC-000000007200 RFB=1-18462071 O BI=FN-FBSC2403516 SELLING BROKER C/OM MI SSION PROPADDR-1607 PINE STRE/ET , PR ESCOTT, IMAD: 0102B6B7HU2R020217 TRN: 1195751002FF | D790: ='2025_Chase9335_Activity_2026062'!D790 -> 78600 | E790: ='2025_Chase9335_Activity_2026062'!E790 -> WIRE_INCOMING | F790: ='2025_Chase9335_Activity_2026062'!F790 -> 381019.61 | G790: ='2025_Chase9335_Activity_2026062'!G790 -> Incoming Commission: Edge Builder | H790: =IF($B790="","",DATE(YEAR($B790),MONTH($B790),1)) -> 45658 | I790: =IF($G790="","Uncategorized — Review",IFERROR(_xlfn.XLOOKUP($G790,Mapping!$A:$A,Mapping!$B:$B),"Uncategorized — Review")) -> Incoming Commission: Edge Builder | J790: =IF($G790="","Uncategorized — Review",IFERROR(_xlfn.XLOOKUP($G790,Mapping!$A:$A,Mapping!$C:$C),"Uncategorized — Review")) -> Commissions — Incoming

Sheet Mapping
A1: Raw Category | B1: Combined Category | C1: Group
A2: ACH Payment - Astronomics | B2: ACH Payment - Astronomics | C2: DWG Operating
A3: ACH payment to CALCPA group | B3: ACH payment to CALCPA group | C3: DWG Operating
A4: AI Subscriptions | B4: AI Subscriptions | C4: Personal — Owner
A5: Amazon | B5: Amazon | C5: Personal — Owner
A6: Amazon Prime Video | B6: Amazon Prime Video | C6: Personal — Owner
A7: American Express Credit Card PMT | B7: American Express Credit Card PMT | C7: Credit Card & Loan Payments
A8: Apple Payment | B8: Apple Payment | C8: P2P Payments (Zelle/Venmo/PayPal)
A9: Bank Fees | B9: Bank Fees | C9: DWG Operating
A10: Ben Mandel - Payroll | B10: Ben Mandel - Payroll | C10: Payroll & Contractors
A11: Deal Specific: Austin Iron | B11: Deal Specific: Austin Iron | C11: Deal-Specific
A12: Deal Specific: Cloverdale | B12: Deal Specific: Cloverdale | C12: Deal-Specific
... A79: Zelle to Sentha | B79: Zelle to Sentha | C79: P2P Payments (Zelle/Venmo/PayPal)

Sheet 2025_Chase9335_Activity_2026062
A1: Details | B1: Posting Date | C1: Description | D1: Amount | E1: Type | F1: Balance | G1: Categories
A2: DEBIT | B2: 46022 | C2: Online Transfer to CHK ...9769 transaction#: 27532473331 12/31 | D2: -33349 | E2: ACCT_XFER | F2: 263614.45 | G2: Transfer to JAL Southbend
A3: DEBIT | B3: 46022 | C3: APPLE.COM/BILL 866-712-7753 CA 12/31 | D3: -51.45 | E3: DEBIT_CARD | F3: 296963.45 | G3: Personal - Subscriptions
A4: CREDIT | B4: 46022 | C4: Online Transfer from CHK ...3922 transaction#: 27532478452 | D4: 23350 | E4: ACCT_XFER | F4: 297014.9 | G4: Transfer from DWG Capital Partners
A5: DEBIT | B5: 46021 | C5: FOREIGN EXCHANGE RATE ADJUSTMENT FEE 12/30R PARKING | D5: -0.17 | E5: FEE_TRANSACTION | F5: 273664.9 | G5: Personal - Travel (Canada)
A6: DEBIT | B6: 46021 | C6: R PARKING VIC VICTORIA BC 12/30 CA DOLLAR 8.00 X 0.7325000 (EXCHG RTE) | D6: -5.86 | E6: DEBIT_CARD | F6: 273665.07 | G6: Personal - Travel (Canada)
A7: DEBIT | B7: 46020 | C7: FOREIGN EXCHANGE RATE ADJUSTMENT FEE 12/26HARBOURVI | D7: -3.96 | E7: FEE_TRANSACTION | F7: 273670.93 | G7: Personal - Travel (Canada)
A8: DEBIT | B8: 46020 | C8: FOREIGN EXCHANGE RATE ADJUSTMENT FEE 12/26SHED TOFI | D8: -4.21 | E8: FEE_TRANSACTION | F8: 273674.89 | G8: Personal - Travel (Canada)
A9: DEBIT | B9: 46020 | C9: Prime Video *NV19F8ZS 888-802-3080 WA 12/29 | D9: -16 | E9: DEBIT_CARD | F9: 273679.1 | G9: Amazon Prime Video
A10: DEBIT | B10: 46020 | C10: APPLE COM BILL CUPERTINO CA 115913 12/27 | D10: -30.89 | E10: DEBIT_CARD | F10: 273695.1 | G10: Personal - Subscriptions
A11: DEBIT | B11: 46020 | C11: Amazon.com*9E8JZ24W3 Amzn.com/bill WA 12/27 | D11: -22.87 | E11: DEBIT_CARD | F11: 273725.99 | G11: Amazon
A12: DEBIT | B12: 46020 | C12: SHED TOFINO BC 12/26 CA DOLLAR 191.46 X 0.7331558 (EXCHG RTE) | D12: -140.37 | E12: DEBIT_CARD | F12: 273748.86 | G12: Personal - Travel (Canada)
A13: DEBIT | B13: 46020 | C13: HARBOURVIEW DRUGSTORE UCLUELET BC 12/26 CA DOLLAR 180.35 X 0.7319656 (EXCHG RTE) | D13: -132.01 | E13: DEBIT_CARD | F13: 273889.23 | G13: Personal - Travel (Canada)
... A790: CREDIT | B790: 45659 | C790: FEDWIRE CREDIT VIA: BANK OF AMERICA, N.A./026009593 B/O: CT SOCAL COMM FBSC/CT BS FXBC RIVERSIDE CA 92505 US REF: CHASE NYC/CTR/BNF=POSEIDON ASSET GROUP, LLC LOS ANGELES CA 90066-3638 US/AC-000000007200 RFB=1-18462071 O BI=FN-FBSC2403516 SELLING BROKER C/OM MI SSION PROPADDR-1607 PINE STRE/ET , PR ESCOTT, IMAD: 0102B6B7HU2R020217 TRN: 1195751002FF | D790: 78600 | E790: WIRE_INCOMING | F790: 381019.61 | G790: Incoming Commission: Edge Builder
