Workbook

Sheet Category Summary
A1: Chase 1168 — DWG Capital Group 2025 Activity
A2: Category Summary | Jan 2025 – Dec 2025
A4: Entity | B4: DWG Capital Group
A5: Account | B5: Business Checking — Chase 1168
A6: Period | B6: Jan 2025 – Dec 2025
A8: TOTALS
A9: Total Inflows | B9: =SUMIFS('Transaction Overview'!$D$2:$D$1850,'Transaction Overview'!$D$2:$D$1850,">0") -> 2173385.3
A10: Total Outflows | B10: =SUMIFS('Transaction Overview'!$D$2:$D$1850,'Transaction Overview'!$D$2:$D$1850,"<0") -> -2192318.1
A11: Net Change | B11: =B9+B10 -> -18932.79
A14: Category | B14: Inflows | C14: Outflows | D14: Net
A15: Deal-Specific
A16: Deal Specific: Moab | B16: =SUMIFS('Transaction Overview'!$D$2:$D$1850,'Transaction Overview'!$I$2:$I$1850,$A16,'Transaction Overview'!$D$2:$D$1850,">0") -> 0 | C16: =SUMIFS('Transaction Overview'!$D$2:$D$1850,'Transaction Overview'!$I$2:$I$1850,$A16,'Transaction Overview'!$D$2:$D$1850,"<0") -> -40000 | D16: =B16+C16 -> -40000
A17: Deal Specific: Moab (Reimbursement) | B17: =SUMIFS('Transaction Overview'!$D$2:$D$1850,'Transaction Overview'!$I$2:$I$1850,$A17,'Transaction Overview'!$D$2:$D$1850,">0") -> 40000 | C17: =SUMIFS('Transaction Overview'!$D$2:$D$1850,'Transaction Overview'!$I$2:$I$1850,$A17,'Transaction Overview'!$D$2:$D$1850,"<0") -> 0 | D17: =B17+C17 -> 40000
A18: Deal Specific: TBD | B18: =SUMIFS('Transaction Overview'!$D$2:$D$1850,'Transaction Overview'!$I$2:$I$1850,$A18,'Transaction Overview'!$D$2:$D$1850,">0") -> 0 | C18: =SUMIFS('Transaction Overview'!$D$2:$D$1850,'Transaction Overview'!$I$2:$I$1850,$A18,'Transaction Overview'!$D$2:$D$1850,"<0") -> -15000 | D18: =B18+C18 -> -15000
A19: Subtotal — Deal-Specific | B19: =SUMIFS('Transaction Overview'!$D$2:$D$1850,'Transaction Overview'!$J$2:$J$1850,"Deal-Specific",'Transaction Overview'!$D$2:$D$1850,">0") -> 40000 | C19: =SUMIFS('Transaction Overview'!$D$2:$D$1850,'Transaction Overview'!$J$2:$J$1850,"Deal-Specific",'Transaction Overview'!$D$2:$D$1850,"<0") -> -55000 | D19: =B19+C19 -> -15000
A21: Commissions — Incoming
A22: Incoming Commission: Aspen | B22: =SUMIFS('Transaction Overview'!$D$2:$D$1850,'Transaction Overview'!$I$2:$I$1850,$A22,'Transaction Overview'!$D$2:$D$1850,">0") -> 87850 | C22: =SUMIFS('Transaction Overview'!$D$2:$D$1850,'Transaction Overview'!$I$2:$I$1850,$A22,'Transaction Overview'!$D$2:$D$1850,"<0") -> 0 | D22: =B22+C22 -> 87850
A23: Incoming Commission: Charlmont | B23: =SUMIFS('Transaction Overview'!$D$2:$D$1850,'Transaction Overview'!$I$2:$I$1850,$A23,'Transaction Overview'!$D$2:$D$1850,">0") -> 235000 | C23: =SUMIFS('Transaction Overview'!$D$2:$D$1850,'Transaction Overview'!$I$2:$I$1850,$A23,'Transaction Overview'!$D$2:$D$1850,"<0") -> -25000 | D23: =B23+C23 -> 210000
A24: Incoming Commission: 115 Penn | B24: =SUMIFS('Transaction Overview'!$D$2:$D$1850,'Transaction Overview'!$I$2:$I$1850,$A24,'Transaction Overview'!$D$2:$D$1850,">0") -> 42500 | C24: =SUMIFS('Transaction Overview'!$D$2:$D$1850,'Transaction Overview'!$I$2:$I$1850,$A24,'Transaction Overview'!$D$2:$D$1850,"<0") -> 0 | D24: =B24+C24 -> 42500
A25: Incoming Commission: 2055 Laguna Canyon | B25: =SUMIFS('Transaction Overview'!$D$2:$D$1850,'Transaction Overview'!$I$2:$I$1850,$A25,'Transaction Overview'!$D$2:$D$1850,">0") -> 40000 | C25: =SUMIFS('Transaction Overview'!$D$2:$D$1850,'Transaction Overview'!$I$2:$I$1850,$A25,'Transaction Overview'!$D$2:$D$1850,"<0") -> 0 | D25: =B25+C25 -> 40000
A26: Incoming Commission: 20635 N 29th Pl, Phoenix AZ (Deer Valley) | B26: =SUMIFS('Transaction Overview'!$D$2:$D$1850,'Transaction Overview'!$I$2:$I$1850,$A26,'Transaction Overview'!$D$2:$D$1850,">0") -> 69000 | C26: =SUMIFS('Transaction Overview'!$D$2:$D$1850,'Transaction Overview'!$I$2:$I$1850,$A26,'Transaction Overview'!$D$2:$D$1850,"<0") -> 0 | D26: =B26+C26 -> 69000
A27: Incoming Commission: 315 York | B27: =SUMIFS('Transaction Overview'!$D$2:$D$1850,'Transaction Overview'!$I$2:$I$1850,$A27,'Transaction Overview'!$D$2:$D$1850,">0") -> 40350 | C27: =SUMIFS('Transaction Overview'!$D$2:$D$1850,'Transaction Overview'!$I$2:$I$1850,$A27,'Transaction Overview'!$D$2:$D$1850,"<0") -> 0 | D27: =B27+C27 -> 40350
A28: Incoming Commission: 3811 E Bankhead | B28: =SUMIFS('Transaction Overview'!$D$2:$D$1850,'Transaction Overview'!$I$2:$I$1850,$A28,'Transaction Overview'!$D$2:$D$1850,">0") -> 85700 | C28: =SUMIFS('Transaction Overview'!$D$2:$D$1850,'Transaction Overview'!$I$2:$I$1850,$A28,'Transaction Overview'!$D$2:$D$1850,"<0") -> 0 | D28: =B28+C28 -> 85700
A29: Incoming Commission: Edge Builder | B29: =SUMIFS('Transaction Overview'!$D$2:$D$1850,'Transaction Overview'!$I$2:$I$1850,$A29,'Transaction Overview'!$D$2:$D$1850,">0") -> 61037 | C29: =SUMIFS('Transaction Overview'!$D$2:$D$1850,'Transaction Overview'!$I$2:$I$1850,$A29,'Transaction Overview'!$D$2:$D$1850,"<0") -> 0 | D29: =B29+C29 -> 61037
A30: Subtotal — Commissions — Incoming | B30: =SUMIFS('Transaction Overview'!$D$2:$D$1850,'Transaction Overview'!$J$2:$J$1850,"Commissions — Incoming",'Transaction Overview'!$D$2:$D$1850,">0") -> 661437 | C30: =SUMIFS('Transaction Overview'!$D$2:$D$1850,'Transaction Overview'!$J$2:$J$1850,"Commissions — Incoming",'Transaction Overview'!$D$2:$D$1850,"<0") -> -25000 | D30: =B30+C30 -> 636437
A32: Commissions — Outgoing
A33: Commission Paid: Brian Bowis (Charlmont) | B33: =SUMIFS('Transaction Overview'!$D$2:$D$1850,'Transaction Overview'!$I$2:$I$1850,$A33,'Transaction Overview'!$D$2:$D$1850,">0") -> 0 | C33: =SUMIFS('Transaction Overview'!$D$2:$D$1850,'Transaction Overview'!$I$2:$I$1850,$A33,'Transaction Overview'!$D$2:$D$1850,"<0") -> -102500 | D33: =B33+C33 -> -102500
A34: Subtotal — Commissions — Outgoing | B34: =SUMIFS('Transaction Overview'!$D$2:$D$1850,'Transaction Overview'!$J$2:$J$1850,"Commissions — Outgoing",'Transaction Overview'!$D$2:$D$1850,">0") -> 0 | C34: =SUMIFS('Transaction Overview'!$D$2:$D$1850,'Transaction Overview'!$J$2:$J$1850,"Commissions — Outgoing",'Transaction Overview'!$D$2:$D$1850,"<0") -> -102500 | D34: =B34+C34 -> -102500
A36: MAG Pass-Through
A37: Due to Andrew – MAG Pass-Through 30% | B37: =SUMIFS('Transaction Overview'!$D$2:$D$1850,'Transaction Overview'!$I$2:$I$1850,$A37,'Transaction Overview'!$D$2:$D$1850,">0") -> 0 | C37: =SUMIFS('Transaction Overview'!$D$2:$D$1850,'Transaction Overview'!$I$2:$I$1850,$A37,'Transaction Overview'!$D$2:$D$1850,"<0") -> -114028.02 | D37: =B37+C37 -> -114028.02
A38: Due to Andrew – MAG Pass-Through 30% | B38: =SUMIFS('Transaction Overview'!$D$2:$D$1850,'Transaction Overview'!$I$2:$I$1850,$A38,'Transaction Overview'!$D$2:$D$1850,">0") -> 0 | C38: =SUMIFS('Transaction Overview'!$D$2:$D$1850,'Transaction Overview'!$I$2:$I$1850,$A38,'Transaction Overview'!$D$2:$D$1850,"<0") -> -83437 | D38: =B38+C38 -> -83437
A39: Due to Dax – MAG Pass-Through 70% | B39: =SUMIFS('Transaction Overview'!$D$2:$D$1850,'Transaction Overview'!$I$2:$I$1850,$A39,'Transaction Overview'!$D$2:$D$1850,">0") -> 0 | C39: =SUMIFS('Transaction Overview'!$D$2:$D$1850,'Transaction Overview'!$I$2:$I$1850,$A39,'Transaction Overview'!$D$2:$D$1850,"<0") -> -454752.37 | D39: =B39+C39 -> -454752.37
A40: MAG - Admeer Advisory Transfer | B40: =SUMIFS('Transaction Overview'!$D$2:$D$1850,'Transaction Overview'!$I$2:$I$1850,$A40,'Transaction Overview'!$D$2:$D$1850,">0") -> 0 | C40: =SUMIFS('Transaction Overview'!$D$2:$D$1850,'Transaction Overview'!$I$2:$I$1850,$A40,'Transaction Overview'!$D$2:$D$1850,"<0") -> -10000 | D40: =B40+C40 -> -10000
A41: MAG Capital Partners Pass-Through Wire – 70/30 Split | B41: =SUMIFS('Transaction Overview'!$D$2:$D$1850,'Transaction Overview'!$I$2:$I$1850,$A41,'Transaction Overview'!$D$2:$D$1850,">0") -> 365125 | C41: =SUMIFS('Transaction Overview'!$D$2:$D$1850,'Transaction Overview'!$I$2:$I$1850,$A41,'Transaction Overview'!$D$2:$D$1850,"<0") -> 0 | D41: =B41+C41 -> 365125
A42: Subtotal — MAG Pass-Through | B42: =SUMIFS('Transaction Overview'!$D$2:$D$1850,'Transaction Overview'!$J$2:$J$1850,"MAG Pass-Through",'Transaction Overview'!$D$2:$D$1850,">0") -> 365125 | C42: =SUMIFS('Transaction Overview'!$D$2:$D$1850,'Transaction Overview'!$J$2:$J$1850,"MAG Pass-Through",'Transaction Overview'!$D$2:$D$1850,"<0") -> -662217.39 | D42: =B42+C42 -> -297092.39
A44: Poseidon Asset Group
A45: Poseidon Asset Group (Incoming) | B45: =SUMIFS('Transaction Overview'!$D$2:$D$1850,'Transaction Overview'!$I$2:$I$1850,$A45,'Transaction Overview'!$D$2:$D$1850,">0") -> 423000 | C45: =SUMIFS('Transaction Overview'!$D$2:$D$1850,'Transaction Overview'!$I$2:$I$1850,$A45,'Transaction Overview'!$D$2:$D$1850,"<0") -> 0 | D45: =B45+C45 -> 423000
A46: Transfer From Poseidon Asset Group | B46: =SUMIFS('Transaction Overview'!$D$2:$D$1850,'Transaction Overview'!$I$2:$I$1850,$A46,'Transaction Overview'!$D$2:$D$1850,">0") -> 255000 | C46: =SUMIFS('Transaction Overview'!$D$2:$D$1850,'Transaction Overview'!$I$2:$I$1850,$A46,'Transaction Overview'!$D$2:$D$1850,"<0") -> 0 | D46: =B46+C46 -> 255000
A47: Transfer to Poseidon | B47: =SUMIFS('Transaction Overview'!$D$2:$D$1850,'Transaction Overview'!$I$2:$I$1850,$A47,'Transaction Overview'!$D$2:$D$1850,">0") -> 0 | C47: =SUMIFS('Transaction Overview'!$D$2:$D$1850,'Transaction Overview'!$I$2:$I$1850,$A47,'Transaction Overview'!$D$2:$D$1850,"<0") -> -5000 | D47: =B47+C47 -> -5000
A48: Subtotal — Poseidon Asset Group | B48: =SUMIFS('Transaction Overview'!$D$2:$D$1850,'Transaction Overview'!$J$2:$J$1850,"Poseidon Asset Group",'Transaction Overview'!$D$2:$D$1850,">0") -> 678000 | C48: =SUMIFS('Transaction Overview'!$D$2:$D$1850,'Transaction Overview'!$J$2:$J$1850,"Poseidon Asset Group",'Transaction Overview'!$D$2:$D$1850,"<0") -> -5000 | D48: =B48+C48 -> 673000
A50: Intercompany & Savings Transfers
A51: DWG Capital Partners - Outgoing | B51: =SUMIFS('Transaction Overview'!$D$2:$D$1850,'Transaction Overview'!$I$2:$I$1850,$A51,'Transaction Overview'!$D$2:$D$1850,">0") -> 0 | C51: =SUMIFS('Transaction Overview'!$D$2:$D$1850,'Transaction Overview'!$I$2:$I$1850,$A51,'Transaction Overview'!$D$2:$D$1850,"<0") -> -90500 | D51: =B51+C51 -> -90500
A52: Internal Transfer | B52: =SUMIFS('Transaction Overview'!$D$2:$D$1850,'Transaction Overview'!$I$2:$I$1850,$A52,'Transaction Overview'!$D$2:$D$1850,">0") -> 20000 | C52: =SUMIFS('Transaction Overview'!$D$2:$D$1850,'Transaction Overview'!$I$2:$I$1850,$A52,'Transaction Overview'!$D$2:$D$1850,"<0") -> 0 | D52: =B52+C52 -> 20000
A53: Transfer From Butler Weldments | B53: =SUMIFS('Transaction Overview'!$D$2:$D$1850,'Transaction Overview'!$I$2:$I$1850,$A53,'Transaction Overview'!$D$2:$D$1850,">0") -> 1500 | C53: =SUMIFS('Transaction Overview'!$D$2:$D$1850,'Transaction Overview'!$I$2:$I$1850,$A53,'Transaction Overview'!$D$2:$D$1850,"<0") -> 0 | D53: =B53+C53 -> 1500
A54: Transfer From DWG Capital Partners | B54: =SUMIFS('Transaction Overview'!$D$2:$D$1850,'Transaction Overview'!$I$2:$I$1850,$A54,'Transaction Overview'!$D$2:$D$1850,">0") -> 5000 | C54: =SUMIFS('Transaction Overview'!$D$2:$D$1850,'Transaction Overview'!$I$2:$I$1850,$A54,'Transaction Overview'!$D$2:$D$1850,"<0") -> 0 | D54: =B54+C54 -> 5000
A55: Transfer to Breese Marketing | B55: =SUMIFS('Transaction Overview'!$D$2:$D$1850,'Transaction Overview'!$I$2:$I$1850,$A55,'Transaction Overview'!$D$2:$D$1850,">0") -> 0 | C55: =SUMIFS('Transaction Overview'!$D$2:$D$1850,'Transaction Overview'!$I$2:$I$1850,$A55,'Transaction Overview'!$D$2:$D$1850,"<0") -> -500 | D55: =B55+C55 -> -500
A56: Transfer to DWG Capital Group_Costar | B56: =SUMIFS('Transaction Overview'!$D$2:$D$1850,'Transaction Overview'!$I$2:$I$1850,$A56,'Transaction Overview'!$D$2:$D$1850,">0") -> 0 | C56: =SUMIFS('Transaction Overview'!$D$2:$D$1850,'Transaction Overview'!$I$2:$I$1850,$A56,'Transaction Overview'!$D$2:$D$1850,"<0") -> -9000 | D56: =B56+C56 -> -9000
A57: Transfer to DWG Savings | B57: =SUMIFS('Transaction Overview'!$D$2:$D$1850,'Transaction Overview'!$I$2:$I$1850,$A57,'Transaction Overview'!$D$2:$D$1850,">0") -> 0 | C57: =SUMIFS('Transaction Overview'!$D$2:$D$1850,'Transaction Overview'!$I$2:$I$1850,$A57,'Transaction Overview'!$D$2:$D$1850,"<0") -> -15300 | D57: =B57+C57 -> -15300
A58: Transfer to DWG Capital Partners | B58: =SUMIFS('Transaction Overview'!$D$2:$D$1850,'Transaction Overview'!$I$2:$I$1850,$A58,'Transaction Overview'!$D$2:$D$1850,">0") -> 0 | C58: =SUMIFS('Transaction Overview'!$D$2:$D$1850,'Transaction Overview'!$I$2:$I$1850,$A58,'Transaction Overview'!$D$2:$D$1850,"<0") -> -1000 | D58: =B58+C58 -> -1000
A59: Transfer to DWG Holdings | B59: =SUMIFS('Transaction Overview'!$D$2:$D$1850,'Transaction Overview'!$I$2:$I$1850,$A59,'Transaction Overview'!$D$2:$D$1850,">0") -> 0 | C59: =SUMIFS('Transaction Overview'!$D$2:$D$1850,'Transaction Overview'!$I$2:$I$1850,$A59,'Transaction Overview'!$D$2:$D$1850,"<0") -> -100 | D59: =B59+C59 -> -100
A60: Transfer to DWGCG_Costar | B60: =SUMIFS('Transaction Overview'!$D$2:$D$1850,'Transaction Overview'!$I$2:$I$1850,$A60,'Transaction Overview'!$D$2:$D$1850,">0") -> 0 | C60: =SUMIFS('Transaction Overview'!$D$2:$D$1850,'Transaction Overview'!$I$2:$I$1850,$A60,'Transaction Overview'!$D$2:$D$1850,"<0") -> -3902.89 | D60: =B60+C60 -> -3902.89
A61: Transfer to Ecomm_PosPrtnrs | B61: =SUMIFS('Transaction Overview'!$D$2:$D$1850,'Transaction Overview'!$I$2:$I$1850,$A61,'Transaction Overview'!$D$2:$D$1850,">0") -> 10000 | C61: =SUMIFS('Transaction Overview'!$D$2:$D$1850,'Transaction Overview'!$I$2:$I$1850,$A61,'Transaction Overview'!$D$2:$D$1850,"<0") -> 0 | D61: =B61+C61 -> 10000
A62: Transfer to Judd Sol Prop | B62: =SUMIFS('Transaction Overview'!$D$2:$D$1850,'Transaction Overview'!$I$2:$I$1850,$A62,'Transaction Overview'!$D$2:$D$1850,">0") -> 0 | C62: =SUMIFS('Transaction Overview'!$D$2:$D$1850,'Transaction Overview'!$I$2:$I$1850,$A62,'Transaction Overview'!$D$2:$D$1850,"<0") -> -500 | D62: =B62+C62 -> -500
... A66: Transfer to Theut Glass | B66: =SUMIFS('Transaction Overview'!$D$2:$D$1850,'Transaction Overview'!$I$2:$I$1850,$A66,'Transaction Overview'!$D$2:$D$1850,">0") -> 0 | C66: =SUMIFS('Transaction Overview'!$D$2:$D$1850,'Transaction Overview'!$I$2:$I$1850,$A66,'Transaction Overview'!$D$2:$D$1850,"<0") -> -1000 | D66: =B66+C66 -> -1000
A67: Subtotal — Intercompany & Savings Transfers | B67: =SUMIFS('Transaction Overview'!$D$2:$D$1850,'Transaction Overview'!$J$2:$J$1850,"Intercompany & Savings Transfers",'Transaction Overview'!$D$2:$D$1850,">0") -> 36500 | C67: =SUMIFS('Transaction Overview'!$D$2:$D$1850,'Transaction Overview'!$J$2:$J$1850,"Intercompany & Savings Transfers",'Transaction Overview'!$D$2:$D$1850,"<0") -> -123202.89 | D67: =B67+C67 -> -86702.89
A69: Payroll & Contractors
A70: Andres Alarcon Payroll | B70: =SUMIFS('Transaction Overview'!$D$2:$D$1850,'Transaction Overview'!$I$2:$I$1850,$A70,'Transaction Overview'!$D$2:$D$1850,">0") -> 0 | C70: =SUMIFS('Transaction Overview'!$D$2:$D$1850,'Transaction Overview'!$I$2:$I$1850,$A70,'Transaction Overview'!$D$2:$D$1850,"<0") -> -21448.99 | D70: =B70+C70 -> -21448.99
A71: Ashley Sarshar - Payroll | B71: =SUMIFS('Transaction Overview'!$D$2:$D$1850,'Transaction Overview'!$I$2:$I$1850,$A71,'Transaction Overview'!$D$2:$D$1850,">0") -> 0 | C71: =SUMIFS('Transaction Overview'!$D$2:$D$1850,'Transaction Overview'!$I$2:$I$1850,$A71,'Transaction Overview'!$D$2:$D$1850,"<0") -> -4000 | D71: =B71+C71 -> -4000
A72: DWG HR | B72: =SUMIFS('Transaction Overview'!$D$2:$D$1850,'Transaction Overview'!$I$2:$I$1850,$A72,'Transaction Overview'!$D$2:$D$1850,">0") -> 0 | C72: =SUMIFS('Transaction Overview'!$D$2:$D$1850,'Transaction Overview'!$I$2:$I$1850,$A72,'Transaction Overview'!$D$2:$D$1850,"<0") -> -20790.27 | D72: =B72+C72 -> -20790.27
A73: Max Rodriguez - Payroll | B73: =SUMIFS('Transaction Overview'!$D$2:$D$1850,'Transaction Overview'!$I$2:$I$1850,$A73,'Transaction Overview'!$D$2:$D$1850,">0") -> 0 | C73: =SUMIFS('Transaction Overview'!$D$2:$D$1850,'Transaction Overview'!$I$2:$I$1850,$A73,'Transaction Overview'!$D$2:$D$1850,"<0") -> -15000 | D73: =B73+C73 -> -15000
A74: Mike Paytonjian - Payroll | B74: =SUMIFS('Transaction Overview'!$D$2:$D$1850,'Transaction Overview'!$I$2:$I$1850,$A74,'Transaction Overview'!$D$2:$D$1850,">0") -> 0 | C74: =SUMIFS('Transaction Overview'!$D$2:$D$1850,'Transaction Overview'!$I$2:$I$1850,$A74,'Transaction Overview'!$D$2:$D$1850,"<0") -> -43250 | D74: =B74+C74 -> -43250
A75: Online Payroll Payment Reversed | B75: =SUMIFS('Transaction Overview'!$D$2:$D$1850,'Transaction Overview'!$I$2:$I$1850,$A75,'Transaction Overview'!$D$2:$D$1850,">0") -> 750 | C75: =SUMIFS('Transaction Overview'!$D$2:$D$1850,'Transaction Overview'!$I$2:$I$1850,$A75,'Transaction Overview'!$D$2:$D$1850,"<0") -> -750 | D75: =B75+C75 -> 0
A76: Rami Frankl - Payroll | B76: =SUMIFS('Transaction Overview'!$D$2:$D$1850,'Transaction Overview'!$I$2:$I$1850,$A76,'Transaction Overview'!$D$2:$D$1850,">0") -> 0 | C76: =SUMIFS('Transaction Overview'!$D$2:$D$1850,'Transaction Overview'!$I$2:$I$1850,$A76,'Transaction Overview'!$D$2:$D$1850,"<0") -> -1250 | D76: =B76+C76 -> -1250
A77: Ruth Alcancia - Forward Bridge Payment | B77: =SUMIFS('Transaction Overview'!$D$2:$D$1850,'Transaction Overview'!$I$2:$I$1850,$A77,'Transaction Overview'!$D$2:$D$1850,">0") -> 0 | C77: =SUMIFS('Transaction Overview'!$D$2:$D$1850,'Transaction Overview'!$I$2:$I$1850,$A77,'Transaction Overview'!$D$2:$D$1850,"<0") -> -4140 | D77: =B77+C77 -> -4140
A78: Ryan Billings - Payroll | B78: =SUMIFS('Transaction Overview'!$D$2:$D$1850,'Transaction Overview'!$I$2:$I$1850,$A78,'Transaction Overview'!$D$2:$D$1850,">0") -> 0 | C78: =SUMIFS('Transaction Overview'!$D$2:$D$1850,'Transaction Overview'!$I$2:$I$1850,$A78,'Transaction Overview'!$D$2:$D$1850,"<0") -> -28800 | D78: =B78+C78 -> -28800
A79: Suad - Payroll | B79: =SUMIFS('Transaction Overview'!$D$2:$D$1850,'Transaction Overview'!$I$2:$I$1850,$A79,'Transaction Overview'!$D$2:$D$1850,">0") -> 0 | C79: =SUMIFS('Transaction Overview'!$D$2:$D$1850,'Transaction Overview'!$I$2:$I$1850,$A79,'Transaction Overview'!$D$2:$D$1850,"<0") -> -2555 | D79: =B79+C79 -> -2555
A80: Upwork - Sergei M. | B80: =SUMIFS('Transaction Overview'!$D$2:$D$1850,'Transaction Overview'!$I$2:$I$1850,$A80,'Transaction Overview'!$D$2:$D$1850,">0") -> 0 | C80: =SUMIFS('Transaction Overview'!$D$2:$D$1850,'Transaction Overview'!$I$2:$I$1850,$A80,'Transaction Overview'!$D$2:$D$1850,"<0") -> -18667.49 | D80: =B80+C80 -> -18667.49
A81: Subtotal — Payroll & Contractors | B81: =SUMIFS('Transaction Overview'!$D$2:$D$1850,'Transaction Overview'!$J$2:$J$1850,"Payroll & Contractors",'Transaction Overview'!$D$2:$D$1850,">0") -> 750 | C81: =SUMIFS('Transaction Overview'!$D$2:$D$1850,'Transaction Overview'!$J$2:$J$1850,"Payroll & Contractors",'Transaction Overview'!$D$2:$D$1850,"<0") -> -160651.75 | D81: =B81+C81 -> -159901.75
A83: P2P Payments (Zelle/Venmo/PayPal)
A84: PayPal | B84: =SUMIFS('Transaction Overview'!$D$2:$D$1850,'Transaction Overview'!$I$2:$I$1850,$A84,'Transaction Overview'!$D$2:$D$1850,">0") -> 0 | C84: =SUMIFS('Transaction Overview'!$D$2:$D$1850,'Transaction Overview'!$I$2:$I$1850,$A84,'Transaction Overview'!$D$2:$D$1850,"<0") -> -2637.5 | D84: =B84+C84 -> -2637.5
A85: Paypal | B85: =SUMIFS('Transaction Overview'!$D$2:$D$1850,'Transaction Overview'!$I$2:$I$1850,$A85,'Transaction Overview'!$D$2:$D$1850,">0") -> 0 | C85: =SUMIFS('Transaction Overview'!$D$2:$D$1850,'Transaction Overview'!$I$2:$I$1850,$A85,'Transaction Overview'!$D$2:$D$1850,"<0") -> -2637.5 | D85: =B85+C85 -> -2637.5
A86: Venmo | B86: =SUMIFS('Transaction Overview'!$D$2:$D$1850,'Transaction Overview'!$I$2:$I$1850,$A86,'Transaction Overview'!$D$2:$D$1850,">0") -> 0 | C86: =SUMIFS('Transaction Overview'!$D$2:$D$1850,'Transaction Overview'!$I$2:$I$1850,$A86,'Transaction Overview'!$D$2:$D$1850,"<0") -> -67344.81 | D86: =B86+C86 -> -67344.81
A87: Zelle - Aaron Frankel | B87: =SUMIFS('Transaction Overview'!$D$2:$D$1850,'Transaction Overview'!$I$2:$I$1850,$A87,'Transaction Overview'!$D$2:$D$1850,">0") -> 0 | C87: =SUMIFS('Transaction Overview'!$D$2:$D$1850,'Transaction Overview'!$I$2:$I$1850,$A87,'Transaction Overview'!$D$2:$D$1850,"<0") -> -3450 | D87: =B87+C87 -> -3450
A88: Zelle - Adolfo V. | B88: =SUMIFS('Transaction Overview'!$D$2:$D$1850,'Transaction Overview'!$I$2:$I$1850,$A88,'Transaction Overview'!$D$2:$D$1850,">0") -> 0 | C88: =SUMIFS('Transaction Overview'!$D$2:$D$1850,'Transaction Overview'!$I$2:$I$1850,$A88,'Transaction Overview'!$D$2:$D$1850,"<0") -> -1700 | D88: =B88+C88 -> -1700
A89: Zelle - DWG Investor *** | B89: =SUMIFS('Transaction Overview'!$D$2:$D$1850,'Transaction Overview'!$I$2:$I$1850,$A89,'Transaction Overview'!$D$2:$D$1850,">0") -> 0 | C89: =SUMIFS('Transaction Overview'!$D$2:$D$1850,'Transaction Overview'!$I$2:$I$1850,$A89,'Transaction Overview'!$D$2:$D$1850,"<0") -> -1500 | D89: =B89+C89 -> -1500
A90: Zelle - Estella M. | B90: =SUMIFS('Transaction Overview'!$D$2:$D$1850,'Transaction Overview'!$I$2:$I$1850,$A90,'Transaction Overview'!$D$2:$D$1850,">0") -> 0 | C90: =SUMIFS('Transaction Overview'!$D$2:$D$1850,'Transaction Overview'!$I$2:$I$1850,$A90,'Transaction Overview'!$D$2:$D$1850,"<0") -> -7700 | D90: =B90+C90 -> -7700
A91: Zelle - Francisco Bautista | B91: =SUMIFS('Transaction Overview'!$D$2:$D$1850,'Transaction Overview'!$I$2:$I$1850,$A91,'Transaction Overview'!$D$2:$D$1850,">0") -> 0 | C91: =SUMIFS('Transaction Overview'!$D$2:$D$1850,'Transaction Overview'!$I$2:$I$1850,$A91,'Transaction Overview'!$D$2:$D$1850,"<0") -> -1050 | D91: =B91+C91 -> -1050
A92: Zelle - Jeff Fajardo | B92: =SUMIFS('Transaction Overview'!$D$2:$D$1850,'Transaction Overview'!$I$2:$I$1850,$A92,'Transaction Overview'!$D$2:$D$1850,">0") -> 0 | C92: =SUMIFS('Transaction Overview'!$D$2:$D$1850,'Transaction Overview'!$I$2:$I$1850,$A92,'Transaction Overview'!$D$2:$D$1850,"<0") -> -41648 | D92: =B92+C92 -> -41648
A93: Zelle - Jeff Seider | B93: =SUMIFS('Transaction Overview'!$D$2:$D$1850,'Transaction Overview'!$I$2:$I$1850,$A93,'Transaction Overview'!$D$2:$D$1850,">0") -> 0 | C93: =SUMIFS('Transaction Overview'!$D$2:$D$1850,'Transaction Overview'!$I$2:$I$1850,$A93,'Transaction Overview'!$D$2:$D$1850,"<0") -> -8711.83 | D93: =B93+C93 -> -8711.83
A94: Zelle - Joe Saunders | B94: =SUMIFS('Transaction Overview'!$D$2:$D$1850,'Transaction Overview'!$I$2:$I$1850,$A94,'Transaction Overview'!$D$2:$D$1850,">0") -> 0 | C94: =SUMIFS('Transaction Overview'!$D$2:$D$1850,'Transaction Overview'!$I$2:$I$1850,$A94,'Transaction Overview'!$D$2:$D$1850,"<0") -> -500 | D94: =B94+C94 -> -500
A95: Zelle - Meg Maran | B95: =SUMIFS('Transaction Overview'!$D$2:$D$1850,'Transaction Overview'!$I$2:$I$1850,$A95,'Transaction Overview'!$D$2:$D$1850,">0") -> 0 | C95: =SUMIFS('Transaction Overview'!$D$2:$D$1850,'Transaction Overview'!$I$2:$I$1850,$A95,'Transaction Overview'!$D$2:$D$1850,"<0") -> -51.75 | D95: =B95+C95 -> -51.75
... A99: Zelle/P2P | B99: =SUMIFS('Transaction Overview'!$D$2:$D$1850,'Transaction Overview'!$I$2:$I$1850,$A99,'Transaction Overview'!$D$2:$D$1850,">0") -> 0 | C99: =SUMIFS('Transaction Overview'!$D$2:$D$1850,'Transaction Overview'!$I$2:$I$1850,$A99,'Transaction Overview'!$D$2:$D$1850,"<0") -> -1810 | D99: =B99+C99 -> -1810
A100: Subtotal — P2P Payments (Zelle/Venmo/PayPal) | B100: =SUMIFS('Transaction Overview'!$D$2:$D$1850,'Transaction Overview'!$J$2:$J$1850,"P2P Payments (Zelle/Venmo/PayPal)",'Transaction Overview'!$D$2:$D$1850,">0") -> 0 | C100: =SUMIFS('Transaction Overview'!$D$2:$D$1850,'Transaction Overview'!$J$2:$J$1850,"P2P Payments (Zelle/Venmo/PayPal)",'Transaction Overview'!$D$2:$D$1850,"<0") -> -146403.89 | D100: =B100+C100 -> -146403.89
A102: Owner / Family Distributions
A103: Transfer to Angela Dunning | B103: =SUMIFS('Transaction Overview'!$D$2:$D$1850,'Transaction Overview'!$I$2:$I$1850,$A103,'Transaction Overview'!$D$2:$D$1850,">0") -> 0 | C103: =SUMIFS('Transaction Overview'!$D$2:$D$1850,'Transaction Overview'!$I$2:$I$1850,$A103,'Transaction Overview'!$D$2:$D$1850,"<0") -> -304000 | D103: =B103+C103 -> -304000
A104: Transfer to Ava Perez-Dunning | B104: =SUMIFS('Transaction Overview'!$D$2:$D$1850,'Transaction Overview'!$I$2:$I$1850,$A104,'Transaction Overview'!$D$2:$D$1850,">0") -> 0 | C104: =SUMIFS('Transaction Overview'!$D$2:$D$1850,'Transaction Overview'!$I$2:$I$1850,$A104,'Transaction Overview'!$D$2:$D$1850,"<0") -> -19650 | D104: =B104+C104 -> -19650
A105: Transfer to TX Personal Joint | B105: =SUMIFS('Transaction Overview'!$D$2:$D$1850,'Transaction Overview'!$I$2:$I$1850,$A105,'Transaction Overview'!$D$2:$D$1850,">0") -> 0 | C105: =SUMIFS('Transaction Overview'!$D$2:$D$1850,'Transaction Overview'!$I$2:$I$1850,$A105,'Transaction Overview'!$D$2:$D$1850,"<0") -> -124000 | D105: =B105+C105 -> -124000
A106: Subtotal — Owner / Family Distributions | B106: =SUMIFS('Transaction Overview'!$D$2:$D$1850,'Transaction Overview'!$J$2:$J$1850,"Owner / Family Distributions",'Transaction Overview'!$D$2:$D$1850,">0") -> 0 | C106: =SUMIFS('Transaction Overview'!$D$2:$D$1850,'Transaction Overview'!$J$2:$J$1850,"Owner / Family Distributions",'Transaction Overview'!$D$2:$D$1850,"<0") -> -447650 | D106: =B106+C106 -> -447650
A108: Credit Card & Loan Payments
A109: American Express Credit Card PMT | B109: =SUMIFS('Transaction Overview'!$D$2:$D$1850,'Transaction Overview'!$I$2:$I$1850,$A109,'Transaction Overview'!$D$2:$D$1850,">0") -> 0 | C109: =SUMIFS('Transaction Overview'!$D$2:$D$1850,'Transaction Overview'!$I$2:$I$1850,$A109,'Transaction Overview'!$D$2:$D$1850,"<0") -> -165080.55 | D109: =B109+C109 -> -165080.55
A110: SBA EIDL Loan | B110: =SUMIFS('Transaction Overview'!$D$2:$D$1850,'Transaction Overview'!$I$2:$I$1850,$A110,'Transaction Overview'!$D$2:$D$1850,">0") -> 0 | C110: =SUMIFS('Transaction Overview'!$D$2:$D$1850,'Transaction Overview'!$I$2:$I$1850,$A110,'Transaction Overview'!$D$2:$D$1850,"<0") -> -10096 | D110: =B110+C110 -> -10096
A111: SBC EIDL Loan | B111: =SUMIFS('Transaction Overview'!$D$2:$D$1850,'Transaction Overview'!$I$2:$I$1850,$A111,'Transaction Overview'!$D$2:$D$1850,">0") -> 0 | C111: =SUMIFS('Transaction Overview'!$D$2:$D$1850,'Transaction Overview'!$I$2:$I$1850,$A111,'Transaction Overview'!$D$2:$D$1850,"<0") -> -20192 | D111: =B111+C111 -> -20192
A112: Subtotal — Credit Card & Loan Payments | B112: =SUMIFS('Transaction Overview'!$D$2:$D$1850,'Transaction Overview'!$J$2:$J$1850,"Credit Card & Loan Payments",'Transaction Overview'!$D$2:$D$1850,">0") -> 0 | C112: =SUMIFS('Transaction Overview'!$D$2:$D$1850,'Transaction Overview'!$J$2:$J$1850,"Credit Card & Loan Payments",'Transaction Overview'!$D$2:$D$1850,"<0") -> -195368.55 | D112: =B112+C112 -> -195368.55
A114: Taxes
A115: Taxes | B115: =SUMIFS('Transaction Overview'!$D$2:$D$1850,'Transaction Overview'!$I$2:$I$1850,$A115,'Transaction Overview'!$D$2:$D$1850,">0") -> 0 | C115: =SUMIFS('Transaction Overview'!$D$2:$D$1850,'Transaction Overview'!$I$2:$I$1850,$A115,'Transaction Overview'!$D$2:$D$1850,"<0") -> -9322.5 | D115: =B115+C115 -> -9322.5
A116: Subtotal — Taxes | B116: =SUMIFS('Transaction Overview'!$D$2:$D$1850,'Transaction Overview'!$J$2:$J$1850,"Taxes",'Transaction Overview'!$D$2:$D$1850,">0") -> 0 | C116: =SUMIFS('Transaction Overview'!$D$2:$D$1850,'Transaction Overview'!$J$2:$J$1850,"Taxes",'Transaction Overview'!$D$2:$D$1850,"<0") -> -9322.5 | D116: =B116+C116 -> -9322.5
A118: DWG Operating
A119: AI Subscriptions | B119: =SUMIFS('Transaction Overview'!$D$2:$D$1850,'Transaction Overview'!$I$2:$I$1850,$A119,'Transaction Overview'!$D$2:$D$1850,">0") -> 0 | C119: =SUMIFS('Transaction Overview'!$D$2:$D$1850,'Transaction Overview'!$I$2:$I$1850,$A119,'Transaction Overview'!$D$2:$D$1850,"<0") -> -106.4 | D119: =B119+C119 -> -106.4
A120: Bank & Wire Fees | B120: =SUMIFS('Transaction Overview'!$D$2:$D$1850,'Transaction Overview'!$I$2:$I$1850,$A120,'Transaction Overview'!$D$2:$D$1850,">0") -> 0 | C120: =SUMIFS('Transaction Overview'!$D$2:$D$1850,'Transaction Overview'!$I$2:$I$1850,$A120,'Transaction Overview'!$D$2:$D$1850,"<0") -> -405.13 | D120: =B120+C120 -> -405.13
A121: Bank Fees | B121: =SUMIFS('Transaction Overview'!$D$2:$D$1850,'Transaction Overview'!$I$2:$I$1850,$A121,'Transaction Overview'!$D$2:$D$1850,">0") -> 0 | C121: =SUMIFS('Transaction Overview'!$D$2:$D$1850,'Transaction Overview'!$I$2:$I$1850,$A121,'Transaction Overview'!$D$2:$D$1850,"<0") -> -237.31 | D121: =B121+C121 -> -237.31
...

Sheet Monthly Breakdown
A1: Chase 1168 — DWG Capital Group 2025 Activity
A2: Monthly Breakdown | Jan 2025 – Dec 2025
A4: Category | B4: =DATE(2025,1,1) -> 45658 | C4: =DATE(2025,2,1) -> 45689 | D4: =DATE(2025,3,1) -> 45717 | E4: =DATE(2025,4,1) -> 45748 | F4: =DATE(2025,5,1) -> 45778 | G4: =DATE(2025,6,1) -> 45809 | H4: =DATE(2025,7,1) -> 45839 | I4: =DATE(2025,8,1) -> 45870 | J4: =DATE(2025,9,1) -> 45901 | K4: =DATE(2025,10,1) -> 45931 | L4: =DATE(2025,11,1) -> 45962 | M4: =DATE(2025,12,1) -> 45992 | N4: Total
A5: Deal-Specific
A6: Deal Specific: Moab | B6: =SUMIFS('Transaction Overview'!$D$2:$D$1850,'Transaction Overview'!$I$2:$I$1850,$A6,'Transaction Overview'!$H$2:$H$1850,B$4) -> 0 | C6: =SUMIFS('Transaction Overview'!$D$2:$D$1850,'Transaction Overview'!$I$2:$I$1850,$A6,'Transaction Overview'!$H$2:$H$1850,C$4) -> 0 | D6: =SUMIFS('Transaction Overview'!$D$2:$D$1850,'Transaction Overview'!$I$2:$I$1850,$A6,'Transaction Overview'!$H$2:$H$1850,D$4) -> 0 | E6: =SUMIFS('Transaction Overview'!$D$2:$D$1850,'Transaction Overview'!$I$2:$I$1850,$A6,'Transaction Overview'!$H$2:$H$1850,E$4) -> 0 | F6: =SUMIFS('Transaction Overview'!$D$2:$D$1850,'Transaction Overview'!$I$2:$I$1850,$A6,'Transaction Overview'!$H$2:$H$1850,F$4) -> 0 | G6: =SUMIFS('Transaction Overview'!$D$2:$D$1850,'Transaction Overview'!$I$2:$I$1850,$A6,'Transaction Overview'!$H$2:$H$1850,G$4) -> 0 | H6: =SUMIFS('Transaction Overview'!$D$2:$D$1850,'Transaction Overview'!$I$2:$I$1850,$A6,'Transaction Overview'!$H$2:$H$1850,H$4) -> 0 | I6: =SUMIFS('Transaction Overview'!$D$2:$D$1850,'Transaction Overview'!$I$2:$I$1850,$A6,'Transaction Overview'!$H$2:$H$1850,I$4) -> 0 | ... M6: =SUMIFS('Transaction Overview'!$D$2:$D$1850,'Transaction Overview'!$I$2:$I$1850,$A6,'Transaction Overview'!$H$2:$H$1850,M$4) -> 0 | N6: =SUM(B6:M6) -> -40000
A7: Deal Specific: Moab (Reimbursement) | B7: =SUMIFS('Transaction Overview'!$D$2:$D$1850,'Transaction Overview'!$I$2:$I$1850,$A7,'Transaction Overview'!$H$2:$H$1850,B$4) -> 0 | C7: =SUMIFS('Transaction Overview'!$D$2:$D$1850,'Transaction Overview'!$I$2:$I$1850,$A7,'Transaction Overview'!$H$2:$H$1850,C$4) -> 0 | D7: =SUMIFS('Transaction Overview'!$D$2:$D$1850,'Transaction Overview'!$I$2:$I$1850,$A7,'Transaction Overview'!$H$2:$H$1850,D$4) -> 0 | E7: =SUMIFS('Transaction Overview'!$D$2:$D$1850,'Transaction Overview'!$I$2:$I$1850,$A7,'Transaction Overview'!$H$2:$H$1850,E$4) -> 0 | F7: =SUMIFS('Transaction Overview'!$D$2:$D$1850,'Transaction Overview'!$I$2:$I$1850,$A7,'Transaction Overview'!$H$2:$H$1850,F$4) -> 0 | G7: =SUMIFS('Transaction Overview'!$D$2:$D$1850,'Transaction Overview'!$I$2:$I$1850,$A7,'Transaction Overview'!$H$2:$H$1850,G$4) -> 0 | H7: =SUMIFS('Transaction Overview'!$D$2:$D$1850,'Transaction Overview'!$I$2:$I$1850,$A7,'Transaction Overview'!$H$2:$H$1850,H$4) -> 0 | I7: =SUMIFS('Transaction Overview'!$D$2:$D$1850,'Transaction Overview'!$I$2:$I$1850,$A7,'Transaction Overview'!$H$2:$H$1850,I$4) -> 0 | ... M7: =SUMIFS('Transaction Overview'!$D$2:$D$1850,'Transaction Overview'!$I$2:$I$1850,$A7,'Transaction Overview'!$H$2:$H$1850,M$4) -> 0 | N7: =SUM(B7:M7) -> 40000
A8: Deal Specific: TBD | B8: =SUMIFS('Transaction Overview'!$D$2:$D$1850,'Transaction Overview'!$I$2:$I$1850,$A8,'Transaction Overview'!$H$2:$H$1850,B$4) -> 0 | C8: =SUMIFS('Transaction Overview'!$D$2:$D$1850,'Transaction Overview'!$I$2:$I$1850,$A8,'Transaction Overview'!$H$2:$H$1850,C$4) -> 0 | D8: =SUMIFS('Transaction Overview'!$D$2:$D$1850,'Transaction Overview'!$I$2:$I$1850,$A8,'Transaction Overview'!$H$2:$H$1850,D$4) -> -15000 | E8: =SUMIFS('Transaction Overview'!$D$2:$D$1850,'Transaction Overview'!$I$2:$I$1850,$A8,'Transaction Overview'!$H$2:$H$1850,E$4) -> 0 | F8: =SUMIFS('Transaction Overview'!$D$2:$D$1850,'Transaction Overview'!$I$2:$I$1850,$A8,'Transaction Overview'!$H$2:$H$1850,F$4) -> 0 | G8: =SUMIFS('Transaction Overview'!$D$2:$D$1850,'Transaction Overview'!$I$2:$I$1850,$A8,'Transaction Overview'!$H$2:$H$1850,G$4) -> 0 | H8: =SUMIFS('Transaction Overview'!$D$2:$D$1850,'Transaction Overview'!$I$2:$I$1850,$A8,'Transaction Overview'!$H$2:$H$1850,H$4) -> 0 | I8: =SUMIFS('Transaction Overview'!$D$2:$D$1850,'Transaction Overview'!$I$2:$I$1850,$A8,'Transaction Overview'!$H$2:$H$1850,I$4) -> 0 | ... M8: =SUMIFS('Transaction Overview'!$D$2:$D$1850,'Transaction Overview'!$I$2:$I$1850,$A8,'Transaction Overview'!$H$2:$H$1850,M$4) -> 0 | N8: =SUM(B8:M8) -> -15000
A9: Commissions — Incoming
A10: Incoming Commission: Aspen | B10: =SUMIFS('Transaction Overview'!$D$2:$D$1850,'Transaction Overview'!$I$2:$I$1850,$A10,'Transaction Overview'!$H$2:$H$1850,B$4) -> 0 | C10: =SUMIFS('Transaction Overview'!$D$2:$D$1850,'Transaction Overview'!$I$2:$I$1850,$A10,'Transaction Overview'!$H$2:$H$1850,C$4) -> 0 | D10: =SUMIFS('Transaction Overview'!$D$2:$D$1850,'Transaction Overview'!$I$2:$I$1850,$A10,'Transaction Overview'!$H$2:$H$1850,D$4) -> 0 | E10: =SUMIFS('Transaction Overview'!$D$2:$D$1850,'Transaction Overview'!$I$2:$I$1850,$A10,'Transaction Overview'!$H$2:$H$1850,E$4) -> 0 | F10: =SUMIFS('Transaction Overview'!$D$2:$D$1850,'Transaction Overview'!$I$2:$I$1850,$A10,'Transaction Overview'!$H$2:$H$1850,F$4) -> 0 | G10: =SUMIFS('Transaction Overview'!$D$2:$D$1850,'Transaction Overview'!$I$2:$I$1850,$A10,'Transaction Overview'!$H$2:$H$1850,G$4) -> 87850 | H10: =SUMIFS('Transaction Overview'!$D$2:$D$1850,'Transaction Overview'!$I$2:$I$1850,$A10,'Transaction Overview'!$H$2:$H$1850,H$4) -> 0 | I10: =SUMIFS('Transaction Overview'!$D$2:$D$1850,'Transaction Overview'!$I$2:$I$1850,$A10,'Transaction Overview'!$H$2:$H$1850,I$4) -> 0 | ... M10: =SUMIFS('Transaction Overview'!$D$2:$D$1850,'Transaction Overview'!$I$2:$I$1850,$A10,'Transaction Overview'!$H$2:$H$1850,M$4) -> 0 | N10: =SUM(B10:M10) -> 87850
A11: Incoming Commission: Charlmont | B11: =SUMIFS('Transaction Overview'!$D$2:$D$1850,'Transaction Overview'!$I$2:$I$1850,$A11,'Transaction Overview'!$H$2:$H$1850,B$4) -> 0 | C11: =SUMIFS('Transaction Overview'!$D$2:$D$1850,'Transaction Overview'!$I$2:$I$1850,$A11,'Transaction Overview'!$H$2:$H$1850,C$4) -> 0 | D11: =SUMIFS('Transaction Overview'!$D$2:$D$1850,'Transaction Overview'!$I$2:$I$1850,$A11,'Transaction Overview'!$H$2:$H$1850,D$4) -> 0 | E11: =SUMIFS('Transaction Overview'!$D$2:$D$1850,'Transaction Overview'!$I$2:$I$1850,$A11,'Transaction Overview'!$H$2:$H$1850,E$4) -> 0 | F11: =SUMIFS('Transaction Overview'!$D$2:$D$1850,'Transaction Overview'!$I$2:$I$1850,$A11,'Transaction Overview'!$H$2:$H$1850,F$4) -> 0 | G11: =SUMIFS('Transaction Overview'!$D$2:$D$1850,'Transaction Overview'!$I$2:$I$1850,$A11,'Transaction Overview'!$H$2:$H$1850,G$4) -> 0 | H11: =SUMIFS('Transaction Overview'!$D$2:$D$1850,'Transaction Overview'!$I$2:$I$1850,$A11,'Transaction Overview'!$H$2:$H$1850,H$4) -> 0 | I11: =SUMIFS('Transaction Overview'!$D$2:$D$1850,'Transaction Overview'!$I$2:$I$1850,$A11,'Transaction Overview'!$H$2:$H$1850,I$4) -> 0 | ... M11: =SUMIFS('Transaction Overview'!$D$2:$D$1850,'Transaction Overview'!$I$2:$I$1850,$A11,'Transaction Overview'!$H$2:$H$1850,M$4) -> 235000 | N11: =SUM(B11:M11) -> 210000
A12: Incoming Commission: 115 Penn | B12: =SUMIFS('Transaction Overview'!$D$2:$D$1850,'Transaction Overview'!$I$2:$I$1850,$A12,'Transaction Overview'!$H$2:$H$1850,B$4) -> 0 | C12: =SUMIFS('Transaction Overview'!$D$2:$D$1850,'Transaction Overview'!$I$2:$I$1850,$A12,'Transaction Overview'!$H$2:$H$1850,C$4) -> 0 | D12: =SUMIFS('Transaction Overview'!$D$2:$D$1850,'Transaction Overview'!$I$2:$I$1850,$A12,'Transaction Overview'!$H$2:$H$1850,D$4) -> 0 | E12: =SUMIFS('Transaction Overview'!$D$2:$D$1850,'Transaction Overview'!$I$2:$I$1850,$A12,'Transaction Overview'!$H$2:$H$1850,E$4) -> 0 | F12: =SUMIFS('Transaction Overview'!$D$2:$D$1850,'Transaction Overview'!$I$2:$I$1850,$A12,'Transaction Overview'!$H$2:$H$1850,F$4) -> 0 | G12: =SUMIFS('Transaction Overview'!$D$2:$D$1850,'Transaction Overview'!$I$2:$I$1850,$A12,'Transaction Overview'!$H$2:$H$1850,G$4) -> 0 | H12: =SUMIFS('Transaction Overview'!$D$2:$D$1850,'Transaction Overview'!$I$2:$I$1850,$A12,'Transaction Overview'!$H$2:$H$1850,H$4) -> 0 | I12: =SUMIFS('Transaction Overview'!$D$2:$D$1850,'Transaction Overview'!$I$2:$I$1850,$A12,'Transaction Overview'!$H$2:$H$1850,I$4) -> 0 | ... M12: =SUMIFS('Transaction Overview'!$D$2:$D$1850,'Transaction Overview'!$I$2:$I$1850,$A12,'Transaction Overview'!$H$2:$H$1850,M$4) -> 0 | N12: =SUM(B12:M12) -> 42500
A13: Incoming Commission: 2055 Laguna Canyon | B13: =SUMIFS('Transaction Overview'!$D$2:$D$1850,'Transaction Overview'!$I$2:$I$1850,$A13,'Transaction Overview'!$H$2:$H$1850,B$4) -> 0 | C13: =SUMIFS('Transaction Overview'!$D$2:$D$1850,'Transaction Overview'!$I$2:$I$1850,$A13,'Transaction Overview'!$H$2:$H$1850,C$4) -> 0 | D13: =SUMIFS('Transaction Overview'!$D$2:$D$1850,'Transaction Overview'!$I$2:$I$1850,$A13,'Transaction Overview'!$H$2:$H$1850,D$4) -> 0 | E13: =SUMIFS('Transaction Overview'!$D$2:$D$1850,'Transaction Overview'!$I$2:$I$1850,$A13,'Transaction Overview'!$H$2:$H$1850,E$4) -> 0 | F13: =SUMIFS('Transaction Overview'!$D$2:$D$1850,'Transaction Overview'!$I$2:$I$1850,$A13,'Transaction Overview'!$H$2:$H$1850,F$4) -> 0 | G13: =SUMIFS('Transaction Overview'!$D$2:$D$1850,'Transaction Overview'!$I$2:$I$1850,$A13,'Transaction Overview'!$H$2:$H$1850,G$4) -> 0 | H13: =SUMIFS('Transaction Overview'!$D$2:$D$1850,'Transaction Overview'!$I$2:$I$1850,$A13,'Transaction Overview'!$H$2:$H$1850,H$4) -> 0 | I13: =SUMIFS('Transaction Overview'!$D$2:$D$1850,'Transaction Overview'!$I$2:$I$1850,$A13,'Transaction Overview'!$H$2:$H$1850,I$4) -> 0 | ... M13: =SUMIFS('Transaction Overview'!$D$2:$D$1850,'Transaction Overview'!$I$2:$I$1850,$A13,'Transaction Overview'!$H$2:$H$1850,M$4) -> 0 | N13: =SUM(B13:M13) -> 40000
A14: Incoming Commission: 20635 N 29th Pl, Phoenix AZ (Deer Valley) | B14: =SUMIFS('Transaction Overview'!$D$2:$D$1850,'Transaction Overview'!$I$2:$I$1850,$A14,'Transaction Overview'!$H$2:$H$1850,B$4) -> 0 | C14: =SUMIFS('Transaction Overview'!$D$2:$D$1850,'Transaction Overview'!$I$2:$I$1850,$A14,'Transaction Overview'!$H$2:$H$1850,C$4) -> 0 | D14: =SUMIFS('Transaction Overview'!$D$2:$D$1850,'Transaction Overview'!$I$2:$I$1850,$A14,'Transaction Overview'!$H$2:$H$1850,D$4) -> 0 | E14: =SUMIFS('Transaction Overview'!$D$2:$D$1850,'Transaction Overview'!$I$2:$I$1850,$A14,'Transaction Overview'!$H$2:$H$1850,E$4) -> 0 | F14: =SUMIFS('Transaction Overview'!$D$2:$D$1850,'Transaction Overview'!$I$2:$I$1850,$A14,'Transaction Overview'!$H$2:$H$1850,F$4) -> 0 | G14: =SUMIFS('Transaction Overview'!$D$2:$D$1850,'Transaction Overview'!$I$2:$I$1850,$A14,'Transaction Overview'!$H$2:$H$1850,G$4) -> 0 | H14: =SUMIFS('Transaction Overview'!$D$2:$D$1850,'Transaction Overview'!$I$2:$I$1850,$A14,'Transaction Overview'!$H$2:$H$1850,H$4) -> 0 | I14: =SUMIFS('Transaction Overview'!$D$2:$D$1850,'Transaction Overview'!$I$2:$I$1850,$A14,'Transaction Overview'!$H$2:$H$1850,I$4) -> 0 | ... M14: =SUMIFS('Transaction Overview'!$D$2:$D$1850,'Transaction Overview'!$I$2:$I$1850,$A14,'Transaction Overview'!$H$2:$H$1850,M$4) -> 0 | N14: =SUM(B14:M14) -> 69000
A15: Incoming Commission: 315 York | B15: =SUMIFS('Transaction Overview'!$D$2:$D$1850,'Transaction Overview'!$I$2:$I$1850,$A15,'Transaction Overview'!$H$2:$H$1850,B$4) -> 0 | C15: =SUMIFS('Transaction Overview'!$D$2:$D$1850,'Transaction Overview'!$I$2:$I$1850,$A15,'Transaction Overview'!$H$2:$H$1850,C$4) -> 0 | D15: =SUMIFS('Transaction Overview'!$D$2:$D$1850,'Transaction Overview'!$I$2:$I$1850,$A15,'Transaction Overview'!$H$2:$H$1850,D$4) -> 40350 | E15: =SUMIFS('Transaction Overview'!$D$2:$D$1850,'Transaction Overview'!$I$2:$I$1850,$A15,'Transaction Overview'!$H$2:$H$1850,E$4) -> 0 | F15: =SUMIFS('Transaction Overview'!$D$2:$D$1850,'Transaction Overview'!$I$2:$I$1850,$A15,'Transaction Overview'!$H$2:$H$1850,F$4) -> 0 | G15: =SUMIFS('Transaction Overview'!$D$2:$D$1850,'Transaction Overview'!$I$2:$I$1850,$A15,'Transaction Overview'!$H$2:$H$1850,G$4) -> 0 | H15: =SUMIFS('Transaction Overview'!$D$2:$D$1850,'Transaction Overview'!$I$2:$I$1850,$A15,'Transaction Overview'!$H$2:$H$1850,H$4) -> 0 | I15: =SUMIFS('Transaction Overview'!$D$2:$D$1850,'Transaction Overview'!$I$2:$I$1850,$A15,'Transaction Overview'!$H$2:$H$1850,I$4) -> 0 | ... M15: =SUMIFS('Transaction Overview'!$D$2:$D$1850,'Transaction Overview'!$I$2:$I$1850,$A15,'Transaction Overview'!$H$2:$H$1850,M$4) -> 0 | N15: =SUM(B15:M15) -> 40350
A16: Incoming Commission: 3811 E Bankhead | B16: =SUMIFS('Transaction Overview'!$D$2:$D$1850,'Transaction Overview'!$I$2:$I$1850,$A16,'Transaction Overview'!$H$2:$H$1850,B$4) -> 0 | C16: =SUMIFS('Transaction Overview'!$D$2:$D$1850,'Transaction Overview'!$I$2:$I$1850,$A16,'Transaction Overview'!$H$2:$H$1850,C$4) -> 85700 | D16: =SUMIFS('Transaction Overview'!$D$2:$D$1850,'Transaction Overview'!$I$2:$I$1850,$A16,'Transaction Overview'!$H$2:$H$1850,D$4) -> 0 | E16: =SUMIFS('Transaction Overview'!$D$2:$D$1850,'Transaction Overview'!$I$2:$I$1850,$A16,'Transaction Overview'!$H$2:$H$1850,E$4) -> 0 | F16: =SUMIFS('Transaction Overview'!$D$2:$D$1850,'Transaction Overview'!$I$2:$I$1850,$A16,'Transaction Overview'!$H$2:$H$1850,F$4) -> 0 | G16: =SUMIFS('Transaction Overview'!$D$2:$D$1850,'Transaction Overview'!$I$2:$I$1850,$A16,'Transaction Overview'!$H$2:$H$1850,G$4) -> 0 | H16: =SUMIFS('Transaction Overview'!$D$2:$D$1850,'Transaction Overview'!$I$2:$I$1850,$A16,'Transaction Overview'!$H$2:$H$1850,H$4) -> 0 | I16: =SUMIFS('Transaction Overview'!$D$2:$D$1850,'Transaction Overview'!$I$2:$I$1850,$A16,'Transaction Overview'!$H$2:$H$1850,I$4) -> 0 | ... M16: =SUMIFS('Transaction Overview'!$D$2:$D$1850,'Transaction Overview'!$I$2:$I$1850,$A16,'Transaction Overview'!$H$2:$H$1850,M$4) -> 0 | N16: =SUM(B16:M16) -> 85700
A17: Incoming Commission: Edge Builder | B17: =SUMIFS('Transaction Overview'!$D$2:$D$1850,'Transaction Overview'!$I$2:$I$1850,$A17,'Transaction Overview'!$H$2:$H$1850,B$4) -> 61037 | C17: =SUMIFS('Transaction Overview'!$D$2:$D$1850,'Transaction Overview'!$I$2:$I$1850,$A17,'Transaction Overview'!$H$2:$H$1850,C$4) -> 0 | D17: =SUMIFS('Transaction Overview'!$D$2:$D$1850,'Transaction Overview'!$I$2:$I$1850,$A17,'Transaction Overview'!$H$2:$H$1850,D$4) -> 0 | E17: =SUMIFS('Transaction Overview'!$D$2:$D$1850,'Transaction Overview'!$I$2:$I$1850,$A17,'Transaction Overview'!$H$2:$H$1850,E$4) -> 0 | F17: =SUMIFS('Transaction Overview'!$D$2:$D$1850,'Transaction Overview'!$I$2:$I$1850,$A17,'Transaction Overview'!$H$2:$H$1850,F$4) -> 0 | G17: =SUMIFS('Transaction Overview'!$D$2:$D$1850,'Transaction Overview'!$I$2:$I$1850,$A17,'Transaction Overview'!$H$2:$H$1850,G$4) -> 0 | H17: =SUMIFS('Transaction Overview'!$D$2:$D$1850,'Transaction Overview'!$I$2:$I$1850,$A17,'Transaction Overview'!$H$2:$H$1850,H$4) -> 0 | I17: =SUMIFS('Transaction Overview'!$D$2:$D$1850,'Transaction Overview'!$I$2:$I$1850,$A17,'Transaction Overview'!$H$2:$H$1850,I$4) -> 0 | ... M17: =SUMIFS('Transaction Overview'!$D$2:$D$1850,'Transaction Overview'!$I$2:$I$1850,$A17,'Transaction Overview'!$H$2:$H$1850,M$4) -> 0 | N17: =SUM(B17:M17) -> 61037
A18: Commissions — Outgoing
A19: Commission Paid: Brian Bowis (Charlmont) | B19: =SUMIFS('Transaction Overview'!$D$2:$D$1850,'Transaction Overview'!$I$2:$I$1850,$A19,'Transaction Overview'!$H$2:$H$1850,B$4) -> 0 | C19: =SUMIFS('Transaction Overview'!$D$2:$D$1850,'Transaction Overview'!$I$2:$I$1850,$A19,'Transaction Overview'!$H$2:$H$1850,C$4) -> 0 | D19: =SUMIFS('Transaction Overview'!$D$2:$D$1850,'Transaction Overview'!$I$2:$I$1850,$A19,'Transaction Overview'!$H$2:$H$1850,D$4) -> 0 | E19: =SUMIFS('Transaction Overview'!$D$2:$D$1850,'Transaction Overview'!$I$2:$I$1850,$A19,'Transaction Overview'!$H$2:$H$1850,E$4) -> 0 | F19: =SUMIFS('Transaction Overview'!$D$2:$D$1850,'Transaction Overview'!$I$2:$I$1850,$A19,'Transaction Overview'!$H$2:$H$1850,F$4) -> 0 | G19: =SUMIFS('Transaction Overview'!$D$2:$D$1850,'Transaction Overview'!$I$2:$I$1850,$A19,'Transaction Overview'!$H$2:$H$1850,G$4) -> 0 | H19: =SUMIFS('Transaction Overview'!$D$2:$D$1850,'Transaction Overview'!$I$2:$I$1850,$A19,'Transaction Overview'!$H$2:$H$1850,H$4) -> 0 | I19: =SUMIFS('Transaction Overview'!$D$2:$D$1850,'Transaction Overview'!$I$2:$I$1850,$A19,'Transaction Overview'!$H$2:$H$1850,I$4) -> 0 | ... M19: =SUMIFS('Transaction Overview'!$D$2:$D$1850,'Transaction Overview'!$I$2:$I$1850,$A19,'Transaction Overview'!$H$2:$H$1850,M$4) -> -102500 | N19: =SUM(B19:M19) -> -102500
A20: MAG Pass-Through
A21: Due to Andrew – MAG Pass-Through 30% | B21: =SUMIFS('Transaction Overview'!$D$2:$D$1850,'Transaction Overview'!$I$2:$I$1850,$A21,'Transaction Overview'!$H$2:$H$1850,B$4) -> 0 | C21: =SUMIFS('Transaction Overview'!$D$2:$D$1850,'Transaction Overview'!$I$2:$I$1850,$A21,'Transaction Overview'!$H$2:$H$1850,C$4) -> -114028.02 | D21: =SUMIFS('Transaction Overview'!$D$2:$D$1850,'Transaction Overview'!$I$2:$I$1850,$A21,'Transaction Overview'!$H$2:$H$1850,D$4) -> 0 | E21: =SUMIFS('Transaction Overview'!$D$2:$D$1850,'Transaction Overview'!$I$2:$I$1850,$A21,'Transaction Overview'!$H$2:$H$1850,E$4) -> 0 | F21: =SUMIFS('Transaction Overview'!$D$2:$D$1850,'Transaction Overview'!$I$2:$I$1850,$A21,'Transaction Overview'!$H$2:$H$1850,F$4) -> 0 | G21: =SUMIFS('Transaction Overview'!$D$2:$D$1850,'Transaction Overview'!$I$2:$I$1850,$A21,'Transaction Overview'!$H$2:$H$1850,G$4) -> 0 | H21: =SUMIFS('Transaction Overview'!$D$2:$D$1850,'Transaction Overview'!$I$2:$I$1850,$A21,'Transaction Overview'!$H$2:$H$1850,H$4) -> 0 | I21: =SUMIFS('Transaction Overview'!$D$2:$D$1850,'Transaction Overview'!$I$2:$I$1850,$A21,'Transaction Overview'!$H$2:$H$1850,I$4) -> 0 | ... M21: =SUMIFS('Transaction Overview'!$D$2:$D$1850,'Transaction Overview'!$I$2:$I$1850,$A21,'Transaction Overview'!$H$2:$H$1850,M$4) -> 0 | N21: =SUM(B21:M21) -> -114028.02
A22: Due to Andrew – MAG Pass-Through 30% | B22: =SUMIFS('Transaction Overview'!$D$2:$D$1850,'Transaction Overview'!$I$2:$I$1850,$A22,'Transaction Overview'!$H$2:$H$1850,B$4) -> 0 | C22: =SUMIFS('Transaction Overview'!$D$2:$D$1850,'Transaction Overview'!$I$2:$I$1850,$A22,'Transaction Overview'!$H$2:$H$1850,C$4) -> -15300 | D22: =SUMIFS('Transaction Overview'!$D$2:$D$1850,'Transaction Overview'!$I$2:$I$1850,$A22,'Transaction Overview'!$H$2:$H$1850,D$4) -> 0 | E22: =SUMIFS('Transaction Overview'!$D$2:$D$1850,'Transaction Overview'!$I$2:$I$1850,$A22,'Transaction Overview'!$H$2:$H$1850,E$4) -> 0 | F22: =SUMIFS('Transaction Overview'!$D$2:$D$1850,'Transaction Overview'!$I$2:$I$1850,$A22,'Transaction Overview'!$H$2:$H$1850,F$4) -> 0 | G22: =SUMIFS('Transaction Overview'!$D$2:$D$1850,'Transaction Overview'!$I$2:$I$1850,$A22,'Transaction Overview'!$H$2:$H$1850,G$4) -> 0 | H22: =SUMIFS('Transaction Overview'!$D$2:$D$1850,'Transaction Overview'!$I$2:$I$1850,$A22,'Transaction Overview'!$H$2:$H$1850,H$4) -> 0 | I22: =SUMIFS('Transaction Overview'!$D$2:$D$1850,'Transaction Overview'!$I$2:$I$1850,$A22,'Transaction Overview'!$H$2:$H$1850,I$4) -> -25500 | ... M22: =SUMIFS('Transaction Overview'!$D$2:$D$1850,'Transaction Overview'!$I$2:$I$1850,$A22,'Transaction Overview'!$H$2:$H$1850,M$4) -> 0 | N22: =SUM(B22:M22) -> -83437
A23: Due to Dax – MAG Pass-Through 70% | B23: =SUMIFS('Transaction Overview'!$D$2:$D$1850,'Transaction Overview'!$I$2:$I$1850,$A23,'Transaction Overview'!$H$2:$H$1850,B$4) -> 0 | C23: =SUMIFS('Transaction Overview'!$D$2:$D$1850,'Transaction Overview'!$I$2:$I$1850,$A23,'Transaction Overview'!$H$2:$H$1850,C$4) -> -295765.37 | D23: =SUMIFS('Transaction Overview'!$D$2:$D$1850,'Transaction Overview'!$I$2:$I$1850,$A23,'Transaction Overview'!$H$2:$H$1850,D$4) -> 0 | E23: =SUMIFS('Transaction Overview'!$D$2:$D$1850,'Transaction Overview'!$I$2:$I$1850,$A23,'Transaction Overview'!$H$2:$H$1850,E$4) -> 0 | F23: =SUMIFS('Transaction Overview'!$D$2:$D$1850,'Transaction Overview'!$I$2:$I$1850,$A23,'Transaction Overview'!$H$2:$H$1850,F$4) -> 0 | G23: =SUMIFS('Transaction Overview'!$D$2:$D$1850,'Transaction Overview'!$I$2:$I$1850,$A23,'Transaction Overview'!$H$2:$H$1850,G$4) -> 0 | H23: =SUMIFS('Transaction Overview'!$D$2:$D$1850,'Transaction Overview'!$I$2:$I$1850,$A23,'Transaction Overview'!$H$2:$H$1850,H$4) -> 0 | I23: =SUMIFS('Transaction Overview'!$D$2:$D$1850,'Transaction Overview'!$I$2:$I$1850,$A23,'Transaction Overview'!$H$2:$H$1850,I$4) -> -59500 | ... M23: =SUMIFS('Transaction Overview'!$D$2:$D$1850,'Transaction Overview'!$I$2:$I$1850,$A23,'Transaction Overview'!$H$2:$H$1850,M$4) -> 0 | N23: =SUM(B23:M23) -> -454752.37
A24: MAG - Admeer Advisory Transfer | B24: =SUMIFS('Transaction Overview'!$D$2:$D$1850,'Transaction Overview'!$I$2:$I$1850,$A24,'Transaction Overview'!$H$2:$H$1850,B$4) -> 0 | C24: =SUMIFS('Transaction Overview'!$D$2:$D$1850,'Transaction Overview'!$I$2:$I$1850,$A24,'Transaction Overview'!$H$2:$H$1850,C$4) -> 0 | D24: =SUMIFS('Transaction Overview'!$D$2:$D$1850,'Transaction Overview'!$I$2:$I$1850,$A24,'Transaction Overview'!$H$2:$H$1850,D$4) -> 0 | E24: =SUMIFS('Transaction Overview'!$D$2:$D$1850,'Transaction Overview'!$I$2:$I$1850,$A24,'Transaction Overview'!$H$2:$H$1850,E$4) -> 0 | F24: =SUMIFS('Transaction Overview'!$D$2:$D$1850,'Transaction Overview'!$I$2:$I$1850,$A24,'Transaction Overview'!$H$2:$H$1850,F$4) -> 0 | G24: =SUMIFS('Transaction Overview'!$D$2:$D$1850,'Transaction Overview'!$I$2:$I$1850,$A24,'Transaction Overview'!$H$2:$H$1850,G$4) -> 0 | H24: =SUMIFS('Transaction Overview'!$D$2:$D$1850,'Transaction Overview'!$I$2:$I$1850,$A24,'Transaction Overview'!$H$2:$H$1850,H$4) -> 0 | I24: =SUMIFS('Transaction Overview'!$D$2:$D$1850,'Transaction Overview'!$I$2:$I$1850,$A24,'Transaction Overview'!$H$2:$H$1850,I$4) -> 0 | ... M24: =SUMIFS('Transaction Overview'!$D$2:$D$1850,'Transaction Overview'!$I$2:$I$1850,$A24,'Transaction Overview'!$H$2:$H$1850,M$4) -> -10000 | N24: =SUM(B24:M24) -> -10000
A25: MAG Capital Partners Pass-Through Wire – 70/30 Split | B25: =SUMIFS('Transaction Overview'!$D$2:$D$1850,'Transaction Overview'!$I$2:$I$1850,$A25,'Transaction Overview'!$H$2:$H$1850,B$4) -> 0 | C25: =SUMIFS('Transaction Overview'!$D$2:$D$1850,'Transaction Overview'!$I$2:$I$1850,$A25,'Transaction Overview'!$H$2:$H$1850,C$4) -> 50000 | D25: =SUMIFS('Transaction Overview'!$D$2:$D$1850,'Transaction Overview'!$I$2:$I$1850,$A25,'Transaction Overview'!$H$2:$H$1850,D$4) -> 0 | E25: =SUMIFS('Transaction Overview'!$D$2:$D$1850,'Transaction Overview'!$I$2:$I$1850,$A25,'Transaction Overview'!$H$2:$H$1850,E$4) -> 0 | F25: =SUMIFS('Transaction Overview'!$D$2:$D$1850,'Transaction Overview'!$I$2:$I$1850,$A25,'Transaction Overview'!$H$2:$H$1850,F$4) -> 0 | G25: =SUMIFS('Transaction Overview'!$D$2:$D$1850,'Transaction Overview'!$I$2:$I$1850,$A25,'Transaction Overview'!$H$2:$H$1850,G$4) -> 0 | H25: =SUMIFS('Transaction Overview'!$D$2:$D$1850,'Transaction Overview'!$I$2:$I$1850,$A25,'Transaction Overview'!$H$2:$H$1850,H$4) -> 170000 | I25: =SUMIFS('Transaction Overview'!$D$2:$D$1850,'Transaction Overview'!$I$2:$I$1850,$A25,'Transaction Overview'!$H$2:$H$1850,I$4) -> 0 | ... M25: =SUMIFS('Transaction Overview'!$D$2:$D$1850,'Transaction Overview'!$I$2:$I$1850,$A25,'Transaction Overview'!$H$2:$H$1850,M$4) -> 0 | N25: =SUM(B25:M25) -> 365125
A26: Poseidon Asset Group
A27: Poseidon Asset Group (Incoming) | B27: =SUMIFS('Transaction Overview'!$D$2:$D$1850,'Transaction Overview'!$I$2:$I$1850,$A27,'Transaction Overview'!$H$2:$H$1850,B$4) -> 0 | C27: =SUMIFS('Transaction Overview'!$D$2:$D$1850,'Transaction Overview'!$I$2:$I$1850,$A27,'Transaction Overview'!$H$2:$H$1850,C$4) -> 0 | D27: =SUMIFS('Transaction Overview'!$D$2:$D$1850,'Transaction Overview'!$I$2:$I$1850,$A27,'Transaction Overview'!$H$2:$H$1850,D$4) -> 0 | E27: =SUMIFS('Transaction Overview'!$D$2:$D$1850,'Transaction Overview'!$I$2:$I$1850,$A27,'Transaction Overview'!$H$2:$H$1850,E$4) -> 0 | F27: =SUMIFS('Transaction Overview'!$D$2:$D$1850,'Transaction Overview'!$I$2:$I$1850,$A27,'Transaction Overview'!$H$2:$H$1850,F$4) -> 0 | G27: =SUMIFS('Transaction Overview'!$D$2:$D$1850,'Transaction Overview'!$I$2:$I$1850,$A27,'Transaction Overview'!$H$2:$H$1850,G$4) -> 63000 | H27: =SUMIFS('Transaction Overview'!$D$2:$D$1850,'Transaction Overview'!$I$2:$I$1850,$A27,'Transaction Overview'!$H$2:$H$1850,H$4) -> 80000 | I27: =SUMIFS('Transaction Overview'!$D$2:$D$1850,'Transaction Overview'!$I$2:$I$1850,$A27,'Transaction Overview'!$H$2:$H$1850,I$4) -> 30000 | ... M27: =SUMIFS('Transaction Overview'!$D$2:$D$1850,'Transaction Overview'!$I$2:$I$1850,$A27,'Transaction Overview'!$H$2:$H$1850,M$4) -> 50000 | N27: =SUM(B27:M27) -> 423000
A28: Transfer From Poseidon Asset Group | B28: =SUMIFS('Transaction Overview'!$D$2:$D$1850,'Transaction Overview'!$I$2:$I$1850,$A28,'Transaction Overview'!$H$2:$H$1850,B$4) -> 30000 | C28: =SUMIFS('Transaction Overview'!$D$2:$D$1850,'Transaction Overview'!$I$2:$I$1850,$A28,'Transaction Overview'!$H$2:$H$1850,C$4) -> 50000 | D28: =SUMIFS('Transaction Overview'!$D$2:$D$1850,'Transaction Overview'!$I$2:$I$1850,$A28,'Transaction Overview'!$H$2:$H$1850,D$4) -> 105000 | E28: =SUMIFS('Transaction Overview'!$D$2:$D$1850,'Transaction Overview'!$I$2:$I$1850,$A28,'Transaction Overview'!$H$2:$H$1850,E$4) -> 30000 | F28: =SUMIFS('Transaction Overview'!$D$2:$D$1850,'Transaction Overview'!$I$2:$I$1850,$A28,'Transaction Overview'!$H$2:$H$1850,F$4) -> 40000 | G28: =SUMIFS('Transaction Overview'!$D$2:$D$1850,'Transaction Overview'!$I$2:$I$1850,$A28,'Transaction Overview'!$H$2:$H$1850,G$4) -> 0 | H28: =SUMIFS('Transaction Overview'!$D$2:$D$1850,'Transaction Overview'!$I$2:$I$1850,$A28,'Transaction Overview'!$H$2:$H$1850,H$4) -> 0 | I28: =SUMIFS('Transaction Overview'!$D$2:$D$1850,'Transaction Overview'!$I$2:$I$1850,$A28,'Transaction Overview'!$H$2:$H$1850,I$4) -> 0 | ... M28: =SUMIFS('Transaction Overview'!$D$2:$D$1850,'Transaction Overview'!$I$2:$I$1850,$A28,'Transaction Overview'!$H$2:$H$1850,M$4) -> 0 | N28: =SUM(B28:M28) -> 255000
A29: Transfer to Poseidon | B29: =SUMIFS('Transaction Overview'!$D$2:$D$1850,'Transaction Overview'!$I$2:$I$1850,$A29,'Transaction Overview'!$H$2:$H$1850,B$4) -> 0 | C29: =SUMIFS('Transaction Overview'!$D$2:$D$1850,'Transaction Overview'!$I$2:$I$1850,$A29,'Transaction Overview'!$H$2:$H$1850,C$4) -> 0 | D29: =SUMIFS('Transaction Overview'!$D$2:$D$1850,'Transaction Overview'!$I$2:$I$1850,$A29,'Transaction Overview'!$H$2:$H$1850,D$4) -> 0 | E29: =SUMIFS('Transaction Overview'!$D$2:$D$1850,'Transaction Overview'!$I$2:$I$1850,$A29,'Transaction Overview'!$H$2:$H$1850,E$4) -> 0 | F29: =SUMIFS('Transaction Overview'!$D$2:$D$1850,'Transaction Overview'!$I$2:$I$1850,$A29,'Transaction Overview'!$H$2:$H$1850,F$4) -> 0 | G29: =SUMIFS('Transaction Overview'!$D$2:$D$1850,'Transaction Overview'!$I$2:$I$1850,$A29,'Transaction Overview'!$H$2:$H$1850,G$4) -> 0 | H29: =SUMIFS('Transaction Overview'!$D$2:$D$1850,'Transaction Overview'!$I$2:$I$1850,$A29,'Transaction Overview'!$H$2:$H$1850,H$4) -> 0 | I29: =SUMIFS('Transaction Overview'!$D$2:$D$1850,'Transaction Overview'!$I$2:$I$1850,$A29,'Transaction Overview'!$H$2:$H$1850,I$4) -> 0 | ... M29: =SUMIFS('Transaction Overview'!$D$2:$D$1850,'Transaction Overview'!$I$2:$I$1850,$A29,'Transaction Overview'!$H$2:$H$1850,M$4) -> 0 | N29: =SUM(B29:M29) -> -5000
A30: Intercompany & Savings Transfers
A31: DWG Capital Partners - Outgoing | B31: =SUMIFS('Transaction Overview'!$D$2:$D$1850,'Transaction Overview'!$I$2:$I$1850,$A31,'Transaction Overview'!$H$2:$H$1850,B$4) -> 0 | C31: =SUMIFS('Transaction Overview'!$D$2:$D$1850,'Transaction Overview'!$I$2:$I$1850,$A31,'Transaction Overview'!$H$2:$H$1850,C$4) -> 0 | D31: =SUMIFS('Transaction Overview'!$D$2:$D$1850,'Transaction Overview'!$I$2:$I$1850,$A31,'Transaction Overview'!$H$2:$H$1850,D$4) -> 0 | E31: =SUMIFS('Transaction Overview'!$D$2:$D$1850,'Transaction Overview'!$I$2:$I$1850,$A31,'Transaction Overview'!$H$2:$H$1850,E$4) -> 0 | F31: =SUMIFS('Transaction Overview'!$D$2:$D$1850,'Transaction Overview'!$I$2:$I$1850,$A31,'Transaction Overview'!$H$2:$H$1850,F$4) -> 0 | G31: =SUMIFS('Transaction Overview'!$D$2:$D$1850,'Transaction Overview'!$I$2:$I$1850,$A31,'Transaction Overview'!$H$2:$H$1850,G$4) -> -2000 | H31: =SUMIFS('Transaction Overview'!$D$2:$D$1850,'Transaction Overview'!$I$2:$I$1850,$A31,'Transaction Overview'!$H$2:$H$1850,H$4) -> 0 | I31: =SUMIFS('Transaction Overview'!$D$2:$D$1850,'Transaction Overview'!$I$2:$I$1850,$A31,'Transaction Overview'!$H$2:$H$1850,I$4) -> 0 | ... M31: =SUMIFS('Transaction Overview'!$D$2:$D$1850,'Transaction Overview'!$I$2:$I$1850,$A31,'Transaction Overview'!$H$2:$H$1850,M$4) -> -1000 | N31: =SUM(B31:M31) -> -90500
A32: Internal Transfer | B32: =SUMIFS('Transaction Overview'!$D$2:$D$1850,'Transaction Overview'!$I$2:$I$1850,$A32,'Transaction Overview'!$H$2:$H$1850,B$4) -> 0 | C32: =SUMIFS('Transaction Overview'!$D$2:$D$1850,'Transaction Overview'!$I$2:$I$1850,$A32,'Transaction Overview'!$H$2:$H$1850,C$4) -> 0 | D32: =SUMIFS('Transaction Overview'!$D$2:$D$1850,'Transaction Overview'!$I$2:$I$1850,$A32,'Transaction Overview'!$H$2:$H$1850,D$4) -> 0 | E32: =SUMIFS('Transaction Overview'!$D$2:$D$1850,'Transaction Overview'!$I$2:$I$1850,$A32,'Transaction Overview'!$H$2:$H$1850,E$4) -> 0 | F32: =SUMIFS('Transaction Overview'!$D$2:$D$1850,'Transaction Overview'!$I$2:$I$1850,$A32,'Transaction Overview'!$H$2:$H$1850,F$4) -> 0 | G32: =SUMIFS('Transaction Overview'!$D$2:$D$1850,'Transaction Overview'!$I$2:$I$1850,$A32,'Transaction Overview'!$H$2:$H$1850,G$4) -> 20000 | H32: =SUMIFS('Transaction Overview'!$D$2:$D$1850,'Transaction Overview'!$I$2:$I$1850,$A32,'Transaction Overview'!$H$2:$H$1850,H$4) -> 0 | I32: =SUMIFS('Transaction Overview'!$D$2:$D$1850,'Transaction Overview'!$I$2:$I$1850,$A32,'Transaction Overview'!$H$2:$H$1850,I$4) -> 0 | ... M32: =SUMIFS('Transaction Overview'!$D$2:$D$1850,'Transaction Overview'!$I$2:$I$1850,$A32,'Transaction Overview'!$H$2:$H$1850,M$4) -> 0 | N32: =SUM(B32:M32) -> 20000
A33: Transfer From Butler Weldments | B33: =SUMIFS('Transaction Overview'!$D$2:$D$1850,'Transaction Overview'!$I$2:$I$1850,$A33,'Transaction Overview'!$H$2:$H$1850,B$4) -> 0 | C33: =SUMIFS('Transaction Overview'!$D$2:$D$1850,'Transaction Overview'!$I$2:$I$1850,$A33,'Transaction Overview'!$H$2:$H$1850,C$4) -> 0 | D33: =SUMIFS('Transaction Overview'!$D$2:$D$1850,'Transaction Overview'!$I$2:$I$1850,$A33,'Transaction Overview'!$H$2:$H$1850,D$4) -> 1500 | E33: =SUMIFS('Transaction Overview'!$D$2:$D$1850,'Transaction Overview'!$I$2:$I$1850,$A33,'Transaction Overview'!$H$2:$H$1850,E$4) -> 0 | F33: =SUMIFS('Transaction Overview'!$D$2:$D$1850,'Transaction Overview'!$I$2:$I$1850,$A33,'Transaction Overview'!$H$2:$H$1850,F$4) -> 0 | G33: =SUMIFS('Transaction Overview'!$D$2:$D$1850,'Transaction Overview'!$I$2:$I$1850,$A33,'Transaction Overview'!$H$2:$H$1850,G$4) -> 0 | H33: =SUMIFS('Transaction Overview'!$D$2:$D$1850,'Transaction Overview'!$I$2:$I$1850,$A33,'Transaction Overview'!$H$2:$H$1850,H$4) -> 0 | I33: =SUMIFS('Transaction Overview'!$D$2:$D$1850,'Transaction Overview'!$I$2:$I$1850,$A33,'Transaction Overview'!$H$2:$H$1850,I$4) -> 0 | ... M33: =SUMIFS('Transaction Overview'!$D$2:$D$1850,'Transaction Overview'!$I$2:$I$1850,$A33,'Transaction Overview'!$H$2:$H$1850,M$4) -> 0 | N33: =SUM(B33:M33) -> 1500
A34: Transfer From DWG Capital Partners | B34: =SUMIFS('Transaction Overview'!$D$2:$D$1850,'Transaction Overview'!$I$2:$I$1850,$A34,'Transaction Overview'!$H$2:$H$1850,B$4) -> 0 | C34: =SUMIFS('Transaction Overview'!$D$2:$D$1850,'Transaction Overview'!$I$2:$I$1850,$A34,'Transaction Overview'!$H$2:$H$1850,C$4) -> 5000 | D34: =SUMIFS('Transaction Overview'!$D$2:$D$1850,'Transaction Overview'!$I$2:$I$1850,$A34,'Transaction Overview'!$H$2:$H$1850,D$4) -> 0 | E34: =SUMIFS('Transaction Overview'!$D$2:$D$1850,'Transaction Overview'!$I$2:$I$1850,$A34,'Transaction Overview'!$H$2:$H$1850,E$4) -> 0 | F34: =SUMIFS('Transaction Overview'!$D$2:$D$1850,'Transaction Overview'!$I$2:$I$1850,$A34,'Transaction Overview'!$H$2:$H$1850,F$4) -> 0 | G34: =SUMIFS('Transaction Overview'!$D$2:$D$1850,'Transaction Overview'!$I$2:$I$1850,$A34,'Transaction Overview'!$H$2:$H$1850,G$4) -> 0 | H34: =SUMIFS('Transaction Overview'!$D$2:$D$1850,'Transaction Overview'!$I$2:$I$1850,$A34,'Transaction Overview'!$H$2:$H$1850,H$4) -> 0 | I34: =SUMIFS('Transaction Overview'!$D$2:$D$1850,'Transaction Overview'!$I$2:$I$1850,$A34,'Transaction Overview'!$H$2:$H$1850,I$4) -> 0 | ... M34: =SUMIFS('Transaction Overview'!$D$2:$D$1850,'Transaction Overview'!$I$2:$I$1850,$A34,'Transaction Overview'!$H$2:$H$1850,M$4) -> 0 | N34: =SUM(B34:M34) -> 5000
A35: Transfer to Breese Marketing | B35: =SUMIFS('Transaction Overview'!$D$2:$D$1850,'Transaction Overview'!$I$2:$I$1850,$A35,'Transaction Overview'!$H$2:$H$1850,B$4) -> 0 | C35: =SUMIFS('Transaction Overview'!$D$2:$D$1850,'Transaction Overview'!$I$2:$I$1850,$A35,'Transaction Overview'!$H$2:$H$1850,C$4) -> 0 | D35: =SUMIFS('Transaction Overview'!$D$2:$D$1850,'Transaction Overview'!$I$2:$I$1850,$A35,'Transaction Overview'!$H$2:$H$1850,D$4) -> 0 | E35: =SUMIFS('Transaction Overview'!$D$2:$D$1850,'Transaction Overview'!$I$2:$I$1850,$A35,'Transaction Overview'!$H$2:$H$1850,E$4) -> 0 | F35: =SUMIFS('Transaction Overview'!$D$2:$D$1850,'Transaction Overview'!$I$2:$I$1850,$A35,'Transaction Overview'!$H$2:$H$1850,F$4) -> 0 | G35: =SUMIFS('Transaction Overview'!$D$2:$D$1850,'Transaction Overview'!$I$2:$I$1850,$A35,'Transaction Overview'!$H$2:$H$1850,G$4) -> -500 | H35: =SUMIFS('Transaction Overview'!$D$2:$D$1850,'Transaction Overview'!$I$2:$I$1850,$A35,'Transaction Overview'!$H$2:$H$1850,H$4) -> 0 | I35: =SUMIFS('Transaction Overview'!$D$2:$D$1850,'Transaction Overview'!$I$2:$I$1850,$A35,'Transaction Overview'!$H$2:$H$1850,I$4) -> 0 | ... M35: =SUMIFS('Transaction Overview'!$D$2:$D$1850,'Transaction Overview'!$I$2:$I$1850,$A35,'Transaction Overview'!$H$2:$H$1850,M$4) -> 0 | N35: =SUM(B35:M35) -> -500
A36: Transfer to DWG Capital Group_Costar | B36: =SUMIFS('Transaction Overview'!$D$2:$D$1850,'Transaction Overview'!$I$2:$I$1850,$A36,'Transaction Overview'!$H$2:$H$1850,B$4) -> 0 | C36: =SUMIFS('Transaction Overview'!$D$2:$D$1850,'Transaction Overview'!$I$2:$I$1850,$A36,'Transaction Overview'!$H$2:$H$1850,C$4) -> 0 | D36: =SUMIFS('Transaction Overview'!$D$2:$D$1850,'Transaction Overview'!$I$2:$I$1850,$A36,'Transaction Overview'!$H$2:$H$1850,D$4) -> 0 | E36: =SUMIFS('Transaction Overview'!$D$2:$D$1850,'Transaction Overview'!$I$2:$I$1850,$A36,'Transaction Overview'!$H$2:$H$1850,E$4) -> 0 | F36: =SUMIFS('Transaction Overview'!$D$2:$D$1850,'Transaction Overview'!$I$2:$I$1850,$A36,'Transaction Overview'!$H$2:$H$1850,F$4) -> -5000 | G36: =SUMIFS('Transaction Overview'!$D$2:$D$1850,'Transaction Overview'!$I$2:$I$1850,$A36,'Transaction Overview'!$H$2:$H$1850,G$4) -> 0 | H36: =SUMIFS('Transaction Overview'!$D$2:$D$1850,'Transaction Overview'!$I$2:$I$1850,$A36,'Transaction Overview'!$H$2:$H$1850,H$4) -> 0 | I36: =SUMIFS('Transaction Overview'!$D$2:$D$1850,'Transaction Overview'!$I$2:$I$1850,$A36,'Transaction Overview'!$H$2:$H$1850,I$4) -> -1000 | ... M36: =SUMIFS('Transaction Overview'!$D$2:$D$1850,'Transaction Overview'!$I$2:$I$1850,$A36,'Transaction Overview'!$H$2:$H$1850,M$4) -> 0 | N36: =SUM(B36:M36) -> -9000
A37: Transfer to DWG Savings | B37: =SUMIFS('Transaction Overview'!$D$2:$D$1850,'Transaction Overview'!$I$2:$I$1850,$A37,'Transaction Overview'!$H$2:$H$1850,B$4) -> -1000 | C37: =SUMIFS('Transaction Overview'!$D$2:$D$1850,'Transaction Overview'!$I$2:$I$1850,$A37,'Transaction Overview'!$H$2:$H$1850,C$4) -> -1000 | D37: =SUMIFS('Transaction Overview'!$D$2:$D$1850,'Transaction Overview'!$I$2:$I$1850,$A37,'Transaction Overview'!$H$2:$H$1850,D$4) -> -1000 | E37: =SUMIFS('Transaction Overview'!$D$2:$D$1850,'Transaction Overview'!$I$2:$I$1850,$A37,'Transaction Overview'!$H$2:$H$1850,E$4) -> 0 | F37: =SUMIFS('Transaction Overview'!$D$2:$D$1850,'Transaction Overview'!$I$2:$I$1850,$A37,'Transaction Overview'!$H$2:$H$1850,F$4) -> -1800 | G37: =SUMIFS('Transaction Overview'!$D$2:$D$1850,'Transaction Overview'!$I$2:$I$1850,$A37,'Transaction Overview'!$H$2:$H$1850,G$4) -> -1500 | H37: =SUMIFS('Transaction Overview'!$D$2:$D$1850,'Transaction Overview'!$I$2:$I$1850,$A37,'Transaction Overview'!$H$2:$H$1850,H$4) -> -2000 | I37: =SUMIFS('Transaction Overview'!$D$2:$D$1850,'Transaction Overview'!$I$2:$I$1850,$A37,'Transaction Overview'!$H$2:$H$1850,I$4) -> -2000 | ... M37: =SUMIFS('Transaction Overview'!$D$2:$D$1850,'Transaction Overview'!$I$2:$I$1850,$A37,'Transaction Overview'!$H$2:$H$1850,M$4) -> 0 | N37: =SUM(B37:M37) -> -15300
A38: Transfer to DWG Capital Partners | B38: =SUMIFS('Transaction Overview'!$D$2:$D$1850,'Transaction Overview'!$I$2:$I$1850,$A38,'Transaction Overview'!$H$2:$H$1850,B$4) -> 0 | C38: =SUMIFS('Transaction Overview'!$D$2:$D$1850,'Transaction Overview'!$I$2:$I$1850,$A38,'Transaction Overview'!$H$2:$H$1850,C$4) -> 0 | D38: =SUMIFS('Transaction Overview'!$D$2:$D$1850,'Transaction Overview'!$I$2:$I$1850,$A38,'Transaction Overview'!$H$2:$H$1850,D$4) -> 0 | E38: =SUMIFS('Transaction Overview'!$D$2:$D$1850,'Transaction Overview'!$I$2:$I$1850,$A38,'Transaction Overview'!$H$2:$H$1850,E$4) -> 0 | F38: =SUMIFS('Transaction Overview'!$D$2:$D$1850,'Transaction Overview'!$I$2:$I$1850,$A38,'Transaction Overview'!$H$2:$H$1850,F$4) -> -1000 | G38: =SUMIFS('Transaction Overview'!$D$2:$D$1850,'Transaction Overview'!$I$2:$I$1850,$A38,'Transaction Overview'!$H$2:$H$1850,G$4) -> 0 | H38: =SUMIFS('Transaction Overview'!$D$2:$D$1850,'Transaction Overview'!$I$2:$I$1850,$A38,'Transaction Overview'!$H$2:$H$1850,H$4) -> 0 | I38: =SUMIFS('Transaction Overview'!$D$2:$D$1850,'Transaction Overview'!$I$2:$I$1850,$A38,'Transaction Overview'!$H$2:$H$1850,I$4) -> 0 | ... M38: =SUMIFS('Transaction Overview'!$D$2:$D$1850,'Transaction Overview'!$I$2:$I$1850,$A38,'Transaction Overview'!$H$2:$H$1850,M$4) -> 0 | N38: =SUM(B38:M38) -> -1000
A39: Transfer to DWG Holdings | B39: =SUMIFS('Transaction Overview'!$D$2:$D$1850,'Transaction Overview'!$I$2:$I$1850,$A39,'Transaction Overview'!$H$2:$H$1850,B$4) -> 0 | C39: =SUMIFS('Transaction Overview'!$D$2:$D$1850,'Transaction Overview'!$I$2:$I$1850,$A39,'Transaction Overview'!$H$2:$H$1850,C$4) -> -100 | D39: =SUMIFS('Transaction Overview'!$D$2:$D$1850,'Transaction Overview'!$I$2:$I$1850,$A39,'Transaction Overview'!$H$2:$H$1850,D$4) -> 0 | E39: =SUMIFS('Transaction Overview'!$D$2:$D$1850,'Transaction Overview'!$I$2:$I$1850,$A39,'Transaction Overview'!$H$2:$H$1850,E$4) -> 0 | F39: =SUMIFS('Transaction Overview'!$D$2:$D$1850,'Transaction Overview'!$I$2:$I$1850,$A39,'Transaction Overview'!$H$2:$H$1850,F$4) -> 0 | G39: =SUMIFS('Transaction Overview'!$D$2:$D$1850,'Transaction Overview'!$I$2:$I$1850,$A39,'Transaction Overview'!$H$2:$H$1850,G$4) -> 0 | H39: =SUMIFS('Transaction Overview'!$D$2:$D$1850,'Transaction Overview'!$I$2:$I$1850,$A39,'Transaction Overview'!$H$2:$H$1850,H$4) -> 0 | I39: =SUMIFS('Transaction Overview'!$D$2:$D$1850,'Transaction Overview'!$I$2:$I$1850,$A39,'Transaction Overview'!$H$2:$H$1850,I$4) -> 0 | ... M39: =SUMIFS('Transaction Overview'!$D$2:$D$1850,'Transaction Overview'!$I$2:$I$1850,$A39,'Transaction Overview'!$H$2:$H$1850,M$4) -> 0 | N39: =SUM(B39:M39) -> -100
A40: Transfer to DWGCG_Costar | B40: =SUMIFS('Transaction Overview'!$D$2:$D$1850,'Transaction Overview'!$I$2:$I$1850,$A40,'Transaction Overview'!$H$2:$H$1850,B$4) -> -902.89 | C40: =SUMIFS('Transaction Overview'!$D$2:$D$1850,'Transaction Overview'!$I$2:$I$1850,$A40,'Transaction Overview'!$H$2:$H$1850,C$4) -> -3000 | D40: =SUMIFS('Transaction Overview'!$D$2:$D$1850,'Transaction Overview'!$I$2:$I$1850,$A40,'Transaction Overview'!$H$2:$H$1850,D$4) -> 0 | E40: =SUMIFS('Transaction Overview'!$D$2:$D$1850,'Transaction Overview'!$I$2:$I$1850,$A40,'Transaction Overview'!$H$2:$H$1850,E$4) -> 0 | F40: =SUMIFS('Transaction Overview'!$D$2:$D$1850,'Transaction Overview'!$I$2:$I$1850,$A40,'Transaction Overview'!$H$2:$H$1850,F$4) -> 0 | G40: =SUMIFS('Transaction Overview'!$D$2:$D$1850,'Transaction Overview'!$I$2:$I$1850,$A40,'Transaction Overview'!$H$2:$H$1850,G$4) -> 0 | H40: =SUMIFS('Transaction Overview'!$D$2:$D$1850,'Transaction Overview'!$I$2:$I$1850,$A40,'Transaction Overview'!$H$2:$H$1850,H$4) -> 0 | I40: =SUMIFS('Transaction Overview'!$D$2:$D$1850,'Transaction Overview'!$I$2:$I$1850,$A40,'Transaction Overview'!$H$2:$H$1850,I$4) -> 0 | ... M40: =SUMIFS('Transaction Overview'!$D$2:$D$1850,'Transaction Overview'!$I$2:$I$1850,$A40,'Transaction Overview'!$H$2:$H$1850,M$4) -> 0 | N40: =SUM(B40:M40) -> -3902.89
A41: Transfer to Ecomm_PosPrtnrs | B41: =SUMIFS('Transaction Overview'!$D$2:$D$1850,'Transaction Overview'!$I$2:$I$1850,$A41,'Transaction Overview'!$H$2:$H$1850,B$4) -> 10000 | C41: =SUMIFS('Transaction Overview'!$D$2:$D$1850,'Transaction Overview'!$I$2:$I$1850,$A41,'Transaction Overview'!$H$2:$H$1850,C$4) -> 0 | D41: =SUMIFS('Transaction Overview'!$D$2:$D$1850,'Transaction Overview'!$I$2:$I$1850,$A41,'Transaction Overview'!$H$2:$H$1850,D$4) -> 0 | E41: =SUMIFS('Transaction Overview'!$D$2:$D$1850,'Transaction Overview'!$I$2:$I$1850,$A41,'Transaction Overview'!$H$2:$H$1850,E$4) -> 0 | F41: =SUMIFS('Transaction Overview'!$D$2:$D$1850,'Transaction Overview'!$I$2:$I$1850,$A41,'Transaction Overview'!$H$2:$H$1850,F$4) -> 0 | G41: =SUMIFS('Transaction Overview'!$D$2:$D$1850,'Transaction Overview'!$I$2:$I$1850,$A41,'Transaction Overview'!$H$2:$H$1850,G$4) -> 0 | H41: =SUMIFS('Transaction Overview'!$D$2:$D$1850,'Transaction Overview'!$I$2:$I$1850,$A41,'Transaction Overview'!$H$2:$H$1850,H$4) -> 0 | I41: =SUMIFS('Transaction Overview'!$D$2:$D$1850,'Transaction Overview'!$I$2:$I$1850,$A41,'Transaction Overview'!$H$2:$H$1850,I$4) -> 0 | ... M41: =SUMIFS('Transaction Overview'!$D$2:$D$1850,'Transaction Overview'!$I$2:$I$1850,$A41,'Transaction Overview'!$H$2:$H$1850,M$4) -> 0 | N41: =SUM(B41:M41) -> 10000
A42: Transfer to Judd Sol Prop | B42: =SUMIFS('Transaction Overview'!$D$2:$D$1850,'Transaction Overview'!$I$2:$I$1850,$A42,'Transaction Overview'!$H$2:$H$1850,B$4) -> 0 | C42: =SUMIFS('Transaction Overview'!$D$2:$D$1850,'Transaction Overview'!$I$2:$I$1850,$A42,'Transaction Overview'!$H$2:$H$1850,C$4) -> 0 | D42: =SUMIFS('Transaction Overview'!$D$2:$D$1850,'Transaction Overview'!$I$2:$I$1850,$A42,'Transaction Overview'!$H$2:$H$1850,D$4) -> 0 | E42: =SUMIFS('Transaction Overview'!$D$2:$D$1850,'Transaction Overview'!$I$2:$I$1850,$A42,'Transaction Overview'!$H$2:$H$1850,E$4) -> 0 | F42: =SUMIFS('Transaction Overview'!$D$2:$D$1850,'Transaction Overview'!$I$2:$I$1850,$A42,'Transaction Overview'!$H$2:$H$1850,F$4) -> -500 | G42: =SUMIFS('Transaction Overview'!$D$2:$D$1850,'Transaction Overview'!$I$2:$I$1850,$A42,'Transaction Overview'!$H$2:$H$1850,G$4) -> 0 | H42: =SUMIFS('Transaction Overview'!$D$2:$D$1850,'Transaction Overview'!$I$2:$I$1850,$A42,'Transaction Overview'!$H$2:$H$1850,H$4) -> 0 | I42: =SUMIFS('Transaction Overview'!$D$2:$D$1850,'Transaction Overview'!$I$2:$I$1850,$A42,'Transaction Overview'!$H$2:$H$1850,I$4) -> 0 | ... M42: =SUMIFS('Transaction Overview'!$D$2:$D$1850,'Transaction Overview'!$I$2:$I$1850,$A42,'Transaction Overview'!$H$2:$H$1850,M$4) -> 0 | N42: =SUM(B42:M42) -> -500
... A46: Transfer to Theut Glass | B46: =SUMIFS('Transaction Overview'!$D$2:$D$1850,'Transaction Overview'!$I$2:$I$1850,$A46,'Transaction Overview'!$H$2:$H$1850,B$4) -> 0 | C46: =SUMIFS('Transaction Overview'!$D$2:$D$1850,'Transaction Overview'!$I$2:$I$1850,$A46,'Transaction Overview'!$H$2:$H$1850,C$4) -> -1000 | D46: =SUMIFS('Transaction Overview'!$D$2:$D$1850,'Transaction Overview'!$I$2:$I$1850,$A46,'Transaction Overview'!$H$2:$H$1850,D$4) -> 0 | E46: =SUMIFS('Transaction Overview'!$D$2:$D$1850,'Transaction Overview'!$I$2:$I$1850,$A46,'Transaction Overview'!$H$2:$H$1850,E$4) -> 0 | F46: =SUMIFS('Transaction Overview'!$D$2:$D$1850,'Transaction Overview'!$I$2:$I$1850,$A46,'Transaction Overview'!$H$2:$H$1850,F$4) -> 0 | G46: =SUMIFS('Transaction Overview'!$D$2:$D$1850,'Transaction Overview'!$I$2:$I$1850,$A46,'Transaction Overview'!$H$2:$H$1850,G$4) -> 0 | H46: =SUMIFS('Transaction Overview'!$D$2:$D$1850,'Transaction Overview'!$I$2:$I$1850,$A46,'Transaction Overview'!$H$2:$H$1850,H$4) -> 0 | I46: =SUMIFS('Transaction Overview'!$D$2:$D$1850,'Transaction Overview'!$I$2:$I$1850,$A46,'Transaction Overview'!$H$2:$H$1850,I$4) -> 0 | ... M46: =SUMIFS('Transaction Overview'!$D$2:$D$1850,'Transaction Overview'!$I$2:$I$1850,$A46,'Transaction Overview'!$H$2:$H$1850,M$4) -> 0 | N46: =SUM(B46:M46) -> -1000
A47: Payroll & Contractors
A48: Andres Alarcon Payroll | B48: =SUMIFS('Transaction Overview'!$D$2:$D$1850,'Transaction Overview'!$I$2:$I$1850,$A48,'Transaction Overview'!$H$2:$H$1850,B$4) -> -1510 | C48: =SUMIFS('Transaction Overview'!$D$2:$D$1850,'Transaction Overview'!$I$2:$I$1850,$A48,'Transaction Overview'!$H$2:$H$1850,C$4) -> -1510 | D48: =SUMIFS('Transaction Overview'!$D$2:$D$1850,'Transaction Overview'!$I$2:$I$1850,$A48,'Transaction Overview'!$H$2:$H$1850,D$4) -> -1510 | E48: =SUMIFS('Transaction Overview'!$D$2:$D$1850,'Transaction Overview'!$I$2:$I$1850,$A48,'Transaction Overview'!$H$2:$H$1850,E$4) -> -1823.99 | F48: =SUMIFS('Transaction Overview'!$D$2:$D$1850,'Transaction Overview'!$I$2:$I$1850,$A48,'Transaction Overview'!$H$2:$H$1850,F$4) -> -1510 | G48: =SUMIFS('Transaction Overview'!$D$2:$D$1850,'Transaction Overview'!$I$2:$I$1850,$A48,'Transaction Overview'!$H$2:$H$1850,G$4) -> -1510 | H48: =SUMIFS('Transaction Overview'!$D$2:$D$1850,'Transaction Overview'!$I$2:$I$1850,$A48,'Transaction Overview'!$H$2:$H$1850,H$4) -> -2265 | I48: =SUMIFS('Transaction Overview'!$D$2:$D$1850,'Transaction Overview'!$I$2:$I$1850,$A48,'Transaction Overview'!$H$2:$H$1850,I$4) -> -1510 | ... M48: =SUMIFS('Transaction Overview'!$D$2:$D$1850,'Transaction Overview'!$I$2:$I$1850,$A48,'Transaction Overview'!$H$2:$H$1850,M$4) -> -3770 | N48: =SUM(B48:M48) -> -21448.99
A49: Ashley Sarshar - Payroll | B49: =SUMIFS('Transaction Overview'!$D$2:$D$1850,'Transaction Overview'!$I$2:$I$1850,$A49,'Transaction Overview'!$H$2:$H$1850,B$4) -> 0 | C49: =SUMIFS('Transaction Overview'!$D$2:$D$1850,'Transaction Overview'!$I$2:$I$1850,$A49,'Transaction Overview'!$H$2:$H$1850,C$4) -> 0 | D49: =SUMIFS('Transaction Overview'!$D$2:$D$1850,'Transaction Overview'!$I$2:$I$1850,$A49,'Transaction Overview'!$H$2:$H$1850,D$4) -> 0 | E49: =SUMIFS('Transaction Overview'!$D$2:$D$1850,'Transaction Overview'!$I$2:$I$1850,$A49,'Transaction Overview'!$H$2:$H$1850,E$4) -> 0 | F49: =SUMIFS('Transaction Overview'!$D$2:$D$1850,'Transaction Overview'!$I$2:$I$1850,$A49,'Transaction Overview'!$H$2:$H$1850,F$4) -> 0 | G49: =SUMIFS('Transaction Overview'!$D$2:$D$1850,'Transaction Overview'!$I$2:$I$1850,$A49,'Transaction Overview'!$H$2:$H$1850,G$4) -> 0 | H49: =SUMIFS('Transaction Overview'!$D$2:$D$1850,'Transaction Overview'!$I$2:$I$1850,$A49,'Transaction Overview'!$H$2:$H$1850,H$4) -> 0 | I49: =SUMIFS('Transaction Overview'!$D$2:$D$1850,'Transaction Overview'!$I$2:$I$1850,$A49,'Transaction Overview'!$H$2:$H$1850,I$4) -> 0 | ... M49: =SUMIFS('Transaction Overview'!$D$2:$D$1850,'Transaction Overview'!$I$2:$I$1850,$A49,'Transaction Overview'!$H$2:$H$1850,M$4) -> -4000 | N49: =SUM(B49:M49) -> -4000
A50: DWG HR | B50: =SUMIFS('Transaction Overview'!$D$2:$D$1850,'Transaction Overview'!$I$2:$I$1850,$A50,'Transaction Overview'!$H$2:$H$1850,B$4) -> -1629.99 | C50: =SUMIFS('Transaction Overview'!$D$2:$D$1850,'Transaction Overview'!$I$2:$I$1850,$A50,'Transaction Overview'!$H$2:$H$1850,C$4) -> -1109.99 | D50: =SUMIFS('Transaction Overview'!$D$2:$D$1850,'Transaction Overview'!$I$2:$I$1850,$A50,'Transaction Overview'!$H$2:$H$1850,D$4) -> -1070 | E50: =SUMIFS('Transaction Overview'!$D$2:$D$1850,'Transaction Overview'!$I$2:$I$1850,$A50,'Transaction Overview'!$H$2:$H$1850,E$4) -> -1009.99 | F50: =SUMIFS('Transaction Overview'!$D$2:$D$1850,'Transaction Overview'!$I$2:$I$1850,$A50,'Transaction Overview'!$H$2:$H$1850,F$4) -> -2420.82 | G50: =SUMIFS('Transaction Overview'!$D$2:$D$1850,'Transaction Overview'!$I$2:$I$1850,$A50,'Transaction Overview'!$H$2:$H$1850,G$4) -> -5001.34 | H50: =SUMIFS('Transaction Overview'!$D$2:$D$1850,'Transaction Overview'!$I$2:$I$1850,$A50,'Transaction Overview'!$H$2:$H$1850,H$4) -> -3155.25 | I50: =SUMIFS('Transaction Overview'!$D$2:$D$1850,'Transaction Overview'!$I$2:$I$1850,$A50,'Transaction Overview'!$H$2:$H$1850,I$4) -> -896.18 | ... M50: =SUMIFS('Transaction Overview'!$D$2:$D$1850,'Transaction Overview'!$I$2:$I$1850,$A50,'Transaction Overview'!$H$2:$H$1850,M$4) -> -1405.28 | N50: =SUM(B50:M50) -> -20790.27
A51: Max Rodriguez - Payroll | B51: =SUMIFS('Transaction Overview'!$D$2:$D$1850,'Transaction Overview'!$I$2:$I$1850,$A51,'Transaction Overview'!$H$2:$H$1850,B$4) -> 0 | C51: =SUMIFS('Transaction Overview'!$D$2:$D$1850,'Transaction Overview'!$I$2:$I$1850,$A51,'Transaction Overview'!$H$2:$H$1850,C$4) -> 0 | D51: =SUMIFS('Transaction Overview'!$D$2:$D$1850,'Transaction Overview'!$I$2:$I$1850,$A51,'Transaction Overview'!$H$2:$H$1850,D$4) -> 0 | E51: =SUMIFS('Transaction Overview'!$D$2:$D$1850,'Transaction Overview'!$I$2:$I$1850,$A51,'Transaction Overview'!$H$2:$H$1850,E$4) -> -5000 | F51: =SUMIFS('Transaction Overview'!$D$2:$D$1850,'Transaction Overview'!$I$2:$I$1850,$A51,'Transaction Overview'!$H$2:$H$1850,F$4) -> 0 | G51: =SUMIFS('Transaction Overview'!$D$2:$D$1850,'Transaction Overview'!$I$2:$I$1850,$A51,'Transaction Overview'!$H$2:$H$1850,G$4) -> -10000 | H51: =SUMIFS('Transaction Overview'!$D$2:$D$1850,'Transaction Overview'!$I$2:$I$1850,$A51,'Transaction Overview'!$H$2:$H$1850,H$4) -> 0 | I51: =SUMIFS('Transaction Overview'!$D$2:$D$1850,'Transaction Overview'!$I$2:$I$1850,$A51,'Transaction Overview'!$H$2:$H$1850,I$4) -> 0 | ... M51: =SUMIFS('Transaction Overview'!$D$2:$D$1850,'Transaction Overview'!$I$2:$I$1850,$A51,'Transaction Overview'!$H$2:$H$1850,M$4) -> 0 | N51: =SUM(B51:M51) -> -15000
A52: Mike Paytonjian - Payroll | B52: =SUMIFS('Transaction Overview'!$D$2:$D$1850,'Transaction Overview'!$I$2:$I$1850,$A52,'Transaction Overview'!$H$2:$H$1850,B$4) -> 0 | C52: =SUMIFS('Transaction Overview'!$D$2:$D$1850,'Transaction Overview'!$I$2:$I$1850,$A52,'Transaction Overview'!$H$2:$H$1850,C$4) -> 0 | D52: =SUMIFS('Transaction Overview'!$D$2:$D$1850,'Transaction Overview'!$I$2:$I$1850,$A52,'Transaction Overview'!$H$2:$H$1850,D$4) -> 0 | E52: =SUMIFS('Transaction Overview'!$D$2:$D$1850,'Transaction Overview'!$I$2:$I$1850,$A52,'Transaction Overview'!$H$2:$H$1850,E$4) -> 0 | F52: =SUMIFS('Transaction Overview'!$D$2:$D$1850,'Transaction Overview'!$I$2:$I$1850,$A52,'Transaction Overview'!$H$2:$H$1850,F$4) -> 0 | G52: =SUMIFS('Transaction Overview'!$D$2:$D$1850,'Transaction Overview'!$I$2:$I$1850,$A52,'Transaction Overview'!$H$2:$H$1850,G$4) -> 0 | H52: =SUMIFS('Transaction Overview'!$D$2:$D$1850,'Transaction Overview'!$I$2:$I$1850,$A52,'Transaction Overview'!$H$2:$H$1850,H$4) -> -10000 | I52: =SUMIFS('Transaction Overview'!$D$2:$D$1850,'Transaction Overview'!$I$2:$I$1850,$A52,'Transaction Overview'!$H$2:$H$1850,I$4) -> -7500 | ... M52: =SUMIFS('Transaction Overview'!$D$2:$D$1850,'Transaction Overview'!$I$2:$I$1850,$A52,'Transaction Overview'!$H$2:$H$1850,M$4) -> -7750 | N52: =SUM(B52:M52) -> -43250
A53: Online Payroll Payment Reversed | B53: =SUMIFS('Transaction Overview'!$D$2:$D$1850,'Transaction Overview'!$I$2:$I$1850,$A53,'Transaction Overview'!$H$2:$H$1850,B$4) -> 0 | C53: =SUMIFS('Transaction Overview'!$D$2:$D$1850,'Transaction Overview'!$I$2:$I$1850,$A53,'Transaction Overview'!$H$2:$H$1850,C$4) -> 0 | D53: =SUMIFS('Transaction Overview'!$D$2:$D$1850,'Transaction Overview'!$I$2:$I$1850,$A53,'Transaction Overview'!$H$2:$H$1850,D$4) -> 0 | E53: =SUMIFS('Transaction Overview'!$D$2:$D$1850,'Transaction Overview'!$I$2:$I$1850,$A53,'Transaction Overview'!$H$2:$H$1850,E$4) -> 0 | F53: =SUMIFS('Transaction Overview'!$D$2:$D$1850,'Transaction Overview'!$I$2:$I$1850,$A53,'Transaction Overview'!$H$2:$H$1850,F$4) -> 0 | G53: =SUMIFS('Transaction Overview'!$D$2:$D$1850,'Transaction Overview'!$I$2:$I$1850,$A53,'Transaction Overview'!$H$2:$H$1850,G$4) -> 0 | H53: =SUMIFS('Transaction Overview'!$D$2:$D$1850,'Transaction Overview'!$I$2:$I$1850,$A53,'Transaction Overview'!$H$2:$H$1850,H$4) -> 0 | I53: =SUMIFS('Transaction Overview'!$D$2:$D$1850,'Transaction Overview'!$I$2:$I$1850,$A53,'Transaction Overview'!$H$2:$H$1850,I$4) -> 0 | ... M53: =SUMIFS('Transaction Overview'!$D$2:$D$1850,'Transaction Overview'!$I$2:$I$1850,$A53,'Transaction Overview'!$H$2:$H$1850,M$4) -> 0 | N53: =SUM(B53:M53) -> 0
A54: Rami Frankl - Payroll | B54: =SUMIFS('Transaction Overview'!$D$2:$D$1850,'Transaction Overview'!$I$2:$I$1850,$A54,'Transaction Overview'!$H$2:$H$1850,B$4) -> 0 | C54: =SUMIFS('Transaction Overview'!$D$2:$D$1850,'Transaction Overview'!$I$2:$I$1850,$A54,'Transaction Overview'!$H$2:$H$1850,C$4) -> 0 | D54: =SUMIFS('Transaction Overview'!$D$2:$D$1850,'Transaction Overview'!$I$2:$I$1850,$A54,'Transaction Overview'!$H$2:$H$1850,D$4) -> 0 | E54: =SUMIFS('Transaction Overview'!$D$2:$D$1850,'Transaction Overview'!$I$2:$I$1850,$A54,'Transaction Overview'!$H$2:$H$1850,E$4) -> 0 | F54: =SUMIFS('Transaction Overview'!$D$2:$D$1850,'Transaction Overview'!$I$2:$I$1850,$A54,'Transaction Overview'!$H$2:$H$1850,F$4) -> 0 | G54: =SUMIFS('Transaction Overview'!$D$2:$D$1850,'Transaction Overview'!$I$2:$I$1850,$A54,'Transaction Overview'!$H$2:$H$1850,G$4) -> 0 | H54: =SUMIFS('Transaction Overview'!$D$2:$D$1850,'Transaction Overview'!$I$2:$I$1850,$A54,'Transaction Overview'!$H$2:$H$1850,H$4) -> 0 | I54: =SUMIFS('Transaction Overview'!$D$2:$D$1850,'Transaction Overview'!$I$2:$I$1850,$A54,'Transaction Overview'!$H$2:$H$1850,I$4) -> 0 | ... M54: =SUMIFS('Transaction Overview'!$D$2:$D$1850,'Transaction Overview'!$I$2:$I$1850,$A54,'Transaction Overview'!$H$2:$H$1850,M$4) -> 0 | N54: =SUM(B54:M54) -> -1250
A55: Ruth Alcancia - Forward Bridge Payment | B55: =SUMIFS('Transaction Overview'!$D$2:$D$1850,'Transaction Overview'!$I$2:$I$1850,$A55,'Transaction Overview'!$H$2:$H$1850,B$4) -> -600 | C55: =SUMIFS('Transaction Overview'!$D$2:$D$1850,'Transaction Overview'!$I$2:$I$1850,$A55,'Transaction Overview'!$H$2:$H$1850,C$4) -> -180 | D55: =SUMIFS('Transaction Overview'!$D$2:$D$1850,'Transaction Overview'!$I$2:$I$1850,$A55,'Transaction Overview'!$H$2:$H$1850,D$4) -> -200 | E55: =SUMIFS('Transaction Overview'!$D$2:$D$1850,'Transaction Overview'!$I$2:$I$1850,$A55,'Transaction Overview'!$H$2:$H$1850,E$4) -> -300 | F55: =SUMIFS('Transaction Overview'!$D$2:$D$1850,'Transaction Overview'!$I$2:$I$1850,$A55,'Transaction Overview'!$H$2:$H$1850,F$4) -> -200 | G55: =SUMIFS('Transaction Overview'!$D$2:$D$1850,'Transaction Overview'!$I$2:$I$1850,$A55,'Transaction Overview'!$H$2:$H$1850,G$4) -> -300 | H55: =SUMIFS('Transaction Overview'!$D$2:$D$1850,'Transaction Overview'!$I$2:$I$1850,$A55,'Transaction Overview'!$H$2:$H$1850,H$4) -> -200 | I55: =SUMIFS('Transaction Overview'!$D$2:$D$1850,'Transaction Overview'!$I$2:$I$1850,$A55,'Transaction Overview'!$H$2:$H$1850,I$4) -> -300 | ... M55: =SUMIFS('Transaction Overview'!$D$2:$D$1850,'Transaction Overview'!$I$2:$I$1850,$A55,'Transaction Overview'!$H$2:$H$1850,M$4) -> -700 | N55: =SUM(B55:M55) -> -4140
A56: Ryan Billings - Payroll | B56: =SUMIFS('Transaction Overview'!$D$2:$D$1850,'Transaction Overview'!$I$2:$I$1850,$A56,'Transaction Overview'!$H$2:$H$1850,B$4) -> -6000 | C56: =SUMIFS('Transaction Overview'!$D$2:$D$1850,'Transaction Overview'!$I$2:$I$1850,$A56,'Transaction Overview'!$H$2:$H$1850,C$4) -> -22800 | D56: =SUMIFS('Transaction Overview'!$D$2:$D$1850,'Transaction Overview'!$I$2:$I$1850,$A56,'Transaction Overview'!$H$2:$H$1850,D$4) -> 0 | E56: =SUMIFS('Transaction Overview'!$D$2:$D$1850,'Transaction Overview'!$I$2:$I$1850,$A56,'Transaction Overview'!$H$2:$H$1850,E$4) -> 0 | F56: =SUMIFS('Transaction Overview'!$D$2:$D$1850,'Transaction Overview'!$I$2:$I$1850,$A56,'Transaction Overview'!$H$2:$H$1850,F$4) -> 0 | G56: =SUMIFS('Transaction Overview'!$D$2:$D$1850,'Transaction Overview'!$I$2:$I$1850,$A56,'Transaction Overview'!$H$2:$H$1850,G$4) -> 0 | H56: =SUMIFS('Transaction Overview'!$D$2:$D$1850,'Transaction Overview'!$I$2:$I$1850,$A56,'Transaction Overview'!$H$2:$H$1850,H$4) -> 0 | I56: =SUMIFS('Transaction Overview'!$D$2:$D$1850,'Transaction Overview'!$I$2:$I$1850,$A56,'Transaction Overview'!$H$2:$H$1850,I$4) -> 0 | ... M56: =SUMIFS('Transaction Overview'!$D$2:$D$1850,'Transaction Overview'!$I$2:$I$1850,$A56,'Transaction Overview'!$H$2:$H$1850,M$4) -> 0 | N56: =SUM(B56:M56) -> -28800
A57: Suad - Payroll | B57: =SUMIFS('Transaction Overview'!$D$2:$D$1850,'Transaction Overview'!$I$2:$I$1850,$A57,'Transaction Overview'!$H$2:$H$1850,B$4) -> -2555 | C57: =SUMIFS('Transaction Overview'!$D$2:$D$1850,'Transaction Overview'!$I$2:$I$1850,$A57,'Transaction Overview'!$H$2:$H$1850,C$4) -> 0 | D57: =SUMIFS('Transaction Overview'!$D$2:$D$1850,'Transaction Overview'!$I$2:$I$1850,$A57,'Transaction Overview'!$H$2:$H$1850,D$4) -> 0 | E57: =SUMIFS('Transaction Overview'!$D$2:$D$1850,'Transaction Overview'!$I$2:$I$1850,$A57,'Transaction Overview'!$H$2:$H$1850,E$4) -> 0 | F57: =SUMIFS('Transaction Overview'!$D$2:$D$1850,'Transaction Overview'!$I$2:$I$1850,$A57,'Transaction Overview'!$H$2:$H$1850,F$4) -> 0 | G57: =SUMIFS('Transaction Overview'!$D$2:$D$1850,'Transaction Overview'!$I$2:$I$1850,$A57,'Transaction Overview'!$H$2:$H$1850,G$4) -> 0 | H57: =SUMIFS('Transaction Overview'!$D$2:$D$1850,'Transaction Overview'!$I$2:$I$1850,$A57,'Transaction Overview'!$H$2:$H$1850,H$4) -> 0 | I57: =SUMIFS('Transaction Overview'!$D$2:$D$1850,'Transaction Overview'!$I$2:$I$1850,$A57,'Transaction Overview'!$H$2:$H$1850,I$4) -> 0 | ... M57: =SUMIFS('Transaction Overview'!$D$2:$D$1850,'Transaction Overview'!$I$2:$I$1850,$A57,'Transaction Overview'!$H$2:$H$1850,M$4) -> 0 | N57: =SUM(B57:M57) -> -2555
A58: Upwork - Sergei M. | B58: =SUMIFS('Transaction Overview'!$D$2:$D$1850,'Transaction Overview'!$I$2:$I$1850,$A58,'Transaction Overview'!$H$2:$H$1850,B$4) -> -761.25 | C58: =SUMIFS('Transaction Overview'!$D$2:$D$1850,'Transaction Overview'!$I$2:$I$1850,$A58,'Transaction Overview'!$H$2:$H$1850,C$4) -> -1863.75 | D58: =SUMIFS('Transaction Overview'!$D$2:$D$1850,'Transaction Overview'!$I$2:$I$1850,$A58,'Transaction Overview'!$H$2:$H$1850,D$4) -> -2826.25 | E58: =SUMIFS('Transaction Overview'!$D$2:$D$1850,'Transaction Overview'!$I$2:$I$1850,$A58,'Transaction Overview'!$H$2:$H$1850,E$4) -> -271.25 | F58: =SUMIFS('Transaction Overview'!$D$2:$D$1850,'Transaction Overview'!$I$2:$I$1850,$A58,'Transaction Overview'!$H$2:$H$1850,F$4) -> -1496.25 | G58: =SUMIFS('Transaction Overview'!$D$2:$D$1850,'Transaction Overview'!$I$2:$I$1850,$A58,'Transaction Overview'!$H$2:$H$1850,G$4) -> -1093.75 | H58: =SUMIFS('Transaction Overview'!$D$2:$D$1850,'Transaction Overview'!$I$2:$I$1850,$A58,'Transaction Overview'!$H$2:$H$1850,H$4) -> -3893.75 | I58: =SUMIFS('Transaction Overview'!$D$2:$D$1850,'Transaction Overview'!$I$2:$I$1850,$A58,'Transaction Overview'!$H$2:$H$1850,I$4) -> -2143.75 | ... M58: =SUMIFS('Transaction Overview'!$D$2:$D$1850,'Transaction Overview'!$I$2:$I$1850,$A58,'Transaction Overview'!$H$2:$H$1850,M$4) -> -2038.75 | N58: =SUM(B58:M58) -> -18667.49
A59: P2P Payments (Zelle/Venmo/PayPal)
A60: PayPal | B60: =SUMIFS('Transaction Overview'!$D$2:$D$1850,'Transaction Overview'!$I$2:$I$1850,$A60,'Transaction Overview'!$H$2:$H$1850,B$4) -> -227.49 | C60: =SUMIFS('Transaction Overview'!$D$2:$D$1850,'Transaction Overview'!$I$2:$I$1850,$A60,'Transaction Overview'!$H$2:$H$1850,C$4) -> 0 | D60: =SUMIFS('Transaction Overview'!$D$2:$D$1850,'Transaction Overview'!$I$2:$I$1850,$A60,'Transaction Overview'!$H$2:$H$1850,D$4) -> 0 | E60: =SUMIFS('Transaction Overview'!$D$2:$D$1850,'Transaction Overview'!$I$2:$I$1850,$A60,'Transaction Overview'!$H$2:$H$1850,E$4) -> -252.15 | F60: =SUMIFS('Transaction Overview'!$D$2:$D$1850,'Transaction Overview'!$I$2:$I$1850,$A60,'Transaction Overview'!$H$2:$H$1850,F$4) -> -13.99 | G60: =SUMIFS('Transaction Overview'!$D$2:$D$1850,'Transaction Overview'!$I$2:$I$1850,$A60,'Transaction Overview'!$H$2:$H$1850,G$4) -> -344.96 | H60: =SUMIFS('Transaction Overview'!$D$2:$D$1850,'Transaction Overview'!$I$2:$I$1850,$A60,'Transaction Overview'!$H$2:$H$1850,H$4) -> 0 | I60: =SUMIFS('Transaction Overview'!$D$2:$D$1850,'Transaction Overview'!$I$2:$I$1850,$A60,'Transaction Overview'!$H$2:$H$1850,I$4) -> 0 | ... M60: =SUMIFS('Transaction Overview'!$D$2:$D$1850,'Transaction Overview'!$I$2:$I$1850,$A60,'Transaction Overview'!$H$2:$H$1850,M$4) -> 0 | N60: =SUM(B60:M60) -> -2637.5
A61: Paypal | B61: =SUMIFS('Transaction Overview'!$D$2:$D$1850,'Transaction Overview'!$I$2:$I$1850,$A61,'Transaction Overview'!$H$2:$H$1850,B$4) -> -227.49 | C61: =SUMIFS('Transaction Overview'!$D$2:$D$1850,'Transaction Overview'!$I$2:$I$1850,$A61,'Transaction Overview'!$H$2:$H$1850,C$4) -> 0 | D61: =SUMIFS('Transaction Overview'!$D$2:$D$1850,'Transaction Overview'!$I$2:$I$1850,$A61,'Transaction Overview'!$H$2:$H$1850,D$4) -> 0 | E61: =SUMIFS('Transaction Overview'!$D$2:$D$1850,'Transaction Overview'!$I$2:$I$1850,$A61,'Transaction Overview'!$H$2:$H$1850,E$4) -> -252.15 | F61: =SUMIFS('Transaction Overview'!$D$2:$D$1850,'Transaction Overview'!$I$2:$I$1850,$A61,'Transaction Overview'!$H$2:$H$1850,F$4) -> -13.99 | G61: =SUMIFS('Transaction Overview'!$D$2:$D$1850,'Transaction Overview'!$I$2:$I$1850,$A61,'Transaction Overview'!$H$2:$H$1850,G$4) -> -344.96 | H61: =SUMIFS('Transaction Overview'!$D$2:$D$1850,'Transaction Overview'!$I$2:$I$1850,$A61,'Transaction Overview'!$H$2:$H$1850,H$4) -> 0 | I61: =SUMIFS('Transaction Overview'!$D$2:$D$1850,'Transaction Overview'!$I$2:$I$1850,$A61,'Transaction Overview'!$H$2:$H$1850,I$4) -> 0 | ... M61: =SUMIFS('Transaction Overview'!$D$2:$D$1850,'Transaction Overview'!$I$2:$I$1850,$A61,'Transaction Overview'!$H$2:$H$1850,M$4) -> 0 | N61: =SUM(B61:M61) -> -2637.5
A62: Venmo | B62: =SUMIFS('Transaction Overview'!$D$2:$D$1850,'Transaction Overview'!$I$2:$I$1850,$A62,'Transaction Overview'!$H$2:$H$1850,B$4) -> -3035 | C62: =SUMIFS('Transaction Overview'!$D$2:$D$1850,'Transaction Overview'!$I$2:$I$1850,$A62,'Transaction Overview'!$H$2:$H$1850,C$4) -> -2265 | D62: =SUMIFS('Transaction Overview'!$D$2:$D$1850,'Transaction Overview'!$I$2:$I$1850,$A62,'Transaction Overview'!$H$2:$H$1850,D$4) -> -1723.25 | E62: =SUMIFS('Transaction Overview'!$D$2:$D$1850,'Transaction Overview'!$I$2:$I$1850,$A62,'Transaction Overview'!$H$2:$H$1850,E$4) -> -2850 | F62: =SUMIFS('Transaction Overview'!$D$2:$D$1850,'Transaction Overview'!$I$2:$I$1850,$A62,'Transaction Overview'!$H$2:$H$1850,F$4) -> -9330 | G62: =SUMIFS('Transaction Overview'!$D$2:$D$1850,'Transaction Overview'!$I$2:$I$1850,$A62,'Transaction Overview'!$H$2:$H$1850,G$4) -> -7239 | H62: =SUMIFS('Transaction Overview'!$D$2:$D$1850,'Transaction Overview'!$I$2:$I$1850,$A62,'Transaction Overview'!$H$2:$H$1850,H$4) -> -5852 | I62: =SUMIFS('Transaction Overview'!$D$2:$D$1850,'Transaction Overview'!$I$2:$I$1850,$A62,'Transaction Overview'!$H$2:$H$1850,I$4) -> -7927 | ... M62: =SUMIFS('Transaction Overview'!$D$2:$D$1850,'Transaction Overview'!$I$2:$I$1850,$A62,'Transaction Overview'!$H$2:$H$1850,M$4) -> -4488 | N62: =SUM(B62:M62) -> -67344.81
A63: Zelle - Aaron Frankel | B63: =SUMIFS('Transaction Overview'!$D$2:$D$1850,'Transaction Overview'!$I$2:$I$1850,$A63,'Transaction Overview'!$H$2:$H$1850,B$4) -> -900 | C63: =SUMIFS('Transaction Overview'!$D$2:$D$1850,'Transaction Overview'!$I$2:$I$1850,$A63,'Transaction Overview'!$H$2:$H$1850,C$4) -> -1000 | D63: =SUMIFS('Transaction Overview'!$D$2:$D$1850,'Transaction Overview'!$I$2:$I$1850,$A63,'Transaction Overview'!$H$2:$H$1850,D$4) -> -800 | E63: =SUMIFS('Transaction Overview'!$D$2:$D$1850,'Transaction Overview'!$I$2:$I$1850,$A63,'Transaction Overview'!$H$2:$H$1850,E$4) -> 0 | F63: =SUMIFS('Transaction Overview'!$D$2:$D$1850,'Transaction Overview'!$I$2:$I$1850,$A63,'Transaction Overview'!$H$2:$H$1850,F$4) -> 0 | G63: =SUMIFS('Transaction Overview'!$D$2:$D$1850,'Transaction Overview'!$I$2:$I$1850,$A63,'Transaction Overview'!$H$2:$H$1850,G$4) -> -500 | H63: =SUMIFS('Transaction Overview'!$D$2:$D$1850,'Transaction Overview'!$I$2:$I$1850,$A63,'Transaction Overview'!$H$2:$H$1850,H$4) -> 0 | I63: =SUMIFS('Transaction Overview'!$D$2:$D$1850,'Transaction Overview'!$I$2:$I$1850,$A63,'Transaction Overview'!$H$2:$H$1850,I$4) -> -250 | ... M63: =SUMIFS('Transaction Overview'!$D$2:$D$1850,'Transaction Overview'!$I$2:$I$1850,$A63,'Transaction Overview'!$H$2:$H$1850,M$4) -> 0 | N63: =SUM(B63:M63) -> -3450
A64: Zelle - Adolfo V. | B64: =SUMIFS('Transaction Overview'!$D$2:$D$1850,'Transaction Overview'!$I$2:$I$1850,$A64,'Transaction Overview'!$H$2:$H$1850,B$4) -> -1700 | C64: =SUMIFS('Transaction Overview'!$D$2:$D$1850,'Transaction Overview'!$I$2:$I$1850,$A64,'Transaction Overview'!$H$2:$H$1850,C$4) -> 0 | D64: =SUMIFS('Transaction Overview'!$D$2:$D$1850,'Transaction Overview'!$I$2:$I$1850,$A64,'Transaction Overview'!$H$2:$H$1850,D$4) -> 0 | E64: =SUMIFS('Transaction Overview'!$D$2:$D$1850,'Transaction Overview'!$I$2:$I$1850,$A64,'Transaction Overview'!$H$2:$H$1850,E$4) -> 0 | F64: =SUMIFS('Transaction Overview'!$D$2:$D$1850,'Transaction Overview'!$I$2:$I$1850,$A64,'Transaction Overview'!$H$2:$H$1850,F$4) -> 0 | G64: =SUMIFS('Transaction Overview'!$D$2:$D$1850,'Transaction Overview'!$I$2:$I$1850,$A64,'Transaction Overview'!$H$2:$H$1850,G$4) -> 0 | H64: =SUMIFS('Transaction Overview'!$D$2:$D$1850,'Transaction Overview'!$I$2:$I$1850,$A64,'Transaction Overview'!$H$2:$H$1850,H$4) -> 0 | I64: =SUMIFS('Transaction Overview'!$D$2:$D$1850,'Transaction Overview'!$I$2:$I$1850,$A64,'Transaction Overview'!$H$2:$H$1850,I$4) -> 0 | ... M64: =SUMIFS('Transaction Overview'!$D$2:$D$1850,'Transaction Overview'!$I$2:$I$1850,$A64,'Transaction Overview'!$H$2:$H$1850,M$4) -> 0 | N64: =SUM(B64:M64) -> -1700
A65: Zelle - DWG Investor *** | B65: =SUMIFS('Transaction Overview'!$D$2:$D$1850,'Transaction Overview'!$I$2:$I$1850,$A65,'Transaction Overview'!$H$2:$H$1850,B$4) -> 0 | C65: =SUMIFS('Transaction Overview'!$D$2:$D$1850,'Transaction Overview'!$I$2:$I$1850,$A65,'Transaction Overview'!$H$2:$H$1850,C$4) -> 0 | D65: =SUMIFS('Transaction Overview'!$D$2:$D$1850,'Transaction Overview'!$I$2:$I$1850,$A65,'Transaction Overview'!$H$2:$H$1850,D$4) -> -1500 | E65: =SUMIFS('Transaction Overview'!$D$2:$D$1850,'Transaction Overview'!$I$2:$I$1850,$A65,'Transaction Overview'!$H$2:$H$1850,E$4) -> 0 | F65: =SUMIFS('Transaction Overview'!$D$2:$D$1850,'Transaction Overview'!$I$2:$I$1850,$A65,'Transaction Overview'!$H$2:$H$1850,F$4) -> 0 | G65: =SUMIFS('Transaction Overview'!$D$2:$D$1850,'Transaction Overview'!$I$2:$I$1850,$A65,'Transaction Overview'!$H$2:$H$1850,G$4) -> 0 | H65: =SUMIFS('Transaction Overview'!$D$2:$D$1850,'Transaction Overview'!$I$2:$I$1850,$A65,'Transaction Overview'!$H$2:$H$1850,H$4) -> 0 | I65: =SUMIFS('Transaction Overview'!$D$2:$D$1850,'Transaction Overview'!$I$2:$I$1850,$A65,'Transaction Overview'!$H$2:$H$1850,I$4) -> 0 | ... M65: =SUMIFS('Transaction Overview'!$D$2:$D$1850,'Transaction Overview'!$I$2:$I$1850,$A65,'Transaction Overview'!$H$2:$H$1850,M$4) -> 0 | N65: =SUM(B65:M65) -> -1500
A66: Zelle - Estella M. | B66: =SUMIFS('Transaction Overview'!$D$2:$D$1850,'Transaction Overview'!$I$2:$I$1850,$A66,'Transaction Overview'!$H$2:$H$1850,B$4) -> -800 | C66: =SUMIFS('Transaction Overview'!$D$2:$D$1850,'Transaction Overview'!$I$2:$I$1850,$A66,'Transaction Overview'!$H$2:$H$1850,C$4) -> -800 | D66: =SUMIFS('Transaction Overview'!$D$2:$D$1850,'Transaction Overview'!$I$2:$I$1850,$A66,'Transaction Overview'!$H$2:$H$1850,D$4) -> -800 | E66: =SUMIFS('Transaction Overview'!$D$2:$D$1850,'Transaction Overview'!$I$2:$I$1850,$A66,'Transaction Overview'!$H$2:$H$1850,E$4) -> 0 | F66: =SUMIFS('Transaction Overview'!$D$2:$D$1850,'Transaction Overview'!$I$2:$I$1850,$A66,'Transaction Overview'!$H$2:$H$1850,F$4) -> 0 | G66: =SUMIFS('Transaction Overview'!$D$2:$D$1850,'Transaction Overview'!$I$2:$I$1850,$A66,'Transaction Overview'!$H$2:$H$1850,G$4) -> -800 | H66: =SUMIFS('Transaction Overview'!$D$2:$D$1850,'Transaction Overview'!$I$2:$I$1850,$A66,'Transaction Overview'!$H$2:$H$1850,H$4) -> -800 | I66: =SUMIFS('Transaction Overview'!$D$2:$D$1850,'Transaction Overview'!$I$2:$I$1850,$A66,'Transaction Overview'!$H$2:$H$1850,I$4) -> -800 | ... M66: =SUMIFS('Transaction Overview'!$D$2:$D$1850,'Transaction Overview'!$I$2:$I$1850,$A66,'Transaction Overview'!$H$2:$H$1850,M$4) -> -500 | N66: =SUM(B66:M66) -> -7700
A67: Zelle - Francisco Bautista | B67: =SUMIFS('Transaction Overview'!$D$2:$D$1850,'Transaction Overview'!$I$2:$I$1850,$A67,'Transaction Overview'!$H$2:$H$1850,B$4) -> 0 | C67: =SUMIFS('Transaction Overview'!$D$2:$D$1850,'Transaction Overview'!$I$2:$I$1850,$A67,'Transaction Overview'!$H$2:$H$1850,C$4) -> -450 | D67: =SUMIFS('Transaction Overview'!$D$2:$D$1850,'Transaction Overview'!$I$2:$I$1850,$A67,'Transaction Overview'!$H$2:$H$1850,D$4) -> 0 | E67: =SUMIFS('Transaction Overview'!$D$2:$D$1850,'Transaction Overview'!$I$2:$I$1850,$A67,'Transaction Overview'!$H$2:$H$1850,E$4) -> 0 | F67: =SUMIFS('Transaction Overview'!$D$2:$D$1850,'Transaction Overview'!$I$2:$I$1850,$A67,'Transaction Overview'!$H$2:$H$1850,F$4) -> 0 | G67: =SUMIFS('Transaction Overview'!$D$2:$D$1850,'Transaction Overview'!$I$2:$I$1850,$A67,'Transaction Overview'!$H$2:$H$1850,G$4) -> 0 | H67: =SUMIFS('Transaction Overview'!$D$2:$D$1850,'Transaction Overview'!$I$2:$I$1850,$A67,'Transaction Overview'!$H$2:$H$1850,H$4) -> -200 | I67: =SUMIFS('Transaction Overview'!$D$2:$D$1850,'Transaction Overview'!$I$2:$I$1850,$A67,'Transaction Overview'!$H$2:$H$1850,I$4) -> 0 | ... M67: =SUMIFS('Transaction Overview'!$D$2:$D$1850,'Transaction Overview'!$I$2:$I$1850,$A67,'Transaction Overview'!$H$2:$H$1850,M$4) -> 0 | N67: =SUM(B67:M67) -> -1050
A68: Zelle - Jeff Fajardo | B68: =SUMIFS('Transaction Overview'!$D$2:$D$1850,'Transaction Overview'!$I$2:$I$1850,$A68,'Transaction Overview'!$H$2:$H$1850,B$4) -> -2400 | C68: =SUMIFS('Transaction Overview'!$D$2:$D$1850,'Transaction Overview'!$I$2:$I$1850,$A68,'Transaction Overview'!$H$2:$H$1850,C$4) -> -1500 | D68: =SUMIFS('Transaction Overview'!$D$2:$D$1850,'Transaction Overview'!$I$2:$I$1850,$A68,'Transaction Overview'!$H$2:$H$1850,D$4) -> -2300 | E68: =SUMIFS('Transaction Overview'!$D$2:$D$1850,'Transaction Overview'!$I$2:$I$1850,$A68,'Transaction Overview'!$H$2:$H$1850,E$4) -> -200 | F68: =SUMIFS('Transaction Overview'!$D$2:$D$1850,'Transaction Overview'!$I$2:$I$1850,$A68,'Transaction Overview'!$H$2:$H$1850,F$4) -> -13825 | G68: =SUMIFS('Transaction Overview'!$D$2:$D$1850,'Transaction Overview'!$I$2:$I$1850,$A68,'Transaction Overview'!$H$2:$H$1850,G$4) -> -1350 | H68: =SUMIFS('Transaction Overview'!$D$2:$D$1850,'Transaction Overview'!$I$2:$I$1850,$A68,'Transaction Overview'!$H$2:$H$1850,H$4) -> -4258 | I68: =SUMIFS('Transaction Overview'!$D$2:$D$1850,'Transaction Overview'!$I$2:$I$1850,$A68,'Transaction Overview'!$H$2:$H$1850,I$4) -> -2500 | ... M68: =SUMIFS('Transaction Overview'!$D$2:$D$1850,'Transaction Overview'!$I$2:$I$1850,$A68,'Transaction Overview'!$H$2:$H$1850,M$4) -> 0 | N68: =SUM(B68:M68) -> -41648
A69: Zelle - Jeff Seider | B69: =SUMIFS('Transaction Overview'!$D$2:$D$1850,'Transaction Overview'!$I$2:$I$1850,$A69,'Transaction Overview'!$H$2:$H$1850,B$4) -> -600 | C69: =SUMIFS('Transaction Overview'!$D$2:$D$1850,'Transaction Overview'!$I$2:$I$1850,$A69,'Transaction Overview'!$H$2:$H$1850,C$4) -> -1531.83 | D69: =SUMIFS('Transaction Overview'!$D$2:$D$1850,'Transaction Overview'!$I$2:$I$1850,$A69,'Transaction Overview'!$H$2:$H$1850,D$4) -> -1275 | E69: =SUMIFS('Transaction Overview'!$D$2:$D$1850,'Transaction Overview'!$I$2:$I$1850,$A69,'Transaction Overview'!$H$2:$H$1850,E$4) -> 0 | F69: =SUMIFS('Transaction Overview'!$D$2:$D$1850,'Transaction Overview'!$I$2:$I$1850,$A69,'Transaction Overview'!$H$2:$H$1850,F$4) -> 0 | G69: =SUMIFS('Transaction Overview'!$D$2:$D$1850,'Transaction Overview'!$I$2:$I$1850,$A69,'Transaction Overview'!$H$2:$H$1850,G$4) -> -875 | H69: =SUMIFS('Transaction Overview'!$D$2:$D$1850,'Transaction Overview'!$I$2:$I$1850,$A69,'Transaction Overview'!$H$2:$H$1850,H$4) -> -600 | I69: =SUMIFS('Transaction Overview'!$D$2:$D$1850,'Transaction Overview'!$I$2:$I$1850,$A69,'Transaction Overview'!$H$2:$H$1850,I$4) -> -1100 | ... M69: =SUMIFS('Transaction Overview'!$D$2:$D$1850,'Transaction Overview'!$I$2:$I$1850,$A69,'Transaction Overview'!$H$2:$H$1850,M$4) -> -1030 | N69: =SUM(B69:M69) -> -8711.83
A70: Zelle - Joe Saunders | B70: =SUMIFS('Transaction Overview'!$D$2:$D$1850,'Transaction Overview'!$I$2:$I$1850,$A70,'Transaction Overview'!$H$2:$H$1850,B$4) -> 0 | C70: =SUMIFS('Transaction Overview'!$D$2:$D$1850,'Transaction Overview'!$I$2:$I$1850,$A70,'Transaction Overview'!$H$2:$H$1850,C$4) -> 0 | D70: =SUMIFS('Transaction Overview'!$D$2:$D$1850,'Transaction Overview'!$I$2:$I$1850,$A70,'Transaction Overview'!$H$2:$H$1850,D$4) -> 0 | E70: =SUMIFS('Transaction Overview'!$D$2:$D$1850,'Transaction Overview'!$I$2:$I$1850,$A70,'Transaction Overview'!$H$2:$H$1850,E$4) -> 0 | F70: =SUMIFS('Transaction Overview'!$D$2:$D$1850,'Transaction Overview'!$I$2:$I$1850,$A70,'Transaction Overview'!$H$2:$H$1850,F$4) -> -500 | G70: =SUMIFS('Transaction Overview'!$D$2:$D$1850,'Transaction Overview'!$I$2:$I$1850,$A70,'Transaction Overview'!$H$2:$H$1850,G$4) -> 0 | H70: =SUMIFS('Transaction Overview'!$D$2:$D$1850,'Transaction Overview'!$I$2:$I$1850,$A70,'Transaction Overview'!$H$2:$H$1850,H$4) -> 0 | I70: =SUMIFS('Transaction Overview'!$D$2:$D$1850,'Transaction Overview'!$I$2:$I$1850,$A70,'Transaction Overview'!$H$2:$H$1850,I$4) -> 0 | ... M70: =SUMIFS('Transaction Overview'!$D$2:$D$1850,'Transaction Overview'!$I$2:$I$1850,$A70,'Transaction Overview'!$H$2:$H$1850,M$4) -> 0 | N70: =SUM(B70:M70) -> -500
A71: Zelle - Meg Maran | B71: =SUMIFS('Transaction Overview'!$D$2:$D$1850,'Transaction Overview'!$I$2:$I$1850,$A71,'Transaction Overview'!$H$2:$H$1850,B$4) -> 0 | C71: =SUMIFS('Transaction Overview'!$D$2:$D$1850,'Transaction Overview'!$I$2:$I$1850,$A71,'Transaction Overview'!$H$2:$H$1850,C$4) -> 0 | D71: =SUMIFS('Transaction Overview'!$D$2:$D$1850,'Transaction Overview'!$I$2:$I$1850,$A71,'Transaction Overview'!$H$2:$H$1850,D$4) -> -51.75 | E71: =SUMIFS('Transaction Overview'!$D$2:$D$1850,'Transaction Overview'!$I$2:$I$1850,$A71,'Transaction Overview'!$H$2:$H$1850,E$4) -> 0 | F71: =SUMIFS('Transaction Overview'!$D$2:$D$1850,'Transaction Overview'!$I$2:$I$1850,$A71,'Transaction Overview'!$H$2:$H$1850,F$4) -> 0 | G71: =SUMIFS('Transaction Overview'!$D$2:$D$1850,'Transaction Overview'!$I$2:$I$1850,$A71,'Transaction Overview'!$H$2:$H$1850,G$4) -> 0 | H71: =SUMIFS('Transaction Overview'!$D$2:$D$1850,'Transaction Overview'!$I$2:$I$1850,$A71,'Transaction Overview'!$H$2:$H$1850,H$4) -> 0 | I71: =SUMIFS('Transaction Overview'!$D$2:$D$1850,'Transaction Overview'!$I$2:$I$1850,$A71,'Transaction Overview'!$H$2:$H$1850,I$4) -> 0 | ... M71: =SUMIFS('Transaction Overview'!$D$2:$D$1850,'Transaction Overview'!$I$2:$I$1850,$A71,'Transaction Overview'!$H$2:$H$1850,M$4) -> 0 | N71: =SUM(B71:M71) -> -51.75
... A75: Zelle/P2P | B75: =SUMIFS('Transaction Overview'!$D$2:$D$1850,'Transaction Overview'!$I$2:$I$1850,$A75,'Transaction Overview'!$H$2:$H$1850,B$4) -> 0 | C75: =SUMIFS('Transaction Overview'!$D$2:$D$1850,'Transaction Overview'!$I$2:$I$1850,$A75,'Transaction Overview'!$H$2:$H$1850,C$4) -> 0 | D75: =SUMIFS('Transaction Overview'!$D$2:$D$1850,'Transaction Overview'!$I$2:$I$1850,$A75,'Transaction Overview'!$H$2:$H$1850,D$4) -> 0 | E75: =SUMIFS('Transaction Overview'!$D$2:$D$1850,'Transaction Overview'!$I$2:$I$1850,$A75,'Transaction Overview'!$H$2:$H$1850,E$4) -> 0 | F75: =SUMIFS('Transaction Overview'!$D$2:$D$1850,'Transaction Overview'!$I$2:$I$1850,$A75,'Transaction Overview'!$H$2:$H$1850,F$4) -> 0 | G75: =SUMIFS('Transaction Overview'!$D$2:$D$1850,'Transaction Overview'!$I$2:$I$1850,$A75,'Transaction Overview'!$H$2:$H$1850,G$4) -> 0 | H75: =SUMIFS('Transaction Overview'!$D$2:$D$1850,'Transaction Overview'!$I$2:$I$1850,$A75,'Transaction Overview'!$H$2:$H$1850,H$4) -> -1650 | I75: =SUMIFS('Transaction Overview'!$D$2:$D$1850,'Transaction Overview'!$I$2:$I$1850,$A75,'Transaction Overview'!$H$2:$H$1850,I$4) -> 0 | ... M75: =SUMIFS('Transaction Overview'!$D$2:$D$1850,'Transaction Overview'!$I$2:$I$1850,$A75,'Transaction Overview'!$H$2:$H$1850,M$4) -> 0 | N75: =SUM(B75:M75) -> -1810
A76: Owner / Family Distributions
A77: Transfer to Angela Dunning | B77: =SUMIFS('Transaction Overview'!$D$2:$D$1850,'Transaction Overview'!$I$2:$I$1850,$A77,'Transaction Overview'!$H$2:$H$1850,B$4) -> -18000 | C77: =SUMIFS('Transaction Overview'!$D$2:$D$1850,'Transaction Overview'!$I$2:$I$1850,$A77,'Transaction Overview'!$H$2:$H$1850,C$4) -> -20000 | D77: =SUMIFS('Transaction Overview'!$D$2:$D$1850,'Transaction Overview'!$I$2:$I$1850,$A77,'Transaction Overview'!$H$2:$H$1850,D$4) -> -43000 | E77: =SUMIFS('Transaction Overview'!$D$2:$D$1850,'Transaction Overview'!$I$2:$I$1850,$A77,'Transaction Overview'!$H$2:$H$1850,E$4) -> -14000 | F77: =SUMIFS('Transaction Overview'!$D$2:$D$1850,'Transaction Overview'!$I$2:$I$1850,$A77,'Transaction Overview'!$H$2:$H$1850,F$4) -> -10000 | G77: =SUMIFS('Transaction Overview'!$D$2:$D$1850,'Transaction Overview'!$I$2:$I$1850,$A77,'Transaction Overview'!$H$2:$H$1850,G$4) -> -25000 | H77: =SUMIFS('Transaction Overview'!$D$2:$D$1850,'Transaction Overview'!$I$2:$I$1850,$A77,'Transaction Overview'!$H$2:$H$1850,H$4) -> -29000 | I77: =SUMIFS('Transaction Overview'!$D$2:$D$1850,'Transaction Overview'!$I$2:$I$1850,$A77,'Transaction Overview'!$H$2:$H$1850,I$4) -> -22000 | ... M77: =SUMIFS('Transaction Overview'!$D$2:$D$1850,'Transaction Overview'!$I$2:$I$1850,$A77,'Transaction Overview'!$H$2:$H$1850,M$4) -> -31000 | N77: =SUM(B77:M77) -> -304000
A78: Transfer to Ava Perez-Dunning | B78: =SUMIFS('Transaction Overview'!$D$2:$D$1850,'Transaction Overview'!$I$2:$I$1850,$A78,'Transaction Overview'!$H$2:$H$1850,B$4) -> -2000 | C78: =SUMIFS('Transaction Overview'!$D$2:$D$1850,'Transaction Overview'!$I$2:$I$1850,$A78,'Transaction Overview'!$H$2:$H$1850,C$4) -> -300 | D78: =SUMIFS('Transaction Overview'!$D$2:$D$1850,'Transaction Overview'!$I$2:$I$1850,$A78,'Transaction Overview'!$H$2:$H$1850,D$4) -> -2500 | E78: =SUMIFS('Transaction Overview'!$D$2:$D$1850,'Transaction Overview'!$I$2:$I$1850,$A78,'Transaction Overview'!$H$2:$H$1850,E$4) -> -1000 | F78: =SUMIFS('Transaction Overview'!$D$2:$D$1850,'Transaction Overview'!$I$2:$I$1850,$A78,'Transaction Overview'!$H$2:$H$1850,F$4) -> -2000 | G78: =SUMIFS('Transaction Overview'!$D$2:$D$1850,'Transaction Overview'!$I$2:$I$1850,$A78,'Transaction Overview'!$H$2:$H$1850,G$4) -> -3550 | H78: =SUMIFS('Transaction Overview'!$D$2:$D$1850,'Transaction Overview'!$I$2:$I$1850,$A78,'Transaction Overview'!$H$2:$H$1850,H$4) -> -1000 | I78: =SUMIFS('Transaction Overview'!$D$2:$D$1850,'Transaction Overview'!$I$2:$I$1850,$A78,'Transaction Overview'!$H$2:$H$1850,I$4) -> -3000 | ... M78: =SUMIFS('Transaction Overview'!$D$2:$D$1850,'Transaction Overview'!$I$2:$I$1850,$A78,'Transaction Overview'!$H$2:$H$1850,M$4) -> -2300 | N78: =SUM(B78:M78) -> -19650
A79: Transfer to TX Personal Joint | B79: =SUMIFS('Transaction Overview'!$D$2:$D$1850,'Transaction Overview'!$I$2:$I$1850,$A79,'Transaction Overview'!$H$2:$H$1850,B$4) -> -10000 | C79: =SUMIFS('Transaction Overview'!$D$2:$D$1850,'Transaction Overview'!$I$2:$I$1850,$A79,'Transaction Overview'!$H$2:$H$1850,C$4) -> -6000 | D79: =SUMIFS('Transaction Overview'!$D$2:$D$1850,'Transaction Overview'!$I$2:$I$1850,$A79,'Transaction Overview'!$H$2:$H$1850,D$4) -> -8000 | E79: =SUMIFS('Transaction Overview'!$D$2:$D$1850,'Transaction Overview'!$I$2:$I$1850,$A79,'Transaction Overview'!$H$2:$H$1850,E$4) -> -8000 | F79: =SUMIFS('Transaction Overview'!$D$2:$D$1850,'Transaction Overview'!$I$2:$I$1850,$A79,'Transaction Overview'!$H$2:$H$1850,F$4) -> -8000 | G79: =SUMIFS('Transaction Overview'!$D$2:$D$1850,'Transaction Overview'!$I$2:$I$1850,$A79,'Transaction Overview'!$H$2:$H$1850,G$4) -> -32000 | H79: =SUMIFS('Transaction Overview'!$D$2:$D$1850,'Transaction Overview'!$I$2:$I$1850,$A79,'Transaction Overview'!$H$2:$H$1850,H$4) -> -15000 | I79: =SUMIFS('Transaction Overview'!$D$2:$D$1850,'Transaction Overview'!$I$2:$I$1850,$A79,'Transaction Overview'!$H$2:$H$1850,I$4) -> -10000 | ... M79: =SUMIFS('Transaction Overview'!$D$2:$D$1850,'Transaction Overview'!$I$2:$I$1850,$A79,'Transaction Overview'!$H$2:$H$1850,M$4) -> -10000 | N79: =SUM(B79:M79) -> -124000
A80: Credit Card & Loan Payments
A81: American Express Credit Card PMT | B81: =SUMIFS('Transaction Overview'!$D$2:$D$1850,'Transaction Overview'!$I$2:$I$1850,$A81,'Transaction Overview'!$H$2:$H$1850,B$4) -> -2465.25 | C81: =SUMIFS('Transaction Overview'!$D$2:$D$1850,'Transaction Overview'!$I$2:$I$1850,$A81,'Transaction Overview'!$H$2:$H$1850,C$4) -> -64630.22 | D81: =SUMIFS('Transaction Overview'!$D$2:$D$1850,'Transaction Overview'!$I$2:$I$1850,$A81,'Transaction Overview'!$H$2:$H$1850,D$4) -> 0 | E81: =SUMIFS('Transaction Overview'!$D$2:$D$1850,'Transaction Overview'!$I$2:$I$1850,$A81,'Transaction Overview'!$H$2:$H$1850,E$4) -> -918.66 | F81: =SUMIFS('Transaction Overview'!$D$2:$D$1850,'Transaction Overview'!$I$2:$I$1850,$A81,'Transaction Overview'!$H$2:$H$1850,F$4) -> 0 | G81: =SUMIFS('Transaction Overview'!$D$2:$D$1850,'Transaction Overview'!$I$2:$I$1850,$A81,'Transaction Overview'!$H$2:$H$1850,G$4) -> -63792.04 | H81: =SUMIFS('Transaction Overview'!$D$2:$D$1850,'Transaction Overview'!$I$2:$I$1850,$A81,'Transaction Overview'!$H$2:$H$1850,H$4) -> -1373.57 | I81: =SUMIFS('Transaction Overview'!$D$2:$D$1850,'Transaction Overview'!$I$2:$I$1850,$A81,'Transaction Overview'!$H$2:$H$1850,I$4) -> -299.14 | ... M81: =SUMIFS('Transaction Overview'!$D$2:$D$1850,'Transaction Overview'!$I$2:$I$1850,$A81,'Transaction Overview'!$H$2:$H$1850,M$4) -> -31152.9 | N81: =SUM(B81:M81) -> -165080.55
A82: SBA EIDL Loan | B82: =SUMIFS('Transaction Overview'!$D$2:$D$1850,'Transaction Overview'!$I$2:$I$1850,$A82,'Transaction Overview'!$H$2:$H$1850,B$4) -> -2524 | C82: =SUMIFS('Transaction Overview'!$D$2:$D$1850,'Transaction Overview'!$I$2:$I$1850,$A82,'Transaction Overview'!$H$2:$H$1850,C$4) -> -2524 | D82: =SUMIFS('Transaction Overview'!$D$2:$D$1850,'Transaction Overview'!$I$2:$I$1850,$A82,'Transaction Overview'!$H$2:$H$1850,D$4) -> -2524 | E82: =SUMIFS('Transaction Overview'!$D$2:$D$1850,'Transaction Overview'!$I$2:$I$1850,$A82,'Transaction Overview'!$H$2:$H$1850,E$4) -> -2524 | F82: =SUMIFS('Transaction Overview'!$D$2:$D$1850,'Transaction Overview'!$I$2:$I$1850,$A82,'Transaction Overview'!$H$2:$H$1850,F$4) -> 0 | G82: =SUMIFS('Transaction Overview'!$D$2:$D$1850,'Transaction Overview'!$I$2:$I$1850,$A82,'Transaction Overview'!$H$2:$H$1850,G$4) -> 0 | H82: =SUMIFS('Transaction Overview'!$D$2:$D$1850,'Transaction Overview'!$I$2:$I$1850,$A82,'Transaction Overview'!$H$2:$H$1850,H$4) -> 0 | I82: =SUMIFS('Transaction Overview'!$D$2:$D$1850,'Transaction Overview'!$I$2:$I$1850,$A82,'Transaction Overview'!$H$2:$H$1850,I$4) -> 0 | ... M82: =SUMIFS('Transaction Overview'!$D$2:$D$1850,'Transaction Overview'!$I$2:$I$1850,$A82,'Transaction Overview'!$H$2:$H$1850,M$4) -> 0 | N82: =SUM(B82:M82) -> -10096
A83: SBC EIDL Loan | B83: =SUMIFS('Transaction Overview'!$D$2:$D$1850,'Transaction Overview'!$I$2:$I$1850,$A83,'Transaction Overview'!$H$2:$H$1850,B$4) -> 0 | C83: =SUMIFS('Transaction Overview'!$D$2:$D$1850,'Transaction Overview'!$I$2:$I$1850,$A83,'Transaction Overview'!$H$2:$H$1850,C$4) -> 0 | D83: =SUMIFS('Transaction Overview'!$D$2:$D$1850,'Transaction Overview'!$I$2:$I$1850,$A83,'Transaction Overview'!$H$2:$H$1850,D$4) -> 0 | E83: =SUMIFS('Transaction Overview'!$D$2:$D$1850,'Transaction Overview'!$I$2:$I$1850,$A83,'Transaction Overview'!$H$2:$H$1850,E$4) -> 0 | F83: =SUMIFS('Transaction Overview'!$D$2:$D$1850,'Transaction Overview'!$I$2:$I$1850,$A83,'Transaction Overview'!$H$2:$H$1850,F$4) -> -2524 | G83: =SUMIFS('Transaction Overview'!$D$2:$D$1850,'Transaction Overview'!$I$2:$I$1850,$A83,'Transaction Overview'!$H$2:$H$1850,G$4) -> -2524 | H83: =SUMIFS('Transaction Overview'!$D$2:$D$1850,'Transaction Overview'!$I$2:$I$1850,$A83,'Transaction Overview'!$H$2:$H$1850,H$4) -> -2524 | I83: =SUMIFS('Transaction Overview'!$D$2:$D$1850,'Transaction Overview'!$I$2:$I$1850,$A83,'Transaction Overview'!$H$2:$H$1850,I$4) -> 0 | ... M83: =SUMIFS('Transaction Overview'!$D$2:$D$1850,'Transaction Overview'!$I$2:$I$1850,$A83,'Transaction Overview'!$H$2:$H$1850,M$4) -> -5048 | N83: =SUM(B83:M83) -> -20192
A84: Taxes
A85: Taxes | B85: =SUMIFS('Transaction Overview'!$D$2:$D$1850,'Transaction Overview'!$I$2:$I$1850,$A85,'Transaction Overview'!$H$2:$H$1850,B$4) -> -9307.5 | C85: =SUMIFS('Transaction Overview'!$D$2:$D$1850,'Transaction Overview'!$I$2:$I$1850,$A85,'Transaction Overview'!$H$2:$H$1850,C$4) -> 0 | D85: =SUMIFS('Transaction Overview'!$D$2:$D$1850,'Transaction Overview'!$I$2:$I$1850,$A85,'Transaction Overview'!$H$2:$H$1850,D$4) -> 0 | E85: =SUMIFS('Transaction Overview'!$D$2:$D$1850,'Transaction Overview'!$I$2:$I$1850,$A85,'Transaction Overview'!$H$2:$H$1850,E$4) -> 0 | F85: =SUMIFS('Transaction Overview'!$D$2:$D$1850,'Transaction Overview'!$I$2:$I$1850,$A85,'Transaction Overview'!$H$2:$H$1850,F$4) -> 0 | G85: =SUMIFS('Transaction Overview'!$D$2:$D$1850,'Transaction Overview'!$I$2:$I$1850,$A85,'Transaction Overview'!$H$2:$H$1850,G$4) -> 0 | H85: =SUMIFS('Transaction Overview'!$D$2:$D$1850,'Transaction Overview'!$I$2:$I$1850,$A85,'Transaction Overview'!$H$2:$H$1850,H$4) -> 0 | I85: =SUMIFS('Transaction Overview'!$D$2:$D$1850,'Transaction Overview'!$I$2:$I$1850,$A85,'Transaction Overview'!$H$2:$H$1850,I$4) -> 0 | ... M85: =SUMIFS('Transaction Overview'!$D$2:$D$1850,'Transaction Overview'!$I$2:$I$1850,$A85,'Transaction Overview'!$H$2:$H$1850,M$4) -> 0 | N85: =SUM(B85:M85) -> -9322.5
A86: DWG Operating
A87: AI Subscriptions | B87: =SUMIFS('Transaction Overview'!$D$2:$D$1850,'Transaction Overview'!$I$2:$I$1850,$A87,'Transaction Overview'!$H$2:$H$1850,B$4) -> 0 | C87: =SUMIFS('Transaction Overview'!$D$2:$D$1850,'Transaction Overview'!$I$2:$I$1850,$A87,'Transaction Overview'!$H$2:$H$1850,C$4) -> 0 | D87: =SUMIFS('Transaction Overview'!$D$2:$D$1850,'Transaction Overview'!$I$2:$I$1850,$A87,'Transaction Overview'!$H$2:$H$1850,D$4) -> 0 | E87: =SUMIFS('Transaction Overview'!$D$2:$D$1850,'Transaction Overview'!$I$2:$I$1850,$A87,'Transaction Overview'!$H$2:$H$1850,E$4) -> 0 | F87: =SUMIFS('Transaction Overview'!$D$2:$D$1850,'Transaction Overview'!$I$2:$I$1850,$A87,'Transaction Overview'!$H$2:$H$1850,F$4) -> 0 | G87: =SUMIFS('Transaction Overview'!$D$2:$D$1850,'Transaction Overview'!$I$2:$I$1850,$A87,'Transaction Overview'!$H$2:$H$1850,G$4) -> 0 | H87: =SUMIFS('Transaction Overview'!$D$2:$D$1850,'Transaction Overview'!$I$2:$I$1850,$A87,'Transaction Overview'!$H$2:$H$1850,H$4) -> -21.28 | I87: =SUMIFS('Transaction Overview'!$D$2:$D$1850,'Transaction Overview'!$I$2:$I$1850,$A87,'Transaction Overview'!$H$2:$H$1850,I$4) -> -21.28 | ... M87: =SUMIFS('Transaction Overview'!$D$2:$D$1850,'Transaction Overview'!$I$2:$I$1850,$A87,'Transaction Overview'!$H$2:$H$1850,M$4) -> -21.28 | N87: =SUM(B87:M87) -> -106.4
A88: Bank & Wire Fees | B88: =SUMIFS('Transaction Overview'!$D$2:$D$1850,'Transaction Overview'!$I$2:$I$1850,$A88,'Transaction Overview'!$H$2:$H$1850,B$4) -> -90.18 | C88: =SUMIFS('Transaction Overview'!$D$2:$D$1850,'Transaction Overview'!$I$2:$I$1850,$A88,'Transaction Overview'!$H$2:$H$1850,C$4) -> -234.95 | D88: =SUMIFS('Transaction Overview'!$D$2:$D$1850,'Transaction Overview'!$I$2:$I$1850,$A88,'Transaction Overview'!$H$2:$H$1850,D$4) -> 0 | E88: =SUMIFS('Transaction Overview'!$D$2:$D$1850,'Transaction Overview'!$I$2:$I$1850,$A88,'Transaction Overview'!$H$2:$H$1850,E$4) -> -67.5 | F88: =SUMIFS('Transaction Overview'!$D$2:$D$1850,'Transaction Overview'!$I$2:$I$1850,$A88,'Transaction Overview'!$H$2:$H$1850,F$4) -> -12.5 | G88: =SUMIFS('Transaction Overview'!$D$2:$D$1850,'Transaction Overview'!$I$2:$I$1850,$A88,'Transaction Overview'!$H$2:$H$1850,G$4) -> 0 | H88: =SUMIFS('Transaction Overview'!$D$2:$D$1850,'Transaction Overview'!$I$2:$I$1850,$A88,'Transaction Overview'!$H$2:$H$1850,H$4) -> 0 | I88: =SUMIFS('Transaction Overview'!$D$2:$D$1850,'Transaction Overview'!$I$2:$I$1850,$A88,'Transaction Overview'!$H$2:$H$1850,I$4) -> 0 | ... M88: =SUMIFS('Transaction Overview'!$D$2:$D$1850,'Transaction Overview'!$I$2:$I$1850,$A88,'Transaction Overview'!$H$2:$H$1850,M$4) -> 0 | N88: =SUM(B88:M88) -> -405.13
A89: Bank Fees | B89: =SUMIFS('Transaction Overview'!$D$2:$D$1850,'Transaction Overview'!$I$2:$I$1850,$A89,'Transaction Overview'!$H$2:$H$1850,B$4) -> 0 | C89: =SUMIFS('Transaction Overview'!$D$2:$D$1850,'Transaction Overview'!$I$2:$I$1850,$A89,'Transaction Overview'!$H$2:$H$1850,C$4) -> 0 | D89: =SUMIFS('Transaction Overview'!$D$2:$D$1850,'Transaction Overview'!$I$2:$I$1850,$A89,'Transaction Overview'!$H$2:$H$1850,D$4) -> -17.5 | E89: =SUMIFS('Transaction Overview'!$D$2:$D$1850,'Transaction Overview'!$I$2:$I$1850,$A89,'Transaction Overview'!$H$2:$H$1850,E$4) -> 0 | F89: =SUMIFS('Transaction Overview'!$D$2:$D$1850,'Transaction Overview'!$I$2:$I$1850,$A89,'Transaction Overview'!$H$2:$H$1850,F$4) -> 0 | G89: =SUMIFS('Transaction Overview'!$D$2:$D$1850,'Transaction Overview'!$I$2:$I$1850,$A89,'Transaction Overview'!$H$2:$H$1850,G$4) -> -15 | H89: =SUMIFS('Transaction Overview'!$D$2:$D$1850,'Transaction Overview'!$I$2:$I$1850,$A89,'Transaction Overview'!$H$2:$H$1850,H$4) -> -25.6 | I89: =SUMIFS('Transaction Overview'!$D$2:$D$1850,'Transaction Overview'!$I$2:$I$1850,$A89,'Transaction Overview'!$H$2:$H$1850,I$4) -> -51.5 | ... M89: =SUMIFS('Transaction Overview'!$D$2:$D$1850,'Transaction Overview'!$I$2:$I$1850,$A89,'Transaction Overview'!$H$2:$H$1850,M$4) -> -20 | N89: =SUM(B89:M89) -> -237.31
A90: Bill Payment | B90: =SUMIFS('Transaction Overview'!$D$2:$D$1850,'Transaction Overview'!$I$2:$I$1850,$A90,'Transaction Overview'!$H$2:$H$1850,B$4) -> 0 | C90: =SUMIFS('Transaction Overview'!$D$2:$D$1850,'Transaction Overview'!$I$2:$I$1850,$A90,'Transaction Overview'!$H$2:$H$1850,C$4) -> 0 | D90: =SUMIFS('Transaction Overview'!$D$2:$D$1850,'Transaction Overview'!$I$2:$I$1850,$A90,'Transaction Overview'!$H$2:$H$1850,D$4) -> 0 | E90: =SUMIFS('Transaction Overview'!$D$2:$D$1850,'Transaction Overview'!$I$2:$I$1850,$A90,'Transaction Overview'!$H$2:$H$1850,E$4) -> 0 | F90: =SUMIFS('Transaction Overview'!$D$2:$D$1850,'Transaction Overview'!$I$2:$I$1850,$A90,'Transaction Overview'!$H$2:$H$1850,F$4) -> 0 | G90: =SUMIFS('Transaction Overview'!$D$2:$D$1850,'Transaction Overview'!$I$2:$I$1850,$A90,'Transaction Overview'!$H$2:$H$1850,G$4) -> -1473.45 | H90: =SUMIFS('Transaction Overview'!$D$2:$D$1850,'Transaction Overview'!$I$2:$I$1850,$A90,'Transaction Overview'!$H$2:$H$1850,H$4) -> -1781 | I90: =SUMIFS('Transaction Overview'!$D$2:$D$1850,'Transaction Overview'!$I$2:$I$1850,$A90,'Transaction Overview'!$H$2:$H$1850,I$4) -> 0 | ... M90: =SUMIFS('Transaction Overview'!$D$2:$D$1850,'Transaction Overview'!$I$2:$I$1850,$A90,'Transaction Overview'!$H$2:$H$1850,M$4) -> 0 | N90: =SUM(B90:M90) -> -6784.57
A91: DWG Listing Platform | B91: =SUMIFS('Transaction Overview'!$D$2:$D$1850,'Transaction Overview'!$I$2:$I$1850,$A91,'Transaction Overview'!$H$2:$H$1850,B$4) -> 0 | C91: =SUMIFS('Transaction Overview'!$D$2:$D$1850,'Transaction Overview'!$I$2:$I$1850,$A91,'Transaction Overview'!$H$2:$H$1850,C$4) -> 0 | D91: =SUMIFS('Transaction Overview'!$D$2:$D$1850,'Transaction Overview'!$I$2:$I$1850,$A91,'Transaction Overview'!$H$2:$H$1850,D$4) -> 0 | E91: =SUMIFS('Transaction Overview'!$D$2:$D$1850,'Transaction Overview'!$I$2:$I$1850,$A91,'Transaction Overview'!$H$2:$H$1850,E$4) -> 0 | F91: =SUMIFS('Transaction Overview'!$D$2:$D$1850,'Transaction Overview'!$I$2:$I$1850,$A91,'Transaction Overview'!$H$2:$H$1850,F$4) -> 0 | G91: =SUMIFS('Transaction Overview'!$D$2:$D$1850,'Transaction Overview'!$I$2:$I$1850,$A91,'Transaction Overview'!$H$2:$H$1850,G$4) -> 0 | H91: =SUMIFS('Transaction Overview'!$D$2:$D$1850,'Transaction Overview'!$I$2:$I$1850,$A91,'Transaction Overview'!$H$2:$H$1850,H$4) -> 0 | I91: =SUMIFS('Transaction Overview'!$D$2:$D$1850,'Transaction Overview'!$I$2:$I$1850,$A91,'Transaction Overview'!$H$2:$H$1850,I$4) -> -1739.44 | ... M91: =SUMIFS('Transaction Overview'!$D$2:$D$1850,'Transaction Overview'!$I$2:$I$1850,$A91,'Transaction Overview'!$H$2:$H$1850,M$4) -> 0 | N91: =SUM(B91:M91) -> -1739.44
A92: DWG Listing Platform: RCM | B92: =SUMIFS('Transaction Overview'!$D$2:$D$1850,'Transaction Overview'!$I$2:$I$1850,$A92,'Transaction Overview'!$H$2:$H$1850,B$4) -> -2400 | C92: =SUMIFS('Transaction Overview'!$D$2:$D$1850,'Transaction Overview'!$I$2:$I$1850,$A92,'Transaction Overview'!$H$2:$H$1850,C$4) -> 0 | D92: =SUMIFS('Transaction Overview'!$D$2:$D$1850,'Transaction Overview'!$I$2:$I$1850,$A92,'Transaction Overview'!$H$2:$H$1850,D$4) -> 0 | E92: =SUMIFS('Transaction Overview'!$D$2:$D$1850,'Transaction Overview'!$I$2:$I$1850,$A92,'Transaction Overview'!$H$2:$H$1850,E$4) -> 0 | F92: =SUMIFS('Transaction Overview'!$D$2:$D$1850,'Transaction Overview'!$I$2:$I$1850,$A92,'Transaction Overview'!$H$2:$H$1850,F$4) -> 0 | G92: =SUMIFS('Transaction Overview'!$D$2:$D$1850,'Transaction Overview'!$I$2:$I$1850,$A92,'Transaction Overview'!$H$2:$H$1850,G$4) -> 0 | H92: =SUMIFS('Transaction Overview'!$D$2:$D$1850,'Transaction Overview'!$I$2:$I$1850,$A92,'Transaction Overview'!$H$2:$H$1850,H$4) -> 0 | I92: =SUMIFS('Transaction Overview'!$D$2:$D$1850,'Transaction Overview'!$I$2:$I$1850,$A92,'Transaction Overview'!$H$2:$H$1850,I$4) -> 0 | ... M92: =SUMIFS('Transaction Overview'!$D$2:$D$1850,'Transaction Overview'!$I$2:$I$1850,$A92,'Transaction Overview'!$H$2:$H$1850,M$4) -> 0 | N92: =SUM(B92:M92) -> -2400
A93: DWG Marketing | B93: =SUMIFS('Transaction Overview'!$D$2:$D$1850,'Transaction Overview'!$I$2:$I$1850,$A93,'Transaction Overview'!$H$2:$H$1850,B$4) -> -12.99 | C93: =SUMIFS('Transaction Overview'!$D$2:$D$1850,'Transaction Overview'!$I$2:$I$1850,$A93,'Transaction Overview'!$H$2:$H$1850,C$4) -> -12.99 | D93: =SUMIFS('Transaction Overview'!$D$2:$D$1850,'Transaction Overview'!$I$2:$I$1850,$A93,'Transaction Overview'!$H$2:$H$1850,D$4) -> -12.99 | E93: =SUMIFS('Transaction Overview'!$D$2:$D$1850,'Transaction Overview'!$I$2:$I$1850,$A93,'Transaction Overview'!$H$2:$H$1850,E$4) -> -12.99 | F93: =SUMIFS('Transaction Overview'!$D$2:$D$1850,'Transaction Overview'!$I$2:$I$1850,$A93,'Transaction Overview'!$H$2:$H$1850,F$4) -> 0 | G93: =SUMIFS('Transaction Overview'!$D$2:$D$1850,'Transaction Overview'!$I$2:$I$1850,$A93,'Transaction Overview'!$H$2:$H$1850,G$4) -> -117 | H93: =SUMIFS('Transaction Overview'!$D$2:$D$1850,'Transaction Overview'!$I$2:$I$1850,$A93,'Transaction Overview'!$H$2:$H$1850,H$4) -> -117 | I93: =SUMIFS('Transaction Overview'!$D$2:$D$1850,'Transaction Overview'!$I$2:$I$1850,$A93,'Transaction Overview'!$H$2:$H$1850,I$4) -> -117 | ... M93: =SUMIFS('Transaction Overview'!$D$2:$D$1850,'Transaction Overview'!$I$2:$I$1850,$A93,'Transaction Overview'!$H$2:$H$1850,M$4) -> -104.01 | N93: =SUM(B93:M93) -> -881.17
A94: DWG Subscription | B94: =SUMIFS('Transaction Overview'!$D$2:$D$1850,'Transaction Overview'!$I$2:$I$1850,$A94,'Transaction Overview'!$H$2:$H$1850,B$4) -> 0 | C94: =SUMIFS('Transaction Overview'!$D$2:$D$1850,'Transaction Overview'!$I$2:$I$1850,$A94,'Transaction Overview'!$H$2:$H$1850,C$4) -> 0 | D94: =SUMIFS('Transaction Overview'!$D$2:$D$1850,'Transaction Overview'!$I$2:$I$1850,$A94,'Transaction Overview'!$H$2:$H$1850,D$4) -> 0 | E94: =SUMIFS('Transaction Overview'!$D$2:$D$1850,'Transaction Overview'!$I$2:$I$1850,$A94,'Transaction Overview'!$H$2:$H$1850,E$4) -> 0 | F94: =SUMIFS('Transaction Overview'!$D$2:$D$1850,'Transaction Overview'!$I$2:$I$1850,$A94,'Transaction Overview'!$H$2:$H$1850,F$4) -> 0 | G94: =SUMIFS('Transaction Overview'!$D$2:$D$1850,'Transaction Overview'!$I$2:$I$1850,$A94,'Transaction Overview'!$H$2:$H$1850,G$4) -> -168 | H94: =SUMIFS('Transaction Overview'!$D$2:$D$1850,'Transaction Overview'!$I$2:$I$1850,$A94,'Transaction Overview'!$H$2:$H$1850,H$4) -> 0 | I94: =SUMIFS('Transaction Overview'!$D$2:$D$1850,'Transaction Overview'!$I$2:$I$1850,$A94,'Transaction Overview'!$H$2:$H$1850,I$4) -> 0 | ... M94: =SUMIFS('Transaction Overview'!$D$2:$D$1850,'Transaction Overview'!$I$2:$I$1850,$A94,'Transaction Overview'!$H$2:$H$1850,M$4) -> 0 | N94: =SUM(B94:M94) -> -168
A95: DWGCP Business Development | B95: =SUMIFS('Transaction Overview'!$D$2:$D$1850,'Transaction Overview'!$I$2:$I$1850,$A95,'Transaction Overview'!$H$2:$H$1850,B$4) -> -10.78 | C95: =SUMIFS('Transaction Overview'!$D$2:$D$1850,'Transaction Overview'!$I$2:$I$1850,$A95,'Transaction Overview'!$H$2:$H$1850,C$4) -> -10.78 | D95: =SUMIFS('Transaction Overview'!$D$2:$D$1850,'Transaction Overview'!$I$2:$I$1850,$A95,'Transaction Overview'!$H$2:$H$1850,D$4) -> -10.78 | E95: =SUMIFS('Transaction Overview'!$D$2:$D$1850,'Transaction Overview'!$I$2:$I$1850,$A95,'Transaction Overview'!$H$2:$H$1850,E$4) -> -10.78 | F95: =SUMIFS('Transaction Overview'!$D$2:$D$1850,'Transaction Overview'!$I$2:$I$1850,$A95,'Transaction Overview'!$H$2:$H$1850,F$4) -> -10.78 | G95: =SUMIFS('Transaction Overview'!$D$2:$D$1850,'Transaction Overview'!$I$2:$I$1850,$A95,'Transaction Overview'!$H$2:$H$1850,G$4) -> -10.78 | H95: =SUMIFS('Transaction Overview'!$D$2:$D$1850,'Transaction Overview'!$I$2:$I$1850,$A95,'Transaction Overview'!$H$2:$H$1850,H$4) -> -10.78 | I95: =SUMIFS('Transaction Overview'!$D$2:$D$1850,'Transaction Overview'!$I$2:$I$1850,$A95,'Transaction Overview'!$H$2:$H$1850,I$4) -> -10.78 | ... M95: =SUMIFS('Transaction Overview'!$D$2:$D$1850,'Transaction Overview'!$I$2:$I$1850,$A95,'Transaction Overview'!$H$2:$H$1850,M$4) -> -10.78 | N95: =SUM(B95:M95) -> -129.36
A96: Donation | B96: =SUMIFS('Transaction Overview'!$D$2:$D$1850,'Transaction Overview'!$I$2:$I$1850,$A96,'Transaction Overview'!$H$2:$H$1850,B$4) -> 0 | C96: =SUMIFS('Transaction Overview'!$D$2:$D$1850,'Transaction Overview'!$I$2:$I$1850,$A96,'Transaction Overview'!$H$2:$H$1850,C$4) -> 0 | D96: =SUMIFS('Transaction Overview'!$D$2:$D$1850,'Transaction Overview'!$I$2:$I$1850,$A96,'Transaction Overview'!$H$2:$H$1850,D$4) -> 0 | E96: =SUMIFS('Transaction Overview'!$D$2:$D$1850,'Transaction Overview'!$I$2:$I$1850,$A96,'Transaction Overview'!$H$2:$H$1850,E$4) -> 0 | F96: =SUMIFS('Transaction Overview'!$D$2:$D$1850,'Transaction Overview'!$I$2:$I$1850,$A96,'Transaction Overview'!$H$2:$H$1850,F$4) -> 0 | G96: =SUMIFS('Transaction Overview'!$D$2:$D$1850,'Transaction Overview'!$I$2:$I$1850,$A96,'Transaction Overview'!$H$2:$H$1850,G$4) -> 0 | H96: =SUMIFS('Transaction Overview'!$D$2:$D$1850,'Transaction Overview'!$I$2:$I$1850,$A96,'Transaction Overview'!$H$2:$H$1850,H$4) -> -103 | I96: =SUMIFS('Transaction Overview'!$D$2:$D$1850,'Transaction Overview'!$I$2:$I$1850,$A96,'Transaction Overview'!$H$2:$H$1850,I$4) -> 0 | ... M96: =SUMIFS('Transaction Overview'!$D$2:$D$1850,'Transaction Overview'!$I$2:$I$1850,$A96,'Transaction Overview'!$H$2:$H$1850,M$4) -> 0 | N96: =SUM(B96:M96) -> -103
A97: Go Daddy | B97: =SUMIFS('Transaction Overview'!$D$2:$D$1850,'Transaction Overview'!$I$2:$I$1850,$A97,'Transaction Overview'!$H$2:$H$1850,B$4) -> 0 | C97: =SUMIFS('Transaction Overview'!$D$2:$D$1850,'Transaction Overview'!$I$2:$I$1850,$A97,'Transaction Overview'!$H$2:$H$1850,C$4) -> 0 | D97: =SUMIFS('Transaction Overview'!$D$2:$D$1850,'Transaction Overview'!$I$2:$I$1850,$A97,'Transaction Overview'!$H$2:$H$1850,D$4) -> 0 | E97: =SUMIFS('Transaction Overview'!$D$2:$D$1850,'Transaction Overview'!$I$2:$I$1850,$A97,'Transaction Overview'!$H$2:$H$1850,E$4) -> -21.98 | F97: =SUMIFS('Transaction Overview'!$D$2:$D$1850,'Transaction Overview'!$I$2:$I$1850,$A97,'Transaction Overview'!$H$2:$H$1850,F$4) -> -21.98 | G97: =SUMIFS('Transaction Overview'!$D$2:$D$1850,'Transaction Overview'!$I$2:$I$1850,$A97,'Transaction Overview'!$H$2:$H$1850,G$4) -> -21.98 | H97: =SUMIFS('Transaction Overview'!$D$2:$D$1850,'Transaction Overview'!$I$2:$I$1850,$A97,'Transaction Overview'!$H$2:$H$1850,H$4) -> -127.14 | I97: =SUMIFS('Transaction Overview'!$D$2:$D$1850,'Transaction Overview'!$I$2:$I$1850,$A97,'Transaction Overview'!$H$2:$H$1850,I$4) -> -37.96 | ... M97: =SUMIFS('Transaction Overview'!$D$2:$D$1850,'Transaction Overview'!$I$2:$I$1850,$A97,'Transaction Overview'!$H$2:$H$1850,M$4) -> -100.3 | N97: =SUM(B97:M97) -> -445.22
A98: Office/Miscellaneous Reimbursement - Ashley S. | B98: =SUMIFS('Transaction Overview'!$D$2:$D$1850,'Transaction Overview'!$I$2:$I$1850,$A98,'Transaction Overview'!$H$2:$H$1850,B$4) -> 0 | C98: =SUMIFS('Transaction Overview'!$D$2:$D$1850,'Transaction Overview'!$I$2:$I$1850,$A98,'Transaction Overview'!$H$2:$H$1850,C$4) -> 0 | D98: =SUMIFS('Transaction Overview'!$D$2:$D$1850,'Transaction Overview'!$I$2:$I$1850,$A98,'Transaction Overview'!$H$2:$H$1850,D$4) -> 0 | E98: =SUMIFS('Transaction Overview'!$D$2:$D$1850,'Transaction Overview'!$I$2:$I$1850,$A98,'Transaction Overview'!$H$2:$H$1850,E$4) -> 0 | F98: =SUMIFS('Transaction Overview'!$D$2:$D$1850,'Transaction Overview'!$I$2:$I$1850,$A98,'Transaction Overview'!$H$2:$H$1850,F$4) -> 0 | G98: =SUMIFS('Transaction Overview'!$D$2:$D$1850,'Transaction Overview'!$I$2:$I$1850,$A98,'Transaction Overview'!$H$2:$H$1850,G$4) -> 0 | H98: =SUMIFS('Transaction Overview'!$D$2:$D$1850,'Transaction Overview'!$I$2:$I$1850,$A98,'Transaction Overview'!$H$2:$H$1850,H$4) -> 0 | I98: =SUMIFS('Transaction Overview'!$D$2:$D$1850,'Transaction Overview'!$I$2:$I$1850,$A98,'Transaction Overview'!$H$2:$H$1850,I$4) -> 0 | ... M98: =SUMIFS('Transaction Overview'!$D$2:$D$1850,'Transaction Overview'!$I$2:$I$1850,$A98,'Transaction Overview'!$H$2:$H$1850,M$4) -> -10 | N98: =SUM(B98:M98) -> -10
... A102: Wire Fee | B102: =SUMIFS('Transaction Overview'!$D$2:$D$1850,'Transaction Overview'!$I$2:$I$1850,$A102,'Transaction Overview'!$H$2:$H$1850,B$4) -> -120 | C102: =SUMIFS('Transaction Overview'!$D$2:$D$1850,'Transaction Overview'!$I$2:$I$1850,$A102,'Transaction Overview'!$H$2:$H$1850,C$4) -> -105 | D102: =SUMIFS('Transaction Overview'!$D$2:$D$1850,'Transaction Overview'!$I$2:$I$1850,$A102,'Transaction Overview'!$H$2:$H$1850,D$4) -> -40 | E102: =SUMIFS('Transaction Overview'!$D$2:$D$1850,'Transaction Overview'!$I$2:$I$1850,$A102,'Transaction Overview'!$H$2:$H$1850,E$4) -> -25 | F102: =SUMIFS('Transaction Overview'!$D$2:$D$1850,'Transaction Overview'!$I$2:$I$1850,$A102,'Transaction Overview'!$H$2:$H$1850,F$4) -> 0 | G102: =SUMIFS('Transaction Overview'!$D$2:$D$1850,'Transaction Overview'!$I$2:$I$1850,$A102,'Transaction Overview'!$H$2:$H$1850,G$4) -> -40 | H102: =SUMIFS('Transaction Overview'!$D$2:$D$1850,'Transaction Overview'!$I$2:$I$1850,$A102,'Transaction Overview'!$H$2:$H$1850,H$4) -> 0 | I102: =SUMIFS('Transaction Overview'!$D$2:$D$1850,'Transaction Overview'!$I$2:$I$1850,$A102,'Transaction Overview'!$H$2:$H$1850,I$4) -> -25 | ... M102: =SUMIFS('Transaction Overview'!$D$2:$D$1850,'Transaction Overview'!$I$2:$I$1850,$A102,'Transaction Overview'!$H$2:$H$1850,M$4) -> -90 | N102: =SUM(B102:M102) -> -600
A103: Business Travel
A104: 2024/2025 Canada Trip | B104: =SUMIFS('Transaction Overview'!$D$2:$D$1850,'Transaction Overview'!$I$2:$I$1850,$A104,'Transaction Overview'!$H$2:$H$1850,B$4) -> -89.54 | C104: =SUMIFS('Transaction Overview'!$D$2:$D$1850,'Transaction Overview'!$I$2:$I$1850,$A104,'Transaction Overview'!$H$2:$H$1850,C$4) -> 0 | D104: =SUMIFS('Transaction Overview'!$D$2:$D$1850,'Transaction Overview'!$I$2:$I$1850,$A104,'Transaction Overview'!$H$2:$H$1850,D$4) -> 0 | E104: =SUMIFS('Transaction Overview'!$D$2:$D$1850,'Transaction Overview'!$I$2:$I$1850,$A104,'Transaction Overview'!$H$2:$H$1850,E$4) -> 0 | F104: =SUMIFS('Transaction Overview'!$D$2:$D$1850,'Transaction Overview'!$I$2:$I$1850,$A104,'Transaction Overview'!$H$2:$H$1850,F$4) -> 0 | G104: =SUMIFS('Transaction Overview'!$D$2:$D$1850,'Transaction Overview'!$I$2:$I$1850,$A104,'Transaction Overview'!$H$2:$H$1850,G$4) -> 0 | H104: =SUMIFS('Transaction Overview'!$D$2:$D$1850,'Transaction Overview'!$I$2:$I$1850,$A104,'Transaction Overview'!$H$2:$H$1850,H$4) -> 0 | I104: =SUMIFS('Transaction Overview'!$D$2:$D$1850,'Transaction Overview'!$I$2:$I$1850,$A104,'Transaction Overview'!$H$2:$H$1850,I$4) -> 0 | ... M104: =SUMIFS('Transaction Overview'!$D$2:$D$1850,'Transaction Overview'!$I$2:$I$1850,$A104,'Transaction Overview'!$H$2:$H$1850,M$4) -> 0 | N104: =SUM(B104:M104) -> -89.54
A105: 2025 Costa Rica Trip | B105: =SUMIFS('Transaction Overview'!$D$2:$D$1850,'Transaction Overview'!$I$2:$I$1850,$A105,'Transaction Overview'!$H$2:$H$1850,B$4) -> 0 | C105: =SUMIFS('Transaction Overview'!$D$2:$D$1850,'Transaction Overview'!$I$2:$I$1850,$A105,'Transaction Overview'!$H$2:$H$1850,C$4) -> 0 | D105: =SUMIFS('Transaction Overview'!$D$2:$D$1850,'Transaction Overview'!$I$2:$I$1850,$A105,'Transaction Overview'!$H$2:$H$1850,D$4) -> 0 | E105: =SUMIFS('Transaction Overview'!$D$2:$D$1850,'Transaction Overview'!$I$2:$I$1850,$A105,'Transaction Overview'!$H$2:$H$1850,E$4) -> 0 | F105: =SUMIFS('Transaction Overview'!$D$2:$D$1850,'Transaction Overview'!$I$2:$I$1850,$A105,'Transaction Overview'!$H$2:$H$1850,F$4) -> 0 | G105: =SUMIFS('Transaction Overview'!$D$2:$D$1850,'Transaction Overview'!$I$2:$I$1850,$A105,'Transaction Overview'!$H$2:$H$1850,G$4) -> 0 | H105: =SUMIFS('Transaction Overview'!$D$2:$D$1850,'Transaction Overview'!$I$2:$I$1850,$A105,'Transaction Overview'!$H$2:$H$1850,H$4) -> 0 | I105: =SUMIFS('Transaction Overview'!$D$2:$D$1850,'Transaction Overview'!$I$2:$I$1850,$A105,'Transaction Overview'!$H$2:$H$1850,I$4) -> 0 | ... M105: =SUMIFS('Transaction Overview'!$D$2:$D$1850,'Transaction Overview'!$I$2:$I$1850,$A105,'Transaction Overview'!$H$2:$H$1850,M$4) -> 0 | N105: =SUM(B105:M105) -> -2030.81
A106: Miami Investor Event | B106: =SUMIFS('Transaction Overview'!$D$2:$D$1850,'Transaction Overview'!$I$2:$I$1850,$A106,'Transaction Overview'!$H$2:$H$1850,B$4) -> 0 | C106: =SUMIFS('Transaction Overview'!$D$2:$D$1850,'Transaction Overview'!$I$2:$I$1850,$A106,'Transaction Overview'!$H$2:$H$1850,C$4) -> 0 | D106: =SUMIFS('Transaction Overview'!$D$2:$D$1850,'Transaction Overview'!$I$2:$I$1850,$A106,'Transaction Overview'!$H$2:$H$1850,D$4) -> 0 | E106: =SUMIFS('Transaction Overview'!$D$2:$D$1850,'Transaction Overview'!$I$2:$I$1850,$A106,'Transaction Overview'!$H$2:$H$1850,E$4) -> 0 | F106: =SUMIFS('Transaction Overview'!$D$2:$D$1850,'Transaction Overview'!$I$2:$I$1850,$A106,'Transaction Overview'!$H$2:$H$1850,F$4) -> 0 | G106: =SUMIFS('Transaction Overview'!$D$2:$D$1850,'Transaction Overview'!$I$2:$I$1850,$A106,'Transaction Overview'!$H$2:$H$1850,G$4) -> 0 | H106: =SUMIFS('Transaction Overview'!$D$2:$D$1850,'Transaction Overview'!$I$2:$I$1850,$A106,'Transaction Overview'!$H$2:$H$1850,H$4) -> 0 | I106: =SUMIFS('Transaction Overview'!$D$2:$D$1850,'Transaction Overview'!$I$2:$I$1850,$A106,'Transaction Overview'!$H$2:$H$1850,I$4) -> -6.54 | ... M106: =SUMIFS('Transaction Overview'!$D$2:$D$1850,'Transaction Overview'!$I$2:$I$1850,$A106,'Transaction Overview'!$H$2:$H$1850,M$4) -> 0 | N106: =SUM(B106:M106) -> -6.54
A107: San Francisco Investor Meeting | B107: =SUMIFS('Transaction Overview'!$D$2:$D$1850,'Transaction Overview'!$I$2:$I$1850,$A107,'Transaction Overview'!$H$2:$H$1850,B$4) -> 0 | C107: =SUMIFS('Transaction Overview'!$D$2:$D$1850,'Transaction Overview'!$I$2:$I$1850,$A107,'Transaction Overview'!$H$2:$H$1850,C$4) -> 0 | D107: =SUMIFS('Transaction Overview'!$D$2:$D$1850,'Transaction Overview'!$I$2:$I$1850,$A107,'Transaction Overview'!$H$2:$H$1850,D$4) -> 0 | E107: =SUMIFS('Transaction Overview'!$D$2:$D$1850,'Transaction Overview'!$I$2:$I$1850,$A107,'Transaction Overview'!$H$2:$H$1850,E$4) -> 0 | F107: =SUMIFS('Transaction Overview'!$D$2:$D$1850,'Transaction Overview'!$I$2:$I$1850,$A107,'Transaction Overview'!$H$2:$H$1850,F$4) -> 0 | G107: =SUMIFS('Transaction Overview'!$D$2:$D$1850,'Transaction Overview'!$I$2:$I$1850,$A107,'Transaction Overview'!$H$2:$H$1850,G$4) -> 0 | H107: =SUMIFS('Transaction Overview'!$D$2:$D$1850,'Transaction Overview'!$I$2:$I$1850,$A107,'Transaction Overview'!$H$2:$H$1850,H$4) -> -394.76 | I107: =SUMIFS('Transaction Overview'!$D$2:$D$1850,'Transaction Overview'!$I$2:$I$1850,$A107,'Transaction Overview'!$H$2:$H$1850,I$4) -> 0 | ... M107: =SUMIFS('Transaction Overview'!$D$2:$D$1850,'Transaction Overview'!$I$2:$I$1850,$A107,'Transaction Overview'!$H$2:$H$1850,M$4) -> 0 | N107: =SUM(B107:M107) -> -394.76
A108: Travel | B108: =SUMIFS('Transaction Overview'!$D$2:$D$1850,'Transaction Overview'!$I$2:$I$1850,$A108,'Transaction Overview'!$H$2:$H$1850,B$4) -> -8 | C108: =SUMIFS('Transaction Overview'!$D$2:$D$1850,'Transaction Overview'!$I$2:$I$1850,$A108,'Transaction Overview'!$H$2:$H$1850,C$4) -> -40 | D108: =SUMIFS('Transaction Overview'!$D$2:$D$1850,'Transaction Overview'!$I$2:$I$1850,$A108,'Transaction Overview'!$H$2:$H$1850,D$4) -> -24 | E108: =SUMIFS('Transaction Overview'!$D$2:$D$1850,'Transaction Overview'!$I$2:$I$1850,$A108,'Transaction Overview'!$H$2:$H$1850,E$4) -> 0 | F108: =SUMIFS('Transaction Overview'!$D$2:$D$1850,'Transaction Overview'!$I$2:$I$1850,$A108,'Transaction Overview'!$H$2:$H$1850,F$4) -> 0 | G108: =SUMIFS('Transaction Overview'!$D$2:$D$1850,'Transaction Overview'!$I$2:$I$1850,$A108,'Transaction Overview'!$H$2:$H$1850,G$4) -> 0 | H108: =SUMIFS('Transaction Overview'!$D$2:$D$1850,'Transaction Overview'!$I$2:$I$1850,$A108,'Transaction Overview'!$H$2:$H$1850,H$4) -> 0 | I108: =SUMIFS('Transaction Overview'!$D$2:$D$1850,'Transaction Overview'!$I$2:$I$1850,$A108,'Transaction Overview'!$H$2:$H$1850,I$4) -> 0 | ... M108: =SUMIFS('Transaction Overview'!$D$2:$D$1850,'Transaction Overview'!$I$2:$I$1850,$A108,'Transaction Overview'!$H$2:$H$1850,M$4) -> 0 | N108: =SUM(B108:M108) -> -72
A109: Personal — Owner
A110: Personal - Food & Dining | B110: =SUMIFS('Transaction Overview'!$D$2:$D$1850,'Transaction Overview'!$I$2:$I$1850,$A110,'Transaction Overview'!$H$2:$H$1850,B$4) -> -1221.57 | C110: =SUMIFS('Transaction Overview'!$D$2:$D$1850,'Transaction Overview'!$I$2:$I$1850,$A110,'Transaction Overview'!$H$2:$H$1850,C$4) -> -1416.93 | D110: =SUMIFS('Transaction Overview'!$D$2:$D$1850,'Transaction Overview'!$I$2:$I$1850,$A110,'Transaction Overview'!$H$2:$H$1850,D$4) -> -1335.61 | E110: =SUMIFS('Transaction Overview'!$D$2:$D$1850,'Transaction Overview'!$I$2:$I$1850,$A110,'Transaction Overview'!$H$2:$H$1850,E$4) -> -314.32 | F110: =SUMIFS('Transaction Overview'!$D$2:$D$1850,'Transaction Overview'!$I$2:$I$1850,$A110,'Transaction Overview'!$H$2:$H$1850,F$4) -> -179.47 | G110: =SUMIFS('Transaction Overview'!$D$2:$D$1850,'Transaction Overview'!$I$2:$I$1850,$A110,'Transaction Overview'!$H$2:$H$1850,G$4) -> -60.6 | H110: =SUMIFS('Transaction Overview'!$D$2:$D$1850,'Transaction Overview'!$I$2:$I$1850,$A110,'Transaction Overview'!$H$2:$H$1850,H$4) -> -628.57 | I110: =SUMIFS('Transaction Overview'!$D$2:$D$1850,'Transaction Overview'!$I$2:$I$1850,$A110,'Transaction Overview'!$H$2:$H$1850,I$4) -> -364.8 | ... M110: =SUMIFS('Transaction Overview'!$D$2:$D$1850,'Transaction Overview'!$I$2:$I$1850,$A110,'Transaction Overview'!$H$2:$H$1850,M$4) -> -28.27 | N110: =SUM(B110:M110) -> -6486.38
...

Sheet Transfer In
A1: Chase 1168 — DWG Capital Group 2025 Activity
A2: Intercompany Transfers — In | Jan 2025 – Dec 2025
A4: SUMMARY
A5: Total | C5: =SUMIFS('Transaction Overview'!$D$2:$D$1850,'Transaction Overview'!$J$2:$J$1850,"Intercompany & Savings Transfers",'Transaction Overview'!$D$2:$D$1850,">0") -> 36500
A6: # Transactions | C6: =COUNTIFS('Transaction Overview'!$J$2:$J$1850,"Intercompany & Savings Transfers",'Transaction Overview'!$D$2:$D$1850,">0") -> 4

Sheet Transfer Out
A1: Chase 1168 — DWG Capital Group 2025 Activity
A2: Intercompany Transfers — Out | Jan 2025 – Dec 2025
A4: SUMMARY
A5: Total | C5: =SUMIFS('Transaction Overview'!$D$2:$D$1850,'Transaction Overview'!$J$2:$J$1850,"Intercompany & Savings Transfers",'Transaction Overview'!$D$2:$D$1850,"<0") -> -123202.89
A6: # Transactions | C6: =COUNTIFS('Transaction Overview'!$J$2:$J$1850,"Intercompany & Savings Transfers",'Transaction Overview'!$D$2:$D$1850,"<0") -> 33

Sheet Wire In
A1: Chase 1168 — DWG Capital Group 2025 Activity
A2: Wire Transfers — In | Jan 2025 – Dec 2025
A4: SUMMARY
A5: Total | C5: =SUMIFS('Transaction Overview'!$D$2:$D$1850,'Transaction Overview'!$J$2:$J$1850,"Intercompany & Savings Transfers",'Transaction Overview'!$D$2:$D$1850,">0") -> 36500
A6: # Transactions | C6: =COUNTIFS('Transaction Overview'!$J$2:$J$1850,"Intercompany & Savings Transfers",'Transaction Overview'!$D$2:$D$1850,">0") -> 4

Sheet Wire Out
A1: Chase 1168 — DWG Capital Group 2025 Activity
A2: Wire Transfers — Out | Jan 2025 – Dec 2025
A4: SUMMARY
A5: Total | C5: =SUMIFS('Transaction Overview'!$D$2:$D$1850,'Transaction Overview'!$J$2:$J$1850,"Intercompany & Savings Transfers",'Transaction Overview'!$D$2:$D$1850,"<0") -> -123202.89
A6: # Transactions | C6: =COUNTIFS('Transaction Overview'!$J$2:$J$1850,"Intercompany & Savings Transfers",'Transaction Overview'!$D$2:$D$1850,"<0") -> 33

Sheet Commission
A1: Chase 1168 — DWG Capital Group 2025 Activity
A2: Commissions Statement | Jan 2025 – Dec 2025
A4: SUMMARY
A5: Total | C5: =SUMIFS('Transaction Overview'!$D$2:$D$1850,'Transaction Overview'!$J$2:$J$1850,"Commissions — Incoming",'Transaction Overview'!$D$2:$D$1850,">0") -> 661437
A6: # Transactions | C6: =COUNTIFS('Transaction Overview'!$J$2:$J$1850,"Commissions — Incoming",'Transaction Overview'!$D$2:$D$1850,">0") -> 10

Sheet Transaction Overview
A1: Details | B1: Posting Date | C1: Description | D1: Amount | E1: Type | F1: Balance | G1: Category | H1: Month | I1: Combined Category | J1: Group
A2: =Chase1168_2025!A2 -> DEBIT | B2: =Chase1168_2025!B2 -> 46022 | C2: =Chase1168_2025!C2 -> ONLINE FX INTERNATIONAL WIRE FEE | D2: =Chase1168_2025!D2 -> -5 | E2: =Chase1168_2025!E2 -> FEE_TRANSACTION | F2: =Chase1168_2025!F2 -> 30206.23 | G2: =Chase1168_2025!G2 -> Andres Alarcon Payroll | H2: =IF($B2="","",DATE(YEAR($B2),MONTH($B2),1)) -> 45992 | I2: =IF($G2="","Uncategorized — Review",IFERROR(INDEX(Mapping!$B:$B,MATCH($G2,Mapping!$A:$A,0)),"Uncategorized — Review")) -> Andres Alarcon Payroll | J2: =IF($G2="","Uncategorized — Review",IFERROR(INDEX(Mapping!$C:$C,MATCH($G2,Mapping!$A:$A,0)),"Uncategorized — Review")) -> Payroll & Contractors
A3: =Chase1168_2025!A3 -> DEBIT | B3: =Chase1168_2025!B3 -> 46022 | C3: =Chase1168_2025!C3 -> ONLINE INTERNATIONAL WIRE TRANSFER A/C: FOREIGN CUR BUS ACCT BK 1 COLUMBUS NEWARK DE 197132107 US ORG: 00000000283681168 DWG CAPITAL GROUP BEN:/00714849981 MARIA FERNANDA ALARCON PIEDRAHITA REF: TAXID1017222855/TEL573207819186/SAV/SALARY/PAYROLL PAYMENTS/OCMT/COP26 49416,78/EXCH/3532.5557/CNTR/156111 34/INT/ANDRES_52763ATHOTMAIL.C TRN: 6879000365RE 12/31 | D3: =Chase1168_2025!D3 -> -750 | E3: =Chase1168_2025!E3 -> WIRE_OUTGOING | F3: =Chase1168_2025!F3 -> 30211.23 | G3: =Chase1168_2025!G3 -> Andres Alarcon Payroll | H3: =IF($B3="","",DATE(YEAR($B3),MONTH($B3),1)) -> 45992 | I3: =IF($G3="","Uncategorized — Review",IFERROR(INDEX(Mapping!$B:$B,MATCH($G3,Mapping!$A:$A,0)),"Uncategorized — Review")) -> Andres Alarcon Payroll | J3: =IF($G3="","Uncategorized — Review",IFERROR(INDEX(Mapping!$C:$C,MATCH($G3,Mapping!$A:$A,0)),"Uncategorized — Review")) -> Payroll & Contractors
A4: =Chase1168_2025!A4 -> DEBIT | B4: =Chase1168_2025!B4 -> 46022 | C4: =Chase1168_2025!C4 -> ORIG CO NAME:GEICO ORIG ID:3530075853 DESC DATE:251230 CO ENTRY DESCR:PREM COLL SEC:PPD TRACE#:021000020954890 EED:251231 IND ID: IND NAME:ANGELA TRN: 3650954890TC | D4: =Chase1168_2025!D4 -> -619.87 | E4: =Chase1168_2025!E4 -> ACH_DEBIT | F4: =Chase1168_2025!F4 -> 30961.23 | G4: =Chase1168_2025!G4 -> Personal - Car Insurance | H4: =IF($B4="","",DATE(YEAR($B4),MONTH($B4),1)) -> 45992 | I4: =IF($G4="","Uncategorized — Review",IFERROR(INDEX(Mapping!$B:$B,MATCH($G4,Mapping!$A:$A,0)),"Uncategorized — Review")) -> Personal - Car & Auto | J4: =IF($G4="","Uncategorized — Review",IFERROR(INDEX(Mapping!$C:$C,MATCH($G4,Mapping!$A:$A,0)),"Uncategorized — Review")) -> Personal — Owner
A5: =Chase1168_2025!A5 -> DEBIT | B5: =Chase1168_2025!B5 -> 46021 | C5: =Chase1168_2025!C5 -> ORIG CO NAME:SBA EIDL LOAN ORIG ID:7300000118 DESC DATE:251229 CO ENTRY DESCR:PAYMENT SEC:CCD TRACE#:041036049540812 EED:251230 IND ID:0000 IND NAME:JOHN DUNNING 1871308204 ACH TRANSACTION TRN: 3649540812TC | D5: =Chase1168_2025!D5 -> -2524 | E5: =Chase1168_2025!E5 -> ACH_DEBIT | F5: =Chase1168_2025!F5 -> 31581.1 | G5: =Chase1168_2025!G5 -> SBC EIDL Loan | H5: =IF($B5="","",DATE(YEAR($B5),MONTH($B5),1)) -> 45992 | I5: =IF($G5="","Uncategorized — Review",IFERROR(INDEX(Mapping!$B:$B,MATCH($G5,Mapping!$A:$A,0)),"Uncategorized — Review")) -> SBC EIDL Loan | J5: =IF($G5="","Uncategorized — Review",IFERROR(INDEX(Mapping!$C:$C,MATCH($G5,Mapping!$A:$A,0)),"Uncategorized — Review")) -> Credit Card & Loan Payments
A6: =Chase1168_2025!A6 -> DEBIT | B6: =Chase1168_2025!B6 -> 46020 | C6: =Chase1168_2025!C6 -> ORIG CO NAME:TXU ENERGY ORIG ID:1001020329 DESC DATE: CO ENTRY DESCR:TXUE_ACH SEC:WEB TRACE#:021000025255110 EED:251229 IND ID:900062431557 IND NAME:DWG CAPITAL GROUP 17333702810000000000000000000003592 4192821 DIRECT DEBITING TRN: 3635255110TC | D6: =Chase1168_2025!D6 -> -510.09 | E6: =Chase1168_2025!E6 -> ACH_DEBIT | F6: =Chase1168_2025!F6 -> 34105.1 | G6: =Chase1168_2025!G6 -> Texas - House Utilities | H6: =IF($B6="","",DATE(YEAR($B6),MONTH($B6),1)) -> 45992 | I6: =IF($G6="","Uncategorized — Review",IFERROR(INDEX(Mapping!$B:$B,MATCH($G6,Mapping!$A:$A,0)),"Uncategorized — Review")) -> Texas - House Utilities | J6: =IF($G6="","Uncategorized — Review",IFERROR(INDEX(Mapping!$C:$C,MATCH($G6,Mapping!$A:$A,0)),"Uncategorized — Review")) -> Personal — Owner
A7: =Chase1168_2025!A7 -> DEBIT | B7: =Chase1168_2025!B7 -> 46020 | C7: =Chase1168_2025!C7 -> Basic Online Payroll Payment 11200477377 to ########4122 | D7: =Chase1168_2025!D7 -> -1750 | E7: =Chase1168_2025!E7 -> BASIC_PAYROLL | F7: =Chase1168_2025!F7 -> 34615.19 | G7: =Chase1168_2025!G7 -> Mike Paytonjian - Payroll | H7: =IF($B7="","",DATE(YEAR($B7),MONTH($B7),1)) -> 45992 | I7: =IF($G7="","Uncategorized — Review",IFERROR(INDEX(Mapping!$B:$B,MATCH($G7,Mapping!$A:$A,0)),"Uncategorized — Review")) -> Mike Paytonjian - Payroll | J7: =IF($G7="","Uncategorized — Review",IFERROR(INDEX(Mapping!$C:$C,MATCH($G7,Mapping!$A:$A,0)),"Uncategorized — Review")) -> Payroll & Contractors
A8: =Chase1168_2025!A8 -> DEBIT | B8: =Chase1168_2025!B8 -> 46020 | C8: =Chase1168_2025!C8 -> ORIG CO NAME:BANNER LIFE ORIG ID:1521236145 DESC DATE:251228 CO ENTRY DESCR:PREM DEBITSEC:PPD TRACE#:091000014535049 EED:251229 IND ID: IND NAME:ANGELA L DUNNING TRN: 3634535049TC | D8: =Chase1168_2025!D8 -> -12.5 | E8: =Chase1168_2025!E8 -> ACH_DEBIT | F8: =Chase1168_2025!F8 -> 36365.19 | G8: =Chase1168_2025!G8 -> Personal - Life Insurance | H8: =IF($B8="","",DATE(YEAR($B8),MONTH($B8),1)) -> 45992 | I8: =IF($G8="","Uncategorized — Review",IFERROR(INDEX(Mapping!$B:$B,MATCH($G8,Mapping!$A:$A,0)),"Uncategorized — Review")) -> Personal - Life Insurance | J8: =IF($G8="","Uncategorized — Review",IFERROR(INDEX(Mapping!$C:$C,MATCH($G8,Mapping!$A:$A,0)),"Uncategorized — Review")) -> Personal — Owner
A9: =Chase1168_2025!A9 -> DEBIT | B9: =Chase1168_2025!B9 -> 46020 | C9: =Chase1168_2025!C9 -> ORIG CO NAME:BANNER LIFE ORIG ID:1521236145 DESC DATE:251228 CO ENTRY DESCR:PREM DEBITSEC:PPD TRACE#:091000014535050 EED:251229 IND ID: IND NAME:JOHN DUNNING TRN: 3634535050TC | D9: =Chase1168_2025!D9 -> -22.92 | E9: =Chase1168_2025!E9 -> ACH_DEBIT | F9: =Chase1168_2025!F9 -> 36377.69 | G9: =Chase1168_2025!G9 -> Personal - Life Insurance | H9: =IF($B9="","",DATE(YEAR($B9),MONTH($B9),1)) -> 45992 | I9: =IF($G9="","Uncategorized — Review",IFERROR(INDEX(Mapping!$B:$B,MATCH($G9,Mapping!$A:$A,0)),"Uncategorized — Review")) -> Personal - Life Insurance | J9: =IF($G9="","Uncategorized — Review",IFERROR(INDEX(Mapping!$C:$C,MATCH($G9,Mapping!$A:$A,0)),"Uncategorized — Review")) -> Personal — Owner
A10: =Chase1168_2025!A10 -> DEBIT | B10: =Chase1168_2025!B10 -> 46020 | C10: =Chase1168_2025!C10 -> ORIG CO NAME:INTUIT * ORIG ID:0000756346 DESC DATE:251227 CO ENTRY DESCR:QBooks OnlSEC:CCD TRACE#:021000023968943 EED:251229 IND ID:9445751 IND NAME:DWG CAPITAL GROUP 800-446-8848 TRN: 3633968943TC | D10: =Chase1168_2025!D10 -> -121.21 | E10: =Chase1168_2025!E10 -> ACH_DEBIT | F10: =Chase1168_2025!F10 -> 36400.61 | G10: =Chase1168_2025!G10 -> Software/Accounting | H10: =IF($B10="","",DATE(YEAR($B10),MONTH($B10),1)) -> 45992 | I10: =IF($G10="","Uncategorized — Review",IFERROR(INDEX(Mapping!$B:$B,MATCH($G10,Mapping!$A:$A,0)),"Uncategorized — Review")) -> Software/Accounting | J10: =IF($G10="","Uncategorized — Review",IFERROR(INDEX(Mapping!$C:$C,MATCH($G10,Mapping!$A:$A,0)),"Uncategorized — Review")) -> DWG Operating
A11: =Chase1168_2025!A11 -> DEBIT | B11: =Chase1168_2025!B11 -> 46020 | C11: =Chase1168_2025!C11 -> ORIG CO NAME:VENMO ORIG ID:3264681992 DESC DATE:251227 CO ENTRY DESCR:PAYMENT SEC:WEB TRACE#:021000024517263 EED:251229 IND ID:1047213591622 IND NAME:JUDD DUNNING 251227PPZSDJ TRN: 3634517263TC | D11: =Chase1168_2025!D11 -> -150 | E11: =Chase1168_2025!E11 -> ACH_DEBIT | F11: =Chase1168_2025!F11 -> 36521.82 | G11: =Chase1168_2025!G11 -> Venmo | H11: =IF($B11="","",DATE(YEAR($B11),MONTH($B11),1)) -> 45992 | I11: =IF($G11="","Uncategorized — Review",IFERROR(INDEX(Mapping!$B:$B,MATCH($G11,Mapping!$A:$A,0)),"Uncategorized — Review")) -> Venmo | J11: =IF($G11="","Uncategorized — Review",IFERROR(INDEX(Mapping!$C:$C,MATCH($G11,Mapping!$A:$A,0)),"Uncategorized — Review")) -> P2P Payments (Zelle/Venmo/PayPal)
A12: =Chase1168_2025!A12 -> DEBIT | B12: =Chase1168_2025!B12 -> 46020 | C12: =Chase1168_2025!C12 -> ORIG CO NAME:AMERICAN EXPRESS ORIG ID:2005032111 DESC DATE:251229 CO ENTRY DESCR:ACH PMT SEC:CCD TRACE#:021000024677083 EED:251229 IND ID:W9796 IND NAME:John Dunning ER AM TRN: 3634677083TC | D12: =Chase1168_2025!D12 -> -1581.75 | E12: =Chase1168_2025!E12 -> ACH_DEBIT | F12: =Chase1168_2025!F12 -> 36671.82 | G12: =Chase1168_2025!G12 -> American Express Credit Card PMT | H12: =IF($B12="","",DATE(YEAR($B12),MONTH($B12),1)) -> 45992 | I12: =IF($G12="","Uncategorized — Review",IFERROR(INDEX(Mapping!$B:$B,MATCH($G12,Mapping!$A:$A,0)),"Uncategorized — Review")) -> American Express Credit Card PMT | J12: =IF($G12="","Uncategorized — Review",IFERROR(INDEX(Mapping!$C:$C,MATCH($G12,Mapping!$A:$A,0)),"Uncategorized — Review")) -> Credit Card & Loan Payments
A13: =Chase1168_2025!A13 -> DEBIT | B13: =Chase1168_2025!B13 -> 46020 | C13: =Chase1168_2025!C13 -> ORIG CO NAME:GEICO ORIG ID:3530075853 DESC DATE:251228 CO ENTRY DESCR:PREM COLL SEC:PPD TRACE#:021000024725505 EED:251229 IND ID: IND NAME:ANGELA DUNNING TRN: 3634725505TC | D13: =Chase1168_2025!D13 -> -2290.33 | E13: =Chase1168_2025!E13 -> ACH_DEBIT | F13: =Chase1168_2025!F13 -> 38253.57 | G13: =Chase1168_2025!G13 -> Personal - Car Insurance | H13: =IF($B13="","",DATE(YEAR($B13),MONTH($B13),1)) -> 45992 | I13: =IF($G13="","Uncategorized — Review",IFERROR(INDEX(Mapping!$B:$B,MATCH($G13,Mapping!$A:$A,0)),"Uncategorized — Review")) -> Personal - Car & Auto | J13: =IF($G13="","Uncategorized — Review",IFERROR(INDEX(Mapping!$C:$C,MATCH($G13,Mapping!$A:$A,0)),"Uncategorized — Review")) -> Personal — Owner
... A1850: =Chase1168_2025!A1850 -> CREDIT | B1850: =Chase1168_2025!B1850 -> 45659 | C1850: =Chase1168_2025!C1850 -> FEDWIRE CREDIT VIA: BANK OF AMERICA, N.A./026009593 B/O: CT SOCAL COMM FBSC/CT BS FXBC RIVERSIDE CA 92505 US REF: CHASE NYC/CTR/BNF=DWG CAPITAL GROUP LOS ANGELES CA 90066-3638 US/AC-00 0000002836 RFB=1-18462072 OBI=FN-FB SC2403516 ACQUISITION FEE/AND APPRA ISAL REIMB EDGE BUILDER P/ROP AD DR -1607 PINE ST IMAD: 0102B6B7HU1R020333 TRN: 1195641002FF | D1850: =Chase1168_2025!D1850 -> 61037 | E1850: =Chase1168_2025!E1850 -> WIRE_INCOMING | F1850: =Chase1168_2025!F1850 -> 73545.85 | G1850: =Chase1168_2025!G1850 -> Incoming Commission: Edge Builder | H1850: =IF($B1850="","",DATE(YEAR($B1850),MONTH($B1850),1)) -> 45658 | I1850: =IF($G1850="","Uncategorized — Review",IFERROR(INDEX(Mapping!$B:$B,MATCH($G1850,Mapping!$A:$A,0)),"Uncategorized — Review")) -> Incoming Commission: Edge Builder | J1850: =IF($G1850="","Uncategorized — Review",IFERROR(INDEX(Mapping!$C:$C,MATCH($G1850,Mapping!$A:$A,0)),"Uncategorized — Review")) -> Commissions — Incoming

Sheet Mapping
A1: Raw Category | B1: Combined Category | C1: Group
A2: 2024/2025 Canada Trip | B2: 2024/2025 Canada Trip | C2: Business Travel
A3: 2025 Costa Rica Trip | B3: 2025 Costa Rica Trip | C3: Business Travel
A4: ??? | B4: ??? | C4: Uncategorized — Review
A5: AI Subscriptions | B5: AI Subscriptions | C5: DWG Operating
A6: ATM/Cash | B6: ATM/Cash | C6: Uncategorized — Review
A7: American Express Credit Card PMT | B7: American Express Credit Card PMT | C7: Credit Card & Loan Payments
A8: Andres Alarcon Payroll | B8: Andres Alarcon Payroll | C8: Payroll & Contractors
A9: Ashley Sarshar - Payroll | B9: Ashley Sarshar - Payroll | C9: Payroll & Contractors
A10: Bank Fee | B10: Bank & Wire Fees | C10: DWG Operating
A11: Bank Fees | B11: Bank Fees | C11: DWG Operating
A12: Bill Payment | B12: Bill Payment | C12: DWG Operating
... A116: Zelle/P2P | B116: Zelle/P2P | C116: P2P Payments (Zelle/Venmo/PayPal)

Sheet Chase1168_2025
A1: Details | B1: Posting Date | C1: Description | D1: Amount | E1: Type | F1: Balance | G1: Category
A2: DEBIT | B2: 46022 | C2: ONLINE FX INTERNATIONAL WIRE FEE | D2: -5 | E2: FEE_TRANSACTION | F2: 30206.23 | G2: Andres Alarcon Payroll
A3: DEBIT | B3: 46022 | C3: ONLINE INTERNATIONAL WIRE TRANSFER A/C: FOREIGN CUR BUS ACCT BK 1 COLUMBUS NEWARK DE 197132107 US ORG: 00000000283681168 DWG CAPITAL GROUP BEN:/00714849981 MARIA FERNANDA ALARCON PIEDRAHITA REF: TAXID1017222855/TEL573207819186/SAV/SALARY/PAYROLL PAYMENTS/OCMT/COP26 49416,78/EXCH/3532.5557/CNTR/156111 34/INT/ANDRES_52763ATHOTMAIL.C TRN: 6879000365RE 12/31 | D3: -750 | E3: WIRE_OUTGOING | F3: 30211.23 | G3: Andres Alarcon Payroll
A4: DEBIT | B4: 46022 | C4: ORIG CO NAME:GEICO ORIG ID:3530075853 DESC DATE:251230 CO ENTRY DESCR:PREM COLL SEC:PPD TRACE#:021000020954890 EED:251231 IND ID: IND NAME:ANGELA TRN: 3650954890TC | D4: -619.87 | E4: ACH_DEBIT | F4: 30961.23 | G4: Personal - Car Insurance
A5: DEBIT | B5: 46021 | C5: ORIG CO NAME:SBA EIDL LOAN ORIG ID:7300000118 DESC DATE:251229 CO ENTRY DESCR:PAYMENT SEC:CCD TRACE#:041036049540812 EED:251230 IND ID:0000 IND NAME:JOHN DUNNING 1871308204 ACH TRANSACTION TRN: 3649540812TC | D5: -2524 | E5: ACH_DEBIT | F5: 31581.1 | G5: SBC EIDL Loan
A6: DEBIT | B6: 46020 | C6: ORIG CO NAME:TXU ENERGY ORIG ID:1001020329 DESC DATE: CO ENTRY DESCR:TXUE_ACH SEC:WEB TRACE#:021000025255110 EED:251229 IND ID:900062431557 IND NAME:DWG CAPITAL GROUP 17333702810000000000000000000003592 4192821 DIRECT DEBITING TRN: 3635255110TC | D6: -510.09 | E6: ACH_DEBIT | F6: 34105.1 | G6: Texas - House Utilities
A7: DEBIT | B7: 46020 | C7: Basic Online Payroll Payment 11200477377 to ########4122 | D7: -1750 | E7: BASIC_PAYROLL | F7: 34615.19 | G7: Mike Paytonjian - Payroll
A8: DEBIT | B8: 46020 | C8: ORIG CO NAME:BANNER LIFE ORIG ID:1521236145 DESC DATE:251228 CO ENTRY DESCR:PREM DEBITSEC:PPD TRACE#:091000014535049 EED:251229 IND ID: IND NAME:ANGELA L DUNNING TRN: 3634535049TC | D8: -12.5 | E8: ACH_DEBIT | F8: 36365.19 | G8: Personal - Life Insurance
A9: DEBIT | B9: 46020 | C9: ORIG CO NAME:BANNER LIFE ORIG ID:1521236145 DESC DATE:251228 CO ENTRY DESCR:PREM DEBITSEC:PPD TRACE#:091000014535050 EED:251229 IND ID: IND NAME:JOHN DUNNING TRN: 3634535050TC | D9: -22.92 | E9: ACH_DEBIT | F9: 36377.69 | G9: Personal - Life Insurance
A10: DEBIT | B10: 46020 | C10: ORIG CO NAME:INTUIT * ORIG ID:0000756346 DESC DATE:251227 CO ENTRY DESCR:QBooks OnlSEC:CCD TRACE#:021000023968943 EED:251229 IND ID:9445751 IND NAME:DWG CAPITAL GROUP 800-446-8848 TRN: 3633968943TC | D10: -121.21 | E10: ACH_DEBIT | F10: 36400.61 | G10: Software/Accounting
A11: DEBIT | B11: 46020 | C11: ORIG CO NAME:VENMO ORIG ID:3264681992 DESC DATE:251227 CO ENTRY DESCR:PAYMENT SEC:WEB TRACE#:021000024517263 EED:251229 IND ID:1047213591622 IND NAME:JUDD DUNNING 251227PPZSDJ TRN: 3634517263TC | D11: -150 | E11: ACH_DEBIT | F11: 36521.82 | G11: Venmo
A12: DEBIT | B12: 46020 | C12: ORIG CO NAME:AMERICAN EXPRESS ORIG ID:2005032111 DESC DATE:251229 CO ENTRY DESCR:ACH PMT SEC:CCD TRACE#:021000024677083 EED:251229 IND ID:W9796 IND NAME:John Dunning ER AM TRN: 3634677083TC | D12: -1581.75 | E12: ACH_DEBIT | F12: 36671.82 | G12: American Express Credit Card PMT
A13: DEBIT | B13: 46020 | C13: ORIG CO NAME:GEICO ORIG ID:3530075853 DESC DATE:251228 CO ENTRY DESCR:PREM COLL SEC:PPD TRACE#:021000024725505 EED:251229 IND ID: IND NAME:ANGELA DUNNING TRN: 3634725505TC | D13: -2290.33 | E13: ACH_DEBIT | F13: 38253.57 | G13: Personal - Car Insurance
... A1413: CREDIT | B1413: 45735 | C1413: FEDWIRE CREDIT VIA: WORTHINGTON BANK/111924622 B/O: RATTIKIN TITLE COMPANY FORT WORTH TX 76116 REF: CHASE NYC/CTR/BNF=DWG CAPITAL GROUP LOS ANGELES CA 90066-3638 US/AC-00 0000002836 RFB=25-0127 OBI=COMMISSI ONS, 315 YORK AVE WEATHERFO RD, TX 76087 817-332-1171 25-0127 IMAD: 0319GMQFMP01030982 TRN: 1113891078FF | D1413: 40350 | E1413: WIRE_INCOMING | F1413: 57051.01 | G1413: Incoming Commission: 315 York
A1414: DEBIT | B1414: 45734 | C1414: Online Payment 24099720805 To LOS ANGELES MUNICIPAL SERVICE 03/18 | D1414: -1798.56 | E1414: BILLPAY | F1414: 16701.01
A1415: DEBIT | B1415: 45734 | C1415: Online Payment 24099702638 To MERCEDES BENZ FINANCIAL 03/18 | D1415: -409.45 | E1415: BILLPAY | F1415: 18499.57 | G1415: Personal - Car (Mercedes)
A1416: DEBIT | B1416: 45734 | C1416: Online Payment 24099604002 To SOUTHERN CALIFORNIA GAS CO 03/18 | D1416: -300 | E1416: BILLPAY | F1416: 18909.02
A1417: DEBIT | B1417: 45734 | C1417: Zelle payment to jeff Fajardo JPM99b1rxaka | D1417: -300 | E1417: CHASE_TO_PARTNERFI | F1417: 19209.02 | G1417: Zelle - Jeff Fajardo
A1418: DEBIT | B1418: 45734 | C1418: ORIG CO NAME:LEASEDIRECT ORIG ID:138190450 DESC DATE:250317 CO ENTRY DESCR:11783_1 SEC:CCD TRACE#:043000093815408 EED:250318 IND ID:1556926 IND NAME:DWG CAPITAL GROUP INV# 589413700 DUE 03/15/25 REC# 18 94667 11784 TRN: 0773815408TC | D1418: -103.81 | E1418: ACH_DEBIT | F1418: 19509.02 | G1418: DWG - TBD
A1419: DEBIT | B1419: 45734 | C1419: Upwork -790216789REF 650-8534100 CA 03/17 | D1419: -1260 | E1419: DEBIT_CARD | F1419: 19612.83 | G1419: Upwork - Sergei M.
A1420: DEBIT | B1420: 45734 | C1420: PP*APPLE.COM/BILL 800-275-2273 CA 03/17 | D1420: -9.99 | E1420: DEBIT_CARD | F1420: 20872.83 | G1420: Personal - Subscriptions
A1421: DEBIT | B1421: 45733 | C1421: ORIG CO NAME:VENMO ORIG ID:3264681992 DESC DATE:250315 CO ENTRY DESCR:PAYMENT SEC:WEB TRACE#:091000014647380 EED:250317 IND ID:1040910151880 IND NAME:JUDD DUNNING TRN: 0764647380TC | D1421: -300 | E1421: ACH_DEBIT | F1421: 20882.82 | G1421: Venmo
A1422: DEBIT | B1422: 45733 | C1422: Online Transfer to CHK ...1117 transaction#: 24082324824 03/17 | D1422: -2000 | E1422: ACCT_XFER | F1422: 21182.82 | G1422: Transfer to Angela Dunning
A1423: DEBIT | B1423: 45733 | C1423: PP*APPLE.COM/BILL 800-275-2273 CA 03/17 | D1423: -8.99 | E1423: DEBIT_CARD | F1423: 23182.82 | G1423: Personal - Subscriptions
A1424: DEBIT | B1424: 45733 | C1424: PAYPAL *UBER 866-576-1039 CA 03/15 | D1424: -35.8 | E1424: DEBIT_CARD | F1424: 23191.81 | G1424: Personal - Car
A1425: DEBIT | B1425: 45733 | C1425: PAYPAL *UBER 866-576-1039 CA 03/15 | D1425: -4.49 | E1425: DEBIT_CARD | F1425: 23227.61 | G1425: Personal - Car
A1426: DEBIT | B1426: 45733 | C1426: PAYPAL *LINKEDIN 402-935-7733 CA 03/17 | D1426: -69.99 | E1426: DEBIT_CARD | F1426: 23232.1 | G1426: DWG HR
A1427: DEBIT | B1427: 45733 | C1427: PAYPAL *RUTHALCANCI 402-935-7733 CA 03/15 | D1427: -200 | E1427: DEBIT_CARD | F1427: 23302.09 | G1427: Ruth Alcancia - Forward Bridge Payment
A1428: DEBIT | B1428: 45733 | C1428: PP*APPLE.COM/BILL 800-275-2273 CA 03/15 | D1428: -5.99 | E1428: DEBIT_CARD | F1428: 23502.09 | G1428: Personal - Subscriptions
... A1480: CREDIT | B1480: 45722 | C1480: Online Transfer from CHK ...9335 transaction#: 23962559557 | D1480: 20000 | E1480: ACCT_XFER | F1480: 24831.26 | G1480: Transfer From Poseidon Asset Group
A1481: DEBIT | B1481: 45721 | C1481: Basic Online Payroll Payment 11164332803 to ###########4123 | D1481: -63 | E1481: BASIC_PAYROLL | F1481: 4831.26
A1482: DEBIT | B1482: 45720 | C1482: ORIG CO NAME:VENMO ORIG ID:3264681992 DESC DATE:250303 CO ENTRY DESCR:PAYMENT SEC:WEB TRACE#:091000012769161 EED:250304 IND ID:1040660013264 IND NAME:JUDD DUNNING TRN: 0632769161TC | D1482: -500 | E1482: ACH_DEBIT | F1482: 4894.26 | G1482: Venmo
A1483: DEBIT | B1483: 45720 | C1483: Zelle payment to Aaron Frankel JPM99b073qsz | D1483: -500 | E1483: CHASE_TO_PARTNERFI | F1483: 5394.26 | G1483: Zelle - Aaron Frankel
A1484: DEBIT | B1484: 45720 | C1484: Zelle payment to Nate JPM99b073do7 | D1484: -1000 | E1484: CHASE_TO_PARTNERFI | F1484: 5894.26 | G1484: Zelle - TBD
A1485: DEBIT | B1485: 45720 | C1485: TST*THE BUTCHERS DAUGHT Venice CA 03/03 | D1485: -192.51 | E1485: DEBIT_CARD | F1485: 6894.26 | G1485: Personal - Food
A1486: DEBIT | B1486: 45720 | C1486: AA WIFI 1-888-649-6711 Fort Worth TX 03/04 | D1486: -12 | E1486: DEBIT_CARD | F1486: 7086.77 | G1486: Travel
A1487: DEBIT | B1487: 45720 | C1487: PP*APPLE.COM/BILL 800-275-2273 CA 03/04 | D1487: -29.99 | E1487: DEBIT_CARD | F1487: 7098.77 | G1487: Personal - Subscriptions
A1488: DEBIT | B1488: 45720 | C1488: PAYPAL *SANDYPR COM 402-935-7733 CA 03/03 | D1488: -300 | E1488: DEBIT_CARD | F1488: 7128.76 | G1488: Sandy PR Payment
A1489: DEBIT | B1489: 45720 | C1489: PAYPAL *PRAGERUNIVE P 833-772-4378 CA 03/03 | D1489: -10.78 | E1489: DEBIT_CARD | F1489: 7428.76 | G1489: DWGCP Business Development
A1490: DEBIT | B1490: 45719 | C1490: STANDARD ACH PMNTS INITIAL FEE QTY = 7 | D1490: -17.5 | E1490: FEE_TRANSACTION | F1490: 7439.54 | G1490: Bank Fees
A1491: DEBIT | B1491: 45719 | C1491: ORIG CO NAME:BLUESHIELDCA ORIG ID:7529219311 DESC DATE:250228 CO ENTRY DESCR:BILL PAY SEC:CCD TRACE#:031101117496778 EED:250303 IND ID:15649262731 IND NAME:ANGELA DUNNING TRN: 0627496778TC | D1491: -86.47 | E1491: ACH_DEBIT | F1491: 7457.04 | G1491: Personal - Health Insurance
A1492: DEBIT | B1492: 45719 | C1492: PP*APPLE.COM/BILL 800-275-2273 CA 03/03 | D1492: -3.99 | E1492: DEBIT_CARD | F1492: 7543.51 | G1492: Personal - Subscriptions
A1493: DEBIT | B1493: 45719 | C1493: PP*APPLE.COM/BILL 800-275-2273 CA 03/03 | D1493: -12.99 | E1493: DEBIT_CARD | F1493: 7547.5 | G1493: Personal - Subscriptions
... A1624: DEBIT | B1624: 45700 | C1624: Online Transfer to CHK ...0709 transaction#: 23704834601 02/12 | D1624: -1000 | E1624: ACCT_XFER | F1624: 52410.94 | G1624: Transfer to DWG Capital Group_Savings
A1625: DEBIT | B1625: 45700 | C1625: Basic Online Payroll Payment 11161685029 to ###########4123 | D1625: -750 | E1625: BASIC_PAYROLL | F1625: 53410.94
A1626: DEBIT | B1626: 45700 | C1626: PP*SPOTIFYUSAI 203-318-9708 NY 02/12 | D1626: -11.99 | E1626: DEBIT_CARD | F1626: 54160.94 | G1626: Personal - Subscriptions
A1627: DEBIT | B1627: 45699 | C1627: DOMESTIC INCOMING WIRE FEE | D1627: -15 | E1627: FEE_TRANSACTION | F1627: 54172.93 | G1627: Wire Fee
A1628: DEBIT | B1628: 45699 | C1628: ORIG CO NAME:GM Financial ORIG ID:I522190781 DESC DATE:250211 CO ENTRY DESCR:GMF Pymt SEC:PPD TRACE#:091000013913581 EED:250211 IND ID: IND NAME:ANGELA DUNNING TRN: 0423913581TC | D1628: -1249.96 | E1628: ACH_DEBIT | F1628: 54187.93 | G1628: Personal - Car
A1629: DEBIT | B1629: 45699 | C1629: UPWORK * -779118706 866-262-4478 CA 02/10 | D1629: -918.75 | E1629: DEBIT_CARD | F1629: 55437.89 | G1629: Upwork - Sergei M.
A1630: DEBIT | B1630: 45699 | C1630: PP*APPLE.COM/BILL 800-275-2273 CA 02/10 | D1630: -30 | E1630: DEBIT_CARD | F1630: 56356.64 | G1630: Personal - Subscriptions
A1631: DEBIT | B1631: 45699 | C1631: PP*APPLE.COM/BILL 800-275-2273 CA 02/10 | D1631: -17.99 | E1631: DEBIT_CARD | F1631: 56386.64 | G1631: Personal - Subscriptions
A1632: CREDIT | B1632: 45699 | C1632: Online Transfer from CHK ...3922 transaction#: 23689273178 | D1632: 5000 | E1632: ACCT_XFER | F1632: 56404.63 | G1632: Transfer From DWG Capital Partners
A1633: CREDIT | B1633: 45699 | C1633: FEDWIRE CREDIT VIA: BANK OF AMERICA, N.A./026009593 B/O: CT SOCAL COMM FBSC/CT BS FXBC RIVERSIDE CA 92505 US REF: CHASE NYC/CTR/BNF=DWG CAPITAL GROUP LOS ANGELES CA 90066-3638 US/AC-00 0000002836 RFB=1-18608751 OBI=FN-FB SC2404500 2848 WEST SWEETW/AT ER AV ENUE, PHOENIX, AZ PROPADDR-/28 48 W SWEETWATER AV IMAD: 0211B6B7HU3R014212 TRN: 0894891042FF | D1633: 50000 | E1633: WIRE_INCOMING | F1633: 51404.63 | G1633: MAG Capital Partners Pass-Through Wire – 70/30 Split
A1634: DEBIT | B1634: 45698 | C1634: Online Transfer to CHK ...1283 transaction#: 23680847097 02/10 | D1634: -100 | E1634: ACCT_XFER | F1634: 1404.63 | G1634: Transfer to DWG Holdings
A1635: DEBIT | B1635: 45698 | C1635: Online Transfer to CHK ...6586 transaction#: 23680833850 02/10 | D1635: -100 | E1635: ACCT_XFER | F1635: 1504.63 | G1635: Transfer to TGAIF Fund
A1636: DEBIT | B1636: 45698 | C1636: Online Transfer to CHK ...2508 transaction#: 23680822191 02/10 | D1636: -1000 | E1636: ACCT_XFER | F1636: 1604.63 | G1636: Transfer to Theut Glass
A1637: DEBIT | B1637: 45698 | C1637: Online Transfer to CHK ...1117 transaction#: 23680819812 02/10 | D1637: -2000 | E1637: ACCT_XFER | F1637: 2604.63 | G1637: Transfer to Angela Dunning
... A1745: DEBIT | B1745: 45678 | C1745: Online Transfer to CHK ...1117 transaction#: 23450617971 01/21 | D1745: -2000 | E1745: ACCT_XFER | F1745: 9453.16 | G1745: Transfer to Angela Dunning
A1746: DEBIT | B1746: 45678 | C1746: Online Payment 23450485096 To LOS ANGELES MUNICIPAL SERVICE 01/21 | D1746: -2010.1 | E1746: BILLPAY | F1746: 11453.16
A1747: DEBIT | B1747: 45678 | C1747: UPWORK * -772584884 866-262-4478 CA 01/20 | D1747: -761.25 | E1747: DEBIT_CARD | F1747: 13463.26 | G1747: Upwork - Sergei M.
A1748: DEBIT | B1748: 45678 | C1748: PP*APPLE.COM/BILL 800-275-2273 CA 01/20 | D1748: -8.99 | E1748: DEBIT_CARD | F1748: 14224.51 | G1748: Personal - Subscriptions
A1749: DEBIT | B1749: 45678 | C1749: TST*BLUEYS KITCHEN MAR Los Angeles CA 01/19 | D1749: -96.5 | E1749: DEBIT_CARD | F1749: 14233.5 | G1749: Personal - Food
A1750: DEBIT | B1750: 45678 | C1750: PACIFIC MARINA VENTU BEVERLY HILLS CA 01/19 | D1750: -15 | E1750: DEBIT_CARD | F1750: 14330 | G1750: Personal - Food
A1751: DEBIT | B1751: 45678 | C1751: RESTORE.COM RESTORE.COM TX 01/19 | D1751: -62 | E1751: DEBIT_CARD | F1751: 14345 | G1751: Personal - Health
A1752: DEBIT | B1752: 45678 | C1752: SQ *PAYA THAI LA LLC. LOS ANGELES CA 01/19 | D1752: -150 | E1752: DEBIT_CARD | F1752: 14407 | G1752: Personal - Health
A1753: DEBIT | B1753: 45678 | C1753: PP*APPLE.COM/BILL 800-275-2273 CA 01/20 | D1753: -9.99 | E1753: DEBIT_CARD | F1753: 14557 | G1753: Personal - Subscriptions
A1754: DEBIT | B1754: 45678 | C1754: PAYPAL *BEENVERIFIE 786-482-6776 NY 01/21 | D1754: -26.89 | E1754: DEBIT_CARD | F1754: 14566.99 | G1754: Personal - Subscriptions
A1755: DEBIT | B1755: 45678 | C1755: Online Transfer to CHK ...1117 transaction#: 23439350713 01/21 | D1755: -2000 | E1755: ACCT_XFER | F1755: 14593.88 | G1755: Transfer to Angela Dunning
A1756: DEBIT | B1756: 45678 | C1756: PAYPAL *THEREALDEAL O 212-260-1332 NY 01/20 | D1756: -15 | E1756: DEBIT_CARD | F1756: 16593.88 | G1756: Personal - Subscriptions
A1757: DEBIT | B1757: 45678 | C1757: PAYPAL *ON SPORTSWE R 503-222-0691 OR 01/20 | D1757: -136.87 | E1757: DEBIT_CARD | F1757: 16608.88 | G1757: Personal - Clothing
A1758: DEBIT | B1758: 45678 | C1758: On Sportswear Portland OR 01/19 | D1758: -350.4 | E1758: DEBIT_CARD | F1758: 16745.75 | G1758: Personal - Clothing
... A1850: CREDIT | B1850: 45659 | C1850: FEDWIRE CREDIT VIA: BANK OF AMERICA, N.A./026009593 B/O: CT SOCAL COMM FBSC/CT BS FXBC RIVERSIDE CA 92505 US REF: CHASE NYC/CTR/BNF=DWG CAPITAL GROUP LOS ANGELES CA 90066-3638 US/AC-00 0000002836 RFB=1-18462072 OBI=FN-FB SC2403516 ACQUISITION FEE/AND APPRA ISAL REIMB EDGE BUILDER P/ROP AD DR -1607 PINE ST IMAD: 0102B6B7HU1R020333 TRN: 1195641002FF | D1850: 61037 | E1850: WIRE_INCOMING | F1850: 73545.85 | G1850: Incoming Commission: Edge Builder
