Workbook

Sheet Category Summary
A1: Chase 1168 — DWG Capital Group 2026 Activity
A2: Category Summary | Jan 2026 – Dec 2026
A4: Entity | B4: DWG Capital Group
A5: Account | B5: Business Checking — Chase 1168
A6: Period | B6: Jan 2026 – Dec 2026
A8: TOTALS
A9: Total Inflows | B9: =SUMIFS('Transaction Overview'!$D$2:$D$517,'Transaction Overview'!$D$2:$D$517,">0") -> 1037026.5
A10: Total Outflows | B10: =SUMIFS('Transaction Overview'!$D$2:$D$517,'Transaction Overview'!$D$2:$D$517,"<0") -> -1064698.9
A11: Net Change | B11: =B9+B10 -> -27672.4
A14: Category | B14: Inflows | C14: Outflows | D14: Net
A15: Deal-Specific
A16: Deal Specific: 260 S Hibbert | B16: =SUMIFS('Transaction Overview'!$D$2:$D$517,'Transaction Overview'!$I$2:$I$517,$A16,'Transaction Overview'!$D$2:$D$517,">0") -> 40000 | C16: =SUMIFS('Transaction Overview'!$D$2:$D$517,'Transaction Overview'!$I$2:$I$517,$A16,'Transaction Overview'!$D$2:$D$517,"<0") -> -600 | D16: =B16+C16 -> 39400
A17: Incoming MOAB Mortgage Coverage | B17: =SUMIFS('Transaction Overview'!$D$2:$D$517,'Transaction Overview'!$I$2:$I$517,$A17,'Transaction Overview'!$D$2:$D$517,">0") -> 42782.05 | C17: =SUMIFS('Transaction Overview'!$D$2:$D$517,'Transaction Overview'!$I$2:$I$517,$A17,'Transaction Overview'!$D$2:$D$517,"<0") -> 0 | D17: =B17+C17 -> 42782.05
A18: Moab E4 Mortgage Payment | B18: =SUMIFS('Transaction Overview'!$D$2:$D$517,'Transaction Overview'!$I$2:$I$517,$A18,'Transaction Overview'!$D$2:$D$517,">0") -> 0 | C18: =SUMIFS('Transaction Overview'!$D$2:$D$517,'Transaction Overview'!$I$2:$I$517,$A18,'Transaction Overview'!$D$2:$D$517,"<0") -> -21303.03 | D18: =B18+C18 -> -21303.03
A19: Moab E7 Mortgage Payment | B19: =SUMIFS('Transaction Overview'!$D$2:$D$517,'Transaction Overview'!$I$2:$I$517,$A19,'Transaction Overview'!$D$2:$D$517,">0") -> 0 | C19: =SUMIFS('Transaction Overview'!$D$2:$D$517,'Transaction Overview'!$I$2:$I$517,$A19,'Transaction Overview'!$D$2:$D$517,"<0") -> -21479.02 | D19: =B19+C19 -> -21479.02
A20: Subtotal — Deal-Specific | B20: =SUMIFS('Transaction Overview'!$D$2:$D$517,'Transaction Overview'!$J$2:$J$517,"Deal-Specific",'Transaction Overview'!$D$2:$D$517,">0") -> 82782.05 | C20: =SUMIFS('Transaction Overview'!$D$2:$D$517,'Transaction Overview'!$J$2:$J$517,"Deal-Specific",'Transaction Overview'!$D$2:$D$517,"<0") -> -43382.05 | D20: =B20+C20 -> 39400
A22: Commissions — Incoming
A23: Incoming Commission: MDC | B23: =SUMIFS('Transaction Overview'!$D$2:$D$517,'Transaction Overview'!$I$2:$I$517,$A23,'Transaction Overview'!$D$2:$D$517,">0") -> 114000 | C23: =SUMIFS('Transaction Overview'!$D$2:$D$517,'Transaction Overview'!$I$2:$I$517,$A23,'Transaction Overview'!$D$2:$D$517,"<0") -> 0 | D23: =B23+C23 -> 114000
A24: Subtotal — Commissions — Incoming | B24: =SUMIFS('Transaction Overview'!$D$2:$D$517,'Transaction Overview'!$J$2:$J$517,"Commissions — Incoming",'Transaction Overview'!$D$2:$D$517,">0") -> 114000 | C24: =SUMIFS('Transaction Overview'!$D$2:$D$517,'Transaction Overview'!$J$2:$J$517,"Commissions — Incoming",'Transaction Overview'!$D$2:$D$517,"<0") -> 0 | D24: =B24+C24 -> 114000
A26: Commissions — Outgoing
A27: Hugh Gerhke - MDC Commission | B27: =SUMIFS('Transaction Overview'!$D$2:$D$517,'Transaction Overview'!$I$2:$I$517,$A27,'Transaction Overview'!$D$2:$D$517,">0") -> 0 | C27: =SUMIFS('Transaction Overview'!$D$2:$D$517,'Transaction Overview'!$I$2:$I$517,$A27,'Transaction Overview'!$D$2:$D$517,"<0") -> -16875 | D27: =B27+C27 -> -16875
A28: Meg Maran - MDC Commission | B28: =SUMIFS('Transaction Overview'!$D$2:$D$517,'Transaction Overview'!$I$2:$I$517,$A28,'Transaction Overview'!$D$2:$D$517,">0") -> 0 | C28: =SUMIFS('Transaction Overview'!$D$2:$D$517,'Transaction Overview'!$I$2:$I$517,$A28,'Transaction Overview'!$D$2:$D$517,"<0") -> -1500 | D28: =B28+C28 -> -1500
A29: Subtotal — Commissions — Outgoing | B29: =SUMIFS('Transaction Overview'!$D$2:$D$517,'Transaction Overview'!$J$2:$J$517,"Commissions — Outgoing",'Transaction Overview'!$D$2:$D$517,">0") -> 0 | C29: =SUMIFS('Transaction Overview'!$D$2:$D$517,'Transaction Overview'!$J$2:$J$517,"Commissions — Outgoing",'Transaction Overview'!$D$2:$D$517,"<0") -> -18375 | D29: =B29+C29 -> -18375
A31: MAG Pass-Through
A32: Due to Andrew – MAG Pass-Through 30% | B32: =SUMIFS('Transaction Overview'!$D$2:$D$517,'Transaction Overview'!$I$2:$I$517,$A32,'Transaction Overview'!$D$2:$D$517,">0") -> 0 | C32: =SUMIFS('Transaction Overview'!$D$2:$D$517,'Transaction Overview'!$I$2:$I$517,$A32,'Transaction Overview'!$D$2:$D$517,"<0") -> -177000 | D32: =B32+C32 -> -177000
A33: Due to Dax – MAG Pass-Through 70% | B33: =SUMIFS('Transaction Overview'!$D$2:$D$517,'Transaction Overview'!$I$2:$I$517,$A33,'Transaction Overview'!$D$2:$D$517,">0") -> 0 | C33: =SUMIFS('Transaction Overview'!$D$2:$D$517,'Transaction Overview'!$I$2:$I$517,$A33,'Transaction Overview'!$D$2:$D$517,"<0") -> -413000 | D33: =B33+C33 -> -413000
A34: MAG Capital Partners Pass-Through Wire – 70/30 Split | B34: =SUMIFS('Transaction Overview'!$D$2:$D$517,'Transaction Overview'!$I$2:$I$517,$A34,'Transaction Overview'!$D$2:$D$517,">0") -> 600000 | C34: =SUMIFS('Transaction Overview'!$D$2:$D$517,'Transaction Overview'!$I$2:$I$517,$A34,'Transaction Overview'!$D$2:$D$517,"<0") -> 0 | D34: =B34+C34 -> 600000
A35: Subtotal — MAG Pass-Through | B35: =SUMIFS('Transaction Overview'!$D$2:$D$517,'Transaction Overview'!$J$2:$J$517,"MAG Pass-Through",'Transaction Overview'!$D$2:$D$517,">0") -> 600000 | C35: =SUMIFS('Transaction Overview'!$D$2:$D$517,'Transaction Overview'!$J$2:$J$517,"MAG Pass-Through",'Transaction Overview'!$D$2:$D$517,"<0") -> -590000 | D35: =B35+C35 -> 10000
A37: Poseidon Asset Group
A38: Poseidon Asset Group (Incoming) | B38: =SUMIFS('Transaction Overview'!$D$2:$D$517,'Transaction Overview'!$I$2:$I$517,$A38,'Transaction Overview'!$D$2:$D$517,">0") -> 238556.41 | C38: =SUMIFS('Transaction Overview'!$D$2:$D$517,'Transaction Overview'!$I$2:$I$517,$A38,'Transaction Overview'!$D$2:$D$517,"<0") -> 0 | D38: =B38+C38 -> 238556.41
A39: Poseidon Asset Group (Outgoing) | B39: =SUMIFS('Transaction Overview'!$D$2:$D$517,'Transaction Overview'!$I$2:$I$517,$A39,'Transaction Overview'!$D$2:$D$517,">0") -> 0 | C39: =SUMIFS('Transaction Overview'!$D$2:$D$517,'Transaction Overview'!$I$2:$I$517,$A39,'Transaction Overview'!$D$2:$D$517,"<0") -> -8556.41 | D39: =B39+C39 -> -8556.41
A40: Subtotal — Poseidon Asset Group | B40: =SUMIFS('Transaction Overview'!$D$2:$D$517,'Transaction Overview'!$J$2:$J$517,"Poseidon Asset Group",'Transaction Overview'!$D$2:$D$517,">0") -> 238556.41 | C40: =SUMIFS('Transaction Overview'!$D$2:$D$517,'Transaction Overview'!$J$2:$J$517,"Poseidon Asset Group",'Transaction Overview'!$D$2:$D$517,"<0") -> -8556.41 | D40: =B40+C40 -> 230000
A42: Intercompany & Savings Transfers
A43: Transfer to DWG Capital Group_Costar | B43: =SUMIFS('Transaction Overview'!$D$2:$D$517,'Transaction Overview'!$I$2:$I$517,$A43,'Transaction Overview'!$D$2:$D$517,">0") -> 0 | C43: =SUMIFS('Transaction Overview'!$D$2:$D$517,'Transaction Overview'!$I$2:$I$517,$A43,'Transaction Overview'!$D$2:$D$517,"<0") -> -12956.18 | D43: =B43+C43 -> -12956.18
A44: Transfer to DWG Savings | B44: =SUMIFS('Transaction Overview'!$D$2:$D$517,'Transaction Overview'!$I$2:$I$517,$A44,'Transaction Overview'!$D$2:$D$517,">0") -> 0 | C44: =SUMIFS('Transaction Overview'!$D$2:$D$517,'Transaction Overview'!$I$2:$I$517,$A44,'Transaction Overview'!$D$2:$D$517,"<0") -> -4742 | D44: =B44+C44 -> -4742
A45: Transfer to DWG Capital Partners | B45: =SUMIFS('Transaction Overview'!$D$2:$D$517,'Transaction Overview'!$I$2:$I$517,$A45,'Transaction Overview'!$D$2:$D$517,">0") -> 0 | C45: =SUMIFS('Transaction Overview'!$D$2:$D$517,'Transaction Overview'!$I$2:$I$517,$A45,'Transaction Overview'!$D$2:$D$517,"<0") -> -5000 | D45: =B45+C45 -> -5000
A46: Transfer to DWG Holdings | B46: =SUMIFS('Transaction Overview'!$D$2:$D$517,'Transaction Overview'!$I$2:$I$517,$A46,'Transaction Overview'!$D$2:$D$517,">0") -> 0 | C46: =SUMIFS('Transaction Overview'!$D$2:$D$517,'Transaction Overview'!$I$2:$I$517,$A46,'Transaction Overview'!$D$2:$D$517,"<0") -> -200 | D46: =B46+C46 -> -200
A47: Transfer to Edgebuilders | B47: =SUMIFS('Transaction Overview'!$D$2:$D$517,'Transaction Overview'!$I$2:$I$517,$A47,'Transaction Overview'!$D$2:$D$517,">0") -> 0 | C47: =SUMIFS('Transaction Overview'!$D$2:$D$517,'Transaction Overview'!$I$2:$I$517,$A47,'Transaction Overview'!$D$2:$D$517,"<0") -> -300 | D47: =B47+C47 -> -300
A48: Transfer to Judd Sol Prop | B48: =SUMIFS('Transaction Overview'!$D$2:$D$517,'Transaction Overview'!$I$2:$I$517,$A48,'Transaction Overview'!$D$2:$D$517,">0") -> 0 | C48: =SUMIFS('Transaction Overview'!$D$2:$D$517,'Transaction Overview'!$I$2:$I$517,$A48,'Transaction Overview'!$D$2:$D$517,"<0") -> -200 | D48: =B48+C48 -> -200
A49: Transfer to MRM | B49: =SUMIFS('Transaction Overview'!$D$2:$D$517,'Transaction Overview'!$I$2:$I$517,$A49,'Transaction Overview'!$D$2:$D$517,">0") -> 0 | C49: =SUMIFS('Transaction Overview'!$D$2:$D$517,'Transaction Overview'!$I$2:$I$517,$A49,'Transaction Overview'!$D$2:$D$517,"<0") -> -600 | D49: =B49+C49 -> -600
A50: Transfer to SPF | B50: =SUMIFS('Transaction Overview'!$D$2:$D$517,'Transaction Overview'!$I$2:$I$517,$A50,'Transaction Overview'!$D$2:$D$517,">0") -> 0 | C50: =SUMIFS('Transaction Overview'!$D$2:$D$517,'Transaction Overview'!$I$2:$I$517,$A50,'Transaction Overview'!$D$2:$D$517,"<0") -> -200 | D50: =B50+C50 -> -200
A51: Transfer to TGAIF Fund | B51: =SUMIFS('Transaction Overview'!$D$2:$D$517,'Transaction Overview'!$I$2:$I$517,$A51,'Transaction Overview'!$D$2:$D$517,">0") -> 0 | C51: =SUMIFS('Transaction Overview'!$D$2:$D$517,'Transaction Overview'!$I$2:$I$517,$A51,'Transaction Overview'!$D$2:$D$517,"<0") -> -300 | D51: =B51+C51 -> -300
A52: Transfer to Theut Glass | B52: =SUMIFS('Transaction Overview'!$D$2:$D$517,'Transaction Overview'!$I$2:$I$517,$A52,'Transaction Overview'!$D$2:$D$517,">0") -> 0 | C52: =SUMIFS('Transaction Overview'!$D$2:$D$517,'Transaction Overview'!$I$2:$I$517,$A52,'Transaction Overview'!$D$2:$D$517,"<0") -> -700 | D52: =B52+C52 -> -700
A53: Subtotal — Intercompany & Savings Transfers | B53: =SUMIFS('Transaction Overview'!$D$2:$D$517,'Transaction Overview'!$J$2:$J$517,"Intercompany & Savings Transfers",'Transaction Overview'!$D$2:$D$517,">0") -> 0 | C53: =SUMIFS('Transaction Overview'!$D$2:$D$517,'Transaction Overview'!$J$2:$J$517,"Intercompany & Savings Transfers",'Transaction Overview'!$D$2:$D$517,"<0") -> -25198.18 | D53: =B53+C53 -> -25198.18
A55: Payroll & Contractors
A56: Andres Alarcon Payroll | B56: =SUMIFS('Transaction Overview'!$D$2:$D$517,'Transaction Overview'!$I$2:$I$517,$A56,'Transaction Overview'!$D$2:$D$517,">0") -> 0 | C56: =SUMIFS('Transaction Overview'!$D$2:$D$517,'Transaction Overview'!$I$2:$I$517,$A56,'Transaction Overview'!$D$2:$D$517,"<0") -> -8305 | D56: =B56+C56 -> -8305
A57: Chase Hall - Payroll | B57: =SUMIFS('Transaction Overview'!$D$2:$D$517,'Transaction Overview'!$I$2:$I$517,$A57,'Transaction Overview'!$D$2:$D$517,">0") -> 0 | C57: =SUMIFS('Transaction Overview'!$D$2:$D$517,'Transaction Overview'!$I$2:$I$517,$A57,'Transaction Overview'!$D$2:$D$517,"<0") -> -28000 | D57: =B57+C57 -> -28000
A58: DWG HR | B58: =SUMIFS('Transaction Overview'!$D$2:$D$517,'Transaction Overview'!$I$2:$I$517,$A58,'Transaction Overview'!$D$2:$D$517,">0") -> 0 | C58: =SUMIFS('Transaction Overview'!$D$2:$D$517,'Transaction Overview'!$I$2:$I$517,$A58,'Transaction Overview'!$D$2:$D$517,"<0") -> -1086.31 | D58: =B58+C58 -> -1086.31
A59: Mike Paytonjian - Payroll | B59: =SUMIFS('Transaction Overview'!$D$2:$D$517,'Transaction Overview'!$I$2:$I$517,$A59,'Transaction Overview'!$D$2:$D$517,">0") -> 0 | C59: =SUMIFS('Transaction Overview'!$D$2:$D$517,'Transaction Overview'!$I$2:$I$517,$A59,'Transaction Overview'!$D$2:$D$517,"<0") -> -43250 | D59: =B59+C59 -> -43250
A60: Ruth Alcancia - Forward Bridge Payment | B60: =SUMIFS('Transaction Overview'!$D$2:$D$517,'Transaction Overview'!$I$2:$I$517,$A60,'Transaction Overview'!$D$2:$D$517,">0") -> 0 | C60: =SUMIFS('Transaction Overview'!$D$2:$D$517,'Transaction Overview'!$I$2:$I$517,$A60,'Transaction Overview'!$D$2:$D$517,"<0") -> -4046.7 | D60: =B60+C60 -> -4046.7
A61: Upwork - Sergei M. | B61: =SUMIFS('Transaction Overview'!$D$2:$D$517,'Transaction Overview'!$I$2:$I$517,$A61,'Transaction Overview'!$D$2:$D$517,">0") -> 0 | C61: =SUMIFS('Transaction Overview'!$D$2:$D$517,'Transaction Overview'!$I$2:$I$517,$A61,'Transaction Overview'!$D$2:$D$517,"<0") -> -1627.5 | D61: =B61+C61 -> -1627.5
A62: Subtotal — Payroll & Contractors | B62: =SUMIFS('Transaction Overview'!$D$2:$D$517,'Transaction Overview'!$J$2:$J$517,"Payroll & Contractors",'Transaction Overview'!$D$2:$D$517,">0") -> 0 | C62: =SUMIFS('Transaction Overview'!$D$2:$D$517,'Transaction Overview'!$J$2:$J$517,"Payroll & Contractors",'Transaction Overview'!$D$2:$D$517,"<0") -> -86315.51 | D62: =B62+C62 -> -86315.51
A64: P2P Payments (Zelle/Venmo/PayPal)
A65: PayPal | B65: =SUMIFS('Transaction Overview'!$D$2:$D$517,'Transaction Overview'!$I$2:$I$517,$A65,'Transaction Overview'!$D$2:$D$517,">0") -> 0 | C65: =SUMIFS('Transaction Overview'!$D$2:$D$517,'Transaction Overview'!$I$2:$I$517,$A65,'Transaction Overview'!$D$2:$D$517,"<0") -> -74.02 | D65: =B65+C65 -> -74.02
A66: Venmo | B66: =SUMIFS('Transaction Overview'!$D$2:$D$517,'Transaction Overview'!$I$2:$I$517,$A66,'Transaction Overview'!$D$2:$D$517,">0") -> 0 | C66: =SUMIFS('Transaction Overview'!$D$2:$D$517,'Transaction Overview'!$I$2:$I$517,$A66,'Transaction Overview'!$D$2:$D$517,"<0") -> -17179 | D66: =B66+C66 -> -17179
A67: Zelle - Estella M. | B67: =SUMIFS('Transaction Overview'!$D$2:$D$517,'Transaction Overview'!$I$2:$I$517,$A67,'Transaction Overview'!$D$2:$D$517,">0") -> 0 | C67: =SUMIFS('Transaction Overview'!$D$2:$D$517,'Transaction Overview'!$I$2:$I$517,$A67,'Transaction Overview'!$D$2:$D$517,"<0") -> -3600 | D67: =B67+C67 -> -3600
A68: Zelle - Jared Iorio | B68: =SUMIFS('Transaction Overview'!$D$2:$D$517,'Transaction Overview'!$I$2:$I$517,$A68,'Transaction Overview'!$D$2:$D$517,">0") -> 0 | C68: =SUMIFS('Transaction Overview'!$D$2:$D$517,'Transaction Overview'!$I$2:$I$517,$A68,'Transaction Overview'!$D$2:$D$517,"<0") -> -200 | D68: =B68+C68 -> -200
A69: Zelle - Jeff Seider | B69: =SUMIFS('Transaction Overview'!$D$2:$D$517,'Transaction Overview'!$I$2:$I$517,$A69,'Transaction Overview'!$D$2:$D$517,">0") -> 0 | C69: =SUMIFS('Transaction Overview'!$D$2:$D$517,'Transaction Overview'!$I$2:$I$517,$A69,'Transaction Overview'!$D$2:$D$517,"<0") -> -4600 | D69: =B69+C69 -> -4600
A70: Zelle - Natalie C. | B70: =SUMIFS('Transaction Overview'!$D$2:$D$517,'Transaction Overview'!$I$2:$I$517,$A70,'Transaction Overview'!$D$2:$D$517,">0") -> 0 | C70: =SUMIFS('Transaction Overview'!$D$2:$D$517,'Transaction Overview'!$I$2:$I$517,$A70,'Transaction Overview'!$D$2:$D$517,"<0") -> -2000 | D70: =B70+C70 -> -2000
A71: Zelle/P2P | B71: =SUMIFS('Transaction Overview'!$D$2:$D$517,'Transaction Overview'!$I$2:$I$517,$A71,'Transaction Overview'!$D$2:$D$517,">0") -> 0 | C71: =SUMIFS('Transaction Overview'!$D$2:$D$517,'Transaction Overview'!$I$2:$I$517,$A71,'Transaction Overview'!$D$2:$D$517,"<0") -> -325 | D71: =B71+C71 -> -325
A72: Subtotal — P2P Payments (Zelle/Venmo/PayPal) | B72: =SUMIFS('Transaction Overview'!$D$2:$D$517,'Transaction Overview'!$J$2:$J$517,"P2P Payments (Zelle/Venmo/PayPal)",'Transaction Overview'!$D$2:$D$517,">0") -> 0 | C72: =SUMIFS('Transaction Overview'!$D$2:$D$517,'Transaction Overview'!$J$2:$J$517,"P2P Payments (Zelle/Venmo/PayPal)",'Transaction Overview'!$D$2:$D$517,"<0") -> -27978.02 | D72: =B72+C72 -> -27978.02
A74: Owner / Family Distributions
A75: Transfer to Angela Dunning | B75: =SUMIFS('Transaction Overview'!$D$2:$D$517,'Transaction Overview'!$I$2:$I$517,$A75,'Transaction Overview'!$D$2:$D$517,">0") -> 0 | C75: =SUMIFS('Transaction Overview'!$D$2:$D$517,'Transaction Overview'!$I$2:$I$517,$A75,'Transaction Overview'!$D$2:$D$517,"<0") -> -152700 | D75: =B75+C75 -> -152700
A76: Transfer to Ava Perez-Dunning | B76: =SUMIFS('Transaction Overview'!$D$2:$D$517,'Transaction Overview'!$I$2:$I$517,$A76,'Transaction Overview'!$D$2:$D$517,">0") -> 0 | C76: =SUMIFS('Transaction Overview'!$D$2:$D$517,'Transaction Overview'!$I$2:$I$517,$A76,'Transaction Overview'!$D$2:$D$517,"<0") -> -3200 | D76: =B76+C76 -> -3200
A77: Transfer to TX Personal Joint | B77: =SUMIFS('Transaction Overview'!$D$2:$D$517,'Transaction Overview'!$I$2:$I$517,$A77,'Transaction Overview'!$D$2:$D$517,">0") -> 0 | C77: =SUMIFS('Transaction Overview'!$D$2:$D$517,'Transaction Overview'!$I$2:$I$517,$A77,'Transaction Overview'!$D$2:$D$517,"<0") -> -11000 | D77: =B77+C77 -> -11000
A78: Subtotal — Owner / Family Distributions | B78: =SUMIFS('Transaction Overview'!$D$2:$D$517,'Transaction Overview'!$J$2:$J$517,"Owner / Family Distributions",'Transaction Overview'!$D$2:$D$517,">0") -> 0 | C78: =SUMIFS('Transaction Overview'!$D$2:$D$517,'Transaction Overview'!$J$2:$J$517,"Owner / Family Distributions",'Transaction Overview'!$D$2:$D$517,"<0") -> -166900 | D78: =B78+C78 -> -166900
A80: Credit Card & Loan Payments
A81: Loan/Mortgage | B81: =SUMIFS('Transaction Overview'!$D$2:$D$517,'Transaction Overview'!$I$2:$I$517,$A81,'Transaction Overview'!$D$2:$D$517,">0") -> 0 | C81: =SUMIFS('Transaction Overview'!$D$2:$D$517,'Transaction Overview'!$I$2:$I$517,$A81,'Transaction Overview'!$D$2:$D$517,"<0") -> -331.54 | D81: =B81+C81 -> -331.54
A82: SBC EIDL Loan | B82: =SUMIFS('Transaction Overview'!$D$2:$D$517,'Transaction Overview'!$I$2:$I$517,$A82,'Transaction Overview'!$D$2:$D$517,">0") -> 0 | C82: =SUMIFS('Transaction Overview'!$D$2:$D$517,'Transaction Overview'!$I$2:$I$517,$A82,'Transaction Overview'!$D$2:$D$517,"<0") -> -12620 | D82: =B82+C82 -> -12620
A83: Subtotal — Credit Card & Loan Payments | B83: =SUMIFS('Transaction Overview'!$D$2:$D$517,'Transaction Overview'!$J$2:$J$517,"Credit Card & Loan Payments",'Transaction Overview'!$D$2:$D$517,">0") -> 0 | C83: =SUMIFS('Transaction Overview'!$D$2:$D$517,'Transaction Overview'!$J$2:$J$517,"Credit Card & Loan Payments",'Transaction Overview'!$D$2:$D$517,"<0") -> -12951.54 | D83: =B83+C83 -> -12951.54
A85: Taxes
A86: Taxes | B86: =SUMIFS('Transaction Overview'!$D$2:$D$517,'Transaction Overview'!$I$2:$I$517,$A86,'Transaction Overview'!$D$2:$D$517,">0") -> 0 | C86: =SUMIFS('Transaction Overview'!$D$2:$D$517,'Transaction Overview'!$I$2:$I$517,$A86,'Transaction Overview'!$D$2:$D$517,"<0") -> -860 | D86: =B86+C86 -> -860
A87: Subtotal — Taxes | B87: =SUMIFS('Transaction Overview'!$D$2:$D$517,'Transaction Overview'!$J$2:$J$517,"Taxes",'Transaction Overview'!$D$2:$D$517,">0") -> 0 | C87: =SUMIFS('Transaction Overview'!$D$2:$D$517,'Transaction Overview'!$J$2:$J$517,"Taxes",'Transaction Overview'!$D$2:$D$517,"<0") -> -860 | D87: =B87+C87 -> -860
A89: DWG Operating
A90: AI Subscriptions | B90: =SUMIFS('Transaction Overview'!$D$2:$D$517,'Transaction Overview'!$I$2:$I$517,$A90,'Transaction Overview'!$D$2:$D$517,">0") -> 0 | C90: =SUMIFS('Transaction Overview'!$D$2:$D$517,'Transaction Overview'!$I$2:$I$517,$A90,'Transaction Overview'!$D$2:$D$517,"<0") -> -21.28 | D90: =B90+C90 -> -21.28
A91: Bank Fees | B91: =SUMIFS('Transaction Overview'!$D$2:$D$517,'Transaction Overview'!$I$2:$I$517,$A91,'Transaction Overview'!$D$2:$D$517,">0") -> 0 | C91: =SUMIFS('Transaction Overview'!$D$2:$D$517,'Transaction Overview'!$I$2:$I$517,$A91,'Transaction Overview'!$D$2:$D$517,"<0") -> -264.05 | D91: =B91+C91 -> -264.05
A92: Bill Payment | B92: =SUMIFS('Transaction Overview'!$D$2:$D$517,'Transaction Overview'!$I$2:$I$517,$A92,'Transaction Overview'!$D$2:$D$517,">0") -> 0 | C92: =SUMIFS('Transaction Overview'!$D$2:$D$517,'Transaction Overview'!$I$2:$I$517,$A92,'Transaction Overview'!$D$2:$D$517,"<0") -> -1800 | D92: =B92+C92 -> -1800
A93: DWG Marketing | B93: =SUMIFS('Transaction Overview'!$D$2:$D$517,'Transaction Overview'!$I$2:$I$517,$A93,'Transaction Overview'!$D$2:$D$517,">0") -> 0 | C93: =SUMIFS('Transaction Overview'!$D$2:$D$517,'Transaction Overview'!$I$2:$I$517,$A93,'Transaction Overview'!$D$2:$D$517,"<0") -> -520.05 | D93: =B93+C93 -> -520.05
A94: DWGCP Business Development | B94: =SUMIFS('Transaction Overview'!$D$2:$D$517,'Transaction Overview'!$I$2:$I$517,$A94,'Transaction Overview'!$D$2:$D$517,">0") -> 0 | C94: =SUMIFS('Transaction Overview'!$D$2:$D$517,'Transaction Overview'!$I$2:$I$517,$A94,'Transaction Overview'!$D$2:$D$517,"<0") -> -64.68 | D94: =B94+C94 -> -64.68
A95: Go Daddy | B95: =SUMIFS('Transaction Overview'!$D$2:$D$517,'Transaction Overview'!$I$2:$I$517,$A95,'Transaction Overview'!$D$2:$D$517,">0") -> 0 | C95: =SUMIFS('Transaction Overview'!$D$2:$D$517,'Transaction Overview'!$I$2:$I$517,$A95,'Transaction Overview'!$D$2:$D$517,"<0") -> -3951.77 | D95: =B95+C95 -> -3951.77
A96: Office/Miscellaneous Reimbursement - Mike P. | B96: =SUMIFS('Transaction Overview'!$D$2:$D$517,'Transaction Overview'!$I$2:$I$517,$A96,'Transaction Overview'!$D$2:$D$517,">0") -> 0 | C96: =SUMIFS('Transaction Overview'!$D$2:$D$517,'Transaction Overview'!$I$2:$I$517,$A96,'Transaction Overview'!$D$2:$D$517,"<0") -> -288 | D96: =B96+C96 -> -288
A97: Software/Accounting | B97: =SUMIFS('Transaction Overview'!$D$2:$D$517,'Transaction Overview'!$I$2:$I$517,$A97,'Transaction Overview'!$D$2:$D$517,">0") -> 0 | C97: =SUMIFS('Transaction Overview'!$D$2:$D$517,'Transaction Overview'!$I$2:$I$517,$A97,'Transaction Overview'!$D$2:$D$517,"<0") -> -606.05 | D97: =B97+C97 -> -606.05
A98: Team Lunch | B98: =SUMIFS('Transaction Overview'!$D$2:$D$517,'Transaction Overview'!$I$2:$I$517,$A98,'Transaction Overview'!$D$2:$D$517,">0") -> 0 | C98: =SUMIFS('Transaction Overview'!$D$2:$D$517,'Transaction Overview'!$I$2:$I$517,$A98,'Transaction Overview'!$D$2:$D$517,"<0") -> -112.43 | D98: =B98+C98 -> -112.43
A99: Wire Fee | B99: =SUMIFS('Transaction Overview'!$D$2:$D$517,'Transaction Overview'!$I$2:$I$517,$A99,'Transaction Overview'!$D$2:$D$517,">0") -> 0 | C99: =SUMIFS('Transaction Overview'!$D$2:$D$517,'Transaction Overview'!$I$2:$I$517,$A99,'Transaction Overview'!$D$2:$D$517,"<0") -> -90 | D99: =B99+C99 -> -90
A100: Subtotal — DWG Operating | B100: =SUMIFS('Transaction Overview'!$D$2:$D$517,'Transaction Overview'!$J$2:$J$517,"DWG Operating",'Transaction Overview'!$D$2:$D$517,">0") -> 0 | C100: =SUMIFS('Transaction Overview'!$D$2:$D$517,'Transaction Overview'!$J$2:$J$517,"DWG Operating",'Transaction Overview'!$D$2:$D$517,"<0") -> -7718.31 | D100: =B100+C100 -> -7718.31
A102: Business Travel
A103: Employee Travel Reimbursement | B103: =SUMIFS('Transaction Overview'!$D$2:$D$517,'Transaction Overview'!$I$2:$I$517,$A103,'Transaction Overview'!$D$2:$D$517,">0") -> 0 | C103: =SUMIFS('Transaction Overview'!$D$2:$D$517,'Transaction Overview'!$I$2:$I$517,$A103,'Transaction Overview'!$D$2:$D$517,"<0") -> -166.74 | D103: =B103+C103 -> -166.74
A104: Team Travel - Reimbursement | B104: =SUMIFS('Transaction Overview'!$D$2:$D$517,'Transaction Overview'!$I$2:$I$517,$A104,'Transaction Overview'!$D$2:$D$517,">0") -> 0 | C104: =SUMIFS('Transaction Overview'!$D$2:$D$517,'Transaction Overview'!$I$2:$I$517,$A104,'Transaction Overview'!$D$2:$D$517,"<0") -> -315 | D104: =B104+C104 -> -315
A105: Subtotal — Business Travel | B105: =SUMIFS('Transaction Overview'!$D$2:$D$517,'Transaction Overview'!$J$2:$J$517,"Business Travel",'Transaction Overview'!$D$2:$D$517,">0") -> 0 | C105: =SUMIFS('Transaction Overview'!$D$2:$D$517,'Transaction Overview'!$J$2:$J$517,"Business Travel",'Transaction Overview'!$D$2:$D$517,"<0") -> -481.74 | D105: =B105+C105 -> -481.74
A107: Personal — Owner
A108: Personal - Life Insurance | B108: =SUMIFS('Transaction Overview'!$D$2:$D$517,'Transaction Overview'!$I$2:$I$517,$A108,'Transaction Overview'!$D$2:$D$517,">0") -> 0 | C108: =SUMIFS('Transaction Overview'!$D$2:$D$517,'Transaction Overview'!$I$2:$I$517,$A108,'Transaction Overview'!$D$2:$D$517,"<0") -> -519.52 | D108: =B108+C108 -> -519.52
A109: Personal - Food & Dining | B109: =SUMIFS('Transaction Overview'!$D$2:$D$517,'Transaction Overview'!$I$2:$I$517,$A109,'Transaction Overview'!$D$2:$D$517,">0") -> 0 | C109: =SUMIFS('Transaction Overview'!$D$2:$D$517,'Transaction Overview'!$I$2:$I$517,$A109,'Transaction Overview'!$D$2:$D$517,"<0") -> -148.55 | D109: =B109+C109 -> -148.55
A110: Personal - California Mortgage PMT | B110: =SUMIFS('Transaction Overview'!$D$2:$D$517,'Transaction Overview'!$I$2:$I$517,$A110,'Transaction Overview'!$D$2:$D$517,">0") -> 0 | C110: =SUMIFS('Transaction Overview'!$D$2:$D$517,'Transaction Overview'!$I$2:$I$517,$A110,'Transaction Overview'!$D$2:$D$517,"<0") -> -28400 | D110: =B110+C110 -> -28400
A111: Personal - Car & Auto | B111: =SUMIFS('Transaction Overview'!$D$2:$D$517,'Transaction Overview'!$I$2:$I$517,$A111,'Transaction Overview'!$D$2:$D$517,">0") -> 0 | C111: =SUMIFS('Transaction Overview'!$D$2:$D$517,'Transaction Overview'!$I$2:$I$517,$A111,'Transaction Overview'!$D$2:$D$517,"<0") -> -27303.4 | D111: =B111+C111 -> -27303.4
A112: Personal - Entertainment | B112: =SUMIFS('Transaction Overview'!$D$2:$D$517,'Transaction Overview'!$I$2:$I$517,$A112,'Transaction Overview'!$D$2:$D$517,">0") -> 0 | C112: =SUMIFS('Transaction Overview'!$D$2:$D$517,'Transaction Overview'!$I$2:$I$517,$A112,'Transaction Overview'!$D$2:$D$517,"<0") -> -41.99 | D112: =B112+C112 -> -41.99
A113: Personal - Health (incl. Ins.) | B113: =SUMIFS('Transaction Overview'!$D$2:$D$517,'Transaction Overview'!$I$2:$I$517,$A113,'Transaction Overview'!$D$2:$D$517,">0") -> 0 | C113: =SUMIFS('Transaction Overview'!$D$2:$D$517,'Transaction Overview'!$I$2:$I$517,$A113,'Transaction Overview'!$D$2:$D$517,"<0") -> -14380.81 | D113: =B113+C113 -> -14380.81
A114: Personal - Paypal | B114: =SUMIFS('Transaction Overview'!$D$2:$D$517,'Transaction Overview'!$I$2:$I$517,$A114,'Transaction Overview'!$D$2:$D$517,">0") -> 0 | C114: =SUMIFS('Transaction Overview'!$D$2:$D$517,'Transaction Overview'!$I$2:$I$517,$A114,'Transaction Overview'!$D$2:$D$517,"<0") -> -203.2 | D114: =B114+C114 -> -203.2
A115: Personal - Subscriptions | B115: =SUMIFS('Transaction Overview'!$D$2:$D$517,'Transaction Overview'!$I$2:$I$517,$A115,'Transaction Overview'!$D$2:$D$517,">0") -> 0 | C115: =SUMIFS('Transaction Overview'!$D$2:$D$517,'Transaction Overview'!$I$2:$I$517,$A115,'Transaction Overview'!$D$2:$D$517,"<0") -> -424.18 | D115: =B115+C115 -> -424.18
A116: Texas - House Utilities | B116: =SUMIFS('Transaction Overview'!$D$2:$D$517,'Transaction Overview'!$I$2:$I$517,$A116,'Transaction Overview'!$D$2:$D$517,">0") -> 0 | C116: =SUMIFS('Transaction Overview'!$D$2:$D$517,'Transaction Overview'!$I$2:$I$517,$A116,'Transaction Overview'!$D$2:$D$517,"<0") -> -1028.33 | D116: =B116+C116 -> -1028.33
A117: Subtotal — Personal — Owner | B117: =SUMIFS('Transaction Overview'!$D$2:$D$517,'Transaction Overview'!$J$2:$J$517,"Personal — Owner",'Transaction Overview'!$D$2:$D$517,">0") -> 0 | C117: =SUMIFS('Transaction Overview'!$D$2:$D$517,'Transaction Overview'!$J$2:$J$517,"Personal — Owner",'Transaction Overview'!$D$2:$D$517,"<0") -> -72449.98 | D117: =B117+C117 -> -72449.98
...

Sheet Monthly Breakdown
A1: Chase 1168 — DWG Capital Group 2026 Activity
A2: Monthly Breakdown | Jan 2026 – Dec 2026
A4: Category | B4: =DATE(2026,1,1) -> 46023 | C4: =DATE(2026,2,1) -> 46054 | D4: =DATE(2026,3,1) -> 46082 | E4: =DATE(2026,4,1) -> 46113 | F4: =DATE(2026,5,1) -> 46143 | G4: =DATE(2026,6,1) -> 46174 | H4: =DATE(2026,7,1) -> 46204 | I4: =DATE(2026,8,1) -> 46235 | J4: =DATE(2026,9,1) -> 46266 | K4: =DATE(2026,10,1) -> 46296 | L4: =DATE(2026,11,1) -> 46327 | M4: =DATE(2026,12,1) -> 46357 | N4: Total
A5: Deal-Specific
A6: Deal Specific: 260 S Hibbert | B6: =SUMIFS('Transaction Overview'!$D$2:$D$517,'Transaction Overview'!$I$2:$I$517,$A6,'Transaction Overview'!$H$2:$H$517,B$4) -> 0 | C6: =SUMIFS('Transaction Overview'!$D$2:$D$517,'Transaction Overview'!$I$2:$I$517,$A6,'Transaction Overview'!$H$2:$H$517,C$4) -> 20000 | D6: =SUMIFS('Transaction Overview'!$D$2:$D$517,'Transaction Overview'!$I$2:$I$517,$A6,'Transaction Overview'!$H$2:$H$517,D$4) -> 19400 | E6: =SUMIFS('Transaction Overview'!$D$2:$D$517,'Transaction Overview'!$I$2:$I$517,$A6,'Transaction Overview'!$H$2:$H$517,E$4) -> 0 | F6: =SUMIFS('Transaction Overview'!$D$2:$D$517,'Transaction Overview'!$I$2:$I$517,$A6,'Transaction Overview'!$H$2:$H$517,F$4) -> 0 | G6: =SUMIFS('Transaction Overview'!$D$2:$D$517,'Transaction Overview'!$I$2:$I$517,$A6,'Transaction Overview'!$H$2:$H$517,G$4) -> 0 | H6: =SUMIFS('Transaction Overview'!$D$2:$D$517,'Transaction Overview'!$I$2:$I$517,$A6,'Transaction Overview'!$H$2:$H$517,H$4) -> 0 | I6: =SUMIFS('Transaction Overview'!$D$2:$D$517,'Transaction Overview'!$I$2:$I$517,$A6,'Transaction Overview'!$H$2:$H$517,I$4) -> 0 | ... M6: =SUMIFS('Transaction Overview'!$D$2:$D$517,'Transaction Overview'!$I$2:$I$517,$A6,'Transaction Overview'!$H$2:$H$517,M$4) -> 0 | N6: =SUM(B6:M6) -> 39400
A7: Incoming MOAB Mortgage Coverage | B7: =SUMIFS('Transaction Overview'!$D$2:$D$517,'Transaction Overview'!$I$2:$I$517,$A7,'Transaction Overview'!$H$2:$H$517,B$4) -> 0 | C7: =SUMIFS('Transaction Overview'!$D$2:$D$517,'Transaction Overview'!$I$2:$I$517,$A7,'Transaction Overview'!$H$2:$H$517,C$4) -> 8556.41 | D7: =SUMIFS('Transaction Overview'!$D$2:$D$517,'Transaction Overview'!$I$2:$I$517,$A7,'Transaction Overview'!$H$2:$H$517,D$4) -> 8556.41 | E7: =SUMIFS('Transaction Overview'!$D$2:$D$517,'Transaction Overview'!$I$2:$I$517,$A7,'Transaction Overview'!$H$2:$H$517,E$4) -> 8556.41 | F7: =SUMIFS('Transaction Overview'!$D$2:$D$517,'Transaction Overview'!$I$2:$I$517,$A7,'Transaction Overview'!$H$2:$H$517,F$4) -> 8556.41 | G7: =SUMIFS('Transaction Overview'!$D$2:$D$517,'Transaction Overview'!$I$2:$I$517,$A7,'Transaction Overview'!$H$2:$H$517,G$4) -> 8556.41 | H7: =SUMIFS('Transaction Overview'!$D$2:$D$517,'Transaction Overview'!$I$2:$I$517,$A7,'Transaction Overview'!$H$2:$H$517,H$4) -> 0 | I7: =SUMIFS('Transaction Overview'!$D$2:$D$517,'Transaction Overview'!$I$2:$I$517,$A7,'Transaction Overview'!$H$2:$H$517,I$4) -> 0 | ... M7: =SUMIFS('Transaction Overview'!$D$2:$D$517,'Transaction Overview'!$I$2:$I$517,$A7,'Transaction Overview'!$H$2:$H$517,M$4) -> 0 | N7: =SUM(B7:M7) -> 42782.05
A8: Moab E4 Mortgage Payment | B8: =SUMIFS('Transaction Overview'!$D$2:$D$517,'Transaction Overview'!$I$2:$I$517,$A8,'Transaction Overview'!$H$2:$H$517,B$4) -> 0 | C8: =SUMIFS('Transaction Overview'!$D$2:$D$517,'Transaction Overview'!$I$2:$I$517,$A8,'Transaction Overview'!$H$2:$H$517,C$4) -> -4190.21 | D8: =SUMIFS('Transaction Overview'!$D$2:$D$517,'Transaction Overview'!$I$2:$I$517,$A8,'Transaction Overview'!$H$2:$H$517,D$4) -> -4190.21 | E8: =SUMIFS('Transaction Overview'!$D$2:$D$517,'Transaction Overview'!$I$2:$I$517,$A8,'Transaction Overview'!$H$2:$H$517,E$4) -> -4190.21 | F8: =SUMIFS('Transaction Overview'!$D$2:$D$517,'Transaction Overview'!$I$2:$I$517,$A8,'Transaction Overview'!$H$2:$H$517,F$4) -> -4366.2 | G8: =SUMIFS('Transaction Overview'!$D$2:$D$517,'Transaction Overview'!$I$2:$I$517,$A8,'Transaction Overview'!$H$2:$H$517,G$4) -> -4366.2 | H8: =SUMIFS('Transaction Overview'!$D$2:$D$517,'Transaction Overview'!$I$2:$I$517,$A8,'Transaction Overview'!$H$2:$H$517,H$4) -> 0 | I8: =SUMIFS('Transaction Overview'!$D$2:$D$517,'Transaction Overview'!$I$2:$I$517,$A8,'Transaction Overview'!$H$2:$H$517,I$4) -> 0 | ... M8: =SUMIFS('Transaction Overview'!$D$2:$D$517,'Transaction Overview'!$I$2:$I$517,$A8,'Transaction Overview'!$H$2:$H$517,M$4) -> 0 | N8: =SUM(B8:M8) -> -21303.03
A9: Moab E7 Mortgage Payment | B9: =SUMIFS('Transaction Overview'!$D$2:$D$517,'Transaction Overview'!$I$2:$I$517,$A9,'Transaction Overview'!$H$2:$H$517,B$4) -> 0 | C9: =SUMIFS('Transaction Overview'!$D$2:$D$517,'Transaction Overview'!$I$2:$I$517,$A9,'Transaction Overview'!$H$2:$H$517,C$4) -> -4366.2 | D9: =SUMIFS('Transaction Overview'!$D$2:$D$517,'Transaction Overview'!$I$2:$I$517,$A9,'Transaction Overview'!$H$2:$H$517,D$4) -> -4366.2 | E9: =SUMIFS('Transaction Overview'!$D$2:$D$517,'Transaction Overview'!$I$2:$I$517,$A9,'Transaction Overview'!$H$2:$H$517,E$4) -> -4366.2 | F9: =SUMIFS('Transaction Overview'!$D$2:$D$517,'Transaction Overview'!$I$2:$I$517,$A9,'Transaction Overview'!$H$2:$H$517,F$4) -> -4190.21 | G9: =SUMIFS('Transaction Overview'!$D$2:$D$517,'Transaction Overview'!$I$2:$I$517,$A9,'Transaction Overview'!$H$2:$H$517,G$4) -> -4190.21 | H9: =SUMIFS('Transaction Overview'!$D$2:$D$517,'Transaction Overview'!$I$2:$I$517,$A9,'Transaction Overview'!$H$2:$H$517,H$4) -> 0 | I9: =SUMIFS('Transaction Overview'!$D$2:$D$517,'Transaction Overview'!$I$2:$I$517,$A9,'Transaction Overview'!$H$2:$H$517,I$4) -> 0 | ... M9: =SUMIFS('Transaction Overview'!$D$2:$D$517,'Transaction Overview'!$I$2:$I$517,$A9,'Transaction Overview'!$H$2:$H$517,M$4) -> 0 | N9: =SUM(B9:M9) -> -21479.02
A10: Commissions — Incoming
A11: Incoming Commission: MDC | B11: =SUMIFS('Transaction Overview'!$D$2:$D$517,'Transaction Overview'!$I$2:$I$517,$A11,'Transaction Overview'!$H$2:$H$517,B$4) -> 0 | C11: =SUMIFS('Transaction Overview'!$D$2:$D$517,'Transaction Overview'!$I$2:$I$517,$A11,'Transaction Overview'!$H$2:$H$517,C$4) -> 0 | D11: =SUMIFS('Transaction Overview'!$D$2:$D$517,'Transaction Overview'!$I$2:$I$517,$A11,'Transaction Overview'!$H$2:$H$517,D$4) -> 0 | E11: =SUMIFS('Transaction Overview'!$D$2:$D$517,'Transaction Overview'!$I$2:$I$517,$A11,'Transaction Overview'!$H$2:$H$517,E$4) -> 0 | F11: =SUMIFS('Transaction Overview'!$D$2:$D$517,'Transaction Overview'!$I$2:$I$517,$A11,'Transaction Overview'!$H$2:$H$517,F$4) -> 114000 | G11: =SUMIFS('Transaction Overview'!$D$2:$D$517,'Transaction Overview'!$I$2:$I$517,$A11,'Transaction Overview'!$H$2:$H$517,G$4) -> 0 | H11: =SUMIFS('Transaction Overview'!$D$2:$D$517,'Transaction Overview'!$I$2:$I$517,$A11,'Transaction Overview'!$H$2:$H$517,H$4) -> 0 | I11: =SUMIFS('Transaction Overview'!$D$2:$D$517,'Transaction Overview'!$I$2:$I$517,$A11,'Transaction Overview'!$H$2:$H$517,I$4) -> 0 | ... M11: =SUMIFS('Transaction Overview'!$D$2:$D$517,'Transaction Overview'!$I$2:$I$517,$A11,'Transaction Overview'!$H$2:$H$517,M$4) -> 0 | N11: =SUM(B11:M11) -> 114000
A12: Commissions — Outgoing
A13: Hugh Gerhke - MDC Commission | B13: =SUMIFS('Transaction Overview'!$D$2:$D$517,'Transaction Overview'!$I$2:$I$517,$A13,'Transaction Overview'!$H$2:$H$517,B$4) -> 0 | C13: =SUMIFS('Transaction Overview'!$D$2:$D$517,'Transaction Overview'!$I$2:$I$517,$A13,'Transaction Overview'!$H$2:$H$517,C$4) -> 0 | D13: =SUMIFS('Transaction Overview'!$D$2:$D$517,'Transaction Overview'!$I$2:$I$517,$A13,'Transaction Overview'!$H$2:$H$517,D$4) -> 0 | E13: =SUMIFS('Transaction Overview'!$D$2:$D$517,'Transaction Overview'!$I$2:$I$517,$A13,'Transaction Overview'!$H$2:$H$517,E$4) -> 0 | F13: =SUMIFS('Transaction Overview'!$D$2:$D$517,'Transaction Overview'!$I$2:$I$517,$A13,'Transaction Overview'!$H$2:$H$517,F$4) -> -16875 | G13: =SUMIFS('Transaction Overview'!$D$2:$D$517,'Transaction Overview'!$I$2:$I$517,$A13,'Transaction Overview'!$H$2:$H$517,G$4) -> 0 | H13: =SUMIFS('Transaction Overview'!$D$2:$D$517,'Transaction Overview'!$I$2:$I$517,$A13,'Transaction Overview'!$H$2:$H$517,H$4) -> 0 | I13: =SUMIFS('Transaction Overview'!$D$2:$D$517,'Transaction Overview'!$I$2:$I$517,$A13,'Transaction Overview'!$H$2:$H$517,I$4) -> 0 | ... M13: =SUMIFS('Transaction Overview'!$D$2:$D$517,'Transaction Overview'!$I$2:$I$517,$A13,'Transaction Overview'!$H$2:$H$517,M$4) -> 0 | N13: =SUM(B13:M13) -> -16875
A14: Meg Maran - MDC Commission | B14: =SUMIFS('Transaction Overview'!$D$2:$D$517,'Transaction Overview'!$I$2:$I$517,$A14,'Transaction Overview'!$H$2:$H$517,B$4) -> 0 | C14: =SUMIFS('Transaction Overview'!$D$2:$D$517,'Transaction Overview'!$I$2:$I$517,$A14,'Transaction Overview'!$H$2:$H$517,C$4) -> 0 | D14: =SUMIFS('Transaction Overview'!$D$2:$D$517,'Transaction Overview'!$I$2:$I$517,$A14,'Transaction Overview'!$H$2:$H$517,D$4) -> 0 | E14: =SUMIFS('Transaction Overview'!$D$2:$D$517,'Transaction Overview'!$I$2:$I$517,$A14,'Transaction Overview'!$H$2:$H$517,E$4) -> 0 | F14: =SUMIFS('Transaction Overview'!$D$2:$D$517,'Transaction Overview'!$I$2:$I$517,$A14,'Transaction Overview'!$H$2:$H$517,F$4) -> -1500 | G14: =SUMIFS('Transaction Overview'!$D$2:$D$517,'Transaction Overview'!$I$2:$I$517,$A14,'Transaction Overview'!$H$2:$H$517,G$4) -> 0 | H14: =SUMIFS('Transaction Overview'!$D$2:$D$517,'Transaction Overview'!$I$2:$I$517,$A14,'Transaction Overview'!$H$2:$H$517,H$4) -> 0 | I14: =SUMIFS('Transaction Overview'!$D$2:$D$517,'Transaction Overview'!$I$2:$I$517,$A14,'Transaction Overview'!$H$2:$H$517,I$4) -> 0 | ... M14: =SUMIFS('Transaction Overview'!$D$2:$D$517,'Transaction Overview'!$I$2:$I$517,$A14,'Transaction Overview'!$H$2:$H$517,M$4) -> 0 | N14: =SUM(B14:M14) -> -1500
A15: MAG Pass-Through
A16: Due to Andrew – MAG Pass-Through 30% | B16: =SUMIFS('Transaction Overview'!$D$2:$D$517,'Transaction Overview'!$I$2:$I$517,$A16,'Transaction Overview'!$H$2:$H$517,B$4) -> 0 | C16: =SUMIFS('Transaction Overview'!$D$2:$D$517,'Transaction Overview'!$I$2:$I$517,$A16,'Transaction Overview'!$H$2:$H$517,C$4) -> -177000 | D16: =SUMIFS('Transaction Overview'!$D$2:$D$517,'Transaction Overview'!$I$2:$I$517,$A16,'Transaction Overview'!$H$2:$H$517,D$4) -> 0 | E16: =SUMIFS('Transaction Overview'!$D$2:$D$517,'Transaction Overview'!$I$2:$I$517,$A16,'Transaction Overview'!$H$2:$H$517,E$4) -> 0 | F16: =SUMIFS('Transaction Overview'!$D$2:$D$517,'Transaction Overview'!$I$2:$I$517,$A16,'Transaction Overview'!$H$2:$H$517,F$4) -> 0 | G16: =SUMIFS('Transaction Overview'!$D$2:$D$517,'Transaction Overview'!$I$2:$I$517,$A16,'Transaction Overview'!$H$2:$H$517,G$4) -> 0 | H16: =SUMIFS('Transaction Overview'!$D$2:$D$517,'Transaction Overview'!$I$2:$I$517,$A16,'Transaction Overview'!$H$2:$H$517,H$4) -> 0 | I16: =SUMIFS('Transaction Overview'!$D$2:$D$517,'Transaction Overview'!$I$2:$I$517,$A16,'Transaction Overview'!$H$2:$H$517,I$4) -> 0 | ... M16: =SUMIFS('Transaction Overview'!$D$2:$D$517,'Transaction Overview'!$I$2:$I$517,$A16,'Transaction Overview'!$H$2:$H$517,M$4) -> 0 | N16: =SUM(B16:M16) -> -177000
A17: Due to Dax – MAG Pass-Through 70% | B17: =SUMIFS('Transaction Overview'!$D$2:$D$517,'Transaction Overview'!$I$2:$I$517,$A17,'Transaction Overview'!$H$2:$H$517,B$4) -> 0 | C17: =SUMIFS('Transaction Overview'!$D$2:$D$517,'Transaction Overview'!$I$2:$I$517,$A17,'Transaction Overview'!$H$2:$H$517,C$4) -> -413000 | D17: =SUMIFS('Transaction Overview'!$D$2:$D$517,'Transaction Overview'!$I$2:$I$517,$A17,'Transaction Overview'!$H$2:$H$517,D$4) -> 0 | E17: =SUMIFS('Transaction Overview'!$D$2:$D$517,'Transaction Overview'!$I$2:$I$517,$A17,'Transaction Overview'!$H$2:$H$517,E$4) -> 0 | F17: =SUMIFS('Transaction Overview'!$D$2:$D$517,'Transaction Overview'!$I$2:$I$517,$A17,'Transaction Overview'!$H$2:$H$517,F$4) -> 0 | G17: =SUMIFS('Transaction Overview'!$D$2:$D$517,'Transaction Overview'!$I$2:$I$517,$A17,'Transaction Overview'!$H$2:$H$517,G$4) -> 0 | H17: =SUMIFS('Transaction Overview'!$D$2:$D$517,'Transaction Overview'!$I$2:$I$517,$A17,'Transaction Overview'!$H$2:$H$517,H$4) -> 0 | I17: =SUMIFS('Transaction Overview'!$D$2:$D$517,'Transaction Overview'!$I$2:$I$517,$A17,'Transaction Overview'!$H$2:$H$517,I$4) -> 0 | ... M17: =SUMIFS('Transaction Overview'!$D$2:$D$517,'Transaction Overview'!$I$2:$I$517,$A17,'Transaction Overview'!$H$2:$H$517,M$4) -> 0 | N17: =SUM(B17:M17) -> -413000
A18: MAG Capital Partners Pass-Through Wire – 70/30 Split | B18: =SUMIFS('Transaction Overview'!$D$2:$D$517,'Transaction Overview'!$I$2:$I$517,$A18,'Transaction Overview'!$H$2:$H$517,B$4) -> 0 | C18: =SUMIFS('Transaction Overview'!$D$2:$D$517,'Transaction Overview'!$I$2:$I$517,$A18,'Transaction Overview'!$H$2:$H$517,C$4) -> 600000 | D18: =SUMIFS('Transaction Overview'!$D$2:$D$517,'Transaction Overview'!$I$2:$I$517,$A18,'Transaction Overview'!$H$2:$H$517,D$4) -> 0 | E18: =SUMIFS('Transaction Overview'!$D$2:$D$517,'Transaction Overview'!$I$2:$I$517,$A18,'Transaction Overview'!$H$2:$H$517,E$4) -> 0 | F18: =SUMIFS('Transaction Overview'!$D$2:$D$517,'Transaction Overview'!$I$2:$I$517,$A18,'Transaction Overview'!$H$2:$H$517,F$4) -> 0 | G18: =SUMIFS('Transaction Overview'!$D$2:$D$517,'Transaction Overview'!$I$2:$I$517,$A18,'Transaction Overview'!$H$2:$H$517,G$4) -> 0 | H18: =SUMIFS('Transaction Overview'!$D$2:$D$517,'Transaction Overview'!$I$2:$I$517,$A18,'Transaction Overview'!$H$2:$H$517,H$4) -> 0 | I18: =SUMIFS('Transaction Overview'!$D$2:$D$517,'Transaction Overview'!$I$2:$I$517,$A18,'Transaction Overview'!$H$2:$H$517,I$4) -> 0 | ... M18: =SUMIFS('Transaction Overview'!$D$2:$D$517,'Transaction Overview'!$I$2:$I$517,$A18,'Transaction Overview'!$H$2:$H$517,M$4) -> 0 | N18: =SUM(B18:M18) -> 600000
A19: Poseidon Asset Group
A20: Poseidon Asset Group (Incoming) | B20: =SUMIFS('Transaction Overview'!$D$2:$D$517,'Transaction Overview'!$I$2:$I$517,$A20,'Transaction Overview'!$H$2:$H$517,B$4) -> 70000 | C20: =SUMIFS('Transaction Overview'!$D$2:$D$517,'Transaction Overview'!$I$2:$I$517,$A20,'Transaction Overview'!$H$2:$H$517,C$4) -> 48556.41 | D20: =SUMIFS('Transaction Overview'!$D$2:$D$517,'Transaction Overview'!$I$2:$I$517,$A20,'Transaction Overview'!$H$2:$H$517,D$4) -> 55000 | E20: =SUMIFS('Transaction Overview'!$D$2:$D$517,'Transaction Overview'!$I$2:$I$517,$A20,'Transaction Overview'!$H$2:$H$517,E$4) -> 35000 | F20: =SUMIFS('Transaction Overview'!$D$2:$D$517,'Transaction Overview'!$I$2:$I$517,$A20,'Transaction Overview'!$H$2:$H$517,F$4) -> 0 | G20: =SUMIFS('Transaction Overview'!$D$2:$D$517,'Transaction Overview'!$I$2:$I$517,$A20,'Transaction Overview'!$H$2:$H$517,G$4) -> 30000 | H20: =SUMIFS('Transaction Overview'!$D$2:$D$517,'Transaction Overview'!$I$2:$I$517,$A20,'Transaction Overview'!$H$2:$H$517,H$4) -> 0 | I20: =SUMIFS('Transaction Overview'!$D$2:$D$517,'Transaction Overview'!$I$2:$I$517,$A20,'Transaction Overview'!$H$2:$H$517,I$4) -> 0 | ... M20: =SUMIFS('Transaction Overview'!$D$2:$D$517,'Transaction Overview'!$I$2:$I$517,$A20,'Transaction Overview'!$H$2:$H$517,M$4) -> 0 | N20: =SUM(B20:M20) -> 238556.41
A21: Poseidon Asset Group (Outgoing) | B21: =SUMIFS('Transaction Overview'!$D$2:$D$517,'Transaction Overview'!$I$2:$I$517,$A21,'Transaction Overview'!$H$2:$H$517,B$4) -> 0 | C21: =SUMIFS('Transaction Overview'!$D$2:$D$517,'Transaction Overview'!$I$2:$I$517,$A21,'Transaction Overview'!$H$2:$H$517,C$4) -> -8556.41 | D21: =SUMIFS('Transaction Overview'!$D$2:$D$517,'Transaction Overview'!$I$2:$I$517,$A21,'Transaction Overview'!$H$2:$H$517,D$4) -> 0 | E21: =SUMIFS('Transaction Overview'!$D$2:$D$517,'Transaction Overview'!$I$2:$I$517,$A21,'Transaction Overview'!$H$2:$H$517,E$4) -> 0 | F21: =SUMIFS('Transaction Overview'!$D$2:$D$517,'Transaction Overview'!$I$2:$I$517,$A21,'Transaction Overview'!$H$2:$H$517,F$4) -> 0 | G21: =SUMIFS('Transaction Overview'!$D$2:$D$517,'Transaction Overview'!$I$2:$I$517,$A21,'Transaction Overview'!$H$2:$H$517,G$4) -> 0 | H21: =SUMIFS('Transaction Overview'!$D$2:$D$517,'Transaction Overview'!$I$2:$I$517,$A21,'Transaction Overview'!$H$2:$H$517,H$4) -> 0 | I21: =SUMIFS('Transaction Overview'!$D$2:$D$517,'Transaction Overview'!$I$2:$I$517,$A21,'Transaction Overview'!$H$2:$H$517,I$4) -> 0 | ... M21: =SUMIFS('Transaction Overview'!$D$2:$D$517,'Transaction Overview'!$I$2:$I$517,$A21,'Transaction Overview'!$H$2:$H$517,M$4) -> 0 | N21: =SUM(B21:M21) -> -8556.41
A22: Intercompany & Savings Transfers
A23: Transfer to DWG Capital Group_Costar | B23: =SUMIFS('Transaction Overview'!$D$2:$D$517,'Transaction Overview'!$I$2:$I$517,$A23,'Transaction Overview'!$H$2:$H$517,B$4) -> -5000 | C23: =SUMIFS('Transaction Overview'!$D$2:$D$517,'Transaction Overview'!$I$2:$I$517,$A23,'Transaction Overview'!$H$2:$H$517,C$4) -> 0 | D23: =SUMIFS('Transaction Overview'!$D$2:$D$517,'Transaction Overview'!$I$2:$I$517,$A23,'Transaction Overview'!$H$2:$H$517,D$4) -> 0 | E23: =SUMIFS('Transaction Overview'!$D$2:$D$517,'Transaction Overview'!$I$2:$I$517,$A23,'Transaction Overview'!$H$2:$H$517,E$4) -> 0 | F23: =SUMIFS('Transaction Overview'!$D$2:$D$517,'Transaction Overview'!$I$2:$I$517,$A23,'Transaction Overview'!$H$2:$H$517,F$4) -> -7956.18 | G23: =SUMIFS('Transaction Overview'!$D$2:$D$517,'Transaction Overview'!$I$2:$I$517,$A23,'Transaction Overview'!$H$2:$H$517,G$4) -> 0 | H23: =SUMIFS('Transaction Overview'!$D$2:$D$517,'Transaction Overview'!$I$2:$I$517,$A23,'Transaction Overview'!$H$2:$H$517,H$4) -> 0 | I23: =SUMIFS('Transaction Overview'!$D$2:$D$517,'Transaction Overview'!$I$2:$I$517,$A23,'Transaction Overview'!$H$2:$H$517,I$4) -> 0 | ... M23: =SUMIFS('Transaction Overview'!$D$2:$D$517,'Transaction Overview'!$I$2:$I$517,$A23,'Transaction Overview'!$H$2:$H$517,M$4) -> 0 | N23: =SUM(B23:M23) -> -12956.18
A24: Transfer to DWG Savings | B24: =SUMIFS('Transaction Overview'!$D$2:$D$517,'Transaction Overview'!$I$2:$I$517,$A24,'Transaction Overview'!$H$2:$H$517,B$4) -> -1142 | C24: =SUMIFS('Transaction Overview'!$D$2:$D$517,'Transaction Overview'!$I$2:$I$517,$A24,'Transaction Overview'!$H$2:$H$517,C$4) -> 0 | D24: =SUMIFS('Transaction Overview'!$D$2:$D$517,'Transaction Overview'!$I$2:$I$517,$A24,'Transaction Overview'!$H$2:$H$517,D$4) -> -1000 | E24: =SUMIFS('Transaction Overview'!$D$2:$D$517,'Transaction Overview'!$I$2:$I$517,$A24,'Transaction Overview'!$H$2:$H$517,E$4) -> -100 | F24: =SUMIFS('Transaction Overview'!$D$2:$D$517,'Transaction Overview'!$I$2:$I$517,$A24,'Transaction Overview'!$H$2:$H$517,F$4) -> -2500 | G24: =SUMIFS('Transaction Overview'!$D$2:$D$517,'Transaction Overview'!$I$2:$I$517,$A24,'Transaction Overview'!$H$2:$H$517,G$4) -> 0 | H24: =SUMIFS('Transaction Overview'!$D$2:$D$517,'Transaction Overview'!$I$2:$I$517,$A24,'Transaction Overview'!$H$2:$H$517,H$4) -> 0 | I24: =SUMIFS('Transaction Overview'!$D$2:$D$517,'Transaction Overview'!$I$2:$I$517,$A24,'Transaction Overview'!$H$2:$H$517,I$4) -> 0 | ... M24: =SUMIFS('Transaction Overview'!$D$2:$D$517,'Transaction Overview'!$I$2:$I$517,$A24,'Transaction Overview'!$H$2:$H$517,M$4) -> 0 | N24: =SUM(B24:M24) -> -4742
A25: Transfer to DWG Capital Partners | B25: =SUMIFS('Transaction Overview'!$D$2:$D$517,'Transaction Overview'!$I$2:$I$517,$A25,'Transaction Overview'!$H$2:$H$517,B$4) -> 0 | C25: =SUMIFS('Transaction Overview'!$D$2:$D$517,'Transaction Overview'!$I$2:$I$517,$A25,'Transaction Overview'!$H$2:$H$517,C$4) -> 0 | D25: =SUMIFS('Transaction Overview'!$D$2:$D$517,'Transaction Overview'!$I$2:$I$517,$A25,'Transaction Overview'!$H$2:$H$517,D$4) -> 0 | E25: =SUMIFS('Transaction Overview'!$D$2:$D$517,'Transaction Overview'!$I$2:$I$517,$A25,'Transaction Overview'!$H$2:$H$517,E$4) -> 0 | F25: =SUMIFS('Transaction Overview'!$D$2:$D$517,'Transaction Overview'!$I$2:$I$517,$A25,'Transaction Overview'!$H$2:$H$517,F$4) -> -5000 | G25: =SUMIFS('Transaction Overview'!$D$2:$D$517,'Transaction Overview'!$I$2:$I$517,$A25,'Transaction Overview'!$H$2:$H$517,G$4) -> 0 | H25: =SUMIFS('Transaction Overview'!$D$2:$D$517,'Transaction Overview'!$I$2:$I$517,$A25,'Transaction Overview'!$H$2:$H$517,H$4) -> 0 | I25: =SUMIFS('Transaction Overview'!$D$2:$D$517,'Transaction Overview'!$I$2:$I$517,$A25,'Transaction Overview'!$H$2:$H$517,I$4) -> 0 | ... M25: =SUMIFS('Transaction Overview'!$D$2:$D$517,'Transaction Overview'!$I$2:$I$517,$A25,'Transaction Overview'!$H$2:$H$517,M$4) -> 0 | N25: =SUM(B25:M25) -> -5000
A26: Transfer to DWG Holdings | B26: =SUMIFS('Transaction Overview'!$D$2:$D$517,'Transaction Overview'!$I$2:$I$517,$A26,'Transaction Overview'!$H$2:$H$517,B$4) -> 0 | C26: =SUMIFS('Transaction Overview'!$D$2:$D$517,'Transaction Overview'!$I$2:$I$517,$A26,'Transaction Overview'!$H$2:$H$517,C$4) -> 0 | D26: =SUMIFS('Transaction Overview'!$D$2:$D$517,'Transaction Overview'!$I$2:$I$517,$A26,'Transaction Overview'!$H$2:$H$517,D$4) -> 0 | E26: =SUMIFS('Transaction Overview'!$D$2:$D$517,'Transaction Overview'!$I$2:$I$517,$A26,'Transaction Overview'!$H$2:$H$517,E$4) -> 0 | F26: =SUMIFS('Transaction Overview'!$D$2:$D$517,'Transaction Overview'!$I$2:$I$517,$A26,'Transaction Overview'!$H$2:$H$517,F$4) -> 0 | G26: =SUMIFS('Transaction Overview'!$D$2:$D$517,'Transaction Overview'!$I$2:$I$517,$A26,'Transaction Overview'!$H$2:$H$517,G$4) -> -200 | H26: =SUMIFS('Transaction Overview'!$D$2:$D$517,'Transaction Overview'!$I$2:$I$517,$A26,'Transaction Overview'!$H$2:$H$517,H$4) -> 0 | I26: =SUMIFS('Transaction Overview'!$D$2:$D$517,'Transaction Overview'!$I$2:$I$517,$A26,'Transaction Overview'!$H$2:$H$517,I$4) -> 0 | ... M26: =SUMIFS('Transaction Overview'!$D$2:$D$517,'Transaction Overview'!$I$2:$I$517,$A26,'Transaction Overview'!$H$2:$H$517,M$4) -> 0 | N26: =SUM(B26:M26) -> -200
A27: Transfer to Edgebuilders | B27: =SUMIFS('Transaction Overview'!$D$2:$D$517,'Transaction Overview'!$I$2:$I$517,$A27,'Transaction Overview'!$H$2:$H$517,B$4) -> 0 | C27: =SUMIFS('Transaction Overview'!$D$2:$D$517,'Transaction Overview'!$I$2:$I$517,$A27,'Transaction Overview'!$H$2:$H$517,C$4) -> 0 | D27: =SUMIFS('Transaction Overview'!$D$2:$D$517,'Transaction Overview'!$I$2:$I$517,$A27,'Transaction Overview'!$H$2:$H$517,D$4) -> 0 | E27: =SUMIFS('Transaction Overview'!$D$2:$D$517,'Transaction Overview'!$I$2:$I$517,$A27,'Transaction Overview'!$H$2:$H$517,E$4) -> 0 | F27: =SUMIFS('Transaction Overview'!$D$2:$D$517,'Transaction Overview'!$I$2:$I$517,$A27,'Transaction Overview'!$H$2:$H$517,F$4) -> 0 | G27: =SUMIFS('Transaction Overview'!$D$2:$D$517,'Transaction Overview'!$I$2:$I$517,$A27,'Transaction Overview'!$H$2:$H$517,G$4) -> -300 | H27: =SUMIFS('Transaction Overview'!$D$2:$D$517,'Transaction Overview'!$I$2:$I$517,$A27,'Transaction Overview'!$H$2:$H$517,H$4) -> 0 | I27: =SUMIFS('Transaction Overview'!$D$2:$D$517,'Transaction Overview'!$I$2:$I$517,$A27,'Transaction Overview'!$H$2:$H$517,I$4) -> 0 | ... M27: =SUMIFS('Transaction Overview'!$D$2:$D$517,'Transaction Overview'!$I$2:$I$517,$A27,'Transaction Overview'!$H$2:$H$517,M$4) -> 0 | N27: =SUM(B27:M27) -> -300
A28: Transfer to Judd Sol Prop | B28: =SUMIFS('Transaction Overview'!$D$2:$D$517,'Transaction Overview'!$I$2:$I$517,$A28,'Transaction Overview'!$H$2:$H$517,B$4) -> 0 | C28: =SUMIFS('Transaction Overview'!$D$2:$D$517,'Transaction Overview'!$I$2:$I$517,$A28,'Transaction Overview'!$H$2:$H$517,C$4) -> 0 | D28: =SUMIFS('Transaction Overview'!$D$2:$D$517,'Transaction Overview'!$I$2:$I$517,$A28,'Transaction Overview'!$H$2:$H$517,D$4) -> -200 | E28: =SUMIFS('Transaction Overview'!$D$2:$D$517,'Transaction Overview'!$I$2:$I$517,$A28,'Transaction Overview'!$H$2:$H$517,E$4) -> 0 | F28: =SUMIFS('Transaction Overview'!$D$2:$D$517,'Transaction Overview'!$I$2:$I$517,$A28,'Transaction Overview'!$H$2:$H$517,F$4) -> 0 | G28: =SUMIFS('Transaction Overview'!$D$2:$D$517,'Transaction Overview'!$I$2:$I$517,$A28,'Transaction Overview'!$H$2:$H$517,G$4) -> 0 | H28: =SUMIFS('Transaction Overview'!$D$2:$D$517,'Transaction Overview'!$I$2:$I$517,$A28,'Transaction Overview'!$H$2:$H$517,H$4) -> 0 | I28: =SUMIFS('Transaction Overview'!$D$2:$D$517,'Transaction Overview'!$I$2:$I$517,$A28,'Transaction Overview'!$H$2:$H$517,I$4) -> 0 | ... M28: =SUMIFS('Transaction Overview'!$D$2:$D$517,'Transaction Overview'!$I$2:$I$517,$A28,'Transaction Overview'!$H$2:$H$517,M$4) -> 0 | N28: =SUM(B28:M28) -> -200
A29: Transfer to MRM | B29: =SUMIFS('Transaction Overview'!$D$2:$D$517,'Transaction Overview'!$I$2:$I$517,$A29,'Transaction Overview'!$H$2:$H$517,B$4) -> 0 | C29: =SUMIFS('Transaction Overview'!$D$2:$D$517,'Transaction Overview'!$I$2:$I$517,$A29,'Transaction Overview'!$H$2:$H$517,C$4) -> 0 | D29: =SUMIFS('Transaction Overview'!$D$2:$D$517,'Transaction Overview'!$I$2:$I$517,$A29,'Transaction Overview'!$H$2:$H$517,D$4) -> 0 | E29: =SUMIFS('Transaction Overview'!$D$2:$D$517,'Transaction Overview'!$I$2:$I$517,$A29,'Transaction Overview'!$H$2:$H$517,E$4) -> 0 | F29: =SUMIFS('Transaction Overview'!$D$2:$D$517,'Transaction Overview'!$I$2:$I$517,$A29,'Transaction Overview'!$H$2:$H$517,F$4) -> 0 | G29: =SUMIFS('Transaction Overview'!$D$2:$D$517,'Transaction Overview'!$I$2:$I$517,$A29,'Transaction Overview'!$H$2:$H$517,G$4) -> -600 | H29: =SUMIFS('Transaction Overview'!$D$2:$D$517,'Transaction Overview'!$I$2:$I$517,$A29,'Transaction Overview'!$H$2:$H$517,H$4) -> 0 | I29: =SUMIFS('Transaction Overview'!$D$2:$D$517,'Transaction Overview'!$I$2:$I$517,$A29,'Transaction Overview'!$H$2:$H$517,I$4) -> 0 | ... M29: =SUMIFS('Transaction Overview'!$D$2:$D$517,'Transaction Overview'!$I$2:$I$517,$A29,'Transaction Overview'!$H$2:$H$517,M$4) -> 0 | N29: =SUM(B29:M29) -> -600
A30: Transfer to SPF | B30: =SUMIFS('Transaction Overview'!$D$2:$D$517,'Transaction Overview'!$I$2:$I$517,$A30,'Transaction Overview'!$H$2:$H$517,B$4) -> -200 | C30: =SUMIFS('Transaction Overview'!$D$2:$D$517,'Transaction Overview'!$I$2:$I$517,$A30,'Transaction Overview'!$H$2:$H$517,C$4) -> 0 | D30: =SUMIFS('Transaction Overview'!$D$2:$D$517,'Transaction Overview'!$I$2:$I$517,$A30,'Transaction Overview'!$H$2:$H$517,D$4) -> 0 | E30: =SUMIFS('Transaction Overview'!$D$2:$D$517,'Transaction Overview'!$I$2:$I$517,$A30,'Transaction Overview'!$H$2:$H$517,E$4) -> 0 | F30: =SUMIFS('Transaction Overview'!$D$2:$D$517,'Transaction Overview'!$I$2:$I$517,$A30,'Transaction Overview'!$H$2:$H$517,F$4) -> 0 | G30: =SUMIFS('Transaction Overview'!$D$2:$D$517,'Transaction Overview'!$I$2:$I$517,$A30,'Transaction Overview'!$H$2:$H$517,G$4) -> 0 | H30: =SUMIFS('Transaction Overview'!$D$2:$D$517,'Transaction Overview'!$I$2:$I$517,$A30,'Transaction Overview'!$H$2:$H$517,H$4) -> 0 | I30: =SUMIFS('Transaction Overview'!$D$2:$D$517,'Transaction Overview'!$I$2:$I$517,$A30,'Transaction Overview'!$H$2:$H$517,I$4) -> 0 | ... M30: =SUMIFS('Transaction Overview'!$D$2:$D$517,'Transaction Overview'!$I$2:$I$517,$A30,'Transaction Overview'!$H$2:$H$517,M$4) -> 0 | N30: =SUM(B30:M30) -> -200
A31: Transfer to TGAIF Fund | B31: =SUMIFS('Transaction Overview'!$D$2:$D$517,'Transaction Overview'!$I$2:$I$517,$A31,'Transaction Overview'!$H$2:$H$517,B$4) -> 0 | C31: =SUMIFS('Transaction Overview'!$D$2:$D$517,'Transaction Overview'!$I$2:$I$517,$A31,'Transaction Overview'!$H$2:$H$517,C$4) -> 0 | D31: =SUMIFS('Transaction Overview'!$D$2:$D$517,'Transaction Overview'!$I$2:$I$517,$A31,'Transaction Overview'!$H$2:$H$517,D$4) -> 0 | E31: =SUMIFS('Transaction Overview'!$D$2:$D$517,'Transaction Overview'!$I$2:$I$517,$A31,'Transaction Overview'!$H$2:$H$517,E$4) -> 0 | F31: =SUMIFS('Transaction Overview'!$D$2:$D$517,'Transaction Overview'!$I$2:$I$517,$A31,'Transaction Overview'!$H$2:$H$517,F$4) -> -300 | G31: =SUMIFS('Transaction Overview'!$D$2:$D$517,'Transaction Overview'!$I$2:$I$517,$A31,'Transaction Overview'!$H$2:$H$517,G$4) -> 0 | H31: =SUMIFS('Transaction Overview'!$D$2:$D$517,'Transaction Overview'!$I$2:$I$517,$A31,'Transaction Overview'!$H$2:$H$517,H$4) -> 0 | I31: =SUMIFS('Transaction Overview'!$D$2:$D$517,'Transaction Overview'!$I$2:$I$517,$A31,'Transaction Overview'!$H$2:$H$517,I$4) -> 0 | ... M31: =SUMIFS('Transaction Overview'!$D$2:$D$517,'Transaction Overview'!$I$2:$I$517,$A31,'Transaction Overview'!$H$2:$H$517,M$4) -> 0 | N31: =SUM(B31:M31) -> -300
A32: Transfer to Theut Glass | B32: =SUMIFS('Transaction Overview'!$D$2:$D$517,'Transaction Overview'!$I$2:$I$517,$A32,'Transaction Overview'!$H$2:$H$517,B$4) -> -300 | C32: =SUMIFS('Transaction Overview'!$D$2:$D$517,'Transaction Overview'!$I$2:$I$517,$A32,'Transaction Overview'!$H$2:$H$517,C$4) -> 0 | D32: =SUMIFS('Transaction Overview'!$D$2:$D$517,'Transaction Overview'!$I$2:$I$517,$A32,'Transaction Overview'!$H$2:$H$517,D$4) -> 0 | E32: =SUMIFS('Transaction Overview'!$D$2:$D$517,'Transaction Overview'!$I$2:$I$517,$A32,'Transaction Overview'!$H$2:$H$517,E$4) -> -400 | F32: =SUMIFS('Transaction Overview'!$D$2:$D$517,'Transaction Overview'!$I$2:$I$517,$A32,'Transaction Overview'!$H$2:$H$517,F$4) -> 0 | G32: =SUMIFS('Transaction Overview'!$D$2:$D$517,'Transaction Overview'!$I$2:$I$517,$A32,'Transaction Overview'!$H$2:$H$517,G$4) -> 0 | H32: =SUMIFS('Transaction Overview'!$D$2:$D$517,'Transaction Overview'!$I$2:$I$517,$A32,'Transaction Overview'!$H$2:$H$517,H$4) -> 0 | I32: =SUMIFS('Transaction Overview'!$D$2:$D$517,'Transaction Overview'!$I$2:$I$517,$A32,'Transaction Overview'!$H$2:$H$517,I$4) -> 0 | ... M32: =SUMIFS('Transaction Overview'!$D$2:$D$517,'Transaction Overview'!$I$2:$I$517,$A32,'Transaction Overview'!$H$2:$H$517,M$4) -> 0 | N32: =SUM(B32:M32) -> -700
A33: Payroll & Contractors
A34: Andres Alarcon Payroll | B34: =SUMIFS('Transaction Overview'!$D$2:$D$517,'Transaction Overview'!$I$2:$I$517,$A34,'Transaction Overview'!$H$2:$H$517,B$4) -> -1510 | C34: =SUMIFS('Transaction Overview'!$D$2:$D$517,'Transaction Overview'!$I$2:$I$517,$A34,'Transaction Overview'!$H$2:$H$517,C$4) -> -1510 | D34: =SUMIFS('Transaction Overview'!$D$2:$D$517,'Transaction Overview'!$I$2:$I$517,$A34,'Transaction Overview'!$H$2:$H$517,D$4) -> -1510 | E34: =SUMIFS('Transaction Overview'!$D$2:$D$517,'Transaction Overview'!$I$2:$I$517,$A34,'Transaction Overview'!$H$2:$H$517,E$4) -> -1510 | F34: =SUMIFS('Transaction Overview'!$D$2:$D$517,'Transaction Overview'!$I$2:$I$517,$A34,'Transaction Overview'!$H$2:$H$517,F$4) -> -1510 | G34: =SUMIFS('Transaction Overview'!$D$2:$D$517,'Transaction Overview'!$I$2:$I$517,$A34,'Transaction Overview'!$H$2:$H$517,G$4) -> -755 | H34: =SUMIFS('Transaction Overview'!$D$2:$D$517,'Transaction Overview'!$I$2:$I$517,$A34,'Transaction Overview'!$H$2:$H$517,H$4) -> 0 | I34: =SUMIFS('Transaction Overview'!$D$2:$D$517,'Transaction Overview'!$I$2:$I$517,$A34,'Transaction Overview'!$H$2:$H$517,I$4) -> 0 | ... M34: =SUMIFS('Transaction Overview'!$D$2:$D$517,'Transaction Overview'!$I$2:$I$517,$A34,'Transaction Overview'!$H$2:$H$517,M$4) -> 0 | N34: =SUM(B34:M34) -> -8305
A35: Chase Hall - Payroll | B35: =SUMIFS('Transaction Overview'!$D$2:$D$517,'Transaction Overview'!$I$2:$I$517,$A35,'Transaction Overview'!$H$2:$H$517,B$4) -> 0 | C35: =SUMIFS('Transaction Overview'!$D$2:$D$517,'Transaction Overview'!$I$2:$I$517,$A35,'Transaction Overview'!$H$2:$H$517,C$4) -> -3500 | D35: =SUMIFS('Transaction Overview'!$D$2:$D$517,'Transaction Overview'!$I$2:$I$517,$A35,'Transaction Overview'!$H$2:$H$517,D$4) -> -3500 | E35: =SUMIFS('Transaction Overview'!$D$2:$D$517,'Transaction Overview'!$I$2:$I$517,$A35,'Transaction Overview'!$H$2:$H$517,E$4) -> -10500 | F35: =SUMIFS('Transaction Overview'!$D$2:$D$517,'Transaction Overview'!$I$2:$I$517,$A35,'Transaction Overview'!$H$2:$H$517,F$4) -> -7000 | G35: =SUMIFS('Transaction Overview'!$D$2:$D$517,'Transaction Overview'!$I$2:$I$517,$A35,'Transaction Overview'!$H$2:$H$517,G$4) -> -3500 | H35: =SUMIFS('Transaction Overview'!$D$2:$D$517,'Transaction Overview'!$I$2:$I$517,$A35,'Transaction Overview'!$H$2:$H$517,H$4) -> 0 | I35: =SUMIFS('Transaction Overview'!$D$2:$D$517,'Transaction Overview'!$I$2:$I$517,$A35,'Transaction Overview'!$H$2:$H$517,I$4) -> 0 | ... M35: =SUMIFS('Transaction Overview'!$D$2:$D$517,'Transaction Overview'!$I$2:$I$517,$A35,'Transaction Overview'!$H$2:$H$517,M$4) -> 0 | N35: =SUM(B35:M35) -> -28000
A36: DWG HR | B36: =SUMIFS('Transaction Overview'!$D$2:$D$517,'Transaction Overview'!$I$2:$I$517,$A36,'Transaction Overview'!$H$2:$H$517,B$4) -> -937.28 | C36: =SUMIFS('Transaction Overview'!$D$2:$D$517,'Transaction Overview'!$I$2:$I$517,$A36,'Transaction Overview'!$H$2:$H$517,C$4) -> -23.34 | D36: =SUMIFS('Transaction Overview'!$D$2:$D$517,'Transaction Overview'!$I$2:$I$517,$A36,'Transaction Overview'!$H$2:$H$517,D$4) -> -125.69 | E36: =SUMIFS('Transaction Overview'!$D$2:$D$517,'Transaction Overview'!$I$2:$I$517,$A36,'Transaction Overview'!$H$2:$H$517,E$4) -> 0 | F36: =SUMIFS('Transaction Overview'!$D$2:$D$517,'Transaction Overview'!$I$2:$I$517,$A36,'Transaction Overview'!$H$2:$H$517,F$4) -> 0 | G36: =SUMIFS('Transaction Overview'!$D$2:$D$517,'Transaction Overview'!$I$2:$I$517,$A36,'Transaction Overview'!$H$2:$H$517,G$4) -> 0 | H36: =SUMIFS('Transaction Overview'!$D$2:$D$517,'Transaction Overview'!$I$2:$I$517,$A36,'Transaction Overview'!$H$2:$H$517,H$4) -> 0 | I36: =SUMIFS('Transaction Overview'!$D$2:$D$517,'Transaction Overview'!$I$2:$I$517,$A36,'Transaction Overview'!$H$2:$H$517,I$4) -> 0 | ... M36: =SUMIFS('Transaction Overview'!$D$2:$D$517,'Transaction Overview'!$I$2:$I$517,$A36,'Transaction Overview'!$H$2:$H$517,M$4) -> 0 | N36: =SUM(B36:M36) -> -1086.31
A37: Mike Paytonjian - Payroll | B37: =SUMIFS('Transaction Overview'!$D$2:$D$517,'Transaction Overview'!$I$2:$I$517,$A37,'Transaction Overview'!$H$2:$H$517,B$4) -> -7000 | C37: =SUMIFS('Transaction Overview'!$D$2:$D$517,'Transaction Overview'!$I$2:$I$517,$A37,'Transaction Overview'!$H$2:$H$517,C$4) -> -7000 | D37: =SUMIFS('Transaction Overview'!$D$2:$D$517,'Transaction Overview'!$I$2:$I$517,$A37,'Transaction Overview'!$H$2:$H$517,D$4) -> -8750 | E37: =SUMIFS('Transaction Overview'!$D$2:$D$517,'Transaction Overview'!$I$2:$I$517,$A37,'Transaction Overview'!$H$2:$H$517,E$4) -> -7000 | F37: =SUMIFS('Transaction Overview'!$D$2:$D$517,'Transaction Overview'!$I$2:$I$517,$A37,'Transaction Overview'!$H$2:$H$517,F$4) -> -7500 | G37: =SUMIFS('Transaction Overview'!$D$2:$D$517,'Transaction Overview'!$I$2:$I$517,$A37,'Transaction Overview'!$H$2:$H$517,G$4) -> -6000 | H37: =SUMIFS('Transaction Overview'!$D$2:$D$517,'Transaction Overview'!$I$2:$I$517,$A37,'Transaction Overview'!$H$2:$H$517,H$4) -> 0 | I37: =SUMIFS('Transaction Overview'!$D$2:$D$517,'Transaction Overview'!$I$2:$I$517,$A37,'Transaction Overview'!$H$2:$H$517,I$4) -> 0 | ... M37: =SUMIFS('Transaction Overview'!$D$2:$D$517,'Transaction Overview'!$I$2:$I$517,$A37,'Transaction Overview'!$H$2:$H$517,M$4) -> 0 | N37: =SUM(B37:M37) -> -43250
A38: Ruth Alcancia - Forward Bridge Payment | B38: =SUMIFS('Transaction Overview'!$D$2:$D$517,'Transaction Overview'!$I$2:$I$517,$A38,'Transaction Overview'!$H$2:$H$517,B$4) -> -425 | C38: =SUMIFS('Transaction Overview'!$D$2:$D$517,'Transaction Overview'!$I$2:$I$517,$A38,'Transaction Overview'!$H$2:$H$517,C$4) -> -600 | D38: =SUMIFS('Transaction Overview'!$D$2:$D$517,'Transaction Overview'!$I$2:$I$517,$A38,'Transaction Overview'!$H$2:$H$517,D$4) -> -990.4 | E38: =SUMIFS('Transaction Overview'!$D$2:$D$517,'Transaction Overview'!$I$2:$I$517,$A38,'Transaction Overview'!$H$2:$H$517,E$4) -> -791.99 | F38: =SUMIFS('Transaction Overview'!$D$2:$D$517,'Transaction Overview'!$I$2:$I$517,$A38,'Transaction Overview'!$H$2:$H$517,F$4) -> -1049.99 | G38: =SUMIFS('Transaction Overview'!$D$2:$D$517,'Transaction Overview'!$I$2:$I$517,$A38,'Transaction Overview'!$H$2:$H$517,G$4) -> -189.32 | H38: =SUMIFS('Transaction Overview'!$D$2:$D$517,'Transaction Overview'!$I$2:$I$517,$A38,'Transaction Overview'!$H$2:$H$517,H$4) -> 0 | I38: =SUMIFS('Transaction Overview'!$D$2:$D$517,'Transaction Overview'!$I$2:$I$517,$A38,'Transaction Overview'!$H$2:$H$517,I$4) -> 0 | ... M38: =SUMIFS('Transaction Overview'!$D$2:$D$517,'Transaction Overview'!$I$2:$I$517,$A38,'Transaction Overview'!$H$2:$H$517,M$4) -> 0 | N38: =SUM(B38:M38) -> -4046.7
A39: Upwork - Sergei M. | B39: =SUMIFS('Transaction Overview'!$D$2:$D$517,'Transaction Overview'!$I$2:$I$517,$A39,'Transaction Overview'!$H$2:$H$517,B$4) -> -971.25 | C39: =SUMIFS('Transaction Overview'!$D$2:$D$517,'Transaction Overview'!$I$2:$I$517,$A39,'Transaction Overview'!$H$2:$H$517,C$4) -> -656.25 | D39: =SUMIFS('Transaction Overview'!$D$2:$D$517,'Transaction Overview'!$I$2:$I$517,$A39,'Transaction Overview'!$H$2:$H$517,D$4) -> 0 | E39: =SUMIFS('Transaction Overview'!$D$2:$D$517,'Transaction Overview'!$I$2:$I$517,$A39,'Transaction Overview'!$H$2:$H$517,E$4) -> 0 | F39: =SUMIFS('Transaction Overview'!$D$2:$D$517,'Transaction Overview'!$I$2:$I$517,$A39,'Transaction Overview'!$H$2:$H$517,F$4) -> 0 | G39: =SUMIFS('Transaction Overview'!$D$2:$D$517,'Transaction Overview'!$I$2:$I$517,$A39,'Transaction Overview'!$H$2:$H$517,G$4) -> 0 | H39: =SUMIFS('Transaction Overview'!$D$2:$D$517,'Transaction Overview'!$I$2:$I$517,$A39,'Transaction Overview'!$H$2:$H$517,H$4) -> 0 | I39: =SUMIFS('Transaction Overview'!$D$2:$D$517,'Transaction Overview'!$I$2:$I$517,$A39,'Transaction Overview'!$H$2:$H$517,I$4) -> 0 | ... M39: =SUMIFS('Transaction Overview'!$D$2:$D$517,'Transaction Overview'!$I$2:$I$517,$A39,'Transaction Overview'!$H$2:$H$517,M$4) -> 0 | N39: =SUM(B39:M39) -> -1627.5
A40: P2P Payments (Zelle/Venmo/PayPal)
A41: PayPal | B41: =SUMIFS('Transaction Overview'!$D$2:$D$517,'Transaction Overview'!$I$2:$I$517,$A41,'Transaction Overview'!$H$2:$H$517,B$4) -> 0 | C41: =SUMIFS('Transaction Overview'!$D$2:$D$517,'Transaction Overview'!$I$2:$I$517,$A41,'Transaction Overview'!$H$2:$H$517,C$4) -> 0 | D41: =SUMIFS('Transaction Overview'!$D$2:$D$517,'Transaction Overview'!$I$2:$I$517,$A41,'Transaction Overview'!$H$2:$H$517,D$4) -> -37.08 | E41: =SUMIFS('Transaction Overview'!$D$2:$D$517,'Transaction Overview'!$I$2:$I$517,$A41,'Transaction Overview'!$H$2:$H$517,E$4) -> -36.94 | F41: =SUMIFS('Transaction Overview'!$D$2:$D$517,'Transaction Overview'!$I$2:$I$517,$A41,'Transaction Overview'!$H$2:$H$517,F$4) -> 0 | G41: =SUMIFS('Transaction Overview'!$D$2:$D$517,'Transaction Overview'!$I$2:$I$517,$A41,'Transaction Overview'!$H$2:$H$517,G$4) -> 0 | H41: =SUMIFS('Transaction Overview'!$D$2:$D$517,'Transaction Overview'!$I$2:$I$517,$A41,'Transaction Overview'!$H$2:$H$517,H$4) -> 0 | I41: =SUMIFS('Transaction Overview'!$D$2:$D$517,'Transaction Overview'!$I$2:$I$517,$A41,'Transaction Overview'!$H$2:$H$517,I$4) -> 0 | ... M41: =SUMIFS('Transaction Overview'!$D$2:$D$517,'Transaction Overview'!$I$2:$I$517,$A41,'Transaction Overview'!$H$2:$H$517,M$4) -> 0 | N41: =SUM(B41:M41) -> -74.02
A42: Venmo | B42: =SUMIFS('Transaction Overview'!$D$2:$D$517,'Transaction Overview'!$I$2:$I$517,$A42,'Transaction Overview'!$H$2:$H$517,B$4) -> -7489 | C42: =SUMIFS('Transaction Overview'!$D$2:$D$517,'Transaction Overview'!$I$2:$I$517,$A42,'Transaction Overview'!$H$2:$H$517,C$4) -> -2876 | D42: =SUMIFS('Transaction Overview'!$D$2:$D$517,'Transaction Overview'!$I$2:$I$517,$A42,'Transaction Overview'!$H$2:$H$517,D$4) -> -2993 | E42: =SUMIFS('Transaction Overview'!$D$2:$D$517,'Transaction Overview'!$I$2:$I$517,$A42,'Transaction Overview'!$H$2:$H$517,E$4) -> -1620 | F42: =SUMIFS('Transaction Overview'!$D$2:$D$517,'Transaction Overview'!$I$2:$I$517,$A42,'Transaction Overview'!$H$2:$H$517,F$4) -> -981 | G42: =SUMIFS('Transaction Overview'!$D$2:$D$517,'Transaction Overview'!$I$2:$I$517,$A42,'Transaction Overview'!$H$2:$H$517,G$4) -> -1220 | H42: =SUMIFS('Transaction Overview'!$D$2:$D$517,'Transaction Overview'!$I$2:$I$517,$A42,'Transaction Overview'!$H$2:$H$517,H$4) -> 0 | I42: =SUMIFS('Transaction Overview'!$D$2:$D$517,'Transaction Overview'!$I$2:$I$517,$A42,'Transaction Overview'!$H$2:$H$517,I$4) -> 0 | ... M42: =SUMIFS('Transaction Overview'!$D$2:$D$517,'Transaction Overview'!$I$2:$I$517,$A42,'Transaction Overview'!$H$2:$H$517,M$4) -> 0 | N42: =SUM(B42:M42) -> -17179
A43: Zelle - Estella M. | B43: =SUMIFS('Transaction Overview'!$D$2:$D$517,'Transaction Overview'!$I$2:$I$517,$A43,'Transaction Overview'!$H$2:$H$517,B$4) -> -800 | C43: =SUMIFS('Transaction Overview'!$D$2:$D$517,'Transaction Overview'!$I$2:$I$517,$A43,'Transaction Overview'!$H$2:$H$517,C$4) -> -800 | D43: =SUMIFS('Transaction Overview'!$D$2:$D$517,'Transaction Overview'!$I$2:$I$517,$A43,'Transaction Overview'!$H$2:$H$517,D$4) -> -1000 | E43: =SUMIFS('Transaction Overview'!$D$2:$D$517,'Transaction Overview'!$I$2:$I$517,$A43,'Transaction Overview'!$H$2:$H$517,E$4) -> 0 | F43: =SUMIFS('Transaction Overview'!$D$2:$D$517,'Transaction Overview'!$I$2:$I$517,$A43,'Transaction Overview'!$H$2:$H$517,F$4) -> -1000 | G43: =SUMIFS('Transaction Overview'!$D$2:$D$517,'Transaction Overview'!$I$2:$I$517,$A43,'Transaction Overview'!$H$2:$H$517,G$4) -> 0 | H43: =SUMIFS('Transaction Overview'!$D$2:$D$517,'Transaction Overview'!$I$2:$I$517,$A43,'Transaction Overview'!$H$2:$H$517,H$4) -> 0 | I43: =SUMIFS('Transaction Overview'!$D$2:$D$517,'Transaction Overview'!$I$2:$I$517,$A43,'Transaction Overview'!$H$2:$H$517,I$4) -> 0 | ... M43: =SUMIFS('Transaction Overview'!$D$2:$D$517,'Transaction Overview'!$I$2:$I$517,$A43,'Transaction Overview'!$H$2:$H$517,M$4) -> 0 | N43: =SUM(B43:M43) -> -3600
A44: Zelle - Jared Iorio | B44: =SUMIFS('Transaction Overview'!$D$2:$D$517,'Transaction Overview'!$I$2:$I$517,$A44,'Transaction Overview'!$H$2:$H$517,B$4) -> -200 | C44: =SUMIFS('Transaction Overview'!$D$2:$D$517,'Transaction Overview'!$I$2:$I$517,$A44,'Transaction Overview'!$H$2:$H$517,C$4) -> 0 | D44: =SUMIFS('Transaction Overview'!$D$2:$D$517,'Transaction Overview'!$I$2:$I$517,$A44,'Transaction Overview'!$H$2:$H$517,D$4) -> 0 | E44: =SUMIFS('Transaction Overview'!$D$2:$D$517,'Transaction Overview'!$I$2:$I$517,$A44,'Transaction Overview'!$H$2:$H$517,E$4) -> 0 | F44: =SUMIFS('Transaction Overview'!$D$2:$D$517,'Transaction Overview'!$I$2:$I$517,$A44,'Transaction Overview'!$H$2:$H$517,F$4) -> 0 | G44: =SUMIFS('Transaction Overview'!$D$2:$D$517,'Transaction Overview'!$I$2:$I$517,$A44,'Transaction Overview'!$H$2:$H$517,G$4) -> 0 | H44: =SUMIFS('Transaction Overview'!$D$2:$D$517,'Transaction Overview'!$I$2:$I$517,$A44,'Transaction Overview'!$H$2:$H$517,H$4) -> 0 | I44: =SUMIFS('Transaction Overview'!$D$2:$D$517,'Transaction Overview'!$I$2:$I$517,$A44,'Transaction Overview'!$H$2:$H$517,I$4) -> 0 | ... M44: =SUMIFS('Transaction Overview'!$D$2:$D$517,'Transaction Overview'!$I$2:$I$517,$A44,'Transaction Overview'!$H$2:$H$517,M$4) -> 0 | N44: =SUM(B44:M44) -> -200
A45: Zelle - Jeff Seider | B45: =SUMIFS('Transaction Overview'!$D$2:$D$517,'Transaction Overview'!$I$2:$I$517,$A45,'Transaction Overview'!$H$2:$H$517,B$4) -> -800 | C45: =SUMIFS('Transaction Overview'!$D$2:$D$517,'Transaction Overview'!$I$2:$I$517,$A45,'Transaction Overview'!$H$2:$H$517,C$4) -> -1300 | D45: =SUMIFS('Transaction Overview'!$D$2:$D$517,'Transaction Overview'!$I$2:$I$517,$A45,'Transaction Overview'!$H$2:$H$517,D$4) -> -600 | E45: =SUMIFS('Transaction Overview'!$D$2:$D$517,'Transaction Overview'!$I$2:$I$517,$A45,'Transaction Overview'!$H$2:$H$517,E$4) -> -350 | F45: =SUMIFS('Transaction Overview'!$D$2:$D$517,'Transaction Overview'!$I$2:$I$517,$A45,'Transaction Overview'!$H$2:$H$517,F$4) -> -1150 | G45: =SUMIFS('Transaction Overview'!$D$2:$D$517,'Transaction Overview'!$I$2:$I$517,$A45,'Transaction Overview'!$H$2:$H$517,G$4) -> -400 | H45: =SUMIFS('Transaction Overview'!$D$2:$D$517,'Transaction Overview'!$I$2:$I$517,$A45,'Transaction Overview'!$H$2:$H$517,H$4) -> 0 | I45: =SUMIFS('Transaction Overview'!$D$2:$D$517,'Transaction Overview'!$I$2:$I$517,$A45,'Transaction Overview'!$H$2:$H$517,I$4) -> 0 | ... M45: =SUMIFS('Transaction Overview'!$D$2:$D$517,'Transaction Overview'!$I$2:$I$517,$A45,'Transaction Overview'!$H$2:$H$517,M$4) -> 0 | N45: =SUM(B45:M45) -> -4600
A46: Zelle - Natalie C. | B46: =SUMIFS('Transaction Overview'!$D$2:$D$517,'Transaction Overview'!$I$2:$I$517,$A46,'Transaction Overview'!$H$2:$H$517,B$4) -> 0 | C46: =SUMIFS('Transaction Overview'!$D$2:$D$517,'Transaction Overview'!$I$2:$I$517,$A46,'Transaction Overview'!$H$2:$H$517,C$4) -> -500 | D46: =SUMIFS('Transaction Overview'!$D$2:$D$517,'Transaction Overview'!$I$2:$I$517,$A46,'Transaction Overview'!$H$2:$H$517,D$4) -> -500 | E46: =SUMIFS('Transaction Overview'!$D$2:$D$517,'Transaction Overview'!$I$2:$I$517,$A46,'Transaction Overview'!$H$2:$H$517,E$4) -> -500 | F46: =SUMIFS('Transaction Overview'!$D$2:$D$517,'Transaction Overview'!$I$2:$I$517,$A46,'Transaction Overview'!$H$2:$H$517,F$4) -> -500 | G46: =SUMIFS('Transaction Overview'!$D$2:$D$517,'Transaction Overview'!$I$2:$I$517,$A46,'Transaction Overview'!$H$2:$H$517,G$4) -> 0 | H46: =SUMIFS('Transaction Overview'!$D$2:$D$517,'Transaction Overview'!$I$2:$I$517,$A46,'Transaction Overview'!$H$2:$H$517,H$4) -> 0 | I46: =SUMIFS('Transaction Overview'!$D$2:$D$517,'Transaction Overview'!$I$2:$I$517,$A46,'Transaction Overview'!$H$2:$H$517,I$4) -> 0 | ... M46: =SUMIFS('Transaction Overview'!$D$2:$D$517,'Transaction Overview'!$I$2:$I$517,$A46,'Transaction Overview'!$H$2:$H$517,M$4) -> 0 | N46: =SUM(B46:M46) -> -2000
A47: Zelle/P2P | B47: =SUMIFS('Transaction Overview'!$D$2:$D$517,'Transaction Overview'!$I$2:$I$517,$A47,'Transaction Overview'!$H$2:$H$517,B$4) -> 0 | C47: =SUMIFS('Transaction Overview'!$D$2:$D$517,'Transaction Overview'!$I$2:$I$517,$A47,'Transaction Overview'!$H$2:$H$517,C$4) -> 0 | D47: =SUMIFS('Transaction Overview'!$D$2:$D$517,'Transaction Overview'!$I$2:$I$517,$A47,'Transaction Overview'!$H$2:$H$517,D$4) -> 0 | E47: =SUMIFS('Transaction Overview'!$D$2:$D$517,'Transaction Overview'!$I$2:$I$517,$A47,'Transaction Overview'!$H$2:$H$517,E$4) -> 0 | F47: =SUMIFS('Transaction Overview'!$D$2:$D$517,'Transaction Overview'!$I$2:$I$517,$A47,'Transaction Overview'!$H$2:$H$517,F$4) -> -325 | G47: =SUMIFS('Transaction Overview'!$D$2:$D$517,'Transaction Overview'!$I$2:$I$517,$A47,'Transaction Overview'!$H$2:$H$517,G$4) -> 0 | H47: =SUMIFS('Transaction Overview'!$D$2:$D$517,'Transaction Overview'!$I$2:$I$517,$A47,'Transaction Overview'!$H$2:$H$517,H$4) -> 0 | I47: =SUMIFS('Transaction Overview'!$D$2:$D$517,'Transaction Overview'!$I$2:$I$517,$A47,'Transaction Overview'!$H$2:$H$517,I$4) -> 0 | ... M47: =SUMIFS('Transaction Overview'!$D$2:$D$517,'Transaction Overview'!$I$2:$I$517,$A47,'Transaction Overview'!$H$2:$H$517,M$4) -> 0 | N47: =SUM(B47:M47) -> -325
A48: Owner / Family Distributions
A49: Transfer to Angela Dunning | B49: =SUMIFS('Transaction Overview'!$D$2:$D$517,'Transaction Overview'!$I$2:$I$517,$A49,'Transaction Overview'!$H$2:$H$517,B$4) -> -32000 | C49: =SUMIFS('Transaction Overview'!$D$2:$D$517,'Transaction Overview'!$I$2:$I$517,$A49,'Transaction Overview'!$H$2:$H$517,C$4) -> -22000 | D49: =SUMIFS('Transaction Overview'!$D$2:$D$517,'Transaction Overview'!$I$2:$I$517,$A49,'Transaction Overview'!$H$2:$H$517,D$4) -> -41000 | E49: =SUMIFS('Transaction Overview'!$D$2:$D$517,'Transaction Overview'!$I$2:$I$517,$A49,'Transaction Overview'!$H$2:$H$517,E$4) -> -15000 | F49: =SUMIFS('Transaction Overview'!$D$2:$D$517,'Transaction Overview'!$I$2:$I$517,$A49,'Transaction Overview'!$H$2:$H$517,F$4) -> -28000 | G49: =SUMIFS('Transaction Overview'!$D$2:$D$517,'Transaction Overview'!$I$2:$I$517,$A49,'Transaction Overview'!$H$2:$H$517,G$4) -> -14700 | H49: =SUMIFS('Transaction Overview'!$D$2:$D$517,'Transaction Overview'!$I$2:$I$517,$A49,'Transaction Overview'!$H$2:$H$517,H$4) -> 0 | I49: =SUMIFS('Transaction Overview'!$D$2:$D$517,'Transaction Overview'!$I$2:$I$517,$A49,'Transaction Overview'!$H$2:$H$517,I$4) -> 0 | ... M49: =SUMIFS('Transaction Overview'!$D$2:$D$517,'Transaction Overview'!$I$2:$I$517,$A49,'Transaction Overview'!$H$2:$H$517,M$4) -> 0 | N49: =SUM(B49:M49) -> -152700
A50: Transfer to Ava Perez-Dunning | B50: =SUMIFS('Transaction Overview'!$D$2:$D$517,'Transaction Overview'!$I$2:$I$517,$A50,'Transaction Overview'!$H$2:$H$517,B$4) -> -1200 | C50: =SUMIFS('Transaction Overview'!$D$2:$D$517,'Transaction Overview'!$I$2:$I$517,$A50,'Transaction Overview'!$H$2:$H$517,C$4) -> 0 | D50: =SUMIFS('Transaction Overview'!$D$2:$D$517,'Transaction Overview'!$I$2:$I$517,$A50,'Transaction Overview'!$H$2:$H$517,D$4) -> -1000 | E50: =SUMIFS('Transaction Overview'!$D$2:$D$517,'Transaction Overview'!$I$2:$I$517,$A50,'Transaction Overview'!$H$2:$H$517,E$4) -> 0 | F50: =SUMIFS('Transaction Overview'!$D$2:$D$517,'Transaction Overview'!$I$2:$I$517,$A50,'Transaction Overview'!$H$2:$H$517,F$4) -> -1000 | G50: =SUMIFS('Transaction Overview'!$D$2:$D$517,'Transaction Overview'!$I$2:$I$517,$A50,'Transaction Overview'!$H$2:$H$517,G$4) -> 0 | H50: =SUMIFS('Transaction Overview'!$D$2:$D$517,'Transaction Overview'!$I$2:$I$517,$A50,'Transaction Overview'!$H$2:$H$517,H$4) -> 0 | I50: =SUMIFS('Transaction Overview'!$D$2:$D$517,'Transaction Overview'!$I$2:$I$517,$A50,'Transaction Overview'!$H$2:$H$517,I$4) -> 0 | ... M50: =SUMIFS('Transaction Overview'!$D$2:$D$517,'Transaction Overview'!$I$2:$I$517,$A50,'Transaction Overview'!$H$2:$H$517,M$4) -> 0 | N50: =SUM(B50:M50) -> -3200
A51: Transfer to TX Personal Joint | B51: =SUMIFS('Transaction Overview'!$D$2:$D$517,'Transaction Overview'!$I$2:$I$517,$A51,'Transaction Overview'!$H$2:$H$517,B$4) -> -10000 | C51: =SUMIFS('Transaction Overview'!$D$2:$D$517,'Transaction Overview'!$I$2:$I$517,$A51,'Transaction Overview'!$H$2:$H$517,C$4) -> 0 | D51: =SUMIFS('Transaction Overview'!$D$2:$D$517,'Transaction Overview'!$I$2:$I$517,$A51,'Transaction Overview'!$H$2:$H$517,D$4) -> 0 | E51: =SUMIFS('Transaction Overview'!$D$2:$D$517,'Transaction Overview'!$I$2:$I$517,$A51,'Transaction Overview'!$H$2:$H$517,E$4) -> 0 | F51: =SUMIFS('Transaction Overview'!$D$2:$D$517,'Transaction Overview'!$I$2:$I$517,$A51,'Transaction Overview'!$H$2:$H$517,F$4) -> -1000 | G51: =SUMIFS('Transaction Overview'!$D$2:$D$517,'Transaction Overview'!$I$2:$I$517,$A51,'Transaction Overview'!$H$2:$H$517,G$4) -> 0 | H51: =SUMIFS('Transaction Overview'!$D$2:$D$517,'Transaction Overview'!$I$2:$I$517,$A51,'Transaction Overview'!$H$2:$H$517,H$4) -> 0 | I51: =SUMIFS('Transaction Overview'!$D$2:$D$517,'Transaction Overview'!$I$2:$I$517,$A51,'Transaction Overview'!$H$2:$H$517,I$4) -> 0 | ... M51: =SUMIFS('Transaction Overview'!$D$2:$D$517,'Transaction Overview'!$I$2:$I$517,$A51,'Transaction Overview'!$H$2:$H$517,M$4) -> 0 | N51: =SUM(B51:M51) -> -11000
A52: Credit Card & Loan Payments
A53: Loan/Mortgage | B53: =SUMIFS('Transaction Overview'!$D$2:$D$517,'Transaction Overview'!$I$2:$I$517,$A53,'Transaction Overview'!$H$2:$H$517,B$4) -> 0 | C53: =SUMIFS('Transaction Overview'!$D$2:$D$517,'Transaction Overview'!$I$2:$I$517,$A53,'Transaction Overview'!$H$2:$H$517,C$4) -> 0 | D53: =SUMIFS('Transaction Overview'!$D$2:$D$517,'Transaction Overview'!$I$2:$I$517,$A53,'Transaction Overview'!$H$2:$H$517,D$4) -> -331.54 | E53: =SUMIFS('Transaction Overview'!$D$2:$D$517,'Transaction Overview'!$I$2:$I$517,$A53,'Transaction Overview'!$H$2:$H$517,E$4) -> 0 | F53: =SUMIFS('Transaction Overview'!$D$2:$D$517,'Transaction Overview'!$I$2:$I$517,$A53,'Transaction Overview'!$H$2:$H$517,F$4) -> 0 | G53: =SUMIFS('Transaction Overview'!$D$2:$D$517,'Transaction Overview'!$I$2:$I$517,$A53,'Transaction Overview'!$H$2:$H$517,G$4) -> 0 | H53: =SUMIFS('Transaction Overview'!$D$2:$D$517,'Transaction Overview'!$I$2:$I$517,$A53,'Transaction Overview'!$H$2:$H$517,H$4) -> 0 | I53: =SUMIFS('Transaction Overview'!$D$2:$D$517,'Transaction Overview'!$I$2:$I$517,$A53,'Transaction Overview'!$H$2:$H$517,I$4) -> 0 | ... M53: =SUMIFS('Transaction Overview'!$D$2:$D$517,'Transaction Overview'!$I$2:$I$517,$A53,'Transaction Overview'!$H$2:$H$517,M$4) -> 0 | N53: =SUM(B53:M53) -> -331.54
A54: SBC EIDL Loan | B54: =SUMIFS('Transaction Overview'!$D$2:$D$517,'Transaction Overview'!$I$2:$I$517,$A54,'Transaction Overview'!$H$2:$H$517,B$4) -> -2524 | C54: =SUMIFS('Transaction Overview'!$D$2:$D$517,'Transaction Overview'!$I$2:$I$517,$A54,'Transaction Overview'!$H$2:$H$517,C$4) -> 0 | D54: =SUMIFS('Transaction Overview'!$D$2:$D$517,'Transaction Overview'!$I$2:$I$517,$A54,'Transaction Overview'!$H$2:$H$517,D$4) -> -5048 | E54: =SUMIFS('Transaction Overview'!$D$2:$D$517,'Transaction Overview'!$I$2:$I$517,$A54,'Transaction Overview'!$H$2:$H$517,E$4) -> -2524 | F54: =SUMIFS('Transaction Overview'!$D$2:$D$517,'Transaction Overview'!$I$2:$I$517,$A54,'Transaction Overview'!$H$2:$H$517,F$4) -> 0 | G54: =SUMIFS('Transaction Overview'!$D$2:$D$517,'Transaction Overview'!$I$2:$I$517,$A54,'Transaction Overview'!$H$2:$H$517,G$4) -> -2524 | H54: =SUMIFS('Transaction Overview'!$D$2:$D$517,'Transaction Overview'!$I$2:$I$517,$A54,'Transaction Overview'!$H$2:$H$517,H$4) -> 0 | I54: =SUMIFS('Transaction Overview'!$D$2:$D$517,'Transaction Overview'!$I$2:$I$517,$A54,'Transaction Overview'!$H$2:$H$517,I$4) -> 0 | ... M54: =SUMIFS('Transaction Overview'!$D$2:$D$517,'Transaction Overview'!$I$2:$I$517,$A54,'Transaction Overview'!$H$2:$H$517,M$4) -> 0 | N54: =SUM(B54:M54) -> -12620
A55: Taxes
A56: Taxes | B56: =SUMIFS('Transaction Overview'!$D$2:$D$517,'Transaction Overview'!$I$2:$I$517,$A56,'Transaction Overview'!$H$2:$H$517,B$4) -> 0 | C56: =SUMIFS('Transaction Overview'!$D$2:$D$517,'Transaction Overview'!$I$2:$I$517,$A56,'Transaction Overview'!$H$2:$H$517,C$4) -> 0 | D56: =SUMIFS('Transaction Overview'!$D$2:$D$517,'Transaction Overview'!$I$2:$I$517,$A56,'Transaction Overview'!$H$2:$H$517,D$4) -> -60 | E56: =SUMIFS('Transaction Overview'!$D$2:$D$517,'Transaction Overview'!$I$2:$I$517,$A56,'Transaction Overview'!$H$2:$H$517,E$4) -> -800 | F56: =SUMIFS('Transaction Overview'!$D$2:$D$517,'Transaction Overview'!$I$2:$I$517,$A56,'Transaction Overview'!$H$2:$H$517,F$4) -> 0 | G56: =SUMIFS('Transaction Overview'!$D$2:$D$517,'Transaction Overview'!$I$2:$I$517,$A56,'Transaction Overview'!$H$2:$H$517,G$4) -> 0 | H56: =SUMIFS('Transaction Overview'!$D$2:$D$517,'Transaction Overview'!$I$2:$I$517,$A56,'Transaction Overview'!$H$2:$H$517,H$4) -> 0 | I56: =SUMIFS('Transaction Overview'!$D$2:$D$517,'Transaction Overview'!$I$2:$I$517,$A56,'Transaction Overview'!$H$2:$H$517,I$4) -> 0 | ... M56: =SUMIFS('Transaction Overview'!$D$2:$D$517,'Transaction Overview'!$I$2:$I$517,$A56,'Transaction Overview'!$H$2:$H$517,M$4) -> 0 | N56: =SUM(B56:M56) -> -860
A57: DWG Operating
A58: AI Subscriptions | B58: =SUMIFS('Transaction Overview'!$D$2:$D$517,'Transaction Overview'!$I$2:$I$517,$A58,'Transaction Overview'!$H$2:$H$517,B$4) -> -21.28 | C58: =SUMIFS('Transaction Overview'!$D$2:$D$517,'Transaction Overview'!$I$2:$I$517,$A58,'Transaction Overview'!$H$2:$H$517,C$4) -> 0 | D58: =SUMIFS('Transaction Overview'!$D$2:$D$517,'Transaction Overview'!$I$2:$I$517,$A58,'Transaction Overview'!$H$2:$H$517,D$4) -> 0 | E58: =SUMIFS('Transaction Overview'!$D$2:$D$517,'Transaction Overview'!$I$2:$I$517,$A58,'Transaction Overview'!$H$2:$H$517,E$4) -> 0 | F58: =SUMIFS('Transaction Overview'!$D$2:$D$517,'Transaction Overview'!$I$2:$I$517,$A58,'Transaction Overview'!$H$2:$H$517,F$4) -> 0 | G58: =SUMIFS('Transaction Overview'!$D$2:$D$517,'Transaction Overview'!$I$2:$I$517,$A58,'Transaction Overview'!$H$2:$H$517,G$4) -> 0 | H58: =SUMIFS('Transaction Overview'!$D$2:$D$517,'Transaction Overview'!$I$2:$I$517,$A58,'Transaction Overview'!$H$2:$H$517,H$4) -> 0 | I58: =SUMIFS('Transaction Overview'!$D$2:$D$517,'Transaction Overview'!$I$2:$I$517,$A58,'Transaction Overview'!$H$2:$H$517,I$4) -> 0 | ... M58: =SUMIFS('Transaction Overview'!$D$2:$D$517,'Transaction Overview'!$I$2:$I$517,$A58,'Transaction Overview'!$H$2:$H$517,M$4) -> 0 | N58: =SUM(B58:M58) -> -21.28
A59: Bank Fees | B59: =SUMIFS('Transaction Overview'!$D$2:$D$517,'Transaction Overview'!$I$2:$I$517,$A59,'Transaction Overview'!$H$2:$H$517,B$4) -> -125.45 | C59: =SUMIFS('Transaction Overview'!$D$2:$D$517,'Transaction Overview'!$I$2:$I$517,$A59,'Transaction Overview'!$H$2:$H$517,C$4) -> -17.5 | D59: =SUMIFS('Transaction Overview'!$D$2:$D$517,'Transaction Overview'!$I$2:$I$517,$A59,'Transaction Overview'!$H$2:$H$517,D$4) -> -15 | E59: =SUMIFS('Transaction Overview'!$D$2:$D$517,'Transaction Overview'!$I$2:$I$517,$A59,'Transaction Overview'!$H$2:$H$517,E$4) -> -23 | F59: =SUMIFS('Transaction Overview'!$D$2:$D$517,'Transaction Overview'!$I$2:$I$517,$A59,'Transaction Overview'!$H$2:$H$517,F$4) -> -17.5 | G59: =SUMIFS('Transaction Overview'!$D$2:$D$517,'Transaction Overview'!$I$2:$I$517,$A59,'Transaction Overview'!$H$2:$H$517,G$4) -> -65.6 | H59: =SUMIFS('Transaction Overview'!$D$2:$D$517,'Transaction Overview'!$I$2:$I$517,$A59,'Transaction Overview'!$H$2:$H$517,H$4) -> 0 | I59: =SUMIFS('Transaction Overview'!$D$2:$D$517,'Transaction Overview'!$I$2:$I$517,$A59,'Transaction Overview'!$H$2:$H$517,I$4) -> 0 | ... M59: =SUMIFS('Transaction Overview'!$D$2:$D$517,'Transaction Overview'!$I$2:$I$517,$A59,'Transaction Overview'!$H$2:$H$517,M$4) -> 0 | N59: =SUM(B59:M59) -> -264.05
A60: Bill Payment | B60: =SUMIFS('Transaction Overview'!$D$2:$D$517,'Transaction Overview'!$I$2:$I$517,$A60,'Transaction Overview'!$H$2:$H$517,B$4) -> 0 | C60: =SUMIFS('Transaction Overview'!$D$2:$D$517,'Transaction Overview'!$I$2:$I$517,$A60,'Transaction Overview'!$H$2:$H$517,C$4) -> 0 | D60: =SUMIFS('Transaction Overview'!$D$2:$D$517,'Transaction Overview'!$I$2:$I$517,$A60,'Transaction Overview'!$H$2:$H$517,D$4) -> 0 | E60: =SUMIFS('Transaction Overview'!$D$2:$D$517,'Transaction Overview'!$I$2:$I$517,$A60,'Transaction Overview'!$H$2:$H$517,E$4) -> 0 | F60: =SUMIFS('Transaction Overview'!$D$2:$D$517,'Transaction Overview'!$I$2:$I$517,$A60,'Transaction Overview'!$H$2:$H$517,F$4) -> -1800 | G60: =SUMIFS('Transaction Overview'!$D$2:$D$517,'Transaction Overview'!$I$2:$I$517,$A60,'Transaction Overview'!$H$2:$H$517,G$4) -> 0 | H60: =SUMIFS('Transaction Overview'!$D$2:$D$517,'Transaction Overview'!$I$2:$I$517,$A60,'Transaction Overview'!$H$2:$H$517,H$4) -> 0 | I60: =SUMIFS('Transaction Overview'!$D$2:$D$517,'Transaction Overview'!$I$2:$I$517,$A60,'Transaction Overview'!$H$2:$H$517,I$4) -> 0 | ... M60: =SUMIFS('Transaction Overview'!$D$2:$D$517,'Transaction Overview'!$I$2:$I$517,$A60,'Transaction Overview'!$H$2:$H$517,M$4) -> 0 | N60: =SUM(B60:M60) -> -1800
A61: DWG Marketing | B61: =SUMIFS('Transaction Overview'!$D$2:$D$517,'Transaction Overview'!$I$2:$I$517,$A61,'Transaction Overview'!$H$2:$H$517,B$4) -> -104.01 | C61: =SUMIFS('Transaction Overview'!$D$2:$D$517,'Transaction Overview'!$I$2:$I$517,$A61,'Transaction Overview'!$H$2:$H$517,C$4) -> -104.01 | D61: =SUMIFS('Transaction Overview'!$D$2:$D$517,'Transaction Overview'!$I$2:$I$517,$A61,'Transaction Overview'!$H$2:$H$517,D$4) -> -104.01 | E61: =SUMIFS('Transaction Overview'!$D$2:$D$517,'Transaction Overview'!$I$2:$I$517,$A61,'Transaction Overview'!$H$2:$H$517,E$4) -> -104.01 | F61: =SUMIFS('Transaction Overview'!$D$2:$D$517,'Transaction Overview'!$I$2:$I$517,$A61,'Transaction Overview'!$H$2:$H$517,F$4) -> -104.01 | G61: =SUMIFS('Transaction Overview'!$D$2:$D$517,'Transaction Overview'!$I$2:$I$517,$A61,'Transaction Overview'!$H$2:$H$517,G$4) -> 0 | H61: =SUMIFS('Transaction Overview'!$D$2:$D$517,'Transaction Overview'!$I$2:$I$517,$A61,'Transaction Overview'!$H$2:$H$517,H$4) -> 0 | I61: =SUMIFS('Transaction Overview'!$D$2:$D$517,'Transaction Overview'!$I$2:$I$517,$A61,'Transaction Overview'!$H$2:$H$517,I$4) -> 0 | ... M61: =SUMIFS('Transaction Overview'!$D$2:$D$517,'Transaction Overview'!$I$2:$I$517,$A61,'Transaction Overview'!$H$2:$H$517,M$4) -> 0 | N61: =SUM(B61:M61) -> -520.05
A62: DWGCP Business Development | B62: =SUMIFS('Transaction Overview'!$D$2:$D$517,'Transaction Overview'!$I$2:$I$517,$A62,'Transaction Overview'!$H$2:$H$517,B$4) -> -10.78 | C62: =SUMIFS('Transaction Overview'!$D$2:$D$517,'Transaction Overview'!$I$2:$I$517,$A62,'Transaction Overview'!$H$2:$H$517,C$4) -> -10.78 | D62: =SUMIFS('Transaction Overview'!$D$2:$D$517,'Transaction Overview'!$I$2:$I$517,$A62,'Transaction Overview'!$H$2:$H$517,D$4) -> -10.78 | E62: =SUMIFS('Transaction Overview'!$D$2:$D$517,'Transaction Overview'!$I$2:$I$517,$A62,'Transaction Overview'!$H$2:$H$517,E$4) -> -10.78 | F62: =SUMIFS('Transaction Overview'!$D$2:$D$517,'Transaction Overview'!$I$2:$I$517,$A62,'Transaction Overview'!$H$2:$H$517,F$4) -> -10.78 | G62: =SUMIFS('Transaction Overview'!$D$2:$D$517,'Transaction Overview'!$I$2:$I$517,$A62,'Transaction Overview'!$H$2:$H$517,G$4) -> -10.78 | H62: =SUMIFS('Transaction Overview'!$D$2:$D$517,'Transaction Overview'!$I$2:$I$517,$A62,'Transaction Overview'!$H$2:$H$517,H$4) -> 0 | I62: =SUMIFS('Transaction Overview'!$D$2:$D$517,'Transaction Overview'!$I$2:$I$517,$A62,'Transaction Overview'!$H$2:$H$517,I$4) -> 0 | ... M62: =SUMIFS('Transaction Overview'!$D$2:$D$517,'Transaction Overview'!$I$2:$I$517,$A62,'Transaction Overview'!$H$2:$H$517,M$4) -> 0 | N62: =SUM(B62:M62) -> -64.68
A63: Go Daddy | B63: =SUMIFS('Transaction Overview'!$D$2:$D$517,'Transaction Overview'!$I$2:$I$517,$A63,'Transaction Overview'!$H$2:$H$517,B$4) -> -83.91 | C63: =SUMIFS('Transaction Overview'!$D$2:$D$517,'Transaction Overview'!$I$2:$I$517,$A63,'Transaction Overview'!$H$2:$H$517,C$4) -> -60.93 | D63: =SUMIFS('Transaction Overview'!$D$2:$D$517,'Transaction Overview'!$I$2:$I$517,$A63,'Transaction Overview'!$H$2:$H$517,D$4) -> -253.77 | E63: =SUMIFS('Transaction Overview'!$D$2:$D$517,'Transaction Overview'!$I$2:$I$517,$A63,'Transaction Overview'!$H$2:$H$517,E$4) -> -2602.58 | F63: =SUMIFS('Transaction Overview'!$D$2:$D$517,'Transaction Overview'!$I$2:$I$517,$A63,'Transaction Overview'!$H$2:$H$517,F$4) -> -695.23 | G63: =SUMIFS('Transaction Overview'!$D$2:$D$517,'Transaction Overview'!$I$2:$I$517,$A63,'Transaction Overview'!$H$2:$H$517,G$4) -> -255.35 | H63: =SUMIFS('Transaction Overview'!$D$2:$D$517,'Transaction Overview'!$I$2:$I$517,$A63,'Transaction Overview'!$H$2:$H$517,H$4) -> 0 | I63: =SUMIFS('Transaction Overview'!$D$2:$D$517,'Transaction Overview'!$I$2:$I$517,$A63,'Transaction Overview'!$H$2:$H$517,I$4) -> 0 | ... M63: =SUMIFS('Transaction Overview'!$D$2:$D$517,'Transaction Overview'!$I$2:$I$517,$A63,'Transaction Overview'!$H$2:$H$517,M$4) -> 0 | N63: =SUM(B63:M63) -> -3951.77
A64: Office/Miscellaneous Reimbursement - Mike P. | B64: =SUMIFS('Transaction Overview'!$D$2:$D$517,'Transaction Overview'!$I$2:$I$517,$A64,'Transaction Overview'!$H$2:$H$517,B$4) -> -35 | C64: =SUMIFS('Transaction Overview'!$D$2:$D$517,'Transaction Overview'!$I$2:$I$517,$A64,'Transaction Overview'!$H$2:$H$517,C$4) -> 0 | D64: =SUMIFS('Transaction Overview'!$D$2:$D$517,'Transaction Overview'!$I$2:$I$517,$A64,'Transaction Overview'!$H$2:$H$517,D$4) -> -140 | E64: =SUMIFS('Transaction Overview'!$D$2:$D$517,'Transaction Overview'!$I$2:$I$517,$A64,'Transaction Overview'!$H$2:$H$517,E$4) -> 0 | F64: =SUMIFS('Transaction Overview'!$D$2:$D$517,'Transaction Overview'!$I$2:$I$517,$A64,'Transaction Overview'!$H$2:$H$517,F$4) -> -18 | G64: =SUMIFS('Transaction Overview'!$D$2:$D$517,'Transaction Overview'!$I$2:$I$517,$A64,'Transaction Overview'!$H$2:$H$517,G$4) -> -95 | H64: =SUMIFS('Transaction Overview'!$D$2:$D$517,'Transaction Overview'!$I$2:$I$517,$A64,'Transaction Overview'!$H$2:$H$517,H$4) -> 0 | I64: =SUMIFS('Transaction Overview'!$D$2:$D$517,'Transaction Overview'!$I$2:$I$517,$A64,'Transaction Overview'!$H$2:$H$517,I$4) -> 0 | ... M64: =SUMIFS('Transaction Overview'!$D$2:$D$517,'Transaction Overview'!$I$2:$I$517,$A64,'Transaction Overview'!$H$2:$H$517,M$4) -> 0 | N64: =SUM(B64:M64) -> -288
A65: Software/Accounting | B65: =SUMIFS('Transaction Overview'!$D$2:$D$517,'Transaction Overview'!$I$2:$I$517,$A65,'Transaction Overview'!$H$2:$H$517,B$4) -> -121.21 | C65: =SUMIFS('Transaction Overview'!$D$2:$D$517,'Transaction Overview'!$I$2:$I$517,$A65,'Transaction Overview'!$H$2:$H$517,C$4) -> -121.21 | D65: =SUMIFS('Transaction Overview'!$D$2:$D$517,'Transaction Overview'!$I$2:$I$517,$A65,'Transaction Overview'!$H$2:$H$517,D$4) -> -121.21 | E65: =SUMIFS('Transaction Overview'!$D$2:$D$517,'Transaction Overview'!$I$2:$I$517,$A65,'Transaction Overview'!$H$2:$H$517,E$4) -> -121.21 | F65: =SUMIFS('Transaction Overview'!$D$2:$D$517,'Transaction Overview'!$I$2:$I$517,$A65,'Transaction Overview'!$H$2:$H$517,F$4) -> -121.21 | G65: =SUMIFS('Transaction Overview'!$D$2:$D$517,'Transaction Overview'!$I$2:$I$517,$A65,'Transaction Overview'!$H$2:$H$517,G$4) -> 0 | H65: =SUMIFS('Transaction Overview'!$D$2:$D$517,'Transaction Overview'!$I$2:$I$517,$A65,'Transaction Overview'!$H$2:$H$517,H$4) -> 0 | I65: =SUMIFS('Transaction Overview'!$D$2:$D$517,'Transaction Overview'!$I$2:$I$517,$A65,'Transaction Overview'!$H$2:$H$517,I$4) -> 0 | ... M65: =SUMIFS('Transaction Overview'!$D$2:$D$517,'Transaction Overview'!$I$2:$I$517,$A65,'Transaction Overview'!$H$2:$H$517,M$4) -> 0 | N65: =SUM(B65:M65) -> -606.05
A66: Team Lunch | B66: =SUMIFS('Transaction Overview'!$D$2:$D$517,'Transaction Overview'!$I$2:$I$517,$A66,'Transaction Overview'!$H$2:$H$517,B$4) -> 0 | C66: =SUMIFS('Transaction Overview'!$D$2:$D$517,'Transaction Overview'!$I$2:$I$517,$A66,'Transaction Overview'!$H$2:$H$517,C$4) -> 0 | D66: =SUMIFS('Transaction Overview'!$D$2:$D$517,'Transaction Overview'!$I$2:$I$517,$A66,'Transaction Overview'!$H$2:$H$517,D$4) -> 0 | E66: =SUMIFS('Transaction Overview'!$D$2:$D$517,'Transaction Overview'!$I$2:$I$517,$A66,'Transaction Overview'!$H$2:$H$517,E$4) -> -112.43 | F66: =SUMIFS('Transaction Overview'!$D$2:$D$517,'Transaction Overview'!$I$2:$I$517,$A66,'Transaction Overview'!$H$2:$H$517,F$4) -> 0 | G66: =SUMIFS('Transaction Overview'!$D$2:$D$517,'Transaction Overview'!$I$2:$I$517,$A66,'Transaction Overview'!$H$2:$H$517,G$4) -> 0 | H66: =SUMIFS('Transaction Overview'!$D$2:$D$517,'Transaction Overview'!$I$2:$I$517,$A66,'Transaction Overview'!$H$2:$H$517,H$4) -> 0 | I66: =SUMIFS('Transaction Overview'!$D$2:$D$517,'Transaction Overview'!$I$2:$I$517,$A66,'Transaction Overview'!$H$2:$H$517,I$4) -> 0 | ... M66: =SUMIFS('Transaction Overview'!$D$2:$D$517,'Transaction Overview'!$I$2:$I$517,$A66,'Transaction Overview'!$H$2:$H$517,M$4) -> 0 | N66: =SUM(B66:M66) -> -112.43
A67: Wire Fee | B67: =SUMIFS('Transaction Overview'!$D$2:$D$517,'Transaction Overview'!$I$2:$I$517,$A67,'Transaction Overview'!$H$2:$H$517,B$4) -> 0 | C67: =SUMIFS('Transaction Overview'!$D$2:$D$517,'Transaction Overview'!$I$2:$I$517,$A67,'Transaction Overview'!$H$2:$H$517,C$4) -> -50 | D67: =SUMIFS('Transaction Overview'!$D$2:$D$517,'Transaction Overview'!$I$2:$I$517,$A67,'Transaction Overview'!$H$2:$H$517,D$4) -> 0 | E67: =SUMIFS('Transaction Overview'!$D$2:$D$517,'Transaction Overview'!$I$2:$I$517,$A67,'Transaction Overview'!$H$2:$H$517,E$4) -> 0 | F67: =SUMIFS('Transaction Overview'!$D$2:$D$517,'Transaction Overview'!$I$2:$I$517,$A67,'Transaction Overview'!$H$2:$H$517,F$4) -> -40 | G67: =SUMIFS('Transaction Overview'!$D$2:$D$517,'Transaction Overview'!$I$2:$I$517,$A67,'Transaction Overview'!$H$2:$H$517,G$4) -> 0 | H67: =SUMIFS('Transaction Overview'!$D$2:$D$517,'Transaction Overview'!$I$2:$I$517,$A67,'Transaction Overview'!$H$2:$H$517,H$4) -> 0 | I67: =SUMIFS('Transaction Overview'!$D$2:$D$517,'Transaction Overview'!$I$2:$I$517,$A67,'Transaction Overview'!$H$2:$H$517,I$4) -> 0 | ... M67: =SUMIFS('Transaction Overview'!$D$2:$D$517,'Transaction Overview'!$I$2:$I$517,$A67,'Transaction Overview'!$H$2:$H$517,M$4) -> 0 | N67: =SUM(B67:M67) -> -90
A68: Business Travel
A69: Employee Travel Reimbursement | B69: =SUMIFS('Transaction Overview'!$D$2:$D$517,'Transaction Overview'!$I$2:$I$517,$A69,'Transaction Overview'!$H$2:$H$517,B$4) -> 0 | C69: =SUMIFS('Transaction Overview'!$D$2:$D$517,'Transaction Overview'!$I$2:$I$517,$A69,'Transaction Overview'!$H$2:$H$517,C$4) -> 0 | D69: =SUMIFS('Transaction Overview'!$D$2:$D$517,'Transaction Overview'!$I$2:$I$517,$A69,'Transaction Overview'!$H$2:$H$517,D$4) -> 0 | E69: =SUMIFS('Transaction Overview'!$D$2:$D$517,'Transaction Overview'!$I$2:$I$517,$A69,'Transaction Overview'!$H$2:$H$517,E$4) -> 0 | F69: =SUMIFS('Transaction Overview'!$D$2:$D$517,'Transaction Overview'!$I$2:$I$517,$A69,'Transaction Overview'!$H$2:$H$517,F$4) -> -166.74 | G69: =SUMIFS('Transaction Overview'!$D$2:$D$517,'Transaction Overview'!$I$2:$I$517,$A69,'Transaction Overview'!$H$2:$H$517,G$4) -> 0 | H69: =SUMIFS('Transaction Overview'!$D$2:$D$517,'Transaction Overview'!$I$2:$I$517,$A69,'Transaction Overview'!$H$2:$H$517,H$4) -> 0 | I69: =SUMIFS('Transaction Overview'!$D$2:$D$517,'Transaction Overview'!$I$2:$I$517,$A69,'Transaction Overview'!$H$2:$H$517,I$4) -> 0 | ... M69: =SUMIFS('Transaction Overview'!$D$2:$D$517,'Transaction Overview'!$I$2:$I$517,$A69,'Transaction Overview'!$H$2:$H$517,M$4) -> 0 | N69: =SUM(B69:M69) -> -166.74
A70: Team Travel - Reimbursement | B70: =SUMIFS('Transaction Overview'!$D$2:$D$517,'Transaction Overview'!$I$2:$I$517,$A70,'Transaction Overview'!$H$2:$H$517,B$4) -> 0 | C70: =SUMIFS('Transaction Overview'!$D$2:$D$517,'Transaction Overview'!$I$2:$I$517,$A70,'Transaction Overview'!$H$2:$H$517,C$4) -> 0 | D70: =SUMIFS('Transaction Overview'!$D$2:$D$517,'Transaction Overview'!$I$2:$I$517,$A70,'Transaction Overview'!$H$2:$H$517,D$4) -> 0 | E70: =SUMIFS('Transaction Overview'!$D$2:$D$517,'Transaction Overview'!$I$2:$I$517,$A70,'Transaction Overview'!$H$2:$H$517,E$4) -> -315 | F70: =SUMIFS('Transaction Overview'!$D$2:$D$517,'Transaction Overview'!$I$2:$I$517,$A70,'Transaction Overview'!$H$2:$H$517,F$4) -> 0 | G70: =SUMIFS('Transaction Overview'!$D$2:$D$517,'Transaction Overview'!$I$2:$I$517,$A70,'Transaction Overview'!$H$2:$H$517,G$4) -> 0 | H70: =SUMIFS('Transaction Overview'!$D$2:$D$517,'Transaction Overview'!$I$2:$I$517,$A70,'Transaction Overview'!$H$2:$H$517,H$4) -> 0 | I70: =SUMIFS('Transaction Overview'!$D$2:$D$517,'Transaction Overview'!$I$2:$I$517,$A70,'Transaction Overview'!$H$2:$H$517,I$4) -> 0 | ... M70: =SUMIFS('Transaction Overview'!$D$2:$D$517,'Transaction Overview'!$I$2:$I$517,$A70,'Transaction Overview'!$H$2:$H$517,M$4) -> 0 | N70: =SUM(B70:M70) -> -315
A71: Personal — Owner
A72: Personal - Life Insurance | B72: =SUMIFS('Transaction Overview'!$D$2:$D$517,'Transaction Overview'!$I$2:$I$517,$A72,'Transaction Overview'!$H$2:$H$517,B$4) -> -206.63 | C72: =SUMIFS('Transaction Overview'!$D$2:$D$517,'Transaction Overview'!$I$2:$I$517,$A72,'Transaction Overview'!$H$2:$H$517,C$4) -> 0 | D72: =SUMIFS('Transaction Overview'!$D$2:$D$517,'Transaction Overview'!$I$2:$I$517,$A72,'Transaction Overview'!$H$2:$H$517,D$4) -> -70.84 | E72: =SUMIFS('Transaction Overview'!$D$2:$D$517,'Transaction Overview'!$I$2:$I$517,$A72,'Transaction Overview'!$H$2:$H$517,E$4) -> -206.63 | F72: =SUMIFS('Transaction Overview'!$D$2:$D$517,'Transaction Overview'!$I$2:$I$517,$A72,'Transaction Overview'!$H$2:$H$517,F$4) -> -35.42 | G72: =SUMIFS('Transaction Overview'!$D$2:$D$517,'Transaction Overview'!$I$2:$I$517,$A72,'Transaction Overview'!$H$2:$H$517,G$4) -> 0 | H72: =SUMIFS('Transaction Overview'!$D$2:$D$517,'Transaction Overview'!$I$2:$I$517,$A72,'Transaction Overview'!$H$2:$H$517,H$4) -> 0 | I72: =SUMIFS('Transaction Overview'!$D$2:$D$517,'Transaction Overview'!$I$2:$I$517,$A72,'Transaction Overview'!$H$2:$H$517,I$4) -> 0 | ... M72: =SUMIFS('Transaction Overview'!$D$2:$D$517,'Transaction Overview'!$I$2:$I$517,$A72,'Transaction Overview'!$H$2:$H$517,M$4) -> 0 | N72: =SUM(B72:M72) -> -519.52
A73: Personal - Food & Dining | B73: =SUMIFS('Transaction Overview'!$D$2:$D$517,'Transaction Overview'!$I$2:$I$517,$A73,'Transaction Overview'!$H$2:$H$517,B$4) -> 0 | C73: =SUMIFS('Transaction Overview'!$D$2:$D$517,'Transaction Overview'!$I$2:$I$517,$A73,'Transaction Overview'!$H$2:$H$517,C$4) -> 0 | D73: =SUMIFS('Transaction Overview'!$D$2:$D$517,'Transaction Overview'!$I$2:$I$517,$A73,'Transaction Overview'!$H$2:$H$517,D$4) -> 0 | E73: =SUMIFS('Transaction Overview'!$D$2:$D$517,'Transaction Overview'!$I$2:$I$517,$A73,'Transaction Overview'!$H$2:$H$517,E$4) -> -148.55 | F73: =SUMIFS('Transaction Overview'!$D$2:$D$517,'Transaction Overview'!$I$2:$I$517,$A73,'Transaction Overview'!$H$2:$H$517,F$4) -> 0 | G73: =SUMIFS('Transaction Overview'!$D$2:$D$517,'Transaction Overview'!$I$2:$I$517,$A73,'Transaction Overview'!$H$2:$H$517,G$4) -> 0 | H73: =SUMIFS('Transaction Overview'!$D$2:$D$517,'Transaction Overview'!$I$2:$I$517,$A73,'Transaction Overview'!$H$2:$H$517,H$4) -> 0 | I73: =SUMIFS('Transaction Overview'!$D$2:$D$517,'Transaction Overview'!$I$2:$I$517,$A73,'Transaction Overview'!$H$2:$H$517,I$4) -> 0 | ... M73: =SUMIFS('Transaction Overview'!$D$2:$D$517,'Transaction Overview'!$I$2:$I$517,$A73,'Transaction Overview'!$H$2:$H$517,M$4) -> 0 | N73: =SUM(B73:M73) -> -148.55
A74: Personal - California Mortgage PMT | B74: =SUMIFS('Transaction Overview'!$D$2:$D$517,'Transaction Overview'!$I$2:$I$517,$A74,'Transaction Overview'!$H$2:$H$517,B$4) -> -7100 | C74: =SUMIFS('Transaction Overview'!$D$2:$D$517,'Transaction Overview'!$I$2:$I$517,$A74,'Transaction Overview'!$H$2:$H$517,C$4) -> 0 | D74: =SUMIFS('Transaction Overview'!$D$2:$D$517,'Transaction Overview'!$I$2:$I$517,$A74,'Transaction Overview'!$H$2:$H$517,D$4) -> -14200 | E74: =SUMIFS('Transaction Overview'!$D$2:$D$517,'Transaction Overview'!$I$2:$I$517,$A74,'Transaction Overview'!$H$2:$H$517,E$4) -> 0 | F74: =SUMIFS('Transaction Overview'!$D$2:$D$517,'Transaction Overview'!$I$2:$I$517,$A74,'Transaction Overview'!$H$2:$H$517,F$4) -> -7100 | G74: =SUMIFS('Transaction Overview'!$D$2:$D$517,'Transaction Overview'!$I$2:$I$517,$A74,'Transaction Overview'!$H$2:$H$517,G$4) -> 0 | H74: =SUMIFS('Transaction Overview'!$D$2:$D$517,'Transaction Overview'!$I$2:$I$517,$A74,'Transaction Overview'!$H$2:$H$517,H$4) -> 0 | I74: =SUMIFS('Transaction Overview'!$D$2:$D$517,'Transaction Overview'!$I$2:$I$517,$A74,'Transaction Overview'!$H$2:$H$517,I$4) -> 0 | ... M74: =SUMIFS('Transaction Overview'!$D$2:$D$517,'Transaction Overview'!$I$2:$I$517,$A74,'Transaction Overview'!$H$2:$H$517,M$4) -> 0 | N74: =SUM(B74:M74) -> -28400
A75: Personal - Car & Auto | B75: =SUMIFS('Transaction Overview'!$D$2:$D$517,'Transaction Overview'!$I$2:$I$517,$A75,'Transaction Overview'!$H$2:$H$517,B$4) -> -6625.98 | C75: =SUMIFS('Transaction Overview'!$D$2:$D$517,'Transaction Overview'!$I$2:$I$517,$A75,'Transaction Overview'!$H$2:$H$517,C$4) -> -2766.93 | D75: =SUMIFS('Transaction Overview'!$D$2:$D$517,'Transaction Overview'!$I$2:$I$517,$A75,'Transaction Overview'!$H$2:$H$517,D$4) -> -8425.2 | E75: =SUMIFS('Transaction Overview'!$D$2:$D$517,'Transaction Overview'!$I$2:$I$517,$A75,'Transaction Overview'!$H$2:$H$517,E$4) -> -1240.27 | F75: =SUMIFS('Transaction Overview'!$D$2:$D$517,'Transaction Overview'!$I$2:$I$517,$A75,'Transaction Overview'!$H$2:$H$517,F$4) -> -7120.8 | G75: =SUMIFS('Transaction Overview'!$D$2:$D$517,'Transaction Overview'!$I$2:$I$517,$A75,'Transaction Overview'!$H$2:$H$517,G$4) -> -1124.22 | H75: =SUMIFS('Transaction Overview'!$D$2:$D$517,'Transaction Overview'!$I$2:$I$517,$A75,'Transaction Overview'!$H$2:$H$517,H$4) -> 0 | I75: =SUMIFS('Transaction Overview'!$D$2:$D$517,'Transaction Overview'!$I$2:$I$517,$A75,'Transaction Overview'!$H$2:$H$517,I$4) -> 0 | ... M75: =SUMIFS('Transaction Overview'!$D$2:$D$517,'Transaction Overview'!$I$2:$I$517,$A75,'Transaction Overview'!$H$2:$H$517,M$4) -> 0 | N75: =SUM(B75:M75) -> -27303.4
A76: Personal - Entertainment | B76: =SUMIFS('Transaction Overview'!$D$2:$D$517,'Transaction Overview'!$I$2:$I$517,$A76,'Transaction Overview'!$H$2:$H$517,B$4) -> 0 | C76: =SUMIFS('Transaction Overview'!$D$2:$D$517,'Transaction Overview'!$I$2:$I$517,$A76,'Transaction Overview'!$H$2:$H$517,C$4) -> 0 | D76: =SUMIFS('Transaction Overview'!$D$2:$D$517,'Transaction Overview'!$I$2:$I$517,$A76,'Transaction Overview'!$H$2:$H$517,D$4) -> 0 | E76: =SUMIFS('Transaction Overview'!$D$2:$D$517,'Transaction Overview'!$I$2:$I$517,$A76,'Transaction Overview'!$H$2:$H$517,E$4) -> -36.67 | F76: =SUMIFS('Transaction Overview'!$D$2:$D$517,'Transaction Overview'!$I$2:$I$517,$A76,'Transaction Overview'!$H$2:$H$517,F$4) -> -5.32 | G76: =SUMIFS('Transaction Overview'!$D$2:$D$517,'Transaction Overview'!$I$2:$I$517,$A76,'Transaction Overview'!$H$2:$H$517,G$4) -> 0 | H76: =SUMIFS('Transaction Overview'!$D$2:$D$517,'Transaction Overview'!$I$2:$I$517,$A76,'Transaction Overview'!$H$2:$H$517,H$4) -> 0 | I76: =SUMIFS('Transaction Overview'!$D$2:$D$517,'Transaction Overview'!$I$2:$I$517,$A76,'Transaction Overview'!$H$2:$H$517,I$4) -> 0 | ... M76: =SUMIFS('Transaction Overview'!$D$2:$D$517,'Transaction Overview'!$I$2:$I$517,$A76,'Transaction Overview'!$H$2:$H$517,M$4) -> 0 | N76: =SUM(B76:M76) -> -41.99
A77: Personal - Health (incl. Ins.) | B77: =SUMIFS('Transaction Overview'!$D$2:$D$517,'Transaction Overview'!$I$2:$I$517,$A77,'Transaction Overview'!$H$2:$H$517,B$4) -> -2680.47 | C77: =SUMIFS('Transaction Overview'!$D$2:$D$517,'Transaction Overview'!$I$2:$I$517,$A77,'Transaction Overview'!$H$2:$H$517,C$4) -> -2268.26 | D77: =SUMIFS('Transaction Overview'!$D$2:$D$517,'Transaction Overview'!$I$2:$I$517,$A77,'Transaction Overview'!$H$2:$H$517,D$4) -> -3561.69 | E77: =SUMIFS('Transaction Overview'!$D$2:$D$517,'Transaction Overview'!$I$2:$I$517,$A77,'Transaction Overview'!$H$2:$H$517,E$4) -> -1333.85 | F77: =SUMIFS('Transaction Overview'!$D$2:$D$517,'Transaction Overview'!$I$2:$I$517,$A77,'Transaction Overview'!$H$2:$H$517,F$4) -> -2268.27 | G77: =SUMIFS('Transaction Overview'!$D$2:$D$517,'Transaction Overview'!$I$2:$I$517,$A77,'Transaction Overview'!$H$2:$H$517,G$4) -> -2268.27 | H77: =SUMIFS('Transaction Overview'!$D$2:$D$517,'Transaction Overview'!$I$2:$I$517,$A77,'Transaction Overview'!$H$2:$H$517,H$4) -> 0 | I77: =SUMIFS('Transaction Overview'!$D$2:$D$517,'Transaction Overview'!$I$2:$I$517,$A77,'Transaction Overview'!$H$2:$H$517,I$4) -> 0 | ... M77: =SUMIFS('Transaction Overview'!$D$2:$D$517,'Transaction Overview'!$I$2:$I$517,$A77,'Transaction Overview'!$H$2:$H$517,M$4) -> 0 | N77: =SUM(B77:M77) -> -14380.81
A78: Personal - Paypal | B78: =SUMIFS('Transaction Overview'!$D$2:$D$517,'Transaction Overview'!$I$2:$I$517,$A78,'Transaction Overview'!$H$2:$H$517,B$4) -> 0 | C78: =SUMIFS('Transaction Overview'!$D$2:$D$517,'Transaction Overview'!$I$2:$I$517,$A78,'Transaction Overview'!$H$2:$H$517,C$4) -> 0 | D78: =SUMIFS('Transaction Overview'!$D$2:$D$517,'Transaction Overview'!$I$2:$I$517,$A78,'Transaction Overview'!$H$2:$H$517,D$4) -> -100 | E78: =SUMIFS('Transaction Overview'!$D$2:$D$517,'Transaction Overview'!$I$2:$I$517,$A78,'Transaction Overview'!$H$2:$H$517,E$4) -> -103.2 | F78: =SUMIFS('Transaction Overview'!$D$2:$D$517,'Transaction Overview'!$I$2:$I$517,$A78,'Transaction Overview'!$H$2:$H$517,F$4) -> 0 | G78: =SUMIFS('Transaction Overview'!$D$2:$D$517,'Transaction Overview'!$I$2:$I$517,$A78,'Transaction Overview'!$H$2:$H$517,G$4) -> 0 | H78: =SUMIFS('Transaction Overview'!$D$2:$D$517,'Transaction Overview'!$I$2:$I$517,$A78,'Transaction Overview'!$H$2:$H$517,H$4) -> 0 | I78: =SUMIFS('Transaction Overview'!$D$2:$D$517,'Transaction Overview'!$I$2:$I$517,$A78,'Transaction Overview'!$H$2:$H$517,I$4) -> 0 | ... M78: =SUMIFS('Transaction Overview'!$D$2:$D$517,'Transaction Overview'!$I$2:$I$517,$A78,'Transaction Overview'!$H$2:$H$517,M$4) -> 0 | N78: =SUM(B78:M78) -> -203.2
A79: Personal - Subscriptions | B79: =SUMIFS('Transaction Overview'!$D$2:$D$517,'Transaction Overview'!$I$2:$I$517,$A79,'Transaction Overview'!$H$2:$H$517,B$4) -> -95.43 | C79: =SUMIFS('Transaction Overview'!$D$2:$D$517,'Transaction Overview'!$I$2:$I$517,$A79,'Transaction Overview'!$H$2:$H$517,C$4) -> -96.43 | D79: =SUMIFS('Transaction Overview'!$D$2:$D$517,'Transaction Overview'!$I$2:$I$517,$A79,'Transaction Overview'!$H$2:$H$517,D$4) -> -96.43 | E79: =SUMIFS('Transaction Overview'!$D$2:$D$517,'Transaction Overview'!$I$2:$I$517,$A79,'Transaction Overview'!$H$2:$H$517,E$4) -> -97.43 | F79: =SUMIFS('Transaction Overview'!$D$2:$D$517,'Transaction Overview'!$I$2:$I$517,$A79,'Transaction Overview'!$H$2:$H$517,F$4) -> -38.46 | G79: =SUMIFS('Transaction Overview'!$D$2:$D$517,'Transaction Overview'!$I$2:$I$517,$A79,'Transaction Overview'!$H$2:$H$517,G$4) -> 0 | H79: =SUMIFS('Transaction Overview'!$D$2:$D$517,'Transaction Overview'!$I$2:$I$517,$A79,'Transaction Overview'!$H$2:$H$517,H$4) -> 0 | I79: =SUMIFS('Transaction Overview'!$D$2:$D$517,'Transaction Overview'!$I$2:$I$517,$A79,'Transaction Overview'!$H$2:$H$517,I$4) -> 0 | ... M79: =SUMIFS('Transaction Overview'!$D$2:$D$517,'Transaction Overview'!$I$2:$I$517,$A79,'Transaction Overview'!$H$2:$H$517,M$4) -> 0 | N79: =SUM(B79:M79) -> -424.18
A80: Texas - House Utilities | B80: =SUMIFS('Transaction Overview'!$D$2:$D$517,'Transaction Overview'!$I$2:$I$517,$A80,'Transaction Overview'!$H$2:$H$517,B$4) -> 0 | C80: =SUMIFS('Transaction Overview'!$D$2:$D$517,'Transaction Overview'!$I$2:$I$517,$A80,'Transaction Overview'!$H$2:$H$517,C$4) -> 0 | D80: =SUMIFS('Transaction Overview'!$D$2:$D$517,'Transaction Overview'!$I$2:$I$517,$A80,'Transaction Overview'!$H$2:$H$517,D$4) -> 0 | E80: =SUMIFS('Transaction Overview'!$D$2:$D$517,'Transaction Overview'!$I$2:$I$517,$A80,'Transaction Overview'!$H$2:$H$517,E$4) -> -238.53 | F80: =SUMIFS('Transaction Overview'!$D$2:$D$517,'Transaction Overview'!$I$2:$I$517,$A80,'Transaction Overview'!$H$2:$H$517,F$4) -> -252.8 | G80: =SUMIFS('Transaction Overview'!$D$2:$D$517,'Transaction Overview'!$I$2:$I$517,$A80,'Transaction Overview'!$H$2:$H$517,G$4) -> -537 | H80: =SUMIFS('Transaction Overview'!$D$2:$D$517,'Transaction Overview'!$I$2:$I$517,$A80,'Transaction Overview'!$H$2:$H$517,H$4) -> 0 | I80: =SUMIFS('Transaction Overview'!$D$2:$D$517,'Transaction Overview'!$I$2:$I$517,$A80,'Transaction Overview'!$H$2:$H$517,I$4) -> 0 | ... M80: =SUMIFS('Transaction Overview'!$D$2:$D$517,'Transaction Overview'!$I$2:$I$517,$A80,'Transaction Overview'!$H$2:$H$517,M$4) -> 0 | N80: =SUM(B80:M80) -> -1028.33
A81: Adjustments
A82: Insurance | B82: =SUMIFS('Transaction Overview'!$D$2:$D$517,'Transaction Overview'!$I$2:$I$517,$A82,'Transaction Overview'!$H$2:$H$517,B$4) -> 0 | C82: =SUMIFS('Transaction Overview'!$D$2:$D$517,'Transaction Overview'!$I$2:$I$517,$A82,'Transaction Overview'!$H$2:$H$517,C$4) -> 1688.08 | D82: =SUMIFS('Transaction Overview'!$D$2:$D$517,'Transaction Overview'!$I$2:$I$517,$A82,'Transaction Overview'!$H$2:$H$517,D$4) -> 0 | E82: =SUMIFS('Transaction Overview'!$D$2:$D$517,'Transaction Overview'!$I$2:$I$517,$A82,'Transaction Overview'!$H$2:$H$517,E$4) -> 0 | F82: =SUMIFS('Transaction Overview'!$D$2:$D$517,'Transaction Overview'!$I$2:$I$517,$A82,'Transaction Overview'!$H$2:$H$517,F$4) -> 0 | G82: =SUMIFS('Transaction Overview'!$D$2:$D$517,'Transaction Overview'!$I$2:$I$517,$A82,'Transaction Overview'!$H$2:$H$517,G$4) -> 0 | H82: =SUMIFS('Transaction Overview'!$D$2:$D$517,'Transaction Overview'!$I$2:$I$517,$A82,'Transaction Overview'!$H$2:$H$517,H$4) -> 0 | I82: =SUMIFS('Transaction Overview'!$D$2:$D$517,'Transaction Overview'!$I$2:$I$517,$A82,'Transaction Overview'!$H$2:$H$517,I$4) -> 0 | ... M82: =SUMIFS('Transaction Overview'!$D$2:$D$517,'Transaction Overview'!$I$2:$I$517,$A82,'Transaction Overview'!$H$2:$H$517,M$4) -> 0 | N82: =SUM(B82:M82) -> 1688.08
A83: Uncategorized — Review
A84: ??? | B84: =SUMIFS('Transaction Overview'!$D$2:$D$517,'Transaction Overview'!$I$2:$I$517,$A84,'Transaction Overview'!$H$2:$H$517,B$4) -> -331.54 | C84: =SUMIFS('Transaction Overview'!$D$2:$D$517,'Transaction Overview'!$I$2:$I$517,$A84,'Transaction Overview'!$H$2:$H$517,C$4) -> -331.54 | D84: =SUMIFS('Transaction Overview'!$D$2:$D$517,'Transaction Overview'!$I$2:$I$517,$A84,'Transaction Overview'!$H$2:$H$517,D$4) -> -1811.09 | E84: =SUMIFS('Transaction Overview'!$D$2:$D$517,'Transaction Overview'!$I$2:$I$517,$A84,'Transaction Overview'!$H$2:$H$517,E$4) -> 0 | F84: =SUMIFS('Transaction Overview'!$D$2:$D$517,'Transaction Overview'!$I$2:$I$517,$A84,'Transaction Overview'!$H$2:$H$517,F$4) -> -331.54 | G84: =SUMIFS('Transaction Overview'!$D$2:$D$517,'Transaction Overview'!$I$2:$I$517,$A84,'Transaction Overview'!$H$2:$H$517,G$4) -> 0 | H84: =SUMIFS('Transaction Overview'!$D$2:$D$517,'Transaction Overview'!$I$2:$I$517,$A84,'Transaction Overview'!$H$2:$H$517,H$4) -> 0 | I84: =SUMIFS('Transaction Overview'!$D$2:$D$517,'Transaction Overview'!$I$2:$I$517,$A84,'Transaction Overview'!$H$2:$H$517,I$4) -> 0 | ... M84: =SUMIFS('Transaction Overview'!$D$2:$D$517,'Transaction Overview'!$I$2:$I$517,$A84,'Transaction Overview'!$H$2:$H$517,M$4) -> 0 | N84: =SUM(B84:M84) -> -2805.71
A85: ATM/Cash | B85: =SUMIFS('Transaction Overview'!$D$2:$D$517,'Transaction Overview'!$I$2:$I$517,$A85,'Transaction Overview'!$H$2:$H$517,B$4) -> 0 | C85: =SUMIFS('Transaction Overview'!$D$2:$D$517,'Transaction Overview'!$I$2:$I$517,$A85,'Transaction Overview'!$H$2:$H$517,C$4) -> 0 | D85: =SUMIFS('Transaction Overview'!$D$2:$D$517,'Transaction Overview'!$I$2:$I$517,$A85,'Transaction Overview'!$H$2:$H$517,D$4) -> 0 | E85: =SUMIFS('Transaction Overview'!$D$2:$D$517,'Transaction Overview'!$I$2:$I$517,$A85,'Transaction Overview'!$H$2:$H$517,E$4) -> -103.95 | F85: =SUMIFS('Transaction Overview'!$D$2:$D$517,'Transaction Overview'!$I$2:$I$517,$A85,'Transaction Overview'!$H$2:$H$517,F$4) -> 0 | G85: =SUMIFS('Transaction Overview'!$D$2:$D$517,'Transaction Overview'!$I$2:$I$517,$A85,'Transaction Overview'!$H$2:$H$517,G$4) -> 0 | H85: =SUMIFS('Transaction Overview'!$D$2:$D$517,'Transaction Overview'!$I$2:$I$517,$A85,'Transaction Overview'!$H$2:$H$517,H$4) -> 0 | I85: =SUMIFS('Transaction Overview'!$D$2:$D$517,'Transaction Overview'!$I$2:$I$517,$A85,'Transaction Overview'!$H$2:$H$517,I$4) -> 0 | ... M85: =SUMIFS('Transaction Overview'!$D$2:$D$517,'Transaction Overview'!$I$2:$I$517,$A85,'Transaction Overview'!$H$2:$H$517,M$4) -> 0 | N85: =SUM(B85:M85) -> -103.95
A86: XXX? | B86: =SUMIFS('Transaction Overview'!$D$2:$D$517,'Transaction Overview'!$I$2:$I$517,$A86,'Transaction Overview'!$H$2:$H$517,B$4) -> 0 | C86: =SUMIFS('Transaction Overview'!$D$2:$D$517,'Transaction Overview'!$I$2:$I$517,$A86,'Transaction Overview'!$H$2:$H$517,C$4) -> 0 | D86: =SUMIFS('Transaction Overview'!$D$2:$D$517,'Transaction Overview'!$I$2:$I$517,$A86,'Transaction Overview'!$H$2:$H$517,D$4) -> 0 | E86: =SUMIFS('Transaction Overview'!$D$2:$D$517,'Transaction Overview'!$I$2:$I$517,$A86,'Transaction Overview'!$H$2:$H$517,E$4) -> -331.54 | F86: =SUMIFS('Transaction Overview'!$D$2:$D$517,'Transaction Overview'!$I$2:$I$517,$A86,'Transaction Overview'!$H$2:$H$517,F$4) -> 0 | G86: =SUMIFS('Transaction Overview'!$D$2:$D$517,'Transaction Overview'!$I$2:$I$517,$A86,'Transaction Overview'!$H$2:$H$517,G$4) -> 0 | H86: =SUMIFS('Transaction Overview'!$D$2:$D$517,'Transaction Overview'!$I$2:$I$517,$A86,'Transaction Overview'!$H$2:$H$517,H$4) -> 0 | I86: =SUMIFS('Transaction Overview'!$D$2:$D$517,'Transaction Overview'!$I$2:$I$517,$A86,'Transaction Overview'!$H$2:$H$517,I$4) -> 0 | ... M86: =SUMIFS('Transaction Overview'!$D$2:$D$517,'Transaction Overview'!$I$2:$I$517,$A86,'Transaction Overview'!$H$2:$H$517,M$4) -> 0 | N86: =SUM(B86:M86) -> -331.54

Sheet Transfer In
A1: Chase 1168 — DWG Capital Group 2026 Activity
A2: Intercompany Transfers — In | Jan 2026 – Dec 2026
A4: SUMMARY
A5: Total | C5: =SUMIFS('Transaction Overview'!$D$2:$D$517,'Transaction Overview'!$J$2:$J$517,"Intercompany & Savings Transfers",'Transaction Overview'!$D$2:$D$517,">0") -> 0
A6: # Transactions | C6: =COUNTIFS('Transaction Overview'!$J$2:$J$517,"Intercompany & Savings Transfers",'Transaction Overview'!$D$2:$D$517,">0") -> 0

Sheet Transfer Out
A1: Chase 1168 — DWG Capital Group 2026 Activity
A2: Intercompany Transfers — Out | Jan 2026 – Dec 2026
A4: SUMMARY
A5: Total | C5: =SUMIFS('Transaction Overview'!$D$2:$D$517,'Transaction Overview'!$J$2:$J$517,"Intercompany & Savings Transfers",'Transaction Overview'!$D$2:$D$517,"<0") -> -25198.18
A6: # Transactions | C6: =COUNTIFS('Transaction Overview'!$J$2:$J$517,"Intercompany & Savings Transfers",'Transaction Overview'!$D$2:$D$517,"<0") -> 20

Sheet Wire In
A1: Chase 1168 — DWG Capital Group 2026 Activity
A2: Wire Transfers — In | Jan 2026 – Dec 2026
A4: SUMMARY
A5: Total | C5: =SUMIFS('Transaction Overview'!$D$2:$D$517,'Transaction Overview'!$J$2:$J$517,"Intercompany & Savings Transfers",'Transaction Overview'!$D$2:$D$517,">0") -> 0
A6: # Transactions | C6: =COUNTIFS('Transaction Overview'!$J$2:$J$517,"Intercompany & Savings Transfers",'Transaction Overview'!$D$2:$D$517,">0") -> 0

Sheet Wire Out
A1: Chase 1168 — DWG Capital Group 2026 Activity
A2: Wire Transfers — Out | Jan 2026 – Dec 2026
A4: SUMMARY
A5: Total | C5: =SUMIFS('Transaction Overview'!$D$2:$D$517,'Transaction Overview'!$J$2:$J$517,"Intercompany & Savings Transfers",'Transaction Overview'!$D$2:$D$517,"<0") -> -25198.18
A6: # Transactions | C6: =COUNTIFS('Transaction Overview'!$J$2:$J$517,"Intercompany & Savings Transfers",'Transaction Overview'!$D$2:$D$517,"<0") -> 20

Sheet Commission
A1: Chase 1168 — DWG Capital Group 2026 Activity
A2: Commissions Statement | Jan 2026 – Dec 2026
A4: SUMMARY
A5: Total | C5: =SUMIFS('Transaction Overview'!$D$2:$D$517,'Transaction Overview'!$J$2:$J$517,"Commissions — Incoming",'Transaction Overview'!$D$2:$D$517,">0") -> 114000
A6: # Transactions | C6: =COUNTIFS('Transaction Overview'!$J$2:$J$517,"Commissions — Incoming",'Transaction Overview'!$D$2:$D$517,">0") -> 1

Sheet Transaction Overview
A1: Details | B1: Posting Date | C1: Description | D1: Amount | E1: Type | F1: Balance | G1: Category | H1: Month | I1: Combined Category | J1: Group
A2: =Chase1168_2026!A2 -> DEBIT | B2: =Chase1168_2026!B2 -> 46188 | C2: =Chase1168_2026!C2 -> ORIG CO NAME:VENMO CO ENTRY DESCR:PAYMENT SEC:WEB IND ID:1051023030786 ORIG ID:3264681992 | D2: =Chase1168_2026!D2 -> -15 | E2: =Chase1168_2026!E2 -> ACH_DEBIT | F2: =Chase1168_2026!F2 | G2: =Chase1168_2026!G2 -> Venmo | H2: =IF($B2="","",DATE(YEAR($B2),MONTH($B2),1)) -> 46174 | I2: =IF($G2="","Uncategorized — Review",IFERROR(INDEX(Mapping!$B:$B,MATCH($G2,Mapping!$A:$A,0)),"Uncategorized — Review")) -> Venmo | J2: =IF($G2="","Uncategorized — Review",IFERROR(INDEX(Mapping!$C:$C,MATCH($G2,Mapping!$A:$A,0)),"Uncategorized — Review")) -> P2P Payments (Zelle/Venmo/PayPal)
A3: =Chase1168_2026!A3 -> DEBIT | B3: =Chase1168_2026!B3 -> 46188 | C3: =Chase1168_2026!C3 -> ONLINE TRANSFER TO CHK ...1117 TRANSACTION#: 29633194527 06/15 | D3: =Chase1168_2026!D3 -> -1000 | E3: =Chase1168_2026!E3 -> ACCT_XFER | F3: =Chase1168_2026!F3 | G3: =Chase1168_2026!G3 -> Transfer to Angela Dunning | H3: =IF($B3="","",DATE(YEAR($B3),MONTH($B3),1)) -> 46174 | I3: =IF($G3="","Uncategorized — Review",IFERROR(INDEX(Mapping!$B:$B,MATCH($G3,Mapping!$A:$A,0)),"Uncategorized — Review")) -> Transfer to Angela Dunning | J3: =IF($G3="","Uncategorized — Review",IFERROR(INDEX(Mapping!$C:$C,MATCH($G3,Mapping!$A:$A,0)),"Uncategorized — Review")) -> Owner / Family Distributions
A4: =Chase1168_2026!A4 -> DEBIT | B4: =Chase1168_2026!B4 -> 46188 | C4: =Chase1168_2026!C4 -> Online ACH payment to Mike | D4: =Chase1168_2026!D4 -> -2000 | E4: =Chase1168_2026!E4 -> BASIC_PAYROLL | F4: =Chase1168_2026!F4 | G4: =Chase1168_2026!G4 -> Mike Paytonjian - Payroll | H4: =IF($B4="","",DATE(YEAR($B4),MONTH($B4),1)) -> 46174 | I4: =IF($G4="","Uncategorized — Review",IFERROR(INDEX(Mapping!$B:$B,MATCH($G4,Mapping!$A:$A,0)),"Uncategorized — Review")) -> Mike Paytonjian - Payroll | J4: =IF($G4="","Uncategorized — Review",IFERROR(INDEX(Mapping!$C:$C,MATCH($G4,Mapping!$A:$A,0)),"Uncategorized — Review")) -> Payroll & Contractors
A5: =Chase1168_2026!A5 -> DEBIT | B5: =Chase1168_2026!B5 -> 46188 | C5: =Chase1168_2026!C5 -> ORIG CO NAME:VENMO CO ENTRY DESCR:PAYMENT SEC:WEB IND ID:1050998946316 ORIG ID:3264681992 | D5: =Chase1168_2026!D5 -> -150 | E5: =Chase1168_2026!E5 -> ACH_DEBIT | F5: =Chase1168_2026!F5 | G5: =Chase1168_2026!G5 -> Venmo | H5: =IF($B5="","",DATE(YEAR($B5),MONTH($B5),1)) -> 46174 | I5: =IF($G5="","Uncategorized — Review",IFERROR(INDEX(Mapping!$B:$B,MATCH($G5,Mapping!$A:$A,0)),"Uncategorized — Review")) -> Venmo | J5: =IF($G5="","Uncategorized — Review",IFERROR(INDEX(Mapping!$C:$C,MATCH($G5,Mapping!$A:$A,0)),"Uncategorized — Review")) -> P2P Payments (Zelle/Venmo/PayPal)
A6: =Chase1168_2026!A6 -> DEBIT | B6: =Chase1168_2026!B6 -> 46188 | C6: =Chase1168_2026!C6 -> ORIG CO NAME:VENMO CO ENTRY DESCR:PAYMENT SEC:WEB IND ID:1050990087863 ORIG ID:3264681992 | D6: =Chase1168_2026!D6 -> -200 | E6: =Chase1168_2026!E6 -> ACH_DEBIT | F6: =Chase1168_2026!F6 | G6: =Chase1168_2026!G6 -> Venmo | H6: =IF($B6="","",DATE(YEAR($B6),MONTH($B6),1)) -> 46174 | I6: =IF($G6="","Uncategorized — Review",IFERROR(INDEX(Mapping!$B:$B,MATCH($G6,Mapping!$A:$A,0)),"Uncategorized — Review")) -> Venmo | J6: =IF($G6="","Uncategorized — Review",IFERROR(INDEX(Mapping!$C:$C,MATCH($G6,Mapping!$A:$A,0)),"Uncategorized — Review")) -> P2P Payments (Zelle/Venmo/PayPal)
A7: =Chase1168_2026!A7 -> DEBIT | B7: =Chase1168_2026!B7 -> 46188 | C7: =Chase1168_2026!C7 -> ONLINE TRANSFER TO CHK ...1117 TRANSACTION#: 29624118889 06/15 | D7: =Chase1168_2026!D7 -> -500 | E7: =Chase1168_2026!E7 -> ACCT_XFER | F7: =Chase1168_2026!F7 | G7: =Chase1168_2026!G7 -> Transfer to Angela Dunning | H7: =IF($B7="","",DATE(YEAR($B7),MONTH($B7),1)) -> 46174 | I7: =IF($G7="","Uncategorized — Review",IFERROR(INDEX(Mapping!$B:$B,MATCH($G7,Mapping!$A:$A,0)),"Uncategorized — Review")) -> Transfer to Angela Dunning | J7: =IF($G7="","Uncategorized — Review",IFERROR(INDEX(Mapping!$C:$C,MATCH($G7,Mapping!$A:$A,0)),"Uncategorized — Review")) -> Owner / Family Distributions
A8: =Chase1168_2026!A8 -> DEBIT | B8: =Chase1168_2026!B8 -> 46188 | C8: =Chase1168_2026!C8 -> ONLINE TRANSFER TO CHK ...6975 TRANSACTION#: 29624118165 06/15 | D8: =Chase1168_2026!D8 -> -200 | E8: =Chase1168_2026!E8 -> ACCT_XFER | F8: =Chase1168_2026!F8 | G8: =Chase1168_2026!G8 -> Transfer to Angela Dunning | H8: =IF($B8="","",DATE(YEAR($B8),MONTH($B8),1)) -> 46174 | I8: =IF($G8="","Uncategorized — Review",IFERROR(INDEX(Mapping!$B:$B,MATCH($G8,Mapping!$A:$A,0)),"Uncategorized — Review")) -> Transfer to Angela Dunning | J8: =IF($G8="","Uncategorized — Review",IFERROR(INDEX(Mapping!$C:$C,MATCH($G8,Mapping!$A:$A,0)),"Uncategorized — Review")) -> Owner / Family Distributions
A9: =Chase1168_2026!A9 -> DEBIT | B9: =Chase1168_2026!B9 -> 46188 | C9: =Chase1168_2026!C9 -> ZELLE PAYMENT TO JEFFREY SEIDER JPM99CKSLP03 | D9: =Chase1168_2026!D9 -> -200 | E9: =Chase1168_2026!E9 -> CHASE_TO_PARTNERFI | F9: =Chase1168_2026!F9 | G9: =Chase1168_2026!G9 -> Zelle - Jeff Seider | H9: =IF($B9="","",DATE(YEAR($B9),MONTH($B9),1)) -> 46174 | I9: =IF($G9="","Uncategorized — Review",IFERROR(INDEX(Mapping!$B:$B,MATCH($G9,Mapping!$A:$A,0)),"Uncategorized — Review")) -> Zelle - Jeff Seider | J9: =IF($G9="","Uncategorized — Review",IFERROR(INDEX(Mapping!$C:$C,MATCH($G9,Mapping!$A:$A,0)),"Uncategorized — Review")) -> P2P Payments (Zelle/Venmo/PayPal)
A10: =Chase1168_2026!A10 -> DEBIT | B10: =Chase1168_2026!B10 -> 46188 | C10: =Chase1168_2026!C10 -> ONLINE TRANSFER TO CHK ...1117 TRANSACTION#: 29617096887 06/15 | D10: =Chase1168_2026!D10 -> -3000 | E10: =Chase1168_2026!E10 -> ACCT_XFER | F10: =Chase1168_2026!F10 | G10: =Chase1168_2026!G10 -> Transfer to Angela Dunning | H10: =IF($B10="","",DATE(YEAR($B10),MONTH($B10),1)) -> 46174 | I10: =IF($G10="","Uncategorized — Review",IFERROR(INDEX(Mapping!$B:$B,MATCH($G10,Mapping!$A:$A,0)),"Uncategorized — Review")) -> Transfer to Angela Dunning | J10: =IF($G10="","Uncategorized — Review",IFERROR(INDEX(Mapping!$C:$C,MATCH($G10,Mapping!$A:$A,0)),"Uncategorized — Review")) -> Owner / Family Distributions
A11: =Chase1168_2026!A11 -> DEBIT | B11: =Chase1168_2026!B11 -> 46188 | C11: =Chase1168_2026!C11 -> POS DEBIT GODADDY#4111542544 480-5058855 AZ 9052 | D11: =Chase1168_2026!D11 -> -45.96 | E11: =Chase1168_2026!E11 -> MISC_DEBIT | F11: =Chase1168_2026!F11 | G11: =Chase1168_2026!G11 -> Go Daddy | H11: =IF($B11="","",DATE(YEAR($B11),MONTH($B11),1)) -> 46174 | I11: =IF($G11="","Uncategorized — Review",IFERROR(INDEX(Mapping!$B:$B,MATCH($G11,Mapping!$A:$A,0)),"Uncategorized — Review")) -> Go Daddy | J11: =IF($G11="","Uncategorized — Review",IFERROR(INDEX(Mapping!$C:$C,MATCH($G11,Mapping!$A:$A,0)),"Uncategorized — Review")) -> DWG Operating
A12: =Chase1168_2026!A12 -> DEBIT | B12: =Chase1168_2026!B12 -> 46185 | C12: =Chase1168_2026!C12 -> GODADDY#4110236617 480-5058855 AZ 06/11 | D12: =Chase1168_2026!D12 -> -60.73 | E12: =Chase1168_2026!E12 -> DEBIT_CARD | F12: =Chase1168_2026!F12 -> 24009.79 | G12: =Chase1168_2026!G12 -> Go Daddy | H12: =IF($B12="","",DATE(YEAR($B12),MONTH($B12),1)) -> 46174 | I12: =IF($G12="","Uncategorized — Review",IFERROR(INDEX(Mapping!$B:$B,MATCH($G12,Mapping!$A:$A,0)),"Uncategorized — Review")) -> Go Daddy | J12: =IF($G12="","Uncategorized — Review",IFERROR(INDEX(Mapping!$C:$C,MATCH($G12,Mapping!$A:$A,0)),"Uncategorized — Review")) -> DWG Operating
A13: =Chase1168_2026!A13 -> DEBIT | B13: =Chase1168_2026!B13 -> 46184 | C13: =Chase1168_2026!C13 -> Zelle payment to Jeffrey Seider JPM99ckg6uwz | D13: =Chase1168_2026!D13 -> -200 | E13: =Chase1168_2026!E13 -> CHASE_TO_PARTNERFI | F13: =Chase1168_2026!F13 -> 24070.52 | G13: =Chase1168_2026!G13 -> Zelle - Jeff Seider | H13: =IF($B13="","",DATE(YEAR($B13),MONTH($B13),1)) -> 46174 | I13: =IF($G13="","Uncategorized — Review",IFERROR(INDEX(Mapping!$B:$B,MATCH($G13,Mapping!$A:$A,0)),"Uncategorized — Review")) -> Zelle - Jeff Seider | J13: =IF($G13="","Uncategorized — Review",IFERROR(INDEX(Mapping!$C:$C,MATCH($G13,Mapping!$A:$A,0)),"Uncategorized — Review")) -> P2P Payments (Zelle/Venmo/PayPal)
... A517: =Chase1168_2026!A517 -> DEBIT | B517: =Chase1168_2026!B517 -> 46024 | C517: =Chase1168_2026!C517 -> ORIG CO NAME:BLUESHIELDCA ORIG ID:7529219311 DESC DATE:251231 CO ENTRY DESCR:BILL PAY SEC:CCD TRACE#:031101115700064 EED:260102 IND ID:15728029331 IND NAME:ANGELA DUNNING TRN: 0025700064TC | D517: =Chase1168_2026!D517 -> -974.85 | E517: =Chase1168_2026!E517 -> ACH_DEBIT | F517: =Chase1168_2026!F517 -> 29231.38 | G517: =Chase1168_2026!G517 -> Personal - Health Insurance | H517: =IF($B517="","",DATE(YEAR($B517),MONTH($B517),1)) -> 46023 | I517: =IF($G517="","Uncategorized — Review",IFERROR(INDEX(Mapping!$B:$B,MATCH($G517,Mapping!$A:$A,0)),"Uncategorized — Review")) -> Personal - Health (incl. Ins.) | J517: =IF($G517="","Uncategorized — Review",IFERROR(INDEX(Mapping!$C:$C,MATCH($G517,Mapping!$A:$A,0)),"Uncategorized — Review")) -> Personal — Owner

Sheet Mapping
A1: Raw Category | B1: Combined Category | C1: Group
A2: ??? | B2: ??? | C2: Uncategorized — Review
A3: AI Subscriptions | B3: AI Subscriptions | C3: DWG Operating
A4: ATM/Cash | B4: ATM/Cash | C4: Uncategorized — Review
A5: Andres Alarcon Payroll | B5: Andres Alarcon Payroll | C5: Payroll & Contractors
A6: Bank Fees | B6: Bank Fees | C6: DWG Operating
A7: Bill Payment | B7: Bill Payment | C7: DWG Operating
A8: Chase Hall - Payroll | B8: Chase Hall - Payroll | C8: Payroll & Contractors
A9: DWG Capital Group - Taxes | B9: Taxes | C9: Taxes
A10: DWG HR | B10: DWG HR | C10: Payroll & Contractors
A11: DWG Marketing | B11: DWG Marketing | C11: DWG Operating
A12: DWGCP Business Development | B12: DWGCP Business Development | C12: DWG Operating
... A74: Zelle/P2P | B74: Zelle/P2P | C74: P2P Payments (Zelle/Venmo/PayPal)

Sheet Chase1168_2026
A1: Details | B1: Posting Date | C1: Description | D1: Amount | E1: Type | F1: Balance | G1: Category
A2: DEBIT | B2: 46188 | C2: ORIG CO NAME:VENMO CO ENTRY DESCR:PAYMENT SEC:WEB IND ID:1051023030786 ORIG ID:3264681992 | D2: -15 | E2: ACH_DEBIT | G2: Venmo
A3: DEBIT | B3: 46188 | C3: ONLINE TRANSFER TO CHK ...1117 TRANSACTION#: 29633194527 06/15 | D3: -1000 | E3: ACCT_XFER | G3: Transfer to Angela Dunning
A4: DEBIT | B4: 46188 | C4: Online ACH payment to Mike | D4: -2000 | E4: BASIC_PAYROLL | G4: Mike Paytonjian - Payroll
A5: DEBIT | B5: 46188 | C5: ORIG CO NAME:VENMO CO ENTRY DESCR:PAYMENT SEC:WEB IND ID:1050998946316 ORIG ID:3264681992 | D5: -150 | E5: ACH_DEBIT | G5: Venmo
A6: DEBIT | B6: 46188 | C6: ORIG CO NAME:VENMO CO ENTRY DESCR:PAYMENT SEC:WEB IND ID:1050990087863 ORIG ID:3264681992 | D6: -200 | E6: ACH_DEBIT | G6: Venmo
A7: DEBIT | B7: 46188 | C7: ONLINE TRANSFER TO CHK ...1117 TRANSACTION#: 29624118889 06/15 | D7: -500 | E7: ACCT_XFER | G7: Transfer to Angela Dunning
A8: DEBIT | B8: 46188 | C8: ONLINE TRANSFER TO CHK ...6975 TRANSACTION#: 29624118165 06/15 | D8: -200 | E8: ACCT_XFER | G8: Transfer to Angela Dunning
A9: DEBIT | B9: 46188 | C9: ZELLE PAYMENT TO JEFFREY SEIDER JPM99CKSLP03 | D9: -200 | E9: CHASE_TO_PARTNERFI | G9: Zelle - Jeff Seider
A10: DEBIT | B10: 46188 | C10: ONLINE TRANSFER TO CHK ...1117 TRANSACTION#: 29617096887 06/15 | D10: -3000 | E10: ACCT_XFER | G10: Transfer to Angela Dunning
A11: DEBIT | B11: 46188 | C11: POS DEBIT GODADDY#4111542544 480-5058855 AZ 9052 | D11: -45.96 | E11: MISC_DEBIT | G11: Go Daddy
A12: DEBIT | B12: 46185 | C12: GODADDY#4110236617 480-5058855 AZ 06/11 | D12: -60.73 | E12: DEBIT_CARD | F12: 24009.79 | G12: Go Daddy
A13: DEBIT | B13: 46184 | C13: Zelle payment to Jeffrey Seider JPM99ckg6uwz | D13: -200 | E13: CHASE_TO_PARTNERFI | F13: 24070.52 | G13: Zelle - Jeff Seider
A14: DEBIT | B14: 46184 | C14: Basic Online Payroll Payment 11221138563 to #####5820 | D14: -3500 | E14: BASIC_PAYROLL | F14: 24270.52 | G14: Chase Hall - Payroll
A15: DEBIT | B15: 46184 | C15: GODADDY#4109280643 480-5058855 AZ 06/10 | D15: -28.98 | E15: DEBIT_CARD | F15: 27770.52 | G15: Go Daddy
A16: DEBIT | B16: 46183 | C16: PAYPAL *RUTHALCANCI 402-935-7733 CA 06/10 | D16: -81.18 | E16: DEBIT_CARD | F16: 27799.5 | G16: Ruth Alcancia - Forward Bridge Payment
A17: DEBIT | B17: 46183 | C17: GODADDY#4108424098 480-5058855 AZ 06/09 | D17: -13.79 | E17: DEBIT_CARD | F17: 27880.68 | G17: Go Daddy
A18: DEBIT | B18: 46182 | C18: Online Transfer to CHK ...1117 transaction#: 29555521399 06/09 | D18: -2000 | E18: ACCT_XFER | F18: 27894.47 | G18: Transfer to Angela Dunning
A19: DEBIT | B19: 46182 | C19: ORIG CO NAME:VENMO ORIG ID:3264681992 DESC DATE:260609 CO ENTRY DESCR:PAYMENT SEC:WEB TRACE#:021000025685331 EED:260609 IND ID:1050868364682 IND NAME:JUDD DUNNING 260609PPZPM4 TRN: 1605685331TC | D19: -555 | E19: ACH_DEBIT | F19: 29894.47 | G19: Venmo
A20: DEBIT | B20: 46182 | C20: GODADDY#4107740767 480-5058855 AZ 06/08 | D20: -33.97 | E20: DEBIT_CARD | F20: 30449.47 | G20: Go Daddy
A21: DEBIT | B21: 46181 | C21: Zelle payment to Michael Paytonjian JPM99ck4jzdu | D21: -95 | E21: CHASE_TO_PARTNERFI | F21: 30483.44 | G21: Office/Miscellaneous Reimbursement - Mike P.
A22: DEBIT | B22: 46181 | C22: Basic Online Payroll Payment 11221685096 to ########4122 | D22: -2000 | E22: BASIC_PAYROLL | F22: 30578.44 | G22: Mike Paytonjian - Payroll
A23: DEBIT | B23: 46181 | C23: ORIG CO NAME:VENMO ORIG ID:3264681992 DESC DATE:260606 CO ENTRY DESCR:PAYMENT SEC:WEB TRACE#:021000021456247 EED:260608 IND ID:1050813336826 IND NAME:JUDD DUNNING 260606PPZDEU TRN: 1591456247TC | D23: -300 | E23: ACH_DEBIT | F23: 32578.44 | G23: Venmo
... A142: DEBIT | B142: 46146 | C142: DNH*GODADDY#4078685355 480-5058855 AZ 05/02 | D142: -5.99 | E142: DEBIT_CARD | F142: 17910.19 | G142: Go Daddy
A143: DEBIT | B143: 46146 | C143: ORIG CO NAME:EMPLOYMENT DEVEL ORIG ID:2282533055 DESC DATE:050126 CO ENTRY DESCR:EDD EFTPMTSEC:CCD TRACE#:042000016029479 EED:260504 IND ID:1351068640 IND NAME:DWG CAPITAL GROUP PAYMENT TRN: 1246029479TC | D143: -291 | E143: ACH_DEBIT | F143: 17916.18
A144: DEBIT | B144: 46146 | C144: DNH*GODADDY#4077842333 480-5058855 AZ 05/01 | D144: -33.97 | E144: DEBIT_CARD | F144: 18207.18 | G144: Go Daddy
A145: DEBIT | B145: 46143 | C145: STANDARD ACH PMNTS INITIAL FEE QTY = 7 | D145: -17.5 | E145: FEE_TRANSACTION | F145: 18241.15 | G145: Bank Fees
A146: DEBIT | B146: 46143 | C146: ORIG CO NAME:VENMO ORIG ID:3264681992 DESC DATE:260501 CO ENTRY DESCR:PAYMENT SEC:WEB TRACE#:021000029540738 EED:260501 IND ID:1049980492507 IND NAME:JUDD DUNNING 260501PPZO17 TRN: 1219540738TC | D146: -150 | E146: ACH_DEBIT | F146: 18258.65 | G146: Venmo
A147: DEBIT | B147: 46143 | C147: ORIG CO NAME:GEICO ORIG ID:3530075853 DESC DATE:260430 CO ENTRY DESCR:PREM COLL SEC:PPD TRACE#:021000022536535 EED:260501 IND ID: IND NAME:ANGELA TRN: 1212536535TC | D147: -617.48 | E147: ACH_DEBIT | F147: 18408.65 | G147: Personal - Car Insurance
A148: DEBIT | B148: 46143 | C148: ORIG CO NAME:BLUESHIELDCA ORIG ID:7529219311 DESC DATE:260430 CO ENTRY DESCR:BILL PAY SEC:CCD TRACE#:031101116152207 EED:260501 IND ID:15761246761 IND NAME:ANGELA DUNNING TRN: 1216152207TC | D148: -974.85 | E148: ACH_DEBIT | F148: 19026.13 | G148: Personal - Health Insurance
A149: DEBIT | B149: 46143 | C149: ORIG CO NAME:GM Financial ORIG ID:I522190781 DESC DATE:260501 CO ENTRY DESCR:GMF Pymt SEC:WEB TRACE#:091000016699401 EED:260501 IND ID:00112079186353 IND NAME:ANGELA DUNNING TRN: 1216699401TC | D149: -1063.05 | E149: ACH_DEBIT | F149: 20000.98 | G149: Personal - Car
A150: DEBIT | B150: 46143 | C150: Zelle payment to natalie cordova JPM99cf7c3c2 | D150: -500 | E150: CHASE_TO_PARTNERFI | F150: 21064.03 | G150: Zelle - Natalie C.
A151: CREDIT | B151: 46143 | C151: ORIG CO NAME:GI CAPITAL GROUP ORIG ID:9200502235 DESC DATE:260501 CO ENTRY DESCR:ACH Pmt SEC:CCD TRACE#:021000026610717 EED:260501 IND ID:11217147186 IND NAME:DWG CAPITAL GROUP For May-2026 (E4: $4190.21 + E7: 43 66.20 = $8,556.41) TRN: 1216610717TC | D151: 8556.41 | E151: ACH_CREDIT | F151: 21564.03 | G151: Incoming MOAB Mortgage Coverage
A152: DEBIT | B152: 46142 | C152: Basic Online Payroll Payment 11215663814 to #####5820 | D152: -3500 | E152: BASIC_PAYROLL | F152: 13007.62 | G152: Chase Hall - Payroll
A153: DEBIT | B153: 46142 | C153: ORIG CO NAME:SBA EIDL LOAN ORIG ID:7300000118 DESC DATE:260429 CO ENTRY DESCR:PAYMENT SEC:CCD TRACE#:041036048645279 EED:260430 IND ID:0000 IND NAME:JOHN DUNNING 1871308204 ACH TRANSACTION TRN: 1208645279TC | D153: -2524 | E153: ACH_DEBIT | F153: 16507.62 | G153: SBC EIDL Loan
A154: DEBIT | B154: 46141 | C154: ORIG CO NAME:GEICO CO ENTRY DESCR:PREM COLL SEC:PPD ORIG ID:3530075853 | D154: -1240.27 | E154: ACH_DEBIT | G154: Personal - Car Insurance
A155: DEBIT | B155: 46140 | C155: DNH*GODADDY#4075135447 480-5058855 AZ 04/28 | D155: -22.98 | E155: DEBIT_CARD | F155: 6071.89 | G155: Go Daddy
A156: DEBIT | B156: 46140 | C156: ORIG CO NAME:BANNER LIFE ORIG ID:1521236145 DESC DATE:260427 CO ENTRY DESCR:PREM DEBITSEC:PPD TRACE#:091000011992129 EED:260428 IND ID: IND NAME:ANGELA L DUNNING TRN: 1181992129TC | D156: -12.5 | E156: ACH_DEBIT | F156: 6094.87 | G156: Life Insurance
A157: DEBIT | B157: 46140 | C157: ORIG CO NAME:BANNER LIFE ORIG ID:1521236145 DESC DATE:260427 CO ENTRY DESCR:PREM DEBITSEC:PPD TRACE#:091000011992130 EED:260428 IND ID: IND NAME:JOHN DUNNING TRN: 1181992130TC | D157: -22.92 | E157: ACH_DEBIT | F157: 6107.37 | G157: Life Insurance
A158: DEBIT | B158: 46140 | C158: Online Transfer to CHK ...1117 transaction#: 28993634559 04/28 | D158: -2000 | E158: ACCT_XFER | F158: 6130.29 | G158: Transfer to Angela Dunning
A159: DEBIT | B159: 46140 | C159: PAYPAL *RUTHALCANCI 402-935-7733 CA 04/28 | D159: -252.21 | E159: DEBIT_CARD | F159: 8130.29 | G159: Ruth Alcancia - Forward Bridge Payment
A160: DEBIT | B160: 46139 | C160: Online Transfer to CHK ...0709 transaction#: 28990875134 04/27 | D160: -100 | E160: ACCT_XFER | F160: 8382.5 | G160: Transfer to DWG Capital Group_Savings
A161: DEBIT | B161: 46139 | C161: ORIG CO NAME:INTUIT * ORIG ID:0000756346 DESC DATE:260427 CO ENTRY DESCR:QBooks OnlSEC:CCD TRACE#:021000025208866 EED:260427 IND ID:0207602 IND NAME:DWG CAPITAL GROUP 800-446-8848 TRN: 1175208866TC | D161: -121.21 | E161: ACH_DEBIT | F161: 8482.5 | G161: Software/Accounting
A162: DEBIT | B162: 46139 | C162: DNH*GODADDY#4074140861 480-5058855 AZ 04/27 | D162: -17.98 | E162: DEBIT_CARD | F162: 8603.71 | G162: Go Daddy
A163: DEBIT | B163: 46139 | C163: Basic Online Payroll Payment 11215871738 to ########4122 | D163: -1750 | E163: BASIC_PAYROLL | F163: 8621.69 | G163: Mike Paytonjian - Payroll
A164: DEBIT | B164: 46139 | C164: ORIG CO NAME:VENMO ORIG ID:3264681992 DESC DATE:260425 CO ENTRY DESCR:PAYMENT SEC:WEB TRACE#:021000028608910 EED:260427 IND ID:1049840986680 IND NAME:JUDD DUNNING 260425PPZF9K TRN: 1178608910TC | D164: -100 | E164: ACH_DEBIT | F164: 10371.69 | G164: Venmo
A165: DEBIT | B165: 46139 | C165: Disney Plus 888-9057888 CA 04/26 | D165: -20.51 | E165: DEBIT_CARD | F165: 10471.69 | G165: Personal - Subscriptions
A166: DEBIT | B166: 46139 | C166: DNH*GODADDY#4072993950 480-5058855 AZ 04/25 | D166: -16.98 | E166: DEBIT_CARD | F166: 10492.2 | G166: Go Daddy
... A517: DEBIT | B517: 46024 | C517: ORIG CO NAME:BLUESHIELDCA ORIG ID:7529219311 DESC DATE:251231 CO ENTRY DESCR:BILL PAY SEC:CCD TRACE#:031101115700064 EED:260102 IND ID:15728029331 IND NAME:ANGELA DUNNING TRN: 0025700064TC | D517: -974.85 | E517: ACH_DEBIT | F517: 29231.38 | G517: Personal - Health Insurance
