Workbook

Sheet Category Summary
A1: Chase 9335 — 2026 Activity
A2: Category Summary | Jan 2026 – Jun 2026
A4: Entity | B4: Poseidon Asset Group
A5: Account | B5: Personal Checking — Chase 9335
A6: Period | B6: Jan 2026 – Jun 2026
A8: TOTALS
A9: Total Inflows | B9: =SUMIFS('Transaction Overview'!$D$2:$D$467,'Transaction Overview'!$D$2:$D$467,">0") -> 680055.66
A10: Total Outflows | B10: =SUMIFS('Transaction Overview'!$D$2:$D$467,'Transaction Overview'!$D$2:$D$467,"<0") -> -901960.84
A11: Net Change | B11: =B9+B10 -> -221905.18
A13: FLOW BY CATEGORY
A14: Category | B14: Inflows | C14: Outflows | D14: Net
A15: Deal-Specific
A16: Bridge Coverage (JC Whitner) | B16: =SUMIFS('Transaction Overview'!$D$2:$D$467,'Transaction Overview'!$G$2:$G$467,$A16,'Transaction Overview'!$D$2:$D$467,">0") -> 0 | C16: =SUMIFS('Transaction Overview'!$D$2:$D$467,'Transaction Overview'!$G$2:$G$467,$A16,'Transaction Overview'!$D$2:$D$467,"<0") -> -10000 | D16: =B16+C16 -> -10000
A17: Deal Specific: Austin Iron | B17: =SUMIFS('Transaction Overview'!$D$2:$D$467,'Transaction Overview'!$G$2:$G$467,$A17,'Transaction Overview'!$D$2:$D$467,">0") -> 2100 | C17: =SUMIFS('Transaction Overview'!$D$2:$D$467,'Transaction Overview'!$G$2:$G$467,$A17,'Transaction Overview'!$D$2:$D$467,"<0") -> 0 | D17: =B17+C17 -> 2100
A18: Deal Specific: MRM | B18: =SUMIFS('Transaction Overview'!$D$2:$D$467,'Transaction Overview'!$G$2:$G$467,$A18,'Transaction Overview'!$D$2:$D$467,">0") -> 725.61 | C18: =SUMIFS('Transaction Overview'!$D$2:$D$467,'Transaction Overview'!$G$2:$G$467,$A18,'Transaction Overview'!$D$2:$D$467,"<0") -> 0 | D18: =B18+C18 -> 725.61
A19: Deal Specific: Merit-Lancaster | B19: =SUMIFS('Transaction Overview'!$D$2:$D$467,'Transaction Overview'!$G$2:$G$467,$A19,'Transaction Overview'!$D$2:$D$467,">0") -> 2917.98 | C19: =SUMIFS('Transaction Overview'!$D$2:$D$467,'Transaction Overview'!$G$2:$G$467,$A19,'Transaction Overview'!$D$2:$D$467,"<0") -> 0 | D19: =B19+C19 -> 2917.98
A20: Deal Specific: Rabourn Road | B20: =SUMIFS('Transaction Overview'!$D$2:$D$467,'Transaction Overview'!$G$2:$G$467,$A20,'Transaction Overview'!$D$2:$D$467,">0") -> 1399.98 | C20: =SUMIFS('Transaction Overview'!$D$2:$D$467,'Transaction Overview'!$G$2:$G$467,$A20,'Transaction Overview'!$D$2:$D$467,"<0") -> 0 | D20: =B20+C20 -> 1399.98
A21: Deal Specific: T&T Machine | B21: =SUMIFS('Transaction Overview'!$D$2:$D$467,'Transaction Overview'!$G$2:$G$467,$A21,'Transaction Overview'!$D$2:$D$467,">0") -> 1091.42 | C21: =SUMIFS('Transaction Overview'!$D$2:$D$467,'Transaction Overview'!$G$2:$G$467,$A21,'Transaction Overview'!$D$2:$D$467,"<0") -> 0 | D21: =B21+C21 -> 1091.42
A22: Subtotal — Deal-Specific | B22: =SUMIFS('Transaction Overview'!$D$2:$D$467,'Transaction Overview'!$J$2:$J$467,"Deal-Specific",'Transaction Overview'!$D$2:$D$467,">0") -> 8234.99 | C22: =SUMIFS('Transaction Overview'!$D$2:$D$467,'Transaction Overview'!$J$2:$J$467,"Deal-Specific",'Transaction Overview'!$D$2:$D$467,"<0") -> -10000 | D22: =B22+C22 -> -1765.01
A24: Commissions — Incoming
A25: Incoming Commission: Rembrandt | B25: =SUMIFS('Transaction Overview'!$D$2:$D$467,'Transaction Overview'!$G$2:$G$467,$A25,'Transaction Overview'!$D$2:$D$467,">0") -> 168266 | C25: =SUMIFS('Transaction Overview'!$D$2:$D$467,'Transaction Overview'!$G$2:$G$467,$A25,'Transaction Overview'!$D$2:$D$467,"<0") -> 0 | D25: =B25+C25 -> 168266
A26: Incoming Commission: SPF | B26: =SUMIFS('Transaction Overview'!$D$2:$D$467,'Transaction Overview'!$G$2:$G$467,$A26,'Transaction Overview'!$D$2:$D$467,">0") -> 266889.44 | C26: =SUMIFS('Transaction Overview'!$D$2:$D$467,'Transaction Overview'!$G$2:$G$467,$A26,'Transaction Overview'!$D$2:$D$467,"<0") -> 0 | D26: =B26+C26 -> 266889.44
A27: Subtotal — Commissions — Incoming | B27: =SUMIFS('Transaction Overview'!$D$2:$D$467,'Transaction Overview'!$J$2:$J$467,"Commissions — Incoming",'Transaction Overview'!$D$2:$D$467,">0") -> 435155.44 | C27: =SUMIFS('Transaction Overview'!$D$2:$D$467,'Transaction Overview'!$J$2:$J$467,"Commissions — Incoming",'Transaction Overview'!$D$2:$D$467,"<0") -> 0 | D27: =B27+C27 -> 435155.44
A29: Commissions — Outgoing
A30: Kevin Wong Commission (SPF) | B30: =SUMIFS('Transaction Overview'!$D$2:$D$467,'Transaction Overview'!$G$2:$G$467,$A30,'Transaction Overview'!$D$2:$D$467,">0") -> 0 | C30: =SUMIFS('Transaction Overview'!$D$2:$D$467,'Transaction Overview'!$G$2:$G$467,$A30,'Transaction Overview'!$D$2:$D$467,"<0") -> -16087.5 | D30: =B30+C30 -> -16087.5
A31: Kevin Wong Commission (Steve Klar) | B31: =SUMIFS('Transaction Overview'!$D$2:$D$467,'Transaction Overview'!$G$2:$G$467,$A31,'Transaction Overview'!$D$2:$D$467,">0") -> 0 | C31: =SUMIFS('Transaction Overview'!$D$2:$D$467,'Transaction Overview'!$G$2:$G$467,$A31,'Transaction Overview'!$D$2:$D$467,"<0") -> -6000 | D31: =B31+C31 -> -6000
A32: Meg Maran - MDC Commission | B32: =SUMIFS('Transaction Overview'!$D$2:$D$467,'Transaction Overview'!$G$2:$G$467,$A32,'Transaction Overview'!$D$2:$D$467,">0") -> 0 | C32: =SUMIFS('Transaction Overview'!$D$2:$D$467,'Transaction Overview'!$G$2:$G$467,$A32,'Transaction Overview'!$D$2:$D$467,"<0") -> -1500 | D32: =B32+C32 -> -1500
A33: Subtotal — Commissions — Outgoing | B33: =SUMIFS('Transaction Overview'!$D$2:$D$467,'Transaction Overview'!$J$2:$J$467,"Commissions — Outgoing",'Transaction Overview'!$D$2:$D$467,">0") -> 0 | C33: =SUMIFS('Transaction Overview'!$D$2:$D$467,'Transaction Overview'!$J$2:$J$467,"Commissions — Outgoing",'Transaction Overview'!$D$2:$D$467,"<0") -> -23587.5 | D33: =B33+C33 -> -23587.5
A35: MAG Pass-Through
A36: MAG - Admeer Advisory Reimbursement | B36: =SUMIFS('Transaction Overview'!$D$2:$D$467,'Transaction Overview'!$G$2:$G$467,$A36,'Transaction Overview'!$D$2:$D$467,">0") -> 5000 | C36: =SUMIFS('Transaction Overview'!$D$2:$D$467,'Transaction Overview'!$G$2:$G$467,$A36,'Transaction Overview'!$D$2:$D$467,"<0") -> 0 | D36: =B36+C36 -> 5000
A37: MAG - Admeer Advisory Transfer | B37: =SUMIFS('Transaction Overview'!$D$2:$D$467,'Transaction Overview'!$G$2:$G$467,$A37,'Transaction Overview'!$D$2:$D$467,">0") -> 0 | C37: =SUMIFS('Transaction Overview'!$D$2:$D$467,'Transaction Overview'!$G$2:$G$467,$A37,'Transaction Overview'!$D$2:$D$467,"<0") -> -10000 | D37: =B37+C37 -> -10000
A38: MAG Marketing Reimbursement | B38: =SUMIFS('Transaction Overview'!$D$2:$D$467,'Transaction Overview'!$G$2:$G$467,$A38,'Transaction Overview'!$D$2:$D$467,">0") -> 15000 | C38: =SUMIFS('Transaction Overview'!$D$2:$D$467,'Transaction Overview'!$G$2:$G$467,$A38,'Transaction Overview'!$D$2:$D$467,"<0") -> 0 | D38: =B38+C38 -> 15000
A39: Subtotal — MAG Pass-Through | B39: =SUMIFS('Transaction Overview'!$D$2:$D$467,'Transaction Overview'!$J$2:$J$467,"MAG Pass-Through",'Transaction Overview'!$D$2:$D$467,">0") -> 20000 | C39: =SUMIFS('Transaction Overview'!$D$2:$D$467,'Transaction Overview'!$J$2:$J$467,"MAG Pass-Through",'Transaction Overview'!$D$2:$D$467,"<0") -> -10000 | D39: =B39+C39 -> 10000
A41: Wire Transfers — Incoming
A42: Incoming wire from JC Whitner | B42: =SUMIFS('Transaction Overview'!$D$2:$D$467,'Transaction Overview'!$G$2:$G$467,$A42,'Transaction Overview'!$D$2:$D$467,">0") -> 20000 | C42: =SUMIFS('Transaction Overview'!$D$2:$D$467,'Transaction Overview'!$G$2:$G$467,$A42,'Transaction Overview'!$D$2:$D$467,"<0") -> 0 | D42: =B42+C42 -> 20000
A43: Incoming wire from Moab (Leftover Funds) | B43: =SUMIFS('Transaction Overview'!$D$2:$D$467,'Transaction Overview'!$G$2:$G$467,$A43,'Transaction Overview'!$D$2:$D$467,">0") -> 58370.85 | C43: =SUMIFS('Transaction Overview'!$D$2:$D$467,'Transaction Overview'!$G$2:$G$467,$A43,'Transaction Overview'!$D$2:$D$467,"<0") -> 0 | D43: =B43+C43 -> 58370.85
A44: Incoming wire from Steve Klar | B44: =SUMIFS('Transaction Overview'!$D$2:$D$467,'Transaction Overview'!$G$2:$G$467,$A44,'Transaction Overview'!$D$2:$D$467,">0") -> 16000 | C44: =SUMIFS('Transaction Overview'!$D$2:$D$467,'Transaction Overview'!$G$2:$G$467,$A44,'Transaction Overview'!$D$2:$D$467,"<0") -> 0 | D44: =B44+C44 -> 16000
A45: Subtotal — Wire Transfers — Incoming | B45: =SUMIFS('Transaction Overview'!$D$2:$D$467,'Transaction Overview'!$J$2:$J$467,"Wire Transfers — Incoming",'Transaction Overview'!$D$2:$D$467,">0") -> 94370.85 | C45: =SUMIFS('Transaction Overview'!$D$2:$D$467,'Transaction Overview'!$J$2:$J$467,"Wire Transfers — Incoming",'Transaction Overview'!$D$2:$D$467,"<0") -> 0 | D45: =B45+C45 -> 94370.85
A47: Wire Transfers — Outgoing
A48: Wire to Gi Capital Group (+ Moab Funds) | B48: =SUMIFS('Transaction Overview'!$D$2:$D$467,'Transaction Overview'!$G$2:$G$467,$A48,'Transaction Overview'!$D$2:$D$467,">0") -> 0 | C48: =SUMIFS('Transaction Overview'!$D$2:$D$467,'Transaction Overview'!$G$2:$G$467,$A48,'Transaction Overview'!$D$2:$D$467,"<0") -> -56670.85 | D48: =B48+C48 -> -56670.85
A49: Wire to Jon Brandon | B49: =SUMIFS('Transaction Overview'!$D$2:$D$467,'Transaction Overview'!$G$2:$G$467,$A49,'Transaction Overview'!$D$2:$D$467,">0") -> 0 | C49: =SUMIFS('Transaction Overview'!$D$2:$D$467,'Transaction Overview'!$G$2:$G$467,$A49,'Transaction Overview'!$D$2:$D$467,"<0") -> -10000 | D49: =B49+C49 -> -10000
A50: Wire to Ryan Bodmer | B50: =SUMIFS('Transaction Overview'!$D$2:$D$467,'Transaction Overview'!$G$2:$G$467,$A50,'Transaction Overview'!$D$2:$D$467,">0") -> 0 | C50: =SUMIFS('Transaction Overview'!$D$2:$D$467,'Transaction Overview'!$G$2:$G$467,$A50,'Transaction Overview'!$D$2:$D$467,"<0") -> -10000 | D50: =B50+C50 -> -10000
A51: Subtotal — Wire Transfers — Outgoing | B51: =SUMIFS('Transaction Overview'!$D$2:$D$467,'Transaction Overview'!$J$2:$J$467,"Wire Transfers — Outgoing",'Transaction Overview'!$D$2:$D$467,">0") -> 0 | C51: =SUMIFS('Transaction Overview'!$D$2:$D$467,'Transaction Overview'!$J$2:$J$467,"Wire Transfers — Outgoing",'Transaction Overview'!$D$2:$D$467,"<0") -> -76670.85 | D51: =B51+C51 -> -76670.85
A53: Intercompany & Savings Transfers
A54: Transfer From DWG Capital Group | B54: =SUMIFS('Transaction Overview'!$D$2:$D$467,'Transaction Overview'!$G$2:$G$467,$A54,'Transaction Overview'!$D$2:$D$467,">0") -> 8556.41 | C54: =SUMIFS('Transaction Overview'!$D$2:$D$467,'Transaction Overview'!$G$2:$G$467,$A54,'Transaction Overview'!$D$2:$D$467,"<0") -> 0 | D54: =B54+C54 -> 8556.41
A55: Transfer From Poseidon | B55: =SUMIFS('Transaction Overview'!$D$2:$D$467,'Transaction Overview'!$G$2:$G$467,$A55,'Transaction Overview'!$D$2:$D$467,">0") -> 2000 | C55: =SUMIFS('Transaction Overview'!$D$2:$D$467,'Transaction Overview'!$G$2:$G$467,$A55,'Transaction Overview'!$D$2:$D$467,"<0") -> 0 | D55: =B55+C55 -> 2000
A56: Transfer From SPF | B56: =SUMIFS('Transaction Overview'!$D$2:$D$467,'Transaction Overview'!$G$2:$G$467,$A56,'Transaction Overview'!$D$2:$D$467,">0") -> 11450 | C56: =SUMIFS('Transaction Overview'!$D$2:$D$467,'Transaction Overview'!$G$2:$G$467,$A56,'Transaction Overview'!$D$2:$D$467,"<0") -> 0 | D56: =B56+C56 -> 11450
A57: Transfer From Stryten | B57: =SUMIFS('Transaction Overview'!$D$2:$D$467,'Transaction Overview'!$G$2:$G$467,$A57,'Transaction Overview'!$D$2:$D$467,">0") -> 100000 | C57: =SUMIFS('Transaction Overview'!$D$2:$D$467,'Transaction Overview'!$G$2:$G$467,$A57,'Transaction Overview'!$D$2:$D$467,"<0") -> 0 | D57: =B57+C57 -> 100000
A58: Transfer to Buckeye | B58: =SUMIFS('Transaction Overview'!$D$2:$D$467,'Transaction Overview'!$G$2:$G$467,$A58,'Transaction Overview'!$D$2:$D$467,">0") -> 0 | C58: =SUMIFS('Transaction Overview'!$D$2:$D$467,'Transaction Overview'!$G$2:$G$467,$A58,'Transaction Overview'!$D$2:$D$467,"<0") -> -20000 | D58: =B58+C58 -> -20000
A59: Transfer to DWG Capital Group | B59: =SUMIFS('Transaction Overview'!$D$2:$D$467,'Transaction Overview'!$G$2:$G$467,$A59,'Transaction Overview'!$D$2:$D$467,">0") -> 0 | C59: =SUMIFS('Transaction Overview'!$D$2:$D$467,'Transaction Overview'!$G$2:$G$467,$A59,'Transaction Overview'!$D$2:$D$467,"<0") -> -298556.41 | D59: =B59+C59 -> -298556.41
A60: Transfer to DWG Capital Group_Costar | B60: =SUMIFS('Transaction Overview'!$D$2:$D$467,'Transaction Overview'!$G$2:$G$467,$A60,'Transaction Overview'!$D$2:$D$467,">0") -> 0 | C60: =SUMIFS('Transaction Overview'!$D$2:$D$467,'Transaction Overview'!$G$2:$G$467,$A60,'Transaction Overview'!$D$2:$D$467,"<0") -> -15000 | D60: =B60+C60 -> -15000
A61: Transfer to DWG Capital Partners | B61: =SUMIFS('Transaction Overview'!$D$2:$D$467,'Transaction Overview'!$G$2:$G$467,$A61,'Transaction Overview'!$D$2:$D$467,">0") -> 0 | C61: =SUMIFS('Transaction Overview'!$D$2:$D$467,'Transaction Overview'!$G$2:$G$467,$A61,'Transaction Overview'!$D$2:$D$467,"<0") -> -77000 | D61: =B61+C61 -> -77000
A62: Transfer to Edgebuilders | B62: =SUMIFS('Transaction Overview'!$D$2:$D$467,'Transaction Overview'!$G$2:$G$467,$A62,'Transaction Overview'!$D$2:$D$467,">0") -> 0 | C62: =SUMIFS('Transaction Overview'!$D$2:$D$467,'Transaction Overview'!$G$2:$G$467,$A62,'Transaction Overview'!$D$2:$D$467,"<0") -> -35200 | D62: =B62+C62 -> -35200
A63: Transfer to JAL Southbend | B63: =SUMIFS('Transaction Overview'!$D$2:$D$467,'Transaction Overview'!$G$2:$G$467,$A63,'Transaction Overview'!$D$2:$D$467,">0") -> 0 | C63: =SUMIFS('Transaction Overview'!$D$2:$D$467,'Transaction Overview'!$G$2:$G$467,$A63,'Transaction Overview'!$D$2:$D$467,"<0") -> -13000 | D63: =B63+C63 -> -13000
A64: Transfer to Judd Sol Prop | B64: =SUMIFS('Transaction Overview'!$D$2:$D$467,'Transaction Overview'!$G$2:$G$467,$A64,'Transaction Overview'!$D$2:$D$467,">0") -> 0 | C64: =SUMIFS('Transaction Overview'!$D$2:$D$467,'Transaction Overview'!$G$2:$G$467,$A64,'Transaction Overview'!$D$2:$D$467,"<0") -> -200 | D64: =B64+C64 -> -200
A65: Subtotal — Intercompany & Savings Transfers | B65: =SUMIFS('Transaction Overview'!$D$2:$D$467,'Transaction Overview'!$J$2:$J$467,"Intercompany & Savings Transfers",'Transaction Overview'!$D$2:$D$467,">0") -> 122006.41 | C65: =SUMIFS('Transaction Overview'!$D$2:$D$467,'Transaction Overview'!$J$2:$J$467,"Intercompany & Savings Transfers",'Transaction Overview'!$D$2:$D$467,"<0") -> -458956.41 | D65: =B65+C65 -> -336950
A67: Owner / Family Distributions
A68: Transfer to Angela Dunning | B68: =SUMIFS('Transaction Overview'!$D$2:$D$467,'Transaction Overview'!$G$2:$G$467,$A68,'Transaction Overview'!$D$2:$D$467,">0") -> 0 | C68: =SUMIFS('Transaction Overview'!$D$2:$D$467,'Transaction Overview'!$G$2:$G$467,$A68,'Transaction Overview'!$D$2:$D$467,"<0") -> -31000 | D68: =B68+C68 -> -31000
A69: Transfer to TX Personal Joint | B69: =SUMIFS('Transaction Overview'!$D$2:$D$467,'Transaction Overview'!$G$2:$G$467,$A69,'Transaction Overview'!$D$2:$D$467,">0") -> 0 | C69: =SUMIFS('Transaction Overview'!$D$2:$D$467,'Transaction Overview'!$G$2:$G$467,$A69,'Transaction Overview'!$D$2:$D$467,"<0") -> -40000 | D69: =B69+C69 -> -40000
A70: Subtotal — Owner / Family Distributions | B70: =SUMIFS('Transaction Overview'!$D$2:$D$467,'Transaction Overview'!$J$2:$J$467,"Owner / Family Distributions",'Transaction Overview'!$D$2:$D$467,">0") -> 0 | C70: =SUMIFS('Transaction Overview'!$D$2:$D$467,'Transaction Overview'!$J$2:$J$467,"Owner / Family Distributions",'Transaction Overview'!$D$2:$D$467,"<0") -> -71000 | D70: =B70+C70 -> -71000
A72: P2P Payments (Zelle/Venmo/PayPal)
A73: Apple Payment | B73: =SUMIFS('Transaction Overview'!$D$2:$D$467,'Transaction Overview'!$G$2:$G$467,$A73,'Transaction Overview'!$D$2:$D$467,">0") -> 0 | C73: =SUMIFS('Transaction Overview'!$D$2:$D$467,'Transaction Overview'!$G$2:$G$467,$A73,'Transaction Overview'!$D$2:$D$467,"<0") -> -100 | D73: =B73+C73 -> -100
A74: Zelle - Chase Hall | B74: =SUMIFS('Transaction Overview'!$D$2:$D$467,'Transaction Overview'!$G$2:$G$467,$A74,'Transaction Overview'!$D$2:$D$467,">0") -> 0 | C74: =SUMIFS('Transaction Overview'!$D$2:$D$467,'Transaction Overview'!$G$2:$G$467,$A74,'Transaction Overview'!$D$2:$D$467,"<0") -> -325 | D74: =B74+C74 -> -325
A75: Zelle - Francisco Bautista | B75: =SUMIFS('Transaction Overview'!$D$2:$D$467,'Transaction Overview'!$G$2:$G$467,$A75,'Transaction Overview'!$D$2:$D$467,">0") -> 0 | C75: =SUMIFS('Transaction Overview'!$D$2:$D$467,'Transaction Overview'!$G$2:$G$467,$A75,'Transaction Overview'!$D$2:$D$467,"<0") -> -2500 | D75: =B75+C75 -> -2500
A76: Zelle - Scott Brech | B76: =SUMIFS('Transaction Overview'!$D$2:$D$467,'Transaction Overview'!$G$2:$G$467,$A76,'Transaction Overview'!$D$2:$D$467,">0") -> 0 | C76: =SUMIFS('Transaction Overview'!$D$2:$D$467,'Transaction Overview'!$G$2:$G$467,$A76,'Transaction Overview'!$D$2:$D$467,"<0") -> -700 | D76: =B76+C76 -> -700
A77: Apple Cash | B77: =SUMIFS('Transaction Overview'!$D$2:$D$467,'Transaction Overview'!$G$2:$G$467,$A77,'Transaction Overview'!$D$2:$D$467,">0") -> 0 | C77: =SUMIFS('Transaction Overview'!$D$2:$D$467,'Transaction Overview'!$G$2:$G$467,$A77,'Transaction Overview'!$D$2:$D$467,"<0") -> -370 | D77: =B77+C77 -> -370
A78: Subtotal — P2P Payments (Zelle/Venmo/PayPal) | B78: =SUMIFS('Transaction Overview'!$D$2:$D$467,'Transaction Overview'!$J$2:$J$467,"P2P Payments (Zelle/Venmo/PayPal)",'Transaction Overview'!$D$2:$D$467,">0") -> 0 | C78: =SUMIFS('Transaction Overview'!$D$2:$D$467,'Transaction Overview'!$J$2:$J$467,"P2P Payments (Zelle/Venmo/PayPal)",'Transaction Overview'!$D$2:$D$467,"<0") -> -3995 | D78: =B78+C78 -> -3995
A80: Payroll & Contractors
A81: DWG HR | B81: =SUMIFS('Transaction Overview'!$D$2:$D$467,'Transaction Overview'!$G$2:$G$467,$A81,'Transaction Overview'!$D$2:$D$467,">0") -> 0 | C81: =SUMIFS('Transaction Overview'!$D$2:$D$467,'Transaction Overview'!$G$2:$G$467,$A81,'Transaction Overview'!$D$2:$D$467,"<0") -> -1371.45 | D81: =B81+C81 -> -1371.45
A82: Office/Miscellaneous Reimbursement - Mike P. | B82: =SUMIFS('Transaction Overview'!$D$2:$D$467,'Transaction Overview'!$G$2:$G$467,$A82,'Transaction Overview'!$D$2:$D$467,">0") -> 0 | C82: =SUMIFS('Transaction Overview'!$D$2:$D$467,'Transaction Overview'!$G$2:$G$467,$A82,'Transaction Overview'!$D$2:$D$467,"<0") -> -6637 | D82: =B82+C82 -> -6637
A83: Subtotal — Payroll & Contractors | B83: =SUMIFS('Transaction Overview'!$D$2:$D$467,'Transaction Overview'!$J$2:$J$467,"Payroll & Contractors",'Transaction Overview'!$D$2:$D$467,">0") -> 0 | C83: =SUMIFS('Transaction Overview'!$D$2:$D$467,'Transaction Overview'!$J$2:$J$467,"Payroll & Contractors",'Transaction Overview'!$D$2:$D$467,"<0") -> -8008.45 | D83: =B83+C83 -> -8008.45
A85: Credit Card & Loan Payments
A86: American Express Credit Card PMT | B86: =SUMIFS('Transaction Overview'!$D$2:$D$467,'Transaction Overview'!$G$2:$G$467,$A86,'Transaction Overview'!$D$2:$D$467,">0") -> 0 | C86: =SUMIFS('Transaction Overview'!$D$2:$D$467,'Transaction Overview'!$G$2:$G$467,$A86,'Transaction Overview'!$D$2:$D$467,"<0") -> -197763.92 | D86: =B86+C86 -> -197763.92
A87: Subtotal — Credit Card & Loan Payments | B87: =SUMIFS('Transaction Overview'!$D$2:$D$467,'Transaction Overview'!$J$2:$J$467,"Credit Card & Loan Payments",'Transaction Overview'!$D$2:$D$467,">0") -> 0 | C87: =SUMIFS('Transaction Overview'!$D$2:$D$467,'Transaction Overview'!$J$2:$J$467,"Credit Card & Loan Payments",'Transaction Overview'!$D$2:$D$467,"<0") -> -197763.92 | D87: =B87+C87 -> -197763.92
A89: Personal — Owner
A90: ATM/Cash | B90: =SUMIFS('Transaction Overview'!$D$2:$D$467,'Transaction Overview'!$G$2:$G$467,$A90,'Transaction Overview'!$D$2:$D$467,">0") -> 0 | C90: =SUMIFS('Transaction Overview'!$D$2:$D$467,'Transaction Overview'!$G$2:$G$467,$A90,'Transaction Overview'!$D$2:$D$467,"<0") -> -13723.98 | D90: =B90+C90 -> -13723.98
A91: Amazon | B91: =SUMIFS('Transaction Overview'!$D$2:$D$467,'Transaction Overview'!$G$2:$G$467,$A91,'Transaction Overview'!$D$2:$D$467,">0") -> 274.93 | C91: =SUMIFS('Transaction Overview'!$D$2:$D$467,'Transaction Overview'!$G$2:$G$467,$A91,'Transaction Overview'!$D$2:$D$467,"<0") -> -4256.86 | D91: =B91+C91 -> -3981.93
A92: Personal - Car | B92: =SUMIFS('Transaction Overview'!$D$2:$D$467,'Transaction Overview'!$G$2:$G$467,$A92,'Transaction Overview'!$D$2:$D$467,">0") -> 0 | C92: =SUMIFS('Transaction Overview'!$D$2:$D$467,'Transaction Overview'!$G$2:$G$467,$A92,'Transaction Overview'!$D$2:$D$467,"<0") -> -1630.9 | D92: =B92+C92 -> -1630.9
A93: Personal - Entertainment | B93: =SUMIFS('Transaction Overview'!$D$2:$D$467,'Transaction Overview'!$G$2:$G$467,$A93,'Transaction Overview'!$D$2:$D$467,">0") -> 0 | C93: =SUMIFS('Transaction Overview'!$D$2:$D$467,'Transaction Overview'!$G$2:$G$467,$A93,'Transaction Overview'!$D$2:$D$467,"<0") -> -32.31 | D93: =B93+C93 -> -32.31
A94: Personal - Food & Dining | B94: =SUMIFS('Transaction Overview'!$D$2:$D$467,'Transaction Overview'!$G$2:$G$467,$A94,'Transaction Overview'!$D$2:$D$467,">0") -> 0 | C94: =SUMIFS('Transaction Overview'!$D$2:$D$467,'Transaction Overview'!$G$2:$G$467,$A94,'Transaction Overview'!$D$2:$D$467,"<0") -> -1357.76 | D94: =B94+C94 -> -1357.76
A95: Personal - Health (incl. Ins.) | B95: =SUMIFS('Transaction Overview'!$D$2:$D$467,'Transaction Overview'!$G$2:$G$467,$A95,'Transaction Overview'!$D$2:$D$467,">0") -> 0 | C95: =SUMIFS('Transaction Overview'!$D$2:$D$467,'Transaction Overview'!$G$2:$G$467,$A95,'Transaction Overview'!$D$2:$D$467,"<0") -> -1050 | D95: =B95+C95 -> -1050
A96: Personal - House | B96: =SUMIFS('Transaction Overview'!$D$2:$D$467,'Transaction Overview'!$G$2:$G$467,$A96,'Transaction Overview'!$D$2:$D$467,">0") -> 0 | C96: =SUMIFS('Transaction Overview'!$D$2:$D$467,'Transaction Overview'!$G$2:$G$467,$A96,'Transaction Overview'!$D$2:$D$467,"<0") -> -16287.51 | D96: =B96+C96 -> -16287.51
A97: Personal - Subscriptions | B97: =SUMIFS('Transaction Overview'!$D$2:$D$467,'Transaction Overview'!$G$2:$G$467,$A97,'Transaction Overview'!$D$2:$D$467,">0") -> 13.04 | C97: =SUMIFS('Transaction Overview'!$D$2:$D$467,'Transaction Overview'!$G$2:$G$467,$A97,'Transaction Overview'!$D$2:$D$467,"<0") -> -2189.48 | D97: =B97+C97 -> -2176.44
A98: Personal - Travel | B98: =SUMIFS('Transaction Overview'!$D$2:$D$467,'Transaction Overview'!$G$2:$G$467,$A98,'Transaction Overview'!$D$2:$D$467,">0") -> 0 | C98: =SUMIFS('Transaction Overview'!$D$2:$D$467,'Transaction Overview'!$G$2:$G$467,$A98,'Transaction Overview'!$D$2:$D$467,"<0") -> -179.7 | D98: =B98+C98 -> -179.7
A99: Personal - Travel (Portugal) | B99: =SUMIFS('Transaction Overview'!$D$2:$D$467,'Transaction Overview'!$G$2:$G$467,$A99,'Transaction Overview'!$D$2:$D$467,">0") -> 0 | C99: =SUMIFS('Transaction Overview'!$D$2:$D$467,'Transaction Overview'!$G$2:$G$467,$A99,'Transaction Overview'!$D$2:$D$467,"<0") -> -428.27 | D99: =B99+C99 -> -428.27
A100: Subtotal — Personal — Owner | B100: =SUMIFS('Transaction Overview'!$D$2:$D$467,'Transaction Overview'!$J$2:$J$467,"Personal — Owner",'Transaction Overview'!$D$2:$D$467,">0") -> 287.97 | C100: =SUMIFS('Transaction Overview'!$D$2:$D$467,'Transaction Overview'!$J$2:$J$467,"Personal — Owner",'Transaction Overview'!$D$2:$D$467,"<0") -> -41136.77 | D100: =B100+C100 -> -40848.8
A102: DWG Operating
A103: ACH payment to CALCPA group | B103: =SUMIFS('Transaction Overview'!$D$2:$D$467,'Transaction Overview'!$G$2:$G$467,$A103,'Transaction Overview'!$D$2:$D$467,">0") -> 0 | C103: =SUMIFS('Transaction Overview'!$D$2:$D$467,'Transaction Overview'!$G$2:$G$467,$A103,'Transaction Overview'!$D$2:$D$467,"<0") -> -501.25 | D103: =B103+C103 -> -501.25
A104: Bank Fees | B104: =SUMIFS('Transaction Overview'!$D$2:$D$467,'Transaction Overview'!$G$2:$G$467,$A104,'Transaction Overview'!$D$2:$D$467,">0") -> 0 | C104: =SUMIFS('Transaction Overview'!$D$2:$D$467,'Transaction Overview'!$G$2:$G$467,$A104,'Transaction Overview'!$D$2:$D$467,"<0") -> -6 | D104: =B104+C104 -> -6
A105: Facebook | B105: =SUMIFS('Transaction Overview'!$D$2:$D$467,'Transaction Overview'!$G$2:$G$467,$A105,'Transaction Overview'!$D$2:$D$467,">0") -> 0 | C105: =SUMIFS('Transaction Overview'!$D$2:$D$467,'Transaction Overview'!$G$2:$G$467,$A105,'Transaction Overview'!$D$2:$D$467,"<0") -> -14.69 | D105: =B105+C105 -> -14.69
A106: LLC Filing | B106: =SUMIFS('Transaction Overview'!$D$2:$D$467,'Transaction Overview'!$G$2:$G$467,$A106,'Transaction Overview'!$D$2:$D$467,">0") -> 0 | C106: =SUMIFS('Transaction Overview'!$D$2:$D$467,'Transaction Overview'!$G$2:$G$467,$A106,'Transaction Overview'!$D$2:$D$467,"<0") -> -70 | D106: =B106+C106 -> -70
A107: Wire Fee | B107: =SUMIFS('Transaction Overview'!$D$2:$D$467,'Transaction Overview'!$G$2:$G$467,$A107,'Transaction Overview'!$D$2:$D$467,">0") -> 0 | C107: =SUMIFS('Transaction Overview'!$D$2:$D$467,'Transaction Overview'!$G$2:$G$467,$A107,'Transaction Overview'!$D$2:$D$467,"<0") -> -250 | D107: =B107+C107 -> -250
A108: Subtotal — DWG Operating | B108: =SUMIFS('Transaction Overview'!$D$2:$D$467,'Transaction Overview'!$J$2:$J$467,"DWG Operating",'Transaction Overview'!$D$2:$D$467,">0") -> 0 | C108: =SUMIFS('Transaction Overview'!$D$2:$D$467,'Transaction Overview'!$J$2:$J$467,"DWG Operating",'Transaction Overview'!$D$2:$D$467,"<0") -> -841.94 | D108: =B108+C108 -> -841.94
A110: Uncategorized — Review
A111: TBD | B111: =SUMIFS('Transaction Overview'!$D$2:$D$467,'Transaction Overview'!$G$2:$G$467,$A111,'Transaction Overview'!$D$2:$D$467,">0") -> 0 | C111: =SUMIFS('Transaction Overview'!$D$2:$D$467,'Transaction Overview'!$G$2:$G$467,$A111,'Transaction Overview'!$D$2:$D$467,"<0") -> 0 | D111: =B111+C111 -> 0
A112: Subtotal — Uncategorized — Review | B112: =SUMIFS('Transaction Overview'!$D$2:$D$467,'Transaction Overview'!$J$2:$J$467,"Uncategorized — Review",'Transaction Overview'!$D$2:$D$467,">0") -> 0 | C112: =SUMIFS('Transaction Overview'!$D$2:$D$467,'Transaction Overview'!$J$2:$J$467,"Uncategorized — Review",'Transaction Overview'!$D$2:$D$467,"<0") -> 0 | D112: =B112+C112 -> 0

Sheet Monthly Breakdown
A1: Chase 9335 — 2026 Activity
A2: Monthly Breakdown | Net by Category | Jan 2026 – Jun 2026
A4: Category | B4: =DATE(2026,1,1) -> 46023 | C4: =DATE(2026,2,1) -> 46054 | D4: =DATE(2026,3,1) -> 46082 | E4: =DATE(2026,4,1) -> 46113 | F4: =DATE(2026,5,1) -> 46143 | G4: =DATE(2026,6,1) -> 46174 | H4: Total
A5: Deal-Specific
A6: Bridge Coverage (JC Whitner) | B6: =SUMIFS('Transaction Overview'!$D$2:$D$467,'Transaction Overview'!$I$2:$I$467,$A6,'Transaction Overview'!$H$2:$H$467,B$4) -> -10000 | C6: =SUMIFS('Transaction Overview'!$D$2:$D$467,'Transaction Overview'!$I$2:$I$467,$A6,'Transaction Overview'!$H$2:$H$467,C$4) -> 0 | D6: =SUMIFS('Transaction Overview'!$D$2:$D$467,'Transaction Overview'!$I$2:$I$467,$A6,'Transaction Overview'!$H$2:$H$467,D$4) -> 0 | E6: =SUMIFS('Transaction Overview'!$D$2:$D$467,'Transaction Overview'!$I$2:$I$467,$A6,'Transaction Overview'!$H$2:$H$467,E$4) -> 0 | F6: =SUMIFS('Transaction Overview'!$D$2:$D$467,'Transaction Overview'!$I$2:$I$467,$A6,'Transaction Overview'!$H$2:$H$467,F$4) -> 0 | G6: =SUMIFS('Transaction Overview'!$D$2:$D$467,'Transaction Overview'!$I$2:$I$467,$A6,'Transaction Overview'!$H$2:$H$467,G$4) -> 0 | H6: =SUM(B6:G6) -> -10000
A7: Deal Specific: Austin Iron | B7: =SUMIFS('Transaction Overview'!$D$2:$D$467,'Transaction Overview'!$I$2:$I$467,$A7,'Transaction Overview'!$H$2:$H$467,B$4) -> 350 | C7: =SUMIFS('Transaction Overview'!$D$2:$D$467,'Transaction Overview'!$I$2:$I$467,$A7,'Transaction Overview'!$H$2:$H$467,C$4) -> 350 | D7: =SUMIFS('Transaction Overview'!$D$2:$D$467,'Transaction Overview'!$I$2:$I$467,$A7,'Transaction Overview'!$H$2:$H$467,D$4) -> 350 | E7: =SUMIFS('Transaction Overview'!$D$2:$D$467,'Transaction Overview'!$I$2:$I$467,$A7,'Transaction Overview'!$H$2:$H$467,E$4) -> 350 | F7: =SUMIFS('Transaction Overview'!$D$2:$D$467,'Transaction Overview'!$I$2:$I$467,$A7,'Transaction Overview'!$H$2:$H$467,F$4) -> 350 | G7: =SUMIFS('Transaction Overview'!$D$2:$D$467,'Transaction Overview'!$I$2:$I$467,$A7,'Transaction Overview'!$H$2:$H$467,G$4) -> 350 | H7: =SUM(B7:G7) -> 2100
A8: Deal Specific: MRM | B8: =SUMIFS('Transaction Overview'!$D$2:$D$467,'Transaction Overview'!$I$2:$I$467,$A8,'Transaction Overview'!$H$2:$H$467,B$4) -> 241.87 | C8: =SUMIFS('Transaction Overview'!$D$2:$D$467,'Transaction Overview'!$I$2:$I$467,$A8,'Transaction Overview'!$H$2:$H$467,C$4) -> 241.87 | D8: =SUMIFS('Transaction Overview'!$D$2:$D$467,'Transaction Overview'!$I$2:$I$467,$A8,'Transaction Overview'!$H$2:$H$467,D$4) -> 241.87 | E8: =SUMIFS('Transaction Overview'!$D$2:$D$467,'Transaction Overview'!$I$2:$I$467,$A8,'Transaction Overview'!$H$2:$H$467,E$4) -> 0 | F8: =SUMIFS('Transaction Overview'!$D$2:$D$467,'Transaction Overview'!$I$2:$I$467,$A8,'Transaction Overview'!$H$2:$H$467,F$4) -> 0 | G8: =SUMIFS('Transaction Overview'!$D$2:$D$467,'Transaction Overview'!$I$2:$I$467,$A8,'Transaction Overview'!$H$2:$H$467,G$4) -> 0 | H8: =SUM(B8:G8) -> 725.61
A9: Deal Specific: Merit-Lancaster | B9: =SUMIFS('Transaction Overview'!$D$2:$D$467,'Transaction Overview'!$I$2:$I$467,$A9,'Transaction Overview'!$H$2:$H$467,B$4) -> 476.41 | C9: =SUMIFS('Transaction Overview'!$D$2:$D$467,'Transaction Overview'!$I$2:$I$467,$A9,'Transaction Overview'!$H$2:$H$467,C$4) -> 476.41 | D9: =SUMIFS('Transaction Overview'!$D$2:$D$467,'Transaction Overview'!$I$2:$I$467,$A9,'Transaction Overview'!$H$2:$H$467,D$4) -> 491.29 | E9: =SUMIFS('Transaction Overview'!$D$2:$D$467,'Transaction Overview'!$I$2:$I$467,$A9,'Transaction Overview'!$H$2:$H$467,E$4) -> 491.29 | F9: =SUMIFS('Transaction Overview'!$D$2:$D$467,'Transaction Overview'!$I$2:$I$467,$A9,'Transaction Overview'!$H$2:$H$467,F$4) -> 491.29 | G9: =SUMIFS('Transaction Overview'!$D$2:$D$467,'Transaction Overview'!$I$2:$I$467,$A9,'Transaction Overview'!$H$2:$H$467,G$4) -> 491.29 | H9: =SUM(B9:G9) -> 2917.98
A10: Deal Specific: Rabourn Road | B10: =SUMIFS('Transaction Overview'!$D$2:$D$467,'Transaction Overview'!$I$2:$I$467,$A10,'Transaction Overview'!$H$2:$H$467,B$4) -> 233.33 | C10: =SUMIFS('Transaction Overview'!$D$2:$D$467,'Transaction Overview'!$I$2:$I$467,$A10,'Transaction Overview'!$H$2:$H$467,C$4) -> 233.33 | D10: =SUMIFS('Transaction Overview'!$D$2:$D$467,'Transaction Overview'!$I$2:$I$467,$A10,'Transaction Overview'!$H$2:$H$467,D$4) -> 233.33 | E10: =SUMIFS('Transaction Overview'!$D$2:$D$467,'Transaction Overview'!$I$2:$I$467,$A10,'Transaction Overview'!$H$2:$H$467,E$4) -> 233.33 | F10: =SUMIFS('Transaction Overview'!$D$2:$D$467,'Transaction Overview'!$I$2:$I$467,$A10,'Transaction Overview'!$H$2:$H$467,F$4) -> 233.33 | G10: =SUMIFS('Transaction Overview'!$D$2:$D$467,'Transaction Overview'!$I$2:$I$467,$A10,'Transaction Overview'!$H$2:$H$467,G$4) -> 233.33 | H10: =SUM(B10:G10) -> 1399.98
A11: Deal Specific: T&T Machine | B11: =SUMIFS('Transaction Overview'!$D$2:$D$467,'Transaction Overview'!$I$2:$I$467,$A11,'Transaction Overview'!$H$2:$H$467,B$4) -> 356.38 | C11: =SUMIFS('Transaction Overview'!$D$2:$D$467,'Transaction Overview'!$I$2:$I$467,$A11,'Transaction Overview'!$H$2:$H$467,C$4) -> 367.52 | D11: =SUMIFS('Transaction Overview'!$D$2:$D$467,'Transaction Overview'!$I$2:$I$467,$A11,'Transaction Overview'!$H$2:$H$467,D$4) -> 367.52 | E11: =SUMIFS('Transaction Overview'!$D$2:$D$467,'Transaction Overview'!$I$2:$I$467,$A11,'Transaction Overview'!$H$2:$H$467,E$4) -> 0 | F11: =SUMIFS('Transaction Overview'!$D$2:$D$467,'Transaction Overview'!$I$2:$I$467,$A11,'Transaction Overview'!$H$2:$H$467,F$4) -> 0 | G11: =SUMIFS('Transaction Overview'!$D$2:$D$467,'Transaction Overview'!$I$2:$I$467,$A11,'Transaction Overview'!$H$2:$H$467,G$4) -> 0 | H11: =SUM(B11:G11) -> 1091.42
A12: Subtotal — Deal-Specific | B12: =SUM(B6:B11) -> -8342.01 | C12: =SUM(C6:C11) -> 1669.13 | D12: =SUM(D6:D11) -> 1684.01 | E12: =SUM(E6:E11) -> 1074.62 | F12: =SUM(F6:F11) -> 1074.62 | G12: =SUM(G6:G11) -> 1074.62 | H12: =SUM(H6:H11) -> -1765.01
A14: Commissions — Incoming
A15: Incoming Commission: Rembrandt | B15: =SUMIFS('Transaction Overview'!$D$2:$D$467,'Transaction Overview'!$I$2:$I$467,$A15,'Transaction Overview'!$H$2:$H$467,B$4) -> 0 | C15: =SUMIFS('Transaction Overview'!$D$2:$D$467,'Transaction Overview'!$I$2:$I$467,$A15,'Transaction Overview'!$H$2:$H$467,C$4) -> 168266 | D15: =SUMIFS('Transaction Overview'!$D$2:$D$467,'Transaction Overview'!$I$2:$I$467,$A15,'Transaction Overview'!$H$2:$H$467,D$4) -> 0 | E15: =SUMIFS('Transaction Overview'!$D$2:$D$467,'Transaction Overview'!$I$2:$I$467,$A15,'Transaction Overview'!$H$2:$H$467,E$4) -> 0 | F15: =SUMIFS('Transaction Overview'!$D$2:$D$467,'Transaction Overview'!$I$2:$I$467,$A15,'Transaction Overview'!$H$2:$H$467,F$4) -> 0 | G15: =SUMIFS('Transaction Overview'!$D$2:$D$467,'Transaction Overview'!$I$2:$I$467,$A15,'Transaction Overview'!$H$2:$H$467,G$4) -> 0 | H15: =SUM(B15:G15) -> 168266
A16: Incoming Commission: SPF | B16: =SUMIFS('Transaction Overview'!$D$2:$D$467,'Transaction Overview'!$I$2:$I$467,$A16,'Transaction Overview'!$H$2:$H$467,B$4) -> 0 | C16: =SUMIFS('Transaction Overview'!$D$2:$D$467,'Transaction Overview'!$I$2:$I$467,$A16,'Transaction Overview'!$H$2:$H$467,C$4) -> 0 | D16: =SUMIFS('Transaction Overview'!$D$2:$D$467,'Transaction Overview'!$I$2:$I$467,$A16,'Transaction Overview'!$H$2:$H$467,D$4) -> 0 | E16: =SUMIFS('Transaction Overview'!$D$2:$D$467,'Transaction Overview'!$I$2:$I$467,$A16,'Transaction Overview'!$H$2:$H$467,E$4) -> 266889.44 | F16: =SUMIFS('Transaction Overview'!$D$2:$D$467,'Transaction Overview'!$I$2:$I$467,$A16,'Transaction Overview'!$H$2:$H$467,F$4) -> 0 | G16: =SUMIFS('Transaction Overview'!$D$2:$D$467,'Transaction Overview'!$I$2:$I$467,$A16,'Transaction Overview'!$H$2:$H$467,G$4) -> 0 | H16: =SUM(B16:G16) -> 266889.44
A17: Subtotal — Commissions — Incoming | B17: =SUM(B15:B16) -> 0 | C17: =SUM(C15:C16) -> 168266 | D17: =SUM(D15:D16) -> 0 | E17: =SUM(E15:E16) -> 266889.44 | F17: =SUM(F15:F16) -> 0 | G17: =SUM(G15:G16) -> 0 | H17: =SUM(H15:H16) -> 435155.44
A19: Commissions — Outgoing
A20: Kevin Wong Commission (SPF) | B20: =SUMIFS('Transaction Overview'!$D$2:$D$467,'Transaction Overview'!$I$2:$I$467,$A20,'Transaction Overview'!$H$2:$H$467,B$4) -> 0 | C20: =SUMIFS('Transaction Overview'!$D$2:$D$467,'Transaction Overview'!$I$2:$I$467,$A20,'Transaction Overview'!$H$2:$H$467,C$4) -> 0 | D20: =SUMIFS('Transaction Overview'!$D$2:$D$467,'Transaction Overview'!$I$2:$I$467,$A20,'Transaction Overview'!$H$2:$H$467,D$4) -> 0 | E20: =SUMIFS('Transaction Overview'!$D$2:$D$467,'Transaction Overview'!$I$2:$I$467,$A20,'Transaction Overview'!$H$2:$H$467,E$4) -> -16087.5 | F20: =SUMIFS('Transaction Overview'!$D$2:$D$467,'Transaction Overview'!$I$2:$I$467,$A20,'Transaction Overview'!$H$2:$H$467,F$4) -> 0 | G20: =SUMIFS('Transaction Overview'!$D$2:$D$467,'Transaction Overview'!$I$2:$I$467,$A20,'Transaction Overview'!$H$2:$H$467,G$4) -> 0 | H20: =SUM(B20:G20) -> -16087.5
A21: Kevin Wong Commission (Steve Klar) | B21: =SUMIFS('Transaction Overview'!$D$2:$D$467,'Transaction Overview'!$I$2:$I$467,$A21,'Transaction Overview'!$H$2:$H$467,B$4) -> -6000 | C21: =SUMIFS('Transaction Overview'!$D$2:$D$467,'Transaction Overview'!$I$2:$I$467,$A21,'Transaction Overview'!$H$2:$H$467,C$4) -> 0 | D21: =SUMIFS('Transaction Overview'!$D$2:$D$467,'Transaction Overview'!$I$2:$I$467,$A21,'Transaction Overview'!$H$2:$H$467,D$4) -> 0 | E21: =SUMIFS('Transaction Overview'!$D$2:$D$467,'Transaction Overview'!$I$2:$I$467,$A21,'Transaction Overview'!$H$2:$H$467,E$4) -> 0 | F21: =SUMIFS('Transaction Overview'!$D$2:$D$467,'Transaction Overview'!$I$2:$I$467,$A21,'Transaction Overview'!$H$2:$H$467,F$4) -> 0 | G21: =SUMIFS('Transaction Overview'!$D$2:$D$467,'Transaction Overview'!$I$2:$I$467,$A21,'Transaction Overview'!$H$2:$H$467,G$4) -> 0 | H21: =SUM(B21:G21) -> -6000
A22: Meg Maran - MDC Commission | B22: =SUMIFS('Transaction Overview'!$D$2:$D$467,'Transaction Overview'!$I$2:$I$467,$A22,'Transaction Overview'!$H$2:$H$467,B$4) -> 0 | C22: =SUMIFS('Transaction Overview'!$D$2:$D$467,'Transaction Overview'!$I$2:$I$467,$A22,'Transaction Overview'!$H$2:$H$467,C$4) -> 0 | D22: =SUMIFS('Transaction Overview'!$D$2:$D$467,'Transaction Overview'!$I$2:$I$467,$A22,'Transaction Overview'!$H$2:$H$467,D$4) -> 0 | E22: =SUMIFS('Transaction Overview'!$D$2:$D$467,'Transaction Overview'!$I$2:$I$467,$A22,'Transaction Overview'!$H$2:$H$467,E$4) -> -1500 | F22: =SUMIFS('Transaction Overview'!$D$2:$D$467,'Transaction Overview'!$I$2:$I$467,$A22,'Transaction Overview'!$H$2:$H$467,F$4) -> 0 | G22: =SUMIFS('Transaction Overview'!$D$2:$D$467,'Transaction Overview'!$I$2:$I$467,$A22,'Transaction Overview'!$H$2:$H$467,G$4) -> 0 | H22: =SUM(B22:G22) -> -1500
A23: Subtotal — Commissions — Outgoing | B23: =SUM(B20:B22) -> -6000 | C23: =SUM(C20:C22) -> 0 | D23: =SUM(D20:D22) -> 0 | E23: =SUM(E20:E22) -> -17587.5 | F23: =SUM(F20:F22) -> 0 | G23: =SUM(G20:G22) -> 0 | H23: =SUM(H20:H22) -> -23587.5
A25: MAG Pass-Through
A26: MAG - Admeer Advisory Reimbursement | B26: =SUMIFS('Transaction Overview'!$D$2:$D$467,'Transaction Overview'!$I$2:$I$467,$A26,'Transaction Overview'!$H$2:$H$467,B$4) -> 0 | C26: =SUMIFS('Transaction Overview'!$D$2:$D$467,'Transaction Overview'!$I$2:$I$467,$A26,'Transaction Overview'!$H$2:$H$467,C$4) -> 5000 | D26: =SUMIFS('Transaction Overview'!$D$2:$D$467,'Transaction Overview'!$I$2:$I$467,$A26,'Transaction Overview'!$H$2:$H$467,D$4) -> 0 | E26: =SUMIFS('Transaction Overview'!$D$2:$D$467,'Transaction Overview'!$I$2:$I$467,$A26,'Transaction Overview'!$H$2:$H$467,E$4) -> 0 | F26: =SUMIFS('Transaction Overview'!$D$2:$D$467,'Transaction Overview'!$I$2:$I$467,$A26,'Transaction Overview'!$H$2:$H$467,F$4) -> 0 | G26: =SUMIFS('Transaction Overview'!$D$2:$D$467,'Transaction Overview'!$I$2:$I$467,$A26,'Transaction Overview'!$H$2:$H$467,G$4) -> 0 | H26: =SUM(B26:G26) -> 5000
A27: MAG - Admeer Advisory Transfer | B27: =SUMIFS('Transaction Overview'!$D$2:$D$467,'Transaction Overview'!$I$2:$I$467,$A27,'Transaction Overview'!$H$2:$H$467,B$4) -> 0 | C27: =SUMIFS('Transaction Overview'!$D$2:$D$467,'Transaction Overview'!$I$2:$I$467,$A27,'Transaction Overview'!$H$2:$H$467,C$4) -> -5000 | D27: =SUMIFS('Transaction Overview'!$D$2:$D$467,'Transaction Overview'!$I$2:$I$467,$A27,'Transaction Overview'!$H$2:$H$467,D$4) -> 0 | E27: =SUMIFS('Transaction Overview'!$D$2:$D$467,'Transaction Overview'!$I$2:$I$467,$A27,'Transaction Overview'!$H$2:$H$467,E$4) -> -5000 | F27: =SUMIFS('Transaction Overview'!$D$2:$D$467,'Transaction Overview'!$I$2:$I$467,$A27,'Transaction Overview'!$H$2:$H$467,F$4) -> 0 | G27: =SUMIFS('Transaction Overview'!$D$2:$D$467,'Transaction Overview'!$I$2:$I$467,$A27,'Transaction Overview'!$H$2:$H$467,G$4) -> 0 | H27: =SUM(B27:G27) -> -10000
A28: MAG Marketing Reimbursement | B28: =SUMIFS('Transaction Overview'!$D$2:$D$467,'Transaction Overview'!$I$2:$I$467,$A28,'Transaction Overview'!$H$2:$H$467,B$4) -> 0 | C28: =SUMIFS('Transaction Overview'!$D$2:$D$467,'Transaction Overview'!$I$2:$I$467,$A28,'Transaction Overview'!$H$2:$H$467,C$4) -> 0 | D28: =SUMIFS('Transaction Overview'!$D$2:$D$467,'Transaction Overview'!$I$2:$I$467,$A28,'Transaction Overview'!$H$2:$H$467,D$4) -> 0 | E28: =SUMIFS('Transaction Overview'!$D$2:$D$467,'Transaction Overview'!$I$2:$I$467,$A28,'Transaction Overview'!$H$2:$H$467,E$4) -> 15000 | F28: =SUMIFS('Transaction Overview'!$D$2:$D$467,'Transaction Overview'!$I$2:$I$467,$A28,'Transaction Overview'!$H$2:$H$467,F$4) -> 0 | G28: =SUMIFS('Transaction Overview'!$D$2:$D$467,'Transaction Overview'!$I$2:$I$467,$A28,'Transaction Overview'!$H$2:$H$467,G$4) -> 0 | H28: =SUM(B28:G28) -> 15000
A29: Subtotal — MAG Pass-Through | B29: =SUM(B26:B28) -> 0 | C29: =SUM(C26:C28) -> 0 | D29: =SUM(D26:D28) -> 0 | E29: =SUM(E26:E28) -> 10000 | F29: =SUM(F26:F28) -> 0 | G29: =SUM(G26:G28) -> 0 | H29: =SUM(H26:H28) -> 10000
A31: Wire Transfers — Incoming
A32: Incoming wire from JC Whitner | B32: =SUMIFS('Transaction Overview'!$D$2:$D$467,'Transaction Overview'!$I$2:$I$467,$A32,'Transaction Overview'!$H$2:$H$467,B$4) -> 0 | C32: =SUMIFS('Transaction Overview'!$D$2:$D$467,'Transaction Overview'!$I$2:$I$467,$A32,'Transaction Overview'!$H$2:$H$467,C$4) -> 20000 | D32: =SUMIFS('Transaction Overview'!$D$2:$D$467,'Transaction Overview'!$I$2:$I$467,$A32,'Transaction Overview'!$H$2:$H$467,D$4) -> 0 | E32: =SUMIFS('Transaction Overview'!$D$2:$D$467,'Transaction Overview'!$I$2:$I$467,$A32,'Transaction Overview'!$H$2:$H$467,E$4) -> 0 | F32: =SUMIFS('Transaction Overview'!$D$2:$D$467,'Transaction Overview'!$I$2:$I$467,$A32,'Transaction Overview'!$H$2:$H$467,F$4) -> 0 | G32: =SUMIFS('Transaction Overview'!$D$2:$D$467,'Transaction Overview'!$I$2:$I$467,$A32,'Transaction Overview'!$H$2:$H$467,G$4) -> 0 | H32: =SUM(B32:G32) -> 20000
A33: Incoming wire from Moab (Leftover Funds) | B33: =SUMIFS('Transaction Overview'!$D$2:$D$467,'Transaction Overview'!$I$2:$I$467,$A33,'Transaction Overview'!$H$2:$H$467,B$4) -> 0 | C33: =SUMIFS('Transaction Overview'!$D$2:$D$467,'Transaction Overview'!$I$2:$I$467,$A33,'Transaction Overview'!$H$2:$H$467,C$4) -> 58370.85 | D33: =SUMIFS('Transaction Overview'!$D$2:$D$467,'Transaction Overview'!$I$2:$I$467,$A33,'Transaction Overview'!$H$2:$H$467,D$4) -> 0 | E33: =SUMIFS('Transaction Overview'!$D$2:$D$467,'Transaction Overview'!$I$2:$I$467,$A33,'Transaction Overview'!$H$2:$H$467,E$4) -> 0 | F33: =SUMIFS('Transaction Overview'!$D$2:$D$467,'Transaction Overview'!$I$2:$I$467,$A33,'Transaction Overview'!$H$2:$H$467,F$4) -> 0 | G33: =SUMIFS('Transaction Overview'!$D$2:$D$467,'Transaction Overview'!$I$2:$I$467,$A33,'Transaction Overview'!$H$2:$H$467,G$4) -> 0 | H33: =SUM(B33:G33) -> 58370.85
A34: Incoming wire from Steve Klar | B34: =SUMIFS('Transaction Overview'!$D$2:$D$467,'Transaction Overview'!$I$2:$I$467,$A34,'Transaction Overview'!$H$2:$H$467,B$4) -> 16000 | C34: =SUMIFS('Transaction Overview'!$D$2:$D$467,'Transaction Overview'!$I$2:$I$467,$A34,'Transaction Overview'!$H$2:$H$467,C$4) -> 0 | D34: =SUMIFS('Transaction Overview'!$D$2:$D$467,'Transaction Overview'!$I$2:$I$467,$A34,'Transaction Overview'!$H$2:$H$467,D$4) -> 0 | E34: =SUMIFS('Transaction Overview'!$D$2:$D$467,'Transaction Overview'!$I$2:$I$467,$A34,'Transaction Overview'!$H$2:$H$467,E$4) -> 0 | F34: =SUMIFS('Transaction Overview'!$D$2:$D$467,'Transaction Overview'!$I$2:$I$467,$A34,'Transaction Overview'!$H$2:$H$467,F$4) -> 0 | G34: =SUMIFS('Transaction Overview'!$D$2:$D$467,'Transaction Overview'!$I$2:$I$467,$A34,'Transaction Overview'!$H$2:$H$467,G$4) -> 0 | H34: =SUM(B34:G34) -> 16000
A35: Subtotal — Wire Transfers — Incoming | B35: =SUM(B32:B34) -> 16000 | C35: =SUM(C32:C34) -> 78370.85 | D35: =SUM(D32:D34) -> 0 | E35: =SUM(E32:E34) -> 0 | F35: =SUM(F32:F34) -> 0 | G35: =SUM(G32:G34) -> 0 | H35: =SUM(H32:H34) -> 94370.85
A37: Wire Transfers — Outgoing
A38: Wire to Gi Capital Group (+ Moab Funds) | B38: =SUMIFS('Transaction Overview'!$D$2:$D$467,'Transaction Overview'!$I$2:$I$467,$A38,'Transaction Overview'!$H$2:$H$467,B$4) -> 0 | C38: =SUMIFS('Transaction Overview'!$D$2:$D$467,'Transaction Overview'!$I$2:$I$467,$A38,'Transaction Overview'!$H$2:$H$467,C$4) -> -56670.85 | D38: =SUMIFS('Transaction Overview'!$D$2:$D$467,'Transaction Overview'!$I$2:$I$467,$A38,'Transaction Overview'!$H$2:$H$467,D$4) -> 0 | E38: =SUMIFS('Transaction Overview'!$D$2:$D$467,'Transaction Overview'!$I$2:$I$467,$A38,'Transaction Overview'!$H$2:$H$467,E$4) -> 0 | F38: =SUMIFS('Transaction Overview'!$D$2:$D$467,'Transaction Overview'!$I$2:$I$467,$A38,'Transaction Overview'!$H$2:$H$467,F$4) -> 0 | G38: =SUMIFS('Transaction Overview'!$D$2:$D$467,'Transaction Overview'!$I$2:$I$467,$A38,'Transaction Overview'!$H$2:$H$467,G$4) -> 0 | H38: =SUM(B38:G38) -> -56670.85
A39: Wire to Jon Brandon | B39: =SUMIFS('Transaction Overview'!$D$2:$D$467,'Transaction Overview'!$I$2:$I$467,$A39,'Transaction Overview'!$H$2:$H$467,B$4) -> 0 | C39: =SUMIFS('Transaction Overview'!$D$2:$D$467,'Transaction Overview'!$I$2:$I$467,$A39,'Transaction Overview'!$H$2:$H$467,C$4) -> -10000 | D39: =SUMIFS('Transaction Overview'!$D$2:$D$467,'Transaction Overview'!$I$2:$I$467,$A39,'Transaction Overview'!$H$2:$H$467,D$4) -> 0 | E39: =SUMIFS('Transaction Overview'!$D$2:$D$467,'Transaction Overview'!$I$2:$I$467,$A39,'Transaction Overview'!$H$2:$H$467,E$4) -> 0 | F39: =SUMIFS('Transaction Overview'!$D$2:$D$467,'Transaction Overview'!$I$2:$I$467,$A39,'Transaction Overview'!$H$2:$H$467,F$4) -> 0 | G39: =SUMIFS('Transaction Overview'!$D$2:$D$467,'Transaction Overview'!$I$2:$I$467,$A39,'Transaction Overview'!$H$2:$H$467,G$4) -> 0 | H39: =SUM(B39:G39) -> -10000
A40: Wire to Ryan Bodmer | B40: =SUMIFS('Transaction Overview'!$D$2:$D$467,'Transaction Overview'!$I$2:$I$467,$A40,'Transaction Overview'!$H$2:$H$467,B$4) -> 0 | C40: =SUMIFS('Transaction Overview'!$D$2:$D$467,'Transaction Overview'!$I$2:$I$467,$A40,'Transaction Overview'!$H$2:$H$467,C$4) -> -10000 | D40: =SUMIFS('Transaction Overview'!$D$2:$D$467,'Transaction Overview'!$I$2:$I$467,$A40,'Transaction Overview'!$H$2:$H$467,D$4) -> 0 | E40: =SUMIFS('Transaction Overview'!$D$2:$D$467,'Transaction Overview'!$I$2:$I$467,$A40,'Transaction Overview'!$H$2:$H$467,E$4) -> 0 | F40: =SUMIFS('Transaction Overview'!$D$2:$D$467,'Transaction Overview'!$I$2:$I$467,$A40,'Transaction Overview'!$H$2:$H$467,F$4) -> 0 | G40: =SUMIFS('Transaction Overview'!$D$2:$D$467,'Transaction Overview'!$I$2:$I$467,$A40,'Transaction Overview'!$H$2:$H$467,G$4) -> 0 | H40: =SUM(B40:G40) -> -10000
A41: Subtotal — Wire Transfers — Outgoing | B41: =SUM(B38:B40) -> 0 | C41: =SUM(C38:C40) -> -76670.85 | D41: =SUM(D38:D40) -> 0 | E41: =SUM(E38:E40) -> 0 | F41: =SUM(F38:F40) -> 0 | G41: =SUM(G38:G40) -> 0 | H41: =SUM(H38:H40) -> -76670.85
A43: Intercompany & Savings Transfers
A44: Transfer From DWG Capital Group | B44: =SUMIFS('Transaction Overview'!$D$2:$D$467,'Transaction Overview'!$I$2:$I$467,$A44,'Transaction Overview'!$H$2:$H$467,B$4) -> 0 | C44: =SUMIFS('Transaction Overview'!$D$2:$D$467,'Transaction Overview'!$I$2:$I$467,$A44,'Transaction Overview'!$H$2:$H$467,C$4) -> 8556.41 | D44: =SUMIFS('Transaction Overview'!$D$2:$D$467,'Transaction Overview'!$I$2:$I$467,$A44,'Transaction Overview'!$H$2:$H$467,D$4) -> 0 | E44: =SUMIFS('Transaction Overview'!$D$2:$D$467,'Transaction Overview'!$I$2:$I$467,$A44,'Transaction Overview'!$H$2:$H$467,E$4) -> 0 | F44: =SUMIFS('Transaction Overview'!$D$2:$D$467,'Transaction Overview'!$I$2:$I$467,$A44,'Transaction Overview'!$H$2:$H$467,F$4) -> 0 | G44: =SUMIFS('Transaction Overview'!$D$2:$D$467,'Transaction Overview'!$I$2:$I$467,$A44,'Transaction Overview'!$H$2:$H$467,G$4) -> 0 | H44: =SUM(B44:G44) -> 8556.41
A45: Transfer From Poseidon | B45: =SUMIFS('Transaction Overview'!$D$2:$D$467,'Transaction Overview'!$I$2:$I$467,$A45,'Transaction Overview'!$H$2:$H$467,B$4) -> 2000 | C45: =SUMIFS('Transaction Overview'!$D$2:$D$467,'Transaction Overview'!$I$2:$I$467,$A45,'Transaction Overview'!$H$2:$H$467,C$4) -> 0 | D45: =SUMIFS('Transaction Overview'!$D$2:$D$467,'Transaction Overview'!$I$2:$I$467,$A45,'Transaction Overview'!$H$2:$H$467,D$4) -> 0 | E45: =SUMIFS('Transaction Overview'!$D$2:$D$467,'Transaction Overview'!$I$2:$I$467,$A45,'Transaction Overview'!$H$2:$H$467,E$4) -> 0 | F45: =SUMIFS('Transaction Overview'!$D$2:$D$467,'Transaction Overview'!$I$2:$I$467,$A45,'Transaction Overview'!$H$2:$H$467,F$4) -> 0 | G45: =SUMIFS('Transaction Overview'!$D$2:$D$467,'Transaction Overview'!$I$2:$I$467,$A45,'Transaction Overview'!$H$2:$H$467,G$4) -> 0 | H45: =SUM(B45:G45) -> 2000
A46: Transfer From SPF | B46: =SUMIFS('Transaction Overview'!$D$2:$D$467,'Transaction Overview'!$I$2:$I$467,$A46,'Transaction Overview'!$H$2:$H$467,B$4) -> 0 | C46: =SUMIFS('Transaction Overview'!$D$2:$D$467,'Transaction Overview'!$I$2:$I$467,$A46,'Transaction Overview'!$H$2:$H$467,C$4) -> 0 | D46: =SUMIFS('Transaction Overview'!$D$2:$D$467,'Transaction Overview'!$I$2:$I$467,$A46,'Transaction Overview'!$H$2:$H$467,D$4) -> 0 | E46: =SUMIFS('Transaction Overview'!$D$2:$D$467,'Transaction Overview'!$I$2:$I$467,$A46,'Transaction Overview'!$H$2:$H$467,E$4) -> 11450 | F46: =SUMIFS('Transaction Overview'!$D$2:$D$467,'Transaction Overview'!$I$2:$I$467,$A46,'Transaction Overview'!$H$2:$H$467,F$4) -> 0 | G46: =SUMIFS('Transaction Overview'!$D$2:$D$467,'Transaction Overview'!$I$2:$I$467,$A46,'Transaction Overview'!$H$2:$H$467,G$4) -> 0 | H46: =SUM(B46:G46) -> 11450
A47: Transfer From Stryten | B47: =SUMIFS('Transaction Overview'!$D$2:$D$467,'Transaction Overview'!$I$2:$I$467,$A47,'Transaction Overview'!$H$2:$H$467,B$4) -> 0 | C47: =SUMIFS('Transaction Overview'!$D$2:$D$467,'Transaction Overview'!$I$2:$I$467,$A47,'Transaction Overview'!$H$2:$H$467,C$4) -> 50000 | D47: =SUMIFS('Transaction Overview'!$D$2:$D$467,'Transaction Overview'!$I$2:$I$467,$A47,'Transaction Overview'!$H$2:$H$467,D$4) -> 50000 | E47: =SUMIFS('Transaction Overview'!$D$2:$D$467,'Transaction Overview'!$I$2:$I$467,$A47,'Transaction Overview'!$H$2:$H$467,E$4) -> 0 | F47: =SUMIFS('Transaction Overview'!$D$2:$D$467,'Transaction Overview'!$I$2:$I$467,$A47,'Transaction Overview'!$H$2:$H$467,F$4) -> 0 | G47: =SUMIFS('Transaction Overview'!$D$2:$D$467,'Transaction Overview'!$I$2:$I$467,$A47,'Transaction Overview'!$H$2:$H$467,G$4) -> 0 | H47: =SUM(B47:G47) -> 100000
A48: Transfer to Buckeye | B48: =SUMIFS('Transaction Overview'!$D$2:$D$467,'Transaction Overview'!$I$2:$I$467,$A48,'Transaction Overview'!$H$2:$H$467,B$4) -> 0 | C48: =SUMIFS('Transaction Overview'!$D$2:$D$467,'Transaction Overview'!$I$2:$I$467,$A48,'Transaction Overview'!$H$2:$H$467,C$4) -> 0 | D48: =SUMIFS('Transaction Overview'!$D$2:$D$467,'Transaction Overview'!$I$2:$I$467,$A48,'Transaction Overview'!$H$2:$H$467,D$4) -> 0 | E48: =SUMIFS('Transaction Overview'!$D$2:$D$467,'Transaction Overview'!$I$2:$I$467,$A48,'Transaction Overview'!$H$2:$H$467,E$4) -> 0 | F48: =SUMIFS('Transaction Overview'!$D$2:$D$467,'Transaction Overview'!$I$2:$I$467,$A48,'Transaction Overview'!$H$2:$H$467,F$4) -> -20000 | G48: =SUMIFS('Transaction Overview'!$D$2:$D$467,'Transaction Overview'!$I$2:$I$467,$A48,'Transaction Overview'!$H$2:$H$467,G$4) -> 0 | H48: =SUM(B48:G48) -> -20000
A49: Transfer to DWG Capital Group | B49: =SUMIFS('Transaction Overview'!$D$2:$D$467,'Transaction Overview'!$I$2:$I$467,$A49,'Transaction Overview'!$H$2:$H$467,B$4) -> -70000 | C49: =SUMIFS('Transaction Overview'!$D$2:$D$467,'Transaction Overview'!$I$2:$I$467,$A49,'Transaction Overview'!$H$2:$H$467,C$4) -> -68556.41 | D49: =SUMIFS('Transaction Overview'!$D$2:$D$467,'Transaction Overview'!$I$2:$I$467,$A49,'Transaction Overview'!$H$2:$H$467,D$4) -> -55000 | E49: =SUMIFS('Transaction Overview'!$D$2:$D$467,'Transaction Overview'!$I$2:$I$467,$A49,'Transaction Overview'!$H$2:$H$467,E$4) -> -75000 | F49: =SUMIFS('Transaction Overview'!$D$2:$D$467,'Transaction Overview'!$I$2:$I$467,$A49,'Transaction Overview'!$H$2:$H$467,F$4) -> 0 | G49: =SUMIFS('Transaction Overview'!$D$2:$D$467,'Transaction Overview'!$I$2:$I$467,$A49,'Transaction Overview'!$H$2:$H$467,G$4) -> -30000 | H49: =SUM(B49:G49) -> -298556.41
A50: Transfer to DWG Capital Group_Costar | B50: =SUMIFS('Transaction Overview'!$D$2:$D$467,'Transaction Overview'!$I$2:$I$467,$A50,'Transaction Overview'!$H$2:$H$467,B$4) -> 0 | C50: =SUMIFS('Transaction Overview'!$D$2:$D$467,'Transaction Overview'!$I$2:$I$467,$A50,'Transaction Overview'!$H$2:$H$467,C$4) -> -15000 | D50: =SUMIFS('Transaction Overview'!$D$2:$D$467,'Transaction Overview'!$I$2:$I$467,$A50,'Transaction Overview'!$H$2:$H$467,D$4) -> 0 | E50: =SUMIFS('Transaction Overview'!$D$2:$D$467,'Transaction Overview'!$I$2:$I$467,$A50,'Transaction Overview'!$H$2:$H$467,E$4) -> 0 | F50: =SUMIFS('Transaction Overview'!$D$2:$D$467,'Transaction Overview'!$I$2:$I$467,$A50,'Transaction Overview'!$H$2:$H$467,F$4) -> 0 | G50: =SUMIFS('Transaction Overview'!$D$2:$D$467,'Transaction Overview'!$I$2:$I$467,$A50,'Transaction Overview'!$H$2:$H$467,G$4) -> 0 | H50: =SUM(B50:G50) -> -15000
A51: Transfer to DWG Capital Partners | B51: =SUMIFS('Transaction Overview'!$D$2:$D$467,'Transaction Overview'!$I$2:$I$467,$A51,'Transaction Overview'!$H$2:$H$467,B$4) -> -46000 | C51: =SUMIFS('Transaction Overview'!$D$2:$D$467,'Transaction Overview'!$I$2:$I$467,$A51,'Transaction Overview'!$H$2:$H$467,C$4) -> 0 | D51: =SUMIFS('Transaction Overview'!$D$2:$D$467,'Transaction Overview'!$I$2:$I$467,$A51,'Transaction Overview'!$H$2:$H$467,D$4) -> -1000 | E51: =SUMIFS('Transaction Overview'!$D$2:$D$467,'Transaction Overview'!$I$2:$I$467,$A51,'Transaction Overview'!$H$2:$H$467,E$4) -> -10000 | F51: =SUMIFS('Transaction Overview'!$D$2:$D$467,'Transaction Overview'!$I$2:$I$467,$A51,'Transaction Overview'!$H$2:$H$467,F$4) -> -20000 | G51: =SUMIFS('Transaction Overview'!$D$2:$D$467,'Transaction Overview'!$I$2:$I$467,$A51,'Transaction Overview'!$H$2:$H$467,G$4) -> 0 | H51: =SUM(B51:G51) -> -77000
A52: Transfer to Edgebuilders | B52: =SUMIFS('Transaction Overview'!$D$2:$D$467,'Transaction Overview'!$I$2:$I$467,$A52,'Transaction Overview'!$H$2:$H$467,B$4) -> -35000 | C52: =SUMIFS('Transaction Overview'!$D$2:$D$467,'Transaction Overview'!$I$2:$I$467,$A52,'Transaction Overview'!$H$2:$H$467,C$4) -> 0 | D52: =SUMIFS('Transaction Overview'!$D$2:$D$467,'Transaction Overview'!$I$2:$I$467,$A52,'Transaction Overview'!$H$2:$H$467,D$4) -> 0 | E52: =SUMIFS('Transaction Overview'!$D$2:$D$467,'Transaction Overview'!$I$2:$I$467,$A52,'Transaction Overview'!$H$2:$H$467,E$4) -> -200 | F52: =SUMIFS('Transaction Overview'!$D$2:$D$467,'Transaction Overview'!$I$2:$I$467,$A52,'Transaction Overview'!$H$2:$H$467,F$4) -> 0 | G52: =SUMIFS('Transaction Overview'!$D$2:$D$467,'Transaction Overview'!$I$2:$I$467,$A52,'Transaction Overview'!$H$2:$H$467,G$4) -> 0 | H52: =SUM(B52:G52) -> -35200
A53: Transfer to JAL Southbend | B53: =SUMIFS('Transaction Overview'!$D$2:$D$467,'Transaction Overview'!$I$2:$I$467,$A53,'Transaction Overview'!$H$2:$H$467,B$4) -> 0 | C53: =SUMIFS('Transaction Overview'!$D$2:$D$467,'Transaction Overview'!$I$2:$I$467,$A53,'Transaction Overview'!$H$2:$H$467,C$4) -> 0 | D53: =SUMIFS('Transaction Overview'!$D$2:$D$467,'Transaction Overview'!$I$2:$I$467,$A53,'Transaction Overview'!$H$2:$H$467,D$4) -> -13000 | E53: =SUMIFS('Transaction Overview'!$D$2:$D$467,'Transaction Overview'!$I$2:$I$467,$A53,'Transaction Overview'!$H$2:$H$467,E$4) -> 0 | F53: =SUMIFS('Transaction Overview'!$D$2:$D$467,'Transaction Overview'!$I$2:$I$467,$A53,'Transaction Overview'!$H$2:$H$467,F$4) -> 0 | G53: =SUMIFS('Transaction Overview'!$D$2:$D$467,'Transaction Overview'!$I$2:$I$467,$A53,'Transaction Overview'!$H$2:$H$467,G$4) -> 0 | H53: =SUM(B53:G53) -> -13000
A54: Transfer to Judd Sol Prop | B54: =SUMIFS('Transaction Overview'!$D$2:$D$467,'Transaction Overview'!$I$2:$I$467,$A54,'Transaction Overview'!$H$2:$H$467,B$4) -> -100 | C54: =SUMIFS('Transaction Overview'!$D$2:$D$467,'Transaction Overview'!$I$2:$I$467,$A54,'Transaction Overview'!$H$2:$H$467,C$4) -> -100 | D54: =SUMIFS('Transaction Overview'!$D$2:$D$467,'Transaction Overview'!$I$2:$I$467,$A54,'Transaction Overview'!$H$2:$H$467,D$4) -> 0 | E54: =SUMIFS('Transaction Overview'!$D$2:$D$467,'Transaction Overview'!$I$2:$I$467,$A54,'Transaction Overview'!$H$2:$H$467,E$4) -> 0 | F54: =SUMIFS('Transaction Overview'!$D$2:$D$467,'Transaction Overview'!$I$2:$I$467,$A54,'Transaction Overview'!$H$2:$H$467,F$4) -> 0 | G54: =SUMIFS('Transaction Overview'!$D$2:$D$467,'Transaction Overview'!$I$2:$I$467,$A54,'Transaction Overview'!$H$2:$H$467,G$4) -> 0 | H54: =SUM(B54:G54) -> -200
A55: Subtotal — Intercompany & Savings Transfers | B55: =SUM(B44:B54) -> -149100 | C55: =SUM(C44:C54) -> -25100 | D55: =SUM(D44:D54) -> -19000 | E55: =SUM(E44:E54) -> -73750 | F55: =SUM(F44:F54) -> -40000 | G55: =SUM(G44:G54) -> -30000 | H55: =SUM(H44:H54) -> -336950
A57: Owner / Family Distributions
A58: Transfer to Angela Dunning | B58: =SUMIFS('Transaction Overview'!$D$2:$D$467,'Transaction Overview'!$I$2:$I$467,$A58,'Transaction Overview'!$H$2:$H$467,B$4) -> 0 | C58: =SUMIFS('Transaction Overview'!$D$2:$D$467,'Transaction Overview'!$I$2:$I$467,$A58,'Transaction Overview'!$H$2:$H$467,C$4) -> -30000 | D58: =SUMIFS('Transaction Overview'!$D$2:$D$467,'Transaction Overview'!$I$2:$I$467,$A58,'Transaction Overview'!$H$2:$H$467,D$4) -> 0 | E58: =SUMIFS('Transaction Overview'!$D$2:$D$467,'Transaction Overview'!$I$2:$I$467,$A58,'Transaction Overview'!$H$2:$H$467,E$4) -> 0 | F58: =SUMIFS('Transaction Overview'!$D$2:$D$467,'Transaction Overview'!$I$2:$I$467,$A58,'Transaction Overview'!$H$2:$H$467,F$4) -> 0 | G58: =SUMIFS('Transaction Overview'!$D$2:$D$467,'Transaction Overview'!$I$2:$I$467,$A58,'Transaction Overview'!$H$2:$H$467,G$4) -> -1000 | H58: =SUM(B58:G58) -> -31000
A59: Transfer to TX Personal Joint | B59: =SUMIFS('Transaction Overview'!$D$2:$D$467,'Transaction Overview'!$I$2:$I$467,$A59,'Transaction Overview'!$H$2:$H$467,B$4) -> 0 | C59: =SUMIFS('Transaction Overview'!$D$2:$D$467,'Transaction Overview'!$I$2:$I$467,$A59,'Transaction Overview'!$H$2:$H$467,C$4) -> -40000 | D59: =SUMIFS('Transaction Overview'!$D$2:$D$467,'Transaction Overview'!$I$2:$I$467,$A59,'Transaction Overview'!$H$2:$H$467,D$4) -> 0 | E59: =SUMIFS('Transaction Overview'!$D$2:$D$467,'Transaction Overview'!$I$2:$I$467,$A59,'Transaction Overview'!$H$2:$H$467,E$4) -> 0 | F59: =SUMIFS('Transaction Overview'!$D$2:$D$467,'Transaction Overview'!$I$2:$I$467,$A59,'Transaction Overview'!$H$2:$H$467,F$4) -> 0 | G59: =SUMIFS('Transaction Overview'!$D$2:$D$467,'Transaction Overview'!$I$2:$I$467,$A59,'Transaction Overview'!$H$2:$H$467,G$4) -> 0 | H59: =SUM(B59:G59) -> -40000
A60: Subtotal — Owner / Family Distributions | B60: =SUM(B58:B59) -> 0 | C60: =SUM(C58:C59) -> -70000 | D60: =SUM(D58:D59) -> 0 | E60: =SUM(E58:E59) -> 0 | F60: =SUM(F58:F59) -> 0 | G60: =SUM(G58:G59) -> -1000 | H60: =SUM(H58:H59) -> -71000
A62: P2P Payments (Zelle/Venmo/PayPal)
A63: Apple Payment | B63: =SUMIFS('Transaction Overview'!$D$2:$D$467,'Transaction Overview'!$I$2:$I$467,$A63,'Transaction Overview'!$H$2:$H$467,B$4) -> 0 | C63: =SUMIFS('Transaction Overview'!$D$2:$D$467,'Transaction Overview'!$I$2:$I$467,$A63,'Transaction Overview'!$H$2:$H$467,C$4) -> -100 | D63: =SUMIFS('Transaction Overview'!$D$2:$D$467,'Transaction Overview'!$I$2:$I$467,$A63,'Transaction Overview'!$H$2:$H$467,D$4) -> 0 | E63: =SUMIFS('Transaction Overview'!$D$2:$D$467,'Transaction Overview'!$I$2:$I$467,$A63,'Transaction Overview'!$H$2:$H$467,E$4) -> 0 | F63: =SUMIFS('Transaction Overview'!$D$2:$D$467,'Transaction Overview'!$I$2:$I$467,$A63,'Transaction Overview'!$H$2:$H$467,F$4) -> 0 | G63: =SUMIFS('Transaction Overview'!$D$2:$D$467,'Transaction Overview'!$I$2:$I$467,$A63,'Transaction Overview'!$H$2:$H$467,G$4) -> 0 | H63: =SUM(B63:G63) -> -100
A64: Zelle - Chase Hall | B64: =SUMIFS('Transaction Overview'!$D$2:$D$467,'Transaction Overview'!$I$2:$I$467,$A64,'Transaction Overview'!$H$2:$H$467,B$4) -> -325 | C64: =SUMIFS('Transaction Overview'!$D$2:$D$467,'Transaction Overview'!$I$2:$I$467,$A64,'Transaction Overview'!$H$2:$H$467,C$4) -> 0 | D64: =SUMIFS('Transaction Overview'!$D$2:$D$467,'Transaction Overview'!$I$2:$I$467,$A64,'Transaction Overview'!$H$2:$H$467,D$4) -> 0 | E64: =SUMIFS('Transaction Overview'!$D$2:$D$467,'Transaction Overview'!$I$2:$I$467,$A64,'Transaction Overview'!$H$2:$H$467,E$4) -> 0 | F64: =SUMIFS('Transaction Overview'!$D$2:$D$467,'Transaction Overview'!$I$2:$I$467,$A64,'Transaction Overview'!$H$2:$H$467,F$4) -> 0 | G64: =SUMIFS('Transaction Overview'!$D$2:$D$467,'Transaction Overview'!$I$2:$I$467,$A64,'Transaction Overview'!$H$2:$H$467,G$4) -> 0 | H64: =SUM(B64:G64) -> -325
A65: Zelle - Francisco Bautista | B65: =SUMIFS('Transaction Overview'!$D$2:$D$467,'Transaction Overview'!$I$2:$I$467,$A65,'Transaction Overview'!$H$2:$H$467,B$4) -> 0 | C65: =SUMIFS('Transaction Overview'!$D$2:$D$467,'Transaction Overview'!$I$2:$I$467,$A65,'Transaction Overview'!$H$2:$H$467,C$4) -> 0 | D65: =SUMIFS('Transaction Overview'!$D$2:$D$467,'Transaction Overview'!$I$2:$I$467,$A65,'Transaction Overview'!$H$2:$H$467,D$4) -> 0 | E65: =SUMIFS('Transaction Overview'!$D$2:$D$467,'Transaction Overview'!$I$2:$I$467,$A65,'Transaction Overview'!$H$2:$H$467,E$4) -> 0 | F65: =SUMIFS('Transaction Overview'!$D$2:$D$467,'Transaction Overview'!$I$2:$I$467,$A65,'Transaction Overview'!$H$2:$H$467,F$4) -> 0 | G65: =SUMIFS('Transaction Overview'!$D$2:$D$467,'Transaction Overview'!$I$2:$I$467,$A65,'Transaction Overview'!$H$2:$H$467,G$4) -> -2500 | H65: =SUM(B65:G65) -> -2500
A66: Zelle - Scott Brech | B66: =SUMIFS('Transaction Overview'!$D$2:$D$467,'Transaction Overview'!$I$2:$I$467,$A66,'Transaction Overview'!$H$2:$H$467,B$4) -> -700 | C66: =SUMIFS('Transaction Overview'!$D$2:$D$467,'Transaction Overview'!$I$2:$I$467,$A66,'Transaction Overview'!$H$2:$H$467,C$4) -> 0 | D66: =SUMIFS('Transaction Overview'!$D$2:$D$467,'Transaction Overview'!$I$2:$I$467,$A66,'Transaction Overview'!$H$2:$H$467,D$4) -> 0 | E66: =SUMIFS('Transaction Overview'!$D$2:$D$467,'Transaction Overview'!$I$2:$I$467,$A66,'Transaction Overview'!$H$2:$H$467,E$4) -> 0 | F66: =SUMIFS('Transaction Overview'!$D$2:$D$467,'Transaction Overview'!$I$2:$I$467,$A66,'Transaction Overview'!$H$2:$H$467,F$4) -> 0 | G66: =SUMIFS('Transaction Overview'!$D$2:$D$467,'Transaction Overview'!$I$2:$I$467,$A66,'Transaction Overview'!$H$2:$H$467,G$4) -> 0 | H66: =SUM(B66:G66) -> -700
A67: Apple Cash | B67: =SUMIFS('Transaction Overview'!$D$2:$D$467,'Transaction Overview'!$I$2:$I$467,$A67,'Transaction Overview'!$H$2:$H$467,B$4) -> -370 | C67: =SUMIFS('Transaction Overview'!$D$2:$D$467,'Transaction Overview'!$I$2:$I$467,$A67,'Transaction Overview'!$H$2:$H$467,C$4) -> 0 | D67: =SUMIFS('Transaction Overview'!$D$2:$D$467,'Transaction Overview'!$I$2:$I$467,$A67,'Transaction Overview'!$H$2:$H$467,D$4) -> 0 | E67: =SUMIFS('Transaction Overview'!$D$2:$D$467,'Transaction Overview'!$I$2:$I$467,$A67,'Transaction Overview'!$H$2:$H$467,E$4) -> 0 | F67: =SUMIFS('Transaction Overview'!$D$2:$D$467,'Transaction Overview'!$I$2:$I$467,$A67,'Transaction Overview'!$H$2:$H$467,F$4) -> 0 | G67: =SUMIFS('Transaction Overview'!$D$2:$D$467,'Transaction Overview'!$I$2:$I$467,$A67,'Transaction Overview'!$H$2:$H$467,G$4) -> 0 | H67: =SUM(B67:G67) -> -370
A68: Subtotal — P2P Payments (Zelle/Venmo/PayPal) | B68: =SUM(B63:B67) -> -1395 | C68: =SUM(C63:C67) -> -100 | D68: =SUM(D63:D67) -> 0 | E68: =SUM(E63:E67) -> 0 | F68: =SUM(F63:F67) -> 0 | G68: =SUM(G63:G67) -> -2500 | H68: =SUM(H63:H67) -> -3995
A70: Payroll & Contractors
A71: DWG HR | B71: =SUMIFS('Transaction Overview'!$D$2:$D$467,'Transaction Overview'!$I$2:$I$467,$A71,'Transaction Overview'!$H$2:$H$467,B$4) -> 0 | C71: =SUMIFS('Transaction Overview'!$D$2:$D$467,'Transaction Overview'!$I$2:$I$467,$A71,'Transaction Overview'!$H$2:$H$467,C$4) -> -560.31 | D71: =SUMIFS('Transaction Overview'!$D$2:$D$467,'Transaction Overview'!$I$2:$I$467,$A71,'Transaction Overview'!$H$2:$H$467,D$4) -> -811.14 | E71: =SUMIFS('Transaction Overview'!$D$2:$D$467,'Transaction Overview'!$I$2:$I$467,$A71,'Transaction Overview'!$H$2:$H$467,E$4) -> 0 | F71: =SUMIFS('Transaction Overview'!$D$2:$D$467,'Transaction Overview'!$I$2:$I$467,$A71,'Transaction Overview'!$H$2:$H$467,F$4) -> 0 | G71: =SUMIFS('Transaction Overview'!$D$2:$D$467,'Transaction Overview'!$I$2:$I$467,$A71,'Transaction Overview'!$H$2:$H$467,G$4) -> 0 | H71: =SUM(B71:G71) -> -1371.45
A72: Office/Miscellaneous Reimbursement - Mike P. | B72: =SUMIFS('Transaction Overview'!$D$2:$D$467,'Transaction Overview'!$I$2:$I$467,$A72,'Transaction Overview'!$H$2:$H$467,B$4) -> -1120 | C72: =SUMIFS('Transaction Overview'!$D$2:$D$467,'Transaction Overview'!$I$2:$I$467,$A72,'Transaction Overview'!$H$2:$H$467,C$4) -> -95 | D72: =SUMIFS('Transaction Overview'!$D$2:$D$467,'Transaction Overview'!$I$2:$I$467,$A72,'Transaction Overview'!$H$2:$H$467,D$4) -> -162 | E72: =SUMIFS('Transaction Overview'!$D$2:$D$467,'Transaction Overview'!$I$2:$I$467,$A72,'Transaction Overview'!$H$2:$H$467,E$4) -> -5095 | F72: =SUMIFS('Transaction Overview'!$D$2:$D$467,'Transaction Overview'!$I$2:$I$467,$A72,'Transaction Overview'!$H$2:$H$467,F$4) -> -165 | G72: =SUMIFS('Transaction Overview'!$D$2:$D$467,'Transaction Overview'!$I$2:$I$467,$A72,'Transaction Overview'!$H$2:$H$467,G$4) -> 0 | H72: =SUM(B72:G72) -> -6637
A73: Subtotal — Payroll & Contractors | B73: =SUM(B71:B72) -> -1120 | C73: =SUM(C71:C72) -> -655.31 | D73: =SUM(D71:D72) -> -973.14 | E73: =SUM(E71:E72) -> -5095 | F73: =SUM(F71:F72) -> -165 | G73: =SUM(G71:G72) -> 0 | H73: =SUM(H71:H72) -> -8008.45
A75: Credit Card & Loan Payments
A76: American Express Credit Card PMT | B76: =SUMIFS('Transaction Overview'!$D$2:$D$467,'Transaction Overview'!$I$2:$I$467,$A76,'Transaction Overview'!$H$2:$H$467,B$4) -> -14306.25 | C76: =SUMIFS('Transaction Overview'!$D$2:$D$467,'Transaction Overview'!$I$2:$I$467,$A76,'Transaction Overview'!$H$2:$H$467,C$4) -> -59026.56 | D76: =SUMIFS('Transaction Overview'!$D$2:$D$467,'Transaction Overview'!$I$2:$I$467,$A76,'Transaction Overview'!$H$2:$H$467,D$4) -> -17955 | E76: =SUMIFS('Transaction Overview'!$D$2:$D$467,'Transaction Overview'!$I$2:$I$467,$A76,'Transaction Overview'!$H$2:$H$467,E$4) -> -17136.43 | F76: =SUMIFS('Transaction Overview'!$D$2:$D$467,'Transaction Overview'!$I$2:$I$467,$A76,'Transaction Overview'!$H$2:$H$467,F$4) -> -73395.28 | G76: =SUMIFS('Transaction Overview'!$D$2:$D$467,'Transaction Overview'!$I$2:$I$467,$A76,'Transaction Overview'!$H$2:$H$467,G$4) -> -15944.4 | H76: =SUM(B76:G76) -> -197763.92
A77: Subtotal — Credit Card & Loan Payments | B77: =SUM(B76:B76) -> -14306.25 | C77: =SUM(C76:C76) -> -59026.56 | D77: =SUM(D76:D76) -> -17955 | E77: =SUM(E76:E76) -> -17136.43 | F77: =SUM(F76:F76) -> -73395.28 | G77: =SUM(G76:G76) -> -15944.4 | H77: =SUM(H76:H76) -> -197763.92
A79: Personal — Owner
A80: ATM/Cash | B80: =SUMIFS('Transaction Overview'!$D$2:$D$467,'Transaction Overview'!$I$2:$I$467,$A80,'Transaction Overview'!$H$2:$H$467,B$4) -> -723.98 | C80: =SUMIFS('Transaction Overview'!$D$2:$D$467,'Transaction Overview'!$I$2:$I$467,$A80,'Transaction Overview'!$H$2:$H$467,C$4) -> -1000 | D80: =SUMIFS('Transaction Overview'!$D$2:$D$467,'Transaction Overview'!$I$2:$I$467,$A80,'Transaction Overview'!$H$2:$H$467,D$4) -> -12000 | E80: =SUMIFS('Transaction Overview'!$D$2:$D$467,'Transaction Overview'!$I$2:$I$467,$A80,'Transaction Overview'!$H$2:$H$467,E$4) -> 0 | F80: =SUMIFS('Transaction Overview'!$D$2:$D$467,'Transaction Overview'!$I$2:$I$467,$A80,'Transaction Overview'!$H$2:$H$467,F$4) -> 0 | G80: =SUMIFS('Transaction Overview'!$D$2:$D$467,'Transaction Overview'!$I$2:$I$467,$A80,'Transaction Overview'!$H$2:$H$467,G$4) -> 0 | H80: =SUM(B80:G80) -> -13723.98
A81: Amazon | B81: =SUMIFS('Transaction Overview'!$D$2:$D$467,'Transaction Overview'!$I$2:$I$467,$A81,'Transaction Overview'!$H$2:$H$467,B$4) -> -663.72 | C81: =SUMIFS('Transaction Overview'!$D$2:$D$467,'Transaction Overview'!$I$2:$I$467,$A81,'Transaction Overview'!$H$2:$H$467,C$4) -> -810.03 | D81: =SUMIFS('Transaction Overview'!$D$2:$D$467,'Transaction Overview'!$I$2:$I$467,$A81,'Transaction Overview'!$H$2:$H$467,D$4) -> -1094.44 | E81: =SUMIFS('Transaction Overview'!$D$2:$D$467,'Transaction Overview'!$I$2:$I$467,$A81,'Transaction Overview'!$H$2:$H$467,E$4) -> -887.53 | F81: =SUMIFS('Transaction Overview'!$D$2:$D$467,'Transaction Overview'!$I$2:$I$467,$A81,'Transaction Overview'!$H$2:$H$467,F$4) -> -526.21 | G81: =SUMIFS('Transaction Overview'!$D$2:$D$467,'Transaction Overview'!$I$2:$I$467,$A81,'Transaction Overview'!$H$2:$H$467,G$4) -> 0 | H81: =SUM(B81:G81) -> -3981.93
A82: Personal - Car & Auto | B82: =SUMIFS('Transaction Overview'!$D$2:$D$467,'Transaction Overview'!$I$2:$I$467,$A82,'Transaction Overview'!$H$2:$H$467,B$4) -> -15.74 | C82: =SUMIFS('Transaction Overview'!$D$2:$D$467,'Transaction Overview'!$I$2:$I$467,$A82,'Transaction Overview'!$H$2:$H$467,C$4) -> 0 | D82: =SUMIFS('Transaction Overview'!$D$2:$D$467,'Transaction Overview'!$I$2:$I$467,$A82,'Transaction Overview'!$H$2:$H$467,D$4) -> -363.47 | E82: =SUMIFS('Transaction Overview'!$D$2:$D$467,'Transaction Overview'!$I$2:$I$467,$A82,'Transaction Overview'!$H$2:$H$467,E$4) -> -381.79 | F82: =SUMIFS('Transaction Overview'!$D$2:$D$467,'Transaction Overview'!$I$2:$I$467,$A82,'Transaction Overview'!$H$2:$H$467,F$4) -> -429.94 | G82: =SUMIFS('Transaction Overview'!$D$2:$D$467,'Transaction Overview'!$I$2:$I$467,$A82,'Transaction Overview'!$H$2:$H$467,G$4) -> -439.96 | H82: =SUM(B82:G82) -> -1630.9
A83: Personal - Entertainment | B83: =SUMIFS('Transaction Overview'!$D$2:$D$467,'Transaction Overview'!$I$2:$I$467,$A83,'Transaction Overview'!$H$2:$H$467,B$4) -> 0 | C83: =SUMIFS('Transaction Overview'!$D$2:$D$467,'Transaction Overview'!$I$2:$I$467,$A83,'Transaction Overview'!$H$2:$H$467,C$4) -> 0 | D83: =SUMIFS('Transaction Overview'!$D$2:$D$467,'Transaction Overview'!$I$2:$I$467,$A83,'Transaction Overview'!$H$2:$H$467,D$4) -> 0 | E83: =SUMIFS('Transaction Overview'!$D$2:$D$467,'Transaction Overview'!$I$2:$I$467,$A83,'Transaction Overview'!$H$2:$H$467,E$4) -> 0 | F83: =SUMIFS('Transaction Overview'!$D$2:$D$467,'Transaction Overview'!$I$2:$I$467,$A83,'Transaction Overview'!$H$2:$H$467,F$4) -> 0 | G83: =SUMIFS('Transaction Overview'!$D$2:$D$467,'Transaction Overview'!$I$2:$I$467,$A83,'Transaction Overview'!$H$2:$H$467,G$4) -> -32.31 | H83: =SUM(B83:G83) -> -32.31
A84: Personal - Food & Dining | B84: =SUMIFS('Transaction Overview'!$D$2:$D$467,'Transaction Overview'!$I$2:$I$467,$A84,'Transaction Overview'!$H$2:$H$467,B$4) -> -91.22 | C84: =SUMIFS('Transaction Overview'!$D$2:$D$467,'Transaction Overview'!$I$2:$I$467,$A84,'Transaction Overview'!$H$2:$H$467,C$4) -> -181.86 | D84: =SUMIFS('Transaction Overview'!$D$2:$D$467,'Transaction Overview'!$I$2:$I$467,$A84,'Transaction Overview'!$H$2:$H$467,D$4) -> 0 | E84: =SUMIFS('Transaction Overview'!$D$2:$D$467,'Transaction Overview'!$I$2:$I$467,$A84,'Transaction Overview'!$H$2:$H$467,E$4) -> -217.96 | F84: =SUMIFS('Transaction Overview'!$D$2:$D$467,'Transaction Overview'!$I$2:$I$467,$A84,'Transaction Overview'!$H$2:$H$467,F$4) -> -752.88 | G84: =SUMIFS('Transaction Overview'!$D$2:$D$467,'Transaction Overview'!$I$2:$I$467,$A84,'Transaction Overview'!$H$2:$H$467,G$4) -> -113.84 | H84: =SUM(B84:G84) -> -1357.76
A85: Personal - Health (incl. Ins.) | B85: =SUMIFS('Transaction Overview'!$D$2:$D$467,'Transaction Overview'!$I$2:$I$467,$A85,'Transaction Overview'!$H$2:$H$467,B$4) -> 0 | C85: =SUMIFS('Transaction Overview'!$D$2:$D$467,'Transaction Overview'!$I$2:$I$467,$A85,'Transaction Overview'!$H$2:$H$467,C$4) -> 0 | D85: =SUMIFS('Transaction Overview'!$D$2:$D$467,'Transaction Overview'!$I$2:$I$467,$A85,'Transaction Overview'!$H$2:$H$467,D$4) -> -1050 | E85: =SUMIFS('Transaction Overview'!$D$2:$D$467,'Transaction Overview'!$I$2:$I$467,$A85,'Transaction Overview'!$H$2:$H$467,E$4) -> 0 | F85: =SUMIFS('Transaction Overview'!$D$2:$D$467,'Transaction Overview'!$I$2:$I$467,$A85,'Transaction Overview'!$H$2:$H$467,F$4) -> 0 | G85: =SUMIFS('Transaction Overview'!$D$2:$D$467,'Transaction Overview'!$I$2:$I$467,$A85,'Transaction Overview'!$H$2:$H$467,G$4) -> 0 | H85: =SUM(B85:G85) -> -1050
A86: Personal - House | B86: =SUMIFS('Transaction Overview'!$D$2:$D$467,'Transaction Overview'!$I$2:$I$467,$A86,'Transaction Overview'!$H$2:$H$467,B$4) -> 0 | C86: =SUMIFS('Transaction Overview'!$D$2:$D$467,'Transaction Overview'!$I$2:$I$467,$A86,'Transaction Overview'!$H$2:$H$467,C$4) -> -16287.51 | D86: =SUMIFS('Transaction Overview'!$D$2:$D$467,'Transaction Overview'!$I$2:$I$467,$A86,'Transaction Overview'!$H$2:$H$467,D$4) -> 0 | E86: =SUMIFS('Transaction Overview'!$D$2:$D$467,'Transaction Overview'!$I$2:$I$467,$A86,'Transaction Overview'!$H$2:$H$467,E$4) -> 0 | F86: =SUMIFS('Transaction Overview'!$D$2:$D$467,'Transaction Overview'!$I$2:$I$467,$A86,'Transaction Overview'!$H$2:$H$467,F$4) -> 0 | G86: =SUMIFS('Transaction Overview'!$D$2:$D$467,'Transaction Overview'!$I$2:$I$467,$A86,'Transaction Overview'!$H$2:$H$467,G$4) -> 0 | H86: =SUM(B86:G86) -> -16287.51
A87: Personal - Subscriptions | B87: =SUMIFS('Transaction Overview'!$D$2:$D$467,'Transaction Overview'!$I$2:$I$467,$A87,'Transaction Overview'!$H$2:$H$467,B$4) -> -488.64 | C87: =SUMIFS('Transaction Overview'!$D$2:$D$467,'Transaction Overview'!$I$2:$I$467,$A87,'Transaction Overview'!$H$2:$H$467,C$4) -> -339.69 | D87: =SUMIFS('Transaction Overview'!$D$2:$D$467,'Transaction Overview'!$I$2:$I$467,$A87,'Transaction Overview'!$H$2:$H$467,D$4) -> -414.57 | E87: =SUMIFS('Transaction Overview'!$D$2:$D$467,'Transaction Overview'!$I$2:$I$467,$A87,'Transaction Overview'!$H$2:$H$467,E$4) -> -330.67 | F87: =SUMIFS('Transaction Overview'!$D$2:$D$467,'Transaction Overview'!$I$2:$I$467,$A87,'Transaction Overview'!$H$2:$H$467,F$4) -> -352.57 | G87: =SUMIFS('Transaction Overview'!$D$2:$D$467,'Transaction Overview'!$I$2:$I$467,$A87,'Transaction Overview'!$H$2:$H$467,G$4) -> -250.3 | H87: =SUM(B87:G87) -> -2176.44
A88: Personal - Travel | B88: =SUMIFS('Transaction Overview'!$D$2:$D$467,'Transaction Overview'!$I$2:$I$467,$A88,'Transaction Overview'!$H$2:$H$467,B$4) -> -55.7 | C88: =SUMIFS('Transaction Overview'!$D$2:$D$467,'Transaction Overview'!$I$2:$I$467,$A88,'Transaction Overview'!$H$2:$H$467,C$4) -> -124 | D88: =SUMIFS('Transaction Overview'!$D$2:$D$467,'Transaction Overview'!$I$2:$I$467,$A88,'Transaction Overview'!$H$2:$H$467,D$4) -> 0 | E88: =SUMIFS('Transaction Overview'!$D$2:$D$467,'Transaction Overview'!$I$2:$I$467,$A88,'Transaction Overview'!$H$2:$H$467,E$4) -> 0 | F88: =SUMIFS('Transaction Overview'!$D$2:$D$467,'Transaction Overview'!$I$2:$I$467,$A88,'Transaction Overview'!$H$2:$H$467,F$4) -> 0 | G88: =SUMIFS('Transaction Overview'!$D$2:$D$467,'Transaction Overview'!$I$2:$I$467,$A88,'Transaction Overview'!$H$2:$H$467,G$4) -> 0 | H88: =SUM(B88:G88) -> -179.7
A89: Personal - Travel (Portugal) | B89: =SUMIFS('Transaction Overview'!$D$2:$D$467,'Transaction Overview'!$I$2:$I$467,$A89,'Transaction Overview'!$H$2:$H$467,B$4) -> 0 | C89: =SUMIFS('Transaction Overview'!$D$2:$D$467,'Transaction Overview'!$I$2:$I$467,$A89,'Transaction Overview'!$H$2:$H$467,C$4) -> 0 | D89: =SUMIFS('Transaction Overview'!$D$2:$D$467,'Transaction Overview'!$I$2:$I$467,$A89,'Transaction Overview'!$H$2:$H$467,D$4) -> 0 | E89: =SUMIFS('Transaction Overview'!$D$2:$D$467,'Transaction Overview'!$I$2:$I$467,$A89,'Transaction Overview'!$H$2:$H$467,E$4) -> -428.27 | F89: =SUMIFS('Transaction Overview'!$D$2:$D$467,'Transaction Overview'!$I$2:$I$467,$A89,'Transaction Overview'!$H$2:$H$467,F$4) -> 0 | G89: =SUMIFS('Transaction Overview'!$D$2:$D$467,'Transaction Overview'!$I$2:$I$467,$A89,'Transaction Overview'!$H$2:$H$467,G$4) -> 0 | H89: =SUM(B89:G89) -> -428.27
A90: Subtotal — Personal — Owner | B90: =SUM(B80:B89) -> -2039 | C90: =SUM(C80:C89) -> -18743.09 | D90: =SUM(D80:D89) -> -14922.48 | E90: =SUM(E80:E89) -> -2246.22 | F90: =SUM(F80:F89) -> -2061.6 | G90: =SUM(G80:G89) -> -836.41 | H90: =SUM(H80:H89) -> -40848.8
A92: DWG Operating
A93: ACH payment to CALCPA group | B93: =SUMIFS('Transaction Overview'!$D$2:$D$467,'Transaction Overview'!$I$2:$I$467,$A93,'Transaction Overview'!$H$2:$H$467,B$4) -> -501.25 | C93: =SUMIFS('Transaction Overview'!$D$2:$D$467,'Transaction Overview'!$I$2:$I$467,$A93,'Transaction Overview'!$H$2:$H$467,C$4) -> 0 | D93: =SUMIFS('Transaction Overview'!$D$2:$D$467,'Transaction Overview'!$I$2:$I$467,$A93,'Transaction Overview'!$H$2:$H$467,D$4) -> 0 | E93: =SUMIFS('Transaction Overview'!$D$2:$D$467,'Transaction Overview'!$I$2:$I$467,$A93,'Transaction Overview'!$H$2:$H$467,E$4) -> 0 | F93: =SUMIFS('Transaction Overview'!$D$2:$D$467,'Transaction Overview'!$I$2:$I$467,$A93,'Transaction Overview'!$H$2:$H$467,F$4) -> 0 | G93: =SUMIFS('Transaction Overview'!$D$2:$D$467,'Transaction Overview'!$I$2:$I$467,$A93,'Transaction Overview'!$H$2:$H$467,G$4) -> 0 | H93: =SUM(B93:G93) -> -501.25
A94: Bank Fees | B94: =SUMIFS('Transaction Overview'!$D$2:$D$467,'Transaction Overview'!$I$2:$I$467,$A94,'Transaction Overview'!$H$2:$H$467,B$4) -> -6 | C94: =SUMIFS('Transaction Overview'!$D$2:$D$467,'Transaction Overview'!$I$2:$I$467,$A94,'Transaction Overview'!$H$2:$H$467,C$4) -> 0 | D94: =SUMIFS('Transaction Overview'!$D$2:$D$467,'Transaction Overview'!$I$2:$I$467,$A94,'Transaction Overview'!$H$2:$H$467,D$4) -> 0 | E94: =SUMIFS('Transaction Overview'!$D$2:$D$467,'Transaction Overview'!$I$2:$I$467,$A94,'Transaction Overview'!$H$2:$H$467,E$4) -> 0 | F94: =SUMIFS('Transaction Overview'!$D$2:$D$467,'Transaction Overview'!$I$2:$I$467,$A94,'Transaction Overview'!$H$2:$H$467,F$4) -> 0 | G94: =SUMIFS('Transaction Overview'!$D$2:$D$467,'Transaction Overview'!$I$2:$I$467,$A94,'Transaction Overview'!$H$2:$H$467,G$4) -> 0 | H94: =SUM(B94:G94) -> -6
A95: Facebook | B95: =SUMIFS('Transaction Overview'!$D$2:$D$467,'Transaction Overview'!$I$2:$I$467,$A95,'Transaction Overview'!$H$2:$H$467,B$4) -> 0 | C95: =SUMIFS('Transaction Overview'!$D$2:$D$467,'Transaction Overview'!$I$2:$I$467,$A95,'Transaction Overview'!$H$2:$H$467,C$4) -> 0 | D95: =SUMIFS('Transaction Overview'!$D$2:$D$467,'Transaction Overview'!$I$2:$I$467,$A95,'Transaction Overview'!$H$2:$H$467,D$4) -> 0 | E95: =SUMIFS('Transaction Overview'!$D$2:$D$467,'Transaction Overview'!$I$2:$I$467,$A95,'Transaction Overview'!$H$2:$H$467,E$4) -> 0 | F95: =SUMIFS('Transaction Overview'!$D$2:$D$467,'Transaction Overview'!$I$2:$I$467,$A95,'Transaction Overview'!$H$2:$H$467,F$4) -> -14.69 | G95: =SUMIFS('Transaction Overview'!$D$2:$D$467,'Transaction Overview'!$I$2:$I$467,$A95,'Transaction Overview'!$H$2:$H$467,G$4) -> 0 | H95: =SUM(B95:G95) -> -14.69
A96: LLC Filing | B96: =SUMIFS('Transaction Overview'!$D$2:$D$467,'Transaction Overview'!$I$2:$I$467,$A96,'Transaction Overview'!$H$2:$H$467,B$4) -> 0 | C96: =SUMIFS('Transaction Overview'!$D$2:$D$467,'Transaction Overview'!$I$2:$I$467,$A96,'Transaction Overview'!$H$2:$H$467,C$4) -> 0 | D96: =SUMIFS('Transaction Overview'!$D$2:$D$467,'Transaction Overview'!$I$2:$I$467,$A96,'Transaction Overview'!$H$2:$H$467,D$4) -> 0 | E96: =SUMIFS('Transaction Overview'!$D$2:$D$467,'Transaction Overview'!$I$2:$I$467,$A96,'Transaction Overview'!$H$2:$H$467,E$4) -> 0 | F96: =SUMIFS('Transaction Overview'!$D$2:$D$467,'Transaction Overview'!$I$2:$I$467,$A96,'Transaction Overview'!$H$2:$H$467,F$4) -> -70 | G96: =SUMIFS('Transaction Overview'!$D$2:$D$467,'Transaction Overview'!$I$2:$I$467,$A96,'Transaction Overview'!$H$2:$H$467,G$4) -> 0 | H96: =SUM(B96:G96) -> -70
A97: Wire Fee | B97: =SUMIFS('Transaction Overview'!$D$2:$D$467,'Transaction Overview'!$I$2:$I$467,$A97,'Transaction Overview'!$H$2:$H$467,B$4) -> -65 | C97: =SUMIFS('Transaction Overview'!$D$2:$D$467,'Transaction Overview'!$I$2:$I$467,$A97,'Transaction Overview'!$H$2:$H$467,C$4) -> -90 | D97: =SUMIFS('Transaction Overview'!$D$2:$D$467,'Transaction Overview'!$I$2:$I$467,$A97,'Transaction Overview'!$H$2:$H$467,D$4) -> 0 | E97: =SUMIFS('Transaction Overview'!$D$2:$D$467,'Transaction Overview'!$I$2:$I$467,$A97,'Transaction Overview'!$H$2:$H$467,E$4) -> -95 | F97: =SUMIFS('Transaction Overview'!$D$2:$D$467,'Transaction Overview'!$I$2:$I$467,$A97,'Transaction Overview'!$H$2:$H$467,F$4) -> 0 | G97: =SUMIFS('Transaction Overview'!$D$2:$D$467,'Transaction Overview'!$I$2:$I$467,$A97,'Transaction Overview'!$H$2:$H$467,G$4) -> 0 | H97: =SUM(B97:G97) -> -250
A98: Subtotal — DWG Operating | B98: =SUM(B93:B97) -> -572.25 | C98: =SUM(C93:C97) -> -90 | D98: =SUM(D93:D97) -> 0 | E98: =SUM(E93:E97) -> -95 | F98: =SUM(F93:F97) -> -84.69 | G98: =SUM(G93:G97) -> 0 | H98: =SUM(H93:H97) -> -841.94
A100: Uncategorized — Review
A101: TBD | B101: =SUMIFS('Transaction Overview'!$D$2:$D$467,'Transaction Overview'!$I$2:$I$467,$A101,'Transaction Overview'!$H$2:$H$467,B$4) -> 0 | C101: =SUMIFS('Transaction Overview'!$D$2:$D$467,'Transaction Overview'!$I$2:$I$467,$A101,'Transaction Overview'!$H$2:$H$467,C$4) -> 0 | D101: =SUMIFS('Transaction Overview'!$D$2:$D$467,'Transaction Overview'!$I$2:$I$467,$A101,'Transaction Overview'!$H$2:$H$467,D$4) -> 0 | E101: =SUMIFS('Transaction Overview'!$D$2:$D$467,'Transaction Overview'!$I$2:$I$467,$A101,'Transaction Overview'!$H$2:$H$467,E$4) -> 0 | F101: =SUMIFS('Transaction Overview'!$D$2:$D$467,'Transaction Overview'!$I$2:$I$467,$A101,'Transaction Overview'!$H$2:$H$467,F$4) -> 0 | G101: =SUMIFS('Transaction Overview'!$D$2:$D$467,'Transaction Overview'!$I$2:$I$467,$A101,'Transaction Overview'!$H$2:$H$467,G$4) -> 0 | H101: =SUM(B101:G101) -> 0
A102: Subtotal — Uncategorized — Review | B102: =SUM(B101:B101) -> 0 | C102: =SUM(C101:C101) -> 0 | D102: =SUM(D101:D101) -> 0 | E102: =SUM(E101:E101) -> 0 | F102: =SUM(F101:F101) -> 0 | G102: =SUM(G101:G101) -> 0 | H102: =SUM(H101:H101) -> 0

Sheet Monthly Detail
A1: Chase 9335 — 2026 Activity
A2: Monthly Detail — Spend by Individual Category | Jan 2026 – Jun 2026
A4: Category | B4: Group | C4: =DATE(2026,1,1) -> 46023 | D4: =DATE(2026,2,1) -> 46054 | E4: =DATE(2026,3,1) -> 46082 | F4: =DATE(2026,4,1) -> 46113 | G4: =DATE(2026,5,1) -> 46143 | H4: =DATE(2026,6,1) -> 46174 | I4: Total
A5: Bridge Coverage (JC Whitner) | B5: Deal-Specific | C5: =SUMIFS('Transaction Overview'!$D$2:$D$467,'Transaction Overview'!$G$2:$G$467,$A5,'Transaction Overview'!$H$2:$H$467,C$4) -> -10000 | D5: =SUMIFS('Transaction Overview'!$D$2:$D$467,'Transaction Overview'!$G$2:$G$467,$A5,'Transaction Overview'!$H$2:$H$467,D$4) -> 0 | E5: =SUMIFS('Transaction Overview'!$D$2:$D$467,'Transaction Overview'!$G$2:$G$467,$A5,'Transaction Overview'!$H$2:$H$467,E$4) -> 0 | F5: =SUMIFS('Transaction Overview'!$D$2:$D$467,'Transaction Overview'!$G$2:$G$467,$A5,'Transaction Overview'!$H$2:$H$467,F$4) -> 0 | G5: =SUMIFS('Transaction Overview'!$D$2:$D$467,'Transaction Overview'!$G$2:$G$467,$A5,'Transaction Overview'!$H$2:$H$467,G$4) -> 0 | H5: =SUMIFS('Transaction Overview'!$D$2:$D$467,'Transaction Overview'!$G$2:$G$467,$A5,'Transaction Overview'!$H$2:$H$467,H$4) -> 0 | I5: =SUM(C5:H5) -> -10000
A6: Deal Specific: Austin Iron | B6: Deal-Specific | C6: =SUMIFS('Transaction Overview'!$D$2:$D$467,'Transaction Overview'!$G$2:$G$467,$A6,'Transaction Overview'!$H$2:$H$467,C$4) -> 350 | D6: =SUMIFS('Transaction Overview'!$D$2:$D$467,'Transaction Overview'!$G$2:$G$467,$A6,'Transaction Overview'!$H$2:$H$467,D$4) -> 350 | E6: =SUMIFS('Transaction Overview'!$D$2:$D$467,'Transaction Overview'!$G$2:$G$467,$A6,'Transaction Overview'!$H$2:$H$467,E$4) -> 350 | F6: =SUMIFS('Transaction Overview'!$D$2:$D$467,'Transaction Overview'!$G$2:$G$467,$A6,'Transaction Overview'!$H$2:$H$467,F$4) -> 350 | G6: =SUMIFS('Transaction Overview'!$D$2:$D$467,'Transaction Overview'!$G$2:$G$467,$A6,'Transaction Overview'!$H$2:$H$467,G$4) -> 350 | H6: =SUMIFS('Transaction Overview'!$D$2:$D$467,'Transaction Overview'!$G$2:$G$467,$A6,'Transaction Overview'!$H$2:$H$467,H$4) -> 350 | I6: =SUM(C6:H6) -> 2100
A7: Deal Specific: MRM | B7: Deal-Specific | C7: =SUMIFS('Transaction Overview'!$D$2:$D$467,'Transaction Overview'!$G$2:$G$467,$A7,'Transaction Overview'!$H$2:$H$467,C$4) -> 241.87 | D7: =SUMIFS('Transaction Overview'!$D$2:$D$467,'Transaction Overview'!$G$2:$G$467,$A7,'Transaction Overview'!$H$2:$H$467,D$4) -> 241.87 | E7: =SUMIFS('Transaction Overview'!$D$2:$D$467,'Transaction Overview'!$G$2:$G$467,$A7,'Transaction Overview'!$H$2:$H$467,E$4) -> 241.87 | F7: =SUMIFS('Transaction Overview'!$D$2:$D$467,'Transaction Overview'!$G$2:$G$467,$A7,'Transaction Overview'!$H$2:$H$467,F$4) -> 0 | G7: =SUMIFS('Transaction Overview'!$D$2:$D$467,'Transaction Overview'!$G$2:$G$467,$A7,'Transaction Overview'!$H$2:$H$467,G$4) -> 0 | H7: =SUMIFS('Transaction Overview'!$D$2:$D$467,'Transaction Overview'!$G$2:$G$467,$A7,'Transaction Overview'!$H$2:$H$467,H$4) -> 0 | I7: =SUM(C7:H7) -> 725.61
A8: Deal Specific: Merit-Lancaster | B8: Deal-Specific | C8: =SUMIFS('Transaction Overview'!$D$2:$D$467,'Transaction Overview'!$G$2:$G$467,$A8,'Transaction Overview'!$H$2:$H$467,C$4) -> 476.41 | D8: =SUMIFS('Transaction Overview'!$D$2:$D$467,'Transaction Overview'!$G$2:$G$467,$A8,'Transaction Overview'!$H$2:$H$467,D$4) -> 476.41 | E8: =SUMIFS('Transaction Overview'!$D$2:$D$467,'Transaction Overview'!$G$2:$G$467,$A8,'Transaction Overview'!$H$2:$H$467,E$4) -> 491.29 | F8: =SUMIFS('Transaction Overview'!$D$2:$D$467,'Transaction Overview'!$G$2:$G$467,$A8,'Transaction Overview'!$H$2:$H$467,F$4) -> 491.29 | G8: =SUMIFS('Transaction Overview'!$D$2:$D$467,'Transaction Overview'!$G$2:$G$467,$A8,'Transaction Overview'!$H$2:$H$467,G$4) -> 491.29 | H8: =SUMIFS('Transaction Overview'!$D$2:$D$467,'Transaction Overview'!$G$2:$G$467,$A8,'Transaction Overview'!$H$2:$H$467,H$4) -> 491.29 | I8: =SUM(C8:H8) -> 2917.98
A9: Deal Specific: Rabourn Road | B9: Deal-Specific | C9: =SUMIFS('Transaction Overview'!$D$2:$D$467,'Transaction Overview'!$G$2:$G$467,$A9,'Transaction Overview'!$H$2:$H$467,C$4) -> 233.33 | D9: =SUMIFS('Transaction Overview'!$D$2:$D$467,'Transaction Overview'!$G$2:$G$467,$A9,'Transaction Overview'!$H$2:$H$467,D$4) -> 233.33 | E9: =SUMIFS('Transaction Overview'!$D$2:$D$467,'Transaction Overview'!$G$2:$G$467,$A9,'Transaction Overview'!$H$2:$H$467,E$4) -> 233.33 | F9: =SUMIFS('Transaction Overview'!$D$2:$D$467,'Transaction Overview'!$G$2:$G$467,$A9,'Transaction Overview'!$H$2:$H$467,F$4) -> 233.33 | G9: =SUMIFS('Transaction Overview'!$D$2:$D$467,'Transaction Overview'!$G$2:$G$467,$A9,'Transaction Overview'!$H$2:$H$467,G$4) -> 233.33 | H9: =SUMIFS('Transaction Overview'!$D$2:$D$467,'Transaction Overview'!$G$2:$G$467,$A9,'Transaction Overview'!$H$2:$H$467,H$4) -> 233.33 | I9: =SUM(C9:H9) -> 1399.98
A10: Deal Specific: T&T Machine | B10: Deal-Specific | C10: =SUMIFS('Transaction Overview'!$D$2:$D$467,'Transaction Overview'!$G$2:$G$467,$A10,'Transaction Overview'!$H$2:$H$467,C$4) -> 356.38 | D10: =SUMIFS('Transaction Overview'!$D$2:$D$467,'Transaction Overview'!$G$2:$G$467,$A10,'Transaction Overview'!$H$2:$H$467,D$4) -> 367.52 | E10: =SUMIFS('Transaction Overview'!$D$2:$D$467,'Transaction Overview'!$G$2:$G$467,$A10,'Transaction Overview'!$H$2:$H$467,E$4) -> 367.52 | F10: =SUMIFS('Transaction Overview'!$D$2:$D$467,'Transaction Overview'!$G$2:$G$467,$A10,'Transaction Overview'!$H$2:$H$467,F$4) -> 0 | G10: =SUMIFS('Transaction Overview'!$D$2:$D$467,'Transaction Overview'!$G$2:$G$467,$A10,'Transaction Overview'!$H$2:$H$467,G$4) -> 0 | H10: =SUMIFS('Transaction Overview'!$D$2:$D$467,'Transaction Overview'!$G$2:$G$467,$A10,'Transaction Overview'!$H$2:$H$467,H$4) -> 0 | I10: =SUM(C10:H10) -> 1091.42
A11: Incoming Commission: Rembrandt | B11: Commissions — Incoming | C11: =SUMIFS('Transaction Overview'!$D$2:$D$467,'Transaction Overview'!$G$2:$G$467,$A11,'Transaction Overview'!$H$2:$H$467,C$4) -> 0 | D11: =SUMIFS('Transaction Overview'!$D$2:$D$467,'Transaction Overview'!$G$2:$G$467,$A11,'Transaction Overview'!$H$2:$H$467,D$4) -> 168266 | E11: =SUMIFS('Transaction Overview'!$D$2:$D$467,'Transaction Overview'!$G$2:$G$467,$A11,'Transaction Overview'!$H$2:$H$467,E$4) -> 0 | F11: =SUMIFS('Transaction Overview'!$D$2:$D$467,'Transaction Overview'!$G$2:$G$467,$A11,'Transaction Overview'!$H$2:$H$467,F$4) -> 0 | G11: =SUMIFS('Transaction Overview'!$D$2:$D$467,'Transaction Overview'!$G$2:$G$467,$A11,'Transaction Overview'!$H$2:$H$467,G$4) -> 0 | H11: =SUMIFS('Transaction Overview'!$D$2:$D$467,'Transaction Overview'!$G$2:$G$467,$A11,'Transaction Overview'!$H$2:$H$467,H$4) -> 0 | I11: =SUM(C11:H11) -> 168266
A12: Incoming Commission: SPF | B12: Commissions — Incoming | C12: =SUMIFS('Transaction Overview'!$D$2:$D$467,'Transaction Overview'!$G$2:$G$467,$A12,'Transaction Overview'!$H$2:$H$467,C$4) -> 0 | D12: =SUMIFS('Transaction Overview'!$D$2:$D$467,'Transaction Overview'!$G$2:$G$467,$A12,'Transaction Overview'!$H$2:$H$467,D$4) -> 0 | E12: =SUMIFS('Transaction Overview'!$D$2:$D$467,'Transaction Overview'!$G$2:$G$467,$A12,'Transaction Overview'!$H$2:$H$467,E$4) -> 0 | F12: =SUMIFS('Transaction Overview'!$D$2:$D$467,'Transaction Overview'!$G$2:$G$467,$A12,'Transaction Overview'!$H$2:$H$467,F$4) -> 266889.44 | G12: =SUMIFS('Transaction Overview'!$D$2:$D$467,'Transaction Overview'!$G$2:$G$467,$A12,'Transaction Overview'!$H$2:$H$467,G$4) -> 0 | H12: =SUMIFS('Transaction Overview'!$D$2:$D$467,'Transaction Overview'!$G$2:$G$467,$A12,'Transaction Overview'!$H$2:$H$467,H$4) -> 0 | I12: =SUM(C12:H12) -> 266889.44
A13: Kevin Wong Commission (SPF) | B13: Commissions — Outgoing | C13: =SUMIFS('Transaction Overview'!$D$2:$D$467,'Transaction Overview'!$G$2:$G$467,$A13,'Transaction Overview'!$H$2:$H$467,C$4) -> 0 | D13: =SUMIFS('Transaction Overview'!$D$2:$D$467,'Transaction Overview'!$G$2:$G$467,$A13,'Transaction Overview'!$H$2:$H$467,D$4) -> 0 | E13: =SUMIFS('Transaction Overview'!$D$2:$D$467,'Transaction Overview'!$G$2:$G$467,$A13,'Transaction Overview'!$H$2:$H$467,E$4) -> 0 | F13: =SUMIFS('Transaction Overview'!$D$2:$D$467,'Transaction Overview'!$G$2:$G$467,$A13,'Transaction Overview'!$H$2:$H$467,F$4) -> -16087.5 | G13: =SUMIFS('Transaction Overview'!$D$2:$D$467,'Transaction Overview'!$G$2:$G$467,$A13,'Transaction Overview'!$H$2:$H$467,G$4) -> 0 | H13: =SUMIFS('Transaction Overview'!$D$2:$D$467,'Transaction Overview'!$G$2:$G$467,$A13,'Transaction Overview'!$H$2:$H$467,H$4) -> 0 | I13: =SUM(C13:H13) -> -16087.5
A14: Kevin Wong Commission (Steve Klar) | B14: Commissions — Outgoing | C14: =SUMIFS('Transaction Overview'!$D$2:$D$467,'Transaction Overview'!$G$2:$G$467,$A14,'Transaction Overview'!$H$2:$H$467,C$4) -> -6000 | D14: =SUMIFS('Transaction Overview'!$D$2:$D$467,'Transaction Overview'!$G$2:$G$467,$A14,'Transaction Overview'!$H$2:$H$467,D$4) -> 0 | E14: =SUMIFS('Transaction Overview'!$D$2:$D$467,'Transaction Overview'!$G$2:$G$467,$A14,'Transaction Overview'!$H$2:$H$467,E$4) -> 0 | F14: =SUMIFS('Transaction Overview'!$D$2:$D$467,'Transaction Overview'!$G$2:$G$467,$A14,'Transaction Overview'!$H$2:$H$467,F$4) -> 0 | G14: =SUMIFS('Transaction Overview'!$D$2:$D$467,'Transaction Overview'!$G$2:$G$467,$A14,'Transaction Overview'!$H$2:$H$467,G$4) -> 0 | H14: =SUMIFS('Transaction Overview'!$D$2:$D$467,'Transaction Overview'!$G$2:$G$467,$A14,'Transaction Overview'!$H$2:$H$467,H$4) -> 0 | I14: =SUM(C14:H14) -> -6000
A15: Meg Maran - MDC Commission | B15: Commissions — Outgoing | C15: =SUMIFS('Transaction Overview'!$D$2:$D$467,'Transaction Overview'!$G$2:$G$467,$A15,'Transaction Overview'!$H$2:$H$467,C$4) -> 0 | D15: =SUMIFS('Transaction Overview'!$D$2:$D$467,'Transaction Overview'!$G$2:$G$467,$A15,'Transaction Overview'!$H$2:$H$467,D$4) -> 0 | E15: =SUMIFS('Transaction Overview'!$D$2:$D$467,'Transaction Overview'!$G$2:$G$467,$A15,'Transaction Overview'!$H$2:$H$467,E$4) -> 0 | F15: =SUMIFS('Transaction Overview'!$D$2:$D$467,'Transaction Overview'!$G$2:$G$467,$A15,'Transaction Overview'!$H$2:$H$467,F$4) -> -1500 | G15: =SUMIFS('Transaction Overview'!$D$2:$D$467,'Transaction Overview'!$G$2:$G$467,$A15,'Transaction Overview'!$H$2:$H$467,G$4) -> 0 | H15: =SUMIFS('Transaction Overview'!$D$2:$D$467,'Transaction Overview'!$G$2:$G$467,$A15,'Transaction Overview'!$H$2:$H$467,H$4) -> 0 | I15: =SUM(C15:H15) -> -1500
A16: MAG - Admeer Advisory Reimbursement | B16: MAG Pass-Through | C16: =SUMIFS('Transaction Overview'!$D$2:$D$467,'Transaction Overview'!$G$2:$G$467,$A16,'Transaction Overview'!$H$2:$H$467,C$4) -> 0 | D16: =SUMIFS('Transaction Overview'!$D$2:$D$467,'Transaction Overview'!$G$2:$G$467,$A16,'Transaction Overview'!$H$2:$H$467,D$4) -> 5000 | E16: =SUMIFS('Transaction Overview'!$D$2:$D$467,'Transaction Overview'!$G$2:$G$467,$A16,'Transaction Overview'!$H$2:$H$467,E$4) -> 0 | F16: =SUMIFS('Transaction Overview'!$D$2:$D$467,'Transaction Overview'!$G$2:$G$467,$A16,'Transaction Overview'!$H$2:$H$467,F$4) -> 0 | G16: =SUMIFS('Transaction Overview'!$D$2:$D$467,'Transaction Overview'!$G$2:$G$467,$A16,'Transaction Overview'!$H$2:$H$467,G$4) -> 0 | H16: =SUMIFS('Transaction Overview'!$D$2:$D$467,'Transaction Overview'!$G$2:$G$467,$A16,'Transaction Overview'!$H$2:$H$467,H$4) -> 0 | I16: =SUM(C16:H16) -> 5000
... A61: TBD | B61: Uncategorized — Review | C61: =SUMIFS('Transaction Overview'!$D$2:$D$467,'Transaction Overview'!$G$2:$G$467,$A61,'Transaction Overview'!$H$2:$H$467,C$4) -> 0 | D61: =SUMIFS('Transaction Overview'!$D$2:$D$467,'Transaction Overview'!$G$2:$G$467,$A61,'Transaction Overview'!$H$2:$H$467,D$4) -> 0 | E61: =SUMIFS('Transaction Overview'!$D$2:$D$467,'Transaction Overview'!$G$2:$G$467,$A61,'Transaction Overview'!$H$2:$H$467,E$4) -> 0 | F61: =SUMIFS('Transaction Overview'!$D$2:$D$467,'Transaction Overview'!$G$2:$G$467,$A61,'Transaction Overview'!$H$2:$H$467,F$4) -> 0 | G61: =SUMIFS('Transaction Overview'!$D$2:$D$467,'Transaction Overview'!$G$2:$G$467,$A61,'Transaction Overview'!$H$2:$H$467,G$4) -> 0 | H61: =SUMIFS('Transaction Overview'!$D$2:$D$467,'Transaction Overview'!$G$2:$G$467,$A61,'Transaction Overview'!$H$2:$H$467,H$4) -> 0 | I61: =SUM(C61:H61) -> 0

Sheet Transfer In
A1: Chase 9335 — 2026 Activity — Transfer In
A2: Statement | Jan 2026 – Jun 2026
A4: SUMMARY
A5: Total | C5: =SUMIFS('Transaction Overview'!$D$2:$D$467,'Transaction Overview'!$E$2:$E$467,"ACCT_XFER",'Transaction Overview'!$D$2:$D$467,">0")+SUMIFS('Transaction Overview'!$D$2:$D$467,'Transaction Overview'!$E$2:$E$467,"CHASE_TO_PARTNERFI",'Transaction Overview'!$D$2:$D$467,">0")+SUMIFS('Transaction Overview'!$D$2:$D$467,'Transaction Overview'!$E$2:$E$467,"QUICKPAY_DEBIT",'Transaction Overview'!$D$2:$D$467,">0") -> 122006.41
A6: # Transactions | C6: =COUNTIFS('Transaction Overview'!$E$2:$E$467,"ACCT_XFER",'Transaction Overview'!$D$2:$D$467,">0")+COUNTIFS('Transaction Overview'!$E$2:$E$467,"CHASE_TO_PARTNERFI",'Transaction Overview'!$D$2:$D$467,">0")+COUNTIFS('Transaction Overview'!$E$2:$E$467,"QUICKPAY_DEBIT",'Transaction Overview'!$D$2:$D$467,">0") -> 5
A8: BY COUNTERPARTY
A9: Counterparty | B9: # Txns | C9: Amount
A10: Transfer From DWG Capital Group | B10: =COUNTIFS('Transaction Overview'!$G$2:$G$467,$A10,'Transaction Overview'!$D$2:$D$467,">0") -> 1 | C10: =SUMIFS('Transaction Overview'!$D$2:$D$467,'Transaction Overview'!$G$2:$G$467,$A10,'Transaction Overview'!$D$2:$D$467,">0") -> 8556.41
A11: Transfer From Poseidon | B11: =COUNTIFS('Transaction Overview'!$G$2:$G$467,$A11,'Transaction Overview'!$D$2:$D$467,">0") -> 1 | C11: =SUMIFS('Transaction Overview'!$D$2:$D$467,'Transaction Overview'!$G$2:$G$467,$A11,'Transaction Overview'!$D$2:$D$467,">0") -> 2000
A12: Transfer From SPF | B12: =COUNTIFS('Transaction Overview'!$G$2:$G$467,$A12,'Transaction Overview'!$D$2:$D$467,">0") -> 1 | C12: =SUMIFS('Transaction Overview'!$D$2:$D$467,'Transaction Overview'!$G$2:$G$467,$A12,'Transaction Overview'!$D$2:$D$467,">0") -> 11450
A13: Transfer From Stryten | B13: =COUNTIFS('Transaction Overview'!$G$2:$G$467,$A13,'Transaction Overview'!$D$2:$D$467,">0") -> 2 | C13: =SUMIFS('Transaction Overview'!$D$2:$D$467,'Transaction Overview'!$G$2:$G$467,$A13,'Transaction Overview'!$D$2:$D$467,">0") -> 100000
A14: Subtotal | B14: =SUM(B10:B13) -> 5 | C14: =SUM(C10:C13) -> 122006.41
A16: DETAIL
A17: Date | B17: Counterparty | C17: Amount
A18: {=_xlfn._xlws.FILTER('Transaction Overview'!$B$2:$B$467,((('Transaction Overview'!$E$2:$E$467="ACCT_XFER")+('Transaction Overview'!$E$2:$E$467="CHASE_TO_PARTNERFI")+('Transaction Overview'!$E$2:$E$467="QUICKPAY_DEBIT"))*('Transaction Overview'!$D$2:$D$467>0)))} -> 46136 | B18: {=_xlfn._xlws.FILTER('Transaction Overview'!$G$2:$G$467,((('Transaction Overview'!$E$2:$E$467="ACCT_XFER")+('Transaction Overview'!$E$2:$E$467="CHASE_TO_PARTNERFI")+('Transaction Overview'!$E$2:$E$467="QUICKPAY_DEBIT"))*('Transaction Overview'!$D$2:$D$467>0)))} -> Transfer From SPF | C18: {=_xlfn._xlws.FILTER('Transaction Overview'!$D$2:$D$467,((('Transaction Overview'!$E$2:$E$467="ACCT_XFER")+('Transaction Overview'!$E$2:$E$467="CHASE_TO_PARTNERFI")+('Transaction Overview'!$E$2:$E$467="QUICKPAY_DEBIT"))*('Transaction Overview'!$D$2:$D$467>0)))} -> 11450
A19: 46111 | B19: Transfer From Stryten | C19: 50000
A20: 46056 | B20: Transfer From DWG Capital Group | C20: 8556.41
A21: 46055 | B21: Transfer From Stryten | C21: 50000
A22: 46035 | B22: Transfer From Poseidon | C22: 2000

Sheet Transfer Out
A1: Chase 9335 — 2026 Activity — Transfer Out
A2: Statement | Jan 2026 – Jun 2026
A4: SUMMARY
A5: Total | C5: =SUMIFS('Transaction Overview'!$D$2:$D$467,'Transaction Overview'!$E$2:$E$467,"ACCT_XFER",'Transaction Overview'!$D$2:$D$467,"<0")+SUMIFS('Transaction Overview'!$D$2:$D$467,'Transaction Overview'!$E$2:$E$467,"CHASE_TO_PARTNERFI",'Transaction Overview'!$D$2:$D$467,"<0")+SUMIFS('Transaction Overview'!$D$2:$D$467,'Transaction Overview'!$E$2:$E$467,"QUICKPAY_DEBIT",'Transaction Overview'!$D$2:$D$467,"<0") -> -541618.41
A6: # Transactions | C6: =COUNTIFS('Transaction Overview'!$E$2:$E$467,"ACCT_XFER",'Transaction Overview'!$D$2:$D$467,"<0")+COUNTIFS('Transaction Overview'!$E$2:$E$467,"CHASE_TO_PARTNERFI",'Transaction Overview'!$D$2:$D$467,"<0")+COUNTIFS('Transaction Overview'!$E$2:$E$467,"QUICKPAY_DEBIT",'Transaction Overview'!$D$2:$D$467,"<0") -> 51
A8: BY COUNTERPARTY
A9: Counterparty | B9: # Txns | C9: Amount
A10: Transfer to Angela Dunning | B10: =COUNTIFS('Transaction Overview'!$G$2:$G$467,$A10,'Transaction Overview'!$D$2:$D$467,"<0") -> 3 | C10: =SUMIFS('Transaction Overview'!$D$2:$D$467,'Transaction Overview'!$G$2:$G$467,$A10,'Transaction Overview'!$D$2:$D$467,"<0") -> -31000
A11: Transfer to Buckeye | B11: =COUNTIFS('Transaction Overview'!$G$2:$G$467,$A11,'Transaction Overview'!$D$2:$D$467,"<0") -> 1 | C11: =SUMIFS('Transaction Overview'!$D$2:$D$467,'Transaction Overview'!$G$2:$G$467,$A11,'Transaction Overview'!$D$2:$D$467,"<0") -> -20000
A12: Transfer to DWG Capital Group | B12: =COUNTIFS('Transaction Overview'!$G$2:$G$467,$A12,'Transaction Overview'!$D$2:$D$467,"<0") -> 17 | C12: =SUMIFS('Transaction Overview'!$D$2:$D$467,'Transaction Overview'!$G$2:$G$467,$A12,'Transaction Overview'!$D$2:$D$467,"<0") -> -298556.41
A13: Transfer to DWG Capital Group_Costar | B13: =COUNTIFS('Transaction Overview'!$G$2:$G$467,$A13,'Transaction Overview'!$D$2:$D$467,"<0") -> 1 | C13: =SUMIFS('Transaction Overview'!$D$2:$D$467,'Transaction Overview'!$G$2:$G$467,$A13,'Transaction Overview'!$D$2:$D$467,"<0") -> -15000
A14: Transfer to DWG Capital Partners | B14: =COUNTIFS('Transaction Overview'!$G$2:$G$467,$A14,'Transaction Overview'!$D$2:$D$467,"<0") -> 5 | C14: =SUMIFS('Transaction Overview'!$D$2:$D$467,'Transaction Overview'!$G$2:$G$467,$A14,'Transaction Overview'!$D$2:$D$467,"<0") -> -77000
A15: Transfer to Edgebuilders | B15: =COUNTIFS('Transaction Overview'!$G$2:$G$467,$A15,'Transaction Overview'!$D$2:$D$467,"<0") -> 2 | C15: =SUMIFS('Transaction Overview'!$D$2:$D$467,'Transaction Overview'!$G$2:$G$467,$A15,'Transaction Overview'!$D$2:$D$467,"<0") -> -35200
A16: Transfer to JAL Southbend | B16: =COUNTIFS('Transaction Overview'!$G$2:$G$467,$A16,'Transaction Overview'!$D$2:$D$467,"<0") -> 1 | C16: =SUMIFS('Transaction Overview'!$D$2:$D$467,'Transaction Overview'!$G$2:$G$467,$A16,'Transaction Overview'!$D$2:$D$467,"<0") -> -13000
A17: Transfer to Judd Sol Prop | B17: =COUNTIFS('Transaction Overview'!$G$2:$G$467,$A17,'Transaction Overview'!$D$2:$D$467,"<0") -> 2 | C17: =SUMIFS('Transaction Overview'!$D$2:$D$467,'Transaction Overview'!$G$2:$G$467,$A17,'Transaction Overview'!$D$2:$D$467,"<0") -> -200
A18: Transfer to TX Personal Joint | B18: =COUNTIFS('Transaction Overview'!$G$2:$G$467,$A18,'Transaction Overview'!$D$2:$D$467,"<0") -> 2 | C18: =SUMIFS('Transaction Overview'!$D$2:$D$467,'Transaction Overview'!$G$2:$G$467,$A18,'Transaction Overview'!$D$2:$D$467,"<0") -> -40000
A19: Meg Maran - MDC Commission | B19: =COUNTIFS('Transaction Overview'!$G$2:$G$467,$A19,'Transaction Overview'!$D$2:$D$467,"<0") -> 1 | C19: =SUMIFS('Transaction Overview'!$D$2:$D$467,'Transaction Overview'!$G$2:$G$467,$A19,'Transaction Overview'!$D$2:$D$467,"<0") -> -1500
A20: Office/Miscellaneous Reimbursement - Mike P. | B20: =COUNTIFS('Transaction Overview'!$G$2:$G$467,$A20,'Transaction Overview'!$D$2:$D$467,"<0") -> 13 | C20: =SUMIFS('Transaction Overview'!$D$2:$D$467,'Transaction Overview'!$G$2:$G$467,$A20,'Transaction Overview'!$D$2:$D$467,"<0") -> -6637
A21: Zelle - Chase Hall | B21: =COUNTIFS('Transaction Overview'!$G$2:$G$467,$A21,'Transaction Overview'!$D$2:$D$467,"<0") -> 1 | C21: =SUMIFS('Transaction Overview'!$D$2:$D$467,'Transaction Overview'!$G$2:$G$467,$A21,'Transaction Overview'!$D$2:$D$467,"<0") -> -325
... A23: Zelle - Scott Brech | B23: =COUNTIFS('Transaction Overview'!$G$2:$G$467,$A23,'Transaction Overview'!$D$2:$D$467,"<0") -> 1 | C23: =SUMIFS('Transaction Overview'!$D$2:$D$467,'Transaction Overview'!$G$2:$G$467,$A23,'Transaction Overview'!$D$2:$D$467,"<0") -> -700
A24: Subtotal | B24: =SUM(B10:B23) -> 51 | C24: =SUM(C10:C23) -> -541618.41
A26: DETAIL
A27: Date | B27: Counterparty | C27: Amount
A28: {=_xlfn._xlws.FILTER('Transaction Overview'!$B$2:$B$467,((('Transaction Overview'!$E$2:$E$467="ACCT_XFER")+('Transaction Overview'!$E$2:$E$467="CHASE_TO_PARTNERFI")+('Transaction Overview'!$E$2:$E$467="QUICKPAY_DEBIT"))*('Transaction Overview'!$D$2:$D$467<0)))} -> 46177 | B28: {=_xlfn._xlws.FILTER('Transaction Overview'!$G$2:$G$467,((('Transaction Overview'!$E$2:$E$467="ACCT_XFER")+('Transaction Overview'!$E$2:$E$467="CHASE_TO_PARTNERFI")+('Transaction Overview'!$E$2:$E$467="QUICKPAY_DEBIT"))*('Transaction Overview'!$D$2:$D$467<0)))} -> Transfer to Angela Dunning | C28: {=_xlfn._xlws.FILTER('Transaction Overview'!$D$2:$D$467,((('Transaction Overview'!$E$2:$E$467="ACCT_XFER")+('Transaction Overview'!$E$2:$E$467="CHASE_TO_PARTNERFI")+('Transaction Overview'!$E$2:$E$467="QUICKPAY_DEBIT"))*('Transaction Overview'!$D$2:$D$467<0)))} -> -1000
A29: 46175 | B29: Transfer to DWG Capital Group | C29: -30000
A30: 46175 | B30: Zelle - Francisco Bautista | C30: -2500
A31: 46160 | B31: Office/Miscellaneous Reimbursement - Mike P. | C31: -25
A32: 46157 | B32: Transfer to DWG Capital Partners | C32: -20000
A33: 46157 | B33: Transfer to Buckeye | C33: -20000
A34: 46153 | B34: Office/Miscellaneous Reimbursement - Mike P. | C34: -140
A35: 46142 | B35: Transfer to DWG Capital Partners | C35: -10000
A36: 46141 | B36: Transfer to DWG Capital Group | C36: -10000
A37: 46141 | B37: Transfer to DWG Capital Group | C37: -30000
A38: 46140 | B38: Office/Miscellaneous Reimbursement - Mike P. | C38: -5000
A39: 46139 | B39: Meg Maran - MDC Commission | C39: -1500
A40: 46135 | B40: Transfer to DWG Capital Group | C40: -15000
... A78: 46030 | B78: Transfer to Edgebuilders | C78: -35000

Sheet Commission
A1: Chase 9335 — 2026 Activity
A2: Commissions Statement | Jan 2026 – Jun 2026
A4: SUMMARY
A5: Commissions Earned (net) | C5: =SUMIFS('Transaction Overview'!$D$2:$D$467,'Transaction Overview'!$J$2:$J$467,"Commissions — Incoming") -> 435155.44
A6: Commissions Paid Out | C6: =SUMIFS('Transaction Overview'!$D$2:$D$467,'Transaction Overview'!$J$2:$J$467,"Commissions — Outgoing") -> -23587.5
A7: Net Commission Kept | C7: =C5+C6 -> 411567.94
A9: BY DEAL — INCOMING
A10: Category | B10: # Txns | C10: Amount
A11: Incoming Commission: Rembrandt | B11: =COUNTIFS('Transaction Overview'!$G$2:$G$467,$A11) -> 1 | C11: =SUMIFS('Transaction Overview'!$D$2:$D$467,'Transaction Overview'!$G$2:$G$467,$A11) -> 168266
A12: Incoming Commission: SPF | B12: =COUNTIFS('Transaction Overview'!$G$2:$G$467,$A12) -> 3 | C12: =SUMIFS('Transaction Overview'!$D$2:$D$467,'Transaction Overview'!$G$2:$G$467,$A12) -> 266889.44
A13: Subtotal — Incoming | B13: =SUM(B11:B12) -> 4 | C13: =SUM(C11:C12) -> 435155.44
A15: BY DEAL — OUTGOING
A16: Category | B16: # Txns | C16: Amount
A17: Kevin Wong Commission (SPF) | B17: =COUNTIFS('Transaction Overview'!$G$2:$G$467,$A17) -> 1 | C17: =SUMIFS('Transaction Overview'!$D$2:$D$467,'Transaction Overview'!$G$2:$G$467,$A17) -> -16087.5
A18: Kevin Wong Commission (Steve Klar) | B18: =COUNTIFS('Transaction Overview'!$G$2:$G$467,$A18) -> 1 | C18: =SUMIFS('Transaction Overview'!$D$2:$D$467,'Transaction Overview'!$G$2:$G$467,$A18) -> -6000
A19: Meg Maran - MDC Commission | B19: =COUNTIFS('Transaction Overview'!$G$2:$G$467,$A19) -> 1 | C19: =SUMIFS('Transaction Overview'!$D$2:$D$467,'Transaction Overview'!$G$2:$G$467,$A19) -> -1500
A20: Subtotal — Outgoing | B20: =SUM(B17:B19) -> 3 | C20: =SUM(C17:C19) -> -23587.5

Sheet Wire In
A1: Chase 9335 — 2026 Activity — Wire In
A2: Statement | Jan 2026 – Jun 2026
A4: SUMMARY
A5: Total | C5: =SUMIFS('Transaction Overview'!$D$2:$D$467,'Transaction Overview'!$E$2:$E$467,"WIRE_INCOMING") -> 529526.29
A6: # Transactions | C6: =COUNTIFS('Transaction Overview'!$E$2:$E$467,"WIRE_INCOMING") -> 7
A8: BY COUNTERPARTY
A9: Counterparty | B9: # Txns | C9: Amount
A10: Incoming Commission: Rembrandt | B10: =COUNTIFS('Transaction Overview'!$G$2:$G$467,$A10,'Transaction Overview'!$E$2:$E$467,"WIRE_INCOMING") -> 1 | C10: =SUMIFS('Transaction Overview'!$D$2:$D$467,'Transaction Overview'!$G$2:$G$467,$A10,'Transaction Overview'!$E$2:$E$467,"WIRE_INCOMING") -> 168266
A11: Incoming Commission: SPF | B11: =COUNTIFS('Transaction Overview'!$G$2:$G$467,$A11,'Transaction Overview'!$E$2:$E$467,"WIRE_INCOMING") -> 3 | C11: =SUMIFS('Transaction Overview'!$D$2:$D$467,'Transaction Overview'!$G$2:$G$467,$A11,'Transaction Overview'!$E$2:$E$467,"WIRE_INCOMING") -> 266889.44
A12: Incoming wire from JC Whitner | B12: =COUNTIFS('Transaction Overview'!$G$2:$G$467,$A12,'Transaction Overview'!$E$2:$E$467,"WIRE_INCOMING") -> 1 | C12: =SUMIFS('Transaction Overview'!$D$2:$D$467,'Transaction Overview'!$G$2:$G$467,$A12,'Transaction Overview'!$E$2:$E$467,"WIRE_INCOMING") -> 20000
A13: Incoming wire from Moab (Leftover Funds) | B13: =COUNTIFS('Transaction Overview'!$G$2:$G$467,$A13,'Transaction Overview'!$E$2:$E$467,"WIRE_INCOMING") -> 1 | C13: =SUMIFS('Transaction Overview'!$D$2:$D$467,'Transaction Overview'!$G$2:$G$467,$A13,'Transaction Overview'!$E$2:$E$467,"WIRE_INCOMING") -> 58370.85
A14: Incoming wire from Steve Klar | B14: =COUNTIFS('Transaction Overview'!$G$2:$G$467,$A14,'Transaction Overview'!$E$2:$E$467,"WIRE_INCOMING") -> 1 | C14: =SUMIFS('Transaction Overview'!$D$2:$D$467,'Transaction Overview'!$G$2:$G$467,$A14,'Transaction Overview'!$E$2:$E$467,"WIRE_INCOMING") -> 16000
A15: Subtotal | B15: =SUM(B10:B14) -> 7 | C15: =SUM(C10:C14) -> 529526.29
A17: DETAIL
A18: Date | B18: Counterparty | C18: Amount
A19: {=_xlfn._xlws.FILTER('Transaction Overview'!$B$2:$B$467,('Transaction Overview'!$E$2:$E$467="WIRE_INCOMING"))} -> 46135 | B19: {=_xlfn._xlws.FILTER('Transaction Overview'!$G$2:$G$467,('Transaction Overview'!$E$2:$E$467="WIRE_INCOMING"))} -> Incoming Commission: SPF | C19: {=_xlfn._xlws.FILTER('Transaction Overview'!$D$2:$D$467,('Transaction Overview'!$E$2:$E$467="WIRE_INCOMING"))} -> 23139.44
A20: 46135 | B20: Incoming Commission: SPF | C20: 48750
A21: 46135 | B21: Incoming Commission: SPF | C21: 195000
A22: 46072 | B22: Incoming Commission: Rembrandt | C22: 168266
A23: 46056 | B23: Incoming wire from Moab (Leftover Funds) | C23: 58370.85
A24: 46055 | B24: Incoming wire from JC Whitner | C24: 20000
A25: 46029 | B25: Incoming wire from Steve Klar | C25: 16000

Sheet Wire Out
A1: Chase 9335 — 2026 Activity — Wire Out
A2: Statement | Jan 2026 – Jun 2026
A4: SUMMARY
A5: Total | C5: =SUMIFS('Transaction Overview'!$D$2:$D$467,'Transaction Overview'!$E$2:$E$467,"WIRE_OUTGOING") -> -108758.35
A6: # Transactions | C6: =COUNTIFS('Transaction Overview'!$E$2:$E$467,"WIRE_OUTGOING") -> 7
A8: BY COUNTERPARTY
A9: Counterparty | B9: # Txns | C9: Amount
A10: Bridge Coverage (JC Whitner) | B10: =COUNTIFS('Transaction Overview'!$G$2:$G$467,$A10,'Transaction Overview'!$E$2:$E$467,"WIRE_OUTGOING") -> 1 | C10: =SUMIFS('Transaction Overview'!$D$2:$D$467,'Transaction Overview'!$G$2:$G$467,$A10,'Transaction Overview'!$E$2:$E$467,"WIRE_OUTGOING") -> -10000
A11: Kevin Wong Commission (SPF) | B11: =COUNTIFS('Transaction Overview'!$G$2:$G$467,$A11,'Transaction Overview'!$E$2:$E$467,"WIRE_OUTGOING") -> 1 | C11: =SUMIFS('Transaction Overview'!$D$2:$D$467,'Transaction Overview'!$G$2:$G$467,$A11,'Transaction Overview'!$E$2:$E$467,"WIRE_OUTGOING") -> -16087.5
A12: Kevin Wong Commission (Steve Klar) | B12: =COUNTIFS('Transaction Overview'!$G$2:$G$467,$A12,'Transaction Overview'!$E$2:$E$467,"WIRE_OUTGOING") -> 1 | C12: =SUMIFS('Transaction Overview'!$D$2:$D$467,'Transaction Overview'!$G$2:$G$467,$A12,'Transaction Overview'!$E$2:$E$467,"WIRE_OUTGOING") -> -6000
A13: MAG - Admeer Advisory Transfer | B13: =COUNTIFS('Transaction Overview'!$G$2:$G$467,$A13,'Transaction Overview'!$E$2:$E$467,"WIRE_OUTGOING") -> 2 | C13: =SUMIFS('Transaction Overview'!$D$2:$D$467,'Transaction Overview'!$G$2:$G$467,$A13,'Transaction Overview'!$E$2:$E$467,"WIRE_OUTGOING") -> -10000
A14: Wire to Gi Capital Group (+ Moab Funds) | B14: =COUNTIFS('Transaction Overview'!$G$2:$G$467,$A14,'Transaction Overview'!$E$2:$E$467,"WIRE_OUTGOING") -> 1 | C14: =SUMIFS('Transaction Overview'!$D$2:$D$467,'Transaction Overview'!$G$2:$G$467,$A14,'Transaction Overview'!$E$2:$E$467,"WIRE_OUTGOING") -> -56670.85
A15: Wire to Ryan Bodmer | B15: =COUNTIFS('Transaction Overview'!$G$2:$G$467,$A15,'Transaction Overview'!$E$2:$E$467,"WIRE_OUTGOING") -> 1 | C15: =SUMIFS('Transaction Overview'!$D$2:$D$467,'Transaction Overview'!$G$2:$G$467,$A15,'Transaction Overview'!$E$2:$E$467,"WIRE_OUTGOING") -> -10000
A16: Subtotal | B16: =SUM(B10:B15) -> 7 | C16: =SUM(C10:C15) -> -108758.35
A18: DETAIL
A19: Date | B19: Counterparty | C19: Amount
A20: {=_xlfn._xlws.FILTER('Transaction Overview'!$B$2:$B$467,('Transaction Overview'!$E$2:$E$467="WIRE_OUTGOING"))} -> 46139 | B20: {=_xlfn._xlws.FILTER('Transaction Overview'!$G$2:$G$467,('Transaction Overview'!$E$2:$E$467="WIRE_OUTGOING"))} -> Kevin Wong Commission (SPF) | C20: {=_xlfn._xlws.FILTER('Transaction Overview'!$D$2:$D$467,('Transaction Overview'!$E$2:$E$467="WIRE_OUTGOING"))} -> -16087.5
A21: 46132 | B21: MAG - Admeer Advisory Transfer | C21: -5000
A22: 46057 | B22: Wire to Ryan Bodmer | C22: -10000
A23: 46056 | B23: Wire to Gi Capital Group (+ Moab Funds) | C23: -56670.85
A24: 46056 | B24: MAG - Admeer Advisory Transfer | C24: -5000
A25: 46029 | B25: Bridge Coverage (JC Whitner) | C25: -10000
A26: 46029 | B26: Kevin Wong Commission (Steve Klar) | C26: -6000

Sheet Transaction Overview
A1: Details | B1: Posting Date | C1: Description | D1: Amount | E1: Type | F1: Balance | G1: Category | H1: Month | I1: Combined Category | J1: Group
A2: ='2026_Chase9335_Activity_2026062'!A2 -> DEBIT | B2: ='2026_Chase9335_Activity_2026062'!B2 -> 46195 | C2: ='2026_Chase9335_Activity_2026062'!C2 -> ORIG CO NAME:AMERICAN EXPRESS ORIG ID:2005032111 DESC DATE:260622 CO ENTRY DESCR:ACH PMT SEC:CCD TRACE#:021000023462426 EED:260622 IND ID:W7800 IND NAME:JOHN DUNNING ER AM TRN: 1733462426TC | D2: ='2026_Chase9335_Activity_2026062'!D2 -> -35.04 | E2: ='2026_Chase9335_Activity_2026062'!E2 -> ACH_DEBIT | F2: ='2026_Chase9335_Activity_2026062'!F2 -> 41709.27 | G2: ='2026_Chase9335_Activity_2026062'!G2 -> American Express Credit Card PMT | H2: =IF($B2="","",DATE(YEAR($B2),MONTH($B2),1)) -> 46174 | I2: =IF($G2="","Uncategorized — Review",IFERROR(_xlfn.XLOOKUP($G2,Mapping!$A:$A,Mapping!$B:$B),"Uncategorized — Review")) -> American Express Credit Card PMT | J2: =IF($G2="","Uncategorized — Review",IFERROR(_xlfn.XLOOKUP($G2,Mapping!$A:$A,Mapping!$C:$C),"Uncategorized — Review")) -> Credit Card & Loan Payments
A3: ='2026_Chase9335_Activity_2026062'!A3 -> DEBIT | B3: ='2026_Chase9335_Activity_2026062'!B3 -> 46195 | C3: ='2026_Chase9335_Activity_2026062'!C3 -> UBER * EATS PENDIN SAN FRANCISCO CA137460 06/22 | D3: ='2026_Chase9335_Activity_2026062'!D3 -> -50.83 | E3: ='2026_Chase9335_Activity_2026062'!E3 -> DEBIT_CARD | F3: ='2026_Chase9335_Activity_2026062'!F3 -> 41744.31 | G3: ='2026_Chase9335_Activity_2026062'!G3 -> Personal - Car | H3: =IF($B3="","",DATE(YEAR($B3),MONTH($B3),1)) -> 46174 | I3: =IF($G3="","Uncategorized — Review",IFERROR(_xlfn.XLOOKUP($G3,Mapping!$A:$A,Mapping!$B:$B),"Uncategorized — Review")) -> Personal - Car & Auto | J3: =IF($G3="","Uncategorized — Review",IFERROR(_xlfn.XLOOKUP($G3,Mapping!$A:$A,Mapping!$C:$C),"Uncategorized — Review")) -> Personal — Owner
A4: ='2026_Chase9335_Activity_2026062'!A4 -> DEBIT | B4: ='2026_Chase9335_Activity_2026062'!B4 -> 46195 | C4: ='2026_Chase9335_Activity_2026062'!C4 -> UBER * EATS PENDIN SAN FRANCISCO CA016992 06/21 | D4: ='2026_Chase9335_Activity_2026062'!D4 -> -124.58 | E4: ='2026_Chase9335_Activity_2026062'!E4 -> DEBIT_CARD | F4: ='2026_Chase9335_Activity_2026062'!F4 -> 41795.14 | G4: ='2026_Chase9335_Activity_2026062'!G4 -> Personal - Car | H4: =IF($B4="","",DATE(YEAR($B4),MONTH($B4),1)) -> 46174 | I4: =IF($G4="","Uncategorized — Review",IFERROR(_xlfn.XLOOKUP($G4,Mapping!$A:$A,Mapping!$B:$B),"Uncategorized — Review")) -> Personal - Car & Auto | J4: =IF($G4="","Uncategorized — Review",IFERROR(_xlfn.XLOOKUP($G4,Mapping!$A:$A,Mapping!$C:$C),"Uncategorized — Review")) -> Personal — Owner
A5: ='2026_Chase9335_Activity_2026062'!A5 -> DEBIT | B5: ='2026_Chase9335_Activity_2026062'!B5 -> 46195 | C5: ='2026_Chase9335_Activity_2026062'!C5 -> Netflix 1 8445052993 CA 06/21 | D5: ='2026_Chase9335_Activity_2026062'!D5 -> -26.99 | E5: ='2026_Chase9335_Activity_2026062'!E5 -> DEBIT_CARD | F5: ='2026_Chase9335_Activity_2026062'!F5 -> 41919.72 | G5: ='2026_Chase9335_Activity_2026062'!G5 -> Personal - Subscriptions | H5: =IF($B5="","",DATE(YEAR($B5),MONTH($B5),1)) -> 46174 | I5: =IF($G5="","Uncategorized — Review",IFERROR(_xlfn.XLOOKUP($G5,Mapping!$A:$A,Mapping!$B:$B),"Uncategorized — Review")) -> Personal - Subscriptions | J5: =IF($G5="","Uncategorized — Review",IFERROR(_xlfn.XLOOKUP($G5,Mapping!$A:$A,Mapping!$C:$C),"Uncategorized — Review")) -> Personal — Owner
A6: ='2026_Chase9335_Activity_2026062'!A6 -> DEBIT | B6: ='2026_Chase9335_Activity_2026062'!B6 -> 46195 | C6: ='2026_Chase9335_Activity_2026062'!C6 -> APPLE.COM/BILL 866-712-7753 CA 06/21 | D6: ='2026_Chase9335_Activity_2026062'!D6 -> -30.89 | E6: ='2026_Chase9335_Activity_2026062'!E6 -> DEBIT_CARD | F6: ='2026_Chase9335_Activity_2026062'!F6 -> 41946.71 | G6: ='2026_Chase9335_Activity_2026062'!G6 -> Personal - Subscriptions | H6: =IF($B6="","",DATE(YEAR($B6),MONTH($B6),1)) -> 46174 | I6: =IF($G6="","Uncategorized — Review",IFERROR(_xlfn.XLOOKUP($G6,Mapping!$A:$A,Mapping!$B:$B),"Uncategorized — Review")) -> Personal - Subscriptions | J6: =IF($G6="","Uncategorized — Review",IFERROR(_xlfn.XLOOKUP($G6,Mapping!$A:$A,Mapping!$C:$C),"Uncategorized — Review")) -> Personal — Owner
A7: ='2026_Chase9335_Activity_2026062'!A7 -> DEBIT | B7: ='2026_Chase9335_Activity_2026062'!B7 -> 46191 | C7: ='2026_Chase9335_Activity_2026062'!C7 -> ORIG CO NAME:AMERICAN EXPRESS ORIG ID:2005032111 DESC DATE:260618 CO ENTRY DESCR:ACH PMT SEC:CCD TRACE#:021000025422371 EED:260618 IND ID:W3988 IND NAME:JOHN DUNNING ER AM TRN: 1695422371TC | D7: ='2026_Chase9335_Activity_2026062'!D7 -> -5000 | E7: ='2026_Chase9335_Activity_2026062'!E7 -> ACH_DEBIT | F7: ='2026_Chase9335_Activity_2026062'!F7 -> 41977.6 | G7: ='2026_Chase9335_Activity_2026062'!G7 -> American Express Credit Card PMT | H7: =IF($B7="","",DATE(YEAR($B7),MONTH($B7),1)) -> 46174 | I7: =IF($G7="","Uncategorized — Review",IFERROR(_xlfn.XLOOKUP($G7,Mapping!$A:$A,Mapping!$B:$B),"Uncategorized — Review")) -> American Express Credit Card PMT | J7: =IF($G7="","Uncategorized — Review",IFERROR(_xlfn.XLOOKUP($G7,Mapping!$A:$A,Mapping!$C:$C),"Uncategorized — Review")) -> Credit Card & Loan Payments
A8: ='2026_Chase9335_Activity_2026062'!A8 -> DEBIT | B8: ='2026_Chase9335_Activity_2026062'!B8 -> 46188 | C8: ='2026_Chase9335_Activity_2026062'!C8 -> APPLE.COM/BILL 866-712-7753 CA 06/14 | D8: ='2026_Chase9335_Activity_2026062'!D8 -> -30.89 | E8: ='2026_Chase9335_Activity_2026062'!E8 -> DEBIT_CARD | F8: ='2026_Chase9335_Activity_2026062'!F8 -> 46977.6 | G8: ='2026_Chase9335_Activity_2026062'!G8 -> Personal - Subscriptions | H8: =IF($B8="","",DATE(YEAR($B8),MONTH($B8),1)) -> 46174 | I8: =IF($G8="","Uncategorized — Review",IFERROR(_xlfn.XLOOKUP($G8,Mapping!$A:$A,Mapping!$B:$B),"Uncategorized — Review")) -> Personal - Subscriptions | J8: =IF($G8="","Uncategorized — Review",IFERROR(_xlfn.XLOOKUP($G8,Mapping!$A:$A,Mapping!$C:$C),"Uncategorized — Review")) -> Personal — Owner
A9: ='2026_Chase9335_Activity_2026062'!A9 -> DEBIT | B9: ='2026_Chase9335_Activity_2026062'!B9 -> 46188 | C9: ='2026_Chase9335_Activity_2026062'!C9 -> VIOLET VAPOR - 2 WEATHERFORD TX 999940 06/13 | D9: ='2026_Chase9335_Activity_2026062'!D9 -> -32.31 | E9: ='2026_Chase9335_Activity_2026062'!E9 -> DEBIT_CARD | F9: ='2026_Chase9335_Activity_2026062'!F9 -> 47008.49 | G9: ='2026_Chase9335_Activity_2026062'!G9 -> Personal - Entertainment | H9: =IF($B9="","",DATE(YEAR($B9),MONTH($B9),1)) -> 46174 | I9: =IF($G9="","Uncategorized — Review",IFERROR(_xlfn.XLOOKUP($G9,Mapping!$A:$A,Mapping!$B:$B),"Uncategorized — Review")) -> Personal - Entertainment | J9: =IF($G9="","Uncategorized — Review",IFERROR(_xlfn.XLOOKUP($G9,Mapping!$A:$A,Mapping!$C:$C),"Uncategorized — Review")) -> Personal — Owner
A10: ='2026_Chase9335_Activity_2026062'!A10 -> DEBIT | B10: ='2026_Chase9335_Activity_2026062'!B10 -> 46185 | C10: ='2026_Chase9335_Activity_2026062'!C10 -> BLOOMBERG* 37033964 BLOOMBERG.COM NY 06/12 | D10: ='2026_Chase9335_Activity_2026062'!D10 -> -39.99 | E10: ='2026_Chase9335_Activity_2026062'!E10 -> DEBIT_CARD | F10: ='2026_Chase9335_Activity_2026062'!F10 -> 47040.8 | G10: ='2026_Chase9335_Activity_2026062'!G10 -> Personal - Subscriptions | H10: =IF($B10="","",DATE(YEAR($B10),MONTH($B10),1)) -> 46174 | I10: =IF($G10="","Uncategorized — Review",IFERROR(_xlfn.XLOOKUP($G10,Mapping!$A:$A,Mapping!$B:$B),"Uncategorized — Review")) -> Personal - Subscriptions | J10: =IF($G10="","Uncategorized — Review",IFERROR(_xlfn.XLOOKUP($G10,Mapping!$A:$A,Mapping!$C:$C),"Uncategorized — Review")) -> Personal — Owner
A11: ='2026_Chase9335_Activity_2026062'!A11 -> DEBIT | B11: ='2026_Chase9335_Activity_2026062'!B11 -> 46183 | C11: ='2026_Chase9335_Activity_2026062'!C11 -> ORIG CO NAME:AMERICAN EXPRESS ORIG ID:2005032111 DESC DATE:260610 CO ENTRY DESCR:ACH PMT SEC:CCD TRACE#:021000028992821 EED:260610 IND ID:W5660 IND NAME:JOHN DUNNING ER AM TRN: 1618992821TC | D11: ='2026_Chase9335_Activity_2026062'!D11 -> -4103.05 | E11: ='2026_Chase9335_Activity_2026062'!E11 -> ACH_DEBIT | F11: ='2026_Chase9335_Activity_2026062'!F11 -> 47080.79 | G11: ='2026_Chase9335_Activity_2026062'!G11 -> American Express Credit Card PMT | H11: =IF($B11="","",DATE(YEAR($B11),MONTH($B11),1)) -> 46174 | I11: =IF($G11="","Uncategorized — Review",IFERROR(_xlfn.XLOOKUP($G11,Mapping!$A:$A,Mapping!$B:$B),"Uncategorized — Review")) -> American Express Credit Card PMT | J11: =IF($G11="","Uncategorized — Review",IFERROR(_xlfn.XLOOKUP($G11,Mapping!$A:$A,Mapping!$C:$C),"Uncategorized — Review")) -> Credit Card & Loan Payments
A12: ='2026_Chase9335_Activity_2026062'!A12 -> DEBIT | B12: ='2026_Chase9335_Activity_2026062'!B12 -> 46183 | C12: ='2026_Chase9335_Activity_2026062'!C12 -> ORIG CO NAME:AMERICAN EXPRESS ORIG ID:2005032111 DESC DATE:260610 CO ENTRY DESCR:ACH PMT SEC:CCD TRACE#:021000028992161 EED:260610 IND ID:W3546 IND NAME:JOHN DUNNING ER AM TRN: 1618992161TC | D12: ='2026_Chase9335_Activity_2026062'!D12 -> -6806.31 | E12: ='2026_Chase9335_Activity_2026062'!E12 -> ACH_DEBIT | F12: ='2026_Chase9335_Activity_2026062'!F12 -> 51183.84 | G12: ='2026_Chase9335_Activity_2026062'!G12 -> American Express Credit Card PMT | H12: =IF($B12="","",DATE(YEAR($B12),MONTH($B12),1)) -> 46174 | I12: =IF($G12="","Uncategorized — Review",IFERROR(_xlfn.XLOOKUP($G12,Mapping!$A:$A,Mapping!$B:$B),"Uncategorized — Review")) -> American Express Credit Card PMT | J12: =IF($G12="","Uncategorized — Review",IFERROR(_xlfn.XLOOKUP($G12,Mapping!$A:$A,Mapping!$C:$C),"Uncategorized — Review")) -> Credit Card & Loan Payments
A13: ='2026_Chase9335_Activity_2026062'!A13 -> CREDIT | B13: ='2026_Chase9335_Activity_2026062'!B13 -> 46183 | C13: ='2026_Chase9335_Activity_2026062'!C13 -> ORIG CO NAME:Austin Iron Hold ORIG ID:945440567 DESC DATE: CO ENTRY DESCR:PAYMENT SEC:PPD TRACE#:273976360594060 EED:260610 IND ID: IND NAME:John Dunning TRN: 1610594060TC | D13: ='2026_Chase9335_Activity_2026062'!D13 -> 350 | E13: ='2026_Chase9335_Activity_2026062'!E13 -> ACH_CREDIT | F13: ='2026_Chase9335_Activity_2026062'!F13 -> 57990.15 | G13: ='2026_Chase9335_Activity_2026062'!G13 -> Deal Specific: Austin Iron | H13: =IF($B13="","",DATE(YEAR($B13),MONTH($B13),1)) -> 46174 | I13: =IF($G13="","Uncategorized — Review",IFERROR(_xlfn.XLOOKUP($G13,Mapping!$A:$A,Mapping!$B:$B),"Uncategorized — Review")) -> Deal Specific: Austin Iron | J13: =IF($G13="","Uncategorized — Review",IFERROR(_xlfn.XLOOKUP($G13,Mapping!$A:$A,Mapping!$C:$C),"Uncategorized — Review")) -> Deal-Specific
... A467: ='2026_Chase9335_Activity_2026062'!A467 -> DEBIT | B467: ='2026_Chase9335_Activity_2026062'!B467 -> 46024 | C467: ='2026_Chase9335_Activity_2026062'!C467 -> Experian* Credit Repor 479-3436237 CA 01/01 | D467: ='2026_Chase9335_Activity_2026062'!D467 -> -27.05 | E467: ='2026_Chase9335_Activity_2026062'!E467 -> DEBIT_CARD | F467: ='2026_Chase9335_Activity_2026062'!F467 -> 263587.4 | G467: ='2026_Chase9335_Activity_2026062'!G467 -> Personal - Subscriptions | H467: =IF($B467="","",DATE(YEAR($B467),MONTH($B467),1)) -> 46023 | I467: =IF($G467="","Uncategorized — Review",IFERROR(_xlfn.XLOOKUP($G467,Mapping!$A:$A,Mapping!$B:$B),"Uncategorized — Review")) -> Personal - Subscriptions | J467: =IF($G467="","Uncategorized — Review",IFERROR(_xlfn.XLOOKUP($G467,Mapping!$A:$A,Mapping!$C:$C),"Uncategorized — Review")) -> Personal — Owner

Sheet Mapping
A1: Raw Category | B1: Combined Category | C1: Group
A2: ACH payment to CALCPA group | B2: ACH payment to CALCPA group | C2: DWG Operating
A3: ATM/Cash | B3: ATM/Cash | C3: Personal — Owner
A4: Amazon | B4: Amazon | C4: Personal — Owner
A5: American Express Credit Card PMT | B5: American Express Credit Card PMT | C5: Credit Card & Loan Payments
A6: Apple Payment | B6: Apple Payment | C6: P2P Payments (Zelle/Venmo/PayPal)
A7: Bank Fees | B7: Bank Fees | C7: DWG Operating
A8: Bridge Coverage (JC Whitner) | B8: Bridge Coverage (JC Whitner) | C8: Deal-Specific
A9: DWG HR | B9: DWG HR | C9: Payroll & Contractors
A10: Deal Specific: Austin Iron | B10: Deal Specific: Austin Iron | C10: Deal-Specific
A11: Deal Specific: MRM | B11: Deal Specific: MRM | C11: Deal-Specific
A12: Deal Specific: Merit-Lancaster | B12: Deal Specific: Merit-Lancaster | C12: Deal-Specific
... A58: Apple Cash | B58: Apple Cash | C58: P2P Payments (Zelle/Venmo/PayPal)

Sheet 2026_Chase9335_Activity_2026062
A1: Details | B1: Posting Date | C1: Description | D1: Amount | E1: Type | F1: Balance | G1: Category
A2: DEBIT | B2: 46195 | C2: ORIG CO NAME:AMERICAN EXPRESS ORIG ID:2005032111 DESC DATE:260622 CO ENTRY DESCR:ACH PMT SEC:CCD TRACE#:021000023462426 EED:260622 IND ID:W7800 IND NAME:JOHN DUNNING ER AM TRN: 1733462426TC | D2: -35.04 | E2: ACH_DEBIT | F2: 41709.27 | G2: American Express Credit Card PMT
A3: DEBIT | B3: 46195 | C3: UBER * EATS PENDIN SAN FRANCISCO CA137460 06/22 | D3: -50.83 | E3: DEBIT_CARD | F3: 41744.31 | G3: Personal - Car
A4: DEBIT | B4: 46195 | C4: UBER * EATS PENDIN SAN FRANCISCO CA016992 06/21 | D4: -124.58 | E4: DEBIT_CARD | F4: 41795.14 | G4: Personal - Car
A5: DEBIT | B5: 46195 | C5: Netflix 1 8445052993 CA 06/21 | D5: -26.99 | E5: DEBIT_CARD | F5: 41919.72 | G5: Personal - Subscriptions
A6: DEBIT | B6: 46195 | C6: APPLE.COM/BILL 866-712-7753 CA 06/21 | D6: -30.89 | E6: DEBIT_CARD | F6: 41946.71 | G6: Personal - Subscriptions
A7: DEBIT | B7: 46191 | C7: ORIG CO NAME:AMERICAN EXPRESS ORIG ID:2005032111 DESC DATE:260618 CO ENTRY DESCR:ACH PMT SEC:CCD TRACE#:021000025422371 EED:260618 IND ID:W3988 IND NAME:JOHN DUNNING ER AM TRN: 1695422371TC | D7: -5000 | E7: ACH_DEBIT | F7: 41977.6 | G7: American Express Credit Card PMT
A8: DEBIT | B8: 46188 | C8: APPLE.COM/BILL 866-712-7753 CA 06/14 | D8: -30.89 | E8: DEBIT_CARD | F8: 46977.6 | G8: Personal - Subscriptions
A9: DEBIT | B9: 46188 | C9: VIOLET VAPOR - 2 WEATHERFORD TX 999940 06/13 | D9: -32.31 | E9: DEBIT_CARD | F9: 47008.49 | G9: Personal - Entertainment
A10: DEBIT | B10: 46185 | C10: BLOOMBERG* 37033964 BLOOMBERG.COM NY 06/12 | D10: -39.99 | E10: DEBIT_CARD | F10: 47040.8 | G10: Personal - Subscriptions
A11: DEBIT | B11: 46183 | C11: ORIG CO NAME:AMERICAN EXPRESS ORIG ID:2005032111 DESC DATE:260610 CO ENTRY DESCR:ACH PMT SEC:CCD TRACE#:021000028992821 EED:260610 IND ID:W5660 IND NAME:JOHN DUNNING ER AM TRN: 1618992821TC | D11: -4103.05 | E11: ACH_DEBIT | F11: 47080.79 | G11: American Express Credit Card PMT
A12: DEBIT | B12: 46183 | C12: ORIG CO NAME:AMERICAN EXPRESS ORIG ID:2005032111 DESC DATE:260610 CO ENTRY DESCR:ACH PMT SEC:CCD TRACE#:021000028992161 EED:260610 IND ID:W3546 IND NAME:JOHN DUNNING ER AM TRN: 1618992161TC | D12: -6806.31 | E12: ACH_DEBIT | F12: 51183.84 | G12: American Express Credit Card PMT
A13: CREDIT | B13: 46183 | C13: ORIG CO NAME:Austin Iron Hold ORIG ID:945440567 DESC DATE: CO ENTRY DESCR:PAYMENT SEC:PPD TRACE#:273976360594060 EED:260610 IND ID: IND NAME:John Dunning TRN: 1610594060TC | D13: 350 | E13: ACH_CREDIT | F13: 57990.15 | G13: Deal Specific: Austin Iron
... A467: DEBIT | B467: 46024 | C467: Experian* Credit Repor 479-3436237 CA 01/01 | D467: -27.05 | E467: DEBIT_CARD | F467: 263587.4 | G467: Personal - Subscriptions
