Workbook

Sheet Transaction Summary
A1: Chase Personal Banking — Angela
A2: Statement Summary | Jan 2, 2026 – Jul 8, 2026
A4: Account | B4: Angela — Chase 1117
A5: Statement Period | B5: Jan 2026 – Jul 2026
A7: TOTALS
A8: Charges (Outflows) | B8: =SUMIF(Angela_2026_Chase1117_Activity_!$D$2:$D$1368,"<0") -> -225740.02
A9: Credits & Payments (Inflows) | B9: =SUMIF(Angela_2026_Chase1117_Activity_!$D$2:$D$1368,">0") -> 225286.54
A10: Net Balance | B10: =B8+B9 -> -453.48
A12: ACTIVITY — INFLOWS vs OUTFLOWS
A13: Flow | B13: # Txns | C13: Amount
A14: Inflows (Credits) | B14: =COUNTIF(Angela_2026_Chase1117_Activity_!$D$2:$D$1368,">0") -> 100 | C14: =B9 -> 225286.54
A15: Outflows (Charges) | B15: =COUNTIF(Angela_2026_Chase1117_Activity_!$D$2:$D$1368,"<0") -> 1267 | C15: =B8 -> -225740.02
A16: Net | B16: =B14+B15 -> 1367 | C16: =C14+C15 -> -453.48
A18: SPEND BY CATEGORY
A19: Category | B19: Amount | C19: % of Charges
A20: Transfers
A21: Transfer from DWG Capital Group | B21: =SUMIF(Angela_2026_Chase1117_Activity_!$G$2:$G$1368,$A21,Angela_2026_Chase1117_Activity_!$D$2:$D$1368) -> 181500 | C21: =B21/$B$8 -> -0.80402226
A22: Transfer to Ava | B22: =SUMIF(Angela_2026_Chase1117_Activity_!$G$2:$G$1368,$A22,Angela_2026_Chase1117_Activity_!$D$2:$D$1368) -> -8750 | C22: =B22/$B$8 -> 0.038761403
A23: Transfer from Poseidon Asset Group | B23: =SUMIF(Angela_2026_Chase1117_Activity_!$G$2:$G$1368,$A23,Angela_2026_Chase1117_Activity_!$D$2:$D$1368) -> 31000 | C23: =B23/$B$8 -> -0.13732612
A24: Subtotal — Transfers | B24: =SUM(B21:B23) -> 203750 | C24: =SUM(C21:C23) -> -0.90258697
A25: Zelle
A26: Zelle from Mary Margaret Trahan | B26: =SUMIF(Angela_2026_Chase1117_Activity_!$G$2:$G$1368,$A26,Angela_2026_Chase1117_Activity_!$D$2:$D$1368) -> 350 | C26: =B26/$B$8 -> -0.0015504561
A27: Zelle from Rose Li | B27: =SUMIF(Angela_2026_Chase1117_Activity_!$G$2:$G$1368,$A27,Angela_2026_Chase1117_Activity_!$D$2:$D$1368) -> 1350 | C27: =B27/$B$8 -> -0.0059803308
A28: Zelle from Joe Saunders | B28: =SUMIF(Angela_2026_Chase1117_Activity_!$G$2:$G$1368,$A28,Angela_2026_Chase1117_Activity_!$D$2:$D$1368) -> 2000 | C28: =B28/$B$8 -> -0.0088597494
A29: Zelle to Joe Saunders | B29: =SUMIF(Angela_2026_Chase1117_Activity_!$G$2:$G$1368,$A29,Angela_2026_Chase1117_Activity_!$D$2:$D$1368) -> -1000 | C29: =B29/$B$8 -> 0.0044298747
A30: Zelle from Tanya Miller | B30: =SUMIF(Angela_2026_Chase1117_Activity_!$G$2:$G$1368,$A30,Angela_2026_Chase1117_Activity_!$D$2:$D$1368) -> 800 | C30: =B30/$B$8 -> -0.0035438997
A31: Zelle to Britt Magadini | B31: =SUMIF(Angela_2026_Chase1117_Activity_!$G$2:$G$1368,$A31,Angela_2026_Chase1117_Activity_!$D$2:$D$1368) -> -1100 | C31: =B31/$B$8 -> 0.0048728622
A32: Zelle from Eunice G Chang | B32: =SUMIF(Angela_2026_Chase1117_Activity_!$G$2:$G$1368,$A32,Angela_2026_Chase1117_Activity_!$D$2:$D$1368) -> 175 | C32: =B32/$B$8 -> -0.00077522807
A33: Zelle from G-Eunice LLC | B33: =SUMIF(Angela_2026_Chase1117_Activity_!$G$2:$G$1368,$A33,Angela_2026_Chase1117_Activity_!$D$2:$D$1368) -> 175 | C33: =B33/$B$8 -> -0.00077522807
A34: Zelle-Leelee | B34: =SUMIF(Angela_2026_Chase1117_Activity_!$G$2:$G$1368,$A34,Angela_2026_Chase1117_Activity_!$D$2:$D$1368) -> -1300 | C34: =B34/$B$8 -> 0.0057588371
A35: Zelle to Natalie Cordova | B35: =SUMIF(Angela_2026_Chase1117_Activity_!$G$2:$G$1368,$A35,Angela_2026_Chase1117_Activity_!$D$2:$D$1368) -> -300 | C35: =B35/$B$8 -> 0.0013289624
A36: Zelle to Shaffa | B36: =SUMIF(Angela_2026_Chase1117_Activity_!$G$2:$G$1368,$A36,Angela_2026_Chase1117_Activity_!$D$2:$D$1368) -> -300 | C36: =B36/$B$8 -> 0.0013289624
A37: Subtotal — Zelle | B37: =SUM(B26:B36) -> 850 | C37: =SUM(C26:C36) -> -0.0037653935
A38: PayPal ACH
A39: PayPal ACH - RAYSTARLIGH | B39: =SUMIF(Angela_2026_Chase1117_Activity_!$G$2:$G$1368,$A39,Angela_2026_Chase1117_Activity_!$D$2:$D$1368) -> -212.86 | C39: =B39/$B$8 -> 0.00094294313
A40: PayPal ACH - OTHERSIDEMI | B40: =SUMIF(Angela_2026_Chase1117_Activity_!$G$2:$G$1368,$A40,Angela_2026_Chase1117_Activity_!$D$2:$D$1368) -> -9.95 | C40: =B40/$B$8 -> 4.4077253e-05
A41: PayPal ACH - PSYCHICMARY | B41: =SUMIF(Angela_2026_Chase1117_Activity_!$G$2:$G$1368,$A41,Angela_2026_Chase1117_Activity_!$D$2:$D$1368) -> -125 | C41: =B41/$B$8 -> 0.00055373434
A42: Subtotal — PayPal ACH | B42: =SUM(B39:B41) -> -347.81 | C42: =SUM(C39:C41) -> 0.0015407547
A43: Personal Travel
A44: Personal Travel | B44: =SUMIF(Angela_2026_Chase1117_Activity_!$G$2:$G$1368,$A44,Angela_2026_Chase1117_Activity_!$D$2:$D$1368) -> -41752.33 | C44: =B44/$B$8 -> 0.18495759
A45: Personal Travel - Portugal | B45: =SUMIF(Angela_2026_Chase1117_Activity_!$G$2:$G$1368,$A45,Angela_2026_Chase1117_Activity_!$D$2:$D$1368) -> -81.34 | C45: =B45/$B$8 -> 0.00036032601
A46: Personal Travel - New Orleans | B46: =SUMIF(Angela_2026_Chase1117_Activity_!$G$2:$G$1368,$A46,Angela_2026_Chase1117_Activity_!$D$2:$D$1368) -> -3043.85 | C46: =B46/$B$8 -> 0.013483874
A47: Palm Springs | B47: =SUMIF(Angela_2026_Chase1117_Activity_!$G$2:$G$1368,$A47,Angela_2026_Chase1117_Activity_!$D$2:$D$1368) -> -639.13 | C47: =B47/$B$8 -> 0.0028312658
A48: Frontier | B48: =SUMIF(Angela_2026_Chase1117_Activity_!$G$2:$G$1368,$A48,Angela_2026_Chase1117_Activity_!$D$2:$D$1368) -> -393.96 | C48: =B48/$B$8 -> 0.0017451934
A49: Subtotal — Personal Travel | B49: =SUM(B44:B48) -> -45910.61 | C49: =SUM(C44:C48) -> 0.20337825
A50: Personal - Everyday
A51: Personal - Health | B51: =SUMIF(Angela_2026_Chase1117_Activity_!$G$2:$G$1368,$A51,Angela_2026_Chase1117_Activity_!$D$2:$D$1368) -> -16867.13 | C51: =B51/$B$8 -> 0.074719272
A52: Personal - Health Insurance | B52: =SUMIF(Angela_2026_Chase1117_Activity_!$G$2:$G$1368,$A52,Angela_2026_Chase1117_Activity_!$D$2:$D$1368) -> -7629.54 | C52: =B52/$B$8 -> 0.033797906
A53: Personal - Clothing | B53: =SUMIF(Angela_2026_Chase1117_Activity_!$G$2:$G$1368,$A53,Angela_2026_Chase1117_Activity_!$D$2:$D$1368) -> -5282.93 | C53: =B53/$B$8 -> 0.023402718
A54: Personal - Subscription | B54: =SUMIF(Angela_2026_Chase1117_Activity_!$G$2:$G$1368,$A54,Angela_2026_Chase1117_Activity_!$D$2:$D$1368) -> -2599.3 | C54: =B54/$B$8 -> 0.011514573
A55: Personal - Car | B55: =SUMIF(Angela_2026_Chase1117_Activity_!$G$2:$G$1368,$A55,Angela_2026_Chase1117_Activity_!$D$2:$D$1368) -> -2531.23 | C55: =B55/$B$8 -> 0.011213032
A56: Personal - Food | B56: =SUMIF(Angela_2026_Chase1117_Activity_!$G$2:$G$1368,$A56,Angela_2026_Chase1117_Activity_!$D$2:$D$1368) -> -13950.2 | C56: =B56/$B$8 -> 0.061797638
A57: Personal - Entertainment | B57: =SUMIF(Angela_2026_Chase1117_Activity_!$G$2:$G$1368,$A57,Angela_2026_Chase1117_Activity_!$D$2:$D$1368) -> -3391.22 | C57: =B57/$B$8 -> 0.01502268
A58: Personal - Shopping | B58: =SUMIF(Angela_2026_Chase1117_Activity_!$G$2:$G$1368,$A58,Angela_2026_Chase1117_Activity_!$D$2:$D$1368) -> -26143.87 | C58: =B58/$B$8 -> 0.11581407
A59: Personal - House Bills | B59: =SUMIF(Angela_2026_Chase1117_Activity_!$G$2:$G$1368,$A59,Angela_2026_Chase1117_Activity_!$D$2:$D$1368) -> -15812.86 | C59: =B59/$B$8 -> 0.070048988
A60: Personal - Misc | B60: =SUMIF(Angela_2026_Chase1117_Activity_!$G$2:$G$1368,$A60,Angela_2026_Chase1117_Activity_!$D$2:$D$1368) -> -923.84 | C60: =B60/$B$8 -> 0.0040924954
A61: Personal - Uber | B61: =SUMIF(Angela_2026_Chase1117_Activity_!$G$2:$G$1368,$A61,Angela_2026_Chase1117_Activity_!$D$2:$D$1368) -> -566.12 | C61: =B61/$B$8 -> 0.0025078407
A62: Personal - Work | B62: =SUMIF(Angela_2026_Chase1117_Activity_!$G$2:$G$1368,$A62,Angela_2026_Chase1117_Activity_!$D$2:$D$1368) -> -227 | C62: =B62/$B$8 -> 0.0010055816
A63: Personal - Court | B63: =SUMIF(Angela_2026_Chase1117_Activity_!$G$2:$G$1368,$A63,Angela_2026_Chase1117_Activity_!$D$2:$D$1368) -> -474.1 | C63: =B63/$B$8 -> 0.0021002036
A64: Subtotal — Personal - Everyday | B64: =SUM(B51:B63) -> -96399.34 | C64: =SUM(C51:C63) -> 0.427037
A65: Brands & Services
A66: Amazon | B66: =SUMIF(Angela_2026_Chase1117_Activity_!$G$2:$G$1368,$A66,Angela_2026_Chase1117_Activity_!$D$2:$D$1368) -> -28112.86 | C66: =B66/$B$8 -> 0.12453645
A67: Poshmark | B67: =SUMIF(Angela_2026_Chase1117_Activity_!$G$2:$G$1368,$A67,Angela_2026_Chase1117_Activity_!$D$2:$D$1368) -> -1169.09 | C67: =B67/$B$8 -> 0.0051789222
A68: Etsy | B68: =SUMIF(Angela_2026_Chase1117_Activity_!$G$2:$G$1368,$A68,Angela_2026_Chase1117_Activity_!$D$2:$D$1368) -> -2440.23 | C68: =B68/$B$8 -> 0.010809913
A69: YouTube Premium | B69: =SUMIF(Angela_2026_Chase1117_Activity_!$G$2:$G$1368,$A69,Angela_2026_Chase1117_Activity_!$D$2:$D$1368) -> -101.93 | C69: =B69/$B$8 -> 0.00045153713
A70: Apple | B70: =SUMIF(Angela_2026_Chase1117_Activity_!$G$2:$G$1368,$A70,Angela_2026_Chase1117_Activity_!$D$2:$D$1368) -> -4857.61 | C70: =B70/$B$8 -> 0.021518604
A71: AT&T | B71: =SUMIF(Angela_2026_Chase1117_Activity_!$G$2:$G$1368,$A71,Angela_2026_Chase1117_Activity_!$D$2:$D$1368) -> -4471.4 | C71: =B71/$B$8 -> 0.019807742
A72: Shipping | B72: =SUMIF(Angela_2026_Chase1117_Activity_!$G$2:$G$1368,$A72,Angela_2026_Chase1117_Activity_!$D$2:$D$1368) -> -236.38 | C72: =B72/$B$8 -> 0.0010471338
A73: Uber Eats | B73: =SUMIF(Angela_2026_Chase1117_Activity_!$G$2:$G$1368,$A73,Angela_2026_Chase1117_Activity_!$D$2:$D$1368) -> -2130.44 | C73: =B73/$B$8 -> 0.0094375822
A74: Subtotal — Brands & Services | B74: =SUM(B66:B73) -> -43519.94 | C74: =SUM(C66:C73) -> 0.19278788
A75: Bank & Admin
A76: Bank Fees | B76: =SUMIF(Angela_2026_Chase1117_Activity_!$G$2:$G$1368,$A76,Angela_2026_Chase1117_Activity_!$D$2:$D$1368) -> -69.12 | C76: =B76/$B$8 -> 0.00030619294
A77: Checks Paid | B77: =SUMIF(Angela_2026_Chase1117_Activity_!$G$2:$G$1368,$A77,Angela_2026_Chase1117_Activity_!$D$2:$D$1368) -> -3400 | C77: =B77/$B$8 -> 0.015061574
A78: Deposit | B78: =SUMIF(Angela_2026_Chase1117_Activity_!$G$2:$G$1368,$A78,Angela_2026_Chase1117_Activity_!$D$2:$D$1368) -> 5360.27 | C78: =B78/$B$8 -> -0.023745324
A79: Withdrawal | B79: =SUMIF(Angela_2026_Chase1117_Activity_!$G$2:$G$1368,$A79,Angela_2026_Chase1117_Activity_!$D$2:$D$1368) -> -20081.93 | C79: =B79/$B$8 -> 0.088960433
A80: Subtotal — Bank & Admin | B80: =SUM(B76:B79) -> -18190.78 | C80: =SUM(C76:C79) -> 0.080582876
A81: Donation
A82: Donation | B82: =SUMIF(Angela_2026_Chase1117_Activity_!$G$2:$G$1368,$A82,Angela_2026_Chase1117_Activity_!$D$2:$D$1368) -> -685 | C82: =B82/$B$8 -> 0.0030344642
A83: Subtotal — Donation | B83: =SUM(B82:B82) -> -685 | C83: =SUM(C82:C82) -> 0.0030344642
A85: NET — ALL CATEGORIES | B85: =B24+B37+B42+B49+B64+B74+B80+B83 -> -453.48

Sheet Transfers
A1: Chase Personal Banking — Angela
A2: Transfers | Jan 2, 2026 – Jul 8, 2026
A4: Category | B4: Amount | C4: # Txns
A5: Transfers (Own Accounts)
A6: Transfer from DWG Capital Group | B6: =SUMIF(Angela_2026_Chase1117_Activity_!$G$2:$G$1368,$A6,Angela_2026_Chase1117_Activity_!$D$2:$D$1368) -> 181500 | C6: =COUNTIF(Angela_2026_Chase1117_Activity_!$G$2:$G$1368,$A6) -> 51
A7: Transfer to Ava | B7: =SUMIF(Angela_2026_Chase1117_Activity_!$G$2:$G$1368,$A7,Angela_2026_Chase1117_Activity_!$D$2:$D$1368) -> -8750 | C7: =COUNTIF(Angela_2026_Chase1117_Activity_!$G$2:$G$1368,$A7) -> 13
A8: Transfer from Poseidon Asset Group | B8: =SUMIF(Angela_2026_Chase1117_Activity_!$G$2:$G$1368,$A8,Angela_2026_Chase1117_Activity_!$D$2:$D$1368) -> 31000 | C8: =COUNTIF(Angela_2026_Chase1117_Activity_!$G$2:$G$1368,$A8) -> 3
A9: Subtotal — Transfers (Own Accounts) | B9: =SUM(B6:B8) -> 203750 | C9: =SUM(C6:C8) -> 67
A10: Zelle (Person-to-Person)
A11: Zelle from Mary Margaret Trahan | B11: =SUMIF(Angela_2026_Chase1117_Activity_!$G$2:$G$1368,$A11,Angela_2026_Chase1117_Activity_!$D$2:$D$1368) -> 350 | C11: =COUNTIF(Angela_2026_Chase1117_Activity_!$G$2:$G$1368,$A11) -> 6
A12: Zelle from Rose Li | B12: =SUMIF(Angela_2026_Chase1117_Activity_!$G$2:$G$1368,$A12,Angela_2026_Chase1117_Activity_!$D$2:$D$1368) -> 1350 | C12: =COUNTIF(Angela_2026_Chase1117_Activity_!$G$2:$G$1368,$A12) -> 3
A13: Zelle from Joe Saunders | B13: =SUMIF(Angela_2026_Chase1117_Activity_!$G$2:$G$1368,$A13,Angela_2026_Chase1117_Activity_!$D$2:$D$1368) -> 2000 | C13: =COUNTIF(Angela_2026_Chase1117_Activity_!$G$2:$G$1368,$A13) -> 4
A14: Zelle to Joe Saunders | B14: =SUMIF(Angela_2026_Chase1117_Activity_!$G$2:$G$1368,$A14,Angela_2026_Chase1117_Activity_!$D$2:$D$1368) -> -1000 | C14: =COUNTIF(Angela_2026_Chase1117_Activity_!$G$2:$G$1368,$A14) -> 1
A15: Zelle from Tanya Miller | B15: =SUMIF(Angela_2026_Chase1117_Activity_!$G$2:$G$1368,$A15,Angela_2026_Chase1117_Activity_!$D$2:$D$1368) -> 800 | C15: =COUNTIF(Angela_2026_Chase1117_Activity_!$G$2:$G$1368,$A15) -> 8
A16: Zelle to Britt Magadini | B16: =SUMIF(Angela_2026_Chase1117_Activity_!$G$2:$G$1368,$A16,Angela_2026_Chase1117_Activity_!$D$2:$D$1368) -> -1100 | C16: =COUNTIF(Angela_2026_Chase1117_Activity_!$G$2:$G$1368,$A16) -> 3
A17: Zelle from Eunice G Chang | B17: =SUMIF(Angela_2026_Chase1117_Activity_!$G$2:$G$1368,$A17,Angela_2026_Chase1117_Activity_!$D$2:$D$1368) -> 175 | C17: =COUNTIF(Angela_2026_Chase1117_Activity_!$G$2:$G$1368,$A17) -> 1
A18: Zelle from G-Eunice LLC | B18: =SUMIF(Angela_2026_Chase1117_Activity_!$G$2:$G$1368,$A18,Angela_2026_Chase1117_Activity_!$D$2:$D$1368) -> 175 | C18: =COUNTIF(Angela_2026_Chase1117_Activity_!$G$2:$G$1368,$A18) -> 1
A19: Zelle-Leelee | B19: =SUMIF(Angela_2026_Chase1117_Activity_!$G$2:$G$1368,$A19,Angela_2026_Chase1117_Activity_!$D$2:$D$1368) -> -1300 | C19: =COUNTIF(Angela_2026_Chase1117_Activity_!$G$2:$G$1368,$A19) -> 2
A20: Zelle to Natalie Cordova | B20: =SUMIF(Angela_2026_Chase1117_Activity_!$G$2:$G$1368,$A20,Angela_2026_Chase1117_Activity_!$D$2:$D$1368) -> -300 | C20: =COUNTIF(Angela_2026_Chase1117_Activity_!$G$2:$G$1368,$A20) -> 1
A21: Zelle to Shaffa | B21: =SUMIF(Angela_2026_Chase1117_Activity_!$G$2:$G$1368,$A21,Angela_2026_Chase1117_Activity_!$D$2:$D$1368) -> -300 | C21: =COUNTIF(Angela_2026_Chase1117_Activity_!$G$2:$G$1368,$A21) -> 1
A22: Subtotal — Zelle (Person-to-Person) | B22: =SUM(B11:B21) -> 850 | C22: =SUM(C11:C21) -> 31
A23: PayPal ACH
A24: PayPal ACH - RAYSTARLIGH | B24: =SUMIF(Angela_2026_Chase1117_Activity_!$G$2:$G$1368,$A24,Angela_2026_Chase1117_Activity_!$D$2:$D$1368) -> -212.86 | C24: =COUNTIF(Angela_2026_Chase1117_Activity_!$G$2:$G$1368,$A24) -> 2
A25: PayPal ACH - OTHERSIDEMI | B25: =SUMIF(Angela_2026_Chase1117_Activity_!$G$2:$G$1368,$A25,Angela_2026_Chase1117_Activity_!$D$2:$D$1368) -> -9.95 | C25: =COUNTIF(Angela_2026_Chase1117_Activity_!$G$2:$G$1368,$A25) -> 1
A26: PayPal ACH - PSYCHICMARY | B26: =SUMIF(Angela_2026_Chase1117_Activity_!$G$2:$G$1368,$A26,Angela_2026_Chase1117_Activity_!$D$2:$D$1368) -> -125 | C26: =COUNTIF(Angela_2026_Chase1117_Activity_!$G$2:$G$1368,$A26) -> 1
A27: Subtotal — PayPal ACH | B27: =SUM(B24:B26) -> -347.81 | C27: =SUM(C24:C26) -> 4
A29: TOTAL — ALL TRANSFERS | B29: =B9+B22+B27 -> 204252.19 | C29: =C9+C22+C27 -> 102

Sheet Transaction Details
A1: Chase Personal Banking — Angela
A2: Transaction Detail | Jan 2, 2026 – Jul 8, 2026
A4: Date | B4: Merchant / Description | C4: Category | D4: Amount
A5: =Angela_2026_Chase1117_Activity_!B2 -> 46211 | B5: =Angela_2026_Chase1117_Activity_!C2 -> POS DEBIT UBER * EATS PENDING SAN FRANCISC CA | C5: =Angela_2026_Chase1117_Activity_!G2 -> Uber Eats | D5: =Angela_2026_Chase1117_Activity_!D2 -> -20.54
A6: =Angela_2026_Chase1117_Activity_!B3 -> 46211 | B6: =Angela_2026_Chase1117_Activity_!C3 -> POS DEBIT 6DAYWEIGHT* 6DAYWEIGHT +18187829038 CA 0089 | C6: =Angela_2026_Chase1117_Activity_!G3 -> Personal - Health | D6: =Angela_2026_Chase1117_Activity_!D3 -> -395
A7: =Angela_2026_Chase1117_Activity_!B4 -> 46211 | B7: =Angela_2026_Chase1117_Activity_!C4 -> POS DEBIT Prime Video Channels amzn.com/bil WA 0360 | C7: =Angela_2026_Chase1117_Activity_!G4 -> Amazon | D7: =Angela_2026_Chase1117_Activity_!D4 -> -15.99
A8: =Angela_2026_Chase1117_Activity_!B5 -> 46211 | B8: =Angela_2026_Chase1117_Activity_!C5 -> POS DEBIT Amazon Tips Amzn.com/bil WA 0360 | C8: =Angela_2026_Chase1117_Activity_!G5 -> Amazon | D8: =Angela_2026_Chase1117_Activity_!D5 -> -15
A9: =Angela_2026_Chase1117_Activity_!B6 -> 46210 | B9: =Angela_2026_Chase1117_Activity_!C6 -> UBER * EATS PENDIN SAN FRANCISCO CA148376 07/07 | C9: =Angela_2026_Chase1117_Activity_!G6 -> Uber Eats | D9: =Angela_2026_Chase1117_Activity_!D6 -> -27.55
A10: =Angela_2026_Chase1117_Activity_!B7 -> 46210 | B10: =Angela_2026_Chase1117_Activity_!C7 -> WITHDRAWAL 07/07 | C10: =Angela_2026_Chase1117_Activity_!G7 -> Withdrawal | D10: =Angela_2026_Chase1117_Activity_!D7 -> -5000
A11: =Angela_2026_Chase1117_Activity_!B8 -> 46210 | B11: =Angela_2026_Chase1117_Activity_!C8 -> AMAZON RETA* XR6945C WWW.AMAZON.CO WA 07/07 | C11: =Angela_2026_Chase1117_Activity_!G8 -> Amazon | D11: =Angela_2026_Chase1117_Activity_!D8 -> -25.62
A12: =Angela_2026_Chase1117_Activity_!B9 -> 46210 | B12: =Angela_2026_Chase1117_Activity_!C9 -> SP VALASTA LLC VALASTA.NET SC 07/06 | C12: =Angela_2026_Chase1117_Activity_!G9 -> Personal - Health | D12: =Angela_2026_Chase1117_Activity_!D9 -> -430.03
A13: =Angela_2026_Chase1117_Activity_!B10 -> 46210 | B13: =Angela_2026_Chase1117_Activity_!C10 -> GRANDVIEW CLEANERS LOS ANGELES CA 07/06 | C13: =Angela_2026_Chase1117_Activity_!G10 -> Personal - Clothing | D13: =Angela_2026_Chase1117_Activity_!D10 -> -133
A14: =Angela_2026_Chase1117_Activity_!B11 -> 46210 | B14: =Angela_2026_Chase1117_Activity_!C11 -> Amazon Tips*SA10C2A4 Amzn.com/bill WA 07/06 | C14: =Angela_2026_Chase1117_Activity_!G11 -> Amazon | D14: =Angela_2026_Chase1117_Activity_!D11 -> -30
A15: =Angela_2026_Chase1117_Activity_!B12 -> 46210 | B15: =Angela_2026_Chase1117_Activity_!C12 -> AMAZON RETA* WC81L6V WWW.AMAZON.CO WA 07/06 | C15: =Angela_2026_Chase1117_Activity_!G12 -> Amazon | D15: =Angela_2026_Chase1117_Activity_!D12 -> -11.75
A16: =Angela_2026_Chase1117_Activity_!B13 -> 46210 | B16: =Angela_2026_Chase1117_Activity_!C13 -> AMAZON RETA* TR3I78I WWW.AMAZON.CO WA 07/07 | C16: =Angela_2026_Chase1117_Activity_!G13 -> Amazon | D16: =Angela_2026_Chase1117_Activity_!D13 -> -7.75
... A1371: =Angela_2026_Chase1117_Activity_!B1368 -> 46024 | B1371: =Angela_2026_Chase1117_Activity_!C1368 -> Online Transfer from CHK ...1168 transaction#: 27551465996 | C1371: =Angela_2026_Chase1117_Activity_!G1368 -> Transfer from DWG Capital Group | D1371: =Angela_2026_Chase1117_Activity_!D1368 -> 5000

Sheet Monthly Breakdown
A1: Chase Personal Banking — Angela
A2: Monthly Breakdown by Category | Jan 2026 – Jul 2026
A4: Category | B4: =DATE(2026,1,1) -> 46023 | C4: =EDATE(B4,1) -> 46054 | D4: =EDATE(C4,1) -> 46082 | E4: =EDATE(D4,1) -> 46113 | F4: =EDATE(E4,1) -> 46143 | G4: =EDATE(F4,1) -> 46174 | H4: =EDATE(G4,1) -> 46204 | I4: Total
A5: Transfer from DWG Capital Group | B5: =SUMIFS(Angela_2026_Chase1117_Activity_!$D$2:$D$1368,Angela_2026_Chase1117_Activity_!$B$2:$B$1368,">="&B$4,Angela_2026_Chase1117_Activity_!$B$2:$B$1368,"<="&EOMONTH(B$4,0),Angela_2026_Chase1117_Activity_!$G$2:$G$1368,$A5) -> 32000 | C5: =SUMIFS(Angela_2026_Chase1117_Activity_!$D$2:$D$1368,Angela_2026_Chase1117_Activity_!$B$2:$B$1368,">="&C$4,Angela_2026_Chase1117_Activity_!$B$2:$B$1368,"<="&EOMONTH(C$4,0),Angela_2026_Chase1117_Activity_!$G$2:$G$1368,$A5) -> 22000 | D5: =SUMIFS(Angela_2026_Chase1117_Activity_!$D$2:$D$1368,Angela_2026_Chase1117_Activity_!$B$2:$B$1368,">="&D$4,Angela_2026_Chase1117_Activity_!$B$2:$B$1368,"<="&EOMONTH(D$4,0),Angela_2026_Chase1117_Activity_!$G$2:$G$1368,$A5) -> 41000 | E5: =SUMIFS(Angela_2026_Chase1117_Activity_!$D$2:$D$1368,Angela_2026_Chase1117_Activity_!$B$2:$B$1368,">="&E$4,Angela_2026_Chase1117_Activity_!$B$2:$B$1368,"<="&EOMONTH(E$4,0),Angela_2026_Chase1117_Activity_!$G$2:$G$1368,$A5) -> 20000 | F5: =SUMIFS(Angela_2026_Chase1117_Activity_!$D$2:$D$1368,Angela_2026_Chase1117_Activity_!$B$2:$B$1368,">="&F$4,Angela_2026_Chase1117_Activity_!$B$2:$B$1368,"<="&EOMONTH(F$4,0),Angela_2026_Chase1117_Activity_!$G$2:$G$1368,$A5) -> 28000 | G5: =SUMIFS(Angela_2026_Chase1117_Activity_!$D$2:$D$1368,Angela_2026_Chase1117_Activity_!$B$2:$B$1368,">="&G$4,Angela_2026_Chase1117_Activity_!$B$2:$B$1368,"<="&EOMONTH(G$4,0),Angela_2026_Chase1117_Activity_!$G$2:$G$1368,$A5) -> 33500 | H5: =SUMIFS(Angela_2026_Chase1117_Activity_!$D$2:$D$1368,Angela_2026_Chase1117_Activity_!$B$2:$B$1368,">="&H$4,Angela_2026_Chase1117_Activity_!$B$2:$B$1368,"<="&EOMONTH(H$4,0),Angela_2026_Chase1117_Activity_!$G$2:$G$1368,$A5) -> 5000 | I5: =SUM(B5:H5) -> 181500
A6: Transfer to Ava | B6: =SUMIFS(Angela_2026_Chase1117_Activity_!$D$2:$D$1368,Angela_2026_Chase1117_Activity_!$B$2:$B$1368,">="&B$4,Angela_2026_Chase1117_Activity_!$B$2:$B$1368,"<="&EOMONTH(B$4,0),Angela_2026_Chase1117_Activity_!$G$2:$G$1368,$A6) -> -500 | C6: =SUMIFS(Angela_2026_Chase1117_Activity_!$D$2:$D$1368,Angela_2026_Chase1117_Activity_!$B$2:$B$1368,">="&C$4,Angela_2026_Chase1117_Activity_!$B$2:$B$1368,"<="&EOMONTH(C$4,0),Angela_2026_Chase1117_Activity_!$G$2:$G$1368,$A6) -> -350 | D6: =SUMIFS(Angela_2026_Chase1117_Activity_!$D$2:$D$1368,Angela_2026_Chase1117_Activity_!$B$2:$B$1368,">="&D$4,Angela_2026_Chase1117_Activity_!$B$2:$B$1368,"<="&EOMONTH(D$4,0),Angela_2026_Chase1117_Activity_!$G$2:$G$1368,$A6) -> -3600 | E6: =SUMIFS(Angela_2026_Chase1117_Activity_!$D$2:$D$1368,Angela_2026_Chase1117_Activity_!$B$2:$B$1368,">="&E$4,Angela_2026_Chase1117_Activity_!$B$2:$B$1368,"<="&EOMONTH(E$4,0),Angela_2026_Chase1117_Activity_!$G$2:$G$1368,$A6) -> -2500 | F6: =SUMIFS(Angela_2026_Chase1117_Activity_!$D$2:$D$1368,Angela_2026_Chase1117_Activity_!$B$2:$B$1368,">="&F$4,Angela_2026_Chase1117_Activity_!$B$2:$B$1368,"<="&EOMONTH(F$4,0),Angela_2026_Chase1117_Activity_!$G$2:$G$1368,$A6) -> -600 | G6: =SUMIFS(Angela_2026_Chase1117_Activity_!$D$2:$D$1368,Angela_2026_Chase1117_Activity_!$B$2:$B$1368,">="&G$4,Angela_2026_Chase1117_Activity_!$B$2:$B$1368,"<="&EOMONTH(G$4,0),Angela_2026_Chase1117_Activity_!$G$2:$G$1368,$A6) -> -1200 | H6: =SUMIFS(Angela_2026_Chase1117_Activity_!$D$2:$D$1368,Angela_2026_Chase1117_Activity_!$B$2:$B$1368,">="&H$4,Angela_2026_Chase1117_Activity_!$B$2:$B$1368,"<="&EOMONTH(H$4,0),Angela_2026_Chase1117_Activity_!$G$2:$G$1368,$A6) -> 0 | I6: =SUM(B6:H6) -> -8750
A7: Transfer from Poseidon Asset Group | B7: =SUMIFS(Angela_2026_Chase1117_Activity_!$D$2:$D$1368,Angela_2026_Chase1117_Activity_!$B$2:$B$1368,">="&B$4,Angela_2026_Chase1117_Activity_!$B$2:$B$1368,"<="&EOMONTH(B$4,0),Angela_2026_Chase1117_Activity_!$G$2:$G$1368,$A7) -> 0 | C7: =SUMIFS(Angela_2026_Chase1117_Activity_!$D$2:$D$1368,Angela_2026_Chase1117_Activity_!$B$2:$B$1368,">="&C$4,Angela_2026_Chase1117_Activity_!$B$2:$B$1368,"<="&EOMONTH(C$4,0),Angela_2026_Chase1117_Activity_!$G$2:$G$1368,$A7) -> 30000 | D7: =SUMIFS(Angela_2026_Chase1117_Activity_!$D$2:$D$1368,Angela_2026_Chase1117_Activity_!$B$2:$B$1368,">="&D$4,Angela_2026_Chase1117_Activity_!$B$2:$B$1368,"<="&EOMONTH(D$4,0),Angela_2026_Chase1117_Activity_!$G$2:$G$1368,$A7) -> 0 | E7: =SUMIFS(Angela_2026_Chase1117_Activity_!$D$2:$D$1368,Angela_2026_Chase1117_Activity_!$B$2:$B$1368,">="&E$4,Angela_2026_Chase1117_Activity_!$B$2:$B$1368,"<="&EOMONTH(E$4,0),Angela_2026_Chase1117_Activity_!$G$2:$G$1368,$A7) -> 0 | F7: =SUMIFS(Angela_2026_Chase1117_Activity_!$D$2:$D$1368,Angela_2026_Chase1117_Activity_!$B$2:$B$1368,">="&F$4,Angela_2026_Chase1117_Activity_!$B$2:$B$1368,"<="&EOMONTH(F$4,0),Angela_2026_Chase1117_Activity_!$G$2:$G$1368,$A7) -> 0 | G7: =SUMIFS(Angela_2026_Chase1117_Activity_!$D$2:$D$1368,Angela_2026_Chase1117_Activity_!$B$2:$B$1368,">="&G$4,Angela_2026_Chase1117_Activity_!$B$2:$B$1368,"<="&EOMONTH(G$4,0),Angela_2026_Chase1117_Activity_!$G$2:$G$1368,$A7) -> 1000 | H7: =SUMIFS(Angela_2026_Chase1117_Activity_!$D$2:$D$1368,Angela_2026_Chase1117_Activity_!$B$2:$B$1368,">="&H$4,Angela_2026_Chase1117_Activity_!$B$2:$B$1368,"<="&EOMONTH(H$4,0),Angela_2026_Chase1117_Activity_!$G$2:$G$1368,$A7) -> 0 | I7: =SUM(B7:H7) -> 31000
A8: Zelle from Mary Margaret Trahan | B8: =SUMIFS(Angela_2026_Chase1117_Activity_!$D$2:$D$1368,Angela_2026_Chase1117_Activity_!$B$2:$B$1368,">="&B$4,Angela_2026_Chase1117_Activity_!$B$2:$B$1368,"<="&EOMONTH(B$4,0),Angela_2026_Chase1117_Activity_!$G$2:$G$1368,$A8) -> 0 | C8: =SUMIFS(Angela_2026_Chase1117_Activity_!$D$2:$D$1368,Angela_2026_Chase1117_Activity_!$B$2:$B$1368,">="&C$4,Angela_2026_Chase1117_Activity_!$B$2:$B$1368,"<="&EOMONTH(C$4,0),Angela_2026_Chase1117_Activity_!$G$2:$G$1368,$A8) -> 150 | D8: =SUMIFS(Angela_2026_Chase1117_Activity_!$D$2:$D$1368,Angela_2026_Chase1117_Activity_!$B$2:$B$1368,">="&D$4,Angela_2026_Chase1117_Activity_!$B$2:$B$1368,"<="&EOMONTH(D$4,0),Angela_2026_Chase1117_Activity_!$G$2:$G$1368,$A8) -> 0 | E8: =SUMIFS(Angela_2026_Chase1117_Activity_!$D$2:$D$1368,Angela_2026_Chase1117_Activity_!$B$2:$B$1368,">="&E$4,Angela_2026_Chase1117_Activity_!$B$2:$B$1368,"<="&EOMONTH(E$4,0),Angela_2026_Chase1117_Activity_!$G$2:$G$1368,$A8) -> 0 | F8: =SUMIFS(Angela_2026_Chase1117_Activity_!$D$2:$D$1368,Angela_2026_Chase1117_Activity_!$B$2:$B$1368,">="&F$4,Angela_2026_Chase1117_Activity_!$B$2:$B$1368,"<="&EOMONTH(F$4,0),Angela_2026_Chase1117_Activity_!$G$2:$G$1368,$A8) -> 75 | G8: =SUMIFS(Angela_2026_Chase1117_Activity_!$D$2:$D$1368,Angela_2026_Chase1117_Activity_!$B$2:$B$1368,">="&G$4,Angela_2026_Chase1117_Activity_!$B$2:$B$1368,"<="&EOMONTH(G$4,0),Angela_2026_Chase1117_Activity_!$G$2:$G$1368,$A8) -> 100 | H8: =SUMIFS(Angela_2026_Chase1117_Activity_!$D$2:$D$1368,Angela_2026_Chase1117_Activity_!$B$2:$B$1368,">="&H$4,Angela_2026_Chase1117_Activity_!$B$2:$B$1368,"<="&EOMONTH(H$4,0),Angela_2026_Chase1117_Activity_!$G$2:$G$1368,$A8) -> 25 | I8: =SUM(B8:H8) -> 350
A9: Zelle from Rose Li | B9: =SUMIFS(Angela_2026_Chase1117_Activity_!$D$2:$D$1368,Angela_2026_Chase1117_Activity_!$B$2:$B$1368,">="&B$4,Angela_2026_Chase1117_Activity_!$B$2:$B$1368,"<="&EOMONTH(B$4,0),Angela_2026_Chase1117_Activity_!$G$2:$G$1368,$A9) -> 0 | C9: =SUMIFS(Angela_2026_Chase1117_Activity_!$D$2:$D$1368,Angela_2026_Chase1117_Activity_!$B$2:$B$1368,">="&C$4,Angela_2026_Chase1117_Activity_!$B$2:$B$1368,"<="&EOMONTH(C$4,0),Angela_2026_Chase1117_Activity_!$G$2:$G$1368,$A9) -> 0 | D9: =SUMIFS(Angela_2026_Chase1117_Activity_!$D$2:$D$1368,Angela_2026_Chase1117_Activity_!$B$2:$B$1368,">="&D$4,Angela_2026_Chase1117_Activity_!$B$2:$B$1368,"<="&EOMONTH(D$4,0),Angela_2026_Chase1117_Activity_!$G$2:$G$1368,$A9) -> 450 | E9: =SUMIFS(Angela_2026_Chase1117_Activity_!$D$2:$D$1368,Angela_2026_Chase1117_Activity_!$B$2:$B$1368,">="&E$4,Angela_2026_Chase1117_Activity_!$B$2:$B$1368,"<="&EOMONTH(E$4,0),Angela_2026_Chase1117_Activity_!$G$2:$G$1368,$A9) -> 0 | F9: =SUMIFS(Angela_2026_Chase1117_Activity_!$D$2:$D$1368,Angela_2026_Chase1117_Activity_!$B$2:$B$1368,">="&F$4,Angela_2026_Chase1117_Activity_!$B$2:$B$1368,"<="&EOMONTH(F$4,0),Angela_2026_Chase1117_Activity_!$G$2:$G$1368,$A9) -> 0 | G9: =SUMIFS(Angela_2026_Chase1117_Activity_!$D$2:$D$1368,Angela_2026_Chase1117_Activity_!$B$2:$B$1368,">="&G$4,Angela_2026_Chase1117_Activity_!$B$2:$B$1368,"<="&EOMONTH(G$4,0),Angela_2026_Chase1117_Activity_!$G$2:$G$1368,$A9) -> 450 | H9: =SUMIFS(Angela_2026_Chase1117_Activity_!$D$2:$D$1368,Angela_2026_Chase1117_Activity_!$B$2:$B$1368,">="&H$4,Angela_2026_Chase1117_Activity_!$B$2:$B$1368,"<="&EOMONTH(H$4,0),Angela_2026_Chase1117_Activity_!$G$2:$G$1368,$A9) -> 450 | I9: =SUM(B9:H9) -> 1350
A10: Zelle from Joe Saunders | B10: =SUMIFS(Angela_2026_Chase1117_Activity_!$D$2:$D$1368,Angela_2026_Chase1117_Activity_!$B$2:$B$1368,">="&B$4,Angela_2026_Chase1117_Activity_!$B$2:$B$1368,"<="&EOMONTH(B$4,0),Angela_2026_Chase1117_Activity_!$G$2:$G$1368,$A10) -> 0 | C10: =SUMIFS(Angela_2026_Chase1117_Activity_!$D$2:$D$1368,Angela_2026_Chase1117_Activity_!$B$2:$B$1368,">="&C$4,Angela_2026_Chase1117_Activity_!$B$2:$B$1368,"<="&EOMONTH(C$4,0),Angela_2026_Chase1117_Activity_!$G$2:$G$1368,$A10) -> 0 | D10: =SUMIFS(Angela_2026_Chase1117_Activity_!$D$2:$D$1368,Angela_2026_Chase1117_Activity_!$B$2:$B$1368,">="&D$4,Angela_2026_Chase1117_Activity_!$B$2:$B$1368,"<="&EOMONTH(D$4,0),Angela_2026_Chase1117_Activity_!$G$2:$G$1368,$A10) -> 0 | E10: =SUMIFS(Angela_2026_Chase1117_Activity_!$D$2:$D$1368,Angela_2026_Chase1117_Activity_!$B$2:$B$1368,">="&E$4,Angela_2026_Chase1117_Activity_!$B$2:$B$1368,"<="&EOMONTH(E$4,0),Angela_2026_Chase1117_Activity_!$G$2:$G$1368,$A10) -> 500 | F10: =SUMIFS(Angela_2026_Chase1117_Activity_!$D$2:$D$1368,Angela_2026_Chase1117_Activity_!$B$2:$B$1368,">="&F$4,Angela_2026_Chase1117_Activity_!$B$2:$B$1368,"<="&EOMONTH(F$4,0),Angela_2026_Chase1117_Activity_!$G$2:$G$1368,$A10) -> 500 | G10: =SUMIFS(Angela_2026_Chase1117_Activity_!$D$2:$D$1368,Angela_2026_Chase1117_Activity_!$B$2:$B$1368,">="&G$4,Angela_2026_Chase1117_Activity_!$B$2:$B$1368,"<="&EOMONTH(G$4,0),Angela_2026_Chase1117_Activity_!$G$2:$G$1368,$A10) -> 1000 | H10: =SUMIFS(Angela_2026_Chase1117_Activity_!$D$2:$D$1368,Angela_2026_Chase1117_Activity_!$B$2:$B$1368,">="&H$4,Angela_2026_Chase1117_Activity_!$B$2:$B$1368,"<="&EOMONTH(H$4,0),Angela_2026_Chase1117_Activity_!$G$2:$G$1368,$A10) -> 0 | I10: =SUM(B10:H10) -> 2000
A11: Zelle to Joe Saunders | B11: =SUMIFS(Angela_2026_Chase1117_Activity_!$D$2:$D$1368,Angela_2026_Chase1117_Activity_!$B$2:$B$1368,">="&B$4,Angela_2026_Chase1117_Activity_!$B$2:$B$1368,"<="&EOMONTH(B$4,0),Angela_2026_Chase1117_Activity_!$G$2:$G$1368,$A11) -> 0 | C11: =SUMIFS(Angela_2026_Chase1117_Activity_!$D$2:$D$1368,Angela_2026_Chase1117_Activity_!$B$2:$B$1368,">="&C$4,Angela_2026_Chase1117_Activity_!$B$2:$B$1368,"<="&EOMONTH(C$4,0),Angela_2026_Chase1117_Activity_!$G$2:$G$1368,$A11) -> 0 | D11: =SUMIFS(Angela_2026_Chase1117_Activity_!$D$2:$D$1368,Angela_2026_Chase1117_Activity_!$B$2:$B$1368,">="&D$4,Angela_2026_Chase1117_Activity_!$B$2:$B$1368,"<="&EOMONTH(D$4,0),Angela_2026_Chase1117_Activity_!$G$2:$G$1368,$A11) -> 0 | E11: =SUMIFS(Angela_2026_Chase1117_Activity_!$D$2:$D$1368,Angela_2026_Chase1117_Activity_!$B$2:$B$1368,">="&E$4,Angela_2026_Chase1117_Activity_!$B$2:$B$1368,"<="&EOMONTH(E$4,0),Angela_2026_Chase1117_Activity_!$G$2:$G$1368,$A11) -> 0 | F11: =SUMIFS(Angela_2026_Chase1117_Activity_!$D$2:$D$1368,Angela_2026_Chase1117_Activity_!$B$2:$B$1368,">="&F$4,Angela_2026_Chase1117_Activity_!$B$2:$B$1368,"<="&EOMONTH(F$4,0),Angela_2026_Chase1117_Activity_!$G$2:$G$1368,$A11) -> 0 | G11: =SUMIFS(Angela_2026_Chase1117_Activity_!$D$2:$D$1368,Angela_2026_Chase1117_Activity_!$B$2:$B$1368,">="&G$4,Angela_2026_Chase1117_Activity_!$B$2:$B$1368,"<="&EOMONTH(G$4,0),Angela_2026_Chase1117_Activity_!$G$2:$G$1368,$A11) -> -1000 | H11: =SUMIFS(Angela_2026_Chase1117_Activity_!$D$2:$D$1368,Angela_2026_Chase1117_Activity_!$B$2:$B$1368,">="&H$4,Angela_2026_Chase1117_Activity_!$B$2:$B$1368,"<="&EOMONTH(H$4,0),Angela_2026_Chase1117_Activity_!$G$2:$G$1368,$A11) -> 0 | I11: =SUM(B11:H11) -> -1000
A12: Zelle from Tanya Miller | B12: =SUMIFS(Angela_2026_Chase1117_Activity_!$D$2:$D$1368,Angela_2026_Chase1117_Activity_!$B$2:$B$1368,">="&B$4,Angela_2026_Chase1117_Activity_!$B$2:$B$1368,"<="&EOMONTH(B$4,0),Angela_2026_Chase1117_Activity_!$G$2:$G$1368,$A12) -> 0 | C12: =SUMIFS(Angela_2026_Chase1117_Activity_!$D$2:$D$1368,Angela_2026_Chase1117_Activity_!$B$2:$B$1368,">="&C$4,Angela_2026_Chase1117_Activity_!$B$2:$B$1368,"<="&EOMONTH(C$4,0),Angela_2026_Chase1117_Activity_!$G$2:$G$1368,$A12) -> 200 | D12: =SUMIFS(Angela_2026_Chase1117_Activity_!$D$2:$D$1368,Angela_2026_Chase1117_Activity_!$B$2:$B$1368,">="&D$4,Angela_2026_Chase1117_Activity_!$B$2:$B$1368,"<="&EOMONTH(D$4,0),Angela_2026_Chase1117_Activity_!$G$2:$G$1368,$A12) -> 200 | E12: =SUMIFS(Angela_2026_Chase1117_Activity_!$D$2:$D$1368,Angela_2026_Chase1117_Activity_!$B$2:$B$1368,">="&E$4,Angela_2026_Chase1117_Activity_!$B$2:$B$1368,"<="&EOMONTH(E$4,0),Angela_2026_Chase1117_Activity_!$G$2:$G$1368,$A12) -> 100 | F12: =SUMIFS(Angela_2026_Chase1117_Activity_!$D$2:$D$1368,Angela_2026_Chase1117_Activity_!$B$2:$B$1368,">="&F$4,Angela_2026_Chase1117_Activity_!$B$2:$B$1368,"<="&EOMONTH(F$4,0),Angela_2026_Chase1117_Activity_!$G$2:$G$1368,$A12) -> 100 | G12: =SUMIFS(Angela_2026_Chase1117_Activity_!$D$2:$D$1368,Angela_2026_Chase1117_Activity_!$B$2:$B$1368,">="&G$4,Angela_2026_Chase1117_Activity_!$B$2:$B$1368,"<="&EOMONTH(G$4,0),Angela_2026_Chase1117_Activity_!$G$2:$G$1368,$A12) -> 200 | H12: =SUMIFS(Angela_2026_Chase1117_Activity_!$D$2:$D$1368,Angela_2026_Chase1117_Activity_!$B$2:$B$1368,">="&H$4,Angela_2026_Chase1117_Activity_!$B$2:$B$1368,"<="&EOMONTH(H$4,0),Angela_2026_Chase1117_Activity_!$G$2:$G$1368,$A12) -> 0 | I12: =SUM(B12:H12) -> 800
A13: Zelle to Britt Magadini | B13: =SUMIFS(Angela_2026_Chase1117_Activity_!$D$2:$D$1368,Angela_2026_Chase1117_Activity_!$B$2:$B$1368,">="&B$4,Angela_2026_Chase1117_Activity_!$B$2:$B$1368,"<="&EOMONTH(B$4,0),Angela_2026_Chase1117_Activity_!$G$2:$G$1368,$A13) -> 0 | C13: =SUMIFS(Angela_2026_Chase1117_Activity_!$D$2:$D$1368,Angela_2026_Chase1117_Activity_!$B$2:$B$1368,">="&C$4,Angela_2026_Chase1117_Activity_!$B$2:$B$1368,"<="&EOMONTH(C$4,0),Angela_2026_Chase1117_Activity_!$G$2:$G$1368,$A13) -> -500 | D13: =SUMIFS(Angela_2026_Chase1117_Activity_!$D$2:$D$1368,Angela_2026_Chase1117_Activity_!$B$2:$B$1368,">="&D$4,Angela_2026_Chase1117_Activity_!$B$2:$B$1368,"<="&EOMONTH(D$4,0),Angela_2026_Chase1117_Activity_!$G$2:$G$1368,$A13) -> 0 | E13: =SUMIFS(Angela_2026_Chase1117_Activity_!$D$2:$D$1368,Angela_2026_Chase1117_Activity_!$B$2:$B$1368,">="&E$4,Angela_2026_Chase1117_Activity_!$B$2:$B$1368,"<="&EOMONTH(E$4,0),Angela_2026_Chase1117_Activity_!$G$2:$G$1368,$A13) -> -300 | F13: =SUMIFS(Angela_2026_Chase1117_Activity_!$D$2:$D$1368,Angela_2026_Chase1117_Activity_!$B$2:$B$1368,">="&F$4,Angela_2026_Chase1117_Activity_!$B$2:$B$1368,"<="&EOMONTH(F$4,0),Angela_2026_Chase1117_Activity_!$G$2:$G$1368,$A13) -> 0 | G13: =SUMIFS(Angela_2026_Chase1117_Activity_!$D$2:$D$1368,Angela_2026_Chase1117_Activity_!$B$2:$B$1368,">="&G$4,Angela_2026_Chase1117_Activity_!$B$2:$B$1368,"<="&EOMONTH(G$4,0),Angela_2026_Chase1117_Activity_!$G$2:$G$1368,$A13) -> -300 | H13: =SUMIFS(Angela_2026_Chase1117_Activity_!$D$2:$D$1368,Angela_2026_Chase1117_Activity_!$B$2:$B$1368,">="&H$4,Angela_2026_Chase1117_Activity_!$B$2:$B$1368,"<="&EOMONTH(H$4,0),Angela_2026_Chase1117_Activity_!$G$2:$G$1368,$A13) -> 0 | I13: =SUM(B13:H13) -> -1100
A14: Zelle from Eunice G Chang | B14: =SUMIFS(Angela_2026_Chase1117_Activity_!$D$2:$D$1368,Angela_2026_Chase1117_Activity_!$B$2:$B$1368,">="&B$4,Angela_2026_Chase1117_Activity_!$B$2:$B$1368,"<="&EOMONTH(B$4,0),Angela_2026_Chase1117_Activity_!$G$2:$G$1368,$A14) -> 0 | C14: =SUMIFS(Angela_2026_Chase1117_Activity_!$D$2:$D$1368,Angela_2026_Chase1117_Activity_!$B$2:$B$1368,">="&C$4,Angela_2026_Chase1117_Activity_!$B$2:$B$1368,"<="&EOMONTH(C$4,0),Angela_2026_Chase1117_Activity_!$G$2:$G$1368,$A14) -> 0 | D14: =SUMIFS(Angela_2026_Chase1117_Activity_!$D$2:$D$1368,Angela_2026_Chase1117_Activity_!$B$2:$B$1368,">="&D$4,Angela_2026_Chase1117_Activity_!$B$2:$B$1368,"<="&EOMONTH(D$4,0),Angela_2026_Chase1117_Activity_!$G$2:$G$1368,$A14) -> 0 | E14: =SUMIFS(Angela_2026_Chase1117_Activity_!$D$2:$D$1368,Angela_2026_Chase1117_Activity_!$B$2:$B$1368,">="&E$4,Angela_2026_Chase1117_Activity_!$B$2:$B$1368,"<="&EOMONTH(E$4,0),Angela_2026_Chase1117_Activity_!$G$2:$G$1368,$A14) -> 0 | F14: =SUMIFS(Angela_2026_Chase1117_Activity_!$D$2:$D$1368,Angela_2026_Chase1117_Activity_!$B$2:$B$1368,">="&F$4,Angela_2026_Chase1117_Activity_!$B$2:$B$1368,"<="&EOMONTH(F$4,0),Angela_2026_Chase1117_Activity_!$G$2:$G$1368,$A14) -> 175 | G14: =SUMIFS(Angela_2026_Chase1117_Activity_!$D$2:$D$1368,Angela_2026_Chase1117_Activity_!$B$2:$B$1368,">="&G$4,Angela_2026_Chase1117_Activity_!$B$2:$B$1368,"<="&EOMONTH(G$4,0),Angela_2026_Chase1117_Activity_!$G$2:$G$1368,$A14) -> 0 | H14: =SUMIFS(Angela_2026_Chase1117_Activity_!$D$2:$D$1368,Angela_2026_Chase1117_Activity_!$B$2:$B$1368,">="&H$4,Angela_2026_Chase1117_Activity_!$B$2:$B$1368,"<="&EOMONTH(H$4,0),Angela_2026_Chase1117_Activity_!$G$2:$G$1368,$A14) -> 0 | I14: =SUM(B14:H14) -> 175
A15: Zelle from G-Eunice LLC | B15: =SUMIFS(Angela_2026_Chase1117_Activity_!$D$2:$D$1368,Angela_2026_Chase1117_Activity_!$B$2:$B$1368,">="&B$4,Angela_2026_Chase1117_Activity_!$B$2:$B$1368,"<="&EOMONTH(B$4,0),Angela_2026_Chase1117_Activity_!$G$2:$G$1368,$A15) -> 0 | C15: =SUMIFS(Angela_2026_Chase1117_Activity_!$D$2:$D$1368,Angela_2026_Chase1117_Activity_!$B$2:$B$1368,">="&C$4,Angela_2026_Chase1117_Activity_!$B$2:$B$1368,"<="&EOMONTH(C$4,0),Angela_2026_Chase1117_Activity_!$G$2:$G$1368,$A15) -> 175 | D15: =SUMIFS(Angela_2026_Chase1117_Activity_!$D$2:$D$1368,Angela_2026_Chase1117_Activity_!$B$2:$B$1368,">="&D$4,Angela_2026_Chase1117_Activity_!$B$2:$B$1368,"<="&EOMONTH(D$4,0),Angela_2026_Chase1117_Activity_!$G$2:$G$1368,$A15) -> 0 | E15: =SUMIFS(Angela_2026_Chase1117_Activity_!$D$2:$D$1368,Angela_2026_Chase1117_Activity_!$B$2:$B$1368,">="&E$4,Angela_2026_Chase1117_Activity_!$B$2:$B$1368,"<="&EOMONTH(E$4,0),Angela_2026_Chase1117_Activity_!$G$2:$G$1368,$A15) -> 0 | F15: =SUMIFS(Angela_2026_Chase1117_Activity_!$D$2:$D$1368,Angela_2026_Chase1117_Activity_!$B$2:$B$1368,">="&F$4,Angela_2026_Chase1117_Activity_!$B$2:$B$1368,"<="&EOMONTH(F$4,0),Angela_2026_Chase1117_Activity_!$G$2:$G$1368,$A15) -> 0 | G15: =SUMIFS(Angela_2026_Chase1117_Activity_!$D$2:$D$1368,Angela_2026_Chase1117_Activity_!$B$2:$B$1368,">="&G$4,Angela_2026_Chase1117_Activity_!$B$2:$B$1368,"<="&EOMONTH(G$4,0),Angela_2026_Chase1117_Activity_!$G$2:$G$1368,$A15) -> 0 | H15: =SUMIFS(Angela_2026_Chase1117_Activity_!$D$2:$D$1368,Angela_2026_Chase1117_Activity_!$B$2:$B$1368,">="&H$4,Angela_2026_Chase1117_Activity_!$B$2:$B$1368,"<="&EOMONTH(H$4,0),Angela_2026_Chase1117_Activity_!$G$2:$G$1368,$A15) -> 0 | I15: =SUM(B15:H15) -> 175
A16: Zelle-Leelee | B16: =SUMIFS(Angela_2026_Chase1117_Activity_!$D$2:$D$1368,Angela_2026_Chase1117_Activity_!$B$2:$B$1368,">="&B$4,Angela_2026_Chase1117_Activity_!$B$2:$B$1368,"<="&EOMONTH(B$4,0),Angela_2026_Chase1117_Activity_!$G$2:$G$1368,$A16) -> -700 | C16: =SUMIFS(Angela_2026_Chase1117_Activity_!$D$2:$D$1368,Angela_2026_Chase1117_Activity_!$B$2:$B$1368,">="&C$4,Angela_2026_Chase1117_Activity_!$B$2:$B$1368,"<="&EOMONTH(C$4,0),Angela_2026_Chase1117_Activity_!$G$2:$G$1368,$A16) -> 0 | D16: =SUMIFS(Angela_2026_Chase1117_Activity_!$D$2:$D$1368,Angela_2026_Chase1117_Activity_!$B$2:$B$1368,">="&D$4,Angela_2026_Chase1117_Activity_!$B$2:$B$1368,"<="&EOMONTH(D$4,0),Angela_2026_Chase1117_Activity_!$G$2:$G$1368,$A16) -> 0 | E16: =SUMIFS(Angela_2026_Chase1117_Activity_!$D$2:$D$1368,Angela_2026_Chase1117_Activity_!$B$2:$B$1368,">="&E$4,Angela_2026_Chase1117_Activity_!$B$2:$B$1368,"<="&EOMONTH(E$4,0),Angela_2026_Chase1117_Activity_!$G$2:$G$1368,$A16) -> 0 | F16: =SUMIFS(Angela_2026_Chase1117_Activity_!$D$2:$D$1368,Angela_2026_Chase1117_Activity_!$B$2:$B$1368,">="&F$4,Angela_2026_Chase1117_Activity_!$B$2:$B$1368,"<="&EOMONTH(F$4,0),Angela_2026_Chase1117_Activity_!$G$2:$G$1368,$A16) -> -600 | G16: =SUMIFS(Angela_2026_Chase1117_Activity_!$D$2:$D$1368,Angela_2026_Chase1117_Activity_!$B$2:$B$1368,">="&G$4,Angela_2026_Chase1117_Activity_!$B$2:$B$1368,"<="&EOMONTH(G$4,0),Angela_2026_Chase1117_Activity_!$G$2:$G$1368,$A16) -> 0 | H16: =SUMIFS(Angela_2026_Chase1117_Activity_!$D$2:$D$1368,Angela_2026_Chase1117_Activity_!$B$2:$B$1368,">="&H$4,Angela_2026_Chase1117_Activity_!$B$2:$B$1368,"<="&EOMONTH(H$4,0),Angela_2026_Chase1117_Activity_!$G$2:$G$1368,$A16) -> 0 | I16: =SUM(B16:H16) -> -1300
... A52: Donation | B52: =SUMIFS(Angela_2026_Chase1117_Activity_!$D$2:$D$1368,Angela_2026_Chase1117_Activity_!$B$2:$B$1368,">="&B$4,Angela_2026_Chase1117_Activity_!$B$2:$B$1368,"<="&EOMONTH(B$4,0),Angela_2026_Chase1117_Activity_!$G$2:$G$1368,$A52) -> 0 | C52: =SUMIFS(Angela_2026_Chase1117_Activity_!$D$2:$D$1368,Angela_2026_Chase1117_Activity_!$B$2:$B$1368,">="&C$4,Angela_2026_Chase1117_Activity_!$B$2:$B$1368,"<="&EOMONTH(C$4,0),Angela_2026_Chase1117_Activity_!$G$2:$G$1368,$A52) -> -310 | D52: =SUMIFS(Angela_2026_Chase1117_Activity_!$D$2:$D$1368,Angela_2026_Chase1117_Activity_!$B$2:$B$1368,">="&D$4,Angela_2026_Chase1117_Activity_!$B$2:$B$1368,"<="&EOMONTH(D$4,0),Angela_2026_Chase1117_Activity_!$G$2:$G$1368,$A52) -> 100 | E52: =SUMIFS(Angela_2026_Chase1117_Activity_!$D$2:$D$1368,Angela_2026_Chase1117_Activity_!$B$2:$B$1368,">="&E$4,Angela_2026_Chase1117_Activity_!$B$2:$B$1368,"<="&EOMONTH(E$4,0),Angela_2026_Chase1117_Activity_!$G$2:$G$1368,$A52) -> 0 | F52: =SUMIFS(Angela_2026_Chase1117_Activity_!$D$2:$D$1368,Angela_2026_Chase1117_Activity_!$B$2:$B$1368,">="&F$4,Angela_2026_Chase1117_Activity_!$B$2:$B$1368,"<="&EOMONTH(F$4,0),Angela_2026_Chase1117_Activity_!$G$2:$G$1368,$A52) -> -295 | G52: =SUMIFS(Angela_2026_Chase1117_Activity_!$D$2:$D$1368,Angela_2026_Chase1117_Activity_!$B$2:$B$1368,">="&G$4,Angela_2026_Chase1117_Activity_!$B$2:$B$1368,"<="&EOMONTH(G$4,0),Angela_2026_Chase1117_Activity_!$G$2:$G$1368,$A52) -> -180 | H52: =SUMIFS(Angela_2026_Chase1117_Activity_!$D$2:$D$1368,Angela_2026_Chase1117_Activity_!$B$2:$B$1368,">="&H$4,Angela_2026_Chase1117_Activity_!$B$2:$B$1368,"<="&EOMONTH(H$4,0),Angela_2026_Chase1117_Activity_!$G$2:$G$1368,$A52) -> 0 | I52: =SUM(B52:H52) -> -685
A53: TOTAL — ALL CATEGORIES | B53: =SUM(B5:B52) -> 3776.99 | C53: =SUM(C5:C52) -> 4538.18 | D53: =SUM(D5:D52) -> 631.4 | E53: =SUM(E5:E52) -> -8763.51 | F53: =SUM(F5:F52) -> -1282.76 | G53: =SUM(G5:G52) -> 5118.09 | H53: =SUM(H5:H52) -> -4471.87 | I53: =SUM(I5:I52) -> -453.48

Sheet Category Rules
A1: Keyword | B1: Category
A2: DOORDASH | B2: Uber Eats
A3: AMAZON | B3: Amazon
A4: PRIME VIDEO | B4: Amazon
A5: POSHMARK | B5: Poshmark
A6: GRANDVIEW | B6: Personal - Clothing
A7: AMERICAN AI | B7: Personal Travel
A8: UNITED | B8: Personal Travel
A9: EXPEDIA | B9: Personal Travel
A10: SEVENTH | B10: Personal Travel
A11: SOUTHWEST | B11: Personal Travel
A12: FRONTIER AI | B12: Frontier
... A194: RAINBOW ACRES | B194: Personal - Misc

Sheet Angela_2026_Chase1117_Activity_
A1: Details | B1: Posting Date | C1: Description | D1: Amount | E1: Type | F1: Balance | G1: Category
A2: DEBIT | B2: 46211 | C2: POS DEBIT UBER * EATS PENDING SAN FRANCISC CA | D2: -20.54 | E2: MISC_DEBIT | G2: {=IF(AND(ISNUMBER(SEARCH("UBER",C2)),ISNUMBER(SEARCH("EATS",C2))),"Uber Eats",IF(LEFT(C2,6)="CHECK ","Checks Paid",IF(OR(E2="BILLPAY",ISNUMBER(SEARCH("FRANCHISE TAX",C2)),ISNUMBER(SEARCH("NEXTLINK",C2))),"Personal - House Bills",IF(AND(ISNUMBER(SEARCH("PAYMENT FROM",C2)),ISNUMBER(SEARCH("JOE SAUNDERS",C2))),"Zelle from Joe Saunders",IF(AND(ISNUMBER(SEARCH("PAYMENT TO",C2)),ISNUMBER(SEARCH("JOE SAUNDERS",C2))),"Zelle to Joe Saunders",IF(OR(ISNUMBER(SEARCH("NEW ORLEANS",C2)),ISNUMBER(SEARCH("KENNER",C2)),ISNUMBER(SEARCH("HENRY HOWARD",C2)),ISNUMBER(SEARCH("MISS CLAUDIA",C2))),"Personal Travel - New Orleans",IFERROR(INDEX('Category Rules'!$B$2:$B$194,MATCH(TRUE,ISNUMBER(SEARCH('Category Rules'!$A$2:$A$194,C2)),0)),"")))))))} -> Uber Eats
A3: DEBIT | B3: 46211 | C3: POS DEBIT 6DAYWEIGHT* 6DAYWEIGHT +18187829038 CA 0089 | D3: -395 | E3: MISC_DEBIT | G3: {=IF(AND(ISNUMBER(SEARCH("UBER",C3)),ISNUMBER(SEARCH("EATS",C3))),"Uber Eats",IF(LEFT(C3,6)="CHECK ","Checks Paid",IF(OR(E3="BILLPAY",ISNUMBER(SEARCH("FRANCHISE TAX",C3)),ISNUMBER(SEARCH("NEXTLINK",C3))),"Personal - House Bills",IF(AND(ISNUMBER(SEARCH("PAYMENT FROM",C3)),ISNUMBER(SEARCH("JOE SAUNDERS",C3))),"Zelle from Joe Saunders",IF(AND(ISNUMBER(SEARCH("PAYMENT TO",C3)),ISNUMBER(SEARCH("JOE SAUNDERS",C3))),"Zelle to Joe Saunders",IF(OR(ISNUMBER(SEARCH("NEW ORLEANS",C3)),ISNUMBER(SEARCH("KENNER",C3)),ISNUMBER(SEARCH("HENRY HOWARD",C3)),ISNUMBER(SEARCH("MISS CLAUDIA",C3))),"Personal Travel - New Orleans",IFERROR(INDEX('Category Rules'!$B$2:$B$194,MATCH(TRUE,ISNUMBER(SEARCH('Category Rules'!$A$2:$A$194,C3)),0)),"")))))))} -> Personal - Health
A4: DEBIT | B4: 46211 | C4: POS DEBIT Prime Video Channels amzn.com/bil WA 0360 | D4: -15.99 | E4: MISC_DEBIT | G4: {=IF(AND(ISNUMBER(SEARCH("UBER",C4)),ISNUMBER(SEARCH("EATS",C4))),"Uber Eats",IF(LEFT(C4,6)="CHECK ","Checks Paid",IF(OR(E4="BILLPAY",ISNUMBER(SEARCH("FRANCHISE TAX",C4)),ISNUMBER(SEARCH("NEXTLINK",C4))),"Personal - House Bills",IF(AND(ISNUMBER(SEARCH("PAYMENT FROM",C4)),ISNUMBER(SEARCH("JOE SAUNDERS",C4))),"Zelle from Joe Saunders",IF(AND(ISNUMBER(SEARCH("PAYMENT TO",C4)),ISNUMBER(SEARCH("JOE SAUNDERS",C4))),"Zelle to Joe Saunders",IF(OR(ISNUMBER(SEARCH("NEW ORLEANS",C4)),ISNUMBER(SEARCH("KENNER",C4)),ISNUMBER(SEARCH("HENRY HOWARD",C4)),ISNUMBER(SEARCH("MISS CLAUDIA",C4))),"Personal Travel - New Orleans",IFERROR(INDEX('Category Rules'!$B$2:$B$194,MATCH(TRUE,ISNUMBER(SEARCH('Category Rules'!$A$2:$A$194,C4)),0)),"")))))))} -> Amazon
A5: DEBIT | B5: 46211 | C5: POS DEBIT Amazon Tips Amzn.com/bil WA 0360 | D5: -15 | E5: MISC_DEBIT | G5: {=IF(AND(ISNUMBER(SEARCH("UBER",C5)),ISNUMBER(SEARCH("EATS",C5))),"Uber Eats",IF(LEFT(C5,6)="CHECK ","Checks Paid",IF(OR(E5="BILLPAY",ISNUMBER(SEARCH("FRANCHISE TAX",C5)),ISNUMBER(SEARCH("NEXTLINK",C5))),"Personal - House Bills",IF(AND(ISNUMBER(SEARCH("PAYMENT FROM",C5)),ISNUMBER(SEARCH("JOE SAUNDERS",C5))),"Zelle from Joe Saunders",IF(AND(ISNUMBER(SEARCH("PAYMENT TO",C5)),ISNUMBER(SEARCH("JOE SAUNDERS",C5))),"Zelle to Joe Saunders",IF(OR(ISNUMBER(SEARCH("NEW ORLEANS",C5)),ISNUMBER(SEARCH("KENNER",C5)),ISNUMBER(SEARCH("HENRY HOWARD",C5)),ISNUMBER(SEARCH("MISS CLAUDIA",C5))),"Personal Travel - New Orleans",IFERROR(INDEX('Category Rules'!$B$2:$B$194,MATCH(TRUE,ISNUMBER(SEARCH('Category Rules'!$A$2:$A$194,C5)),0)),"")))))))} -> Amazon
A6: DEBIT | B6: 46210 | C6: UBER * EATS PENDIN SAN FRANCISCO CA148376 07/07 | D6: -27.55 | E6: DEBIT_CARD | F6: 1542.75 | G6: {=IF(AND(ISNUMBER(SEARCH("UBER",C6)),ISNUMBER(SEARCH("EATS",C6))),"Uber Eats",IF(LEFT(C6,6)="CHECK ","Checks Paid",IF(OR(E6="BILLPAY",ISNUMBER(SEARCH("FRANCHISE TAX",C6)),ISNUMBER(SEARCH("NEXTLINK",C6))),"Personal - House Bills",IF(AND(ISNUMBER(SEARCH("PAYMENT FROM",C6)),ISNUMBER(SEARCH("JOE SAUNDERS",C6))),"Zelle from Joe Saunders",IF(AND(ISNUMBER(SEARCH("PAYMENT TO",C6)),ISNUMBER(SEARCH("JOE SAUNDERS",C6))),"Zelle to Joe Saunders",IF(OR(ISNUMBER(SEARCH("NEW ORLEANS",C6)),ISNUMBER(SEARCH("KENNER",C6)),ISNUMBER(SEARCH("HENRY HOWARD",C6)),ISNUMBER(SEARCH("MISS CLAUDIA",C6))),"Personal Travel - New Orleans",IFERROR(INDEX('Category Rules'!$B$2:$B$194,MATCH(TRUE,ISNUMBER(SEARCH('Category Rules'!$A$2:$A$194,C6)),0)),"")))))))} -> Uber Eats
A7: DEBIT | B7: 46210 | C7: WITHDRAWAL 07/07 | D7: -5000 | E7: MISC_DEBIT | F7: 1570.3 | G7: {=IF(AND(ISNUMBER(SEARCH("UBER",C7)),ISNUMBER(SEARCH("EATS",C7))),"Uber Eats",IF(LEFT(C7,6)="CHECK ","Checks Paid",IF(OR(E7="BILLPAY",ISNUMBER(SEARCH("FRANCHISE TAX",C7)),ISNUMBER(SEARCH("NEXTLINK",C7))),"Personal - House Bills",IF(AND(ISNUMBER(SEARCH("PAYMENT FROM",C7)),ISNUMBER(SEARCH("JOE SAUNDERS",C7))),"Zelle from Joe Saunders",IF(AND(ISNUMBER(SEARCH("PAYMENT TO",C7)),ISNUMBER(SEARCH("JOE SAUNDERS",C7))),"Zelle to Joe Saunders",IF(OR(ISNUMBER(SEARCH("NEW ORLEANS",C7)),ISNUMBER(SEARCH("KENNER",C7)),ISNUMBER(SEARCH("HENRY HOWARD",C7)),ISNUMBER(SEARCH("MISS CLAUDIA",C7))),"Personal Travel - New Orleans",IFERROR(INDEX('Category Rules'!$B$2:$B$194,MATCH(TRUE,ISNUMBER(SEARCH('Category Rules'!$A$2:$A$194,C7)),0)),"")))))))} -> Withdrawal
A8: DEBIT | B8: 46210 | C8: AMAZON RETA* XR6945C WWW.AMAZON.CO WA 07/07 | D8: -25.62 | E8: DEBIT_CARD | F8: 6570.3 | G8: {=IF(AND(ISNUMBER(SEARCH("UBER",C8)),ISNUMBER(SEARCH("EATS",C8))),"Uber Eats",IF(LEFT(C8,6)="CHECK ","Checks Paid",IF(OR(E8="BILLPAY",ISNUMBER(SEARCH("FRANCHISE TAX",C8)),ISNUMBER(SEARCH("NEXTLINK",C8))),"Personal - House Bills",IF(AND(ISNUMBER(SEARCH("PAYMENT FROM",C8)),ISNUMBER(SEARCH("JOE SAUNDERS",C8))),"Zelle from Joe Saunders",IF(AND(ISNUMBER(SEARCH("PAYMENT TO",C8)),ISNUMBER(SEARCH("JOE SAUNDERS",C8))),"Zelle to Joe Saunders",IF(OR(ISNUMBER(SEARCH("NEW ORLEANS",C8)),ISNUMBER(SEARCH("KENNER",C8)),ISNUMBER(SEARCH("HENRY HOWARD",C8)),ISNUMBER(SEARCH("MISS CLAUDIA",C8))),"Personal Travel - New Orleans",IFERROR(INDEX('Category Rules'!$B$2:$B$194,MATCH(TRUE,ISNUMBER(SEARCH('Category Rules'!$A$2:$A$194,C8)),0)),"")))))))} -> Amazon
A9: DEBIT | B9: 46210 | C9: SP VALASTA LLC VALASTA.NET SC 07/06 | D9: -430.03 | E9: DEBIT_CARD | F9: 6595.92 | G9: {=IF(AND(ISNUMBER(SEARCH("UBER",C9)),ISNUMBER(SEARCH("EATS",C9))),"Uber Eats",IF(LEFT(C9,6)="CHECK ","Checks Paid",IF(OR(E9="BILLPAY",ISNUMBER(SEARCH("FRANCHISE TAX",C9)),ISNUMBER(SEARCH("NEXTLINK",C9))),"Personal - House Bills",IF(AND(ISNUMBER(SEARCH("PAYMENT FROM",C9)),ISNUMBER(SEARCH("JOE SAUNDERS",C9))),"Zelle from Joe Saunders",IF(AND(ISNUMBER(SEARCH("PAYMENT TO",C9)),ISNUMBER(SEARCH("JOE SAUNDERS",C9))),"Zelle to Joe Saunders",IF(OR(ISNUMBER(SEARCH("NEW ORLEANS",C9)),ISNUMBER(SEARCH("KENNER",C9)),ISNUMBER(SEARCH("HENRY HOWARD",C9)),ISNUMBER(SEARCH("MISS CLAUDIA",C9))),"Personal Travel - New Orleans",IFERROR(INDEX('Category Rules'!$B$2:$B$194,MATCH(TRUE,ISNUMBER(SEARCH('Category Rules'!$A$2:$A$194,C9)),0)),"")))))))} -> Personal - Health
A10: DEBIT | B10: 46210 | C10: GRANDVIEW CLEANERS LOS ANGELES CA 07/06 | D10: -133 | E10: DEBIT_CARD | F10: 7025.95 | G10: {=IF(AND(ISNUMBER(SEARCH("UBER",C10)),ISNUMBER(SEARCH("EATS",C10))),"Uber Eats",IF(LEFT(C10,6)="CHECK ","Checks Paid",IF(OR(E10="BILLPAY",ISNUMBER(SEARCH("FRANCHISE TAX",C10)),ISNUMBER(SEARCH("NEXTLINK",C10))),"Personal - House Bills",IF(AND(ISNUMBER(SEARCH("PAYMENT FROM",C10)),ISNUMBER(SEARCH("JOE SAUNDERS",C10))),"Zelle from Joe Saunders",IF(AND(ISNUMBER(SEARCH("PAYMENT TO",C10)),ISNUMBER(SEARCH("JOE SAUNDERS",C10))),"Zelle to Joe Saunders",IF(OR(ISNUMBER(SEARCH("NEW ORLEANS",C10)),ISNUMBER(SEARCH("KENNER",C10)),ISNUMBER(SEARCH("HENRY HOWARD",C10)),ISNUMBER(SEARCH("MISS CLAUDIA",C10))),"Personal Travel - New Orleans",IFERROR(INDEX('Category Rules'!$B$2:$B$194,MATCH(TRUE,ISNUMBER(SEARCH('Category Rules'!$A$2:$A$194,C10)),0)),"")))))))} -> Personal - Clothing
A11: DEBIT | B11: 46210 | C11: Amazon Tips*SA10C2A4 Amzn.com/bill WA 07/06 | D11: -30 | E11: DEBIT_CARD | F11: 7158.95 | G11: {=IF(AND(ISNUMBER(SEARCH("UBER",C11)),ISNUMBER(SEARCH("EATS",C11))),"Uber Eats",IF(LEFT(C11,6)="CHECK ","Checks Paid",IF(OR(E11="BILLPAY",ISNUMBER(SEARCH("FRANCHISE TAX",C11)),ISNUMBER(SEARCH("NEXTLINK",C11))),"Personal - House Bills",IF(AND(ISNUMBER(SEARCH("PAYMENT FROM",C11)),ISNUMBER(SEARCH("JOE SAUNDERS",C11))),"Zelle from Joe Saunders",IF(AND(ISNUMBER(SEARCH("PAYMENT TO",C11)),ISNUMBER(SEARCH("JOE SAUNDERS",C11))),"Zelle to Joe Saunders",IF(OR(ISNUMBER(SEARCH("NEW ORLEANS",C11)),ISNUMBER(SEARCH("KENNER",C11)),ISNUMBER(SEARCH("HENRY HOWARD",C11)),ISNUMBER(SEARCH("MISS CLAUDIA",C11))),"Personal Travel - New Orleans",IFERROR(INDEX('Category Rules'!$B$2:$B$194,MATCH(TRUE,ISNUMBER(SEARCH('Category Rules'!$A$2:$A$194,C11)),0)),"")))))))} -> Amazon
A12: DEBIT | B12: 46210 | C12: AMAZON RETA* WC81L6V WWW.AMAZON.CO WA 07/06 | D12: -11.75 | E12: DEBIT_CARD | F12: 7188.95 | G12: {=IF(AND(ISNUMBER(SEARCH("UBER",C12)),ISNUMBER(SEARCH("EATS",C12))),"Uber Eats",IF(LEFT(C12,6)="CHECK ","Checks Paid",IF(OR(E12="BILLPAY",ISNUMBER(SEARCH("FRANCHISE TAX",C12)),ISNUMBER(SEARCH("NEXTLINK",C12))),"Personal - House Bills",IF(AND(ISNUMBER(SEARCH("PAYMENT FROM",C12)),ISNUMBER(SEARCH("JOE SAUNDERS",C12))),"Zelle from Joe Saunders",IF(AND(ISNUMBER(SEARCH("PAYMENT TO",C12)),ISNUMBER(SEARCH("JOE SAUNDERS",C12))),"Zelle to Joe Saunders",IF(OR(ISNUMBER(SEARCH("NEW ORLEANS",C12)),ISNUMBER(SEARCH("KENNER",C12)),ISNUMBER(SEARCH("HENRY HOWARD",C12)),ISNUMBER(SEARCH("MISS CLAUDIA",C12))),"Personal Travel - New Orleans",IFERROR(INDEX('Category Rules'!$B$2:$B$194,MATCH(TRUE,ISNUMBER(SEARCH('Category Rules'!$A$2:$A$194,C12)),0)),"")))))))} -> Amazon
A13: DEBIT | B13: 46210 | C13: AMAZON RETA* TR3I78I WWW.AMAZON.CO WA 07/07 | D13: -7.75 | E13: DEBIT_CARD | F13: 7200.7 | G13: {=IF(AND(ISNUMBER(SEARCH("UBER",C13)),ISNUMBER(SEARCH("EATS",C13))),"Uber Eats",IF(LEFT(C13,6)="CHECK ","Checks Paid",IF(OR(E13="BILLPAY",ISNUMBER(SEARCH("FRANCHISE TAX",C13)),ISNUMBER(SEARCH("NEXTLINK",C13))),"Personal - House Bills",IF(AND(ISNUMBER(SEARCH("PAYMENT FROM",C13)),ISNUMBER(SEARCH("JOE SAUNDERS",C13))),"Zelle from Joe Saunders",IF(AND(ISNUMBER(SEARCH("PAYMENT TO",C13)),ISNUMBER(SEARCH("JOE SAUNDERS",C13))),"Zelle to Joe Saunders",IF(OR(ISNUMBER(SEARCH("NEW ORLEANS",C13)),ISNUMBER(SEARCH("KENNER",C13)),ISNUMBER(SEARCH("HENRY HOWARD",C13)),ISNUMBER(SEARCH("MISS CLAUDIA",C13))),"Personal Travel - New Orleans",IFERROR(INDEX('Category Rules'!$B$2:$B$194,MATCH(TRUE,ISNUMBER(SEARCH('Category Rules'!$A$2:$A$194,C13)),0)),"")))))))} -> Amazon
A14: DEBIT | B14: 46210 | C14: AMAZON RETA* 7S20V2V WWW.AMAZON.CO WA 07/07 | D14: -2.98 | E14: DEBIT_CARD | F14: 7208.45 | G14: {=IF(AND(ISNUMBER(SEARCH("UBER",C14)),ISNUMBER(SEARCH("EATS",C14))),"Uber Eats",IF(LEFT(C14,6)="CHECK ","Checks Paid",IF(OR(E14="BILLPAY",ISNUMBER(SEARCH("FRANCHISE TAX",C14)),ISNUMBER(SEARCH("NEXTLINK",C14))),"Personal - House Bills",IF(AND(ISNUMBER(SEARCH("PAYMENT FROM",C14)),ISNUMBER(SEARCH("JOE SAUNDERS",C14))),"Zelle from Joe Saunders",IF(AND(ISNUMBER(SEARCH("PAYMENT TO",C14)),ISNUMBER(SEARCH("JOE SAUNDERS",C14))),"Zelle to Joe Saunders",IF(OR(ISNUMBER(SEARCH("NEW ORLEANS",C14)),ISNUMBER(SEARCH("KENNER",C14)),ISNUMBER(SEARCH("HENRY HOWARD",C14)),ISNUMBER(SEARCH("MISS CLAUDIA",C14))),"Personal Travel - New Orleans",IFERROR(INDEX('Category Rules'!$B$2:$B$194,MATCH(TRUE,ISNUMBER(SEARCH('Category Rules'!$A$2:$A$194,C14)),0)),"")))))))} -> Amazon
A15: DEBIT | B15: 46210 | C15: Amazon.com*J13TY12U3 Amzn.com/bill WA 07/06 | D15: -77.09 | E15: DEBIT_CARD | F15: 7211.43 | G15: {=IF(AND(ISNUMBER(SEARCH("UBER",C15)),ISNUMBER(SEARCH("EATS",C15))),"Uber Eats",IF(LEFT(C15,6)="CHECK ","Checks Paid",IF(OR(E15="BILLPAY",ISNUMBER(SEARCH("FRANCHISE TAX",C15)),ISNUMBER(SEARCH("NEXTLINK",C15))),"Personal - House Bills",IF(AND(ISNUMBER(SEARCH("PAYMENT FROM",C15)),ISNUMBER(SEARCH("JOE SAUNDERS",C15))),"Zelle from Joe Saunders",IF(AND(ISNUMBER(SEARCH("PAYMENT TO",C15)),ISNUMBER(SEARCH("JOE SAUNDERS",C15))),"Zelle to Joe Saunders",IF(OR(ISNUMBER(SEARCH("NEW ORLEANS",C15)),ISNUMBER(SEARCH("KENNER",C15)),ISNUMBER(SEARCH("HENRY HOWARD",C15)),ISNUMBER(SEARCH("MISS CLAUDIA",C15))),"Personal Travel - New Orleans",IFERROR(INDEX('Category Rules'!$B$2:$B$194,MATCH(TRUE,ISNUMBER(SEARCH('Category Rules'!$A$2:$A$194,C15)),0)),"")))))))} -> Amazon
A16: DEBIT | B16: 46210 | C16: AMAZON RETA* TN0B08X WWW.AMAZON.CO WA 07/06 | D16: -42.47 | E16: DEBIT_CARD | F16: 7288.52 | G16: {=IF(AND(ISNUMBER(SEARCH("UBER",C16)),ISNUMBER(SEARCH("EATS",C16))),"Uber Eats",IF(LEFT(C16,6)="CHECK ","Checks Paid",IF(OR(E16="BILLPAY",ISNUMBER(SEARCH("FRANCHISE TAX",C16)),ISNUMBER(SEARCH("NEXTLINK",C16))),"Personal - House Bills",IF(AND(ISNUMBER(SEARCH("PAYMENT FROM",C16)),ISNUMBER(SEARCH("JOE SAUNDERS",C16))),"Zelle from Joe Saunders",IF(AND(ISNUMBER(SEARCH("PAYMENT TO",C16)),ISNUMBER(SEARCH("JOE SAUNDERS",C16))),"Zelle to Joe Saunders",IF(OR(ISNUMBER(SEARCH("NEW ORLEANS",C16)),ISNUMBER(SEARCH("KENNER",C16)),ISNUMBER(SEARCH("HENRY HOWARD",C16)),ISNUMBER(SEARCH("MISS CLAUDIA",C16))),"Personal Travel - New Orleans",IFERROR(INDEX('Category Rules'!$B$2:$B$194,MATCH(TRUE,ISNUMBER(SEARCH('Category Rules'!$A$2:$A$194,C16)),0)),"")))))))} -> Amazon
A17: DSLIP | B17: 46210 | C17: DEPOSIT ID NUMBER 891007 | D17: 120 | E17: DEPOSIT | F17: 7330.99 | G17: {=IF(AND(ISNUMBER(SEARCH("UBER",C17)),ISNUMBER(SEARCH("EATS",C17))),"Uber Eats",IF(LEFT(C17,6)="CHECK ","Checks Paid",IF(OR(E17="BILLPAY",ISNUMBER(SEARCH("FRANCHISE TAX",C17)),ISNUMBER(SEARCH("NEXTLINK",C17))),"Personal - House Bills",IF(AND(ISNUMBER(SEARCH("PAYMENT FROM",C17)),ISNUMBER(SEARCH("JOE SAUNDERS",C17))),"Zelle from Joe Saunders",IF(AND(ISNUMBER(SEARCH("PAYMENT TO",C17)),ISNUMBER(SEARCH("JOE SAUNDERS",C17))),"Zelle to Joe Saunders",IF(OR(ISNUMBER(SEARCH("NEW ORLEANS",C17)),ISNUMBER(SEARCH("KENNER",C17)),ISNUMBER(SEARCH("HENRY HOWARD",C17)),ISNUMBER(SEARCH("MISS CLAUDIA",C17))),"Personal Travel - New Orleans",IFERROR(INDEX('Category Rules'!$B$2:$B$194,MATCH(TRUE,ISNUMBER(SEARCH('Category Rules'!$A$2:$A$194,C17)),0)),"")))))))} -> Deposit
... A1094: DEBIT | B1094: 46064 | C1094: Amazon Tips*9Z40N0UM Amzn.com/bill WA 02/10 | D1094: -15 | E1094: DEBIT_CARD | F1094: 2555.56 | G1094: {=IF(AND(ISNUMBER(SEARCH("UBER",C1094)),ISNUMBER(SEARCH("EATS",C1094))),"Uber Eats",IF(LEFT(C1094,6)="CHECK ","Checks Paid",IF(OR(E1094="BILLPAY",ISNUMBER(SEARCH("FRANCHISE TAX",C1094)),ISNUMBER(SEARCH("NEXTLINK",C1094))),"Personal - House Bills",IF(AND(ISNUMBER(SEARCH("PAYMENT FROM",C1094)),ISNUMBER(SEARCH("JOE SAUNDERS",C1094))),"Zelle from Joe Saunders",IF(AND(ISNUMBER(SEARCH("PAYMENT TO",C1094)),ISNUMBER(SEARCH("JOE SAUNDERS",C1094))),"Zelle to Joe Saunders",IF(OR(ISNUMBER(SEARCH("NEW ORLEANS",C1094)),ISNUMBER(SEARCH("KENNER",C1094)),ISNUMBER(SEARCH("HENRY HOWARD",C1094)),ISNUMBER(SEARCH("MISS CLAUDIA",C1094))),"Personal Travel - New Orleans",IFERROR(INDEX('Category Rules'!$B$2:$B$194,MATCH(TRUE,ISNUMBER(SEARCH('Category Rules'!$A$2:$A$194,C1094)),0)),"")))))))} -> Amazon
A1095: DEBIT | B1095: 46063 | C1095: CNP* VOGUE - DIGITAL CONDENAST.COM NY 02/10 | D1095: -24.99 | E1095: DEBIT_CARD | F1095: 2570.56 | G1095: Personal - Shopping
A1096: DEBIT | B1096: 46063 | C1096: Online Transfer to CHK ...6975 transaction#: 28016408490 02/10 | D1096: -250 | E1096: ACCT_XFER | F1096: 2595.55 | G1096: {=IF(AND(ISNUMBER(SEARCH("UBER",C1096)),ISNUMBER(SEARCH("EATS",C1096))),"Uber Eats",IF(LEFT(C1096,6)="CHECK ","Checks Paid",IF(OR(E1096="BILLPAY",ISNUMBER(SEARCH("FRANCHISE TAX",C1096)),ISNUMBER(SEARCH("NEXTLINK",C1096))),"Personal - House Bills",IF(AND(ISNUMBER(SEARCH("PAYMENT FROM",C1096)),ISNUMBER(SEARCH("JOE SAUNDERS",C1096))),"Zelle from Joe Saunders",IF(AND(ISNUMBER(SEARCH("PAYMENT TO",C1096)),ISNUMBER(SEARCH("JOE SAUNDERS",C1096))),"Zelle to Joe Saunders",IF(OR(ISNUMBER(SEARCH("NEW ORLEANS",C1096)),ISNUMBER(SEARCH("KENNER",C1096)),ISNUMBER(SEARCH("HENRY HOWARD",C1096)),ISNUMBER(SEARCH("MISS CLAUDIA",C1096))),"Personal Travel - New Orleans",IFERROR(INDEX('Category Rules'!$B$2:$B$194,MATCH(TRUE,ISNUMBER(SEARCH('Category Rules'!$A$2:$A$194,C1096)),0)),"")))))))} -> Transfer to Ava
A1097: DEBIT | B1097: 46063 | C1097: AMAZON MARK* 8Y4Q08G AMAZON.COM/MA WA 02/10 | D1097: -69.08 | E1097: DEBIT_CARD | F1097: 2845.55 | G1097: {=IF(AND(ISNUMBER(SEARCH("UBER",C1097)),ISNUMBER(SEARCH("EATS",C1097))),"Uber Eats",IF(LEFT(C1097,6)="CHECK ","Checks Paid",IF(OR(E1097="BILLPAY",ISNUMBER(SEARCH("FRANCHISE TAX",C1097)),ISNUMBER(SEARCH("NEXTLINK",C1097))),"Personal - House Bills",IF(AND(ISNUMBER(SEARCH("PAYMENT FROM",C1097)),ISNUMBER(SEARCH("JOE SAUNDERS",C1097))),"Zelle from Joe Saunders",IF(AND(ISNUMBER(SEARCH("PAYMENT TO",C1097)),ISNUMBER(SEARCH("JOE SAUNDERS",C1097))),"Zelle to Joe Saunders",IF(OR(ISNUMBER(SEARCH("NEW ORLEANS",C1097)),ISNUMBER(SEARCH("KENNER",C1097)),ISNUMBER(SEARCH("HENRY HOWARD",C1097)),ISNUMBER(SEARCH("MISS CLAUDIA",C1097))),"Personal Travel - New Orleans",IFERROR(INDEX('Category Rules'!$B$2:$B$194,MATCH(TRUE,ISNUMBER(SEARCH('Category Rules'!$A$2:$A$194,C1097)),0)),"")))))))} -> Amazon
A1098: DEBIT | B1098: 46063 | C1098: Amazon.com*XC33A0EY3 Amzn.com/bill WA 02/09 | D1098: -31.46 | E1098: DEBIT_CARD | F1098: 2914.63 | G1098: {=IF(AND(ISNUMBER(SEARCH("UBER",C1098)),ISNUMBER(SEARCH("EATS",C1098))),"Uber Eats",IF(LEFT(C1098,6)="CHECK ","Checks Paid",IF(OR(E1098="BILLPAY",ISNUMBER(SEARCH("FRANCHISE TAX",C1098)),ISNUMBER(SEARCH("NEXTLINK",C1098))),"Personal - House Bills",IF(AND(ISNUMBER(SEARCH("PAYMENT FROM",C1098)),ISNUMBER(SEARCH("JOE SAUNDERS",C1098))),"Zelle from Joe Saunders",IF(AND(ISNUMBER(SEARCH("PAYMENT TO",C1098)),ISNUMBER(SEARCH("JOE SAUNDERS",C1098))),"Zelle to Joe Saunders",IF(OR(ISNUMBER(SEARCH("NEW ORLEANS",C1098)),ISNUMBER(SEARCH("KENNER",C1098)),ISNUMBER(SEARCH("HENRY HOWARD",C1098)),ISNUMBER(SEARCH("MISS CLAUDIA",C1098))),"Personal Travel - New Orleans",IFERROR(INDEX('Category Rules'!$B$2:$B$194,MATCH(TRUE,ISNUMBER(SEARCH('Category Rules'!$A$2:$A$194,C1098)),0)),"")))))))} -> Amazon
A1099: DEBIT | B1099: 46063 | C1099: Amazon.com*LA0TR9IZ3 Amzn.com/bill WA 02/09 | D1099: -104.95 | E1099: DEBIT_CARD | F1099: 2946.09 | G1099: {=IF(AND(ISNUMBER(SEARCH("UBER",C1099)),ISNUMBER(SEARCH("EATS",C1099))),"Uber Eats",IF(LEFT(C1099,6)="CHECK ","Checks Paid",IF(OR(E1099="BILLPAY",ISNUMBER(SEARCH("FRANCHISE TAX",C1099)),ISNUMBER(SEARCH("NEXTLINK",C1099))),"Personal - House Bills",IF(AND(ISNUMBER(SEARCH("PAYMENT FROM",C1099)),ISNUMBER(SEARCH("JOE SAUNDERS",C1099))),"Zelle from Joe Saunders",IF(AND(ISNUMBER(SEARCH("PAYMENT TO",C1099)),ISNUMBER(SEARCH("JOE SAUNDERS",C1099))),"Zelle to Joe Saunders",IF(OR(ISNUMBER(SEARCH("NEW ORLEANS",C1099)),ISNUMBER(SEARCH("KENNER",C1099)),ISNUMBER(SEARCH("HENRY HOWARD",C1099)),ISNUMBER(SEARCH("MISS CLAUDIA",C1099))),"Personal Travel - New Orleans",IFERROR(INDEX('Category Rules'!$B$2:$B$194,MATCH(TRUE,ISNUMBER(SEARCH('Category Rules'!$A$2:$A$194,C1099)),0)),"")))))))} -> Amazon
A1100: DEBIT | B1100: 46063 | C1100: NTTA AUTOCHARGE 972-818-6882 TX 02/09 | D1100: -40 | E1100: DEBIT_CARD | F1100: 3051.04 | G1100: {=IF(AND(ISNUMBER(SEARCH("UBER",C1100)),ISNUMBER(SEARCH("EATS",C1100))),"Uber Eats",IF(LEFT(C1100,6)="CHECK ","Checks Paid",IF(OR(E1100="BILLPAY",ISNUMBER(SEARCH("FRANCHISE TAX",C1100)),ISNUMBER(SEARCH("NEXTLINK",C1100))),"Personal - House Bills",IF(AND(ISNUMBER(SEARCH("PAYMENT FROM",C1100)),ISNUMBER(SEARCH("JOE SAUNDERS",C1100))),"Zelle from Joe Saunders",IF(AND(ISNUMBER(SEARCH("PAYMENT TO",C1100)),ISNUMBER(SEARCH("JOE SAUNDERS",C1100))),"Zelle to Joe Saunders",IF(OR(ISNUMBER(SEARCH("NEW ORLEANS",C1100)),ISNUMBER(SEARCH("KENNER",C1100)),ISNUMBER(SEARCH("HENRY HOWARD",C1100)),ISNUMBER(SEARCH("MISS CLAUDIA",C1100))),"Personal Travel - New Orleans",IFERROR(INDEX('Category Rules'!$B$2:$B$194,MATCH(TRUE,ISNUMBER(SEARCH('Category Rules'!$A$2:$A$194,C1100)),0)),"")))))))} -> Personal - Car
A1101: DEBIT | B1101: 46063 | C1101: AMAZON MARK* UW3I221 AMAZON.COM/MA WA 02/10 | D1101: -140.82 | E1101: DEBIT_CARD | F1101: 3091.04 | G1101: {=IF(AND(ISNUMBER(SEARCH("UBER",C1101)),ISNUMBER(SEARCH("EATS",C1101))),"Uber Eats",IF(LEFT(C1101,6)="CHECK ","Checks Paid",IF(OR(E1101="BILLPAY",ISNUMBER(SEARCH("FRANCHISE TAX",C1101)),ISNUMBER(SEARCH("NEXTLINK",C1101))),"Personal - House Bills",IF(AND(ISNUMBER(SEARCH("PAYMENT FROM",C1101)),ISNUMBER(SEARCH("JOE SAUNDERS",C1101))),"Zelle from Joe Saunders",IF(AND(ISNUMBER(SEARCH("PAYMENT TO",C1101)),ISNUMBER(SEARCH("JOE SAUNDERS",C1101))),"Zelle to Joe Saunders",IF(OR(ISNUMBER(SEARCH("NEW ORLEANS",C1101)),ISNUMBER(SEARCH("KENNER",C1101)),ISNUMBER(SEARCH("HENRY HOWARD",C1101)),ISNUMBER(SEARCH("MISS CLAUDIA",C1101))),"Personal Travel - New Orleans",IFERROR(INDEX('Category Rules'!$B$2:$B$194,MATCH(TRUE,ISNUMBER(SEARCH('Category Rules'!$A$2:$A$194,C1101)),0)),"")))))))} -> Amazon
A1102: DEBIT | B1102: 46063 | C1102: AMAZON MKTPL*IG30P45 Amzn.com/bill WA 02/09 | D1102: -112.45 | E1102: DEBIT_CARD | F1102: 3231.86 | G1102: {=IF(AND(ISNUMBER(SEARCH("UBER",C1102)),ISNUMBER(SEARCH("EATS",C1102))),"Uber Eats",IF(LEFT(C1102,6)="CHECK ","Checks Paid",IF(OR(E1102="BILLPAY",ISNUMBER(SEARCH("FRANCHISE TAX",C1102)),ISNUMBER(SEARCH("NEXTLINK",C1102))),"Personal - House Bills",IF(AND(ISNUMBER(SEARCH("PAYMENT FROM",C1102)),ISNUMBER(SEARCH("JOE SAUNDERS",C1102))),"Zelle from Joe Saunders",IF(AND(ISNUMBER(SEARCH("PAYMENT TO",C1102)),ISNUMBER(SEARCH("JOE SAUNDERS",C1102))),"Zelle to Joe Saunders",IF(OR(ISNUMBER(SEARCH("NEW ORLEANS",C1102)),ISNUMBER(SEARCH("KENNER",C1102)),ISNUMBER(SEARCH("HENRY HOWARD",C1102)),ISNUMBER(SEARCH("MISS CLAUDIA",C1102))),"Personal Travel - New Orleans",IFERROR(INDEX('Category Rules'!$B$2:$B$194,MATCH(TRUE,ISNUMBER(SEARCH('Category Rules'!$A$2:$A$194,C1102)),0)),"")))))))} -> Amazon
A1103: CREDIT | B1103: 46063 | C1103: Zelle payment from G-EUNICE LLC 28023181510 | D1103: 175 | E1103: QUICKPAY_CREDIT | F1103: 3344.31 | G1103: {=IF(AND(ISNUMBER(SEARCH("UBER",C1103)),ISNUMBER(SEARCH("EATS",C1103))),"Uber Eats",IF(LEFT(C1103,6)="CHECK ","Checks Paid",IF(OR(E1103="BILLPAY",ISNUMBER(SEARCH("FRANCHISE TAX",C1103)),ISNUMBER(SEARCH("NEXTLINK",C1103))),"Personal - House Bills",IF(AND(ISNUMBER(SEARCH("PAYMENT FROM",C1103)),ISNUMBER(SEARCH("JOE SAUNDERS",C1103))),"Zelle from Joe Saunders",IF(AND(ISNUMBER(SEARCH("PAYMENT TO",C1103)),ISNUMBER(SEARCH("JOE SAUNDERS",C1103))),"Zelle to Joe Saunders",IF(OR(ISNUMBER(SEARCH("NEW ORLEANS",C1103)),ISNUMBER(SEARCH("KENNER",C1103)),ISNUMBER(SEARCH("HENRY HOWARD",C1103)),ISNUMBER(SEARCH("MISS CLAUDIA",C1103))),"Personal Travel - New Orleans",IFERROR(INDEX('Category Rules'!$B$2:$B$194,MATCH(TRUE,ISNUMBER(SEARCH('Category Rules'!$A$2:$A$194,C1103)),0)),"")))))))} -> Zelle from G-Eunice LLC
A1104: DEBIT | B1104: 46062 | C1104: ZARA USA INC. ESTADOS UNIDO NY 026837 02/09 | D1104: -826.35 | E1104: DEBIT_CARD | F1104: 3169.31 | G1104: {=IF(AND(ISNUMBER(SEARCH("UBER",C1104)),ISNUMBER(SEARCH("EATS",C1104))),"Uber Eats",IF(LEFT(C1104,6)="CHECK ","Checks Paid",IF(OR(E1104="BILLPAY",ISNUMBER(SEARCH("FRANCHISE TAX",C1104)),ISNUMBER(SEARCH("NEXTLINK",C1104))),"Personal - House Bills",IF(AND(ISNUMBER(SEARCH("PAYMENT FROM",C1104)),ISNUMBER(SEARCH("JOE SAUNDERS",C1104))),"Zelle from Joe Saunders",IF(AND(ISNUMBER(SEARCH("PAYMENT TO",C1104)),ISNUMBER(SEARCH("JOE SAUNDERS",C1104))),"Zelle to Joe Saunders",IF(OR(ISNUMBER(SEARCH("NEW ORLEANS",C1104)),ISNUMBER(SEARCH("KENNER",C1104)),ISNUMBER(SEARCH("HENRY HOWARD",C1104)),ISNUMBER(SEARCH("MISS CLAUDIA",C1104))),"Personal Travel - New Orleans",IFERROR(INDEX('Category Rules'!$B$2:$B$194,MATCH(TRUE,ISNUMBER(SEARCH('Category Rules'!$A$2:$A$194,C1104)),0)),"")))))))} -> Personal - Shopping
A1105: DEBIT | B1105: 46062 | C1105: APPLE COM BILL CUPERTINO CA 653129 02/09 | D1105: -12.99 | E1105: DEBIT_CARD | F1105: 3995.66 | G1105: {=IF(AND(ISNUMBER(SEARCH("UBER",C1105)),ISNUMBER(SEARCH("EATS",C1105))),"Uber Eats",IF(LEFT(C1105,6)="CHECK ","Checks Paid",IF(OR(E1105="BILLPAY",ISNUMBER(SEARCH("FRANCHISE TAX",C1105)),ISNUMBER(SEARCH("NEXTLINK",C1105))),"Personal - House Bills",IF(AND(ISNUMBER(SEARCH("PAYMENT FROM",C1105)),ISNUMBER(SEARCH("JOE SAUNDERS",C1105))),"Zelle from Joe Saunders",IF(AND(ISNUMBER(SEARCH("PAYMENT TO",C1105)),ISNUMBER(SEARCH("JOE SAUNDERS",C1105))),"Zelle to Joe Saunders",IF(OR(ISNUMBER(SEARCH("NEW ORLEANS",C1105)),ISNUMBER(SEARCH("KENNER",C1105)),ISNUMBER(SEARCH("HENRY HOWARD",C1105)),ISNUMBER(SEARCH("MISS CLAUDIA",C1105))),"Personal Travel - New Orleans",IFERROR(INDEX('Category Rules'!$B$2:$B$194,MATCH(TRUE,ISNUMBER(SEARCH('Category Rules'!$A$2:$A$194,C1105)),0)),"")))))))} -> Apple
A1106: DEBIT | B1106: 46062 | C1106: AMAZON RETA* 9D7EI8W WWW.AMAZON.CO WA 02/09 | D1106: -15.16 | E1106: DEBIT_CARD | F1106: 4008.65 | G1106: {=IF(AND(ISNUMBER(SEARCH("UBER",C1106)),ISNUMBER(SEARCH("EATS",C1106))),"Uber Eats",IF(LEFT(C1106,6)="CHECK ","Checks Paid",IF(OR(E1106="BILLPAY",ISNUMBER(SEARCH("FRANCHISE TAX",C1106)),ISNUMBER(SEARCH("NEXTLINK",C1106))),"Personal - House Bills",IF(AND(ISNUMBER(SEARCH("PAYMENT FROM",C1106)),ISNUMBER(SEARCH("JOE SAUNDERS",C1106))),"Zelle from Joe Saunders",IF(AND(ISNUMBER(SEARCH("PAYMENT TO",C1106)),ISNUMBER(SEARCH("JOE SAUNDERS",C1106))),"Zelle to Joe Saunders",IF(OR(ISNUMBER(SEARCH("NEW ORLEANS",C1106)),ISNUMBER(SEARCH("KENNER",C1106)),ISNUMBER(SEARCH("HENRY HOWARD",C1106)),ISNUMBER(SEARCH("MISS CLAUDIA",C1106))),"Personal Travel - New Orleans",IFERROR(INDEX('Category Rules'!$B$2:$B$194,MATCH(TRUE,ISNUMBER(SEARCH('Category Rules'!$A$2:$A$194,C1106)),0)),"")))))))} -> Amazon
A1107: DEBIT | B1107: 46062 | C1107: PACOS TACOS LOS ANGELES CA 02/08 | D1107: -128.35 | E1107: DEBIT_CARD | F1107: 4023.81 | G1107: {=IF(AND(ISNUMBER(SEARCH("UBER",C1107)),ISNUMBER(SEARCH("EATS",C1107))),"Uber Eats",IF(LEFT(C1107,6)="CHECK ","Checks Paid",IF(OR(E1107="BILLPAY",ISNUMBER(SEARCH("FRANCHISE TAX",C1107)),ISNUMBER(SEARCH("NEXTLINK",C1107))),"Personal - House Bills",IF(AND(ISNUMBER(SEARCH("PAYMENT FROM",C1107)),ISNUMBER(SEARCH("JOE SAUNDERS",C1107))),"Zelle from Joe Saunders",IF(AND(ISNUMBER(SEARCH("PAYMENT TO",C1107)),ISNUMBER(SEARCH("JOE SAUNDERS",C1107))),"Zelle to Joe Saunders",IF(OR(ISNUMBER(SEARCH("NEW ORLEANS",C1107)),ISNUMBER(SEARCH("KENNER",C1107)),ISNUMBER(SEARCH("HENRY HOWARD",C1107)),ISNUMBER(SEARCH("MISS CLAUDIA",C1107))),"Personal Travel - New Orleans",IFERROR(INDEX('Category Rules'!$B$2:$B$194,MATCH(TRUE,ISNUMBER(SEARCH('Category Rules'!$A$2:$A$194,C1107)),0)),"")))))))} -> Personal - Food
... A1141: DEBIT | B1141: 46057 | C1141: T J MAXX #1295 WEATHERFORD TX 014889 02/04 | D1141: -129.89 | E1141: DEBIT_CARD | F1141: 4366.06 | G1141: {=IF(AND(ISNUMBER(SEARCH("UBER",C1141)),ISNUMBER(SEARCH("EATS",C1141))),"Uber Eats",IF(LEFT(C1141,6)="CHECK ","Checks Paid",IF(OR(E1141="BILLPAY",ISNUMBER(SEARCH("FRANCHISE TAX",C1141)),ISNUMBER(SEARCH("NEXTLINK",C1141))),"Personal - House Bills",IF(AND(ISNUMBER(SEARCH("PAYMENT FROM",C1141)),ISNUMBER(SEARCH("JOE SAUNDERS",C1141))),"Zelle from Joe Saunders",IF(AND(ISNUMBER(SEARCH("PAYMENT TO",C1141)),ISNUMBER(SEARCH("JOE SAUNDERS",C1141))),"Zelle to Joe Saunders",IF(OR(ISNUMBER(SEARCH("NEW ORLEANS",C1141)),ISNUMBER(SEARCH("KENNER",C1141)),ISNUMBER(SEARCH("HENRY HOWARD",C1141)),ISNUMBER(SEARCH("MISS CLAUDIA",C1141))),"Personal Travel - New Orleans",IFERROR(INDEX('Category Rules'!$B$2:$B$194,MATCH(TRUE,ISNUMBER(SEARCH('Category Rules'!$A$2:$A$194,C1141)),0)),"")))))))} -> Personal - Shopping
A1142: DEBIT | B1142: 46057 | C1142: BONENANZA BARN BOOKS & GLEN ROSE TX 02/03 | D1142: -33.62 | E1142: DEBIT_CARD | F1142: 4495.95 | G1142: Personal - Shopping
A1143: DEBIT | B1143: 46057 | C1143: AMAZON MKTPL*3S19952 Amzn.com/bill WA 02/04 | D1143: -10.42 | E1143: DEBIT_CARD | F1143: 4529.57 | G1143: {=IF(AND(ISNUMBER(SEARCH("UBER",C1143)),ISNUMBER(SEARCH("EATS",C1143))),"Uber Eats",IF(LEFT(C1143,6)="CHECK ","Checks Paid",IF(OR(E1143="BILLPAY",ISNUMBER(SEARCH("FRANCHISE TAX",C1143)),ISNUMBER(SEARCH("NEXTLINK",C1143))),"Personal - House Bills",IF(AND(ISNUMBER(SEARCH("PAYMENT FROM",C1143)),ISNUMBER(SEARCH("JOE SAUNDERS",C1143))),"Zelle from Joe Saunders",IF(AND(ISNUMBER(SEARCH("PAYMENT TO",C1143)),ISNUMBER(SEARCH("JOE SAUNDERS",C1143))),"Zelle to Joe Saunders",IF(OR(ISNUMBER(SEARCH("NEW ORLEANS",C1143)),ISNUMBER(SEARCH("KENNER",C1143)),ISNUMBER(SEARCH("HENRY HOWARD",C1143)),ISNUMBER(SEARCH("MISS CLAUDIA",C1143))),"Personal Travel - New Orleans",IFERROR(INDEX('Category Rules'!$B$2:$B$194,MATCH(TRUE,ISNUMBER(SEARCH('Category Rules'!$A$2:$A$194,C1143)),0)),"")))))))} -> Amazon
A1144: DEBIT | B1144: 46057 | C1144: Amazon.com*A20B27X53 Amzn.com/bill WA 02/04 | D1144: -9.83 | E1144: DEBIT_CARD | F1144: 4539.99 | G1144: {=IF(AND(ISNUMBER(SEARCH("UBER",C1144)),ISNUMBER(SEARCH("EATS",C1144))),"Uber Eats",IF(LEFT(C1144,6)="CHECK ","Checks Paid",IF(OR(E1144="BILLPAY",ISNUMBER(SEARCH("FRANCHISE TAX",C1144)),ISNUMBER(SEARCH("NEXTLINK",C1144))),"Personal - House Bills",IF(AND(ISNUMBER(SEARCH("PAYMENT FROM",C1144)),ISNUMBER(SEARCH("JOE SAUNDERS",C1144))),"Zelle from Joe Saunders",IF(AND(ISNUMBER(SEARCH("PAYMENT TO",C1144)),ISNUMBER(SEARCH("JOE SAUNDERS",C1144))),"Zelle to Joe Saunders",IF(OR(ISNUMBER(SEARCH("NEW ORLEANS",C1144)),ISNUMBER(SEARCH("KENNER",C1144)),ISNUMBER(SEARCH("HENRY HOWARD",C1144)),ISNUMBER(SEARCH("MISS CLAUDIA",C1144))),"Personal Travel - New Orleans",IFERROR(INDEX('Category Rules'!$B$2:$B$194,MATCH(TRUE,ISNUMBER(SEARCH('Category Rules'!$A$2:$A$194,C1144)),0)),"")))))))} -> Amazon
A1145: DEBIT | B1145: 46057 | C1145: SQ *BIG DEAL FARMS & AN Glen Rose TX 02/03 | D1145: -156.64 | E1145: DEBIT_CARD | F1145: 4549.82 | G1145: Personal - Shopping
A1146: DEBIT | B1146: 46057 | C1146: AMAZON MKTPL*9D5U24U Amzn.com/bill WA 02/04 | D1146: -10.66 | E1146: DEBIT_CARD | F1146: 4706.46 | G1146: {=IF(AND(ISNUMBER(SEARCH("UBER",C1146)),ISNUMBER(SEARCH("EATS",C1146))),"Uber Eats",IF(LEFT(C1146,6)="CHECK ","Checks Paid",IF(OR(E1146="BILLPAY",ISNUMBER(SEARCH("FRANCHISE TAX",C1146)),ISNUMBER(SEARCH("NEXTLINK",C1146))),"Personal - House Bills",IF(AND(ISNUMBER(SEARCH("PAYMENT FROM",C1146)),ISNUMBER(SEARCH("JOE SAUNDERS",C1146))),"Zelle from Joe Saunders",IF(AND(ISNUMBER(SEARCH("PAYMENT TO",C1146)),ISNUMBER(SEARCH("JOE SAUNDERS",C1146))),"Zelle to Joe Saunders",IF(OR(ISNUMBER(SEARCH("NEW ORLEANS",C1146)),ISNUMBER(SEARCH("KENNER",C1146)),ISNUMBER(SEARCH("HENRY HOWARD",C1146)),ISNUMBER(SEARCH("MISS CLAUDIA",C1146))),"Personal Travel - New Orleans",IFERROR(INDEX('Category Rules'!$B$2:$B$194,MATCH(TRUE,ISNUMBER(SEARCH('Category Rules'!$A$2:$A$194,C1146)),0)),"")))))))} -> Amazon
A1147: DEBIT | B1147: 46057 | C1147: WITHERSPOONS ANTIQUE MA GRANBURY TX 02/03 | D1147: -176.98 | E1147: DEBIT_CARD | F1147: 4717.12 | G1147: {=IF(AND(ISNUMBER(SEARCH("UBER",C1147)),ISNUMBER(SEARCH("EATS",C1147))),"Uber Eats",IF(LEFT(C1147,6)="CHECK ","Checks Paid",IF(OR(E1147="BILLPAY",ISNUMBER(SEARCH("FRANCHISE TAX",C1147)),ISNUMBER(SEARCH("NEXTLINK",C1147))),"Personal - House Bills",IF(AND(ISNUMBER(SEARCH("PAYMENT FROM",C1147)),ISNUMBER(SEARCH("JOE SAUNDERS",C1147))),"Zelle from Joe Saunders",IF(AND(ISNUMBER(SEARCH("PAYMENT TO",C1147)),ISNUMBER(SEARCH("JOE SAUNDERS",C1147))),"Zelle to Joe Saunders",IF(OR(ISNUMBER(SEARCH("NEW ORLEANS",C1147)),ISNUMBER(SEARCH("KENNER",C1147)),ISNUMBER(SEARCH("HENRY HOWARD",C1147)),ISNUMBER(SEARCH("MISS CLAUDIA",C1147))),"Personal Travel - New Orleans",IFERROR(INDEX('Category Rules'!$B$2:$B$194,MATCH(TRUE,ISNUMBER(SEARCH('Category Rules'!$A$2:$A$194,C1147)),0)),"")))))))} -> Personal - Shopping
A1148: DEBIT | B1148: 46057 | C1148: FANDANGO * FANDANGO.COM CA 02/03 | D1148: -43.36 | E1148: DEBIT_CARD | F1148: 4894.1 | G1148: {=IF(AND(ISNUMBER(SEARCH("UBER",C1148)),ISNUMBER(SEARCH("EATS",C1148))),"Uber Eats",IF(LEFT(C1148,6)="CHECK ","Checks Paid",IF(OR(E1148="BILLPAY",ISNUMBER(SEARCH("FRANCHISE TAX",C1148)),ISNUMBER(SEARCH("NEXTLINK",C1148))),"Personal - House Bills",IF(AND(ISNUMBER(SEARCH("PAYMENT FROM",C1148)),ISNUMBER(SEARCH("JOE SAUNDERS",C1148))),"Zelle from Joe Saunders",IF(AND(ISNUMBER(SEARCH("PAYMENT TO",C1148)),ISNUMBER(SEARCH("JOE SAUNDERS",C1148))),"Zelle to Joe Saunders",IF(OR(ISNUMBER(SEARCH("NEW ORLEANS",C1148)),ISNUMBER(SEARCH("KENNER",C1148)),ISNUMBER(SEARCH("HENRY HOWARD",C1148)),ISNUMBER(SEARCH("MISS CLAUDIA",C1148))),"Personal Travel - New Orleans",IFERROR(INDEX('Category Rules'!$B$2:$B$194,MATCH(TRUE,ISNUMBER(SEARCH('Category Rules'!$A$2:$A$194,C1148)),0)),"")))))))} -> Personal - Entertainment
A1149: CREDIT | B1149: 46057 | C1149: Zelle payment from MARY MARGARET TRAHAN 27942980358 | D1149: 150 | E1149: QUICKPAY_CREDIT | F1149: 4937.46 | G1149: {=IF(AND(ISNUMBER(SEARCH("UBER",C1149)),ISNUMBER(SEARCH("EATS",C1149))),"Uber Eats",IF(LEFT(C1149,6)="CHECK ","Checks Paid",IF(OR(E1149="BILLPAY",ISNUMBER(SEARCH("FRANCHISE TAX",C1149)),ISNUMBER(SEARCH("NEXTLINK",C1149))),"Personal - House Bills",IF(AND(ISNUMBER(SEARCH("PAYMENT FROM",C1149)),ISNUMBER(SEARCH("JOE SAUNDERS",C1149))),"Zelle from Joe Saunders",IF(AND(ISNUMBER(SEARCH("PAYMENT TO",C1149)),ISNUMBER(SEARCH("JOE SAUNDERS",C1149))),"Zelle to Joe Saunders",IF(OR(ISNUMBER(SEARCH("NEW ORLEANS",C1149)),ISNUMBER(SEARCH("KENNER",C1149)),ISNUMBER(SEARCH("HENRY HOWARD",C1149)),ISNUMBER(SEARCH("MISS CLAUDIA",C1149))),"Personal Travel - New Orleans",IFERROR(INDEX('Category Rules'!$B$2:$B$194,MATCH(TRUE,ISNUMBER(SEARCH('Category Rules'!$A$2:$A$194,C1149)),0)),"")))))))} -> Zelle from Mary Margaret Trahan
A1150: DEBIT | B1150: 46056 | C1150: APPLE.COM/BILL 866-712-7753 CA 02/02 | D1150: -3.99 | E1150: DEBIT_CARD | F1150: 4787.46 | G1150: {=IF(AND(ISNUMBER(SEARCH("UBER",C1150)),ISNUMBER(SEARCH("EATS",C1150))),"Uber Eats",IF(LEFT(C1150,6)="CHECK ","Checks Paid",IF(OR(E1150="BILLPAY",ISNUMBER(SEARCH("FRANCHISE TAX",C1150)),ISNUMBER(SEARCH("NEXTLINK",C1150))),"Personal - House Bills",IF(AND(ISNUMBER(SEARCH("PAYMENT FROM",C1150)),ISNUMBER(SEARCH("JOE SAUNDERS",C1150))),"Zelle from Joe Saunders",IF(AND(ISNUMBER(SEARCH("PAYMENT TO",C1150)),ISNUMBER(SEARCH("JOE SAUNDERS",C1150))),"Zelle to Joe Saunders",IF(OR(ISNUMBER(SEARCH("NEW ORLEANS",C1150)),ISNUMBER(SEARCH("KENNER",C1150)),ISNUMBER(SEARCH("HENRY HOWARD",C1150)),ISNUMBER(SEARCH("MISS CLAUDIA",C1150))),"Personal Travel - New Orleans",IFERROR(INDEX('Category Rules'!$B$2:$B$194,MATCH(TRUE,ISNUMBER(SEARCH('Category Rules'!$A$2:$A$194,C1150)),0)),"")))))))} -> Apple
A1151: DEBIT | B1151: 46056 | C1151: AMERICAN AIR00144849199 FORT WORTH TX 02/02 | D1151: -35 | E1151: DEBIT_CARD | F1151: 4791.45 | G1151: {=IF(AND(ISNUMBER(SEARCH("UBER",C1151)),ISNUMBER(SEARCH("EATS",C1151))),"Uber Eats",IF(LEFT(C1151,6)="CHECK ","Checks Paid",IF(OR(E1151="BILLPAY",ISNUMBER(SEARCH("FRANCHISE TAX",C1151)),ISNUMBER(SEARCH("NEXTLINK",C1151))),"Personal - House Bills",IF(AND(ISNUMBER(SEARCH("PAYMENT FROM",C1151)),ISNUMBER(SEARCH("JOE SAUNDERS",C1151))),"Zelle from Joe Saunders",IF(AND(ISNUMBER(SEARCH("PAYMENT TO",C1151)),ISNUMBER(SEARCH("JOE SAUNDERS",C1151))),"Zelle to Joe Saunders",IF(OR(ISNUMBER(SEARCH("NEW ORLEANS",C1151)),ISNUMBER(SEARCH("KENNER",C1151)),ISNUMBER(SEARCH("HENRY HOWARD",C1151)),ISNUMBER(SEARCH("MISS CLAUDIA",C1151))),"Personal Travel - New Orleans",IFERROR(INDEX('Category Rules'!$B$2:$B$194,MATCH(TRUE,ISNUMBER(SEARCH('Category Rules'!$A$2:$A$194,C1151)),0)),"")))))))} -> Personal Travel
A1152: DEBIT | B1152: 46056 | C1152: AMERICAN AIR00144849199 FORT WORTH TX 02/02 | D1152: -35 | E1152: DEBIT_CARD | F1152: 4826.45 | G1152: {=IF(AND(ISNUMBER(SEARCH("UBER",C1152)),ISNUMBER(SEARCH("EATS",C1152))),"Uber Eats",IF(LEFT(C1152,6)="CHECK ","Checks Paid",IF(OR(E1152="BILLPAY",ISNUMBER(SEARCH("FRANCHISE TAX",C1152)),ISNUMBER(SEARCH("NEXTLINK",C1152))),"Personal - House Bills",IF(AND(ISNUMBER(SEARCH("PAYMENT FROM",C1152)),ISNUMBER(SEARCH("JOE SAUNDERS",C1152))),"Zelle from Joe Saunders",IF(AND(ISNUMBER(SEARCH("PAYMENT TO",C1152)),ISNUMBER(SEARCH("JOE SAUNDERS",C1152))),"Zelle to Joe Saunders",IF(OR(ISNUMBER(SEARCH("NEW ORLEANS",C1152)),ISNUMBER(SEARCH("KENNER",C1152)),ISNUMBER(SEARCH("HENRY HOWARD",C1152)),ISNUMBER(SEARCH("MISS CLAUDIA",C1152))),"Personal Travel - New Orleans",IFERROR(INDEX('Category Rules'!$B$2:$B$194,MATCH(TRUE,ISNUMBER(SEARCH('Category Rules'!$A$2:$A$194,C1152)),0)),"")))))))} -> Personal Travel
A1153: DEBIT | B1153: 46056 | C1153: AMERICAN AIR00144849199 FORT WORTH TX 02/02 | D1153: -35 | E1153: DEBIT_CARD | F1153: 4861.45 | G1153: {=IF(AND(ISNUMBER(SEARCH("UBER",C1153)),ISNUMBER(SEARCH("EATS",C1153))),"Uber Eats",IF(LEFT(C1153,6)="CHECK ","Checks Paid",IF(OR(E1153="BILLPAY",ISNUMBER(SEARCH("FRANCHISE TAX",C1153)),ISNUMBER(SEARCH("NEXTLINK",C1153))),"Personal - House Bills",IF(AND(ISNUMBER(SEARCH("PAYMENT FROM",C1153)),ISNUMBER(SEARCH("JOE SAUNDERS",C1153))),"Zelle from Joe Saunders",IF(AND(ISNUMBER(SEARCH("PAYMENT TO",C1153)),ISNUMBER(SEARCH("JOE SAUNDERS",C1153))),"Zelle to Joe Saunders",IF(OR(ISNUMBER(SEARCH("NEW ORLEANS",C1153)),ISNUMBER(SEARCH("KENNER",C1153)),ISNUMBER(SEARCH("HENRY HOWARD",C1153)),ISNUMBER(SEARCH("MISS CLAUDIA",C1153))),"Personal Travel - New Orleans",IFERROR(INDEX('Category Rules'!$B$2:$B$194,MATCH(TRUE,ISNUMBER(SEARCH('Category Rules'!$A$2:$A$194,C1153)),0)),"")))))))} -> Personal Travel
A1154: DEBIT | B1154: 46056 | C1154: Amazon.com*X947A51O3 Amzn.com/bill WA 02/03 | D1154: -37.31 | E1154: DEBIT_CARD | F1154: 4896.45 | G1154: {=IF(AND(ISNUMBER(SEARCH("UBER",C1154)),ISNUMBER(SEARCH("EATS",C1154))),"Uber Eats",IF(LEFT(C1154,6)="CHECK ","Checks Paid",IF(OR(E1154="BILLPAY",ISNUMBER(SEARCH("FRANCHISE TAX",C1154)),ISNUMBER(SEARCH("NEXTLINK",C1154))),"Personal - House Bills",IF(AND(ISNUMBER(SEARCH("PAYMENT FROM",C1154)),ISNUMBER(SEARCH("JOE SAUNDERS",C1154))),"Zelle from Joe Saunders",IF(AND(ISNUMBER(SEARCH("PAYMENT TO",C1154)),ISNUMBER(SEARCH("JOE SAUNDERS",C1154))),"Zelle to Joe Saunders",IF(OR(ISNUMBER(SEARCH("NEW ORLEANS",C1154)),ISNUMBER(SEARCH("KENNER",C1154)),ISNUMBER(SEARCH("HENRY HOWARD",C1154)),ISNUMBER(SEARCH("MISS CLAUDIA",C1154))),"Personal Travel - New Orleans",IFERROR(INDEX('Category Rules'!$B$2:$B$194,MATCH(TRUE,ISNUMBER(SEARCH('Category Rules'!$A$2:$A$194,C1154)),0)),"")))))))} -> Amazon
A1155: CREDIT | B1155: 46056 | C1155: Online Transfer from CHK ...1168 transaction#: 27936175999 | D1155: 2000 | E1155: ACCT_XFER | F1155: 4933.76 | G1155: {=IF(AND(ISNUMBER(SEARCH("UBER",C1155)),ISNUMBER(SEARCH("EATS",C1155))),"Uber Eats",IF(LEFT(C1155,6)="CHECK ","Checks Paid",IF(OR(E1155="BILLPAY",ISNUMBER(SEARCH("FRANCHISE TAX",C1155)),ISNUMBER(SEARCH("NEXTLINK",C1155))),"Personal - House Bills",IF(AND(ISNUMBER(SEARCH("PAYMENT FROM",C1155)),ISNUMBER(SEARCH("JOE SAUNDERS",C1155))),"Zelle from Joe Saunders",IF(AND(ISNUMBER(SEARCH("PAYMENT TO",C1155)),ISNUMBER(SEARCH("JOE SAUNDERS",C1155))),"Zelle to Joe Saunders",IF(OR(ISNUMBER(SEARCH("NEW ORLEANS",C1155)),ISNUMBER(SEARCH("KENNER",C1155)),ISNUMBER(SEARCH("HENRY HOWARD",C1155)),ISNUMBER(SEARCH("MISS CLAUDIA",C1155))),"Personal Travel - New Orleans",IFERROR(INDEX('Category Rules'!$B$2:$B$194,MATCH(TRUE,ISNUMBER(SEARCH('Category Rules'!$A$2:$A$194,C1155)),0)),"")))))))} -> Transfer from DWG Capital Group
A1156: DEBIT | B1156: 46055 | C1156: HOBBYLOBBY WEATHERFORD TX 045553 02/02 | D1156: -21.49 | E1156: DEBIT_CARD | F1156: 2933.76 | G1156: Personal - Shopping
A1157: DEBIT | B1157: 46055 | C1157: SQ *REA COMMERCIAL SECU gosq.com CA 02/02 | D1157: -100 | E1157: DEBIT_CARD | F1157: 2955.25 | G1157: {=IF(AND(ISNUMBER(SEARCH("UBER",C1157)),ISNUMBER(SEARCH("EATS",C1157))),"Uber Eats",IF(LEFT(C1157,6)="CHECK ","Checks Paid",IF(OR(E1157="BILLPAY",ISNUMBER(SEARCH("FRANCHISE TAX",C1157)),ISNUMBER(SEARCH("NEXTLINK",C1157))),"Personal - House Bills",IF(AND(ISNUMBER(SEARCH("PAYMENT FROM",C1157)),ISNUMBER(SEARCH("JOE SAUNDERS",C1157))),"Zelle from Joe Saunders",IF(AND(ISNUMBER(SEARCH("PAYMENT TO",C1157)),ISNUMBER(SEARCH("JOE SAUNDERS",C1157))),"Zelle to Joe Saunders",IF(OR(ISNUMBER(SEARCH("NEW ORLEANS",C1157)),ISNUMBER(SEARCH("KENNER",C1157)),ISNUMBER(SEARCH("HENRY HOWARD",C1157)),ISNUMBER(SEARCH("MISS CLAUDIA",C1157))),"Personal Travel - New Orleans",IFERROR(INDEX('Category Rules'!$B$2:$B$194,MATCH(TRUE,ISNUMBER(SEARCH('Category Rules'!$A$2:$A$194,C1157)),0)),"")))))))} -> Personal - Subscription
A1158: DEBIT | B1158: 46055 | C1158: FSP*CAMFT 858-292-2638 CA 02/01 | D1158: -227 | E1158: DEBIT_CARD | F1158: 3055.25 | G1158: {=IF(AND(ISNUMBER(SEARCH("UBER",C1158)),ISNUMBER(SEARCH("EATS",C1158))),"Uber Eats",IF(LEFT(C1158,6)="CHECK ","Checks Paid",IF(OR(E1158="BILLPAY",ISNUMBER(SEARCH("FRANCHISE TAX",C1158)),ISNUMBER(SEARCH("NEXTLINK",C1158))),"Personal - House Bills",IF(AND(ISNUMBER(SEARCH("PAYMENT FROM",C1158)),ISNUMBER(SEARCH("JOE SAUNDERS",C1158))),"Zelle from Joe Saunders",IF(AND(ISNUMBER(SEARCH("PAYMENT TO",C1158)),ISNUMBER(SEARCH("JOE SAUNDERS",C1158))),"Zelle to Joe Saunders",IF(OR(ISNUMBER(SEARCH("NEW ORLEANS",C1158)),ISNUMBER(SEARCH("KENNER",C1158)),ISNUMBER(SEARCH("HENRY HOWARD",C1158)),ISNUMBER(SEARCH("MISS CLAUDIA",C1158))),"Personal Travel - New Orleans",IFERROR(INDEX('Category Rules'!$B$2:$B$194,MATCH(TRUE,ISNUMBER(SEARCH('Category Rules'!$A$2:$A$194,C1158)),0)),"")))))))} -> Personal - Work
A1159: DEBIT | B1159: 46055 | C1159: LS LEAVES BOOK AND TE 168-22334832 TX 01/31 | D1159: -30.64 | E1159: DEBIT_CARD | F1159: 3282.25 | G1159: Personal - Shopping
A1160: DEBIT | B1160: 46055 | C1160: BENITOS RESTAURANTES FORT WORTH TX 01/31 | D1160: -99.65 | E1160: DEBIT_CARD | F1160: 3312.89 | G1160: {=IF(AND(ISNUMBER(SEARCH("UBER",C1160)),ISNUMBER(SEARCH("EATS",C1160))),"Uber Eats",IF(LEFT(C1160,6)="CHECK ","Checks Paid",IF(OR(E1160="BILLPAY",ISNUMBER(SEARCH("FRANCHISE TAX",C1160)),ISNUMBER(SEARCH("NEXTLINK",C1160))),"Personal - House Bills",IF(AND(ISNUMBER(SEARCH("PAYMENT FROM",C1160)),ISNUMBER(SEARCH("JOE SAUNDERS",C1160))),"Zelle from Joe Saunders",IF(AND(ISNUMBER(SEARCH("PAYMENT TO",C1160)),ISNUMBER(SEARCH("JOE SAUNDERS",C1160))),"Zelle to Joe Saunders",IF(OR(ISNUMBER(SEARCH("NEW ORLEANS",C1160)),ISNUMBER(SEARCH("KENNER",C1160)),ISNUMBER(SEARCH("HENRY HOWARD",C1160)),ISNUMBER(SEARCH("MISS CLAUDIA",C1160))),"Personal Travel - New Orleans",IFERROR(INDEX('Category Rules'!$B$2:$B$194,MATCH(TRUE,ISNUMBER(SEARCH('Category Rules'!$A$2:$A$194,C1160)),0)),"")))))))} -> Personal - Food
A1161: DEBIT | B1161: 46055 | C1161: BLUE SHIELD CALIFORNI 800-393-6130 CA 01/31 | D1161: -1275.3 | E1161: DEBIT_CARD | F1161: 3412.54 | G1161: {=IF(AND(ISNUMBER(SEARCH("UBER",C1161)),ISNUMBER(SEARCH("EATS",C1161))),"Uber Eats",IF(LEFT(C1161,6)="CHECK ","Checks Paid",IF(OR(E1161="BILLPAY",ISNUMBER(SEARCH("FRANCHISE TAX",C1161)),ISNUMBER(SEARCH("NEXTLINK",C1161))),"Personal - House Bills",IF(AND(ISNUMBER(SEARCH("PAYMENT FROM",C1161)),ISNUMBER(SEARCH("JOE SAUNDERS",C1161))),"Zelle from Joe Saunders",IF(AND(ISNUMBER(SEARCH("PAYMENT TO",C1161)),ISNUMBER(SEARCH("JOE SAUNDERS",C1161))),"Zelle to Joe Saunders",IF(OR(ISNUMBER(SEARCH("NEW ORLEANS",C1161)),ISNUMBER(SEARCH("KENNER",C1161)),ISNUMBER(SEARCH("HENRY HOWARD",C1161)),ISNUMBER(SEARCH("MISS CLAUDIA",C1161))),"Personal Travel - New Orleans",IFERROR(INDEX('Category Rules'!$B$2:$B$194,MATCH(TRUE,ISNUMBER(SEARCH('Category Rules'!$A$2:$A$194,C1161)),0)),"")))))))} -> Personal - Health Insurance
A1162: DEBIT | B1162: 46055 | C1162: EATZI'S - FT. WORTH FORT WORTH TX 01/30 | D1162: -95.74 | E1162: DEBIT_CARD | F1162: 4687.84 | G1162: Personal - Food
A1163: DEBIT | B1163: 46055 | C1163: AMERICAN AIR00183243373 FORT WORTH TX 01/30 | D1163: -29.03 | E1163: DEBIT_CARD | F1163: 4783.58 | G1163: {=IF(AND(ISNUMBER(SEARCH("UBER",C1163)),ISNUMBER(SEARCH("EATS",C1163))),"Uber Eats",IF(LEFT(C1163,6)="CHECK ","Checks Paid",IF(OR(E1163="BILLPAY",ISNUMBER(SEARCH("FRANCHISE TAX",C1163)),ISNUMBER(SEARCH("NEXTLINK",C1163))),"Personal - House Bills",IF(AND(ISNUMBER(SEARCH("PAYMENT FROM",C1163)),ISNUMBER(SEARCH("JOE SAUNDERS",C1163))),"Zelle from Joe Saunders",IF(AND(ISNUMBER(SEARCH("PAYMENT TO",C1163)),ISNUMBER(SEARCH("JOE SAUNDERS",C1163))),"Zelle to Joe Saunders",IF(OR(ISNUMBER(SEARCH("NEW ORLEANS",C1163)),ISNUMBER(SEARCH("KENNER",C1163)),ISNUMBER(SEARCH("HENRY HOWARD",C1163)),ISNUMBER(SEARCH("MISS CLAUDIA",C1163))),"Personal Travel - New Orleans",IFERROR(INDEX('Category Rules'!$B$2:$B$194,MATCH(TRUE,ISNUMBER(SEARCH('Category Rules'!$A$2:$A$194,C1163)),0)),"")))))))} -> Personal Travel
A1164: DEBIT | B1164: 46055 | C1164: AMERICAN AIR00183243373 FORT WORTH TX 01/30 | D1164: -38.41 | E1164: DEBIT_CARD | F1164: 4812.61 | G1164: {=IF(AND(ISNUMBER(SEARCH("UBER",C1164)),ISNUMBER(SEARCH("EATS",C1164))),"Uber Eats",IF(LEFT(C1164,6)="CHECK ","Checks Paid",IF(OR(E1164="BILLPAY",ISNUMBER(SEARCH("FRANCHISE TAX",C1164)),ISNUMBER(SEARCH("NEXTLINK",C1164))),"Personal - House Bills",IF(AND(ISNUMBER(SEARCH("PAYMENT FROM",C1164)),ISNUMBER(SEARCH("JOE SAUNDERS",C1164))),"Zelle from Joe Saunders",IF(AND(ISNUMBER(SEARCH("PAYMENT TO",C1164)),ISNUMBER(SEARCH("JOE SAUNDERS",C1164))),"Zelle to Joe Saunders",IF(OR(ISNUMBER(SEARCH("NEW ORLEANS",C1164)),ISNUMBER(SEARCH("KENNER",C1164)),ISNUMBER(SEARCH("HENRY HOWARD",C1164)),ISNUMBER(SEARCH("MISS CLAUDIA",C1164))),"Personal Travel - New Orleans",IFERROR(INDEX('Category Rules'!$B$2:$B$194,MATCH(TRUE,ISNUMBER(SEARCH('Category Rules'!$A$2:$A$194,C1164)),0)),"")))))))} -> Personal Travel
A1165: DEBIT | B1165: 46055 | C1165: AMERICAN AIR00183243373 FORT WORTH TX 01/30 | D1165: -38.41 | E1165: DEBIT_CARD | F1165: 4851.02 | G1165: {=IF(AND(ISNUMBER(SEARCH("UBER",C1165)),ISNUMBER(SEARCH("EATS",C1165))),"Uber Eats",IF(LEFT(C1165,6)="CHECK ","Checks Paid",IF(OR(E1165="BILLPAY",ISNUMBER(SEARCH("FRANCHISE TAX",C1165)),ISNUMBER(SEARCH("NEXTLINK",C1165))),"Personal - House Bills",IF(AND(ISNUMBER(SEARCH("PAYMENT FROM",C1165)),ISNUMBER(SEARCH("JOE SAUNDERS",C1165))),"Zelle from Joe Saunders",IF(AND(ISNUMBER(SEARCH("PAYMENT TO",C1165)),ISNUMBER(SEARCH("JOE SAUNDERS",C1165))),"Zelle to Joe Saunders",IF(OR(ISNUMBER(SEARCH("NEW ORLEANS",C1165)),ISNUMBER(SEARCH("KENNER",C1165)),ISNUMBER(SEARCH("HENRY HOWARD",C1165)),ISNUMBER(SEARCH("MISS CLAUDIA",C1165))),"Personal Travel - New Orleans",IFERROR(INDEX('Category Rules'!$B$2:$B$194,MATCH(TRUE,ISNUMBER(SEARCH('Category Rules'!$A$2:$A$194,C1165)),0)),"")))))))} -> Personal Travel
A1166: DEBIT | B1166: 46055 | C1166: AMERICAN AIR00174063275 FORT WORTH TX 01/30 | D1166: -274.4 | E1166: DEBIT_CARD | F1166: 4889.43 | G1166: {=IF(AND(ISNUMBER(SEARCH("UBER",C1166)),ISNUMBER(SEARCH("EATS",C1166))),"Uber Eats",IF(LEFT(C1166,6)="CHECK ","Checks Paid",IF(OR(E1166="BILLPAY",ISNUMBER(SEARCH("FRANCHISE TAX",C1166)),ISNUMBER(SEARCH("NEXTLINK",C1166))),"Personal - House Bills",IF(AND(ISNUMBER(SEARCH("PAYMENT FROM",C1166)),ISNUMBER(SEARCH("JOE SAUNDERS",C1166))),"Zelle from Joe Saunders",IF(AND(ISNUMBER(SEARCH("PAYMENT TO",C1166)),ISNUMBER(SEARCH("JOE SAUNDERS",C1166))),"Zelle to Joe Saunders",IF(OR(ISNUMBER(SEARCH("NEW ORLEANS",C1166)),ISNUMBER(SEARCH("KENNER",C1166)),ISNUMBER(SEARCH("HENRY HOWARD",C1166)),ISNUMBER(SEARCH("MISS CLAUDIA",C1166))),"Personal Travel - New Orleans",IFERROR(INDEX('Category Rules'!$B$2:$B$194,MATCH(TRUE,ISNUMBER(SEARCH('Category Rules'!$A$2:$A$194,C1166)),0)),"")))))))} -> Personal Travel
A1167: DEBIT | B1167: 46055 | C1167: AMERICAN AIR00174063275 FORT WORTH TX 01/30 | D1167: -274.4 | E1167: DEBIT_CARD | F1167: 5163.83 | G1167: {=IF(AND(ISNUMBER(SEARCH("UBER",C1167)),ISNUMBER(SEARCH("EATS",C1167))),"Uber Eats",IF(LEFT(C1167,6)="CHECK ","Checks Paid",IF(OR(E1167="BILLPAY",ISNUMBER(SEARCH("FRANCHISE TAX",C1167)),ISNUMBER(SEARCH("NEXTLINK",C1167))),"Personal - House Bills",IF(AND(ISNUMBER(SEARCH("PAYMENT FROM",C1167)),ISNUMBER(SEARCH("JOE SAUNDERS",C1167))),"Zelle from Joe Saunders",IF(AND(ISNUMBER(SEARCH("PAYMENT TO",C1167)),ISNUMBER(SEARCH("JOE SAUNDERS",C1167))),"Zelle to Joe Saunders",IF(OR(ISNUMBER(SEARCH("NEW ORLEANS",C1167)),ISNUMBER(SEARCH("KENNER",C1167)),ISNUMBER(SEARCH("HENRY HOWARD",C1167)),ISNUMBER(SEARCH("MISS CLAUDIA",C1167))),"Personal Travel - New Orleans",IFERROR(INDEX('Category Rules'!$B$2:$B$194,MATCH(TRUE,ISNUMBER(SEARCH('Category Rules'!$A$2:$A$194,C1167)),0)),"")))))))} -> Personal Travel
A1168: DEBIT | B1168: 46055 | C1168: AMERICAN AIR00174063275 FORT WORTH TX 01/30 | D1168: -274.4 | E1168: DEBIT_CARD | F1168: 5438.23 | G1168: {=IF(AND(ISNUMBER(SEARCH("UBER",C1168)),ISNUMBER(SEARCH("EATS",C1168))),"Uber Eats",IF(LEFT(C1168,6)="CHECK ","Checks Paid",IF(OR(E1168="BILLPAY",ISNUMBER(SEARCH("FRANCHISE TAX",C1168)),ISNUMBER(SEARCH("NEXTLINK",C1168))),"Personal - House Bills",IF(AND(ISNUMBER(SEARCH("PAYMENT FROM",C1168)),ISNUMBER(SEARCH("JOE SAUNDERS",C1168))),"Zelle from Joe Saunders",IF(AND(ISNUMBER(SEARCH("PAYMENT TO",C1168)),ISNUMBER(SEARCH("JOE SAUNDERS",C1168))),"Zelle to Joe Saunders",IF(OR(ISNUMBER(SEARCH("NEW ORLEANS",C1168)),ISNUMBER(SEARCH("KENNER",C1168)),ISNUMBER(SEARCH("HENRY HOWARD",C1168)),ISNUMBER(SEARCH("MISS CLAUDIA",C1168))),"Personal Travel - New Orleans",IFERROR(INDEX('Category Rules'!$B$2:$B$194,MATCH(TRUE,ISNUMBER(SEARCH('Category Rules'!$A$2:$A$194,C1168)),0)),"")))))))} -> Personal Travel
A1169: DEBIT | B1169: 46055 | C1169: EXPEDIA 73361550876210 EXPEDIA.COM WA 01/30 | D1169: -32.53 | E1169: DEBIT_CARD | F1169: 5712.63 | G1169: {=IF(AND(ISNUMBER(SEARCH("UBER",C1169)),ISNUMBER(SEARCH("EATS",C1169))),"Uber Eats",IF(LEFT(C1169,6)="CHECK ","Checks Paid",IF(OR(E1169="BILLPAY",ISNUMBER(SEARCH("FRANCHISE TAX",C1169)),ISNUMBER(SEARCH("NEXTLINK",C1169))),"Personal - House Bills",IF(AND(ISNUMBER(SEARCH("PAYMENT FROM",C1169)),ISNUMBER(SEARCH("JOE SAUNDERS",C1169))),"Zelle from Joe Saunders",IF(AND(ISNUMBER(SEARCH("PAYMENT TO",C1169)),ISNUMBER(SEARCH("JOE SAUNDERS",C1169))),"Zelle to Joe Saunders",IF(OR(ISNUMBER(SEARCH("NEW ORLEANS",C1169)),ISNUMBER(SEARCH("KENNER",C1169)),ISNUMBER(SEARCH("HENRY HOWARD",C1169)),ISNUMBER(SEARCH("MISS CLAUDIA",C1169))),"Personal Travel - New Orleans",IFERROR(INDEX('Category Rules'!$B$2:$B$194,MATCH(TRUE,ISNUMBER(SEARCH('Category Rules'!$A$2:$A$194,C1169)),0)),"")))))))} -> Personal Travel
A1170: DEBIT | B1170: 46055 | C1170: AMERICAN AIR00174060200 FORT WORTH TX 01/31 | D1170: 418.47 | E1170: DEBIT_CARD | F1170: 5745.16 | G1170: {=IF(AND(ISNUMBER(SEARCH("UBER",C1170)),ISNUMBER(SEARCH("EATS",C1170))),"Uber Eats",IF(LEFT(C1170,6)="CHECK ","Checks Paid",IF(OR(E1170="BILLPAY",ISNUMBER(SEARCH("FRANCHISE TAX",C1170)),ISNUMBER(SEARCH("NEXTLINK",C1170))),"Personal - House Bills",IF(AND(ISNUMBER(SEARCH("PAYMENT FROM",C1170)),ISNUMBER(SEARCH("JOE SAUNDERS",C1170))),"Zelle from Joe Saunders",IF(AND(ISNUMBER(SEARCH("PAYMENT TO",C1170)),ISNUMBER(SEARCH("JOE SAUNDERS",C1170))),"Zelle to Joe Saunders",IF(OR(ISNUMBER(SEARCH("NEW ORLEANS",C1170)),ISNUMBER(SEARCH("KENNER",C1170)),ISNUMBER(SEARCH("HENRY HOWARD",C1170)),ISNUMBER(SEARCH("MISS CLAUDIA",C1170))),"Personal Travel - New Orleans",IFERROR(INDEX('Category Rules'!$B$2:$B$194,MATCH(TRUE,ISNUMBER(SEARCH('Category Rules'!$A$2:$A$194,C1170)),0)),"")))))))} -> Personal Travel
A1171: DEBIT | B1171: 46052 | C1171: WHOLEFDS FTW #10 3400 FORT WORTH TX 262781 01/30 | D1171: -587.14 | E1171: DEBIT_CARD | F1171: 5326.69 | G1171: {=IF(AND(ISNUMBER(SEARCH("UBER",C1171)),ISNUMBER(SEARCH("EATS",C1171))),"Uber Eats",IF(LEFT(C1171,6)="CHECK ","Checks Paid",IF(OR(E1171="BILLPAY",ISNUMBER(SEARCH("FRANCHISE TAX",C1171)),ISNUMBER(SEARCH("NEXTLINK",C1171))),"Personal - House Bills",IF(AND(ISNUMBER(SEARCH("PAYMENT FROM",C1171)),ISNUMBER(SEARCH("JOE SAUNDERS",C1171))),"Zelle from Joe Saunders",IF(AND(ISNUMBER(SEARCH("PAYMENT TO",C1171)),ISNUMBER(SEARCH("JOE SAUNDERS",C1171))),"Zelle to Joe Saunders",IF(OR(ISNUMBER(SEARCH("NEW ORLEANS",C1171)),ISNUMBER(SEARCH("KENNER",C1171)),ISNUMBER(SEARCH("HENRY HOWARD",C1171)),ISNUMBER(SEARCH("MISS CLAUDIA",C1171))),"Personal Travel - New Orleans",IFERROR(INDEX('Category Rules'!$B$2:$B$194,MATCH(TRUE,ISNUMBER(SEARCH('Category Rules'!$A$2:$A$194,C1171)),0)),"")))))))} -> Personal - Food
A1172: DEBIT | B1172: 46052 | C1172: WHOLEFDS FTW #10 3400 FORT WORTH TX 665894 01/30 | D1172: -11.5 | E1172: DEBIT_CARD | F1172: 5913.83 | G1172: {=IF(AND(ISNUMBER(SEARCH("UBER",C1172)),ISNUMBER(SEARCH("EATS",C1172))),"Uber Eats",IF(LEFT(C1172,6)="CHECK ","Checks Paid",IF(OR(E1172="BILLPAY",ISNUMBER(SEARCH("FRANCHISE TAX",C1172)),ISNUMBER(SEARCH("NEXTLINK",C1172))),"Personal - House Bills",IF(AND(ISNUMBER(SEARCH("PAYMENT FROM",C1172)),ISNUMBER(SEARCH("JOE SAUNDERS",C1172))),"Zelle from Joe Saunders",IF(AND(ISNUMBER(SEARCH("PAYMENT TO",C1172)),ISNUMBER(SEARCH("JOE SAUNDERS",C1172))),"Zelle to Joe Saunders",IF(OR(ISNUMBER(SEARCH("NEW ORLEANS",C1172)),ISNUMBER(SEARCH("KENNER",C1172)),ISNUMBER(SEARCH("HENRY HOWARD",C1172)),ISNUMBER(SEARCH("MISS CLAUDIA",C1172))),"Personal Travel - New Orleans",IFERROR(INDEX('Category Rules'!$B$2:$B$194,MATCH(TRUE,ISNUMBER(SEARCH('Category Rules'!$A$2:$A$194,C1172)),0)),"")))))))} -> Personal - Food
A1173: DEBIT | B1173: 46052 | C1173: PENTESTER.COM PENTESTER.COM FL 01/30 | D1173: -19 | E1173: DEBIT_CARD | F1173: 5925.33 | G1173: {=IF(AND(ISNUMBER(SEARCH("UBER",C1173)),ISNUMBER(SEARCH("EATS",C1173))),"Uber Eats",IF(LEFT(C1173,6)="CHECK ","Checks Paid",IF(OR(E1173="BILLPAY",ISNUMBER(SEARCH("FRANCHISE TAX",C1173)),ISNUMBER(SEARCH("NEXTLINK",C1173))),"Personal - House Bills",IF(AND(ISNUMBER(SEARCH("PAYMENT FROM",C1173)),ISNUMBER(SEARCH("JOE SAUNDERS",C1173))),"Zelle from Joe Saunders",IF(AND(ISNUMBER(SEARCH("PAYMENT TO",C1173)),ISNUMBER(SEARCH("JOE SAUNDERS",C1173))),"Zelle to Joe Saunders",IF(OR(ISNUMBER(SEARCH("NEW ORLEANS",C1173)),ISNUMBER(SEARCH("KENNER",C1173)),ISNUMBER(SEARCH("HENRY HOWARD",C1173)),ISNUMBER(SEARCH("MISS CLAUDIA",C1173))),"Personal Travel - New Orleans",IFERROR(INDEX('Category Rules'!$B$2:$B$194,MATCH(TRUE,ISNUMBER(SEARCH('Category Rules'!$A$2:$A$194,C1173)),0)),"")))))))} -> Personal - Subscription
A1174: DEBIT | B1174: 46052 | C1174: AMAZON MKTPL*GS66X59 Amzn.com/bill WA 01/29 | D1174: -44.98 | E1174: DEBIT_CARD | F1174: 5944.33 | G1174: {=IF(AND(ISNUMBER(SEARCH("UBER",C1174)),ISNUMBER(SEARCH("EATS",C1174))),"Uber Eats",IF(LEFT(C1174,6)="CHECK ","Checks Paid",IF(OR(E1174="BILLPAY",ISNUMBER(SEARCH("FRANCHISE TAX",C1174)),ISNUMBER(SEARCH("NEXTLINK",C1174))),"Personal - House Bills",IF(AND(ISNUMBER(SEARCH("PAYMENT FROM",C1174)),ISNUMBER(SEARCH("JOE SAUNDERS",C1174))),"Zelle from Joe Saunders",IF(AND(ISNUMBER(SEARCH("PAYMENT TO",C1174)),ISNUMBER(SEARCH("JOE SAUNDERS",C1174))),"Zelle to Joe Saunders",IF(OR(ISNUMBER(SEARCH("NEW ORLEANS",C1174)),ISNUMBER(SEARCH("KENNER",C1174)),ISNUMBER(SEARCH("HENRY HOWARD",C1174)),ISNUMBER(SEARCH("MISS CLAUDIA",C1174))),"Personal Travel - New Orleans",IFERROR(INDEX('Category Rules'!$B$2:$B$194,MATCH(TRUE,ISNUMBER(SEARCH('Category Rules'!$A$2:$A$194,C1174)),0)),"")))))))} -> Amazon
... A1194: DEBIT | B1194: 46049 | C1194: SQ *REA COMMERCIAL SECU gosq.com CA 01/27 | D1194: -100 | E1194: DEBIT_CARD | F1194: 10317.87 | G1194: {=IF(AND(ISNUMBER(SEARCH("UBER",C1194)),ISNUMBER(SEARCH("EATS",C1194))),"Uber Eats",IF(LEFT(C1194,6)="CHECK ","Checks Paid",IF(OR(E1194="BILLPAY",ISNUMBER(SEARCH("FRANCHISE TAX",C1194)),ISNUMBER(SEARCH("NEXTLINK",C1194))),"Personal - House Bills",IF(AND(ISNUMBER(SEARCH("PAYMENT FROM",C1194)),ISNUMBER(SEARCH("JOE SAUNDERS",C1194))),"Zelle from Joe Saunders",IF(AND(ISNUMBER(SEARCH("PAYMENT TO",C1194)),ISNUMBER(SEARCH("JOE SAUNDERS",C1194))),"Zelle to Joe Saunders",IF(OR(ISNUMBER(SEARCH("NEW ORLEANS",C1194)),ISNUMBER(SEARCH("KENNER",C1194)),ISNUMBER(SEARCH("HENRY HOWARD",C1194)),ISNUMBER(SEARCH("MISS CLAUDIA",C1194))),"Personal Travel - New Orleans",IFERROR(INDEX('Category Rules'!$B$2:$B$194,MATCH(TRUE,ISNUMBER(SEARCH('Category Rules'!$A$2:$A$194,C1194)),0)),"")))))))} -> Personal - Subscription
A1195: DEBIT | B1195: 46049 | C1195: SPACEWEATHERNEWS.COM SPACEWEATHERN CO 01/26 | D1195: -5.99 | E1195: DEBIT_CARD | F1195: 10417.87 | G1195: Personal - Subscription
A1196: DEBIT | B1196: 46049 | C1196: Prime Video Channels amzn.com/bill WA 01/26 | D1196: -6.99 | E1196: DEBIT_CARD | F1196: 10423.86 | G1196: {=IF(AND(ISNUMBER(SEARCH("UBER",C1196)),ISNUMBER(SEARCH("EATS",C1196))),"Uber Eats",IF(LEFT(C1196,6)="CHECK ","Checks Paid",IF(OR(E1196="BILLPAY",ISNUMBER(SEARCH("FRANCHISE TAX",C1196)),ISNUMBER(SEARCH("NEXTLINK",C1196))),"Personal - House Bills",IF(AND(ISNUMBER(SEARCH("PAYMENT FROM",C1196)),ISNUMBER(SEARCH("JOE SAUNDERS",C1196))),"Zelle from Joe Saunders",IF(AND(ISNUMBER(SEARCH("PAYMENT TO",C1196)),ISNUMBER(SEARCH("JOE SAUNDERS",C1196))),"Zelle to Joe Saunders",IF(OR(ISNUMBER(SEARCH("NEW ORLEANS",C1196)),ISNUMBER(SEARCH("KENNER",C1196)),ISNUMBER(SEARCH("HENRY HOWARD",C1196)),ISNUMBER(SEARCH("MISS CLAUDIA",C1196))),"Personal Travel - New Orleans",IFERROR(INDEX('Category Rules'!$B$2:$B$194,MATCH(TRUE,ISNUMBER(SEARCH('Category Rules'!$A$2:$A$194,C1196)),0)),"")))))))} -> Amazon
A1197: DEBIT | B1197: 46049 | C1197: EXPEDIA 73358196852883 EXPEDIA.COM WA 01/26 | D1197: -18.75 | E1197: DEBIT_CARD | F1197: 10430.85 | G1197: {=IF(AND(ISNUMBER(SEARCH("UBER",C1197)),ISNUMBER(SEARCH("EATS",C1197))),"Uber Eats",IF(LEFT(C1197,6)="CHECK ","Checks Paid",IF(OR(E1197="BILLPAY",ISNUMBER(SEARCH("FRANCHISE TAX",C1197)),ISNUMBER(SEARCH("NEXTLINK",C1197))),"Personal - House Bills",IF(AND(ISNUMBER(SEARCH("PAYMENT FROM",C1197)),ISNUMBER(SEARCH("JOE SAUNDERS",C1197))),"Zelle from Joe Saunders",IF(AND(ISNUMBER(SEARCH("PAYMENT TO",C1197)),ISNUMBER(SEARCH("JOE SAUNDERS",C1197))),"Zelle to Joe Saunders",IF(OR(ISNUMBER(SEARCH("NEW ORLEANS",C1197)),ISNUMBER(SEARCH("KENNER",C1197)),ISNUMBER(SEARCH("HENRY HOWARD",C1197)),ISNUMBER(SEARCH("MISS CLAUDIA",C1197))),"Personal Travel - New Orleans",IFERROR(INDEX('Category Rules'!$B$2:$B$194,MATCH(TRUE,ISNUMBER(SEARCH('Category Rules'!$A$2:$A$194,C1197)),0)),"")))))))} -> Personal Travel
A1198: DEBIT | B1198: 46049 | C1198: CSC PALM SPRINGS TENNI 855-8596983 AZ 01/23 | D1198: -249.86 | E1198: DEBIT_CARD | F1198: 10449.6 | G1198: {=IF(AND(ISNUMBER(SEARCH("UBER",C1198)),ISNUMBER(SEARCH("EATS",C1198))),"Uber Eats",IF(LEFT(C1198,6)="CHECK ","Checks Paid",IF(OR(E1198="BILLPAY",ISNUMBER(SEARCH("FRANCHISE TAX",C1198)),ISNUMBER(SEARCH("NEXTLINK",C1198))),"Personal - House Bills",IF(AND(ISNUMBER(SEARCH("PAYMENT FROM",C1198)),ISNUMBER(SEARCH("JOE SAUNDERS",C1198))),"Zelle from Joe Saunders",IF(AND(ISNUMBER(SEARCH("PAYMENT TO",C1198)),ISNUMBER(SEARCH("JOE SAUNDERS",C1198))),"Zelle to Joe Saunders",IF(OR(ISNUMBER(SEARCH("NEW ORLEANS",C1198)),ISNUMBER(SEARCH("KENNER",C1198)),ISNUMBER(SEARCH("HENRY HOWARD",C1198)),ISNUMBER(SEARCH("MISS CLAUDIA",C1198))),"Personal Travel - New Orleans",IFERROR(INDEX('Category Rules'!$B$2:$B$194,MATCH(TRUE,ISNUMBER(SEARCH('Category Rules'!$A$2:$A$194,C1198)),0)),"")))))))} -> Palm Springs
A1199: CREDIT | B1199: 46049 | C1199: Online Transfer from CHK ...1168 transaction#: 27845107163 | D1199: 5000 | E1199: ACCT_XFER | F1199: 10699.46 | G1199: {=IF(AND(ISNUMBER(SEARCH("UBER",C1199)),ISNUMBER(SEARCH("EATS",C1199))),"Uber Eats",IF(LEFT(C1199,6)="CHECK ","Checks Paid",IF(OR(E1199="BILLPAY",ISNUMBER(SEARCH("FRANCHISE TAX",C1199)),ISNUMBER(SEARCH("NEXTLINK",C1199))),"Personal - House Bills",IF(AND(ISNUMBER(SEARCH("PAYMENT FROM",C1199)),ISNUMBER(SEARCH("JOE SAUNDERS",C1199))),"Zelle from Joe Saunders",IF(AND(ISNUMBER(SEARCH("PAYMENT TO",C1199)),ISNUMBER(SEARCH("JOE SAUNDERS",C1199))),"Zelle to Joe Saunders",IF(OR(ISNUMBER(SEARCH("NEW ORLEANS",C1199)),ISNUMBER(SEARCH("KENNER",C1199)),ISNUMBER(SEARCH("HENRY HOWARD",C1199)),ISNUMBER(SEARCH("MISS CLAUDIA",C1199))),"Personal Travel - New Orleans",IFERROR(INDEX('Category Rules'!$B$2:$B$194,MATCH(TRUE,ISNUMBER(SEARCH('Category Rules'!$A$2:$A$194,C1199)),0)),"")))))))} -> Transfer from DWG Capital Group
A1200: DEBIT | B1200: 46049 | C1200: EXPEDIA 73356202666221 EXPEDIA.COM NV 01/26 | D1200: 16.43 | E1200: DEBIT_CARD | F1200: 5699.46 | G1200: {=IF(AND(ISNUMBER(SEARCH("UBER",C1200)),ISNUMBER(SEARCH("EATS",C1200))),"Uber Eats",IF(LEFT(C1200,6)="CHECK ","Checks Paid",IF(OR(E1200="BILLPAY",ISNUMBER(SEARCH("FRANCHISE TAX",C1200)),ISNUMBER(SEARCH("NEXTLINK",C1200))),"Personal - House Bills",IF(AND(ISNUMBER(SEARCH("PAYMENT FROM",C1200)),ISNUMBER(SEARCH("JOE SAUNDERS",C1200))),"Zelle from Joe Saunders",IF(AND(ISNUMBER(SEARCH("PAYMENT TO",C1200)),ISNUMBER(SEARCH("JOE SAUNDERS",C1200))),"Zelle to Joe Saunders",IF(OR(ISNUMBER(SEARCH("NEW ORLEANS",C1200)),ISNUMBER(SEARCH("KENNER",C1200)),ISNUMBER(SEARCH("HENRY HOWARD",C1200)),ISNUMBER(SEARCH("MISS CLAUDIA",C1200))),"Personal Travel - New Orleans",IFERROR(INDEX('Category Rules'!$B$2:$B$194,MATCH(TRUE,ISNUMBER(SEARCH('Category Rules'!$A$2:$A$194,C1200)),0)),"")))))))} -> Personal Travel
A1201: DEBIT | B1201: 46048 | C1201: UBER *TRIP SAN FRANCISCO CA 805433 01/26 | D1201: -10 | E1201: DEBIT_CARD | F1201: 5683.03 | G1201: {=IF(AND(ISNUMBER(SEARCH("UBER",C1201)),ISNUMBER(SEARCH("EATS",C1201))),"Uber Eats",IF(LEFT(C1201,6)="CHECK ","Checks Paid",IF(OR(E1201="BILLPAY",ISNUMBER(SEARCH("FRANCHISE TAX",C1201)),ISNUMBER(SEARCH("NEXTLINK",C1201))),"Personal - House Bills",IF(AND(ISNUMBER(SEARCH("PAYMENT FROM",C1201)),ISNUMBER(SEARCH("JOE SAUNDERS",C1201))),"Zelle from Joe Saunders",IF(AND(ISNUMBER(SEARCH("PAYMENT TO",C1201)),ISNUMBER(SEARCH("JOE SAUNDERS",C1201))),"Zelle to Joe Saunders",IF(OR(ISNUMBER(SEARCH("NEW ORLEANS",C1201)),ISNUMBER(SEARCH("KENNER",C1201)),ISNUMBER(SEARCH("HENRY HOWARD",C1201)),ISNUMBER(SEARCH("MISS CLAUDIA",C1201))),"Personal Travel - New Orleans",IFERROR(INDEX('Category Rules'!$B$2:$B$194,MATCH(TRUE,ISNUMBER(SEARCH('Category Rules'!$A$2:$A$194,C1201)),0)),"")))))))} -> Personal - Uber
A1202: DEBIT | B1202: 46048 | C1202: AMAZON MKTPL*1O0NR5H Amzn.com/bill WA 01/26 | D1202: -83.41 | E1202: DEBIT_CARD | F1202: 5693.03 | G1202: {=IF(AND(ISNUMBER(SEARCH("UBER",C1202)),ISNUMBER(SEARCH("EATS",C1202))),"Uber Eats",IF(LEFT(C1202,6)="CHECK ","Checks Paid",IF(OR(E1202="BILLPAY",ISNUMBER(SEARCH("FRANCHISE TAX",C1202)),ISNUMBER(SEARCH("NEXTLINK",C1202))),"Personal - House Bills",IF(AND(ISNUMBER(SEARCH("PAYMENT FROM",C1202)),ISNUMBER(SEARCH("JOE SAUNDERS",C1202))),"Zelle from Joe Saunders",IF(AND(ISNUMBER(SEARCH("PAYMENT TO",C1202)),ISNUMBER(SEARCH("JOE SAUNDERS",C1202))),"Zelle to Joe Saunders",IF(OR(ISNUMBER(SEARCH("NEW ORLEANS",C1202)),ISNUMBER(SEARCH("KENNER",C1202)),ISNUMBER(SEARCH("HENRY HOWARD",C1202)),ISNUMBER(SEARCH("MISS CLAUDIA",C1202))),"Personal Travel - New Orleans",IFERROR(INDEX('Category Rules'!$B$2:$B$194,MATCH(TRUE,ISNUMBER(SEARCH('Category Rules'!$A$2:$A$194,C1202)),0)),"")))))))} -> Amazon
A1203: DEBIT | B1203: 46048 | C1203: LUKE UNFILTERED WEARECHANGE.O FL 01/25 | D1203: -15 | E1203: DEBIT_CARD | F1203: 5776.44 | G1203: {=IF(AND(ISNUMBER(SEARCH("UBER",C1203)),ISNUMBER(SEARCH("EATS",C1203))),"Uber Eats",IF(LEFT(C1203,6)="CHECK ","Checks Paid",IF(OR(E1203="BILLPAY",ISNUMBER(SEARCH("FRANCHISE TAX",C1203)),ISNUMBER(SEARCH("NEXTLINK",C1203))),"Personal - House Bills",IF(AND(ISNUMBER(SEARCH("PAYMENT FROM",C1203)),ISNUMBER(SEARCH("JOE SAUNDERS",C1203))),"Zelle from Joe Saunders",IF(AND(ISNUMBER(SEARCH("PAYMENT TO",C1203)),ISNUMBER(SEARCH("JOE SAUNDERS",C1203))),"Zelle to Joe Saunders",IF(OR(ISNUMBER(SEARCH("NEW ORLEANS",C1203)),ISNUMBER(SEARCH("KENNER",C1203)),ISNUMBER(SEARCH("HENRY HOWARD",C1203)),ISNUMBER(SEARCH("MISS CLAUDIA",C1203))),"Personal Travel - New Orleans",IFERROR(INDEX('Category Rules'!$B$2:$B$194,MATCH(TRUE,ISNUMBER(SEARCH('Category Rules'!$A$2:$A$194,C1203)),0)),"")))))))} -> Personal - Subscription
A1204: DEBIT | B1204: 46048 | C1204: AMAZON PRIME*X20F73V Amzn.com/bill WA 01/24 | D1204: -16.45 | E1204: DEBIT_CARD | F1204: 5791.44 | G1204: {=IF(AND(ISNUMBER(SEARCH("UBER",C1204)),ISNUMBER(SEARCH("EATS",C1204))),"Uber Eats",IF(LEFT(C1204,6)="CHECK ","Checks Paid",IF(OR(E1204="BILLPAY",ISNUMBER(SEARCH("FRANCHISE TAX",C1204)),ISNUMBER(SEARCH("NEXTLINK",C1204))),"Personal - House Bills",IF(AND(ISNUMBER(SEARCH("PAYMENT FROM",C1204)),ISNUMBER(SEARCH("JOE SAUNDERS",C1204))),"Zelle from Joe Saunders",IF(AND(ISNUMBER(SEARCH("PAYMENT TO",C1204)),ISNUMBER(SEARCH("JOE SAUNDERS",C1204))),"Zelle to Joe Saunders",IF(OR(ISNUMBER(SEARCH("NEW ORLEANS",C1204)),ISNUMBER(SEARCH("KENNER",C1204)),ISNUMBER(SEARCH("HENRY HOWARD",C1204)),ISNUMBER(SEARCH("MISS CLAUDIA",C1204))),"Personal Travel - New Orleans",IFERROR(INDEX('Category Rules'!$B$2:$B$194,MATCH(TRUE,ISNUMBER(SEARCH('Category Rules'!$A$2:$A$194,C1204)),0)),"")))))))} -> Amazon
A1205: DEBIT | B1205: 46048 | C1205: Amazon Tips*EE9C3076 Amzn.com/bill WA 01/24 | D1205: -10 | E1205: DEBIT_CARD | F1205: 5807.89 | G1205: {=IF(AND(ISNUMBER(SEARCH("UBER",C1205)),ISNUMBER(SEARCH("EATS",C1205))),"Uber Eats",IF(LEFT(C1205,6)="CHECK ","Checks Paid",IF(OR(E1205="BILLPAY",ISNUMBER(SEARCH("FRANCHISE TAX",C1205)),ISNUMBER(SEARCH("NEXTLINK",C1205))),"Personal - House Bills",IF(AND(ISNUMBER(SEARCH("PAYMENT FROM",C1205)),ISNUMBER(SEARCH("JOE SAUNDERS",C1205))),"Zelle from Joe Saunders",IF(AND(ISNUMBER(SEARCH("PAYMENT TO",C1205)),ISNUMBER(SEARCH("JOE SAUNDERS",C1205))),"Zelle to Joe Saunders",IF(OR(ISNUMBER(SEARCH("NEW ORLEANS",C1205)),ISNUMBER(SEARCH("KENNER",C1205)),ISNUMBER(SEARCH("HENRY HOWARD",C1205)),ISNUMBER(SEARCH("MISS CLAUDIA",C1205))),"Personal Travel - New Orleans",IFERROR(INDEX('Category Rules'!$B$2:$B$194,MATCH(TRUE,ISNUMBER(SEARCH('Category Rules'!$A$2:$A$194,C1205)),0)),"")))))))} -> Amazon
A1206: DEBIT | B1206: 46048 | C1206: ATT*BILL PAYMENT 800-288-2020 TX 01/24 | D1206: -572.98 | E1206: DEBIT_CARD | F1206: 5817.89 | G1206: {=IF(AND(ISNUMBER(SEARCH("UBER",C1206)),ISNUMBER(SEARCH("EATS",C1206))),"Uber Eats",IF(LEFT(C1206,6)="CHECK ","Checks Paid",IF(OR(E1206="BILLPAY",ISNUMBER(SEARCH("FRANCHISE TAX",C1206)),ISNUMBER(SEARCH("NEXTLINK",C1206))),"Personal - House Bills",IF(AND(ISNUMBER(SEARCH("PAYMENT FROM",C1206)),ISNUMBER(SEARCH("JOE SAUNDERS",C1206))),"Zelle from Joe Saunders",IF(AND(ISNUMBER(SEARCH("PAYMENT TO",C1206)),ISNUMBER(SEARCH("JOE SAUNDERS",C1206))),"Zelle to Joe Saunders",IF(OR(ISNUMBER(SEARCH("NEW ORLEANS",C1206)),ISNUMBER(SEARCH("KENNER",C1206)),ISNUMBER(SEARCH("HENRY HOWARD",C1206)),ISNUMBER(SEARCH("MISS CLAUDIA",C1206))),"Personal Travel - New Orleans",IFERROR(INDEX('Category Rules'!$B$2:$B$194,MATCH(TRUE,ISNUMBER(SEARCH('Category Rules'!$A$2:$A$194,C1206)),0)),"")))))))} -> AT&T
A1207: DEBIT | B1207: 46048 | C1207: Zara.com 212-3551415 NY 01/24 | D1207: -424.6 | E1207: DEBIT_CARD | F1207: 6390.87 | G1207: {=IF(AND(ISNUMBER(SEARCH("UBER",C1207)),ISNUMBER(SEARCH("EATS",C1207))),"Uber Eats",IF(LEFT(C1207,6)="CHECK ","Checks Paid",IF(OR(E1207="BILLPAY",ISNUMBER(SEARCH("FRANCHISE TAX",C1207)),ISNUMBER(SEARCH("NEXTLINK",C1207))),"Personal - House Bills",IF(AND(ISNUMBER(SEARCH("PAYMENT FROM",C1207)),ISNUMBER(SEARCH("JOE SAUNDERS",C1207))),"Zelle from Joe Saunders",IF(AND(ISNUMBER(SEARCH("PAYMENT TO",C1207)),ISNUMBER(SEARCH("JOE SAUNDERS",C1207))),"Zelle to Joe Saunders",IF(OR(ISNUMBER(SEARCH("NEW ORLEANS",C1207)),ISNUMBER(SEARCH("KENNER",C1207)),ISNUMBER(SEARCH("HENRY HOWARD",C1207)),ISNUMBER(SEARCH("MISS CLAUDIA",C1207))),"Personal Travel - New Orleans",IFERROR(INDEX('Category Rules'!$B$2:$B$194,MATCH(TRUE,ISNUMBER(SEARCH('Category Rules'!$A$2:$A$194,C1207)),0)),"")))))))} -> Personal - Shopping
... A1246: DEBIT | B1246: 46042 | C1246: SHELL SERVICE STATION WEATHERFORD TX 340832 01/17 | D1246: -54.45 | E1246: DEBIT_CARD | F1246: 2363.26 | G1246: {=IF(AND(ISNUMBER(SEARCH("UBER",C1246)),ISNUMBER(SEARCH("EATS",C1246))),"Uber Eats",IF(LEFT(C1246,6)="CHECK ","Checks Paid",IF(OR(E1246="BILLPAY",ISNUMBER(SEARCH("FRANCHISE TAX",C1246)),ISNUMBER(SEARCH("NEXTLINK",C1246))),"Personal - House Bills",IF(AND(ISNUMBER(SEARCH("PAYMENT FROM",C1246)),ISNUMBER(SEARCH("JOE SAUNDERS",C1246))),"Zelle from Joe Saunders",IF(AND(ISNUMBER(SEARCH("PAYMENT TO",C1246)),ISNUMBER(SEARCH("JOE SAUNDERS",C1246))),"Zelle to Joe Saunders",IF(OR(ISNUMBER(SEARCH("NEW ORLEANS",C1246)),ISNUMBER(SEARCH("KENNER",C1246)),ISNUMBER(SEARCH("HENRY HOWARD",C1246)),ISNUMBER(SEARCH("MISS CLAUDIA",C1246))),"Personal Travel - New Orleans",IFERROR(INDEX('Category Rules'!$B$2:$B$194,MATCH(TRUE,ISNUMBER(SEARCH('Category Rules'!$A$2:$A$194,C1246)),0)),"")))))))} -> Personal - Car
A1247: DEBIT | B1247: 46042 | C1247: RIPLEY'S GRAND PRAIR GRAND PRAIRIE TX 01/17 | D1247: -89.75 | E1247: DEBIT_CARD | F1247: 2417.71 | G1247: Personal - Entertainment
A1248: DEBIT | B1248: 46042 | C1248: RIPLEY'S GRAND PRAIR GRAND PRAIRIE TX 01/17 | D1248: -97.39 | E1248: DEBIT_CARD | F1248: 2507.46 | G1248: Personal - Entertainment
A1249: DEBIT | B1249: 46042 | C1249: LEELA QUANTUM TECH LEELAQ.COM NM 01/17 | D1249: -30 | E1249: DEBIT_CARD | F1249: 2604.85 | G1249: {=IF(AND(ISNUMBER(SEARCH("UBER",C1249)),ISNUMBER(SEARCH("EATS",C1249))),"Uber Eats",IF(LEFT(C1249,6)="CHECK ","Checks Paid",IF(OR(E1249="BILLPAY",ISNUMBER(SEARCH("FRANCHISE TAX",C1249)),ISNUMBER(SEARCH("NEXTLINK",C1249))),"Personal - House Bills",IF(AND(ISNUMBER(SEARCH("PAYMENT FROM",C1249)),ISNUMBER(SEARCH("JOE SAUNDERS",C1249))),"Zelle from Joe Saunders",IF(AND(ISNUMBER(SEARCH("PAYMENT TO",C1249)),ISNUMBER(SEARCH("JOE SAUNDERS",C1249))),"Zelle to Joe Saunders",IF(OR(ISNUMBER(SEARCH("NEW ORLEANS",C1249)),ISNUMBER(SEARCH("KENNER",C1249)),ISNUMBER(SEARCH("HENRY HOWARD",C1249)),ISNUMBER(SEARCH("MISS CLAUDIA",C1249))),"Personal Travel - New Orleans",IFERROR(INDEX('Category Rules'!$B$2:$B$194,MATCH(TRUE,ISNUMBER(SEARCH('Category Rules'!$A$2:$A$194,C1249)),0)),"")))))))} -> Personal - Subscription
A1250: DEBIT | B1250: 46042 | C1250: PY *LAS PALMAS LUNCH AN DALLAS TX 01/18 | D1250: -188.83 | E1250: DEBIT_CARD | F1250: 2634.85 | G1250: Personal - Food
A1251: DEBIT | B1251: 46042 | C1251: 2711 FAIRMOUNT, LP DALLAS TX 01/18 | D1251: -15 | E1251: DEBIT_CARD | F1251: 2823.68 | G1251: Personal - Food
A1252: DEBIT | B1252: 46042 | C1252: AMAZON MKTPL*DQ6JM7W Amzn.com/bill WA 01/17 | D1252: -58.7 | E1252: DEBIT_CARD | F1252: 2838.68 | G1252: {=IF(AND(ISNUMBER(SEARCH("UBER",C1252)),ISNUMBER(SEARCH("EATS",C1252))),"Uber Eats",IF(LEFT(C1252,6)="CHECK ","Checks Paid",IF(OR(E1252="BILLPAY",ISNUMBER(SEARCH("FRANCHISE TAX",C1252)),ISNUMBER(SEARCH("NEXTLINK",C1252))),"Personal - House Bills",IF(AND(ISNUMBER(SEARCH("PAYMENT FROM",C1252)),ISNUMBER(SEARCH("JOE SAUNDERS",C1252))),"Zelle from Joe Saunders",IF(AND(ISNUMBER(SEARCH("PAYMENT TO",C1252)),ISNUMBER(SEARCH("JOE SAUNDERS",C1252))),"Zelle to Joe Saunders",IF(OR(ISNUMBER(SEARCH("NEW ORLEANS",C1252)),ISNUMBER(SEARCH("KENNER",C1252)),ISNUMBER(SEARCH("HENRY HOWARD",C1252)),ISNUMBER(SEARCH("MISS CLAUDIA",C1252))),"Personal Travel - New Orleans",IFERROR(INDEX('Category Rules'!$B$2:$B$194,MATCH(TRUE,ISNUMBER(SEARCH('Category Rules'!$A$2:$A$194,C1252)),0)),"")))))))} -> Amazon
A1253: DEBIT | B1253: 46042 | C1253: Etsy.com*Multiple Shop ETSY.COM NY 01/16 | D1253: -442.17 | E1253: DEBIT_CARD | F1253: 2897.38 | G1253: {=IF(AND(ISNUMBER(SEARCH("UBER",C1253)),ISNUMBER(SEARCH("EATS",C1253))),"Uber Eats",IF(LEFT(C1253,6)="CHECK ","Checks Paid",IF(OR(E1253="BILLPAY",ISNUMBER(SEARCH("FRANCHISE TAX",C1253)),ISNUMBER(SEARCH("NEXTLINK",C1253))),"Personal - House Bills",IF(AND(ISNUMBER(SEARCH("PAYMENT FROM",C1253)),ISNUMBER(SEARCH("JOE SAUNDERS",C1253))),"Zelle from Joe Saunders",IF(AND(ISNUMBER(SEARCH("PAYMENT TO",C1253)),ISNUMBER(SEARCH("JOE SAUNDERS",C1253))),"Zelle to Joe Saunders",IF(OR(ISNUMBER(SEARCH("NEW ORLEANS",C1253)),ISNUMBER(SEARCH("KENNER",C1253)),ISNUMBER(SEARCH("HENRY HOWARD",C1253)),ISNUMBER(SEARCH("MISS CLAUDIA",C1253))),"Personal Travel - New Orleans",IFERROR(INDEX('Category Rules'!$B$2:$B$194,MATCH(TRUE,ISNUMBER(SEARCH('Category Rules'!$A$2:$A$194,C1253)),0)),"")))))))} -> Etsy
A1254: DEBIT | B1254: 46042 | C1254: NTTA AUTOCHARGE 972-818-6882 TX 01/16 | D1254: -40 | E1254: DEBIT_CARD | F1254: 3339.55 | G1254: {=IF(AND(ISNUMBER(SEARCH("UBER",C1254)),ISNUMBER(SEARCH("EATS",C1254))),"Uber Eats",IF(LEFT(C1254,6)="CHECK ","Checks Paid",IF(OR(E1254="BILLPAY",ISNUMBER(SEARCH("FRANCHISE TAX",C1254)),ISNUMBER(SEARCH("NEXTLINK",C1254))),"Personal - House Bills",IF(AND(ISNUMBER(SEARCH("PAYMENT FROM",C1254)),ISNUMBER(SEARCH("JOE SAUNDERS",C1254))),"Zelle from Joe Saunders",IF(AND(ISNUMBER(SEARCH("PAYMENT TO",C1254)),ISNUMBER(SEARCH("JOE SAUNDERS",C1254))),"Zelle to Joe Saunders",IF(OR(ISNUMBER(SEARCH("NEW ORLEANS",C1254)),ISNUMBER(SEARCH("KENNER",C1254)),ISNUMBER(SEARCH("HENRY HOWARD",C1254)),ISNUMBER(SEARCH("MISS CLAUDIA",C1254))),"Personal Travel - New Orleans",IFERROR(INDEX('Category Rules'!$B$2:$B$194,MATCH(TRUE,ISNUMBER(SEARCH('Category Rules'!$A$2:$A$194,C1254)),0)),"")))))))} -> Personal - Car
A1255: DEBIT | B1255: 46042 | C1255: Zara.com 212-3551415 NY 01/17 | D1255: -592.75 | E1255: DEBIT_CARD | F1255: 3379.55 | G1255: {=IF(AND(ISNUMBER(SEARCH("UBER",C1255)),ISNUMBER(SEARCH("EATS",C1255))),"Uber Eats",IF(LEFT(C1255,6)="CHECK ","Checks Paid",IF(OR(E1255="BILLPAY",ISNUMBER(SEARCH("FRANCHISE TAX",C1255)),ISNUMBER(SEARCH("NEXTLINK",C1255))),"Personal - House Bills",IF(AND(ISNUMBER(SEARCH("PAYMENT FROM",C1255)),ISNUMBER(SEARCH("JOE SAUNDERS",C1255))),"Zelle from Joe Saunders",IF(AND(ISNUMBER(SEARCH("PAYMENT TO",C1255)),ISNUMBER(SEARCH("JOE SAUNDERS",C1255))),"Zelle to Joe Saunders",IF(OR(ISNUMBER(SEARCH("NEW ORLEANS",C1255)),ISNUMBER(SEARCH("KENNER",C1255)),ISNUMBER(SEARCH("HENRY HOWARD",C1255)),ISNUMBER(SEARCH("MISS CLAUDIA",C1255))),"Personal Travel - New Orleans",IFERROR(INDEX('Category Rules'!$B$2:$B$194,MATCH(TRUE,ISNUMBER(SEARCH('Category Rules'!$A$2:$A$194,C1255)),0)),"")))))))} -> Personal - Shopping
A1256: CREDIT | B1256: 46042 | C1256: Online Transfer from CHK ...1168 transaction#: 27743673026 | D1256: 4000 | E1256: ACCT_XFER | F1256: 3972.3 | G1256: {=IF(AND(ISNUMBER(SEARCH("UBER",C1256)),ISNUMBER(SEARCH("EATS",C1256))),"Uber Eats",IF(LEFT(C1256,6)="CHECK ","Checks Paid",IF(OR(E1256="BILLPAY",ISNUMBER(SEARCH("FRANCHISE TAX",C1256)),ISNUMBER(SEARCH("NEXTLINK",C1256))),"Personal - House Bills",IF(AND(ISNUMBER(SEARCH("PAYMENT FROM",C1256)),ISNUMBER(SEARCH("JOE SAUNDERS",C1256))),"Zelle from Joe Saunders",IF(AND(ISNUMBER(SEARCH("PAYMENT TO",C1256)),ISNUMBER(SEARCH("JOE SAUNDERS",C1256))),"Zelle to Joe Saunders",IF(OR(ISNUMBER(SEARCH("NEW ORLEANS",C1256)),ISNUMBER(SEARCH("KENNER",C1256)),ISNUMBER(SEARCH("HENRY HOWARD",C1256)),ISNUMBER(SEARCH("MISS CLAUDIA",C1256))),"Personal Travel - New Orleans",IFERROR(INDEX('Category Rules'!$B$2:$B$194,MATCH(TRUE,ISNUMBER(SEARCH('Category Rules'!$A$2:$A$194,C1256)),0)),"")))))))} -> Transfer from DWG Capital Group
A1257: DEBIT | B1257: 46038 | C1257: LIFETOUCH 952-826-4000 MN 01/16 | D1257: -62.03 | E1257: DEBIT_CARD | F1257: -27.7 | G1257: Personal - Shopping
A1258: DEBIT | B1258: 46038 | C1258: AMAZON MKTPL*VW78B5C Amzn.com/bill WA 01/16 | D1258: -156.4 | E1258: DEBIT_CARD | F1258: 34.33 | G1258: {=IF(AND(ISNUMBER(SEARCH("UBER",C1258)),ISNUMBER(SEARCH("EATS",C1258))),"Uber Eats",IF(LEFT(C1258,6)="CHECK ","Checks Paid",IF(OR(E1258="BILLPAY",ISNUMBER(SEARCH("FRANCHISE TAX",C1258)),ISNUMBER(SEARCH("NEXTLINK",C1258))),"Personal - House Bills",IF(AND(ISNUMBER(SEARCH("PAYMENT FROM",C1258)),ISNUMBER(SEARCH("JOE SAUNDERS",C1258))),"Zelle from Joe Saunders",IF(AND(ISNUMBER(SEARCH("PAYMENT TO",C1258)),ISNUMBER(SEARCH("JOE SAUNDERS",C1258))),"Zelle to Joe Saunders",IF(OR(ISNUMBER(SEARCH("NEW ORLEANS",C1258)),ISNUMBER(SEARCH("KENNER",C1258)),ISNUMBER(SEARCH("HENRY HOWARD",C1258)),ISNUMBER(SEARCH("MISS CLAUDIA",C1258))),"Personal Travel - New Orleans",IFERROR(INDEX('Category Rules'!$B$2:$B$194,MATCH(TRUE,ISNUMBER(SEARCH('Category Rules'!$A$2:$A$194,C1258)),0)),"")))))))} -> Amazon
A1259: DEBIT | B1259: 46038 | C1259: TACKETT COMPOUNDING PH HUDSON OAKS TX 01/15 | D1259: -143.41 | E1259: DEBIT_CARD | F1259: 190.73 | G1259: Personal - Health
A1260: DEBIT | B1260: 46038 | C1260: LAKE GRANBURY MED CTR 817-573-2273 TX 01/15 | D1260: -178.45 | E1260: DEBIT_CARD | F1260: 334.14 | G1260: Personal - Health
A1261: DEBIT | B1261: 46038 | C1261: CRESCENT DRUGS INC 800-4694343 CA 01/15 | D1261: -225.49 | E1261: DEBIT_CARD | F1261: 512.59 | G1261: Personal - Health
A1262: DEBIT | B1262: 46038 | C1262: AMAZON MKTPL*6Z3ZQ7N Amzn.com/bill WA 01/16 | D1262: -67.47 | E1262: DEBIT_CARD | F1262: 738.08 | G1262: {=IF(AND(ISNUMBER(SEARCH("UBER",C1262)),ISNUMBER(SEARCH("EATS",C1262))),"Uber Eats",IF(LEFT(C1262,6)="CHECK ","Checks Paid",IF(OR(E1262="BILLPAY",ISNUMBER(SEARCH("FRANCHISE TAX",C1262)),ISNUMBER(SEARCH("NEXTLINK",C1262))),"Personal - House Bills",IF(AND(ISNUMBER(SEARCH("PAYMENT FROM",C1262)),ISNUMBER(SEARCH("JOE SAUNDERS",C1262))),"Zelle from Joe Saunders",IF(AND(ISNUMBER(SEARCH("PAYMENT TO",C1262)),ISNUMBER(SEARCH("JOE SAUNDERS",C1262))),"Zelle to Joe Saunders",IF(OR(ISNUMBER(SEARCH("NEW ORLEANS",C1262)),ISNUMBER(SEARCH("KENNER",C1262)),ISNUMBER(SEARCH("HENRY HOWARD",C1262)),ISNUMBER(SEARCH("MISS CLAUDIA",C1262))),"Personal Travel - New Orleans",IFERROR(INDEX('Category Rules'!$B$2:$B$194,MATCH(TRUE,ISNUMBER(SEARCH('Category Rules'!$A$2:$A$194,C1262)),0)),"")))))))} -> Amazon
A1263: DEBIT | B1263: 46037 | C1263: TARGET T-1981 WEATHERFORD TX 045912 01/15 | D1263: -375.57 | E1263: DEBIT_CARD | F1263: 805.55 | G1263: {=IF(AND(ISNUMBER(SEARCH("UBER",C1263)),ISNUMBER(SEARCH("EATS",C1263))),"Uber Eats",IF(LEFT(C1263,6)="CHECK ","Checks Paid",IF(OR(E1263="BILLPAY",ISNUMBER(SEARCH("FRANCHISE TAX",C1263)),ISNUMBER(SEARCH("NEXTLINK",C1263))),"Personal - House Bills",IF(AND(ISNUMBER(SEARCH("PAYMENT FROM",C1263)),ISNUMBER(SEARCH("JOE SAUNDERS",C1263))),"Zelle from Joe Saunders",IF(AND(ISNUMBER(SEARCH("PAYMENT TO",C1263)),ISNUMBER(SEARCH("JOE SAUNDERS",C1263))),"Zelle to Joe Saunders",IF(OR(ISNUMBER(SEARCH("NEW ORLEANS",C1263)),ISNUMBER(SEARCH("KENNER",C1263)),ISNUMBER(SEARCH("HENRY HOWARD",C1263)),ISNUMBER(SEARCH("MISS CLAUDIA",C1263))),"Personal Travel - New Orleans",IFERROR(INDEX('Category Rules'!$B$2:$B$194,MATCH(TRUE,ISNUMBER(SEARCH('Category Rules'!$A$2:$A$194,C1263)),0)),"")))))))} -> Personal - Shopping
A1264: DEBIT | B1264: 46037 | C1264: BETTER HEALTH MARKET WEATHERFORD TX 299730 01/15 | D1264: -36.55 | E1264: DEBIT_CARD | F1264: 1181.12 | G1264: Personal - Food
A1265: DEBIT | B1265: 46037 | C1265: MANGO.COM NEW YORK NY 149343 01/15 | D1265: -346.46 | E1265: DEBIT_CARD | F1265: 1217.67 | G1265: {=IF(AND(ISNUMBER(SEARCH("UBER",C1265)),ISNUMBER(SEARCH("EATS",C1265))),"Uber Eats",IF(LEFT(C1265,6)="CHECK ","Checks Paid",IF(OR(E1265="BILLPAY",ISNUMBER(SEARCH("FRANCHISE TAX",C1265)),ISNUMBER(SEARCH("NEXTLINK",C1265))),"Personal - House Bills",IF(AND(ISNUMBER(SEARCH("PAYMENT FROM",C1265)),ISNUMBER(SEARCH("JOE SAUNDERS",C1265))),"Zelle from Joe Saunders",IF(AND(ISNUMBER(SEARCH("PAYMENT TO",C1265)),ISNUMBER(SEARCH("JOE SAUNDERS",C1265))),"Zelle to Joe Saunders",IF(OR(ISNUMBER(SEARCH("NEW ORLEANS",C1265)),ISNUMBER(SEARCH("KENNER",C1265)),ISNUMBER(SEARCH("HENRY HOWARD",C1265)),ISNUMBER(SEARCH("MISS CLAUDIA",C1265))),"Personal Travel - New Orleans",IFERROR(INDEX('Category Rules'!$B$2:$B$194,MATCH(TRUE,ISNUMBER(SEARCH('Category Rules'!$A$2:$A$194,C1265)),0)),"")))))))} -> Personal - Shopping
A1266: DEBIT | B1266: 46037 | C1266: Prime Video Channels amzn.com/bill WA 01/14 | D1266: -18.49 | E1266: DEBIT_CARD | F1266: 1564.13 | G1266: {=IF(AND(ISNUMBER(SEARCH("UBER",C1266)),ISNUMBER(SEARCH("EATS",C1266))),"Uber Eats",IF(LEFT(C1266,6)="CHECK ","Checks Paid",IF(OR(E1266="BILLPAY",ISNUMBER(SEARCH("FRANCHISE TAX",C1266)),ISNUMBER(SEARCH("NEXTLINK",C1266))),"Personal - House Bills",IF(AND(ISNUMBER(SEARCH("PAYMENT FROM",C1266)),ISNUMBER(SEARCH("JOE SAUNDERS",C1266))),"Zelle from Joe Saunders",IF(AND(ISNUMBER(SEARCH("PAYMENT TO",C1266)),ISNUMBER(SEARCH("JOE SAUNDERS",C1266))),"Zelle to Joe Saunders",IF(OR(ISNUMBER(SEARCH("NEW ORLEANS",C1266)),ISNUMBER(SEARCH("KENNER",C1266)),ISNUMBER(SEARCH("HENRY HOWARD",C1266)),ISNUMBER(SEARCH("MISS CLAUDIA",C1266))),"Personal Travel - New Orleans",IFERROR(INDEX('Category Rules'!$B$2:$B$194,MATCH(TRUE,ISNUMBER(SEARCH('Category Rules'!$A$2:$A$194,C1266)),0)),"")))))))} -> Amazon
...
