Workbook

Sheet Transaction Summary 2025
A1: FAMILY AMEX
A2: Amex Platinum | Statement Summary · 2025
A4: Account Holder | B4: John Dunning
A5: Account | B5: XXXX-XXXXXX-43006
A6: Statement Period | B6: January 2025 - December 2025
A8: TOTALS
A9: Charges | B9: =SUMIF('Transaction Details 2025'!$E$8:$E$331,">0") -> 35067.32
A10: Credits & Payments | B10: =SUMIF('Transaction Details 2025'!$E$8:$E$331,"<0") -> -35902.93
A11: Net Balance | B11: =B9+B10 -> -835.61
A13: SPEND BY CATEGORY
A14: Category | B14: Amount | C14: % of Charges
A15: John — Business
A16: DWG-RE Platform (Redirected) | B16: =SUMIFS('Transaction Details 2025'!$E$8:$E$331,'Transaction Details 2025'!$J$8:$J$331,A16) -> 16316.48 | C16: =IFERROR(B16/$B$9,0) -> 0.46529019
A17: DWG-RE Platform (Canceled) | B17: =SUMIFS('Transaction Details 2025'!$E$8:$E$331,'Transaction Details 2025'!$J$8:$J$331,A17) -> 48 | C17: =IFERROR(B17/$B$9,0) -> 0.0013687958
A18: Sponsor Cloud | B18: =SUMIFS('Transaction Details 2025'!$E$8:$E$331,'Transaction Details 2025'!$J$8:$J$331,A18) -> 339.31 | C18: =IFERROR(B18/$B$9,0) -> 0.0096759604
A19: Business Services-Other Services | B19: =SUMIFS('Transaction Details 2025'!$E$8:$E$331,'Transaction Details 2025'!$J$8:$J$331,A19) -> -300 | C19: =IFERROR(B19/$B$9,0) -> -0.0085549737
A20: Business Services-Professional Services | B20: =SUMIFS('Transaction Details 2025'!$E$8:$E$331,'Transaction Details 2025'!$J$8:$J$331,A20) -> 119 | C20: =IFERROR(B20/$B$9,0) -> 0.0033934729
A21: Renewal Fee | B21: =SUMIFS('Transaction Details 2025'!$E$8:$E$331,'Transaction Details 2025'!$J$8:$J$331,A21) -> 695 | C21: =IFERROR(B21/$B$9,0) -> 0.019819022
A22: Subtotal — John Business | B22: =SUM(B16:B21) -> 17217.79 | C22: =IFERROR(B22/$B$9,0) -> 0.49099247
A23: John — Travel
A24: Travel | B24: =SUMIFS('Transaction Details 2025'!$E$8:$E$331,'Transaction Details 2025'!$J$8:$J$331,A24) -> 50.31 | C24: =IFERROR(B24/$B$9,0) -> 0.0014346691
A25: Travel-Airline | B25: =SUMIFS('Transaction Details 2025'!$E$8:$E$331,'Transaction Details 2025'!$J$8:$J$331,A25) -> 1143.96 | C25: =IFERROR(B25/$B$9,0) -> 0.032621826
A26: Subtotal — John Travel | B26: =SUM(B24:B25) -> 1194.27 | C26: =IFERROR(B26/$B$9,0) -> 0.034056495
A27: John — Personal / Other
A28: Family | B28: =SUMIFS('Transaction Details 2025'!$E$8:$E$331,'Transaction Details 2025'!$J$8:$J$331,A28) -> 302.87 | C28: =IFERROR(B28/$B$9,0) -> 0.0086368163
A29: Personal - Health | B29: =SUMIFS('Transaction Details 2025'!$E$8:$E$331,'Transaction Details 2025'!$J$8:$J$331,A29) -> 280.44 | C29: =IFERROR(B29/$B$9,0) -> 0.0079971894
A30: Personal - Car | B30: =SUMIFS('Transaction Details 2025'!$E$8:$E$331,'Transaction Details 2025'!$J$8:$J$331,A30) -> 62.8 | C30: =IFERROR(B30/$B$9,0) -> 0.0017908412
A31: Personal | B31: =SUMIFS('Transaction Details 2025'!$E$8:$E$331,'Transaction Details 2025'!$J$8:$J$331,A31) -> 591.26 | C31: =IFERROR(B31/$B$9,0) -> 0.016860712
A32: Other-Miscellaneous | B32: =SUMIFS('Transaction Details 2025'!$E$8:$E$331,'Transaction Details 2025'!$J$8:$J$331,A32) -> -368.31 | C32: =IFERROR(B32/$B$9,0) -> -0.010502941
A33: Fees & Adjustments-Fees & Adjustments | B33: =SUMIFS('Transaction Details 2025'!$E$8:$E$331,'Transaction Details 2025'!$J$8:$J$331,A33) -> 2509.78 | C33: =IFERROR(B33/$B$9,0) -> 0.07157034
A34: Subtotal — John Personal / Other | B34: =SUM(B28:B33) -> 3378.84 | C34: =IFERROR(B34/$B$9,0) -> 0.096352958
A35: Other Card Members
A36: Ava Perez | B36: =SUMIFS('Transaction Details 2025'!$E$8:$E$331,'Transaction Details 2025'!$J$8:$J$331,A36) -> 10690.63 | C36: =IFERROR(B36/$B$9,0) -> 0.30486019
A37: Angela L Dunning | B37: =SUMIFS('Transaction Details 2025'!$E$8:$E$331,'Transaction Details 2025'!$J$8:$J$331,A37) -> 447.99 | C37: =IFERROR(B37/$B$9,0) -> 0.012775142
A38: Subtotal — Card Members | B38: =SUM(B36:B37) -> 11138.62 | C38: =IFERROR(B38/$B$9,0) -> 0.31763534
A39: Credits & Payments
A40: Online AMEX Payment | B40: =SUMIFS('Transaction Details 2025'!$E$8:$E$331,'Transaction Details 2025'!$J$8:$J$331,A40) -> -33765.13 | C40: =IFERROR(B40/$B$9,0) -> -0.962866
A41: Subtotal — Credits & Payments | B41: =SUM(B40:B40) -> -33765.13 | C41: =IFERROR(B41/$B$9,0) -> -0.962866
A42: GRAND TOTAL | B42: =B22+B26+B34+B38+B41 -> -835.61 | C42: =IFERROR(B42/$B$9,0) -> -0.023828739
A44: SPEND BY MONTH
A45: Month | B45: Charges | C45: Credits | D45: Net
A46: =DATE(2025,1,1) -> 45658 | B46: =SUMIFS('Transaction Details 2025'!$E$8:$E$331,'Transaction Details 2025'!$I$8:$I$331,$A46,'Transaction Details 2025'!$E$8:$E$331,">0") -> 5242.75 | C46: =SUMIFS('Transaction Details 2025'!$E$8:$E$331,'Transaction Details 2025'!$I$8:$I$331,$A46,'Transaction Details 2025'!$E$8:$E$331,"<0") -> -5429.5 | D46: =B46+C46 -> -186.75
A47: =EDATE(A46,1) -> 45689 | B47: =SUMIFS('Transaction Details 2025'!$E$8:$E$331,'Transaction Details 2025'!$I$8:$I$331,$A47,'Transaction Details 2025'!$E$8:$E$331,">0") -> 2796.12 | C47: =SUMIFS('Transaction Details 2025'!$E$8:$E$331,'Transaction Details 2025'!$I$8:$I$331,$A47,'Transaction Details 2025'!$E$8:$E$331,"<0") -> -3171.33 | D47: =B47+C47 -> -375.21
A48: =EDATE(A47,1) -> 45717 | B48: =SUMIFS('Transaction Details 2025'!$E$8:$E$331,'Transaction Details 2025'!$I$8:$I$331,$A48,'Transaction Details 2025'!$E$8:$E$331,">0") -> 2046.88 | C48: =SUMIFS('Transaction Details 2025'!$E$8:$E$331,'Transaction Details 2025'!$I$8:$I$331,$A48,'Transaction Details 2025'!$E$8:$E$331,"<0") -> -2132.01 | D48: =B48+C48 -> -85.13
A49: =EDATE(A48,1) -> 45748 | B49: =SUMIFS('Transaction Details 2025'!$E$8:$E$331,'Transaction Details 2025'!$I$8:$I$331,$A49,'Transaction Details 2025'!$E$8:$E$331,">0") -> 2110.8 | C49: =SUMIFS('Transaction Details 2025'!$E$8:$E$331,'Transaction Details 2025'!$I$8:$I$331,$A49,'Transaction Details 2025'!$E$8:$E$331,"<0") -> -2241.85 | D49: =B49+C49 -> -131.05
A50: =EDATE(A49,1) -> 45778 | B50: =SUMIFS('Transaction Details 2025'!$E$8:$E$331,'Transaction Details 2025'!$I$8:$I$331,$A50,'Transaction Details 2025'!$E$8:$E$331,">0") -> 12482.35 | C50: =SUMIFS('Transaction Details 2025'!$E$8:$E$331,'Transaction Details 2025'!$I$8:$I$331,$A50,'Transaction Details 2025'!$E$8:$E$331,"<0") -> -1542.61 | D50: =B50+C50 -> 10939.74
A51: =EDATE(A50,1) -> 45809 | B51: =SUMIFS('Transaction Details 2025'!$E$8:$E$331,'Transaction Details 2025'!$I$8:$I$331,$A51,'Transaction Details 2025'!$E$8:$E$331,">0") -> 1737.73 | C51: =SUMIFS('Transaction Details 2025'!$E$8:$E$331,'Transaction Details 2025'!$I$8:$I$331,$A51,'Transaction Details 2025'!$E$8:$E$331,"<0") -> -12616.91 | D51: =B51+C51 -> -10879.18
A52: =EDATE(A51,1) -> 45839 | B52: =SUMIFS('Transaction Details 2025'!$E$8:$E$331,'Transaction Details 2025'!$I$8:$I$331,$A52,'Transaction Details 2025'!$E$8:$E$331,">0") -> 1632.17 | C52: =SUMIFS('Transaction Details 2025'!$E$8:$E$331,'Transaction Details 2025'!$I$8:$I$331,$A52,'Transaction Details 2025'!$E$8:$E$331,"<0") -> -1373.57 | D52: =B52+C52 -> 258.6
A53: =EDATE(A52,1) -> 45870 | B53: =SUMIFS('Transaction Details 2025'!$E$8:$E$331,'Transaction Details 2025'!$I$8:$I$331,$A53,'Transaction Details 2025'!$E$8:$E$331,">0") -> 1493.06 | C53: =SUMIFS('Transaction Details 2025'!$E$8:$E$331,'Transaction Details 2025'!$I$8:$I$331,$A53,'Transaction Details 2025'!$E$8:$E$331,"<0") -> -2055.22 | D53: =B53+C53 -> -562.16
A54: =EDATE(A53,1) -> 45901 | B54: =SUMIFS('Transaction Details 2025'!$E$8:$E$331,'Transaction Details 2025'!$I$8:$I$331,$A54,'Transaction Details 2025'!$E$8:$E$331,">0") -> 1301.58 | C54: =SUMIFS('Transaction Details 2025'!$E$8:$E$331,'Transaction Details 2025'!$I$8:$I$331,$A54,'Transaction Details 2025'!$E$8:$E$331,"<0") -> 0 | D54: =B54+C54 -> 1301.58
A55: =EDATE(A54,1) -> 45931 | B55: =SUMIFS('Transaction Details 2025'!$E$8:$E$331,'Transaction Details 2025'!$I$8:$I$331,$A55,'Transaction Details 2025'!$E$8:$E$331,">0") -> 1394.91 | C55: =SUMIFS('Transaction Details 2025'!$E$8:$E$331,'Transaction Details 2025'!$I$8:$I$331,$A55,'Transaction Details 2025'!$E$8:$E$331,"<0") -> -1274.54 | D55: =B55+C55 -> 120.37
A56: =EDATE(A55,1) -> 45962 | B56: =SUMIFS('Transaction Details 2025'!$E$8:$E$331,'Transaction Details 2025'!$I$8:$I$331,$A56,'Transaction Details 2025'!$E$8:$E$331,">0") -> 1091.55 | C56: =SUMIFS('Transaction Details 2025'!$E$8:$E$331,'Transaction Details 2025'!$I$8:$I$331,$A56,'Transaction Details 2025'!$E$8:$E$331,"<0") -> -2439.53 | D56: =B56+C56 -> -1347.98
A57: =EDATE(A56,1) -> 45992 | B57: =SUMIFS('Transaction Details 2025'!$E$8:$E$331,'Transaction Details 2025'!$I$8:$I$331,$A57,'Transaction Details 2025'!$E$8:$E$331,">0") -> 1737.42 | C57: =SUMIFS('Transaction Details 2025'!$E$8:$E$331,'Transaction Details 2025'!$I$8:$I$331,$A57,'Transaction Details 2025'!$E$8:$E$331,"<0") -> -1625.86 | D57: =B57+C57 -> 111.56
A58: Total | B58: =SUM(B46:B57) -> 35067.32 | C58: =SUM(C46:C57) -> -35902.93 | D58: =SUM(D46:D57) -> -835.61
A60: SPEND BY CARD MEMBER
A61: Card Member | B61: Charges | C61: Credits | D61: Net
A62: John Dunning | B62: =SUMIFS('Transaction Details 2025'!$E$8:$E$331,'Transaction Details 2025'!$C$8:$C$331,$A62,'Transaction Details 2025'!$E$8:$E$331,">0") -> 23639.85 | C62: =SUMIFS('Transaction Details 2025'!$E$8:$E$331,'Transaction Details 2025'!$C$8:$C$331,$A62,'Transaction Details 2025'!$E$8:$E$331,"<0") -> -35614.08 | D62: =B62+C62 -> -11974.23
A63: Ava Perez | B63: =SUMIFS('Transaction Details 2025'!$E$8:$E$331,'Transaction Details 2025'!$C$8:$C$331,$A63,'Transaction Details 2025'!$E$8:$E$331,">0") -> 10979.48 | C63: =SUMIFS('Transaction Details 2025'!$E$8:$E$331,'Transaction Details 2025'!$C$8:$C$331,$A63,'Transaction Details 2025'!$E$8:$E$331,"<0") -> -288.85 | D63: =B63+C63 -> 10690.63
A64: Angela L Dunning | B64: =SUMIFS('Transaction Details 2025'!$E$8:$E$331,'Transaction Details 2025'!$C$8:$C$331,$A64,'Transaction Details 2025'!$E$8:$E$331,">0") -> 447.99 | C64: =SUMIFS('Transaction Details 2025'!$E$8:$E$331,'Transaction Details 2025'!$C$8:$C$331,$A64,'Transaction Details 2025'!$E$8:$E$331,"<0") -> 0 | D64: =B64+C64 -> 447.99
A65: Total | B65: =SUM(B62:B64) -> 35067.32 | C65: =SUM(C62:C64) -> -35902.93 | D65: =SUM(D62:D64) -> -835.61
A67: PAYMENTS, CREDITS & REFUNDS DETAIL
A68: Date | B68: Description | C68: Card Member | D68: Amount
A69: ='Transaction Details 2025'!A13 -> 12/18/2025 | B69: ='Transaction Details 2025'!B13 -> ONLINE PAYMENT - THANK YOU | C69: ='Transaction Details 2025'!C13 -> JOHN DUNNING | D69: ='Transaction Details 2025'!E13 -> -1625.86
A70: ='Transaction Details 2025'!A30 -> 11/26/2025 | B70: ='Transaction Details 2025'!B30 -> CUSTOMER SERVICE PAYMENT - THANK YOU | C70: ='Transaction Details 2025'!C30 -> JOHN DUNNING | D70: ='Transaction Details 2025'!E30 -> -2439.53
A71: ='Transaction Details 2025'!A48 -> 10/27/2025 | B71: ='Transaction Details 2025'!B48 -> ONLINE PAYMENT - THANK YOU | C71: ='Transaction Details 2025'!C48 -> JOHN DUNNING | D71: ='Transaction Details 2025'!E48 -> -1242.84
A72: ='Transaction Details 2025'!A71 -> 10/03/2025 | B72: ='Transaction Details 2025'!B71 -> ADJ REDIST PURCHASE BAL | C72: ='Transaction Details 2025'!C71 -> JOHN DUNNING | D72: ='Transaction Details 2025'!E71 -> -31.7
A73: ='Transaction Details 2025'!A100 -> 08/28/2025 | B73: ='Transaction Details 2025'!B100 -> DEPOP BROOKLYN NY | C73: ='Transaction Details 2025'!C100 -> AVA PEREZ | D73: ='Transaction Details 2025'!E100 -> -120.19
A74: ='Transaction Details 2025'!A101 -> 08/28/2025 | B74: ='Transaction Details 2025'!B101 -> ONLINE PAYMENT - THANK YOU | C74: ='Transaction Details 2025'!C101 -> JOHN DUNNING | D74: ='Transaction Details 2025'!E101 -> -1935.03
A75: ='Transaction Details 2025'!A136 -> 07/17/2025 | B75: ='Transaction Details 2025'!B136 -> ONLINE PAYMENT - THANK YOU | C75: ='Transaction Details 2025'!C136 -> JOHN DUNNING | D75: ='Transaction Details 2025'!E136 -> -1373.57
A76: ='Transaction Details 2025'!A158 -> 06/27/2025 | B76: ='Transaction Details 2025'!B158 -> CUSTOMER SERVICE PAYMENT - THANK YOU | C76: ='Transaction Details 2025'!C158 -> JOHN DUNNING | D76: ='Transaction Details 2025'!E158 -> -11124
A77: ='Transaction Details 2025'!A159 -> 06/27/2025 | B77: ='Transaction Details 2025'!B159 -> CUSTOMER SERVICE PAYMENT - THANK YOU | C77: ='Transaction Details 2025'!C159 -> JOHN DUNNING | D77: ='Transaction Details 2025'!E159 -> -1492.91
A78: ='Transaction Details 2025'!A192 -> 05/26/2025 | B78: ='Transaction Details 2025'!B192 -> CUSTOMER SERVICE PAYMENT - THANK YOU | C78: ='Transaction Details 2025'!C192 -> JOHN DUNNING | D78: ='Transaction Details 2025'!E192 -> -1542.61
A79: ='Transaction Details 2025'!A214 -> 04/28/2025 | B79: ='Transaction Details 2025'!B214 -> CUSTOMER SERVICE PAYMENT - THANK YOU | C79: ='Transaction Details 2025'!C214 -> JOHN DUNNING | D79: ='Transaction Details 2025'!E214 -> -2222.92
A80: ='Transaction Details 2025'!A234 -> 04/06/2025 | B80: ='Transaction Details 2025'!B234 -> PAYPAL *POSHMARK 6502624771 CA | C80: ='Transaction Details 2025'!C234 -> AVA PEREZ | D80: ='Transaction Details 2025'!E234 -> -18.93
A81: ='Transaction Details 2025'!A243 -> 03/29/2025 | B81: ='Transaction Details 2025'!B243 -> DEPOP NEW YORK NY | C81: ='Transaction Details 2025'!C243 -> AVA PEREZ | D81: ='Transaction Details 2025'!E243 -> -149.73
A82: ='Transaction Details 2025'!A245 -> 03/28/2025 | B82: ='Transaction Details 2025'!B245 -> CUSTOMER SERVICE PAYMENT - THANK YOU | C82: ='Transaction Details 2025'!C245 -> JOHN DUNNING | D82: ='Transaction Details 2025'!E245 -> -1982.28
A83: ='Transaction Details 2025'!A275 -> 02/24/2025 | B83: ='Transaction Details 2025'!B275 -> ONLINE PAYMENT - THANK YOU | C83: ='Transaction Details 2025'!C275 -> JOHN DUNNING | D83: ='Transaction Details 2025'!E275 -> -1853.08
A84: ='Transaction Details 2025'!A278 -> 02/20/2025 | B84: ='Transaction Details 2025'!B278 -> EQUINOX PLUS NEW YORK | C84: ='Transaction Details 2025'!C278 -> JOHN DUNNING | D84: ='Transaction Details 2025'!E278 -> -300
A85: ='Transaction Details 2025'!A294 -> 02/04/2025 | B85: ='Transaction Details 2025'!B294 -> AMEX TRAVEL PURCHASE WITH MR POINTS CREDIT | C85: ='Transaction Details 2025'!C294 -> JOHN DUNNING | D85: ='Transaction Details 2025'!E294 -> -705.48
A86: ='Transaction Details 2025'!A295 -> 02/04/2025 | B86: ='Transaction Details 2025'!B295 -> Credit for AMEX Error | C86: ='Transaction Details 2025'!C295 -> JOHN DUNNING | D86: ='Transaction Details 2025'!E295 -> -12.77
A87: ='Transaction Details 2025'!A296 -> 02/03/2025 | B87: ='Transaction Details 2025'!B296 -> ADJ REDIST PURCHASE BAL | C87: ='Transaction Details 2025'!C296 -> JOHN DUNNING | D87: ='Transaction Details 2025'!E296 -> -300
A88: ='Transaction Details 2025'!A301 -> 01/30/2025 | B88: ='Transaction Details 2025'!B301 -> CUSTOMER SERVICE PAYMENT - THANK YOU | C88: ='Transaction Details 2025'!C301 -> JOHN DUNNING | D88: ='Transaction Details 2025'!E301 -> -2465.25
A89: ='Transaction Details 2025'!A302 -> 01/28/2025 | B89: ='Transaction Details 2025'!B302 -> ONLINE PAYMENT - THANK YOU | C89: ='Transaction Details 2025'!C302 -> JOHN DUNNING | D89: ='Transaction Details 2025'!E302 -> -2465.25
A90: ='Transaction Details 2025'!A311 -> 01/17/2025 | B90: ='Transaction Details 2025'!B311 -> AMERICAN EXPRESS COMNEW YORK | C90: ='Transaction Details 2025'!C311 -> JOHN DUNNING | D90: ='Transaction Details 2025'!E311 -> -300
A91: ='Transaction Details 2025'!A324 -> 01/07/2025 | B91: ='Transaction Details 2025'!B324 -> CLEAR NEW YORK | C91: ='Transaction Details 2025'!C324 -> JOHN DUNNING | D91: ='Transaction Details 2025'!E324 -> -199
A92: Total Credits & Payments | D92: =SUM(D69:D91) -> -35902.93
B93: =IF(ROUND(D92-B10,2)=0,"✓ ties to Credits & Payments total","⚠ mismatch") -> ✓ ties to Credits & Payments total

Sheet Monthly Breakdown 2025
A1: FAMILY AMEX
A2: Amex Platinum | Monthly Breakdown · 2025
A4: Category | B4: =DATE(2025,1,1) -> 45658 | C4: =EDATE(B4,1) -> 45689 | D4: =EDATE(C4,1) -> 45717 | E4: =EDATE(D4,1) -> 45748 | F4: =EDATE(E4,1) -> 45778 | G4: =EDATE(F4,1) -> 45809 | H4: =EDATE(G4,1) -> 45839 | I4: =EDATE(H4,1) -> 45870 | J4: =EDATE(I4,1) -> 45901 | ... M4: =EDATE(L4,1) -> 45992 | N4: Total
A5: DWG-RE Platform (Redirected) | B5: =SUMIFS('Transaction Details 2025'!$E$8:$E$331,'Transaction Details 2025'!$J$8:$J$331,$A5,'Transaction Details 2025'!$I$8:$I$331,B$4) -> 362.92 | C5: =SUMIFS('Transaction Details 2025'!$E$8:$E$331,'Transaction Details 2025'!$J$8:$J$331,$A5,'Transaction Details 2025'!$I$8:$I$331,C$4) -> 365.92 | D5: =SUMIFS('Transaction Details 2025'!$E$8:$E$331,'Transaction Details 2025'!$J$8:$J$331,$A5,'Transaction Details 2025'!$I$8:$I$331,D$4) -> 365.92 | E5: =SUMIFS('Transaction Details 2025'!$E$8:$E$331,'Transaction Details 2025'!$J$8:$J$331,$A5,'Transaction Details 2025'!$I$8:$I$331,E$4) -> 1129.91 | F5: =SUMIFS('Transaction Details 2025'!$E$8:$E$331,'Transaction Details 2025'!$J$8:$J$331,$A5,'Transaction Details 2025'!$I$8:$I$331,F$4) -> 11489.92 | G5: =SUMIFS('Transaction Details 2025'!$E$8:$E$331,'Transaction Details 2025'!$J$8:$J$331,$A5,'Transaction Details 2025'!$I$8:$I$331,G$4) -> 365.92 | H5: =SUMIFS('Transaction Details 2025'!$E$8:$E$331,'Transaction Details 2025'!$J$8:$J$331,$A5,'Transaction Details 2025'!$I$8:$I$331,H$4) -> 365.92 | I5: =SUMIFS('Transaction Details 2025'!$E$8:$E$331,'Transaction Details 2025'!$J$8:$J$331,$A5,'Transaction Details 2025'!$I$8:$I$331,I$4) -> 365.92 | ... M5: =SUMIFS('Transaction Details 2025'!$E$8:$E$331,'Transaction Details 2025'!$J$8:$J$331,$A5,'Transaction Details 2025'!$I$8:$I$331,M$4) -> 386.37 | N5: =SUM(B5:M5) -> 16316.48
A6: DWG-RE Platform (Canceled) | B6: =SUMIFS('Transaction Details 2025'!$E$8:$E$331,'Transaction Details 2025'!$J$8:$J$331,$A6,'Transaction Details 2025'!$I$8:$I$331,B$4) -> 0 | C6: =SUMIFS('Transaction Details 2025'!$E$8:$E$331,'Transaction Details 2025'!$J$8:$J$331,$A6,'Transaction Details 2025'!$I$8:$I$331,C$4) -> 0 | D6: =SUMIFS('Transaction Details 2025'!$E$8:$E$331,'Transaction Details 2025'!$J$8:$J$331,$A6,'Transaction Details 2025'!$I$8:$I$331,D$4) -> 0 | E6: =SUMIFS('Transaction Details 2025'!$E$8:$E$331,'Transaction Details 2025'!$J$8:$J$331,$A6,'Transaction Details 2025'!$I$8:$I$331,E$4) -> 0 | F6: =SUMIFS('Transaction Details 2025'!$E$8:$E$331,'Transaction Details 2025'!$J$8:$J$331,$A6,'Transaction Details 2025'!$I$8:$I$331,F$4) -> 0 | G6: =SUMIFS('Transaction Details 2025'!$E$8:$E$331,'Transaction Details 2025'!$J$8:$J$331,$A6,'Transaction Details 2025'!$I$8:$I$331,G$4) -> 0 | H6: =SUMIFS('Transaction Details 2025'!$E$8:$E$331,'Transaction Details 2025'!$J$8:$J$331,$A6,'Transaction Details 2025'!$I$8:$I$331,H$4) -> 0 | I6: =SUMIFS('Transaction Details 2025'!$E$8:$E$331,'Transaction Details 2025'!$J$8:$J$331,$A6,'Transaction Details 2025'!$I$8:$I$331,I$4) -> 0 | ... M6: =SUMIFS('Transaction Details 2025'!$E$8:$E$331,'Transaction Details 2025'!$J$8:$J$331,$A6,'Transaction Details 2025'!$I$8:$I$331,M$4) -> 48 | N6: =SUM(B6:M6) -> 48
A7: Sponsor Cloud | B7: =SUMIFS('Transaction Details 2025'!$E$8:$E$331,'Transaction Details 2025'!$J$8:$J$331,$A7,'Transaction Details 2025'!$I$8:$I$331,B$4) -> 0 | C7: =SUMIFS('Transaction Details 2025'!$E$8:$E$331,'Transaction Details 2025'!$J$8:$J$331,$A7,'Transaction Details 2025'!$I$8:$I$331,C$4) -> 2.94 | D7: =SUMIFS('Transaction Details 2025'!$E$8:$E$331,'Transaction Details 2025'!$J$8:$J$331,$A7,'Transaction Details 2025'!$I$8:$I$331,D$4) -> 152.11 | E7: =SUMIFS('Transaction Details 2025'!$E$8:$E$331,'Transaction Details 2025'!$J$8:$J$331,$A7,'Transaction Details 2025'!$I$8:$I$331,E$4) -> 184.26 | F7: =SUMIFS('Transaction Details 2025'!$E$8:$E$331,'Transaction Details 2025'!$J$8:$J$331,$A7,'Transaction Details 2025'!$I$8:$I$331,F$4) -> 0 | G7: =SUMIFS('Transaction Details 2025'!$E$8:$E$331,'Transaction Details 2025'!$J$8:$J$331,$A7,'Transaction Details 2025'!$I$8:$I$331,G$4) -> 0 | H7: =SUMIFS('Transaction Details 2025'!$E$8:$E$331,'Transaction Details 2025'!$J$8:$J$331,$A7,'Transaction Details 2025'!$I$8:$I$331,H$4) -> 0 | I7: =SUMIFS('Transaction Details 2025'!$E$8:$E$331,'Transaction Details 2025'!$J$8:$J$331,$A7,'Transaction Details 2025'!$I$8:$I$331,I$4) -> 0 | ... M7: =SUMIFS('Transaction Details 2025'!$E$8:$E$331,'Transaction Details 2025'!$J$8:$J$331,$A7,'Transaction Details 2025'!$I$8:$I$331,M$4) -> 0 | N7: =SUM(B7:M7) -> 339.31
A8: Business Services-Other Services | B8: =SUMIFS('Transaction Details 2025'!$E$8:$E$331,'Transaction Details 2025'!$J$8:$J$331,$A8,'Transaction Details 2025'!$I$8:$I$331,B$4) -> -300 | C8: =SUMIFS('Transaction Details 2025'!$E$8:$E$331,'Transaction Details 2025'!$J$8:$J$331,$A8,'Transaction Details 2025'!$I$8:$I$331,C$4) -> 0 | D8: =SUMIFS('Transaction Details 2025'!$E$8:$E$331,'Transaction Details 2025'!$J$8:$J$331,$A8,'Transaction Details 2025'!$I$8:$I$331,D$4) -> 0 | E8: =SUMIFS('Transaction Details 2025'!$E$8:$E$331,'Transaction Details 2025'!$J$8:$J$331,$A8,'Transaction Details 2025'!$I$8:$I$331,E$4) -> 0 | F8: =SUMIFS('Transaction Details 2025'!$E$8:$E$331,'Transaction Details 2025'!$J$8:$J$331,$A8,'Transaction Details 2025'!$I$8:$I$331,F$4) -> 0 | G8: =SUMIFS('Transaction Details 2025'!$E$8:$E$331,'Transaction Details 2025'!$J$8:$J$331,$A8,'Transaction Details 2025'!$I$8:$I$331,G$4) -> 0 | H8: =SUMIFS('Transaction Details 2025'!$E$8:$E$331,'Transaction Details 2025'!$J$8:$J$331,$A8,'Transaction Details 2025'!$I$8:$I$331,H$4) -> 0 | I8: =SUMIFS('Transaction Details 2025'!$E$8:$E$331,'Transaction Details 2025'!$J$8:$J$331,$A8,'Transaction Details 2025'!$I$8:$I$331,I$4) -> 0 | ... M8: =SUMIFS('Transaction Details 2025'!$E$8:$E$331,'Transaction Details 2025'!$J$8:$J$331,$A8,'Transaction Details 2025'!$I$8:$I$331,M$4) -> 0 | N8: =SUM(B8:M8) -> -300
A9: Business Services-Professional Services | B9: =SUMIFS('Transaction Details 2025'!$E$8:$E$331,'Transaction Details 2025'!$J$8:$J$331,$A9,'Transaction Details 2025'!$I$8:$I$331,B$4) -> 119 | C9: =SUMIFS('Transaction Details 2025'!$E$8:$E$331,'Transaction Details 2025'!$J$8:$J$331,$A9,'Transaction Details 2025'!$I$8:$I$331,C$4) -> 0 | D9: =SUMIFS('Transaction Details 2025'!$E$8:$E$331,'Transaction Details 2025'!$J$8:$J$331,$A9,'Transaction Details 2025'!$I$8:$I$331,D$4) -> 0 | E9: =SUMIFS('Transaction Details 2025'!$E$8:$E$331,'Transaction Details 2025'!$J$8:$J$331,$A9,'Transaction Details 2025'!$I$8:$I$331,E$4) -> 0 | F9: =SUMIFS('Transaction Details 2025'!$E$8:$E$331,'Transaction Details 2025'!$J$8:$J$331,$A9,'Transaction Details 2025'!$I$8:$I$331,F$4) -> 0 | G9: =SUMIFS('Transaction Details 2025'!$E$8:$E$331,'Transaction Details 2025'!$J$8:$J$331,$A9,'Transaction Details 2025'!$I$8:$I$331,G$4) -> 0 | H9: =SUMIFS('Transaction Details 2025'!$E$8:$E$331,'Transaction Details 2025'!$J$8:$J$331,$A9,'Transaction Details 2025'!$I$8:$I$331,H$4) -> 0 | I9: =SUMIFS('Transaction Details 2025'!$E$8:$E$331,'Transaction Details 2025'!$J$8:$J$331,$A9,'Transaction Details 2025'!$I$8:$I$331,I$4) -> 0 | ... M9: =SUMIFS('Transaction Details 2025'!$E$8:$E$331,'Transaction Details 2025'!$J$8:$J$331,$A9,'Transaction Details 2025'!$I$8:$I$331,M$4) -> 0 | N9: =SUM(B9:M9) -> 119
A10: Renewal Fee | B10: =SUMIFS('Transaction Details 2025'!$E$8:$E$331,'Transaction Details 2025'!$J$8:$J$331,$A10,'Transaction Details 2025'!$I$8:$I$331,B$4) -> 0 | C10: =SUMIFS('Transaction Details 2025'!$E$8:$E$331,'Transaction Details 2025'!$J$8:$J$331,$A10,'Transaction Details 2025'!$I$8:$I$331,C$4) -> 0 | D10: =SUMIFS('Transaction Details 2025'!$E$8:$E$331,'Transaction Details 2025'!$J$8:$J$331,$A10,'Transaction Details 2025'!$I$8:$I$331,D$4) -> 0 | E10: =SUMIFS('Transaction Details 2025'!$E$8:$E$331,'Transaction Details 2025'!$J$8:$J$331,$A10,'Transaction Details 2025'!$I$8:$I$331,E$4) -> 0 | F10: =SUMIFS('Transaction Details 2025'!$E$8:$E$331,'Transaction Details 2025'!$J$8:$J$331,$A10,'Transaction Details 2025'!$I$8:$I$331,F$4) -> 0 | G10: =SUMIFS('Transaction Details 2025'!$E$8:$E$331,'Transaction Details 2025'!$J$8:$J$331,$A10,'Transaction Details 2025'!$I$8:$I$331,G$4) -> 0 | H10: =SUMIFS('Transaction Details 2025'!$E$8:$E$331,'Transaction Details 2025'!$J$8:$J$331,$A10,'Transaction Details 2025'!$I$8:$I$331,H$4) -> 0 | I10: =SUMIFS('Transaction Details 2025'!$E$8:$E$331,'Transaction Details 2025'!$J$8:$J$331,$A10,'Transaction Details 2025'!$I$8:$I$331,I$4) -> 0 | ... M10: =SUMIFS('Transaction Details 2025'!$E$8:$E$331,'Transaction Details 2025'!$J$8:$J$331,$A10,'Transaction Details 2025'!$I$8:$I$331,M$4) -> 695 | N10: =SUM(B10:M10) -> 695
A11: Travel | B11: =SUMIFS('Transaction Details 2025'!$E$8:$E$331,'Transaction Details 2025'!$J$8:$J$331,$A11,'Transaction Details 2025'!$I$8:$I$331,B$4) -> 0 | C11: =SUMIFS('Transaction Details 2025'!$E$8:$E$331,'Transaction Details 2025'!$J$8:$J$331,$A11,'Transaction Details 2025'!$I$8:$I$331,C$4) -> 0 | D11: =SUMIFS('Transaction Details 2025'!$E$8:$E$331,'Transaction Details 2025'!$J$8:$J$331,$A11,'Transaction Details 2025'!$I$8:$I$331,D$4) -> 50.31 | E11: =SUMIFS('Transaction Details 2025'!$E$8:$E$331,'Transaction Details 2025'!$J$8:$J$331,$A11,'Transaction Details 2025'!$I$8:$I$331,E$4) -> 0 | F11: =SUMIFS('Transaction Details 2025'!$E$8:$E$331,'Transaction Details 2025'!$J$8:$J$331,$A11,'Transaction Details 2025'!$I$8:$I$331,F$4) -> 0 | G11: =SUMIFS('Transaction Details 2025'!$E$8:$E$331,'Transaction Details 2025'!$J$8:$J$331,$A11,'Transaction Details 2025'!$I$8:$I$331,G$4) -> 0 | H11: =SUMIFS('Transaction Details 2025'!$E$8:$E$331,'Transaction Details 2025'!$J$8:$J$331,$A11,'Transaction Details 2025'!$I$8:$I$331,H$4) -> 0 | I11: =SUMIFS('Transaction Details 2025'!$E$8:$E$331,'Transaction Details 2025'!$J$8:$J$331,$A11,'Transaction Details 2025'!$I$8:$I$331,I$4) -> 0 | ... M11: =SUMIFS('Transaction Details 2025'!$E$8:$E$331,'Transaction Details 2025'!$J$8:$J$331,$A11,'Transaction Details 2025'!$I$8:$I$331,M$4) -> 0 | N11: =SUM(B11:M11) -> 50.31
A12: Travel-Airline | B12: =SUMIFS('Transaction Details 2025'!$E$8:$E$331,'Transaction Details 2025'!$J$8:$J$331,$A12,'Transaction Details 2025'!$I$8:$I$331,B$4) -> 438.48 | C12: =SUMIFS('Transaction Details 2025'!$E$8:$E$331,'Transaction Details 2025'!$J$8:$J$331,$A12,'Transaction Details 2025'!$I$8:$I$331,C$4) -> 705.48 | D12: =SUMIFS('Transaction Details 2025'!$E$8:$E$331,'Transaction Details 2025'!$J$8:$J$331,$A12,'Transaction Details 2025'!$I$8:$I$331,D$4) -> 0 | E12: =SUMIFS('Transaction Details 2025'!$E$8:$E$331,'Transaction Details 2025'!$J$8:$J$331,$A12,'Transaction Details 2025'!$I$8:$I$331,E$4) -> 0 | F12: =SUMIFS('Transaction Details 2025'!$E$8:$E$331,'Transaction Details 2025'!$J$8:$J$331,$A12,'Transaction Details 2025'!$I$8:$I$331,F$4) -> 0 | G12: =SUMIFS('Transaction Details 2025'!$E$8:$E$331,'Transaction Details 2025'!$J$8:$J$331,$A12,'Transaction Details 2025'!$I$8:$I$331,G$4) -> 0 | H12: =SUMIFS('Transaction Details 2025'!$E$8:$E$331,'Transaction Details 2025'!$J$8:$J$331,$A12,'Transaction Details 2025'!$I$8:$I$331,H$4) -> 0 | I12: =SUMIFS('Transaction Details 2025'!$E$8:$E$331,'Transaction Details 2025'!$J$8:$J$331,$A12,'Transaction Details 2025'!$I$8:$I$331,I$4) -> 0 | ... M12: =SUMIFS('Transaction Details 2025'!$E$8:$E$331,'Transaction Details 2025'!$J$8:$J$331,$A12,'Transaction Details 2025'!$I$8:$I$331,M$4) -> 0 | N12: =SUM(B12:M12) -> 1143.96
A13: Family | B13: =SUMIFS('Transaction Details 2025'!$E$8:$E$331,'Transaction Details 2025'!$J$8:$J$331,$A13,'Transaction Details 2025'!$I$8:$I$331,B$4) -> 22.99 | C13: =SUMIFS('Transaction Details 2025'!$E$8:$E$331,'Transaction Details 2025'!$J$8:$J$331,$A13,'Transaction Details 2025'!$I$8:$I$331,C$4) -> 22.99 | D13: =SUMIFS('Transaction Details 2025'!$E$8:$E$331,'Transaction Details 2025'!$J$8:$J$331,$A13,'Transaction Details 2025'!$I$8:$I$331,D$4) -> 24.99 | E13: =SUMIFS('Transaction Details 2025'!$E$8:$E$331,'Transaction Details 2025'!$J$8:$J$331,$A13,'Transaction Details 2025'!$I$8:$I$331,E$4) -> 31.98 | F13: =SUMIFS('Transaction Details 2025'!$E$8:$E$331,'Transaction Details 2025'!$J$8:$J$331,$A13,'Transaction Details 2025'!$I$8:$I$331,F$4) -> 24.99 | G13: =SUMIFS('Transaction Details 2025'!$E$8:$E$331,'Transaction Details 2025'!$J$8:$J$331,$A13,'Transaction Details 2025'!$I$8:$I$331,G$4) -> 24.99 | H13: =SUMIFS('Transaction Details 2025'!$E$8:$E$331,'Transaction Details 2025'!$J$8:$J$331,$A13,'Transaction Details 2025'!$I$8:$I$331,H$4) -> 24.99 | I13: =SUMIFS('Transaction Details 2025'!$E$8:$E$331,'Transaction Details 2025'!$J$8:$J$331,$A13,'Transaction Details 2025'!$I$8:$I$331,I$4) -> 24.99 | ... M13: =SUMIFS('Transaction Details 2025'!$E$8:$E$331,'Transaction Details 2025'!$J$8:$J$331,$A13,'Transaction Details 2025'!$I$8:$I$331,M$4) -> 24.99 | N13: =SUM(B13:M13) -> 302.87
A14: Personal - Health | B14: =SUMIFS('Transaction Details 2025'!$E$8:$E$331,'Transaction Details 2025'!$J$8:$J$331,$A14,'Transaction Details 2025'!$I$8:$I$331,B$4) -> 28.5 | C14: =SUMIFS('Transaction Details 2025'!$E$8:$E$331,'Transaction Details 2025'!$J$8:$J$331,$A14,'Transaction Details 2025'!$I$8:$I$331,C$4) -> 0 | D14: =SUMIFS('Transaction Details 2025'!$E$8:$E$331,'Transaction Details 2025'!$J$8:$J$331,$A14,'Transaction Details 2025'!$I$8:$I$331,D$4) -> 0 | E14: =SUMIFS('Transaction Details 2025'!$E$8:$E$331,'Transaction Details 2025'!$J$8:$J$331,$A14,'Transaction Details 2025'!$I$8:$I$331,E$4) -> 0 | F14: =SUMIFS('Transaction Details 2025'!$E$8:$E$331,'Transaction Details 2025'!$J$8:$J$331,$A14,'Transaction Details 2025'!$I$8:$I$331,F$4) -> 0 | G14: =SUMIFS('Transaction Details 2025'!$E$8:$E$331,'Transaction Details 2025'!$J$8:$J$331,$A14,'Transaction Details 2025'!$I$8:$I$331,G$4) -> 0 | H14: =SUMIFS('Transaction Details 2025'!$E$8:$E$331,'Transaction Details 2025'!$J$8:$J$331,$A14,'Transaction Details 2025'!$I$8:$I$331,H$4) -> 0 | I14: =SUMIFS('Transaction Details 2025'!$E$8:$E$331,'Transaction Details 2025'!$J$8:$J$331,$A14,'Transaction Details 2025'!$I$8:$I$331,I$4) -> 0 | ... M14: =SUMIFS('Transaction Details 2025'!$E$8:$E$331,'Transaction Details 2025'!$J$8:$J$331,$A14,'Transaction Details 2025'!$I$8:$I$331,M$4) -> 0 | N14: =SUM(B14:M14) -> 280.44
A15: Personal - Car | B15: =SUMIFS('Transaction Details 2025'!$E$8:$E$331,'Transaction Details 2025'!$J$8:$J$331,$A15,'Transaction Details 2025'!$I$8:$I$331,B$4) -> 62.8 | C15: =SUMIFS('Transaction Details 2025'!$E$8:$E$331,'Transaction Details 2025'!$J$8:$J$331,$A15,'Transaction Details 2025'!$I$8:$I$331,C$4) -> 0 | D15: =SUMIFS('Transaction Details 2025'!$E$8:$E$331,'Transaction Details 2025'!$J$8:$J$331,$A15,'Transaction Details 2025'!$I$8:$I$331,D$4) -> 0 | E15: =SUMIFS('Transaction Details 2025'!$E$8:$E$331,'Transaction Details 2025'!$J$8:$J$331,$A15,'Transaction Details 2025'!$I$8:$I$331,E$4) -> 0 | F15: =SUMIFS('Transaction Details 2025'!$E$8:$E$331,'Transaction Details 2025'!$J$8:$J$331,$A15,'Transaction Details 2025'!$I$8:$I$331,F$4) -> 0 | G15: =SUMIFS('Transaction Details 2025'!$E$8:$E$331,'Transaction Details 2025'!$J$8:$J$331,$A15,'Transaction Details 2025'!$I$8:$I$331,G$4) -> 0 | H15: =SUMIFS('Transaction Details 2025'!$E$8:$E$331,'Transaction Details 2025'!$J$8:$J$331,$A15,'Transaction Details 2025'!$I$8:$I$331,H$4) -> 0 | I15: =SUMIFS('Transaction Details 2025'!$E$8:$E$331,'Transaction Details 2025'!$J$8:$J$331,$A15,'Transaction Details 2025'!$I$8:$I$331,I$4) -> 0 | ... M15: =SUMIFS('Transaction Details 2025'!$E$8:$E$331,'Transaction Details 2025'!$J$8:$J$331,$A15,'Transaction Details 2025'!$I$8:$I$331,M$4) -> 0 | N15: =SUM(B15:M15) -> 62.8
A16: Personal | B16: =SUMIFS('Transaction Details 2025'!$E$8:$E$331,'Transaction Details 2025'!$J$8:$J$331,$A16,'Transaction Details 2025'!$I$8:$I$331,B$4) -> 591.26 | C16: =SUMIFS('Transaction Details 2025'!$E$8:$E$331,'Transaction Details 2025'!$J$8:$J$331,$A16,'Transaction Details 2025'!$I$8:$I$331,C$4) -> 0 | D16: =SUMIFS('Transaction Details 2025'!$E$8:$E$331,'Transaction Details 2025'!$J$8:$J$331,$A16,'Transaction Details 2025'!$I$8:$I$331,D$4) -> 0 | E16: =SUMIFS('Transaction Details 2025'!$E$8:$E$331,'Transaction Details 2025'!$J$8:$J$331,$A16,'Transaction Details 2025'!$I$8:$I$331,E$4) -> 0 | F16: =SUMIFS('Transaction Details 2025'!$E$8:$E$331,'Transaction Details 2025'!$J$8:$J$331,$A16,'Transaction Details 2025'!$I$8:$I$331,F$4) -> 0 | G16: =SUMIFS('Transaction Details 2025'!$E$8:$E$331,'Transaction Details 2025'!$J$8:$J$331,$A16,'Transaction Details 2025'!$I$8:$I$331,G$4) -> 0 | H16: =SUMIFS('Transaction Details 2025'!$E$8:$E$331,'Transaction Details 2025'!$J$8:$J$331,$A16,'Transaction Details 2025'!$I$8:$I$331,H$4) -> 0 | I16: =SUMIFS('Transaction Details 2025'!$E$8:$E$331,'Transaction Details 2025'!$J$8:$J$331,$A16,'Transaction Details 2025'!$I$8:$I$331,I$4) -> 0 | ... M16: =SUMIFS('Transaction Details 2025'!$E$8:$E$331,'Transaction Details 2025'!$J$8:$J$331,$A16,'Transaction Details 2025'!$I$8:$I$331,M$4) -> 0 | N16: =SUM(B16:M16) -> 591.26
... A22: Online AMEX Payment | B22: =SUMIFS('Transaction Details 2025'!$E$8:$E$331,'Transaction Details 2025'!$J$8:$J$331,$A22,'Transaction Details 2025'!$I$8:$I$331,B$4) -> -4930.5 | C22: =SUMIFS('Transaction Details 2025'!$E$8:$E$331,'Transaction Details 2025'!$J$8:$J$331,$A22,'Transaction Details 2025'!$I$8:$I$331,C$4) -> -1853.08 | D22: =SUMIFS('Transaction Details 2025'!$E$8:$E$331,'Transaction Details 2025'!$J$8:$J$331,$A22,'Transaction Details 2025'!$I$8:$I$331,D$4) -> -1982.28 | E22: =SUMIFS('Transaction Details 2025'!$E$8:$E$331,'Transaction Details 2025'!$J$8:$J$331,$A22,'Transaction Details 2025'!$I$8:$I$331,E$4) -> -2222.92 | F22: =SUMIFS('Transaction Details 2025'!$E$8:$E$331,'Transaction Details 2025'!$J$8:$J$331,$A22,'Transaction Details 2025'!$I$8:$I$331,F$4) -> -1542.61 | G22: =SUMIFS('Transaction Details 2025'!$E$8:$E$331,'Transaction Details 2025'!$J$8:$J$331,$A22,'Transaction Details 2025'!$I$8:$I$331,G$4) -> -12616.91 | H22: =SUMIFS('Transaction Details 2025'!$E$8:$E$331,'Transaction Details 2025'!$J$8:$J$331,$A22,'Transaction Details 2025'!$I$8:$I$331,H$4) -> -1373.57 | I22: =SUMIFS('Transaction Details 2025'!$E$8:$E$331,'Transaction Details 2025'!$J$8:$J$331,$A22,'Transaction Details 2025'!$I$8:$I$331,I$4) -> -1935.03 | ... M22: =SUMIFS('Transaction Details 2025'!$E$8:$E$331,'Transaction Details 2025'!$J$8:$J$331,$A22,'Transaction Details 2025'!$I$8:$I$331,M$4) -> -1625.86 | N22: =SUM(B22:M22) -> -33765.13
A24: Total Charges | B24: =SUMIFS('Transaction Details 2025'!$E$8:$E$331,'Transaction Details 2025'!$I$8:$I$331,B$4,'Transaction Details 2025'!$E$8:$E$331,">0") -> 5242.75 | C24: =SUMIFS('Transaction Details 2025'!$E$8:$E$331,'Transaction Details 2025'!$I$8:$I$331,C$4,'Transaction Details 2025'!$E$8:$E$331,">0") -> 2796.12 | D24: =SUMIFS('Transaction Details 2025'!$E$8:$E$331,'Transaction Details 2025'!$I$8:$I$331,D$4,'Transaction Details 2025'!$E$8:$E$331,">0") -> 2046.88 | E24: =SUMIFS('Transaction Details 2025'!$E$8:$E$331,'Transaction Details 2025'!$I$8:$I$331,E$4,'Transaction Details 2025'!$E$8:$E$331,">0") -> 2110.8 | F24: =SUMIFS('Transaction Details 2025'!$E$8:$E$331,'Transaction Details 2025'!$I$8:$I$331,F$4,'Transaction Details 2025'!$E$8:$E$331,">0") -> 12482.35 | G24: =SUMIFS('Transaction Details 2025'!$E$8:$E$331,'Transaction Details 2025'!$I$8:$I$331,G$4,'Transaction Details 2025'!$E$8:$E$331,">0") -> 1737.73 | H24: =SUMIFS('Transaction Details 2025'!$E$8:$E$331,'Transaction Details 2025'!$I$8:$I$331,H$4,'Transaction Details 2025'!$E$8:$E$331,">0") -> 1632.17 | I24: =SUMIFS('Transaction Details 2025'!$E$8:$E$331,'Transaction Details 2025'!$I$8:$I$331,I$4,'Transaction Details 2025'!$E$8:$E$331,">0") -> 1493.06 | ... M24: =SUMIFS('Transaction Details 2025'!$E$8:$E$331,'Transaction Details 2025'!$I$8:$I$331,M$4,'Transaction Details 2025'!$E$8:$E$331,">0") -> 1737.42 | N24: =SUM(B24:M24) -> 35067.32
A25: Total Credits & Payments | B25: =SUMIFS('Transaction Details 2025'!$E$8:$E$331,'Transaction Details 2025'!$I$8:$I$331,B$4,'Transaction Details 2025'!$E$8:$E$331,"<0") -> -5429.5 | C25: =SUMIFS('Transaction Details 2025'!$E$8:$E$331,'Transaction Details 2025'!$I$8:$I$331,C$4,'Transaction Details 2025'!$E$8:$E$331,"<0") -> -3171.33 | D25: =SUMIFS('Transaction Details 2025'!$E$8:$E$331,'Transaction Details 2025'!$I$8:$I$331,D$4,'Transaction Details 2025'!$E$8:$E$331,"<0") -> -2132.01 | E25: =SUMIFS('Transaction Details 2025'!$E$8:$E$331,'Transaction Details 2025'!$I$8:$I$331,E$4,'Transaction Details 2025'!$E$8:$E$331,"<0") -> -2241.85 | F25: =SUMIFS('Transaction Details 2025'!$E$8:$E$331,'Transaction Details 2025'!$I$8:$I$331,F$4,'Transaction Details 2025'!$E$8:$E$331,"<0") -> -1542.61 | G25: =SUMIFS('Transaction Details 2025'!$E$8:$E$331,'Transaction Details 2025'!$I$8:$I$331,G$4,'Transaction Details 2025'!$E$8:$E$331,"<0") -> -12616.91 | H25: =SUMIFS('Transaction Details 2025'!$E$8:$E$331,'Transaction Details 2025'!$I$8:$I$331,H$4,'Transaction Details 2025'!$E$8:$E$331,"<0") -> -1373.57 | I25: =SUMIFS('Transaction Details 2025'!$E$8:$E$331,'Transaction Details 2025'!$I$8:$I$331,I$4,'Transaction Details 2025'!$E$8:$E$331,"<0") -> -2055.22 | ... M25: =SUMIFS('Transaction Details 2025'!$E$8:$E$331,'Transaction Details 2025'!$I$8:$I$331,M$4,'Transaction Details 2025'!$E$8:$E$331,"<0") -> -1625.86 | N25: =SUM(B25:M25) -> -35902.93
A26: Net | B26: =B24+B25 -> -186.75 | C26: =C24+C25 -> -375.21 | D26: =D24+D25 -> -85.13 | E26: =E24+E25 -> -131.05 | F26: =F24+F25 -> 10939.74 | G26: =G24+G25 -> -10879.18 | H26: =H24+H25 -> 258.6 | I26: =I24+I25 -> -562.16 | ... M26: =M24+M25 -> 111.56 | N26: =SUM(B26:M26) -> -835.61
A28: =IF(ROUND(N26-'Transaction Summary 2025'!B11,2)=0,"✓ Net ties to Transaction Summary 2025","⚠ mismatch") -> ✓ Net ties to Transaction Summary 2025

Sheet Transaction Details 2025
A1: FAMILY AMEX | B1: Platinum Card® / Jan 01, 2025 to Dec 31, 2025
A2: Prepared for
A3: JOHN DUNNING
A4: Account Number
A5: XXXX-XXXXXX-43006
A7: Date | B7: Description | C7: Card Member | D7: Account # | E7: Amount | F7: Extended Details | G7: Appears On Your Statement As | H7: Category | I7: Month | J7: Category (clean)
A8: 12/30/2025 | B8: PAYPAL *CANVA 416131887 DE | C8: AVA PEREZ | D8: -46025 | E8: 15 | F8: 10199647970 416131887 PAYPAL *CANVA 416131887 DE Description : OEM SOFTWARE Price : 0.00 416131887 | G8: PAYPAL *CANVA 416131887 DE | H8: Merchandise & Supplies-Computer Supplies | I8: =DATE(RIGHT(A8,4)+0,LEFT(A8,2)+0,1) -> 45992 | J8: =IF(C8="JOHN DUNNING",IF(TRIM(H8)="",IF(ISNUMBER(SEARCH("PAYMENT",B8)),"Online AMEX Payment","(Uncategorized)"),TRIM(H8)),C8) -> AVA PEREZ
A9: 12/22/2025 | B9: PAYPAL *RESUME IO RE767110326 NL | C9: AVA PEREZ | D9: -46025 | E9: 26.86 | F9: 10199031816 767110326 19.95 UNITED KINGDOM POUND STERLING CONVE PAYPAL *RESUME IO RESUME. 767110326 NL Description : HIRING SERVICES Price : 0.00 767110326Foreign Spend Amount: 19.95 UNITED KINGDOM POUND STERLING Commission Amount: Currency Exchange Rate: null | G9: PAYPAL *RESUME IO RE767110326 NL | H9: Business Services-Employment Agencies | I9: =DATE(RIGHT(A9,4)+0,LEFT(A9,2)+0,1) -> 45992 | J9: =IF(C9="JOHN DUNNING",IF(TRIM(H9)="",IF(ISNUMBER(SEARCH("PAYMENT",B9)),"Online AMEX Payment","(Uncategorized)"),TRIM(H9)),C9) -> AVA PEREZ
A10: 12/21/2025 | B10: PAYPAL *PDFNET 4029357733 CA | C10: AVA PEREZ | D10: -46025 | E10: 1.95 | F10: 10198961903 4029357733 PAYPAL *PDFNET 4029357733 CA Description : DIGITAL APPLICATION Price : 0.00 4029357733 | G10: PAYPAL *PDFNET 4029357733 CA | H10: Merchandise & Supplies-Internet Purchase | I10: =DATE(RIGHT(A10,4)+0,LEFT(A10,2)+0,1) -> 45992 | J10: =IF(C10="JOHN DUNNING",IF(TRIM(H10)="",IF(ISNUMBER(SEARCH("PAYMENT",B10)),"Online AMEX Payment","(Uncategorized)"),TRIM(H10)),C10) -> AVA PEREZ
A11: 12/19/2025 | B11: ADOBE SYSTEMS Adobe SAN JOSE CA | C11: JOHN DUNNING | D11: -43006 | E11: 69.99 | F11: 538929008 www.adobe.com ADOBE SYSTEMS Adobe Systems SAN JOSE CA Description : DEFAULT Price : 0.6999 www.adobe.com | G11: ADOBE SYSTEMS Adobe SAN JOSE CA | H11: DWG-RE Platform (Redirected) | I11: =DATE(RIGHT(A11,4)+0,LEFT(A11,2)+0,1) -> 45992 | J11: =IF(C11="JOHN DUNNING",IF(TRIM(H11)="",IF(ISNUMBER(SEARCH("PAYMENT",B11)),"Online AMEX Payment","(Uncategorized)"),TRIM(H11)),C11) -> DWG-RE Platform (Redirected)
A12: 12/19/2025 | B12: MICROSOFT*MICROSOFT MSBILL.INFO WA | C12: JOHN DUNNING | D12: -43006 | E12: 12.99 | F12: Z72YHGRFAFM MSBILL.INFO MICROSOFT*MICROSOFT 365 F MSBILL.INFO WA MSBILL.INFO | G12: MICROSOFT*MICROSOFT MSBILL.INFO WA | H12: DWG-RE Platform (Redirected) | I12: =DATE(RIGHT(A12,4)+0,LEFT(A12,2)+0,1) -> 45992 | J12: =IF(C12="JOHN DUNNING",IF(TRIM(H12)="",IF(ISNUMBER(SEARCH("PAYMENT",B12)),"Online AMEX Payment","(Uncategorized)"),TRIM(H12)),C12) -> DWG-RE Platform (Redirected)
A13: 12/18/2025 | B13: ONLINE PAYMENT - THANK YOU | C13: JOHN DUNNING | D13: -43006 | E13: -1625.86 | F13: ONLINE PAYMENT - THANK YOU | G13: ONLINE PAYMENT - THANK YOU | H13: Online AMEX Payment | I13: =DATE(RIGHT(A13,4)+0,LEFT(A13,2)+0,1) -> 45992 | J13: =IF(C13="JOHN DUNNING",IF(TRIM(H13)="",IF(ISNUMBER(SEARCH("PAYMENT",B13)),"Online AMEX Payment","(Uncategorized)"),TRIM(H13)),C13) -> Online AMEX Payment
A14: 12/16/2025 | B14: LASTPASS.COM BOSTON MA | C14: JOHN DUNNING | D14: -43006 | E14: 48 | F14: 40466747QJ6 SAAS LASTPASS.COM BOSTON MA SAAS | G14: LASTPASS.COM BOSTON MA | H14: DWG-RE Platform (Canceled) | I14: =DATE(RIGHT(A14,4)+0,LEFT(A14,2)+0,1) -> 45992 | J14: =IF(C14="JOHN DUNNING",IF(TRIM(H14)="",IF(ISNUMBER(SEARCH("PAYMENT",B14)),"Online AMEX Payment","(Uncategorized)"),TRIM(H14)),C14) -> DWG-RE Platform (Canceled)
A15: 12/16/2025 | B15: NETFLIX.COM 866-579-7172 CA | C15: JOHN DUNNING | D15: -43006 | E15: 24.99 | F15: 57053627809 NETFLIX.COM NETFLIX.COM 866-579-7172 CA NETFLIX.COM | G15: NETFLIX.COM 866-579-7172 CA | H15: Family | I15: =DATE(RIGHT(A15,4)+0,LEFT(A15,2)+0,1) -> 45992 | J15: =IF(C15="JOHN DUNNING",IF(TRIM(H15)="",IF(ISNUMBER(SEARCH("PAYMENT",B15)),"Online AMEX Payment","(Uncategorized)"),TRIM(H15)),C15) -> Family
A16: 12/11/2025 | B16: PAYPAL *APPLE.COM/BI8002752273 CA | C16: AVA PEREZ | D16: -46025 | E16: 19.99 | F16: 10198043274 8002752273 PAYPAL *APPLE.COM/BILL 8002752273 CA Description : MUSIC Price : 0.00 8002752273 | G16: PAYPAL *APPLE.COM/BI8002752273 CA | H16: Merchandise & Supplies-Music & Video | I16: =DATE(RIGHT(A16,4)+0,LEFT(A16,2)+0,1) -> 45992 | J16: =IF(C16="JOHN DUNNING",IF(TRIM(H16)="",IF(ISNUMBER(SEARCH("PAYMENT",B16)),"Online AMEX Payment","(Uncategorized)"),TRIM(H16)),C16) -> AVA PEREZ
A17: 12/11/2025 | B17: PAYPAL *SOUNDLY 93294327 NO | C17: AVA PEREZ | D17: -46025 | E17: 14.99 | F17: 10198006277 93294327 PAYPAL *SOUNDLY 93294327 NO Description : DIGITAL APPLICATION Price : 0.00 93294327 | G17: PAYPAL *SOUNDLY 93294327 NO | H17: Business Services-Internet Services | I17: =DATE(RIGHT(A17,4)+0,LEFT(A17,2)+0,1) -> 45992 | J17: =IF(C17="JOHN DUNNING",IF(TRIM(H17)="",IF(ISNUMBER(SEARCH("PAYMENT",B17)),"Online AMEX Payment","(Uncategorized)"),TRIM(H17)),C17) -> AVA PEREZ
A18: 12/10/2025 | B18: PAYPAL *SPOTIFY*P3D42033189708 NY | C18: AVA PEREZ | D18: -46025 | E18: 11.99 | F18: 10197958977 2033189708 PAYPAL *SPOTIFY*P3D4B816E 2033189708 NY Description : GENERAL Price : 0.00 2033189708 | G18: PAYPAL *SPOTIFY*P3D42033189708 NY | H18: Communications-Other Telecom | I18: =DATE(RIGHT(A18,4)+0,LEFT(A18,2)+0,1) -> 45992 | J18: =IF(C18="JOHN DUNNING",IF(TRIM(H18)="",IF(ISNUMBER(SEARCH("PAYMENT",B18)),"Online AMEX Payment","(Uncategorized)"),TRIM(H18)),C18) -> AVA PEREZ
A19: 12/08/2025 | B19: PAYPAL *ETSY INC 4029357733 NY | C19: AVA PEREZ | D19: -46025 | E19: 131.7 | F19: 10197746553 4029357733 PAYPAL *ETSY INC 4029357733 NY Description : MISC. GENERAL MERCH Price : 0.00 4029357733 | G19: PAYPAL *ETSY INC 4029357733 NY | H19: Merchandise & Supplies-General Retail | I19: =DATE(RIGHT(A19,4)+0,LEFT(A19,2)+0,1) -> 45992 | J19: =IF(C19="JOHN DUNNING",IF(TRIM(H19)="",IF(ISNUMBER(SEARCH("PAYMENT",B19)),"Online AMEX Payment","(Uncategorized)"),TRIM(H19)),C19) -> AVA PEREZ
... A135: 07/19/2025 | B135: PAYPAL *ETSY INC 4029357733 NY | C135: AVA PEREZ | D135: -46025 | E135: 45.68 | F135: 10185688675 4029357733 PAYPAL *ETSY INC 4029357733 NY Description : MISC. GENERAL MERCH Price : 0.00 4029357733 | G135: PAYPAL *ETSY INC 4029357733 NY | H135: Merchandise & Supplies-General Retail | I135: =DATE(RIGHT(A135,4)+0,LEFT(A135,2)+0,1) -> 45839 | J135: =IF(C135="JOHN DUNNING",IF(TRIM(H135)="",IF(ISNUMBER(SEARCH("PAYMENT",B135)),"Online AMEX Payment","(Uncategorized)"),TRIM(H135)),C135) -> AVA PEREZ
A136: 07/17/2025 | B136: ONLINE PAYMENT - THANK YOU | C136: JOHN DUNNING | D136: -43006 | E136: -1373.57 | F136: ONLINE PAYMENT - THANK YOU | G136: ONLINE PAYMENT - THANK YOU | I136: =DATE(RIGHT(A136,4)+0,LEFT(A136,2)+0,1) -> 45839 | J136: =IF(C136="JOHN DUNNING",IF(TRIM(H136)="",IF(ISNUMBER(SEARCH("PAYMENT",B136)),"Online AMEX Payment","(Uncategorized)"),TRIM(H136)),C136) -> Online AMEX Payment
A137: 07/16/2025 | B137: NETFLIX.COM 866-579-7172 CA | C137: JOHN DUNNING | D137: -43006 | E137: 24.99 | F137: 50121674982 CABLE & PAY TV NETFLIX.COM 866-579-7172 CA CABLE & PAY TV | G137: NETFLIX.COM 866-579-7172 CA | H137: Family | I137: =DATE(RIGHT(A137,4)+0,LEFT(A137,2)+0,1) -> 45839 | J137: =IF(C137="JOHN DUNNING",IF(TRIM(H137)="",IF(ISNUMBER(SEARCH("PAYMENT",B137)),"Online AMEX Payment","(Uncategorized)"),TRIM(H137)),C137) -> Family
A138: 07/15/2025 | B138: PAYPAL *ETSY INC 4029357733 NY | C138: AVA PEREZ | D138: -46025 | E138: 15.33 | F138: 10185361380 4029357733 PAYPAL *ETSY INC 4029357733 NY Description : MISC. GENERAL MERCH Price : 0.00 4029357733 | G138: PAYPAL *ETSY INC 4029357733 NY | H138: Merchandise & Supplies-General Retail | I138: =DATE(RIGHT(A138,4)+0,LEFT(A138,2)+0,1) -> 45839 | J138: =IF(C138="JOHN DUNNING",IF(TRIM(H138)="",IF(ISNUMBER(SEARCH("PAYMENT",B138)),"Online AMEX Payment","(Uncategorized)"),TRIM(H138)),C138) -> AVA PEREZ
A139: 07/13/2025 | B139: PAYPAL *BLACKMOONCO 8182632784 CA | C139: AVA PEREZ | D139: -46025 | E139: 88.51 | F139: 10185171014 8182632784 PAYPAL *BLACKMOONCO 8182632784 CA Description : COSMETIC STORES Price : 0.00 8182632784 | G139: PAYPAL *BLACKMOONCO 8182632784 CA | H139: Merchandise & Supplies-Department Stores | I139: =DATE(RIGHT(A139,4)+0,LEFT(A139,2)+0,1) -> 45839 | J139: =IF(C139="JOHN DUNNING",IF(TRIM(H139)="",IF(ISNUMBER(SEARCH("PAYMENT",B139)),"Online AMEX Payment","(Uncategorized)"),TRIM(H139)),C139) -> AVA PEREZ
A140: 07/13/2025 | B140: PAYPAL *EBAY 800-4564029357733 CA | C140: AVA PEREZ | D140: -46025 | E140: 41.05 | F140: 10185175818 4029357733 PAYPAL *EBAY 800-456-3229 4029357733 CA Description : VARIETY STORE Price : 0.00 4029357733 | G140: PAYPAL *EBAY 800-4564029357733 CA | H140: Merchandise & Supplies-General Retail | I140: =DATE(RIGHT(A140,4)+0,LEFT(A140,2)+0,1) -> 45839 | J140: =IF(C140="JOHN DUNNING",IF(TRIM(H140)="",IF(ISNUMBER(SEARCH("PAYMENT",B140)),"Online AMEX Payment","(Uncategorized)"),TRIM(H140)),C140) -> AVA PEREZ
A141: 07/13/2025 | B141: PAYPAL *ETSY INC 4029357733 NY | C141: AVA PEREZ | D141: -46025 | E141: 27.9 | F141: 10185130567 4029357733 PAYPAL *ETSY INC 4029357733 NY Description : MISC. GENERAL MERCH Price : 0.00 4029357733 | G141: PAYPAL *ETSY INC 4029357733 NY | H141: Merchandise & Supplies-General Retail | I141: =DATE(RIGHT(A141,4)+0,LEFT(A141,2)+0,1) -> 45839 | J141: =IF(C141="JOHN DUNNING",IF(TRIM(H141)="",IF(ISNUMBER(SEARCH("PAYMENT",B141)),"Online AMEX Payment","(Uncategorized)"),TRIM(H141)),C141) -> AVA PEREZ
A142: 07/13/2025 | B142: PAYPAL *POSHMARK 6502624771 CA | C142: AVA PEREZ | D142: -46025 | E142: 30.1 | F142: 10185169366 6502624771 PAYPAL *POSHMARK 6502624771 CA Description : USED AND SECONDHAND Price : 0.00 6502624771 | G142: PAYPAL *POSHMARK 6502624771 CA | H142: Merchandise & Supplies-General Retail | I142: =DATE(RIGHT(A142,4)+0,LEFT(A142,2)+0,1) -> 45839 | J142: =IF(C142="JOHN DUNNING",IF(TRIM(H142)="",IF(ISNUMBER(SEARCH("PAYMENT",B142)),"Online AMEX Payment","(Uncategorized)"),TRIM(H142)),C142) -> AVA PEREZ
A143: 07/12/2025 | B143: GRAMMARLY.COM (888)3SAN FRANCISCO CA | C143: ANGELA L DUNNING | D143: -46017 | E143: 60 | F143: H6RGDBQ3 89825994 94104 GRAMMARLY.COM (888)318-6146 SAN FRANCISCO CA 89825994 94104 | G143: GRAMMARLY.COM (888)3SAN FRANCISCO CA | H143: Merchandise & Supplies-Internet Purchase | I143: =DATE(RIGHT(A143,4)+0,LEFT(A143,2)+0,1) -> 45839 | J143: =IF(C143="JOHN DUNNING",IF(TRIM(H143)="",IF(ISNUMBER(SEARCH("PAYMENT",B143)),"Online AMEX Payment","(Uncategorized)"),TRIM(H143)),C143) -> ANGELA L DUNNING
A144: 07/12/2025 | B144: PAYPAL *EBAY 800-4564029357733 CA | C144: AVA PEREZ | D144: -46025 | E144: 35.56 | F144: 10185064346 4029357733 PAYPAL *EBAY 800-456-3229 4029357733 CA Description : VARIETY STORE Price : 0.00 4029357733 | G144: PAYPAL *EBAY 800-4564029357733 CA | H144: Merchandise & Supplies-General Retail | I144: =DATE(RIGHT(A144,4)+0,LEFT(A144,2)+0,1) -> 45839 | J144: =IF(C144="JOHN DUNNING",IF(TRIM(H144)="",IF(ISNUMBER(SEARCH("PAYMENT",B144)),"Online AMEX Payment","(Uncategorized)"),TRIM(H144)),C144) -> AVA PEREZ
A145: 07/12/2025 | B145: PAYPAL *EBAY 800-4564029357733 CA | C145: AVA PEREZ | D145: -46025 | E145: 40.11 | F145: 10185127784 4029357733 PAYPAL *EBAY 800-456-3229 4029357733 CA Description : VARIETY STORE Price : 0.00 4029357733 | G145: PAYPAL *EBAY 800-4564029357733 CA | H145: Merchandise & Supplies-General Retail | I145: =DATE(RIGHT(A145,4)+0,LEFT(A145,2)+0,1) -> 45839 | J145: =IF(C145="JOHN DUNNING",IF(TRIM(H145)="",IF(ISNUMBER(SEARCH("PAYMENT",B145)),"Online AMEX Payment","(Uncategorized)"),TRIM(H145)),C145) -> AVA PEREZ
A146: 07/11/2025 | B146: PAYPAL *APPLE.COM/BI8002752273 CA | C146: AVA PEREZ | D146: -46025 | E146: 19.99 | F146: 10185020027 8002752273 PAYPAL *APPLE.COM/BILL 8002752273 CA Description : MUSIC Price : 0.00 8002752273 | G146: PAYPAL *APPLE.COM/BI8002752273 CA | H146: Merchandise & Supplies-Music & Video | I146: =DATE(RIGHT(A146,4)+0,LEFT(A146,2)+0,1) -> 45839 | J146: =IF(C146="JOHN DUNNING",IF(TRIM(H146)="",IF(ISNUMBER(SEARCH("PAYMENT",B146)),"Online AMEX Payment","(Uncategorized)"),TRIM(H146)),C146) -> AVA PEREZ
A147: 07/11/2025 | B147: PAYPAL *SOUNDLY 93294327 NO | C147: AVA PEREZ | D147: -46025 | E147: 14.99 | F147: 10184992038 93294327 PAYPAL *SOUNDLY 93294327 NO Description : DIGITAL APPLICATION Price : 0.00 93294327 | G147: PAYPAL *SOUNDLY 93294327 NO | H147: Business Services-Internet Services | I147: =DATE(RIGHT(A147,4)+0,LEFT(A147,2)+0,1) -> 45839 | J147: =IF(C147="JOHN DUNNING",IF(TRIM(H147)="",IF(ISNUMBER(SEARCH("PAYMENT",B147)),"Online AMEX Payment","(Uncategorized)"),TRIM(H147)),C147) -> AVA PEREZ
A148: 07/10/2025 | B148: PAYPAL *SPOTIFY*P3872033189708 NY | C148: AVA PEREZ | D148: -46025 | E148: 11.99 | F148: 10184952003 2033189708 PAYPAL *SPOTIFY*P38782D27 2033189708 NY Description : GENERAL Price : 0.00 2033189708 | G148: PAYPAL *SPOTIFY*P3872033189708 NY | H148: Communications-Other Telecom | I148: =DATE(RIGHT(A148,4)+0,LEFT(A148,2)+0,1) -> 45839 | J148: =IF(C148="JOHN DUNNING",IF(TRIM(H148)="",IF(ISNUMBER(SEARCH("PAYMENT",B148)),"Online AMEX Payment","(Uncategorized)"),TRIM(H148)),C148) -> AVA PEREZ
... A191: 05/27/2025 | B191: LIGHTBOX PARENT SHELTON CT | C191: JOHN DUNNING | D191: -43006 | E191: 11124 | F191: 49684083 855-337-5126 LIGHTBOX PARENT SHELTON CT Description : BUSINESS SERVICES Price : 0.00 855-337-5126 | G191: LIGHTBOX PARENT SHELTON CT | H191: DWG-RE Platform (Redirected) | I191: =DATE(RIGHT(A191,4)+0,LEFT(A191,2)+0,1) -> 45778 | J191: =IF(C191="JOHN DUNNING",IF(TRIM(H191)="",IF(ISNUMBER(SEARCH("PAYMENT",B191)),"Online AMEX Payment","(Uncategorized)"),TRIM(H191)),C191) -> DWG-RE Platform (Redirected)
A192: 05/26/2025 | B192: CUSTOMER SERVICE PAYMENT - THANK YOU | C192: JOHN DUNNING | D192: -43006 | E192: -1542.61 | F192: CUSTOMER SERVICE PAYMENT - THANK YOU | G192: CUSTOMER SERVICE PAYMENT - THANK YOU | I192: =DATE(RIGHT(A192,4)+0,LEFT(A192,2)+0,1) -> 45778 | J192: =IF(C192="JOHN DUNNING",IF(TRIM(H192)="",IF(ISNUMBER(SEARCH("PAYMENT",B192)),"Online AMEX Payment","(Uncategorized)"),TRIM(H192)),C192) -> Online AMEX Payment
A193: 05/20/2025 | B193: PAYPAL *APPLE.COM/BI8002752273 CA | C193: AVA PEREZ | D193: -46025 | E193: 2.99 | F193: 10180688282 8002752273 PAYPAL *APPLE.COM/BILL 8002752273 CA Description : MUSIC Price : 0.00 8002752273 | G193: PAYPAL *APPLE.COM/BI8002752273 CA | H193: Merchandise & Supplies-Music & Video | I193: =DATE(RIGHT(A193,4)+0,LEFT(A193,2)+0,1) -> 45778 | J193: =IF(C193="JOHN DUNNING",IF(TRIM(H193)="",IF(ISNUMBER(SEARCH("PAYMENT",B193)),"Online AMEX Payment","(Uncategorized)"),TRIM(H193)),C193) -> AVA PEREZ
A194: 05/19/2025 | B194: ADOBE SYSTEMS Adobe SAN JOSE CA | C194: JOHN DUNNING | D194: -43006 | E194: 59.99 | F194: 585723726 www.adobe.com ADOBE SYSTEMS Adobe Systems SAN JOSE CA Description : 0 Price : 0.5999 www.adobe.com | G194: ADOBE SYSTEMS Adobe SAN JOSE CA | H194: DWG-RE Platform (Redirected) | I194: =DATE(RIGHT(A194,4)+0,LEFT(A194,2)+0,1) -> 45778 | J194: =IF(C194="JOHN DUNNING",IF(TRIM(H194)="",IF(ISNUMBER(SEARCH("PAYMENT",B194)),"Online AMEX Payment","(Uncategorized)"),TRIM(H194)),C194) -> DWG-RE Platform (Redirected)
A195: 05/19/2025 | B195: MICROSOFT MSBILL.INFO | C195: JOHN DUNNING | D195: -43006 | E195: 12.99 | F195: Z72G47RMZ0TZ72G47RMZ0TL 98052 MICROSOFT MSBILL.INFO Z72G47RMZ0TL 98052 | G195: MICROSOFT MSBILL.INFO | H195: DWG-RE Platform (Redirected) | I195: =DATE(RIGHT(A195,4)+0,LEFT(A195,2)+0,1) -> 45778 | J195: =IF(C195="JOHN DUNNING",IF(TRIM(H195)="",IF(ISNUMBER(SEARCH("PAYMENT",B195)),"Online AMEX Payment","(Uncategorized)"),TRIM(H195)),C195) -> DWG-RE Platform (Redirected)
A196: 05/19/2025 | B196: PAYPAL *ETSY INC 4029357733 NY | C196: AVA PEREZ | D196: -46025 | E196: 142.68 | F196: 10180660397 4029357733 PAYPAL *ETSY INC 4029357733 NY Description : MISC. GENERAL MERCH Price : 0.00 4029357733 | G196: PAYPAL *ETSY INC 4029357733 NY | H196: Merchandise & Supplies-General Retail | I196: =DATE(RIGHT(A196,4)+0,LEFT(A196,2)+0,1) -> 45778 | J196: =IF(C196="JOHN DUNNING",IF(TRIM(H196)="",IF(ISNUMBER(SEARCH("PAYMENT",B196)),"Online AMEX Payment","(Uncategorized)"),TRIM(H196)),C196) -> AVA PEREZ
A197: 05/18/2025 | B197: PAYPAL *ETSY INC 4029357733 NY | C197: AVA PEREZ | D197: -46025 | E197: 67.77 | F197: 10180573566 4029357733 PAYPAL *ETSY INC 4029357733 NY Description : MISC. GENERAL MERCH Price : 0.00 4029357733 | G197: PAYPAL *ETSY INC 4029357733 NY | H197: Merchandise & Supplies-General Retail | I197: =DATE(RIGHT(A197,4)+0,LEFT(A197,2)+0,1) -> 45778 | J197: =IF(C197="JOHN DUNNING",IF(TRIM(H197)="",IF(ISNUMBER(SEARCH("PAYMENT",B197)),"Online AMEX Payment","(Uncategorized)"),TRIM(H197)),C197) -> AVA PEREZ
A198: 05/16/2025 | B198: NETFLIX.COM 866-579-7172 CA | C198: JOHN DUNNING | D198: -43006 | E198: 24.99 | F198: 47357647053 CABLE & PAY TV NETFLIX.COM 866-579-7172 CA CABLE & PAY TV | G198: NETFLIX.COM 866-579-7172 CA | H198: Family | I198: =DATE(RIGHT(A198,4)+0,LEFT(A198,2)+0,1) -> 45778 | J198: =IF(C198="JOHN DUNNING",IF(TRIM(H198)="",IF(ISNUMBER(SEARCH("PAYMENT",B198)),"Online AMEX Payment","(Uncategorized)"),TRIM(H198)),C198) -> Family
A199: 05/15/2025 | B199: PAYPAL *EBAY 800-4564029357733 CA | C199: AVA PEREZ | D199: -46025 | E199: 65.85 | F199: 10180342440 4029357733 PAYPAL *EBAY 800-456-3229 4029357733 CA Description : VARIETY STORE Price : 0.00 4029357733 | G199: PAYPAL *EBAY 800-4564029357733 CA | H199: Merchandise & Supplies-General Retail | I199: =DATE(RIGHT(A199,4)+0,LEFT(A199,2)+0,1) -> 45778 | J199: =IF(C199="JOHN DUNNING",IF(TRIM(H199)="",IF(ISNUMBER(SEARCH("PAYMENT",B199)),"Online AMEX Payment","(Uncategorized)"),TRIM(H199)),C199) -> AVA PEREZ
A200: 05/13/2025 | B200: PAYPAL *POSHMARK 6502624771 CA | C200: AVA PEREZ | D200: -46025 | E200: 30.22 | F200: 10180165121 6502624771 PAYPAL *POSHMARK 6502624771 CA Description : USED AND SECONDHAND Price : 0.00 6502624771 | G200: PAYPAL *POSHMARK 6502624771 CA | H200: Merchandise & Supplies-General Retail | I200: =DATE(RIGHT(A200,4)+0,LEFT(A200,2)+0,1) -> 45778 | J200: =IF(C200="JOHN DUNNING",IF(TRIM(H200)="",IF(ISNUMBER(SEARCH("PAYMENT",B200)),"Online AMEX Payment","(Uncategorized)"),TRIM(H200)),C200) -> AVA PEREZ
A201: 05/12/2025 | B201: PAYPAL *RESUME IO RE767110326 NL | C201: AVA PEREZ | D201: -46025 | E201: 26.52 | F201: 10180069756 767110326 19.95 UNITED KINGDOM POUND STERLING CONVE PAYPAL *RESUME IO RESUME. 767110326 NL Description : HIRING SERVICES Price : 0.00 767110326Foreign Spend Amount: 19.95 UNITED KINGDOM POUND STERLING Commission Amount: Currency Exchange Rate: null | G201: PAYPAL *RESUME IO RE767110326 NL | H201: Business Services-Employment Agencies | I201: =DATE(RIGHT(A201,4)+0,LEFT(A201,2)+0,1) -> 45778 | J201: =IF(C201="JOHN DUNNING",IF(TRIM(H201)="",IF(ISNUMBER(SEARCH("PAYMENT",B201)),"Online AMEX Payment","(Uncategorized)"),TRIM(H201)),C201) -> AVA PEREZ
A202: 05/11/2025 | B202: PAYPAL *APPLE.COM/BI8002752273 CA | C202: AVA PEREZ | D202: -46025 | E202: 19.99 | F202: 10179979441 8002752273 PAYPAL *APPLE.COM/BILL 8002752273 CA Description : MUSIC Price : 0.00 8002752273 | G202: PAYPAL *APPLE.COM/BI8002752273 CA | H202: Merchandise & Supplies-Music & Video | I202: =DATE(RIGHT(A202,4)+0,LEFT(A202,2)+0,1) -> 45778 | J202: =IF(C202="JOHN DUNNING",IF(TRIM(H202)="",IF(ISNUMBER(SEARCH("PAYMENT",B202)),"Online AMEX Payment","(Uncategorized)"),TRIM(H202)),C202) -> AVA PEREZ
A203: 05/11/2025 | B203: PAYPAL *SOUNDLY 93294327 NO | C203: AVA PEREZ | D203: -46025 | E203: 14.99 | F203: 10179954304 93294327 PAYPAL *SOUNDLY 93294327 NO Description : DIGITAL APPLICATION Price : 0.00 93294327 | G203: PAYPAL *SOUNDLY 93294327 NO | H203: Business Services-Internet Services | I203: =DATE(RIGHT(A203,4)+0,LEFT(A203,2)+0,1) -> 45778 | J203: =IF(C203="JOHN DUNNING",IF(TRIM(H203)="",IF(ISNUMBER(SEARCH("PAYMENT",B203)),"Online AMEX Payment","(Uncategorized)"),TRIM(H203)),C203) -> AVA PEREZ
A204: 05/10/2025 | B204: PAYPAL *P36AC36BF3 2033189708 NY | C204: AVA PEREZ | D204: -46025 | E204: 11.99 | F204: 10179920854 2033189708 PAYPAL *P36AC36BF3 2033189708 NY Description : GENERAL Price : 0.00 2033189708 | G204: PAYPAL *P36AC36BF3 2033189708 NY | H204: Communications-Other Telecom | I204: =DATE(RIGHT(A204,4)+0,LEFT(A204,2)+0,1) -> 45778 | J204: =IF(C204="JOHN DUNNING",IF(TRIM(H204)="",IF(ISNUMBER(SEARCH("PAYMENT",B204)),"Online AMEX Payment","(Uncategorized)"),TRIM(H204)),C204) -> AVA PEREZ
... A300: 01/30/2025 | B300: AMERICAN EXPRESS TVLPHOENIX AZ | C300: JOHN DUNNING | D300: -43006 | E300: 438.48 | F300: 020409 AIRLINE/AIR CARRIER PASSENGER TICKET AMERICAN EXPRESS TVL SVC PHOENIX AZ Carrier : AMERICAN AIRLINES Passenger Name : DUNNING/JOHN BARKER Ticket Number : 00171766397574 Departure Day : 02/05 Additional Info : PASSENGER TICKET From : LOS ANGELES INTERN To : DALLAS/FORT WORTH Class : M | G300: AMERICAN EXPRESS TVLPHOENIX AZ | H300: Travel-Airline | I300: =DATE(RIGHT(A300,4)+0,LEFT(A300,2)+0,1) -> 45658 | J300: =IF(C300="JOHN DUNNING",IF(TRIM(H300)="",IF(ISNUMBER(SEARCH("PAYMENT",B300)),"Online AMEX Payment","(Uncategorized)"),TRIM(H300)),C300) -> Travel-Airline
A301: 01/30/2025 | B301: CUSTOMER SERVICE PAYMENT - THANK YOU | C301: JOHN DUNNING | D301: -43006 | E301: -2465.25 | F301: CUSTOMER SERVICE PAYMENT - THANK YOU | G301: CUSTOMER SERVICE PAYMENT - THANK YOU | I301: =DATE(RIGHT(A301,4)+0,LEFT(A301,2)+0,1) -> 45658 | J301: =IF(C301="JOHN DUNNING",IF(TRIM(H301)="",IF(ISNUMBER(SEARCH("PAYMENT",B301)),"Online AMEX Payment","(Uncategorized)"),TRIM(H301)),C301) -> Online AMEX Payment
A302: 01/28/2025 | B302: ONLINE PAYMENT - THANK YOU | C302: JOHN DUNNING | D302: -43006 | E302: -2465.25 | F302: ONLINE PAYMENT - THANK YOU | G302: ONLINE PAYMENT - THANK YOU | I302: =DATE(RIGHT(A302,4)+0,LEFT(A302,2)+0,1) -> 45658 | J302: =IF(C302="JOHN DUNNING",IF(TRIM(H302)="",IF(ISNUMBER(SEARCH("PAYMENT",B302)),"Online AMEX Payment","(Uncategorized)"),TRIM(H302)),C302) -> Online AMEX Payment
A303: 01/28/2025 | B303: RETURNED CHECK/DECLIANK TRANSACTIONS | C303: JOHN DUNNING | D303: -43006 | E303: 2465.25 | F303: RETURNED CHECK/DECLINED BANK TRANSACTIONS ANK TRANSACTIONS | G303: RETURNED CHECK/DECLIANK TRANSACTIONS | H303: Fees & Adjustments-Fees & Adjustments | I303: =DATE(RIGHT(A303,4)+0,LEFT(A303,2)+0,1) -> 45658 | J303: =IF(C303="JOHN DUNNING",IF(TRIM(H303)="",IF(ISNUMBER(SEARCH("PAYMENT",B303)),"Online AMEX Payment","(Uncategorized)"),TRIM(H303)),C303) -> Fees & Adjustments-Fees & Adjustments
A304: 01/20/2025 | B304: AMAZON.COM AMZN.COM/BILL WA | C304: AVA PEREZ | D304: -46025 | E304: 85.16 | F304: 6MX2RQ6U94C MERCHANDISE AMAZON.COM AMZN.COM/BILL WA MERCHANDISE | G304: AMAZON.COM AMZN.COM/BILL WA | H304: Merchandise & Supplies-Internet Purchase | I304: =DATE(RIGHT(A304,4)+0,LEFT(A304,2)+0,1) -> 45658 | J304: =IF(C304="JOHN DUNNING",IF(TRIM(H304)="",IF(ISNUMBER(SEARCH("PAYMENT",B304)),"Online AMEX Payment","(Uncategorized)"),TRIM(H304)),C304) -> AVA PEREZ
A305: 01/20/2025 | B305: PAYPAL *APPLE.COM/BI8002752273 CA | C305: AVA PEREZ | D305: -46025 | E305: 2.99 | F305: 10170788307 8002752273 PAYPAL *APPLE.COM/BILL 8002752273 CA Description : MUSIC Price : 0.00 8002752273 | G305: PAYPAL *APPLE.COM/BI8002752273 CA | H305: Merchandise & Supplies-Music & Video | I305: =DATE(RIGHT(A305,4)+0,LEFT(A305,2)+0,1) -> 45658 | J305: =IF(C305="JOHN DUNNING",IF(TRIM(H305)="",IF(ISNUMBER(SEARCH("PAYMENT",B305)),"Online AMEX Payment","(Uncategorized)"),TRIM(H305)),C305) -> AVA PEREZ
A306: 01/20/2025 | B306: PAYPAL *RESUME IO 767110326 NL | C306: AVA PEREZ | D306: -46025 | E306: 24.57 | F306: 10170827290 767110326 19.95 UNITED KINGDOM POUND STERLING CONVE PAYPAL *RESUME IO 767110326 NL Description : HIRING SERVICES Price : 0.00 767110326Foreign Spend Amount: 19.95 UNITED KINGDOM POUND STERLING Commission Amount: Currency Exchange Rate: null | G306: PAYPAL *RESUME IO 767110326 NL | H306: Business Services-Employment Agencies | I306: =DATE(RIGHT(A306,4)+0,LEFT(A306,2)+0,1) -> 45658 | J306: =IF(C306="JOHN DUNNING",IF(TRIM(H306)="",IF(ISNUMBER(SEARCH("PAYMENT",B306)),"Online AMEX Payment","(Uncategorized)"),TRIM(H306)),C306) -> AVA PEREZ
A307: 01/19/2025 | B307: ADOBE SYSTEMS Adobe SAN JOSE CA | C307: JOHN DUNNING | D307: -43006 | E307: 59.99 | F307: 568974550 www.adobe.com ADOBE SYSTEMS Adobe Systems SAN JOSE CA Description : 0 Price : 0.5999 www.adobe.com | G307: ADOBE SYSTEMS Adobe SAN JOSE CA | H307: DWG-RE Platform (Redirected) | I307: =DATE(RIGHT(A307,4)+0,LEFT(A307,2)+0,1) -> 45658 | J307: =IF(C307="JOHN DUNNING",IF(TRIM(H307)="",IF(ISNUMBER(SEARCH("PAYMENT",B307)),"Online AMEX Payment","(Uncategorized)"),TRIM(H307)),C307) -> DWG-RE Platform (Redirected)
A308: 01/19/2025 | B308: AMAZON MARKEPLACE NA PA | C308: AVA PEREZ | D308: -46025 | E308: 17.47 | F308: 15NHB63ANAA MERCHANDISE AMAZON MARKETPLACE NA PA AMZN.COM/BILL WA MERCHANDISE | G308: AMAZON MARKETPLACE NAMZN.COM/BILL WA | H308: Merchandise & Supplies-Internet Purchase | I308: =DATE(RIGHT(A308,4)+0,LEFT(A308,2)+0,1) -> 45658 | J308: =IF(C308="JOHN DUNNING",IF(TRIM(H308)="",IF(ISNUMBER(SEARCH("PAYMENT",B308)),"Online AMEX Payment","(Uncategorized)"),TRIM(H308)),C308) -> AVA PEREZ
A309: 01/19/2025 | B309: AMAZON MARKEPLACE NA PA | C309: AVA PEREZ | D309: -46025 | E309: 18.2 | F309: Y5MYX4J7F4C MERCHANDISE AMAZON MARKETPLACE NA PA AMZN.COM/BILL WA MERCHANDISE | G309: AMAZON MARKETPLACE NAMZN.COM/BILL WA | H309: Merchandise & Supplies-Internet Purchase | I309: =DATE(RIGHT(A309,4)+0,LEFT(A309,2)+0,1) -> 45658 | J309: =IF(C309="JOHN DUNNING",IF(TRIM(H309)="",IF(ISNUMBER(SEARCH("PAYMENT",B309)),"Online AMEX Payment","(Uncategorized)"),TRIM(H309)),C309) -> AVA PEREZ
A310: 01/19/2025 | B310: MICROSOFT*MICROSOFT MSBILL.INFO WA | C310: JOHN DUNNING | D310: -43006 | E310: 9.99 | F310: Z62CWUOUNWNZ62CWUOUNWNI 90066- COMPUTER HRDWR/SFTWR MICROSOFT*MICROSOFT 365 F 0000 MSBILL.INFO WA COMPUTER HRDWR/SFTWR Z62CWUOUNWNI 90066- | G310: MICROSOFT*MICROSOFT MSBILL.INFO WA | H310: DWG-RE Platform (Redirected) | I310: =DATE(RIGHT(A310,4)+0,LEFT(A310,2)+0,1) -> 45658 | J310: =IF(C310="JOHN DUNNING",IF(TRIM(H310)="",IF(ISNUMBER(SEARCH("PAYMENT",B310)),"Online AMEX Payment","(Uncategorized)"),TRIM(H310)),C310) -> DWG-RE Platform (Redirected)
A311: 01/17/2025 | B311: AMERICAN EXPRESS COMNEW YORK | C311: JOHN DUNNING | D311: -43006 | E311: -300 | F311: Amex SoulBike Credit AMERICAN EXPRESS COMPANY NEW YORK Amex SoulBike Credit | G311: AMERICAN EXPRESS COMNEW YORK | H311: Business Services-Other Services | I311: =DATE(RIGHT(A311,4)+0,LEFT(A311,2)+0,1) -> 45658 | J311: =IF(C311="JOHN DUNNING",IF(TRIM(H311)="",IF(ISNUMBER(SEARCH("PAYMENT",B311)),"Online AMEX Payment","(Uncategorized)"),TRIM(H311)),C311) -> Business Services-Other Services
A312: 01/16/2025 | B312: NETFLIX.COM 866-579-7172 CA | C312: JOHN DUNNING | D312: -43006 | E312: 22.99 | F312: 41924808854 CABLE & PAY TV NETFLIX.COM 866-579-7172 CA CABLE & PAY TV | G312: NETFLIX.COM 866-579-7172 CA | H312: Family | I312: =DATE(RIGHT(A312,4)+0,LEFT(A312,2)+0,1) -> 45658 | J312: =IF(C312="JOHN DUNNING",IF(TRIM(H312)="",IF(ISNUMBER(SEARCH("PAYMENT",B312)),"Online AMEX Payment","(Uncategorized)"),TRIM(H312)),C312) -> Family
A313: 01/14/2025 | B313: ALANA'S COFFEE ROASTLos Angeles CA | C313: JOHN DUNNING | D313: -43006 | E313: 28.5 | F313: hcSUdjejQgm squareup.com/receipts ALANA'S COFFEE ROASTERS Los Angeles CA squareup.com/receipts | G313: ALANA'S COFFEE ROASTLos Angeles CA | H313: Personal - Health | I313: =DATE(RIGHT(A313,4)+0,LEFT(A313,2)+0,1) -> 45658 | J313: =IF(C313="JOHN DUNNING",IF(TRIM(H313)="",IF(ISNUMBER(SEARCH("PAYMENT",B313)),"Online AMEX Payment","(Uncategorized)"),TRIM(H313)),C313) -> Personal - Health
A314: 01/13/2025 | B314: DEPOP NEW YORK NY | C314: AVA PEREZ | D314: -46025 | E314: 18.01 | F314: NT_RAD4LWYQ +18449353879 DEPOP NEW YORK NY +18449353879 | G314: DEPOP NEW YORK NY | H314: Merchandise & Supplies-Clothing Stores | I314: =DATE(RIGHT(A314,4)+0,LEFT(A314,2)+0,1) -> 45658 | J314: =IF(C314="JOHN DUNNING",IF(TRIM(H314)="",IF(ISNUMBER(SEARCH("PAYMENT",B314)),"Online AMEX Payment","(Uncategorized)"),TRIM(H314)),C314) -> AVA PEREZ
... A331: 01/03/2025 | B331: RENEWAL MEMBERSHIP FEE | C331: AVA PEREZ | D331: -46025 | E331: 195 | F331: RENEWAL MEMBERSHIP FEE | G331: RENEWAL MEMBERSHIP FEE | H331: Fees & Adjustments-Fees & Adjustments | I331: =DATE(RIGHT(A331,4)+0,LEFT(A331,2)+0,1) -> 45658 | J331: =IF(C331="JOHN DUNNING",IF(TRIM(H331)="",IF(ISNUMBER(SEARCH("PAYMENT",B331)),"Online AMEX Payment","(Uncategorized)"),TRIM(H331)),C331) -> AVA PEREZ

Sheet Transaction Summary 2026
A1: FAMILY AMEX
A2: Amex Platinum | Statement Summary
A4: Account Holder | B4: John Dunning
A5: Account | B5: XXXX-XXXXXX-43006
A6: Statement Period | B6: January 2026 - June 2026
A8: TOTALS
A9: Charges | B9: =SUMIF('Transaction Details 2026'!$E$8:$E$170,">0") -> 10241.82
A10: Credits & Payments | B10: =SUMIF('Transaction Details 2026'!$E$8:$E$170,"<0") -> -7569.81
A11: Net Balance | B11: =B9+B10 -> 2672.01
A13: SPEND BY CATEGORY
A14: Category | B14: Amount | C14: % of Charges
A15: John — Business
A16: DWG-RE Platform (Redirected) | B16: =SUMIFS('Transaction Details 2026'!$E$8:$E$170,'Transaction Details 2026'!$J$8:$J$170,A16) -> 2860.29 | C16: =IFERROR(B16/$B$9,0) -> 0.27927556
A17: Sponsor Cloud | B17: =SUMIFS('Transaction Details 2026'!$E$8:$E$170,'Transaction Details 2026'!$J$8:$J$170,A17) -> 512.87 | C17: =IFERROR(B17/$B$9,0) -> 0.050076061
A18: Subtotal — John Business | B18: =SUM(B16:B17) -> 3373.16 | C18: =IFERROR(B18/$B$9,0) -> 0.32935162
A19: John — Personal / Other
A20: Family | B20: =SUMIFS('Transaction Details 2026'!$E$8:$E$170,'Transaction Details 2026'!$J$8:$J$170,A20) -> 126.95 | C20: =IFERROR(B20/$B$9,0) -> 0.012395258
A21: Personal - Health | B21: =SUMIFS('Transaction Details 2026'!$E$8:$E$170,'Transaction Details 2026'!$J$8:$J$170,A21) -> 827 | C21: =IFERROR(B21/$B$9,0) -> 0.080747367
A22: (Uncategorized) | B22: =SUMIFS('Transaction Details 2026'!$E$8:$E$170,'Transaction Details 2026'!$J$8:$J$170,A22) -> 54 | C22: =IFERROR(B22/$B$9,0) -> 0.0052725004
A23: Subtotal — John Personal | B23: =SUM(B20:B22) -> 1007.95 | C23: =IFERROR(B23/$B$9,0) -> 0.098415125
A24: Other Card Members
A25: Ava Perez | B25: =SUMIFS('Transaction Details 2026'!$E$8:$E$170,'Transaction Details 2026'!$J$8:$J$170,A25) -> 3694.8 | C25: =IFERROR(B25/$B$9,0) -> 0.36075619
A26: Joe Saunders | B26: =SUMIFS('Transaction Details 2026'!$E$8:$E$170,'Transaction Details 2026'!$J$8:$J$170,A26) -> 1976.47 | C26: =IFERROR(B26/$B$9,0) -> 0.19298035
A27: Angela L Dunning | B27: =SUMIFS('Transaction Details 2026'!$E$8:$E$170,'Transaction Details 2026'!$J$8:$J$170,A27) -> 120 | C27: =IFERROR(B27/$B$9,0) -> 0.011716668
A28: Subtotal — Card Members | B28: =SUM(B25:B27) -> 5791.27 | C28: =IFERROR(B28/$B$9,0) -> 0.56545321
A29: Credits & Payments
A30: Online AMEX Payment | B30: =SUMIFS('Transaction Details 2026'!$E$8:$E$170,'Transaction Details 2026'!$J$8:$J$170,A30) -> -7500.37 | C30: =IFERROR(B30/$B$9,0) -> -0.73232785
A31: Subtotal — Credits & Payments | B31: =SUM(B30:B30) -> -7500.37 | C31: =IFERROR(B31/$B$9,0) -> -0.73232785
A32: GRAND TOTAL | B32: =B18+B23+B28+B31 -> 2672.01 | C32: =IFERROR(B32/$B$9,0) -> 0.26089211
A34: SPEND BY MONTH
A35: Month | B35: Charges | C35: Credits | D35: Net
A36: =DATE(2026,1,1) -> 46023 | B36: =SUMIFS('Transaction Details 2026'!$E$8:$E$170,'Transaction Details 2026'!$I$8:$I$170,$A36,'Transaction Details 2026'!$E$8:$E$170,">0") -> 1418.07 | C36: =SUMIFS('Transaction Details 2026'!$E$8:$E$170,'Transaction Details 2026'!$I$8:$I$170,$A36,'Transaction Details 2026'!$E$8:$E$170,"<0") -> -321.79 | D36: =B36+C36 -> 1096.28
A37: =EDATE(A36,1) -> 46054 | B37: =SUMIFS('Transaction Details 2026'!$E$8:$E$170,'Transaction Details 2026'!$I$8:$I$170,$A37,'Transaction Details 2026'!$E$8:$E$170,">0") -> 898.94 | C37: =SUMIFS('Transaction Details 2026'!$E$8:$E$170,'Transaction Details 2026'!$I$8:$I$170,$A37,'Transaction Details 2026'!$E$8:$E$170,"<0") -> -2012.65 | D37: =B37+C37 -> -1113.71 | E37: Net
A38: =EDATE(A37,1) -> 46082 | B38: =SUMIFS('Transaction Details 2026'!$E$8:$E$170,'Transaction Details 2026'!$I$8:$I$170,$A38,'Transaction Details 2026'!$E$8:$E$170,">0") -> 1940.34 | C38: =SUMIFS('Transaction Details 2026'!$E$8:$E$170,'Transaction Details 2026'!$I$8:$I$170,$A38,'Transaction Details 2026'!$E$8:$E$170,"<0") -> -1775.69 | D38: =B38+C38 -> 164.65 | E38: =C38+D38 -> -1611.04
A39: =EDATE(A38,1) -> 46113 | B39: =SUMIFS('Transaction Details 2026'!$E$8:$E$170,'Transaction Details 2026'!$I$8:$I$170,$A39,'Transaction Details 2026'!$E$8:$E$170,">0") -> 3142.58 | C39: =SUMIFS('Transaction Details 2026'!$E$8:$E$170,'Transaction Details 2026'!$I$8:$I$170,$A39,'Transaction Details 2026'!$E$8:$E$170,"<0") -> -443.1 | D39: =B39+C39 -> 2699.48
A40: =EDATE(A39,1) -> 46143 | B40: =SUMIFS('Transaction Details 2026'!$E$8:$E$170,'Transaction Details 2026'!$I$8:$I$170,$A40,'Transaction Details 2026'!$E$8:$E$170,">0") -> 2248.19 | C40: =SUMIFS('Transaction Details 2026'!$E$8:$E$170,'Transaction Details 2026'!$I$8:$I$170,$A40,'Transaction Details 2026'!$E$8:$E$170,"<0") -> -3016.58 | D40: =B40+C40 -> -768.39
A41: =EDATE(A40,1) -> 46174 | B41: =SUMIFS('Transaction Details 2026'!$E$8:$E$170,'Transaction Details 2026'!$I$8:$I$170,$A41,'Transaction Details 2026'!$E$8:$E$170,">0") -> 593.7 | C41: =SUMIFS('Transaction Details 2026'!$E$8:$E$170,'Transaction Details 2026'!$I$8:$I$170,$A41,'Transaction Details 2026'!$E$8:$E$170,"<0") -> 0 | D41: =B41+C41 -> 593.7
A42: Total | B42: =SUM(B36:B41) -> 10241.82 | C42: =SUM(C36:C41) -> -7569.81 | D42: =SUM(D36:D41) -> 2672.01 | F42: =AVERAGE(B36:B41) -> 1706.97
B43: =EDATE(B42,1) -> 10272
A44: SPEND BY CARD MEMBER | B44: Total | C44: =SUM(C38:C43) -> -12805.18 | D44: =SUM(D38:D43) -> 5361.45 | E44: =SUM(E38:E43) -> -1611.04
A45: Card Member | B45: Charges | C45: Credits | D45: Net
A46: John Dunning | B46: =SUMIFS('Transaction Details 2026'!$E$8:$E$170,'Transaction Details 2026'!$C$8:$C$170,$A46,'Transaction Details 2026'!$E$8:$E$170,">0") -> 4381.11 | C46: =SUMIFS('Transaction Details 2026'!$E$8:$E$170,'Transaction Details 2026'!$C$8:$C$170,$A46,'Transaction Details 2026'!$E$8:$E$170,"<0") -> -7500.37 | D46: =B46+C46 -> -3119.26 | E46: =SUM(E40:E45) -> -1611.04
A47: Ava Perez | B47: =SUMIFS('Transaction Details 2026'!$E$8:$E$170,'Transaction Details 2026'!$C$8:$C$170,$A47,'Transaction Details 2026'!$E$8:$E$170,">0") -> 3708.68 | C47: =SUMIFS('Transaction Details 2026'!$E$8:$E$170,'Transaction Details 2026'!$C$8:$C$170,$A47,'Transaction Details 2026'!$E$8:$E$170,"<0") -> -13.88 | D47: =B47+C47 -> 3694.8 | E47: Net
A48: Joe Saunders | B48: =SUMIFS('Transaction Details 2026'!$E$8:$E$170,'Transaction Details 2026'!$C$8:$C$170,$A48,'Transaction Details 2026'!$E$8:$E$170,">0") -> 2032.03 | C48: =SUMIFS('Transaction Details 2026'!$E$8:$E$170,'Transaction Details 2026'!$C$8:$C$170,$A48,'Transaction Details 2026'!$E$8:$E$170,"<0") -> -55.56 | D48: =B48+C48 -> 1976.47 | E48: =C48+D48 -> 1920.91
A49: Angela L Dunning | B49: =SUMIFS('Transaction Details 2026'!$E$8:$E$170,'Transaction Details 2026'!$C$8:$C$170,$A49,'Transaction Details 2026'!$E$8:$E$170,">0") -> 120 | C49: =SUMIFS('Transaction Details 2026'!$E$8:$E$170,'Transaction Details 2026'!$C$8:$C$170,$A49,'Transaction Details 2026'!$E$8:$E$170,"<0") -> 0 | D49: =B49+C49 -> 120
A50: Total | B50: =SUM(B46:B49) -> 10241.82 | C50: =SUM(C46:C49) -> -7569.81 | D50: =SUM(D46:D49) -> 2672.01
A52: PAYMENTS, CREDITS & REFUNDS DETAIL
A53: Date | B53: Description | C53: Type | D53: Amount
A54: =DATE(2026,5,27) -> 46169 | B54: Online payment received | C54: Payment | D54: -2961.02
A55: =DATE(2026,2,24) -> 46077 | B55: Online payment received | C55: Payment | D55: -2012.65
A56: =DATE(2026,3,28) -> 46109 | B56: Online payment received | C56: Payment | D56: -1775.69
A57: =DATE(2026,4,27) -> 46139 | B57: Online payment received | C57: Payment | D57: -429.22
A58: =DATE(2026,1,27) -> 46049 | B58: Online payment received | C58: Payment | D58: -321.79
A59: =DATE(2026,5,12) -> 46154 | B59: QT 1876 — fuel refund | C59: Refund | D59: -55.56
A60: =DATE(2026,4,28) -> 46140 | B60: PayPal eBay — refund | C60: Refund | D60: -13.88
A61: Total Credits & Payments | D61: =SUM(D54:D60) -> -7569.81
B62: =IF(ROUND(D61-B10,2)=0,"✓ ties to Credits & Payments total","⚠ mismatch") -> ✓ ties to Credits & Payments total

Sheet Monthly Breakdown 2026
A1: FAMILY AMEX
A2: Amex Platinum | Monthly Breakdown
A4: Category | B4: =DATE(2026,1,1) -> 46023 | C4: =EDATE(B4,1) -> 46054 | D4: =EDATE(C4,1) -> 46082 | E4: =EDATE(D4,1) -> 46113 | F4: =EDATE(E4,1) -> 46143 | G4: =EDATE(F4,1) -> 46174 | H4: Total
A5: DWG-RE Platform (Redirected) | B5: =SUMIFS('Transaction Details 2026'!$E$8:$E$170,'Transaction Details 2026'!$J$8:$J$170,$A5,'Transaction Details 2026'!$I$8:$I$170,B$4) -> 373.38 | C5: =SUMIFS('Transaction Details 2026'!$E$8:$E$170,'Transaction Details 2026'!$J$8:$J$170,$A5,'Transaction Details 2026'!$I$8:$I$170,C$4) -> 373.38 | D5: =SUMIFS('Transaction Details 2026'!$E$8:$E$170,'Transaction Details 2026'!$J$8:$J$170,$A5,'Transaction Details 2026'!$I$8:$I$170,D$4) -> 373.38 | E5: =SUMIFS('Transaction Details 2026'!$E$8:$E$170,'Transaction Details 2026'!$J$8:$J$170,$A5,'Transaction Details 2026'!$I$8:$I$170,E$4) -> 1147.37 | F5: =SUMIFS('Transaction Details 2026'!$E$8:$E$170,'Transaction Details 2026'!$J$8:$J$170,$A5,'Transaction Details 2026'!$I$8:$I$170,F$4) -> 373.38 | G5: =SUMIFS('Transaction Details 2026'!$E$8:$E$170,'Transaction Details 2026'!$J$8:$J$170,$A5,'Transaction Details 2026'!$I$8:$I$170,G$4) -> 219.4 | H5: =SUM(B5:G5) -> 2860.29
A6: Sponsor Cloud | B6: =SUMIFS('Transaction Details 2026'!$E$8:$E$170,'Transaction Details 2026'!$J$8:$J$170,$A6,'Transaction Details 2026'!$I$8:$I$170,B$4) -> 0 | C6: =SUMIFS('Transaction Details 2026'!$E$8:$E$170,'Transaction Details 2026'!$J$8:$J$170,$A6,'Transaction Details 2026'!$I$8:$I$170,C$4) -> 0 | D6: =SUMIFS('Transaction Details 2026'!$E$8:$E$170,'Transaction Details 2026'!$J$8:$J$170,$A6,'Transaction Details 2026'!$I$8:$I$170,D$4) -> 0 | E6: =SUMIFS('Transaction Details 2026'!$E$8:$E$170,'Transaction Details 2026'!$J$8:$J$170,$A6,'Transaction Details 2026'!$I$8:$I$170,E$4) -> 423.49 | F6: =SUMIFS('Transaction Details 2026'!$E$8:$E$170,'Transaction Details 2026'!$J$8:$J$170,$A6,'Transaction Details 2026'!$I$8:$I$170,F$4) -> 89.38 | G6: =SUMIFS('Transaction Details 2026'!$E$8:$E$170,'Transaction Details 2026'!$J$8:$J$170,$A6,'Transaction Details 2026'!$I$8:$I$170,G$4) -> 0 | H6: =SUM(B6:G6) -> 512.87
A7: Family | B7: =SUMIFS('Transaction Details 2026'!$E$8:$E$170,'Transaction Details 2026'!$J$8:$J$170,$A7,'Transaction Details 2026'!$I$8:$I$170,B$4) -> 24.99 | C7: =SUMIFS('Transaction Details 2026'!$E$8:$E$170,'Transaction Details 2026'!$J$8:$J$170,$A7,'Transaction Details 2026'!$I$8:$I$170,C$4) -> 24.99 | D7: =SUMIFS('Transaction Details 2026'!$E$8:$E$170,'Transaction Details 2026'!$J$8:$J$170,$A7,'Transaction Details 2026'!$I$8:$I$170,D$4) -> 24.99 | E7: =SUMIFS('Transaction Details 2026'!$E$8:$E$170,'Transaction Details 2026'!$J$8:$J$170,$A7,'Transaction Details 2026'!$I$8:$I$170,E$4) -> 24.99 | F7: =SUMIFS('Transaction Details 2026'!$E$8:$E$170,'Transaction Details 2026'!$J$8:$J$170,$A7,'Transaction Details 2026'!$I$8:$I$170,F$4) -> 26.99 | G7: =SUMIFS('Transaction Details 2026'!$E$8:$E$170,'Transaction Details 2026'!$J$8:$J$170,$A7,'Transaction Details 2026'!$I$8:$I$170,G$4) -> 0 | H7: =SUM(B7:G7) -> 126.95
A8: Personal - Health | B8: =SUMIFS('Transaction Details 2026'!$E$8:$E$170,'Transaction Details 2026'!$J$8:$J$170,$A8,'Transaction Details 2026'!$I$8:$I$170,B$4) -> 0 | C8: =SUMIFS('Transaction Details 2026'!$E$8:$E$170,'Transaction Details 2026'!$J$8:$J$170,$A8,'Transaction Details 2026'!$I$8:$I$170,C$4) -> 0 | D8: =SUMIFS('Transaction Details 2026'!$E$8:$E$170,'Transaction Details 2026'!$J$8:$J$170,$A8,'Transaction Details 2026'!$I$8:$I$170,D$4) -> 230 | E8: =SUMIFS('Transaction Details 2026'!$E$8:$E$170,'Transaction Details 2026'!$J$8:$J$170,$A8,'Transaction Details 2026'!$I$8:$I$170,E$4) -> 199 | F8: =SUMIFS('Transaction Details 2026'!$E$8:$E$170,'Transaction Details 2026'!$J$8:$J$170,$A8,'Transaction Details 2026'!$I$8:$I$170,F$4) -> 398 | G8: =SUMIFS('Transaction Details 2026'!$E$8:$E$170,'Transaction Details 2026'!$J$8:$J$170,$A8,'Transaction Details 2026'!$I$8:$I$170,G$4) -> 0 | H8: =SUM(B8:G8) -> 827
A9: (Uncategorized) | B9: =SUMIFS('Transaction Details 2026'!$E$8:$E$170,'Transaction Details 2026'!$J$8:$J$170,$A9,'Transaction Details 2026'!$I$8:$I$170,B$4) -> 0 | C9: =SUMIFS('Transaction Details 2026'!$E$8:$E$170,'Transaction Details 2026'!$J$8:$J$170,$A9,'Transaction Details 2026'!$I$8:$I$170,C$4) -> 0 | D9: =SUMIFS('Transaction Details 2026'!$E$8:$E$170,'Transaction Details 2026'!$J$8:$J$170,$A9,'Transaction Details 2026'!$I$8:$I$170,D$4) -> 0 | E9: =SUMIFS('Transaction Details 2026'!$E$8:$E$170,'Transaction Details 2026'!$J$8:$J$170,$A9,'Transaction Details 2026'!$I$8:$I$170,E$4) -> 0 | F9: =SUMIFS('Transaction Details 2026'!$E$8:$E$170,'Transaction Details 2026'!$J$8:$J$170,$A9,'Transaction Details 2026'!$I$8:$I$170,F$4) -> 0 | G9: =SUMIFS('Transaction Details 2026'!$E$8:$E$170,'Transaction Details 2026'!$J$8:$J$170,$A9,'Transaction Details 2026'!$I$8:$I$170,G$4) -> 54 | H9: =SUM(B9:G9) -> 54
A10: Ava Perez | B10: =SUMIFS('Transaction Details 2026'!$E$8:$E$170,'Transaction Details 2026'!$J$8:$J$170,$A10,'Transaction Details 2026'!$I$8:$I$170,B$4) -> 959.7 | C10: =SUMIFS('Transaction Details 2026'!$E$8:$E$170,'Transaction Details 2026'!$J$8:$J$170,$A10,'Transaction Details 2026'!$I$8:$I$170,C$4) -> 500.57 | D10: =SUMIFS('Transaction Details 2026'!$E$8:$E$170,'Transaction Details 2026'!$J$8:$J$170,$A10,'Transaction Details 2026'!$I$8:$I$170,D$4) -> 1067.3 | E10: =SUMIFS('Transaction Details 2026'!$E$8:$E$170,'Transaction Details 2026'!$J$8:$J$170,$A10,'Transaction Details 2026'!$I$8:$I$170,E$4) -> 564.46 | F10: =SUMIFS('Transaction Details 2026'!$E$8:$E$170,'Transaction Details 2026'!$J$8:$J$170,$A10,'Transaction Details 2026'!$I$8:$I$170,F$4) -> 482.64 | G10: =SUMIFS('Transaction Details 2026'!$E$8:$E$170,'Transaction Details 2026'!$J$8:$J$170,$A10,'Transaction Details 2026'!$I$8:$I$170,G$4) -> 120.13 | H10: =SUM(B10:G10) -> 3694.8
A11: Joe Saunders | B11: =SUMIFS('Transaction Details 2026'!$E$8:$E$170,'Transaction Details 2026'!$J$8:$J$170,$A11,'Transaction Details 2026'!$I$8:$I$170,B$4) -> 0 | C11: =SUMIFS('Transaction Details 2026'!$E$8:$E$170,'Transaction Details 2026'!$J$8:$J$170,$A11,'Transaction Details 2026'!$I$8:$I$170,C$4) -> 0 | D11: =SUMIFS('Transaction Details 2026'!$E$8:$E$170,'Transaction Details 2026'!$J$8:$J$170,$A11,'Transaction Details 2026'!$I$8:$I$170,D$4) -> 244.67 | E11: =SUMIFS('Transaction Details 2026'!$E$8:$E$170,'Transaction Details 2026'!$J$8:$J$170,$A11,'Transaction Details 2026'!$I$8:$I$170,E$4) -> 709.39 | F11: =SUMIFS('Transaction Details 2026'!$E$8:$E$170,'Transaction Details 2026'!$J$8:$J$170,$A11,'Transaction Details 2026'!$I$8:$I$170,F$4) -> 822.24 | G11: =SUMIFS('Transaction Details 2026'!$E$8:$E$170,'Transaction Details 2026'!$J$8:$J$170,$A11,'Transaction Details 2026'!$I$8:$I$170,G$4) -> 200.17 | H11: =SUM(B11:G11) -> 1976.47
A12: Angela L Dunning | B12: =SUMIFS('Transaction Details 2026'!$E$8:$E$170,'Transaction Details 2026'!$J$8:$J$170,$A12,'Transaction Details 2026'!$I$8:$I$170,B$4) -> 60 | C12: =SUMIFS('Transaction Details 2026'!$E$8:$E$170,'Transaction Details 2026'!$J$8:$J$170,$A12,'Transaction Details 2026'!$I$8:$I$170,C$4) -> 0 | D12: =SUMIFS('Transaction Details 2026'!$E$8:$E$170,'Transaction Details 2026'!$J$8:$J$170,$A12,'Transaction Details 2026'!$I$8:$I$170,D$4) -> 0 | E12: =SUMIFS('Transaction Details 2026'!$E$8:$E$170,'Transaction Details 2026'!$J$8:$J$170,$A12,'Transaction Details 2026'!$I$8:$I$170,E$4) -> 60 | F12: =SUMIFS('Transaction Details 2026'!$E$8:$E$170,'Transaction Details 2026'!$J$8:$J$170,$A12,'Transaction Details 2026'!$I$8:$I$170,F$4) -> 0 | G12: =SUMIFS('Transaction Details 2026'!$E$8:$E$170,'Transaction Details 2026'!$J$8:$J$170,$A12,'Transaction Details 2026'!$I$8:$I$170,G$4) -> 0 | H12: =SUM(B12:G12) -> 120
A13: Online AMEX Payment | B13: =SUMIFS('Transaction Details 2026'!$E$8:$E$170,'Transaction Details 2026'!$J$8:$J$170,$A13,'Transaction Details 2026'!$I$8:$I$170,B$4) -> -321.79 | C13: =SUMIFS('Transaction Details 2026'!$E$8:$E$170,'Transaction Details 2026'!$J$8:$J$170,$A13,'Transaction Details 2026'!$I$8:$I$170,C$4) -> -2012.65 | D13: =SUMIFS('Transaction Details 2026'!$E$8:$E$170,'Transaction Details 2026'!$J$8:$J$170,$A13,'Transaction Details 2026'!$I$8:$I$170,D$4) -> -1775.69 | E13: =SUMIFS('Transaction Details 2026'!$E$8:$E$170,'Transaction Details 2026'!$J$8:$J$170,$A13,'Transaction Details 2026'!$I$8:$I$170,E$4) -> -429.22 | F13: =SUMIFS('Transaction Details 2026'!$E$8:$E$170,'Transaction Details 2026'!$J$8:$J$170,$A13,'Transaction Details 2026'!$I$8:$I$170,F$4) -> -2961.02 | G13: =SUMIFS('Transaction Details 2026'!$E$8:$E$170,'Transaction Details 2026'!$J$8:$J$170,$A13,'Transaction Details 2026'!$I$8:$I$170,G$4) -> 0 | H13: =SUM(B13:G13) -> -7500.37
A15: Total Charges | B15: =SUMIFS('Transaction Details 2026'!$E$8:$E$170,'Transaction Details 2026'!$I$8:$I$170,B$4,'Transaction Details 2026'!$E$8:$E$170,">0") -> 1418.07 | C15: =SUMIFS('Transaction Details 2026'!$E$8:$E$170,'Transaction Details 2026'!$I$8:$I$170,C$4,'Transaction Details 2026'!$E$8:$E$170,">0") -> 898.94 | D15: =SUMIFS('Transaction Details 2026'!$E$8:$E$170,'Transaction Details 2026'!$I$8:$I$170,D$4,'Transaction Details 2026'!$E$8:$E$170,">0") -> 1940.34 | E15: =SUMIFS('Transaction Details 2026'!$E$8:$E$170,'Transaction Details 2026'!$I$8:$I$170,E$4,'Transaction Details 2026'!$E$8:$E$170,">0") -> 3142.58 | F15: =SUMIFS('Transaction Details 2026'!$E$8:$E$170,'Transaction Details 2026'!$I$8:$I$170,F$4,'Transaction Details 2026'!$E$8:$E$170,">0") -> 2248.19 | G15: =SUMIFS('Transaction Details 2026'!$E$8:$E$170,'Transaction Details 2026'!$I$8:$I$170,G$4,'Transaction Details 2026'!$E$8:$E$170,">0") -> 593.7 | H15: =SUM(B15:G15) -> 10241.82
A16: Total Credits & Payments | B16: =SUMIFS('Transaction Details 2026'!$E$8:$E$170,'Transaction Details 2026'!$I$8:$I$170,B$4,'Transaction Details 2026'!$E$8:$E$170,"<0") -> -321.79 | C16: =SUMIFS('Transaction Details 2026'!$E$8:$E$170,'Transaction Details 2026'!$I$8:$I$170,C$4,'Transaction Details 2026'!$E$8:$E$170,"<0") -> -2012.65 | D16: =SUMIFS('Transaction Details 2026'!$E$8:$E$170,'Transaction Details 2026'!$I$8:$I$170,D$4,'Transaction Details 2026'!$E$8:$E$170,"<0") -> -1775.69 | E16: =SUMIFS('Transaction Details 2026'!$E$8:$E$170,'Transaction Details 2026'!$I$8:$I$170,E$4,'Transaction Details 2026'!$E$8:$E$170,"<0") -> -443.1 | F16: =SUMIFS('Transaction Details 2026'!$E$8:$E$170,'Transaction Details 2026'!$I$8:$I$170,F$4,'Transaction Details 2026'!$E$8:$E$170,"<0") -> -3016.58 | G16: =SUMIFS('Transaction Details 2026'!$E$8:$E$170,'Transaction Details 2026'!$I$8:$I$170,G$4,'Transaction Details 2026'!$E$8:$E$170,"<0") -> 0 | H16: =SUM(B16:G16) -> -7569.81
A17: Net | B17: =B15+B16 -> 1096.28 | C17: =C15+C16 -> -1113.71 | D17: =D15+D16 -> 164.65 | E17: =E15+E16 -> 2699.48 | F17: =F15+F16 -> -768.39 | G17: =G15+G16 -> 593.7 | H17: =SUM(B17:G17) -> 2672.01
A19: =IF(ROUND(H17-'Transaction Summary 2026'!B11,2)=0,"✓ Net ties to Transaction Summary","⚠ mismatch") -> ✓ Net ties to Transaction Summary

Sheet Transaction Details 2026
A1: FAMILY AMEX | B1: Platinum Card® / Jan 01, 2026 to Jun 11, 2026
A2: Prepared for
A3: JOHN DUNNING
A4: Account Number
A5: XXXX-XXXXXX-43006
A7: Date | B7: Description | C7: Card Member | D7: Account # | E7: Amount | F7: Extended Details | G7: Appears On Your Statement As | H7: Category | I7: Month | J7: Category (clean)
A8: 06/09/2026 | B8: GULF OIL 92069037 00KILGORE TX | C8: JOE SAUNDERS | D8: -41042 | E8: 68.75 | F8: 000021256 4302532656 GULF OIL 92069037 000000000303638 KILGORE TX 4302532656 | G8: GULF OIL 92069037 00KILGORE TX | H8: Transportation-Fuel | I8: =DATE(RIGHT(A8,4)+0,LEFT(A8,2)+0,1) -> 46174 | J8: =IF(C8="JOHN DUNNING",IF(TRIM(H8)="",IF(ISNUMBER(SEARCH("PAYMENT",B8)),"Online AMEX Payment","(Uncategorized)"),TRIM(H8)),C8) -> JOE SAUNDERS
A9: 06/08/2026 | B9: PAYPAL *EBAY 800-4564029357733 CA | C9: AVA PEREZ | D9: -46025 | E9: 60.46 | F9: 10212874238 4029357733 PAYPAL *EBAY 800-456-3229 4029357733 CA Description : VARIETY STORE Price : 0.00 4029357733 | G9: PAYPAL *EBAY 800-4564029357733 CA | H9: Merchandise & Supplies-General Retail | I9: =DATE(RIGHT(A9,4)+0,LEFT(A9,2)+0,1) -> 46174 | J9: =IF(C9="JOHN DUNNING",IF(TRIM(H9)="",IF(ISNUMBER(SEARCH("PAYMENT",B9)),"Online AMEX Payment","(Uncategorized)"),TRIM(H9)),C9) -> AVA PEREZ
A10: 06/08/2026 | B10: PAYPAL *RESUME IO RE767110326 NL | C10: AVA PEREZ | D10: -46025 | E10: 26.68 | F10: 10212852544 767110326 19.95 UNITED KINGDOM POUND STERLING CONVE PAYPAL *RESUME IO RESUME. 767110326 NL Description : HIRING SERVICES Price : 0.00 767110326Foreign Spend Amount: 19.95 UNITED KINGDOM POUND STERLING Commission Amount: Currency Exchange Rate: null | G10: PAYPAL *RESUME IO RE767110326 NL | H10: Business Services-Employment Agencies | I10: =DATE(RIGHT(A10,4)+0,LEFT(A10,2)+0,1) -> 46174 | J10: =IF(C10="JOHN DUNNING",IF(TRIM(H10)="",IF(ISNUMBER(SEARCH("PAYMENT",B10)),"Online AMEX Payment","(Uncategorized)"),TRIM(H10)),C10) -> AVA PEREZ
A11: 06/07/2026 | B11: REONOMY NEW YORK NY | C11: JOHN DUNNING | D11: -43006 | E11: 219.4 | F11: CH_3TFLNJBY 6468826260 REONOMY NEW YORK NY 6468826260 | G11: REONOMY NEW YORK NY | H11: DWG-RE Platform (Redirected) | I11: =DATE(RIGHT(A11,4)+0,LEFT(A11,2)+0,1) -> 46174 | J11: =IF(C11="JOHN DUNNING",IF(TRIM(H11)="",IF(ISNUMBER(SEARCH("PAYMENT",B11)),"Online AMEX Payment","(Uncategorized)"),TRIM(H11)),C11) -> DWG-RE Platform (Redirected)
A12: 06/07/2026 | B12: UBER | C12: JOE SAUNDERS | D12: -41042 | E12: 131.42 | F12: A1NZYSF7 ZUJUA3OZ 76087 Uber Trip help.uber.com CA ZUJUA3OZ 76087 | G12: Uber Trip help.uber.com CA | H12: Transportation-Taxis & Coach | I12: =DATE(RIGHT(A12,4)+0,LEFT(A12,2)+0,1) -> 46174 | J12: =IF(C12="JOHN DUNNING",IF(TRIM(H12)="",IF(ISNUMBER(SEARCH("PAYMENT",B12)),"Online AMEX Payment","(Uncategorized)"),TRIM(H12)),C12) -> JOE SAUNDERS
A13: 06/05/2026 | B13: DROPBOX*C66C1QMSG4PSSAN FRANCISCO CA | C13: JOHN DUNNING | D13: -43006 | E13: 54 | F13: CZYHK98K 662681638 94107 DROPBOX*C66C1QMSG4PS SAN FRANCISCO CA 662681638 94107 | G13: DROPBOX*C66C1QMSG4PSSAN FRANCISCO CA | I13: =DATE(RIGHT(A13,4)+0,LEFT(A13,2)+0,1) -> 46174 | J13: =IF(C13="JOHN DUNNING",IF(TRIM(H13)="",IF(ISNUMBER(SEARCH("PAYMENT",B13)),"Online AMEX Payment","(Uncategorized)"),TRIM(H13)),C13) -> (Uncategorized)
A14: 06/04/2026 | B14: PAYPAL *APPLE.COM/BI8002752273 CA | C14: AVA PEREZ | D14: -46025 | E14: 2.99 | F14: 10212494455 8002752273 PAYPAL *APPLE.COM/BILL 8002752273 CA Description : MUSIC Price : 0.00 8002752273 | G14: PAYPAL *APPLE.COM/BI8002752273 CA | H14: Merchandise & Supplies-Music & Video | I14: =DATE(RIGHT(A14,4)+0,LEFT(A14,2)+0,1) -> 46174 | J14: =IF(C14="JOHN DUNNING",IF(TRIM(H14)="",IF(ISNUMBER(SEARCH("PAYMENT",B14)),"Online AMEX Payment","(Uncategorized)"),TRIM(H14)),C14) -> AVA PEREZ
A15: 06/01/2026 | B15: PAYPAL *SANTA ANA H 4029357733 CA | C15: AVA PEREZ | D15: -46025 | E15: 30 | F15: 10212294280 4029357733 PAYPAL *SANTA ANA H SANTA ANA HPS 4029357733 CA Description : GENERAL Price : 0.00 4029357733 | G15: PAYPAL *SANTA ANA H 4029357733 CA | H15: Merchandise & Supplies-General Retail | I15: =DATE(RIGHT(A15,4)+0,LEFT(A15,2)+0,1) -> 46174 | J15: =IF(C15="JOHN DUNNING",IF(TRIM(H15)="",IF(ISNUMBER(SEARCH("PAYMENT",B15)),"Online AMEX Payment","(Uncategorized)"),TRIM(H15)),C15) -> AVA PEREZ
A16: 05/31/2026 | B16: SPONSORCLOUD (SYNPROSALT LAKE CITY UT | C16: JOHN DUNNING | D16: -43006 | E16: 89.38 | F16: CH_3TDJHMB7 +13854834872 SPONSORCLOUD (SYNPRO) SALT LAKE CITY UT +13854834872 | G16: SPONSORCLOUD (SYNPROSALT LAKE CITY UT | H16: Sponsor Cloud | I16: =DATE(RIGHT(A16,4)+0,LEFT(A16,2)+0,1) -> 46143 | J16: =IF(C16="JOHN DUNNING",IF(TRIM(H16)="",IF(ISNUMBER(SEARCH("PAYMENT",B16)),"Online AMEX Payment","(Uncategorized)"),TRIM(H16)),C16) -> Sponsor Cloud
A17: 05/28/2026 | B17: PAYPAL *CANVA 416131887 DE | C17: AVA PEREZ | D17: -46025 | E17: 15 | F17: 10211957063 416131887 PAYPAL *CANVA 416131887 DE Description : OEM SOFTWARE Price : 0.00 416131887 | G17: PAYPAL *CANVA 416131887 DE | H17: Merchandise & Supplies-Computer Supplies | I17: =DATE(RIGHT(A17,4)+0,LEFT(A17,2)+0,1) -> 46143 | J17: =IF(C17="JOHN DUNNING",IF(TRIM(H17)="",IF(ISNUMBER(SEARCH("PAYMENT",B17)),"Online AMEX Payment","(Uncategorized)"),TRIM(H17)),C17) -> AVA PEREZ
A18: 05/27/2026 | B18: ONLINE PAYMENT - THANK YOU | C18: JOHN DUNNING | D18: -43006 | E18: -2961.02 | F18: ONLINE PAYMENT - THANK YOU | G18: ONLINE PAYMENT - THANK YOU | H18: Online AMEX Payment | I18: =DATE(RIGHT(A18,4)+0,LEFT(A18,2)+0,1) -> 46143 | J18: =IF(C18="JOHN DUNNING",IF(TRIM(H18)="",IF(ISNUMBER(SEARCH("PAYMENT",B18)),"Online AMEX Payment","(Uncategorized)"),TRIM(H18)),C18) -> Online AMEX Payment
A19: 05/27/2026 | B19: PAYPAL *FANDANGO 8668575191 CA | C19: AVA PEREZ | D19: -46025 | E19: 35 | F19: 10211859468 8668575191 PAYPAL *FANDANGO 8668575191 CA Description : MOVIE TICKETS Price : 0.00 8668575191 | G19: PAYPAL *FANDANGO 8668575191 CA | H19: Entertainment-Theatrical Events | I19: =DATE(RIGHT(A19,4)+0,LEFT(A19,2)+0,1) -> 46143 | J19: =IF(C19="JOHN DUNNING",IF(TRIM(H19)="",IF(ISNUMBER(SEARCH("PAYMENT",B19)),"Online AMEX Payment","(Uncategorized)"),TRIM(H19)),C19) -> AVA PEREZ
A20: 05/23/2026 | B20: PAYPAL *LINKTREEINC 4029357733 DE | C20: AVA PEREZ | D20: -46025 | E20: 15 | F20: 10211499735 4029357733 PAYPAL *LINKTREEINC 4029357733 DE Description : DIGITAL APPLICATION Price : 0.00 4029357733 | G20: PAYPAL *LINKTREEINC 4029357733 DE | H20: Merchandise & Supplies-Internet Purchase | I20: =DATE(RIGHT(A20,4)+0,LEFT(A20,2)+0,1) -> 46143 | J20: =IF(C20="JOHN DUNNING",IF(TRIM(H20)="",IF(ISNUMBER(SEARCH("PAYMENT",B20)),"Online AMEX Payment","(Uncategorized)"),TRIM(H20)),C20) -> AVA PEREZ
A21: 05/20/2026 | B21: PAYPAL *EBAY 800-4564029357733 CA | C21: AVA PEREZ | D21: -46025 | E21: 43.98 | F21: 10211288540 4029357733 PAYPAL *EBAY 800-456-3229 4029357733 CA Description : VARIETY STORE Price : 0.00 4029357733 | G21: PAYPAL *EBAY 800-4564029357733 CA | H21: Merchandise & Supplies-General Retail | I21: =DATE(RIGHT(A21,4)+0,LEFT(A21,2)+0,1) -> 46143 | J21: =IF(C21="JOHN DUNNING",IF(TRIM(H21)="",IF(ISNUMBER(SEARCH("PAYMENT",B21)),"Online AMEX Payment","(Uncategorized)"),TRIM(H21)),C21) -> AVA PEREZ
A22: 05/20/2026 | B22: PAYPAL *UBER 8665761039 CA | C22: AVA PEREZ | D22: -46025 | E22: 20 | F22: 10211271379 8665761039 PAYPAL *UBER 8665761039 CA Description : TAXICABS AND LIMOUS Price : 0.00 8665761039 | G22: PAYPAL *UBER 8665761039 CA | H22: Transportation-Taxis & Coach | I22: =DATE(RIGHT(A22,4)+0,LEFT(A22,2)+0,1) -> 46143 | J22: =IF(C22="JOHN DUNNING",IF(TRIM(H22)="",IF(ISNUMBER(SEARCH("PAYMENT",B22)),"Online AMEX Payment","(Uncategorized)"),TRIM(H22)),C22) -> AVA PEREZ
A23: 05/20/2026 | B23: PAYPAL *UBER 8665761039 CA | C23: AVA PEREZ | D23: -46025 | E23: 54.28 | F23: 10211269338 8665761039 PAYPAL *UBER 8665761039 CA Description : TAXICABS AND LIMOUS Price : 0.00 8665761039 | G23: PAYPAL *UBER 8665761039 CA | H23: Transportation-Taxis & Coach | I23: =DATE(RIGHT(A23,4)+0,LEFT(A23,2)+0,1) -> 46143 | J23: =IF(C23="JOHN DUNNING",IF(TRIM(H23)="",IF(ISNUMBER(SEARCH("PAYMENT",B23)),"Online AMEX Payment","(Uncategorized)"),TRIM(H23)),C23) -> AVA PEREZ
A24: 05/20/2026 | B24: UBER | C24: JOE SAUNDERS | D24: -41042 | E24: 11.69 | F24: 3Y1ZAKYG S4IOZO5T 75261 Uber Trip help.uber.com CA S4IOZO5T 75261 | G24: Uber Trip help.uber.com CA | H24: Transportation-Taxis & Coach | I24: =DATE(RIGHT(A24,4)+0,LEFT(A24,2)+0,1) -> 46143 | J24: =IF(C24="JOHN DUNNING",IF(TRIM(H24)="",IF(ISNUMBER(SEARCH("PAYMENT",B24)),"Online AMEX Payment","(Uncategorized)"),TRIM(H24)),C24) -> JOE SAUNDERS
A25: 05/20/2026 | B25: UBER | C25: JOE SAUNDERS | D25: -41042 | E25: 77.95 | F25: A74PCAMR S4IOZO5T 75261 Uber Trip help.uber.com CA S4IOZO5T 75261 | G25: Uber Trip help.uber.com CA | H25: Transportation-Taxis & Coach | I25: =DATE(RIGHT(A25,4)+0,LEFT(A25,2)+0,1) -> 46143 | J25: =IF(C25="JOHN DUNNING",IF(TRIM(H25)="",IF(ISNUMBER(SEARCH("PAYMENT",B25)),"Online AMEX Payment","(Uncategorized)"),TRIM(H25)),C25) -> JOE SAUNDERS
... A170: 01/01/2026 | B170: AMAZON MARKEPLACE NA PA | C170: AVA PEREZ | D170: -46025 | E170: 276.56 | F170: 6ALZG54IT7M MERCHANDISE AMAZON MARKETPLACE NA PA AMZN.COM/BILL WA MERCHANDISE | G170: AMAZON MARKETPLACE NAMZN.COM/BILL WA | H170: Merchandise & Supplies-Internet Purchase | I170: =DATE(RIGHT(A170,4)+0,LEFT(A170,2)+0,1) -> 46023 | J170: =IF(C170="JOHN DUNNING",IF(TRIM(H170)="",IF(ISNUMBER(SEARCH("PAYMENT",B170)),"Online AMEX Payment","(Uncategorized)"),TRIM(H170)),C170) -> AVA PEREZ
