Workbook

Sheet Transaction Summary
A1: American Express — The Platinum Card
A2: The Platinum Card® | Statement Summary
A4: Account Holder | B4: John L Dunning
A5: Account | B5: XXXX-XXXXXX-27001
A6: Statement Period | B6: Jan 2025 – Present (through Jun 2026)
A8: TOTALS
A9: Charges | B9: ='Transaction Details'!D207 -> 18556.54
A10: Credits & Payments | B10: ='Transaction Details'!D208 -> -18560.46
A11: Net Balance | B11: =B9+B10 -> -3.92
A13: SPEND BY CATEGORY
A14: Category | B14: Amount | C14: % of Charges
A15: Business / DWG
A16: DWG - Costar Billing | B16: =SUMIFS('Transaction Details'!D:D,'Transaction Details'!C:C,A16) -> 4623.59 | C16: =IFERROR(B16/$B$9,0) -> 0.24916229
A17: E&O Insurance Payment | B17: =SUMIFS('Transaction Details'!D:D,'Transaction Details'!C:C,A17) -> 2788.42 | C17: =IFERROR(B17/$B$9,0) -> 0.15026616
A18: Bridge Loan - JC Whitner | B18: =SUMIFS('Transaction Details'!D:D,'Transaction Details'!C:C,A18) -> 3000 | C18: =IFERROR(B18/$B$9,0) -> 0.16166807
A19: Subtotal — Business | B19: =SUM(B16:B18) -> 10412.01 | C19: =IFERROR(B19/$B$9,0) -> 0.56109652
A21: Card Fees & Interest
A22: RENEWAL MEMBERSHIP FEE | B22: =SUMIFS('Transaction Details'!D:D,'Transaction Details'!C:C,A22) -> 1590 | C22: =IFERROR(B22/$B$9,0) -> 0.085684077
A23: LATE FEE | B23: =SUMIFS('Transaction Details'!D:D,'Transaction Details'!C:C,A23) -> 160 | C23: =IFERROR(B23/$B$9,0) -> 0.008622297
A24: Interest Charge on Pay Over Time Purchases | B24: =SUMIFS('Transaction Details'!D:D,'Transaction Details'!C:C,A24) -> 244 | C24: =IFERROR(B24/$B$9,0) -> 0.013149003
A25: Subtotal — Fees & Interest | B25: =SUM(B22:B24) -> 1994 | C25: =IFERROR(B25/$B$9,0) -> 0.10745538
A27: Personal
A28: Personal - Amazon | B28: =SUMIFS('Transaction Details'!D:D,'Transaction Details'!C:C,A28) -> 2539.83 | C28: =IFERROR(B28/$B$9,0) -> 0.1368698
A29: Personal - Food | B29: =SUMIFS('Transaction Details'!D:D,'Transaction Details'!C:C,A29) -> 679.12 | C29: =IFERROR(B29/$B$9,0) -> 0.03659734
A30: Personal - Health | B30: =SUMIFS('Transaction Details'!D:D,'Transaction Details'!C:C,A30) -> 334.58 | C30: =IFERROR(B30/$B$9,0) -> 0.018030301
A31: Personal - Car | B31: =SUMIFS('Transaction Details'!D:D,'Transaction Details'!C:C,A31) -> 9.88 | C31: =IFERROR(B31/$B$9,0) -> 0.00053242684
A32: Personal - House | B32: =SUMIFS('Transaction Details'!D:D,'Transaction Details'!C:C,A32) -> 2587.12 | C32: =IFERROR(B32/$B$9,0) -> 0.13941823
A33: Subtotal — Personal | B33: =SUM(B28:B32) -> 6150.53 | C33: =IFERROR(B33/$B$9,0) -> 0.3314481
A35: TOTAL CHARGES | B35: =B19+B25+B33 -> 18556.54 | C35: =IFERROR(B35/$B$9,0) -> 1

Sheet Monthly Breakdown
A1: American Express — The Platinum Card
A2: The Platinum Card® | Monthly Breakdown
A4: Period | B4: Jan 2025 - Dec 2025
B5: 2025 | N5: 2026
A6: Category | B6: =DATE(2025,1,1) -> 45658 | C6: =EDATE(B6,1) -> 45689 | D6: =EDATE(C6,1) -> 45717 | E6: =EDATE(D6,1) -> 45748 | F6: =EDATE(E6,1) -> 45778 | G6: =EDATE(F6,1) -> 45809 | H6: =EDATE(G6,1) -> 45839 | I6: =EDATE(H6,1) -> 45870 | J6: =EDATE(I6,1) -> 45901 | ... S6: =EDATE(R6,1) -> 46174 | T6: Total
A7: DWG - Costar Billing | B7: =SUMIFS('Transaction Details'!$D:$D,'Transaction Details'!$C:$C,$A7,'Transaction Details'!$A:$A,">="&B$6,'Transaction Details'!$A:$A,"<"&EDATE(B$6,1)) -> 0 | C7: =SUMIFS('Transaction Details'!$D:$D,'Transaction Details'!$C:$C,$A7,'Transaction Details'!$A:$A,">="&C$6,'Transaction Details'!$A:$A,"<"&EDATE(C$6,1)) -> 0 | D7: =SUMIFS('Transaction Details'!$D:$D,'Transaction Details'!$C:$C,$A7,'Transaction Details'!$A:$A,">="&D$6,'Transaction Details'!$A:$A,"<"&EDATE(D$6,1)) -> 0 | E7: =SUMIFS('Transaction Details'!$D:$D,'Transaction Details'!$C:$C,$A7,'Transaction Details'!$A:$A,">="&E$6,'Transaction Details'!$A:$A,"<"&EDATE(E$6,1)) -> 0 | F7: =SUMIFS('Transaction Details'!$D:$D,'Transaction Details'!$C:$C,$A7,'Transaction Details'!$A:$A,">="&F$6,'Transaction Details'!$A:$A,"<"&EDATE(F$6,1)) -> 0 | G7: =SUMIFS('Transaction Details'!$D:$D,'Transaction Details'!$C:$C,$A7,'Transaction Details'!$A:$A,">="&G$6,'Transaction Details'!$A:$A,"<"&EDATE(G$6,1)) -> 4623.59 | H7: =SUMIFS('Transaction Details'!$D:$D,'Transaction Details'!$C:$C,$A7,'Transaction Details'!$A:$A,">="&H$6,'Transaction Details'!$A:$A,"<"&EDATE(H$6,1)) -> 0 | I7: =SUMIFS('Transaction Details'!$D:$D,'Transaction Details'!$C:$C,$A7,'Transaction Details'!$A:$A,">="&I$6,'Transaction Details'!$A:$A,"<"&EDATE(I$6,1)) -> 0 | ... S7: =SUMIFS('Transaction Details'!$D:$D,'Transaction Details'!$C:$C,$A7,'Transaction Details'!$A:$A,">="&S$6,'Transaction Details'!$A:$A,"<"&EDATE(S$6,1)) -> 0 | T7: =SUM(B7:S7) -> 4623.59
A8: E&O Insurance Payment | B8: =SUMIFS('Transaction Details'!$D:$D,'Transaction Details'!$C:$C,$A8,'Transaction Details'!$A:$A,">="&B$6,'Transaction Details'!$A:$A,"<"&EDATE(B$6,1)) -> 0 | C8: =SUMIFS('Transaction Details'!$D:$D,'Transaction Details'!$C:$C,$A8,'Transaction Details'!$A:$A,">="&C$6,'Transaction Details'!$A:$A,"<"&EDATE(C$6,1)) -> 0 | D8: =SUMIFS('Transaction Details'!$D:$D,'Transaction Details'!$C:$C,$A8,'Transaction Details'!$A:$A,">="&D$6,'Transaction Details'!$A:$A,"<"&EDATE(D$6,1)) -> 0 | E8: =SUMIFS('Transaction Details'!$D:$D,'Transaction Details'!$C:$C,$A8,'Transaction Details'!$A:$A,">="&E$6,'Transaction Details'!$A:$A,"<"&EDATE(E$6,1)) -> 0 | F8: =SUMIFS('Transaction Details'!$D:$D,'Transaction Details'!$C:$C,$A8,'Transaction Details'!$A:$A,">="&F$6,'Transaction Details'!$A:$A,"<"&EDATE(F$6,1)) -> 0 | G8: =SUMIFS('Transaction Details'!$D:$D,'Transaction Details'!$C:$C,$A8,'Transaction Details'!$A:$A,">="&G$6,'Transaction Details'!$A:$A,"<"&EDATE(G$6,1)) -> 2788.42 | H8: =SUMIFS('Transaction Details'!$D:$D,'Transaction Details'!$C:$C,$A8,'Transaction Details'!$A:$A,">="&H$6,'Transaction Details'!$A:$A,"<"&EDATE(H$6,1)) -> 0 | I8: =SUMIFS('Transaction Details'!$D:$D,'Transaction Details'!$C:$C,$A8,'Transaction Details'!$A:$A,">="&I$6,'Transaction Details'!$A:$A,"<"&EDATE(I$6,1)) -> 0 | ... S8: =SUMIFS('Transaction Details'!$D:$D,'Transaction Details'!$C:$C,$A8,'Transaction Details'!$A:$A,">="&S$6,'Transaction Details'!$A:$A,"<"&EDATE(S$6,1)) -> 0 | T8: =SUM(B8:S8) -> 2788.42
A9: Bridge Loan - JC Whitner | B9: =SUMIFS('Transaction Details'!$D:$D,'Transaction Details'!$C:$C,$A9,'Transaction Details'!$A:$A,">="&B$6,'Transaction Details'!$A:$A,"<"&EDATE(B$6,1)) -> 0 | C9: =SUMIFS('Transaction Details'!$D:$D,'Transaction Details'!$C:$C,$A9,'Transaction Details'!$A:$A,">="&C$6,'Transaction Details'!$A:$A,"<"&EDATE(C$6,1)) -> 0 | D9: =SUMIFS('Transaction Details'!$D:$D,'Transaction Details'!$C:$C,$A9,'Transaction Details'!$A:$A,">="&D$6,'Transaction Details'!$A:$A,"<"&EDATE(D$6,1)) -> 0 | E9: =SUMIFS('Transaction Details'!$D:$D,'Transaction Details'!$C:$C,$A9,'Transaction Details'!$A:$A,">="&E$6,'Transaction Details'!$A:$A,"<"&EDATE(E$6,1)) -> 0 | F9: =SUMIFS('Transaction Details'!$D:$D,'Transaction Details'!$C:$C,$A9,'Transaction Details'!$A:$A,">="&F$6,'Transaction Details'!$A:$A,"<"&EDATE(F$6,1)) -> 0 | G9: =SUMIFS('Transaction Details'!$D:$D,'Transaction Details'!$C:$C,$A9,'Transaction Details'!$A:$A,">="&G$6,'Transaction Details'!$A:$A,"<"&EDATE(G$6,1)) -> 0 | H9: =SUMIFS('Transaction Details'!$D:$D,'Transaction Details'!$C:$C,$A9,'Transaction Details'!$A:$A,">="&H$6,'Transaction Details'!$A:$A,"<"&EDATE(H$6,1)) -> 0 | I9: =SUMIFS('Transaction Details'!$D:$D,'Transaction Details'!$C:$C,$A9,'Transaction Details'!$A:$A,">="&I$6,'Transaction Details'!$A:$A,"<"&EDATE(I$6,1)) -> 0 | ... S9: =SUMIFS('Transaction Details'!$D:$D,'Transaction Details'!$C:$C,$A9,'Transaction Details'!$A:$A,">="&S$6,'Transaction Details'!$A:$A,"<"&EDATE(S$6,1)) -> 0 | T9: =SUM(B9:S9) -> 3000
A10: RENEWAL MEMBERSHIP FEE | B10: =SUMIFS('Transaction Details'!$D:$D,'Transaction Details'!$C:$C,$A10,'Transaction Details'!$A:$A,">="&B$6,'Transaction Details'!$A:$A,"<"&EDATE(B$6,1)) -> 0 | C10: =SUMIFS('Transaction Details'!$D:$D,'Transaction Details'!$C:$C,$A10,'Transaction Details'!$A:$A,">="&C$6,'Transaction Details'!$A:$A,"<"&EDATE(C$6,1)) -> 0 | D10: =SUMIFS('Transaction Details'!$D:$D,'Transaction Details'!$C:$C,$A10,'Transaction Details'!$A:$A,">="&D$6,'Transaction Details'!$A:$A,"<"&EDATE(D$6,1)) -> 695 | E10: =SUMIFS('Transaction Details'!$D:$D,'Transaction Details'!$C:$C,$A10,'Transaction Details'!$A:$A,">="&E$6,'Transaction Details'!$A:$A,"<"&EDATE(E$6,1)) -> 0 | F10: =SUMIFS('Transaction Details'!$D:$D,'Transaction Details'!$C:$C,$A10,'Transaction Details'!$A:$A,">="&F$6,'Transaction Details'!$A:$A,"<"&EDATE(F$6,1)) -> 0 | G10: =SUMIFS('Transaction Details'!$D:$D,'Transaction Details'!$C:$C,$A10,'Transaction Details'!$A:$A,">="&G$6,'Transaction Details'!$A:$A,"<"&EDATE(G$6,1)) -> 0 | H10: =SUMIFS('Transaction Details'!$D:$D,'Transaction Details'!$C:$C,$A10,'Transaction Details'!$A:$A,">="&H$6,'Transaction Details'!$A:$A,"<"&EDATE(H$6,1)) -> 0 | I10: =SUMIFS('Transaction Details'!$D:$D,'Transaction Details'!$C:$C,$A10,'Transaction Details'!$A:$A,">="&I$6,'Transaction Details'!$A:$A,"<"&EDATE(I$6,1)) -> 0 | ... S10: =SUMIFS('Transaction Details'!$D:$D,'Transaction Details'!$C:$C,$A10,'Transaction Details'!$A:$A,">="&S$6,'Transaction Details'!$A:$A,"<"&EDATE(S$6,1)) -> 0 | T10: =SUM(B10:S10) -> 1590
A11: LATE FEE | B11: =SUMIFS('Transaction Details'!$D:$D,'Transaction Details'!$C:$C,$A11,'Transaction Details'!$A:$A,">="&B$6,'Transaction Details'!$A:$A,"<"&EDATE(B$6,1)) -> 40 | C11: =SUMIFS('Transaction Details'!$D:$D,'Transaction Details'!$C:$C,$A11,'Transaction Details'!$A:$A,">="&C$6,'Transaction Details'!$A:$A,"<"&EDATE(C$6,1)) -> 0 | D11: =SUMIFS('Transaction Details'!$D:$D,'Transaction Details'!$C:$C,$A11,'Transaction Details'!$A:$A,">="&D$6,'Transaction Details'!$A:$A,"<"&EDATE(D$6,1)) -> 40 | E11: =SUMIFS('Transaction Details'!$D:$D,'Transaction Details'!$C:$C,$A11,'Transaction Details'!$A:$A,">="&E$6,'Transaction Details'!$A:$A,"<"&EDATE(E$6,1)) -> 0 | F11: =SUMIFS('Transaction Details'!$D:$D,'Transaction Details'!$C:$C,$A11,'Transaction Details'!$A:$A,">="&F$6,'Transaction Details'!$A:$A,"<"&EDATE(F$6,1)) -> 40 | G11: =SUMIFS('Transaction Details'!$D:$D,'Transaction Details'!$C:$C,$A11,'Transaction Details'!$A:$A,">="&G$6,'Transaction Details'!$A:$A,"<"&EDATE(G$6,1)) -> 0 | H11: =SUMIFS('Transaction Details'!$D:$D,'Transaction Details'!$C:$C,$A11,'Transaction Details'!$A:$A,">="&H$6,'Transaction Details'!$A:$A,"<"&EDATE(H$6,1)) -> 40 | I11: =SUMIFS('Transaction Details'!$D:$D,'Transaction Details'!$C:$C,$A11,'Transaction Details'!$A:$A,">="&I$6,'Transaction Details'!$A:$A,"<"&EDATE(I$6,1)) -> 0 | ... S11: =SUMIFS('Transaction Details'!$D:$D,'Transaction Details'!$C:$C,$A11,'Transaction Details'!$A:$A,">="&S$6,'Transaction Details'!$A:$A,"<"&EDATE(S$6,1)) -> 0 | T11: =SUM(B11:S11) -> 160
A12: Interest Charge on Pay Over Time Purchases | B12: =SUMIFS('Transaction Details'!$D:$D,'Transaction Details'!$C:$C,$A12,'Transaction Details'!$A:$A,">="&B$6,'Transaction Details'!$A:$A,"<"&EDATE(B$6,1)) -> 0 | C12: =SUMIFS('Transaction Details'!$D:$D,'Transaction Details'!$C:$C,$A12,'Transaction Details'!$A:$A,">="&C$6,'Transaction Details'!$A:$A,"<"&EDATE(C$6,1)) -> 0 | D12: =SUMIFS('Transaction Details'!$D:$D,'Transaction Details'!$C:$C,$A12,'Transaction Details'!$A:$A,">="&D$6,'Transaction Details'!$A:$A,"<"&EDATE(D$6,1)) -> 0 | E12: =SUMIFS('Transaction Details'!$D:$D,'Transaction Details'!$C:$C,$A12,'Transaction Details'!$A:$A,">="&E$6,'Transaction Details'!$A:$A,"<"&EDATE(E$6,1)) -> 15.95 | F12: =SUMIFS('Transaction Details'!$D:$D,'Transaction Details'!$C:$C,$A12,'Transaction Details'!$A:$A,">="&F$6,'Transaction Details'!$A:$A,"<"&EDATE(F$6,1)) -> 3.13 | G12: =SUMIFS('Transaction Details'!$D:$D,'Transaction Details'!$C:$C,$A12,'Transaction Details'!$A:$A,">="&G$6,'Transaction Details'!$A:$A,"<"&EDATE(G$6,1)) -> 0.82 | H12: =SUMIFS('Transaction Details'!$D:$D,'Transaction Details'!$C:$C,$A12,'Transaction Details'!$A:$A,">="&H$6,'Transaction Details'!$A:$A,"<"&EDATE(H$6,1)) -> 0.15 | I12: =SUMIFS('Transaction Details'!$D:$D,'Transaction Details'!$C:$C,$A12,'Transaction Details'!$A:$A,">="&I$6,'Transaction Details'!$A:$A,"<"&EDATE(I$6,1)) -> 118.17 | ... S12: =SUMIFS('Transaction Details'!$D:$D,'Transaction Details'!$C:$C,$A12,'Transaction Details'!$A:$A,">="&S$6,'Transaction Details'!$A:$A,"<"&EDATE(S$6,1)) -> 0 | T12: =SUM(B12:S12) -> 244
A13: Personal - Amazon | B13: =SUMIFS('Transaction Details'!$D:$D,'Transaction Details'!$C:$C,$A13,'Transaction Details'!$A:$A,">="&B$6,'Transaction Details'!$A:$A,"<"&EDATE(B$6,1)) -> 83.34 | C13: =SUMIFS('Transaction Details'!$D:$D,'Transaction Details'!$C:$C,$A13,'Transaction Details'!$A:$A,">="&C$6,'Transaction Details'!$A:$A,"<"&EDATE(C$6,1)) -> 84.34 | D13: =SUMIFS('Transaction Details'!$D:$D,'Transaction Details'!$C:$C,$A13,'Transaction Details'!$A:$A,">="&D$6,'Transaction Details'!$A:$A,"<"&EDATE(D$6,1)) -> 87.33 | E13: =SUMIFS('Transaction Details'!$D:$D,'Transaction Details'!$C:$C,$A13,'Transaction Details'!$A:$A,">="&E$6,'Transaction Details'!$A:$A,"<"&EDATE(E$6,1)) -> 80.38 | F13: =SUMIFS('Transaction Details'!$D:$D,'Transaction Details'!$C:$C,$A13,'Transaction Details'!$A:$A,">="&F$6,'Transaction Details'!$A:$A,"<"&EDATE(F$6,1)) -> 87.37 | G13: =SUMIFS('Transaction Details'!$D:$D,'Transaction Details'!$C:$C,$A13,'Transaction Details'!$A:$A,">="&G$6,'Transaction Details'!$A:$A,"<"&EDATE(G$6,1)) -> 87.37 | H13: =SUMIFS('Transaction Details'!$D:$D,'Transaction Details'!$C:$C,$A13,'Transaction Details'!$A:$A,">="&H$6,'Transaction Details'!$A:$A,"<"&EDATE(H$6,1)) -> 87.37 | I13: =SUMIFS('Transaction Details'!$D:$D,'Transaction Details'!$C:$C,$A13,'Transaction Details'!$A:$A,">="&I$6,'Transaction Details'!$A:$A,"<"&EDATE(I$6,1)) -> 74.38 | ... S13: =SUMIFS('Transaction Details'!$D:$D,'Transaction Details'!$C:$C,$A13,'Transaction Details'!$A:$A,">="&S$6,'Transaction Details'!$A:$A,"<"&EDATE(S$6,1)) -> 0 | T13: =SUM(B13:S13) -> 2539.83
A14: Personal - Food | B14: =SUMIFS('Transaction Details'!$D:$D,'Transaction Details'!$C:$C,$A14,'Transaction Details'!$A:$A,">="&B$6,'Transaction Details'!$A:$A,"<"&EDATE(B$6,1)) -> 0 | C14: =SUMIFS('Transaction Details'!$D:$D,'Transaction Details'!$C:$C,$A14,'Transaction Details'!$A:$A,">="&C$6,'Transaction Details'!$A:$A,"<"&EDATE(C$6,1)) -> 0 | D14: =SUMIFS('Transaction Details'!$D:$D,'Transaction Details'!$C:$C,$A14,'Transaction Details'!$A:$A,">="&D$6,'Transaction Details'!$A:$A,"<"&EDATE(D$6,1)) -> 0 | E14: =SUMIFS('Transaction Details'!$D:$D,'Transaction Details'!$C:$C,$A14,'Transaction Details'!$A:$A,">="&E$6,'Transaction Details'!$A:$A,"<"&EDATE(E$6,1)) -> 0 | F14: =SUMIFS('Transaction Details'!$D:$D,'Transaction Details'!$C:$C,$A14,'Transaction Details'!$A:$A,">="&F$6,'Transaction Details'!$A:$A,"<"&EDATE(F$6,1)) -> 0 | G14: =SUMIFS('Transaction Details'!$D:$D,'Transaction Details'!$C:$C,$A14,'Transaction Details'!$A:$A,">="&G$6,'Transaction Details'!$A:$A,"<"&EDATE(G$6,1)) -> 0 | H14: =SUMIFS('Transaction Details'!$D:$D,'Transaction Details'!$C:$C,$A14,'Transaction Details'!$A:$A,">="&H$6,'Transaction Details'!$A:$A,"<"&EDATE(H$6,1)) -> 0 | I14: =SUMIFS('Transaction Details'!$D:$D,'Transaction Details'!$C:$C,$A14,'Transaction Details'!$A:$A,">="&I$6,'Transaction Details'!$A:$A,"<"&EDATE(I$6,1)) -> 0 | ... S14: =SUMIFS('Transaction Details'!$D:$D,'Transaction Details'!$C:$C,$A14,'Transaction Details'!$A:$A,">="&S$6,'Transaction Details'!$A:$A,"<"&EDATE(S$6,1)) -> 0 | T14: =SUM(B14:S14) -> 679.12
A15: Personal - Health | B15: =SUMIFS('Transaction Details'!$D:$D,'Transaction Details'!$C:$C,$A15,'Transaction Details'!$A:$A,">="&B$6,'Transaction Details'!$A:$A,"<"&EDATE(B$6,1)) -> 0 | C15: =SUMIFS('Transaction Details'!$D:$D,'Transaction Details'!$C:$C,$A15,'Transaction Details'!$A:$A,">="&C$6,'Transaction Details'!$A:$A,"<"&EDATE(C$6,1)) -> 0 | D15: =SUMIFS('Transaction Details'!$D:$D,'Transaction Details'!$C:$C,$A15,'Transaction Details'!$A:$A,">="&D$6,'Transaction Details'!$A:$A,"<"&EDATE(D$6,1)) -> 0 | E15: =SUMIFS('Transaction Details'!$D:$D,'Transaction Details'!$C:$C,$A15,'Transaction Details'!$A:$A,">="&E$6,'Transaction Details'!$A:$A,"<"&EDATE(E$6,1)) -> 0 | F15: =SUMIFS('Transaction Details'!$D:$D,'Transaction Details'!$C:$C,$A15,'Transaction Details'!$A:$A,">="&F$6,'Transaction Details'!$A:$A,"<"&EDATE(F$6,1)) -> 0 | G15: =SUMIFS('Transaction Details'!$D:$D,'Transaction Details'!$C:$C,$A15,'Transaction Details'!$A:$A,">="&G$6,'Transaction Details'!$A:$A,"<"&EDATE(G$6,1)) -> 0 | H15: =SUMIFS('Transaction Details'!$D:$D,'Transaction Details'!$C:$C,$A15,'Transaction Details'!$A:$A,">="&H$6,'Transaction Details'!$A:$A,"<"&EDATE(H$6,1)) -> 0 | I15: =SUMIFS('Transaction Details'!$D:$D,'Transaction Details'!$C:$C,$A15,'Transaction Details'!$A:$A,">="&I$6,'Transaction Details'!$A:$A,"<"&EDATE(I$6,1)) -> 0 | ... S15: =SUMIFS('Transaction Details'!$D:$D,'Transaction Details'!$C:$C,$A15,'Transaction Details'!$A:$A,">="&S$6,'Transaction Details'!$A:$A,"<"&EDATE(S$6,1)) -> 0 | T15: =SUM(B15:S15) -> 334.58
A16: Personal - Car | B16: =SUMIFS('Transaction Details'!$D:$D,'Transaction Details'!$C:$C,$A16,'Transaction Details'!$A:$A,">="&B$6,'Transaction Details'!$A:$A,"<"&EDATE(B$6,1)) -> 0 | C16: =SUMIFS('Transaction Details'!$D:$D,'Transaction Details'!$C:$C,$A16,'Transaction Details'!$A:$A,">="&C$6,'Transaction Details'!$A:$A,"<"&EDATE(C$6,1)) -> 0 | D16: =SUMIFS('Transaction Details'!$D:$D,'Transaction Details'!$C:$C,$A16,'Transaction Details'!$A:$A,">="&D$6,'Transaction Details'!$A:$A,"<"&EDATE(D$6,1)) -> 0 | E16: =SUMIFS('Transaction Details'!$D:$D,'Transaction Details'!$C:$C,$A16,'Transaction Details'!$A:$A,">="&E$6,'Transaction Details'!$A:$A,"<"&EDATE(E$6,1)) -> 0 | F16: =SUMIFS('Transaction Details'!$D:$D,'Transaction Details'!$C:$C,$A16,'Transaction Details'!$A:$A,">="&F$6,'Transaction Details'!$A:$A,"<"&EDATE(F$6,1)) -> 2.5 | G16: =SUMIFS('Transaction Details'!$D:$D,'Transaction Details'!$C:$C,$A16,'Transaction Details'!$A:$A,">="&G$6,'Transaction Details'!$A:$A,"<"&EDATE(G$6,1)) -> 0 | H16: =SUMIFS('Transaction Details'!$D:$D,'Transaction Details'!$C:$C,$A16,'Transaction Details'!$A:$A,">="&H$6,'Transaction Details'!$A:$A,"<"&EDATE(H$6,1)) -> 0 | I16: =SUMIFS('Transaction Details'!$D:$D,'Transaction Details'!$C:$C,$A16,'Transaction Details'!$A:$A,">="&I$6,'Transaction Details'!$A:$A,"<"&EDATE(I$6,1)) -> 0 | ... S16: =SUMIFS('Transaction Details'!$D:$D,'Transaction Details'!$C:$C,$A16,'Transaction Details'!$A:$A,">="&S$6,'Transaction Details'!$A:$A,"<"&EDATE(S$6,1)) -> 0 | T16: =SUM(B16:S16) -> 9.88
A17: Personal - House | B17: =SUMIFS('Transaction Details'!$D:$D,'Transaction Details'!$C:$C,$A17,'Transaction Details'!$A:$A,">="&B$6,'Transaction Details'!$A:$A,"<"&EDATE(B$6,1)) -> 0 | C17: =SUMIFS('Transaction Details'!$D:$D,'Transaction Details'!$C:$C,$A17,'Transaction Details'!$A:$A,">="&C$6,'Transaction Details'!$A:$A,"<"&EDATE(C$6,1)) -> 0 | D17: =SUMIFS('Transaction Details'!$D:$D,'Transaction Details'!$C:$C,$A17,'Transaction Details'!$A:$A,">="&D$6,'Transaction Details'!$A:$A,"<"&EDATE(D$6,1)) -> 0 | E17: =SUMIFS('Transaction Details'!$D:$D,'Transaction Details'!$C:$C,$A17,'Transaction Details'!$A:$A,">="&E$6,'Transaction Details'!$A:$A,"<"&EDATE(E$6,1)) -> 0 | F17: =SUMIFS('Transaction Details'!$D:$D,'Transaction Details'!$C:$C,$A17,'Transaction Details'!$A:$A,">="&F$6,'Transaction Details'!$A:$A,"<"&EDATE(F$6,1)) -> 0 | G17: =SUMIFS('Transaction Details'!$D:$D,'Transaction Details'!$C:$C,$A17,'Transaction Details'!$A:$A,">="&G$6,'Transaction Details'!$A:$A,"<"&EDATE(G$6,1)) -> 0 | H17: =SUMIFS('Transaction Details'!$D:$D,'Transaction Details'!$C:$C,$A17,'Transaction Details'!$A:$A,">="&H$6,'Transaction Details'!$A:$A,"<"&EDATE(H$6,1)) -> 0 | I17: =SUMIFS('Transaction Details'!$D:$D,'Transaction Details'!$C:$C,$A17,'Transaction Details'!$A:$A,">="&I$6,'Transaction Details'!$A:$A,"<"&EDATE(I$6,1)) -> 0 | ... S17: =SUMIFS('Transaction Details'!$D:$D,'Transaction Details'!$C:$C,$A17,'Transaction Details'!$A:$A,">="&S$6,'Transaction Details'!$A:$A,"<"&EDATE(S$6,1)) -> 0 | T17: =SUM(B17:S17) -> 2587.12
A18: Total Charges | B18: =SUMIFS('Transaction Details'!$D:$D,'Transaction Details'!$A:$A,">="&B$6,'Transaction Details'!$A:$A,"<"&EDATE(B$6,1),'Transaction Details'!$D:$D,">0") -> 123.34 | C18: =SUMIFS('Transaction Details'!$D:$D,'Transaction Details'!$A:$A,">="&C$6,'Transaction Details'!$A:$A,"<"&EDATE(C$6,1),'Transaction Details'!$D:$D,">0") -> 84.34 | D18: =SUMIFS('Transaction Details'!$D:$D,'Transaction Details'!$A:$A,">="&D$6,'Transaction Details'!$A:$A,"<"&EDATE(D$6,1),'Transaction Details'!$D:$D,">0") -> 822.33 | E18: =SUMIFS('Transaction Details'!$D:$D,'Transaction Details'!$A:$A,">="&E$6,'Transaction Details'!$A:$A,"<"&EDATE(E$6,1),'Transaction Details'!$D:$D,">0") -> 96.33 | F18: =SUMIFS('Transaction Details'!$D:$D,'Transaction Details'!$A:$A,">="&F$6,'Transaction Details'!$A:$A,"<"&EDATE(F$6,1),'Transaction Details'!$D:$D,">0") -> 133 | G18: =SUMIFS('Transaction Details'!$D:$D,'Transaction Details'!$A:$A,">="&G$6,'Transaction Details'!$A:$A,"<"&EDATE(G$6,1),'Transaction Details'!$D:$D,">0") -> 7500.2 | H18: =SUMIFS('Transaction Details'!$D:$D,'Transaction Details'!$A:$A,">="&H$6,'Transaction Details'!$A:$A,"<"&EDATE(H$6,1),'Transaction Details'!$D:$D,">0") -> 127.52 | I18: =SUMIFS('Transaction Details'!$D:$D,'Transaction Details'!$A:$A,">="&I$6,'Transaction Details'!$A:$A,"<"&EDATE(I$6,1),'Transaction Details'!$D:$D,">0") -> 192.55 | ... S18: =SUMIFS('Transaction Details'!$D:$D,'Transaction Details'!$A:$A,">="&S$6,'Transaction Details'!$A:$A,"<"&EDATE(S$6,1),'Transaction Details'!$D:$D,">0") -> 0 | T18: =SUM(B18:S18) -> 18556.54
A19: Credits & Payments | B19: =SUMIFS('Transaction Details'!$D:$D,'Transaction Details'!$A:$A,">="&B$6,'Transaction Details'!$A:$A,"<"&EDATE(B$6,1),'Transaction Details'!$D:$D,"<0") -> -142.32 | C19: =SUMIFS('Transaction Details'!$D:$D,'Transaction Details'!$A:$A,">="&C$6,'Transaction Details'!$A:$A,"<"&EDATE(C$6,1),'Transaction Details'!$D:$D,"<0") -> -74.35 | D19: =SUMIFS('Transaction Details'!$D:$D,'Transaction Details'!$A:$A,">="&D$6,'Transaction Details'!$A:$A,"<"&EDATE(D$6,1),'Transaction Details'!$D:$D,"<0") -> 0 | E19: =SUMIFS('Transaction Details'!$D:$D,'Transaction Details'!$A:$A,">="&E$6,'Transaction Details'!$A:$A,"<"&EDATE(E$6,1),'Transaction Details'!$D:$D,"<0") -> -918.66 | F19: =SUMIFS('Transaction Details'!$D:$D,'Transaction Details'!$A:$A,">="&F$6,'Transaction Details'!$A:$A,"<"&EDATE(F$6,1),'Transaction Details'!$D:$D,"<0") -> 0 | G19: =SUMIFS('Transaction Details'!$D:$D,'Transaction Details'!$A:$A,">="&G$6,'Transaction Details'!$A:$A,"<"&EDATE(G$6,1),'Transaction Details'!$D:$D,"<0") -> -3009.61 | H19: =SUMIFS('Transaction Details'!$D:$D,'Transaction Details'!$A:$A,">="&H$6,'Transaction Details'!$A:$A,"<"&EDATE(H$6,1),'Transaction Details'!$D:$D,"<0") -> 0 | I19: =SUMIFS('Transaction Details'!$D:$D,'Transaction Details'!$A:$A,">="&I$6,'Transaction Details'!$A:$A,"<"&EDATE(I$6,1),'Transaction Details'!$D:$D,"<0") -> -4915.7 | ... S19: =SUMIFS('Transaction Details'!$D:$D,'Transaction Details'!$A:$A,">="&S$6,'Transaction Details'!$A:$A,"<"&EDATE(S$6,1),'Transaction Details'!$D:$D,"<0") -> 0 | T19: =SUM(B19:S19) -> -18560.46
A20: Net | B20: =B18+B19 -> -18.98 | C20: =C18+C19 -> 9.99 | D20: =D18+D19 -> 822.33 | E20: =E18+E19 -> -822.33 | F20: =F18+F19 -> 133 | G20: =G18+G19 -> 4490.59 | H20: =H18+H19 -> 127.52 | I20: =I18+I19 -> -4723.15 | ... T20: =T18+T19 -> -3.92

Sheet Transaction Details
A1: American Express — The Platinum Card
A2: The Platinum Card® | Transaction Detail
A4: Account Holder | B4: John L Dunning
A5: Account | B5: XXXX-XXXXXX-27001
A6: Statement Period | B6: Jan 1, 2025 – Dec 31, 2025
A7: Entity | B7: John L Dunning
A9: Date | B9: Merchant | C9: Category | D9: Amount | E9: B/P | F9: Reimb. | G9: Notes
A10: =IF(ISNUMBER('2026_Transaction Details'!A8),'2026_Transaction Details'!A8,DATEVALUE('2026_Transaction Details'!A8)) -> 46169 | B10: ='2026_Transaction Details'!B8 -> AMAZON.COM AMZN.COM/BILL WA | C10: ='2026_Transaction Details'!H8 -> Personal - Amazon | D10: ='2026_Transaction Details'!E8 -> 35.04 | E10: =IF(LEFT('2026_Transaction Details'!H8,8)="Personal","P","B") -> P
A11: =IF(ISNUMBER('2026_Transaction Details'!A9),'2026_Transaction Details'!A9,DATEVALUE('2026_Transaction Details'!A9)) -> 46169 | B11: ='2026_Transaction Details'!B9 -> ONLINE PAYMENT - THANK YOU | C11: ='2026_Transaction Details'!H9 -> Online AMEX Payment | D11: ='2026_Transaction Details'!E9 -> -40.96 | E11: =IF(LEFT('2026_Transaction Details'!H9,8)="Personal","P","B") -> B
A12: =IF(ISNUMBER('2026_Transaction Details'!A10),'2026_Transaction Details'!A10,DATEVALUE('2026_Transaction Details'!A10)) -> 46164 | B12: ='2026_Transaction Details'!B10 -> AMAZON DIGITAL SVCS AMZN.COM/BILL WA | C12: ='2026_Transaction Details'!H10 -> Personal - Amazon | D12: ='2026_Transaction Details'!E10 -> 12.99 | E12: =IF(LEFT('2026_Transaction Details'!H10,8)="Personal","P","B") -> P
A13: =IF(ISNUMBER('2026_Transaction Details'!A11),'2026_Transaction Details'!A11,DATEVALUE('2026_Transaction Details'!A11)) -> 46160 | B13: ='2026_Transaction Details'!B11 -> AMAZON PRIME*BF01455AMZN.COM/BILL WA | C13: ='2026_Transaction Details'!H11 -> Personal - Amazon | D13: ='2026_Transaction Details'!E11 -> 4.99 | E13: =IF(LEFT('2026_Transaction Details'!H11,8)="Personal","P","B") -> P
A14: =IF(ISNUMBER('2026_Transaction Details'!A12),'2026_Transaction Details'!A12,DATEVALUE('2026_Transaction Details'!A12)) -> 46156 | B14: ='2026_Transaction Details'!B12 -> AMAZON DIGITAL SVCS AMZN.COM/BILL WA | C14: ='2026_Transaction Details'!H12 -> Personal - Amazon | D14: ='2026_Transaction Details'!E12 -> 10.99 | E14: =IF(LEFT('2026_Transaction Details'!H12,8)="Personal","P","B") -> P
A15: =IF(ISNUMBER('2026_Transaction Details'!A13),'2026_Transaction Details'!A13,DATEVALUE('2026_Transaction Details'!A13)) -> 46156 | B15: ='2026_Transaction Details'!B13 -> AMAZON DIGITAL SVCS AMZN.COM/BILL WA | C15: ='2026_Transaction Details'!H13 -> Personal - Amazon | D15: ='2026_Transaction Details'!E13 -> 11.99 | E15: =IF(LEFT('2026_Transaction Details'!H13,8)="Personal","P","B") -> P
A16: =IF(ISNUMBER('2026_Transaction Details'!A14),'2026_Transaction Details'!A14,DATEVALUE('2026_Transaction Details'!A14)) -> 46153 | B16: ='2026_Transaction Details'!B14 -> ONLINE PAYMENT - THANK YOU | C16: ='2026_Transaction Details'!H14 -> Online AMEX Payment | D16: ='2026_Transaction Details'!E14 -> -103.36 | E16: =IF(LEFT('2026_Transaction Details'!H14,8)="Personal","P","B") -> B
A17: =IF(ISNUMBER('2026_Transaction Details'!A15),'2026_Transaction Details'!A15,DATEVALUE('2026_Transaction Details'!A15)) -> 46151 | B17: ='2026_Transaction Details'!B15 -> AMAZON DIGITAL SVCS AMZN.COM/BILL WA | C17: ='2026_Transaction Details'!H15 -> Personal - Amazon | D17: ='2026_Transaction Details'!E15 -> 6.99 | E17: =IF(LEFT('2026_Transaction Details'!H15,8)="Personal","P","B") -> P
A18: =IF(ISNUMBER('2026_Transaction Details'!A16),'2026_Transaction Details'!A16,DATEVALUE('2026_Transaction Details'!A16)) -> 46144 | B18: ='2026_Transaction Details'!B16 -> Amazon Prime Amazon.com WA | C18: ='2026_Transaction Details'!H16 -> Personal - Amazon | D18: ='2026_Transaction Details'!E16 -> 16.45 | E18: =IF(LEFT('2026_Transaction Details'!H16,8)="Personal","P","B") -> P
A19: =IF(ISNUMBER('2026_Transaction Details'!A17),'2026_Transaction Details'!A17,DATEVALUE('2026_Transaction Details'!A17)) -> 46142 | B19: ='2026_Transaction Details'!B17 -> AMAZON DIGITAL SVCS AMZN.COM/BILL WA | C19: ='2026_Transaction Details'!H17 -> Personal - Amazon | D19: ='2026_Transaction Details'!E17 -> 13.99 | E19: =IF(LEFT('2026_Transaction Details'!H17,8)="Personal","P","B") -> P
A20: =IF(ISNUMBER('2026_Transaction Details'!A18),'2026_Transaction Details'!A18,DATEVALUE('2026_Transaction Details'!A18)) -> 46141 | B20: ='2026_Transaction Details'!B18 -> AMAZON DIGITAL SVCS AMZN.COM/BILL WA | C20: ='2026_Transaction Details'!H18 -> Personal - Amazon | D20: ='2026_Transaction Details'!E18 -> 7.99 | E20: =IF(LEFT('2026_Transaction Details'!H18,8)="Personal","P","B") -> P
A21: =IF(ISNUMBER('2026_Transaction Details'!A19),'2026_Transaction Details'!A19,DATEVALUE('2026_Transaction Details'!A19)) -> 46140 | B21: ='2026_Transaction Details'!B19 -> AMAZON DIGITAL SVCS AMZN.COM/BILL WA | C21: ='2026_Transaction Details'!H19 -> Personal - Amazon | D21: ='2026_Transaction Details'!E19 -> 10.99 | E21: =IF(LEFT('2026_Transaction Details'!H19,8)="Personal","P","B") -> P
... A63: =IF(ISNUMBER('2026_Transaction Details'!A61),'2026_Transaction Details'!A61,DATEVALUE('2026_Transaction Details'!A61)) -> 46024 | B63: ='2026_Transaction Details'!B61 -> Amazon Prime Amazon.com WA | C63: ='2026_Transaction Details'!H61 -> Personal - Amazon | D63: ='2026_Transaction Details'!E61 -> 16.45 | E63: =IF(LEFT('2026_Transaction Details'!H61,8)="Personal","P","B") -> P
A64: =IF(ISNUMBER('Raw Data'!A8),'Raw Data'!A8,DATEVALUE('Raw Data'!A8)) -> 46022 | B64: ='Raw Data'!B8 -> PRIME VIDEO CHANNELSAMZN.COM/BILL WA | C64: ='Raw Data'!H8 -> Personal - Amazon | D64: ='Raw Data'!E8 -> 12.99 | E64: =IF(LEFT('Raw Data'!H8,8)="Personal","P","B") -> P
A65: =IF(ISNUMBER('Raw Data'!A9),'Raw Data'!A9,DATEVALUE('Raw Data'!A9)) -> 46020 | B65: ='Raw Data'!B9 -> PRIME VIDEO CHANNELSAMZN.COM/BILL WA | C65: ='Raw Data'!H9 -> Personal - Amazon | D65: ='Raw Data'!E9 -> 7.99 | E65: =IF(LEFT('Raw Data'!H9,8)="Personal","P","B") -> P
A66: =IF(ISNUMBER('Raw Data'!A10),'Raw Data'!A10,DATEVALUE('Raw Data'!A10)) -> 46019 | B66: ='Raw Data'!B10 -> ONLINE PAYMENT - THANK YOU | C66: ='Raw Data'!H10 -> Online AMEX Payment | D66: ='Raw Data'!E10 -> -1581.75 | E66: =IF(LEFT('Raw Data'!H10,8)="Personal","P","B") -> B
A67: =IF(ISNUMBER('Raw Data'!A11),'Raw Data'!A11,DATEVALUE('Raw Data'!A11)) -> 46019 | B67: ='Raw Data'!B11 -> PRIME VIDEO CHANNELSAMZN.COM/BILL WA | C67: ='Raw Data'!H11 -> Personal - Amazon | D67: ='Raw Data'!E11 -> 9.99 | E67: =IF(LEFT('Raw Data'!H11,8)="Personal","P","B") -> P
A68: =IF(ISNUMBER('Raw Data'!A12),'Raw Data'!A12,DATEVALUE('Raw Data'!A12)) -> 46013 | B68: ='Raw Data'!B12 -> PRIME VIDEO CHANNELSAMZN.COM/BILL WA | C68: ='Raw Data'!H12 -> Personal - Amazon | D68: ='Raw Data'!E12 -> 12.99 | E68: =IF(LEFT('Raw Data'!H12,8)="Personal","P","B") -> P
A69: =IF(ISNUMBER('Raw Data'!A13),'Raw Data'!A13,DATEVALUE('Raw Data'!A13)) -> 46008 | B69: ='Raw Data'!B13 -> AMAZON PRIME*6D4319NAMZN.COM/BILL WA | C69: ='Raw Data'!H13 -> Personal - Amazon | D69: ='Raw Data'!E13 -> 2.99 | E69: =IF(LEFT('Raw Data'!H13,8)="Personal","P","B") -> P
A70: =IF(ISNUMBER('Raw Data'!A14),'Raw Data'!A14,DATEVALUE('Raw Data'!A14)) -> 46005 | B70: ='Raw Data'!B14 -> PRIME VIDEO CHANNELSAMZN.COM/BILL WA | C70: ='Raw Data'!H14 -> Personal - Amazon | D70: ='Raw Data'!E14 -> 10.99 | E70: =IF(LEFT('Raw Data'!H14,8)="Personal","P","B") -> P
A71: =IF(ISNUMBER('Raw Data'!A15),'Raw Data'!A15,DATEVALUE('Raw Data'!A15)) -> 46004 | B71: ='Raw Data'!B15 -> PRIME VIDEO CHANNELSAMZN.COM/BILL WA | C71: ='Raw Data'!H15 -> Personal - Amazon | D71: ='Raw Data'!E15 -> 10.99 | E71: =IF(LEFT('Raw Data'!H15,8)="Personal","P","B") -> P
A72: =IF(ISNUMBER('Raw Data'!A16),'Raw Data'!A16,DATEVALUE('Raw Data'!A16)) -> 46000 | B72: ='Raw Data'!B16 -> PRIME VIDEO CHANNELSAMZN.COM/BILL WA | C72: ='Raw Data'!H16 -> Personal - Amazon | D72: ='Raw Data'!E16 -> 6.99 | E72: =IF(LEFT('Raw Data'!H16,8)="Personal","P","B") -> P
A73: =IF(ISNUMBER('Raw Data'!A17),'Raw Data'!A17,DATEVALUE('Raw Data'!A17)) -> 45993 | B73: ='Raw Data'!B17 -> Amazon Prime Amazon.com WA | C73: ='Raw Data'!H17 -> Personal - Amazon | D73: ='Raw Data'!E17 -> 16.45 | E73: =IF(LEFT('Raw Data'!H17,8)="Personal","P","B") -> P
A74: =IF(ISNUMBER('Raw Data'!A18),'Raw Data'!A18,DATEVALUE('Raw Data'!A18)) -> 45993 | B74: ='Raw Data'!B18 -> PACOS TACOS LOS ANGELES CA | C74: ='Raw Data'!H18 -> Personal - Food | D74: ='Raw Data'!E18 -> 161.43 | E74: =IF(LEFT('Raw Data'!H18,8)="Personal","P","B") -> P
A75: =IF(ISNUMBER('Raw Data'!A19),'Raw Data'!A19,DATEVALUE('Raw Data'!A19)) -> 45993 | B75: ='Raw Data'!B19 -> RENOUVEAUM* RENOUVEALOS ANGELES CA | C75: ='Raw Data'!H19 -> Personal - Health | D75: ='Raw Data'!E19 -> 289.02 | E75: =IF(LEFT('Raw Data'!H19,8)="Personal","P","B") -> P
... A205: =IF(ISNUMBER('Raw Data'!A149),'Raw Data'!A149,DATEVALUE('Raw Data'!A149)) -> 45659 | B205: ='Raw Data'!B149 -> Amazon Prime Amazon.com WA | C205: ='Raw Data'!H149 -> Personal - Amazon | D205: ='Raw Data'!E149 -> 16.41 | E205: =IF(LEFT('Raw Data'!H149,8)="Personal","P","B") -> P
A207: Totals | C207: Charges | D207: =SUMIF(D10:D205,">0") -> 18556.54
C208: Credits & Payments | D208: =SUMIF(D10:D205,"<0") -> -18560.46
C209: Net Balance | D209: =D207+D208 -> -3.92

Sheet Raw Data
A1: Transaction Details | B1: Platinum Card® / Jan 01, 2025 to Dec 31, 2025
A2: Prepared for
A3: JOHN L DUNNING
A4: Account Number
A5: XXXX-XXXXXX-27001
A7: Date | B7: Description | C7: Card Member | D7: Account # | E7: Amount | F7: Extended Details | G7: Appears On Your Statement As | H7: Category
A8: 12/31/2025 | B8: PRIME VIDEO CHANNELSAMZN.COM/BILL WA | C8: JOHN L DUNNING | D8: -27001 | E8: 12.99 | F8: 3QK5GQ9GBL6 DIGITAL PRIME VIDEO CHANNELS AMZN.COM/BILL WA DIGITAL | G8: PRIME VIDEO CHANNELSAMZN.COM/BILL WA | H8: Personal - Amazon
A9: 12/29/2025 | B9: PRIME VIDEO CHANNELSAMZN.COM/BILL WA | C9: JOHN L DUNNING | D9: -27001 | E9: 7.99 | F9: 53RR35MYGQS DIGITAL PRIME VIDEO CHANNELS AMZN.COM/BILL WA DIGITAL | G9: PRIME VIDEO CHANNELSAMZN.COM/BILL WA | H9: Personal - Amazon
A10: 12/28/2025 | B10: ONLINE PAYMENT - THANK YOU | C10: JOHN L DUNNING | D10: -27001 | E10: -1581.75 | F10: ONLINE PAYMENT - THANK YOU | G10: ONLINE PAYMENT - THANK YOU | H10: Online AMEX Payment
A11: 12/28/2025 | B11: PRIME VIDEO CHANNELSAMZN.COM/BILL WA | C11: JOHN L DUNNING | D11: -27001 | E11: 9.99 | F11: 6MANALPUIXX DIGITAL PRIME VIDEO CHANNELS AMZN.COM/BILL WA DIGITAL | G11: PRIME VIDEO CHANNELSAMZN.COM/BILL WA | H11: Personal - Amazon
A12: 12/22/2025 | B12: PRIME VIDEO CHANNELSAMZN.COM/BILL WA | C12: JOHN L DUNNING | D12: -27001 | E12: 12.99 | F12: 4476FN18PAD DIGITAL PRIME VIDEO CHANNELS AMZN.COM/BILL WA DIGITAL | G12: PRIME VIDEO CHANNELSAMZN.COM/BILL WA | H12: Personal - Amazon
A13: 12/17/2025 | B13: AMAZON PRIME*6D4319NAMZN.COM/BILL WA | C13: JOHN L DUNNING | D13: -27001 | E13: 2.99 | F13: 79P427D5IIX DIGITAL AMAZON PRIME*6D4319NP3 AMZN.COM/BILL WA DIGITAL | G13: AMAZON PRIME*6D4319NAMZN.COM/BILL WA | H13: Personal - Amazon
A14: 12/14/2025 | B14: PRIME VIDEO CHANNELSAMZN.COM/BILL WA | C14: JOHN L DUNNING | D14: -27001 | E14: 10.99 | F14: 60565C58WFI DIGITAL PRIME VIDEO CHANNELS AMZN.COM/BILL WA DIGITAL | G14: PRIME VIDEO CHANNELSAMZN.COM/BILL WA | H14: Personal - Amazon
A15: 12/13/2025 | B15: PRIME VIDEO CHANNELSAMZN.COM/BILL WA | C15: JOHN L DUNNING | D15: -27001 | E15: 10.99 | F15: 74LUAQB1HHI DIGITAL PRIME VIDEO CHANNELS AMZN.COM/BILL WA DIGITAL | G15: PRIME VIDEO CHANNELSAMZN.COM/BILL WA | H15: Personal - Amazon
A16: 12/09/2025 | B16: PRIME VIDEO CHANNELSAMZN.COM/BILL WA | C16: JOHN L DUNNING | D16: -27001 | E16: 6.99 | F16: 4CGX7HXTJWS DIGITAL PRIME VIDEO CHANNELS AMZN.COM/BILL WA DIGITAL | G16: PRIME VIDEO CHANNELSAMZN.COM/BILL WA | H16: Personal - Amazon
A17: 12/02/2025 | B17: Amazon Prime Amazon.com WA | C17: JOHN L DUNNING | D17: -27001 | E17: 16.45 | F17: 4ZOWVCAMIYL SUBSCRIPTION Amazon Prime Amazon.com WA SUBSCRIPTION | G17: Amazon Prime Amazon.com WA | H17: Personal - Amazon
A18: 12/02/2025 | B18: PACOS TACOS LOS ANGELES CA | C18: JOHN L DUNNING | D18: -27001 | E18: 161.43 | F18: 84600079 310-850-1336 PACOS TACOS LOS ANGELES CA Description : FOOD/BEVERAGE Price : 0.00 310-850-1336 | G18: PACOS TACOS LOS ANGELES CA | H18: Personal - Food
A19: 12/02/2025 | B19: RENOUVEAUM* RENOUVEALOS ANGELES CA | C19: JOHN L DUNNING | D19: -27001 | E19: 289.02 | F19: CH_3SA33SHU +14697464855 RENOUVEAUM* RENOUVEAUM LOS ANGELES CA +14697464855 | G19: RENOUVEAUM* RENOUVEALOS ANGELES CA | H19: Personal - Health
... A149: 01/02/2025 | B149: Amazon Prime Amazon.com WA | C149: JOHN L DUNNING | D149: -27001 | E149: 16.41 | F149: 6Z3D0KHCA56 SUBSCRIPTION Amazon Prime Amazon.com WA SUBSCRIPTION | G149: Amazon Prime Amazon.com WA | H149: Personal - Amazon

Sheet 2026_Transaction Details
A1: Transaction Details | B1: Platinum Card® / Jan 01, 2026 to Jun 12, 2026
A2: Prepared for
A3: JOHN L DUNNING
A4: Account Number
A5: XXXX-XXXXXX-27001
A7: Date | B7: Description | C7: Card Member | D7: Account # | E7: Amount | F7: Extended Details | G7: Appears On Your Statement As | H7: Category
A8: 05/27/2026 | B8: AMAZON.COM AMZN.COM/BILL WA | C8: JOHN L DUNNING | D8: -27001 | E8: 35.04 | F8: 3CIX5Y0WP6O BOOK STORES AMAZON.COM AMZN.COM/BILL WA BOOK STORES | G8: AMAZON.COM AMZN.COM/BILL WA | H8: Personal - Amazon
A9: 05/27/2026 | B9: ONLINE PAYMENT - THANK YOU | C9: JOHN L DUNNING | D9: -27001 | E9: -40.96 | F9: ONLINE PAYMENT - THANK YOU | G9: ONLINE PAYMENT - THANK YOU | H9: Online AMEX Payment
A10: 05/22/2026 | B10: AMAZON DIGITAL SVCS AMZN.COM/BILL WA | C10: JOHN L DUNNING | D10: -27001 | E10: 12.99 | F10: 5EQM5O88DTP DIGITAL AMAZON DIGITAL SVCS AMZN.COM/BILL WA DIGITAL | G10: AMAZON DIGITAL SVCS AMZN.COM/BILL WA | H10: Personal - Amazon
A11: 05/18/2026 | B11: AMAZON PRIME*BF01455AMZN.COM/BILL WA | C11: JOHN L DUNNING | D11: -27001 | E11: 4.99 | F11: 4NFXLEEQAQP DIGITAL AMAZON PRIME*BF0145590 AMZN.COM/BILL WA DIGITAL | G11: AMAZON PRIME*BF01455AMZN.COM/BILL WA | H11: Personal - Amazon
A12: 05/14/2026 | B12: AMAZON DIGITAL SVCS AMZN.COM/BILL WA | C12: JOHN L DUNNING | D12: -27001 | E12: 10.99 | F12: 5EX0WLQGEJ0 DIGITAL AMAZON DIGITAL SVCS AMZN.COM/BILL WA DIGITAL | G12: AMAZON DIGITAL SVCS AMZN.COM/BILL WA | H12: Personal - Amazon
A13: 05/14/2026 | B13: AMAZON DIGITAL SVCS AMZN.COM/BILL WA | C13: JOHN L DUNNING | D13: -27001 | E13: 11.99 | F13: 2FZS2WX0TTV DIGITAL AMAZON DIGITAL SVCS AMZN.COM/BILL WA DIGITAL | G13: AMAZON DIGITAL SVCS AMZN.COM/BILL WA | H13: Personal - Amazon
A14: 05/11/2026 | B14: ONLINE PAYMENT - THANK YOU | C14: JOHN L DUNNING | D14: -27001 | E14: -103.36 | F14: ONLINE PAYMENT - THANK YOU | G14: ONLINE PAYMENT - THANK YOU | H14: Online AMEX Payment
A15: 05/09/2026 | B15: AMAZON DIGITAL SVCS AMZN.COM/BILL WA | C15: JOHN L DUNNING | D15: -27001 | E15: 6.99 | F15: 5Y73M6FGFGI DIGITAL AMAZON DIGITAL SVCS AMZN.COM/BILL WA DIGITAL | G15: AMAZON DIGITAL SVCS AMZN.COM/BILL WA | H15: Personal - Amazon
A16: 05/02/2026 | B16: Amazon Prime Amazon.com WA | C16: JOHN L DUNNING | D16: -27001 | E16: 16.45 | F16: 4Q40467Q7LT SUBSCRIPTION Amazon Prime Amazon.com WA SUBSCRIPTION | G16: Amazon Prime Amazon.com WA | H16: Personal - Amazon
A17: 04/30/2026 | B17: AMAZON DIGITAL SVCS AMZN.COM/BILL WA | C17: JOHN L DUNNING | D17: -27001 | E17: 13.99 | F17: 46IDX3EZWU2 DIGITAL AMAZON DIGITAL SVCS AMZN.COM/BILL WA DIGITAL | G17: AMAZON DIGITAL SVCS AMZN.COM/BILL WA | H17: Personal - Amazon
A18: 04/29/2026 | B18: AMAZON DIGITAL SVCS AMZN.COM/BILL WA | C18: JOHN L DUNNING | D18: -27001 | E18: 7.99 | F18: T10O6IXWQNM DIGITAL AMAZON DIGITAL SVCS AMZN.COM/BILL WA DIGITAL | G18: AMAZON DIGITAL SVCS AMZN.COM/BILL WA | H18: Personal - Amazon
A19: 04/28/2026 | B19: AMAZON DIGITAL SVCS AMZN.COM/BILL WA | C19: JOHN L DUNNING | D19: -27001 | E19: 10.99 | F19: 5OJ2UAMF59V DIGITAL AMAZON DIGITAL SVCS AMZN.COM/BILL WA DIGITAL | G19: AMAZON DIGITAL SVCS AMZN.COM/BILL WA | H19: Personal - Amazon
... A61: 01/02/2026 | B61: Amazon Prime Amazon.com WA | C61: JOHN L DUNNING | D61: -27001 | E61: 16.45 | F61: 5H26486N6Z3 SUBSCRIPTION Amazon Prime Amazon.com WA SUBSCRIPTION | G61: Amazon Prime Amazon.com WA | H61: Personal - Amazon
