Workbook

Sheet Transaction Summary
A1: DWG CAPITAL PARTNERS | D1: #VALUE!
A2: Amex Business Platinum | Statement Summary
A4: Account Holder | B4: John Dunning
A5: Account | B5: XXXX-XXXXXX-01004
A6: Statement Period (Past 3 Mon) | B6: February 2026 - May 2026
A8: TOTALS
A9: Charges | B9: ='Transaction Details'!D112 -> 28501.7
A10: Credits & Payments | B10: ='Transaction Details'!D113 -> -18477.34
A11: Net Balance | B11: =B9+B10 -> 10024.36
A13: SPEND BY CATEGORY
A14: Category | B14: Amount | C14: % of Charges
A15: DWGCP / DWG Operating
A16: DWGCP Team Travel | B16: =SUMIFS('Transaction Details'!D:D,'Transaction Details'!C:C,A16) -> 5640.94 | C16: =IFERROR(B16/$B$9,0) -> 0.19791591
A17: Employee Bonus | B17: =SUMIFS('Transaction Details'!D:D,'Transaction Details'!C:C,A17) -> 141.24 | C17: =IFERROR(B17/$B$9,0) -> 0.0049554939
A18: DWGCP Car | B18: =SUMIFS('Transaction Details'!D:D,'Transaction Details'!C:C,A18) -> 2608 | C18: =IFERROR(B18/$B$9,0) -> 0.091503314
A19: DWGCP Professional Training | B19: =SUMIFS('Transaction Details'!D:D,'Transaction Details'!C:C,A19) -> 1484 | C19: =IFERROR(B19/$B$9,0) -> 0.05206707
A20: DWGCP Investor Dinner | B20: =SUMIFS('Transaction Details'!D:D,'Transaction Details'!C:C,A20) -> 1000 | C20: =IFERROR(B20/$B$9,0) -> 0.035085626
A21: DWGCP Investor Meeting | B21: =SUMIFS('Transaction Details'!D:D,'Transaction Details'!C:C,A21) -> 533.23 | C21: =IFERROR(B21/$B$9,0) -> 0.018708709
A22: DWGCP HR | B22: =SUMIFS('Transaction Details'!D:D,'Transaction Details'!C:C,A22) -> 78.49 | C22: =IFERROR(B22/$B$9,0) -> 0.0027538708
A23: DWG Capital Group | B23: =SUMIFS('Transaction Details'!D:D,'Transaction Details'!C:C,A23) -> 1200 | C23: =IFERROR(B23/$B$9,0) -> 0.042102752
A24: JAL Legal Case | B24: =SUMIFS('Transaction Details'!D:D,'Transaction Details'!C:C,A24) -> 109.54 | C24: =IFERROR(B24/$B$9,0) -> 0.0038432795
A25: Notary Services | B25: =SUMIFS('Transaction Details'!D:D,'Transaction Details'!C:C,A25) -> 35 | C25: =IFERROR(B25/$B$9,0) -> 0.0012279969
A26: Annual AMEX Fee | B26: =SUMIFS('Transaction Details'!D:D,'Transaction Details'!C:C,A26) -> 895 | C26: =IFERROR(B26/$B$9,0) -> 0.031401636
A27: Subtotal — Operating | B27: =SUM(B16:B26) -> 13725.44 | C27: =IFERROR(B27/$B$9,0) -> 0.48156566
A28: Technology & Software
A29: Software & Subscriptions | B29: =SUMIFS('Transaction Details'!D:D,'Transaction Details'!C:C,A29) -> 3027.84 | C29: =IFERROR(B29/$B$9,0) -> 0.10623366
A30: Employee Tech Onboarding | B30: =SUMIFS('Transaction Details'!D:D,'Transaction Details'!C:C,A30) -> 1572.28 | C30: =IFERROR(B30/$B$9,0) -> 0.055164429
A31: Recruiting | B31: =SUMIFS('Transaction Details'!D:D,'Transaction Details'!C:C,A31) -> 1841.11 | C31: =IFERROR(B31/$B$9,0) -> 0.064596498
A32: Subtotal — Technology | B32: =SUM(B29:B31) -> 6441.23 | C32: =IFERROR(B32/$B$9,0) -> 0.22599459
A33: Meals & Ground Transport
A34: Team Lunch | B34: =SUMIFS('Transaction Details'!D:D,'Transaction Details'!C:C,A34) -> 719.4 | C34: =IFERROR(B34/$B$9,0) -> 0.0252406
A35: Team Dinner | B35: =SUMIFS('Transaction Details'!D:D,'Transaction Details'!C:C,A35) -> 65.57 | C35: =IFERROR(B35/$B$9,0) -> 0.0023005645
A36: Travel Meal | B36: =SUMIFS('Transaction Details'!D:D,'Transaction Details'!C:C,A36) -> 69.11 | C36: =IFERROR(B36/$B$9,0) -> 0.0024247676
A37: Transportation | B37: =SUMIFS('Transaction Details'!D:D,'Transaction Details'!C:C,A37) -> 163.32 | C37: =IFERROR(B37/$B$9,0) -> 0.0057301845
A38: Subtotal — Meals & Transport | B38: =SUM(B34:B37) -> 1017.4 | C38: =IFERROR(B38/$B$9,0) -> 0.035696116
A39: One-Time / Capital
A40: Auto (One-Time) | B40: =SUMIFS('Transaction Details'!D:D,'Transaction Details'!C:C,A40) -> 6900.58 | C40: =IFERROR(B40/$B$9,0) -> 0.24211117
A41: Subtotal — Capital | B41: =SUM(B40:B40) -> 6900.58 | C41: =IFERROR(B41/$B$9,0) -> 0.24211117
A42: Personal — Reimburse to Company
A43: Personal | B43: =SUMIFS('Transaction Details'!D:D,'Transaction Details'!C:C,A43) -> 217.05 | C43: =IFERROR(B43/$B$9,0) -> 0.0076153352
A44: Personal Health | B44: =SUMIFS('Transaction Details'!D:D,'Transaction Details'!C:C,A44) -> 200 | C44: =IFERROR(B44/$B$9,0) -> 0.0070171253
A45: Subtotal — Personal | B45: =SUM(B43:B44) -> 417.05 | C45: =IFERROR(B45/$B$9,0) -> 0.014632461
A46: Credits, Refunds & Payments
A47: Refund | B47: =SUMIFS('Transaction Details'!D:D,'Transaction Details'!C:C,A47) -> -462.4 | C47: =IFERROR(B47/$B$9,0) -> -0.016223594
A48: Credit | B48: =SUMIFS('Transaction Details'!D:D,'Transaction Details'!C:C,A48) -> -601.81 | C48: =IFERROR(B48/$B$9,0) -> -0.021114881
A49: Points redemption | B49: =SUMIFS('Transaction Details'!D:D,'Transaction Details'!C:C,A49) -> -350 | C49: =IFERROR(B49/$B$9,0) -> -0.012279969
A50: Payment | B50: =SUMIFS('Transaction Details'!D:D,'Transaction Details'!C:C,A50) -> -17063.13 | C50: =IFERROR(B50/$B$9,0) -> -0.59867061
A51: Subtotal — Credits/Payments | B51: =SUM(B47:B50) -> -18477.34 | C51: =IFERROR(B51/$B$9,0) -> -0.64828905
A52: GRAND TOTAL | B52: =B27+B32+B38+B41+B45+B51 -> 10024.36 | C52: =B52/B9 -> 0.35171095
A54: SPEND BY MONTH
A55: Month | B55: Charges | C55: Credits | D55: Net
A56: 46082 | B56: =SUMIFS('Transaction Details'!D:D,'Transaction Details'!A:A,">="&DATE(2026,3,1),'Transaction Details'!A:A,"<"&DATE(2026,4,1),'Transaction Details'!D:D,">0") -> 10350.31 | C56: =SUMIFS('Transaction Details'!D:D,'Transaction Details'!A:A,">="&DATE(2026,3,1),'Transaction Details'!A:A,"<"&DATE(2026,4,1),'Transaction Details'!D:D,"<0") -> -462.4 | D56: =B56+C56 -> 9887.91
A57: 46113 | B57: =SUMIFS('Transaction Details'!D:D,'Transaction Details'!A:A,">="&DATE(2026,4,1),'Transaction Details'!A:A,"<"&DATE(2026,5,1),'Transaction Details'!D:D,">0") -> 11104.01 | C57: =SUMIFS('Transaction Details'!D:D,'Transaction Details'!A:A,">="&DATE(2026,4,1),'Transaction Details'!A:A,"<"&DATE(2026,5,1),'Transaction Details'!D:D,"<0") -> -1591.53 | D57: =B57+C57 -> 9512.48
A58: 46143 | B58: =SUMIFS('Transaction Details'!D:D,'Transaction Details'!A:A,">="&DATE(2026,5,1),'Transaction Details'!A:A,"<"&DATE(2026,6,1),'Transaction Details'!D:D,">0") -> 7047.38 | C58: =SUMIFS('Transaction Details'!D:D,'Transaction Details'!A:A,">="&DATE(2026,5,1),'Transaction Details'!A:A,"<"&DATE(2026,6,1),'Transaction Details'!D:D,"<0") -> -16423.41 | D58: =B58+C58 -> -9376.03
A59: Total | B59: =SUM(B56:B58) -> 28501.7 | C59: =SUM(C56:C58) -> -18477.34 | D59: =B59+C59 -> 10024.36
A61: PAYMENTS, CREDITS & REFUNDS DETAIL
A62: Date | B62: Description | C62: Type | D62: Amount
A63: 46155 | B63: Online payment received | C63: Payment | D63: -15821.6
A64: 46125 | B64: Online payment received | C64: Payment | D64: -1241.53
A65: 46145 | B65: Amex Travel — Points credit | C65: Credit | D65: -601.81
A66: 46118 | B66: Amex Travel — Points redemption | C66: Points redemption | D66: -200
A67: 46119 | B67: Amex Travel — Points redemption | C67: Points redemption | D67: -150
A68: 46104 | B68: Southwest Airlines refund (Dunning) | C68: Refund | D68: -393.4
A69: 46104 | B69: Southwest Airlines refund (Dunning) | C69: Refund | D69: -69
A70: Total Credits & Payments | D70: =SUM(D63:D69) -> -18477.34

Sheet Monthly Breakdown
A1: DWG CAPITAL PARTNERS | D1: #VALUE!
A2: Amex Business Platinum | Monthly Breakdown
A4: Period | B4: February 2026 - May 2026
A6: 46107
A7: Category | B7: Amount | C7: % of Month Charges
A8: Auto (One-Time) | B8: =SUMIFS('Transaction Details'!D:D,'Transaction Details'!C:C,A8,'Transaction Details'!A:A,">="&DATE(2026,3,1),'Transaction Details'!A:A,"<"&DATE(2026,4,1)) -> 6900.58 | C8: =IFERROR(B8/$B$15,0) -> 0.66670274
A9: DWGCP Team Travel | B9: =SUMIFS('Transaction Details'!D:D,'Transaction Details'!C:C,A9,'Transaction Details'!A:A,">="&DATE(2026,3,1),'Transaction Details'!A:A,"<"&DATE(2026,4,1)) -> 1446.55 | C9: =IFERROR(B9/$B$15,0) -> 0.1397591
A10: Annual AMEX Fee | B10: =SUMIFS('Transaction Details'!D:D,'Transaction Details'!C:C,A10,'Transaction Details'!A:A,">="&DATE(2026,3,1),'Transaction Details'!A:A,"<"&DATE(2026,4,1)) -> 895 | C10: =IFERROR(B10/$B$15,0) -> 0.08647084
A11: Recruiting | B11: =SUMIFS('Transaction Details'!D:D,'Transaction Details'!C:C,A11,'Transaction Details'!A:A,">="&DATE(2026,3,1),'Transaction Details'!A:A,"<"&DATE(2026,4,1)) -> 560 | C11: =IFERROR(B11/$B$15,0) -> 0.05410466
A12: Team Lunch | B12: =SUMIFS('Transaction Details'!D:D,'Transaction Details'!C:C,A12,'Transaction Details'!A:A,">="&DATE(2026,3,1),'Transaction Details'!A:A,"<"&DATE(2026,4,1)) -> 265.56 | C12: =IFERROR(B12/$B$15,0) -> 0.025657203
A13: Personal | B13: =SUMIFS('Transaction Details'!D:D,'Transaction Details'!C:C,A13,'Transaction Details'!A:A,">="&DATE(2026,3,1),'Transaction Details'!A:A,"<"&DATE(2026,4,1)) -> 217.05 | C13: =IFERROR(B13/$B$15,0) -> 0.020970386
A14: Team Dinner | B14: =SUMIFS('Transaction Details'!D:D,'Transaction Details'!C:C,A14,'Transaction Details'!A:A,">="&DATE(2026,3,1),'Transaction Details'!A:A,"<"&DATE(2026,4,1)) -> 65.57 | C14: =IFERROR(B14/$B$15,0) -> 0.006335076
A15: Total Charges | B15: =SUMIFS('Transaction Details'!D:D,'Transaction Details'!A:A,">="&DATE(2026,3,1),'Transaction Details'!A:A,"<"&DATE(2026,4,1),'Transaction Details'!D:D,">0") -> 10350.31
A16: Credits & Payments | B16: =SUMIFS('Transaction Details'!D:D,'Transaction Details'!A:A,">="&DATE(2026,3,1),'Transaction Details'!A:A,"<"&DATE(2026,4,1),'Transaction Details'!D:D,"<0") -> -462.4
A17: Net | B17: =B15+B16 -> 9887.91
A19: 46113
A20: Category | B20: Amount | C20: % of Month Charges
A21: DWGCP Car | B21: =SUMIFS('Transaction Details'!D:D,'Transaction Details'!C:C,A21,'Transaction Details'!A:A,">="&DATE(2026,4,1),'Transaction Details'!A:A,"<"&DATE(2026,5,1)) -> 2608 | C21: =IFERROR(B21/$B$31,0) -> 0.23487011
A22: DWGCP Team Travel | B22: =SUMIFS('Transaction Details'!D:D,'Transaction Details'!C:C,A22,'Transaction Details'!A:A,">="&DATE(2026,4,1),'Transaction Details'!A:A,"<"&DATE(2026,5,1)) -> 2260.59 | C22: =IFERROR(B22/$B$31,0) -> 0.20358321
A23: Software & Subscriptions | B23: =SUMIFS('Transaction Details'!D:D,'Transaction Details'!C:C,A23,'Transaction Details'!A:A,">="&DATE(2026,4,1),'Transaction Details'!A:A,"<"&DATE(2026,5,1)) -> 1774.44 | C23: =IFERROR(B23/$B$31,0) -> 0.15980173
A24: Recruiting | B24: =SUMIFS('Transaction Details'!D:D,'Transaction Details'!C:C,A24,'Transaction Details'!A:A,">="&DATE(2026,4,1),'Transaction Details'!A:A,"<"&DATE(2026,5,1)) -> 1281.11 | C24: =IFERROR(B24/$B$31,0) -> 0.11537364
A25: DWGCP Professional Training | B25: =SUMIFS('Transaction Details'!D:D,'Transaction Details'!C:C,A25,'Transaction Details'!A:A,">="&DATE(2026,4,1),'Transaction Details'!A:A,"<"&DATE(2026,5,1)) -> 1235 | C25: =IFERROR(B25/$B$31,0) -> 0.11122108
A26: DWG Capital Group | B26: =SUMIFS('Transaction Details'!D:D,'Transaction Details'!C:C,A26,'Transaction Details'!A:A,">="&DATE(2026,4,1),'Transaction Details'!A:A,"<"&DATE(2026,5,1)) -> 1200 | C26: =IFERROR(B26/$B$31,0) -> 0.10806907
A27: DWGCP Investor Meeting | B27: =SUMIFS('Transaction Details'!D:D,'Transaction Details'!C:C,A27,'Transaction Details'!A:A,">="&DATE(2026,4,1),'Transaction Details'!A:A,"<"&DATE(2026,5,1)) -> 533.23 | C27: =IFERROR(B27/$B$31,0) -> 0.04802139
A28: Transportation | B28: =SUMIFS('Transaction Details'!D:D,'Transaction Details'!C:C,A28,'Transaction Details'!A:A,">="&DATE(2026,4,1),'Transaction Details'!A:A,"<"&DATE(2026,5,1)) -> 98.15 | C28: =IFERROR(B28/$B$31,0) -> 0.0088391491
A29: DWGCP HR | B29: =SUMIFS('Transaction Details'!D:D,'Transaction Details'!C:C,A29,'Transaction Details'!A:A,">="&DATE(2026,4,1),'Transaction Details'!A:A,"<"&DATE(2026,5,1)) -> 78.49 | C29: =IFERROR(B29/$B$31,0) -> 0.0070686176
A30: Notary Services | B30: =SUMIFS('Transaction Details'!D:D,'Transaction Details'!C:C,A30,'Transaction Details'!A:A,">="&DATE(2026,4,1),'Transaction Details'!A:A,"<"&DATE(2026,5,1)) -> 35 | C30: =IFERROR(B30/$B$31,0) -> 0.0031520145
A31: Total Charges | B31: =SUMIFS('Transaction Details'!D:D,'Transaction Details'!A:A,">="&DATE(2026,4,1),'Transaction Details'!A:A,"<"&DATE(2026,5,1),'Transaction Details'!D:D,">0") -> 11104.01
A32: Credits & Payments | B32: =SUMIFS('Transaction Details'!D:D,'Transaction Details'!A:A,">="&DATE(2026,4,1),'Transaction Details'!A:A,"<"&DATE(2026,5,1),'Transaction Details'!D:D,"<0") -> -1591.53
A33: Net | B33: =B31+B32 -> 9512.48
A35: 46143
A36: Category | B36: Amount | C36: % of Month Charges
A37: DWGCP Team Travel | B37: =SUMIFS('Transaction Details'!D:D,'Transaction Details'!C:C,A37,'Transaction Details'!A:A,">="&DATE(2026,5,1),'Transaction Details'!A:A,"<"&DATE(2026,6,1)) -> 1933.8 | C37: =IFERROR(B37/$B$48,0) -> 0.27439985
A38: Employee Tech Onboarding | B38: =SUMIFS('Transaction Details'!D:D,'Transaction Details'!C:C,A38,'Transaction Details'!A:A,">="&DATE(2026,5,1),'Transaction Details'!A:A,"<"&DATE(2026,6,1)) -> 1572.28 | C38: =IFERROR(B38/$B$48,0) -> 0.22310135
A39: Software & Subscriptions | B39: =SUMIFS('Transaction Details'!D:D,'Transaction Details'!C:C,A39,'Transaction Details'!A:A,">="&DATE(2026,5,1),'Transaction Details'!A:A,"<"&DATE(2026,6,1)) -> 1253.4 | C39: =IFERROR(B39/$B$48,0) -> 0.17785333
A40: DWGCP Investor Dinner | B40: =SUMIFS('Transaction Details'!D:D,'Transaction Details'!C:C,A40,'Transaction Details'!A:A,">="&DATE(2026,5,1),'Transaction Details'!A:A,"<"&DATE(2026,6,1)) -> 1000 | C40: =IFERROR(B40/$B$48,0) -> 0.1418967
A41: Team Lunch | B41: =SUMIFS('Transaction Details'!D:D,'Transaction Details'!C:C,A41,'Transaction Details'!A:A,">="&DATE(2026,5,1),'Transaction Details'!A:A,"<"&DATE(2026,6,1)) -> 453.84 | C41: =IFERROR(B41/$B$48,0) -> 0.064398401
A42: DWGCP Professional Training | B42: =SUMIFS('Transaction Details'!D:D,'Transaction Details'!C:C,A42,'Transaction Details'!A:A,">="&DATE(2026,5,1),'Transaction Details'!A:A,"<"&DATE(2026,6,1)) -> 249 | C42: =IFERROR(B42/$B$48,0) -> 0.03533228
A43: Personal Health | B43: =SUMIFS('Transaction Details'!D:D,'Transaction Details'!C:C,A43,'Transaction Details'!A:A,">="&DATE(2026,5,1),'Transaction Details'!A:A,"<"&DATE(2026,6,1)) -> 200 | C43: =IFERROR(B43/$B$48,0) -> 0.028379341
A44: Employee Bonus | B44: =SUMIFS('Transaction Details'!D:D,'Transaction Details'!C:C,A44,'Transaction Details'!A:A,">="&DATE(2026,5,1),'Transaction Details'!A:A,"<"&DATE(2026,6,1)) -> 141.24 | C44: =IFERROR(B44/$B$48,0) -> 0.020041491
A45: JAL Legal Case | B45: =SUMIFS('Transaction Details'!D:D,'Transaction Details'!C:C,A45,'Transaction Details'!A:A,">="&DATE(2026,5,1),'Transaction Details'!A:A,"<"&DATE(2026,6,1)) -> 109.54 | C45: =IFERROR(B45/$B$48,0) -> 0.015543365
A46: Travel Meal | B46: =SUMIFS('Transaction Details'!D:D,'Transaction Details'!C:C,A46,'Transaction Details'!A:A,">="&DATE(2026,5,1),'Transaction Details'!A:A,"<"&DATE(2026,6,1)) -> 69.11 | C46: =IFERROR(B46/$B$48,0) -> 0.0098064813
A47: Transportation | B47: =SUMIFS('Transaction Details'!D:D,'Transaction Details'!C:C,A47,'Transaction Details'!A:A,">="&DATE(2026,5,1),'Transaction Details'!A:A,"<"&DATE(2026,6,1)) -> 65.17 | C47: =IFERROR(B47/$B$48,0) -> 0.0092474083
A48: Total Charges | B48: =SUMIFS('Transaction Details'!D:D,'Transaction Details'!A:A,">="&DATE(2026,5,1),'Transaction Details'!A:A,"<"&DATE(2026,6,1),'Transaction Details'!D:D,">0") -> 7047.38
A49: Credits & Payments | B49: =SUMIFS('Transaction Details'!D:D,'Transaction Details'!A:A,">="&DATE(2026,5,1),'Transaction Details'!A:A,"<"&DATE(2026,6,1),'Transaction Details'!D:D,"<0") -> -16423.41
A50: Net | B50: =B48+B49 -> -9376.03

Sheet Transaction Details
A1: DWG CAPITAL PARTNERS
A2: Amex Business Platinum | Transaction Detail
A4: Account Holder | B4: John Dunning
A5: Account | B5: XXXX-XXXXXX-01004
A6: Statement Period | B6: Feb 21, 2026 – May 29, 2026
A7: Entity | B7: DWG Capital Partners
A9: Date | B9: Merchant | C9: Category | D9: Amount | E9: B/P | F9: Reimb. | G9: Notes
A10: 46170 | B10: INTUIT QUICKBOOKS | C10: Software & Subscriptions | D10: 4.25 | E10: B
A11: 46169 | B11: ANTHROPIC | C11: Software & Subscriptions | D11: 11.51 | E11: B
A12: 46169 | B12: BESTBUYCOM | C12: Employee Tech Onboarding | D12: 108.24 | E12: B
A13: 46169 | B13: BESTBUYCOM | C13: Employee Tech Onboarding | D13: 1464.04 | E13: B
A14: 46168 | B14: ANTHROPIC | C14: Software & Subscriptions | D14: 10.62 | E14: B
A15: 46168 | B15: ANTHROPIC | C15: Software & Subscriptions | D15: 10.67 | E15: B
A16: 46168 | B16: DELBAR OLD MILTON LLC | C16: DWGCP Investor Dinner | D16: 1000 | E16: B | G16: Alpharetta GA
A17: 46168 | B17: TRAININNG LLC | C17: DWGCP Professional Training | D17: 249 | E17: B | G17: Training
A18: 46167 | B18: UBER EATS | C18: Team Lunch | D18: 35.42 | E18: P?
A19: 46166 | B19: UBER | C19: Transportation | D19: 28.2 | E19: B
A20: 46165 | B20: AMERICAN AIRLINES | C20: DWGCP Team Travel | D20: 49.46 | E20: B | G20: Dunning seat upgrade
A21: 46165 | B21: CLAUDE.AI SUBSCRIPTION | C21: Software & Subscriptions | D21: 105.4 | E21: B
A22: 46164 | B22: LUGG | C22: Employee Bonus | D22: 141.24 | E22: B | G22: Helping move
A23: 46162 | B23: CAMPAIGNER SVC | C23: Software & Subscriptions | D23: 584 | E23: B | G23: Email marketing
A24: 46161 | B24: ANTHROPIC | C24: Software & Subscriptions | D24: 10.98 | E24: B
A25: 46161 | B25: UBER | C25: Transportation | D25: 5.76 | E25: B
A26: 46158 | B26: ANTHROPIC | C26: Software & Subscriptions | D26: 11.06 | E26: B
A27: 46158 | B27: ANTHROPIC | C27: Software & Subscriptions | D27: 11.68 | E27: B
A28: 46158 | B28: NIMBUS HEALTH FIRST | C28: Personal Health | D28: 200 | E28: P? | G28: Marked w/ receipt; verify
A29: 46156 | B29: ANTHROPIC | C29: Software & Subscriptions | D29: 12.13 | E29: B
A30: 46156 | B30: TST* BLUEYS KITCHEN | C30: Team Lunch | D30: 99.44 | E30: P?
A31: 46155 | B31: ANTHROPIC | C31: Software & Subscriptions | D31: 11.66 | E31: B
A32: 46155 | B32: ANTHROPIC | C32: Software & Subscriptions | D32: 12.19 | E32: B
A33: 46155 | B33: ANTHROPIC | C33: Software & Subscriptions | D33: 12.21 | E33: B
A34: 46155 | B34: ANTHROPIC | C34: Software & Subscriptions | D34: 13.5 | E34: B
A35: 46155 | B35: ANTHROPIC | C35: Software & Subscriptions | D35: 15.8 | E35: B
A36: 46155 | B36: ONLINE PAYMENT - THANK YOU | C36: Payment | D36: -15821.6 | G36: Payment received
A37: 46154 | B37: ANTHROPIC | C37: Software & Subscriptions | D37: 11.46 | E37: B
A38: 46154 | B38: ANTHROPIC | C38: Software & Subscriptions | D38: 11.53 | E38: B
A39: 46154 | B39: ANTHROPIC | C39: Software & Subscriptions | D39: 11.94 | E39: B
A40: 46154 | B40: ANTHROPIC | C40: Software & Subscriptions | D40: 13.46 | E40: B
A41: 46154 | B41: CAMDEN & MERIDEW PC | C41: JAL Legal Case | D41: 109.54 | E41: B | G41: Legal services
A42: 46153 | B42: ANTHROPIC | C42: Software & Subscriptions | D42: 10.75 | E42: B
A43: 46153 | B43: ANTHROPIC | C43: Software & Subscriptions | D43: 10.94 | E43: B
A44: 46149 | B44: WWW.PERPLEXITY.AI | C44: Software & Subscriptions | D44: 21.28 | E44: B
A45: 46147 | B45: MERCEDES BAR & GRILLE | C45: Team Lunch | D45: 172.58 | E45: P? | G45: Marina del Rey
A46: 46146 | B46: PIPEDRIVE INC | C46: Software & Subscriptions | D46: 249.8 | E46: B | G46: CRM
A47: 46146 | B47: TST* BLUEYS KITCHEN | C47: Team Lunch | D47: 146.4 | E47: P?
A48: 46145 | B48: AIRBNB | C48: DWGCP Team Travel | D48: 1080.15 | E48: B | G48: SF lodging
A49: 46145 | B49: AMEX TRAVEL POINTS CREDIT | C49: Credit | D49: -601.81 | G49: Points redemption
A50: 46145 | B50: AMERICAN AIRLINES | C50: DWGCP Team Travel | D50: 601.81 | E50: B | G50: Biswas ticket
A51: 46144 | B51: INTUIT QUICKBOOKS | C51: Software & Subscriptions | D51: 60.61 | E51: B
A52: 46144 | B52: SOUTHWEST AIRLINES | C52: DWGCP Team Travel | D52: 5 | E52: B | G52: Hall — fee
A53: 46143 | B53: ANTHROPIC | C53: Software & Subscriptions | D53: 13.97 | E53: B
A54: 46143 | B54: BUDGET RENT A CAR | C54: DWGCP Team Travel | D54: 197.38 | E54: B | G54: SF rental
A55: 46143 | B55: GATESIDE MARKET (SFO) | C55: Travel Meal | D55: 40.29 | E55: B | G55: Airport
A56: 46143 | B56: TST* ZOLA | C56: Travel Meal | D56: 28.82 | E56: B | G56: Palo Alto
A57: 46143 | B57: UBER | C57: Transportation | D57: 31.21 | E57: B
A58: 46142 | B58: AMERICAN AIRLINES | C58: DWGCP Team Travel | D58: 33.08 | E58: B | G58: Dunning fees
A59: 46142 | B59: COTOGNA AND QUINCE | C59: DWGCP Investor Meeting | D59: 92.54 | E59: B | G59: SF
A60: 46142 | B60: TFK - PALO ALTO | C60: DWGCP Investor Meeting | D60: 440.69 | E60: B
A61: 46142 | B61: USFP - 425 BROADWAY | C61: Transportation | D61: 20 | E61: B | G61: Parking SF
A62: 46141 | B62: ANTHROPIC | C62: Software & Subscriptions | D62: 15.81 | E62: B
A63: 46140 | B63: EXPEDIA | C63: DWGCP Team Travel | D63: 315.21 | E63: B
A64: 46140 | B64: NICOLASBOUCHER.ONLINE | C64: DWGCP Professional Training | D64: 997 | E64: B | G64: Course/training
A65: 46140 | B65: UBER | C65: Transportation | D65: 35.52 | E65: B
A66: 46139 | B66: AMERICAN AIRLINES | C66: DWGCP Team Travel | D66: 401.8 | E66: B | G66: Dunning
A67: 46139 | B67: SOUTHWEST AIRLINES | C67: DWGCP Team Travel | D67: 314.4 | E67: B | G67: Hall
A68: 46138 | B68: ANTHROPIC | C68: Software & Subscriptions | D68: 47.43 | E68: B
A69: 46136 | B69: LINKEDIN JOB | C69: Recruiting | D69: 158.1 | E69: B | G69: Recruiting
A70: 46135 | B70: CLAUDE.AI SUBSCRIPTION | C70: Software & Subscriptions | D70: 105.4 | E70: B
A71: 46134 | B71: Background Check: Max | C71: Software & Subscriptions | D71: 119.99 | E71: B | G71: Background check
A72: 46133 | B72: LINKEDIN JOB | C72: Recruiting | D72: 562.79 | E72: B | G72: Recruiting
A73: 46133 | B73: UBER | C73: Transportation | D73: 20 | E73: B
A74: 46133 | B74: UBER | C74: Transportation | D74: 22.63 | E74: B
A75: 46132 | B75: CAMPAIGNER SVC | C75: Software & Subscriptions | D75: 584 | E75: B | G75: Email marketing
A76: 46132 | B76: TRAININNG LLC | C76: DWGCP Professional Training | D76: 238 | E76: B | G76: Training
A77: 46126 | B77: MONTWAY AUTO TRANSPORT | C77: DWGCP Car | D77: 1419 | E77: B | G77: Vehicle transport
A78: 46126 | B78: Background Check: Soumi | C78: DWGCP HR | D78: 78.49 | E78: B | G78: Background check
A79: 46126 | B79: WWW.PERPLEXITY.AI | C79: Software & Subscriptions | D79: 21.28 | E79: B
A80: 46125 | B80: ONLINE PAYMENT - THANK YOU | C80: Payment | D80: -1241.53 | G80: Payment received
A81: 46122 | B81: LINKEDIN JOB | C81: Recruiting | D81: 560.22 | E81: B | G81: Recruiting
A82: 46122 | B82: ONENOTARY | C82: Notary Services | D82: 35 | E82: B | G82: Notary
A83: 46121 | B83: PIPEDRIVE INC | C83: Software & Subscriptions | D83: 69.39 | E83: B | G83: CRM
A84: 46121 | B84: PIPEDRIVE INC | C84: Software & Subscriptions | D84: 166.53 | E84: B | G84: CRM
A85: 46120 | B85: STEVEN BULLOCK PHOTOGRAPHER | C85: DWG Capital Group | D85: 200 | E85: B | G85: Marked w/ receipt
A86: 46119 | B86: AMEX TRAVEL POINTS CREDIT | C86: Points redemption | D86: -150 | G86: Points redemption
A87: 46119 | B87: MONTWAY AUTO TRANSPORT | C87: DWGCP Car | D87: 1189 | E87: B | G87: Vehicle transport
A88: 46119 | B88: AMERICAN AIRLINES | C88: DWGCP Team Travel | D88: 452.2 | E88: B | G88: Hall
A89: 46119 | B89: UNITED AIRLINES | C89: DWGCP Team Travel | D89: 21.49 | E89: B | G89: Hall seat upgrade
A90: 46118 | B90: AIRBNB | C90: DWGCP Team Travel | D90: 263.29 | E90: B | G90: SF lodging
A91: 46118 | B91: AMEX TRAVEL POINTS CREDIT | C91: Points redemption | D91: -200 | G91: Points redemption
A92: 46118 | B92: CAMPAIGNER SVC | C92: Software & Subscriptions | D92: 584 | E92: B | G92: Email marketing
A93: 46118 | B93: DELTA AIR LINES | C93: DWGCP Team Travel | D93: 459.12 | E93: B | G93: Hall
A94: 46114 | B94: INTUIT QUICKBOOKS | C94: Software & Subscriptions | D94: 60.61 | E94: B | G94: Accounting
A95: 46113 | B95: STEVEN BULLOCK PHOTOGRAPHER | C95: DWG Capital Group | D95: 1000 | E95: B | G95: Marked w/ receipt
A96: 46112 | B96: LINKEDIN JOB | C96: Recruiting | D96: 40.4 | E96: B
A97: 46112 | B97: LINKEDIN JOB | C97: Recruiting | D97: 519.6 | E97: B
A98: 46112 | B98: MERCEDES BENZ OF AUSTIN | C98: Auto (One-Time) | D98: 6900.58 | E98: B | G98: Vehicle
A99: 46104 | B99: AMEX MEMBERSHIP FEE | C99: Annual AMEX Fee | D99: 895 | E99: B | G99: Annual fee
A100: 46104 | B100: SOUTHWEST AIRLINES | C100: Refund | D100: -393.4 | E100: B | G100: Dunning refund
A101: 46104 | B101: SOUTHWEST AIRLINES | C101: Refund | D101: -69 | E101: B | G101: Dunning refund
A102: 46104 | B102: SOUTHWEST AIRLINES | C102: DWGCP Team Travel | D102: 835.8 | E102: B | G102: DWG Team Travel
...
